Workbook

Sheet Projected IS
B2: Appendix A - Projected Income Statement
F5: Newtech Limited
F6: Projected Income Statement
F7: Canadian 000's
F8: Fiscal Year Ending June 30th
G11: 2008 | H11: 2009 | I11: 2010 | J11: 2011 | K11: 2012 | L11: 2013
B13: Revenue | G13: 12349 | H13: =G13*1.15 -> 14201.35 | I13: =H13*1.15 -> 16331.552 | J13: =I13*1.05 -> 17148.13 | K13: =J13*1.05 -> 18005.537 | L13: =K13*1.05 -> 18905.813
C14: Software | H14: =H13-H15 -> 11201.35 | I14: =I13-I15 -> 10331.552 | J14: =J13-J15 -> 14148.13 | K14: =K13-K15 -> 15005.537 | L14: =L13-L15 -> 15905.813
C15: Contracts | H15: 3000 | I15: 6000 | J15: 3000 | K15: 3000 | L15: 3000
G16: 12349 | H16: =H14+H15 -> 14201.35 | I16: =I14+I15 -> 16331.552 | J16: =J14+J15 -> 17148.13 | K16: =K14+K15 -> 18005.537 | L16: =L14+L15 -> 18905.813
B18: Cost of Sales | G18: 6026 | H18: =H16-H20 -> 6800.675 | I18: =I16-I20 -> 7565.7762 | J18: =J16-J20 -> 8274.0651 | K18: =K16-K20 -> 8702.7683 | L18: =L16-L20 -> 9152.9067
B20: Gross Profit | G20: 6323 | H20: =(H14*0.5)+(H15*0.6) -> 7400.675 | I20: =(I14*0.5)+(I15*0.6) -> 8765.7763 | J20: =(J14*0.5)+(J15*0.6) -> 8874.0651 | K20: =(K14*0.5)+(K15*0.6) -> 9302.7683 | L20: =(L14*0.5)+(L15*0.6) -> 9752.9067
B22: Operating Expenses
C23: Sales and Marketing | G23: 2533 | H23: =H13*0.2 -> 2840.27 | I23: =I13*0.2 -> 3266.3105 | J23: =J13*0.2 -> 3429.626 | K23: =K13*0.2 -> 3601.1073 | L23: =L13*0.2 -> 3781.1627
C24: General and Administrative | G24: 1494 | H24: =G24*1.05 -> 1568.7 | I24: =H24*1.05 -> 1647.135 | J24: =I24*1.05 -> 1729.4917 | K24: =J24*1.05 -> 1815.9663 | L24: =K24*1.05 -> 1906.7647
C25: Research | G25: 1013 | H25: =H13*0.15/2 -> 1065.1012 | I25: =I13*0.15/2 -> 1224.8664 | J25: =J13*0.15/2 -> 1286.1098 | K25: =K13*0.15/2 -> 1350.4152 | L25: =L13*0.15/2 -> 1417.936
C26: Amortization of Capital Assets | G26: 406 | H26: 400 | I26: 400 | J26: 400 | K26: 400 | L26: 400
C27: Amortization of Development Costs | G27: 1808 | H27: 1207 | I27: 1568 | J27: 1345 | K27: 1405 | L27: 1469
C28: Exchange loss (gain) | G28: -25 | H28: 0 | I28: 0 | J28: 0 | K28: 0 | L28: 0
C29: Restructuriong and other | G29: 500 | H29: 500 | I29: 0 | J29: 0 | K29: 0 | L29: 0
C30: Interest expense | G30: 647 | H30: 199.71 | I30: 199.71 | J30: 199.71 | K30: 199.71 | L30: 199.71
G31: =SUM(G23:G30) -> 8376 | H31: =SUM(H23:H30) -> 7780.7812 | I31: =SUM(I23:I30) -> 8306.0219 | J31: =SUM(J23:J30) -> 8389.9375 | K31: =SUM(K23:K30) -> 8772.1989 | L31: =SUM(L23:L30) -> 9174.5734
B33: Net Income | G33: =G20-G31 -> -2053 | H33: =H20-H31 -> -380.10625 | I33: =I20-I31 -> 459.75431 | J33: =J20-J31 -> 484.12753 | K33: =K20-K31 -> 530.5694 | L33: =L20-L31 -> 578.33337
B36: Opening Balance | G36: -16439 | H36: -18492 | I36: =H37 -> -18872.106 | J36: =I37 -> -18412.352 | K36: =J37 -> -17928.224 | L36: =K37 -> -17397.655
B37: Ending Balance | G37: =G33+G36 -> -18492 | H37: =H36+H33 -> -18872.106 | I37: =I36+I33 -> -18412.352 | J37: =J36+J33 -> -17928.224 | K37: =K36+K33 -> -17397.655 | L37: =L36+L33 -> -16819.322

Sheet WACC
B2: Appendix B - Weighted Average Cost of Capital
D5: Newtech Limited
D6: Weighted Average Cost of Capital
B8: Cost of Equity | H8: Mkt val of equity | I8: =17752*0.75 -> 13314
B9: Required Rate of return on Equity | F9: 0.15 | H9: Value of Firm | I9: =I8/0.8 -> 16642.5
B10: Add - Company Risk | F10: 0.1 | H10: Debt Value | I10: =I9-I8 -> 3328.5
B11: Cost of Equity | F11: =F9+F10 -> 0.25 | H11: Interest (6%) | I11: =0.06*I10 -> 199.71 | K11: *assume constant cause don’t
K12: know how equity value changes
B13: Cost of Debt | F13: 0.06
B14: After Tax Cost of Debt | F14: 0.04
B16: Weight of Equity | F16: 0.8
B17: Weight of Debt | F17: 0.2
B19: WACC | F19: =(F11*F16)+F14*F17 -> 0.208

Sheet DCF Model
B2: Appendix C - Discounted Cash Flow Model
E5: Newtech Limited
E6: Valuation Report
E7: Discounted Cash Flow Valuation
E8: Canadian 000's
F10: 2009 | G10: 2010 | H10: 2011 | I10: 2012 | J10: 2013 | K10: TV
B12: Net Income | F12: ='Projected IS'!H33 -> -380.10625 | G12: ='Projected IS'!I33 -> 459.75431 | H12: ='Projected IS'!J33 -> 484.12753 | I12: ='Projected IS'!K33 -> 530.5694 | J12: ='Projected IS'!L33 -> 578.33337 | K12: =J12*1.03 -> 595.68338
B13: Less: Change in Working Capital | F13: =0.2*('Projected IS'!H16-'Projected IS'!G16) -> 370.47 | G13: =0.2*('Projected IS'!I16-'Projected IS'!H16) -> 426.0405 | H13: =0.2*('Projected IS'!J16-'Projected IS'!I16) -> 163.31553 | I13: =0.2*('Projected IS'!K16-'Projected IS'!J16) -> 171.4813 | J13: =0.2*('Projected IS'!L16-'Projected IS'!K16) -> 180.05537 | K13: =J13*1.03 -> 185.45703
B14: Add: Depreciation | F14: 2200 | G14: 2200 | H14: 2200 | I14: 2200 | J14: 2200 | K14: =J14*1.03 -> 2266
B15: Less:CAPEX (net of CCA tax shield) | F15: =0.7*350 -> 245 | G15: =0.7*350 -> 245 | H15: =0.7*350 -> 245 | I15: =0.7*350 -> 245 | J15: =0.7*350 -> 245 | K15: =J15*1.03 -> 252.35
B16: Free Cash Flows | F16: =F12-F13+F14-F15 -> 1204.4237 | G16: =G12-G13+G14-G15 -> 1988.7138 | H16: =H12-H13+H14-H15 -> 2275.812 | I16: =I12-I13+I14-I15 -> 2314.0881 | J16: =J12-J13+J14-J15 -> 2353.278 | K16: =K12-K13+K14-K15 -> 2423.8763
H18: *Terminal value perpetuity | K18: =K16/(WACC!F19-0.03) -> 13617.283
B20: PV Cash Flows | F20: =F16/(1+WACC!$F$19)^1 -> 997.03953 | G20: =G16/(1+WACC!$F$19)^2 -> 1362.8198 | H20: =H16/(1+WACC!$F$19)^3 -> 1291.0278 | I20: =I16/(1+WACC!$F$19)^4 -> 1086.7062 | J20: =J16/(1+WACC!$F$19)^5 -> 914.82614 | K20: =K18/(1+WACC!$F$19)^5 -> 5293.6569
B22: Enterprise Value | F22: =SUM(F20:K20) -> 10946.076

Sheet Share Value
B2: Appendix D - Share Value Analysis
E5: Newtech Limited
E6: Estimated Value of Shares
E7: Canadian $000's
B9: Enterprise Value | F9: ='DCF Model'!F22 -> 10946.076
B11: Calculated Enterprise Value | F11: =F9 -> 10946.076
B12: Add: Present Value of Tax Pools | F12: 11500
B14: En Block Common Share Value | F14: =F11+F12 -> 22446.076
B16: Shares outstanding | F16: 17752
B18: Value Per Share | F18: =F14/F16 -> 1.2644252

Sheet Questions
B3: 1. is the en block common share value supposed to be way higher then enterprise value cause tax pools are included
