Workbook

Sheet Introduction
B43: Copyright 1999. All rights reserved.
C44: Version: 1 April 99

Sheet Assigning Weights
A1: Assignment of Judgmental Weights
B2: CB | C2: PR | D2: GL | E2: BP | F2: FS
A3: Customer background (CB) | B3: 1 | C3: =1/B4 | D3: =1/B5 | E3: =1/B6 | F3: =1/B7
A4: Payment record (PR) | B4: 5 | C4: 1 | D4: =1/C5 | E4: =1/C6 | F4: =1/C7
A5: Geographical location (GL) | B5: =1/7 | C5: 0.14285714 | D5: 1 | E5: =1/D6 | F5: =1/D7
A6: Business potential (BP) | B6: =1/3 | C6: 0.5 | D6: 5 | E6: 1 | F6: =1/E7
A7: Financial soundness (FS) | B7: 9 | C7: 2 | D7: 9 | E7: 5 | F7: 1
A9: Possible Scores | B9: Score | C9: Reciprocal
A10: Equal importance | B10: 1 | C10: =1/B10
A11: An intermediate value | B11: 2 | C11: =1/B11
A12: Slightly favor one over the other | B12: 3 | C12: =1/B12
A13: An intermediate value | B13: 4 | C13: =1/B13
A14: Strong importance | B14: 5 | C14: =1/B14
A15: An intermediate value | B15: 6 | C15: =1/B15
A16: Very strong importance | B16: 7 | C16: =1/B16
A17: An intermediate value | B17: 8 | C17: =1/B17
A18: Absolute importance | B18: 9 | C18: =1/B18

Sheet Priorities & Attributes
A1: Calculation of Relative Importance of Factors
B2: ='Assigning Weights'!B2 | C2: ='Assigning Weights'!C2 | D2: ='Assigning Weights'!D2 | E2: ='Assigning Weights'!E2 | F2: ='Assigning Weights'!F2
A3: ='Assigning Weights'!A3 | B3: ='Assigning Weights'!B3 | C3: ='Assigning Weights'!C3 | D3: ='Assigning Weights'!D3 | E3: ='Assigning Weights'!E3 | F3: ='Assigning Weights'!F3
A4: ='Assigning Weights'!A4 | B4: ='Assigning Weights'!B4 | C4: ='Assigning Weights'!C4 | D4: ='Assigning Weights'!D4 | E4: ='Assigning Weights'!E4 | F4: ='Assigning Weights'!F4
A5: ='Assigning Weights'!A5 | B5: ='Assigning Weights'!B5 | C5: ='Assigning Weights'!C5 | D5: ='Assigning Weights'!D5 | E5: ='Assigning Weights'!E5 | F5: ='Assigning Weights'!F5
A6: ='Assigning Weights'!A6 | B6: ='Assigning Weights'!B6 | C6: ='Assigning Weights'!C6 | D6: ='Assigning Weights'!D6 | E6: ='Assigning Weights'!E6 | F6: ='Assigning Weights'!F6
A7: ='Assigning Weights'!A7 | B7: ='Assigning Weights'!B7 | C7: ='Assigning Weights'!C7 | D7: ='Assigning Weights'!D7 | E7: ='Assigning Weights'!E7 | F7: ='Assigning Weights'!F7
A8: Totals | B8: =SUM(B3:B7) | C8: =SUM(C3:C7) | D8: =SUM(D3:D7) | E8: =SUM(E3:E7) | F8: =SUM(F3:F7)
A10: Proportions
B11: =B2 | C11: =C2 | D11: =D2 | E11: =E2 | F11: =F2 | G11: Sums | H11: Averages
A12: =A3 | B12: =B3/B$8 | C12: =C3/C$8 | D12: =D3/D$8 | E12: =E3/E$8 | F12: =F3/F$8 | G12: =SUM(B12:F12) | H12: =G12/5
A13: =A4 | B13: =B4/B$8 | C13: =C4/C$8 | D13: =D4/D$8 | E13: =E4/E$8 | F13: =F4/F$8 | G13: =SUM(B13:F13) | H13: =G13/5
A14: =A5 | B14: =B5/B$8 | C14: =C5/C$8 | D14: =D5/D$8 | E14: =E5/E$8 | F14: =F5/F$8 | G14: =SUM(B14:F14) | H14: =G14/5
A15: =A6 | B15: =B6/B$8 | C15: =C6/C$8 | D15: =D6/D$8 | E15: =E6/E$8 | F15: =F6/F$8 | G15: =SUM(B15:F15) | H15: =G15/5
A16: =A7 | B16: =B7/B$8 | C16: =C7/C$8 | D16: =D7/D$8 | E16: =E7/E$8 | F16: =F7/F$8 | G16: =SUM(B16:F16) | H16: =G16/5
A17: Totals | B17: =SUM(B12:B16) | C17: =SUM(C12:C16) | D17: =SUM(D12:D16) | E17: =SUM(E12:E16) | F17: =SUM(F12:F16) | H17: =SUM(H12:H16)
A21: Importance of Customer's Attributes
B23: Grant | C23: Deny
B24: Credit | C24: Credit | E24: Strength
A25: ='Assigning Weights'!A3 | B25: 1 | C25: 5 | E25: =C25/(B25+C25)
A26: ='Assigning Weights'!A4 | B26: 1 | C26: 7 | E26: =C26/(B26+C26)
A27: ='Assigning Weights'!A5 | B27: 1 | C27: =1/3 | E27: =C27/(B27+C27)
A28: ='Assigning Weights'!A6 | B28: 1 | C28: 3 | E28: =C28/(B28+C28)
A29: ='Assigning Weights'!A7 | B29: 1 | C29: 5 | E29: =C29/(B29+C29)
A31: Possible Scores | B31: Score | C31: Reciprocal
A32: ='Assigning Weights'!A10 | B32: ='Assigning Weights'!B10 | C32: ='Assigning Weights'!C10
A33: ='Assigning Weights'!A11 | B33: ='Assigning Weights'!B11 | C33: ='Assigning Weights'!C11
A34: ='Assigning Weights'!A12 | B34: ='Assigning Weights'!B12 | C34: ='Assigning Weights'!C12
A35: ='Assigning Weights'!A13 | B35: ='Assigning Weights'!B13 | C35: ='Assigning Weights'!C13
A36: ='Assigning Weights'!A14 | B36: ='Assigning Weights'!B14 | C36: ='Assigning Weights'!C14
A37: ='Assigning Weights'!A15 | B37: ='Assigning Weights'!B15 | C37: ='Assigning Weights'!C15
A38: ='Assigning Weights'!A16 | B38: ='Assigning Weights'!B16 | C38: ='Assigning Weights'!C16
A39: ='Assigning Weights'!A17 | B39: ='Assigning Weights'!B17 | C39: ='Assigning Weights'!C17
A40: ='Assigning Weights'!A18 | B40: ='Assigning Weights'!B18 | C40: ='Assigning Weights'!C18

Sheet Credit Decision
A1: Credit Decision Model
C2: Customer's
B3: Relative | C3: Assessed | D3: Final
B4: Priority | C4: Strength | D4: Weight
A5: ='Assigning Weights'!A3 | B5: ='Priorities & Attributes'!H12 | C5: ='Priorities & Attributes'!E25 | D5: =B5*C5 | F5: Credit Decision Inputs
A6: ='Assigning Weights'!A4 | B6: ='Priorities & Attributes'!H13 | C6: ='Priorities & Attributes'!E26 | D6: =B6*C6 | E6: Expected sales | H6: 200000
A7: ='Assigning Weights'!A5 | B7: ='Priorities & Attributes'!H14 | C7: ='Priorities & Attributes'!E27 | D7: =B7*C7 | E7: Profit margin | H7: 0.05
A8: ='Assigning Weights'!A6 | B8: ='Priorities & Attributes'!H15 | C8: ='Priorities & Attributes'!E28 | D8: =B8*C8
A9: ='Assigning Weights'!A7 | B9: ='Priorities & Attributes'!H16 | C9: ='Priorities & Attributes'!E29 | D9: =B9*C9
A10: Relative weight for granting credit
A11: Relative weight for denying credit
A12: Model
A13: Weight for granting credit | B13: =D10
A14: x Profit margin | B14: =$H$7
A15: x Expected sales | B15: =$H$6
A16: = Expected margin | B16: =B13*B14*B15
A17: Weight for denying credit | B17: =D11
A18: x (1 - profit margin) | B18: =1-$H$7
A19: x Expected sales | B19: =$H$6
A20: = Expected cost | B20: =B17*B18*B19
A21: Expected net benefit | B21: =B16-B20 | C21: =IF(B21<0,"Deny credit request for a line of credit equal to the expected sales.","Grant credit request for a line of credit equal to the expected sales.")
C22: Click to the next page to see how much credit should be extended.

Sheet Credit Line
A1: Credit Line Range With Collateral
A3: Expected benefit is:
A4: Sales | C4: ='Credit Decision'!H6
A5: Profit margin | C5: ='Credit Decision'!H7
A6: Profit with no default | C6: =C4*C5
A7: However, no default is expected | C7: ='Credit Decision'!D10
A8: Thus, expected profit is | B8: A | C8: =C6*C7
A10: Expected cost is:
A11: Sales | C11: =C4
A12: Cost percentage | C12: =1-C5
A13: Cost of sales | C13: =C11*C12
A14: However, default is expected | C14: ='Credit Decision'!D11
A15: Thus, expected cost is | B15: B | C15: =C13*C14
A17: Expected gain or (loss) without collateral | B17: A - B | C17: =C8-C15
A19: Let's look at expected profit for different scenarios with collateral:
E21: % Profit Margin from Selling the Collateral as Stated in Sales $
C22: 0 | D22: ='Credit Decision'!H7*(1/4) | E22: ='Credit Decision'!H7*(2/4) | F22: ='Credit Decision'!H7*(3/4) | G22: ='Credit Decision'!H7*(4/4)
A23: Expected sales | C23: ='Credit Decision'!$H$6 | D23: ='Credit Decision'!$H$6 | E23: ='Credit Decision'!$H$6 | F23: ='Credit Decision'!$H$6 | G23: ='Credit Decision'!$H$6
A24: The optimal amount of collateral is | C24: =IF('Credit Decision'!H6*(C22-'Credit Decision'!H7*'Credit Decision'!D10+(1-'Credit Decision'!H7)*'Credit Decision'!D11)/((1-'Credit Decision'!H7+C22)*'Credit Decision'!D11)<0,0,'Credit Decision'!H6*(C22-'Credit Decision'!H7*'Credit Decision'!D10+(1-'Credit Decision'!H7)*'Credit Decision'!D11)/((1-'Credit Decision'!H7+C22)*'Credit Decision'!D11)) | D24: =IF('Credit Decision'!H6*(D22-'Credit Decision'!H7*'Credit Decision'!D10+(1-'Credit Decision'!H7)*'Credit Decision'!D11)/((1-'Credit Decision'!H7+D22)*'Credit Decision'!D11)<0,0,'Credit Decision'!H6*(D22-'Credit Decision'!H7*'Credit Decision'!D10+(1-'Credit Decision'!H7)*'Credit Decision'!D11)/((1-'Credit Decision'!H7+D22)*'Credit Decision'!D11)) | E24: =IF('Credit Decision'!H6*(E22-'Credit Decision'!H7*'Credit Decision'!D10+(1-'Credit Decision'!H7)*'Credit Decision'!D11)/((1-'Credit Decision'!H7+E22)*'Credit Decision'!D11)<0,0,'Credit Decision'!H6*(E22-'Credit Decision'!H7*'Credit Decision'!D10+(1-'Credit Decision'!H7)*'Credit Decision'!D11)/((1-'Credit Decision'!H7+E22)*'Credit Decision'!D11)) | F24: =IF('Credit Decision'!H6*(F22-'Credit Decision'!H7*'Credit Decision'!D10+(1-'Credit Decision'!H7)*'Credit Decision'!D11)/((1-'Credit Decision'!H7+F22)*'Credit Decision'!D11)<0,0,'Credit Decision'!H6*(F22-'Credit Decision'!H7*'Credit Decision'!D10+(1-'Credit Decision'!H7)*'Credit Decision'!D11)/((1-'Credit Decision'!H7+F22)*'Credit Decision'!D11)) | G24: =IF('Credit Decision'!H6*(G22-'Credit Decision'!H7*'Credit Decision'!D10+(1-'Credit Decision'!H7)*'Credit Decision'!D11)/((1-'Credit Decision'!H7+G22)*'Credit Decision'!D11)<0,0,'Credit Decision'!H6*(G22-'Credit Decision'!H7*'Credit Decision'!D10+(1-'Credit Decision'!H7)*'Credit Decision'!D11)/((1-'Credit Decision'!H7+G22)*'Credit Decision'!D11))
A25: And the appropriate credit line is | C25: ='Credit Decision'!H6-C24 | D25: ='Credit Decision'!H6-D24 | E25: ='Credit Decision'!H6-E24 | F25: ='Credit Decision'!H6-F24 | G25: ='Credit Decision'!H6-G24
A27: Investment = Collateral x (1 - profit margin) | B27: C | C27: =C24*(1-'Credit Decision'!$H$7) | D27: =D24*(1-'Credit Decision'!$H$7) | E27: =E24*(1-'Credit Decision'!$H$7) | F27: =F24*(1-'Credit Decision'!$H$7) | G27: =G24*(1-'Credit Decision'!$H$7)
A28: If default occurs and profit is based on the
A29: investment in the collateral, profit margin is | B29: D | C29: 0 | D29: ='Credit Decision'!H7*(1/4)/(1-'Credit Decision'!H7) | E29: ='Credit Decision'!H7*(2/4)/(1-'Credit Decision'!H7) | F29: ='Credit Decision'!H7*(3/4)/(1-'Credit Decision'!H7) | G29: ='Credit Decision'!H7*(4/4)/(1-'Credit Decision'!H7)
A30: Collateral value exceeds collateral investment by | B30: C x D | C30: =C27*C29 | D30: =D27*D29 | E30: =E27*E29 | F30: =F27*F29 | G30: =G27*G29
A31: Lost investment on credit line if default occurs
A32: = Credit line x (1 - profit margin) | C32: =-C25*$C$12 | D32: =-D25*$C$12 | E32: =-E25*$C$12 | F32: =-F25*$C$12 | G32: =-G25*$C$12
A33: Total gain (loss) on line & collateral is | C33: =C30+C32 | D33: =D30+D32 | E33: =E30+E32 | F33: =F30+F32 | G33: =G30+G32
A34: However, default is expected to occur
A35: Thus, expected gain or (loss) on line & collateral
A36: Expected benefit (see A above) | C36: =$C$8 | D36: =$C$8 | E36: =$C$8 | F36: =$C$8 | G36: =$C$8
A37: Overall expected profit or (loss)
A39: Overall gain or (loss) as % of sales | C39: =C37/'Credit Decision'!$H$6 | D39: =D37/'Credit Decision'!$H$6 | E39: =E37/'Credit Decision'!$H$6 | F39: =F37/'Credit Decision'!$H$6 | G39: =G37/'Credit Decision'!$H$6
