Workbook

Sheet README
A1: North Sound Terminal — Ramp NS-2 Value Engineering Decision Model
A2: Independent senior civil engineer audit record | prepared 2026-08-24 | accompanies ferry_terminal_ve_board.pptx
A5: PURPOSE: Auditable calculation record supporting the VE board decision on the North Sound vehicle-transfer ramp (Ramp NS-2),
A6: WSDOT Marine Project NS-27-041, Island County (memo: North_Sound_Terminal_Project_Memo.docx, §1–§5).
A8: METHOD: Physical surface area, specification-payable quantity, technician estimate, and vendor-quoted quantity are computed
A9: and carried SEPARATELY (memo §2). Payment quantities follow the supplied measurement clauses (ferry_measurement_payment_rules.csv,
A10: FMR-001…FMR-012) which require field-verified accepted quantities, not vendor schedule quantities. Unit prices are SUBMITTED prices
A11: (estimate dates 2027-02-15 / 2027-04-01) and are treated as unverified evidence claims, benchmarked where WSDOT references allow.
A13: SHEET MAP:
A14: Parameters ............ global assumptions (discount rate, escalation, contingency) — all downstream sheets reference these cells
A15: Segment_Takeoff ....... 48-segment geometry recomputation with payable-quantity rounding per FMR clauses
A16: Quantity_Reconciliation physical vs payable vs technician vs submitted/vendor, per item family, with locators
... A30: (5) 6-hr night closure is contradicted by operations evidence; (6) coating adhesion test contradicted.

Sheet Parameters
A1: Global Parameters & Assumptions
A2: Yellow cells are the only manual inputs; all downstream sheets reference this page.
A4: Ref | B4: Parameter | C4: Value | D4: Unit | E4: Basis / locator
A5: P01 | B5: Real discount rate for lifecycle PW | C5: 0.03 | D5: per yr | E5: Assumption (no agency rate supplied); sensitivity 2%–4% on Lifecycle sheet
A6: P02 | B6: Escalation rate, estimate date to construction midpoint | C6: 0.0218 | D6: per yr | E6: FRED PPI ready-mix PCU327320327320: 2025-07=393.322 to 2026-07=401.896 = +2.18%/yr (fred_ppi_ready_mix_concrete.csv rows 2025-07/2026-07); latest available observation 2026-07; proxy only — steel/fabrication index not supplied
A7: P03 | B7: Years from estimate date (2027-02-15 base / 2027-04-01 VE) to construction midpoint (~2027-12) | C7: 0.85 | D7: yr | E7: Memo §4: construction Oct 2027–Feb 2028; midpoint 2027-12
A8: P04 | B8: Change-order contingency (design-bid-build) | C8: 0.04 | D8: fraction | E8: WSDOT Cost Estimating Manual M 30-34.04 §14.19 (PDF p.86): DBB COC = 4%
A9: P05 | B9: Design/scope allowance on evidence-open quantities | C9: 0.1 | D9: fraction | E9: BDM 12.3.3.A.2 (PDF p.15): minimum 10% contingency to cover scope creep; CEM Exhibit 7-3 (PDF p.39): design phase misc allowance 10–20%
A10: P06 | B10: Overlay/FRP VE claimed service life | C10: 22 | D10: yr | E10: ferry_ramp_dimensions_and_technician_quantities.csv row "Lifecycle, Overlay/FRP VE, Claimed life, 22, years, submitted; verify" — SUBMITTED, UNVERIFIED
A11: P07 | B11: Base replacement analysis life | C11: 40 | D11: yr | E11: Same file, row "Lifecycle, Base replacement, Analysis life, 40, years, planning assumption"
A12: P08 | B12: VE renewal cost as fraction of initial VE independent estimate | C12: 1 | D12: fraction | E12: Assumption: full repeat of VE scope at renewal (conservative); sensitivity on Lifecycle sheet
A13: P09 | B13: Night closure maximum (submitted, contradicted) | C13: 6 | D13: hr/night | E13: ferry_engineering_evidence_ledger.csv FEE-007/015/023 tidal closure 6 h, evidence_state=contradicted; dimensions file "Night closure, Maximum duration, 6, hours, requires operations approval"
A14: P10 | B14: Corrosion risk allowance upper basis | C14: 780 | D14: SF | E14: Technician estimate, dimensions file row "Corrosion, Mapped repair, Technician estimate, 780, SF, unverified submitted quantity" — carried as risk allowance only, NOT payable quantity

Sheet Segment_Takeoff
A1: Segment Takeoff — Independent Recomputation
A2: Source rows: ramp_segment_takeoff.csv RMP-001…RMP-048 (verbatim geometry); computed columns are formulas. Payable rounding per FMR-001/002/004/006.
A4: Segment | B4: Length (ft) | C4: Clear width (ft) | D4: Skew (deg) | E4: Plan area = L×W (SF) | F4: Skew joint length = W/cos(skew) (LF) | G4: Payable removal (SF, 0.1) FMR-001 | H4: Payable new panel (SF, whole) FMR-002 | I4: Payable joint (LF, 0.1) FMR-004 | J4: Submitted panel area (SF) | K4: Submitted joint (LF) | L4: Submitted corrosion (SF) | M4: Payable corrosion (SF, whole) FMR-006 | N4: Inspection record status | O4: Variance: submitted − plan area (SF)
A5: RMP-001 | B5: 2.7 | C5: 19.44 | D5: 18 | E5: =B5*C5 | F5: =C5/COS(RADIANS(D5)) | G5: =ROUND(E5,1) | H5: =ROUND(E5,0) | I5: =ROUND(F5,1) | J5: 56.16 | K5: 19.44 | L5: 1.31 | M5: =ROUND(L5,0) | N5: verified | O5: =J5-E5
A6: RMP-002 | B6: 3.375 | C6: 20.574 | D6: 27 | E6: =B6*C6 | F6: =C6/COS(RADIANS(D6)) | G6: =ROUND(E6,1) | H6: =ROUND(E6,0) | I6: =ROUND(F6,1) | J6: 66.66 | K6: 20.574 | L6: 2.36 | M6: =ROUND(L6,0) | N6: submitted | O6: =J6-E6
A7: RMP-003 | B7: 4.05 | C7: 21.708 | D7: 33 | E7: =B7*C7 | F7: =C7/COS(RADIANS(D7)) | G7: =ROUND(E7,1) | H7: =ROUND(E7,0) | I7: =ROUND(F7,1) | J7: 84.4 | K7: 21.708 | L7: 3.78 | M7: =ROUND(L7,0) | N7: field-check-required | O7: =J7-E7
A8: RMP-004 | B8: 4.725 | C8: 22.842 | D8: 41 | E8: =B8*C8 | F8: =C8/COS(RADIANS(D8)) | G8: =ROUND(E8,1) | H8: =ROUND(E8,0) | I8: =ROUND(F8,1) | J8: 103.61 | K8: 22.842 | L8: 5.61 | M8: =ROUND(L8,0) | N8: verified | O8: =J8-E8
A9: RMP-005 | B9: 2.7 | C9: 23.976 | D9: 18 | E9: =B9*C9 | F9: =C9/COS(RADIANS(D9)) | G9: =ROUND(E9,1) | H9: =ROUND(E9,0) | I9: =ROUND(F9,1) | J9: 62.15 | K9: 23.976 | L9: 3.95 | M9: =ROUND(L9,0) | N9: submitted | O9: =J9-E9
A10: RMP-006 | B10: 3.375 | C10: 25.11 | D10: 27 | E10: =B10*C10 | F10: =C10/COS(RADIANS(D10)) | G10: =ROUND(E10,1) | H10: =ROUND(E10,0) | I10: =ROUND(F10,1) | J10: 81.36 | K10: 25.11 | L10: 2.12 | M10: =ROUND(L10,0) | N10: field-check-required | O10: =J10-E10
A11: RMP-007 | B11: 4.05 | C11: 19.44 | D11: 33 | E11: =B11*C11 | F11: =C11/COS(RADIANS(D11)) | G11: =ROUND(E11,1) | H11: =ROUND(E11,0) | I11: =ROUND(F11,1) | J11: 84.24 | K11: 19.44 | L11: 2.68 | M11: =ROUND(L11,0) | N11: verified | O11: =J11-E11
A12: RMP-008 | B12: 4.725 | C12: 20.574 | D12: 41 | E12: =B12*C12 | F12: =C12/COS(RADIANS(D12)) | G12: =ROUND(E12,1) | H12: =ROUND(E12,0) | I12: =ROUND(F12,1) | J12: 93.32 | K12: 20.574 | L12: 4.18 | M12: =ROUND(L12,0) | N12: submitted | O12: =J12-E12
A13: RMP-009 | B13: 2.7 | C13: 21.708 | D13: 18 | E13: =B13*C13 | F13: =C13/COS(RADIANS(D13)) | G13: =ROUND(E13,1) | H13: =ROUND(E13,0) | I13: =ROUND(F13,1) | J13: 56.27 | K13: 21.708 | L13: 3.05 | M13: =ROUND(L13,0) | N13: field-check-required | O13: =J13-E13
A14: RMP-010 | B14: 3.375 | C14: 22.842 | D14: 27 | E14: =B14*C14 | F14: =C14/COS(RADIANS(D14)) | G14: =ROUND(E14,1) | H14: =ROUND(E14,0) | I14: =ROUND(F14,1) | J14: 74.01 | K14: 22.842 | L14: 4.7 | M14: =ROUND(L14,0) | N14: verified | O14: =J14-E14
A15: RMP-011 | B15: 4.05 | C15: 23.976 | D15: 33 | E15: =B15*C15 | F15: =C15/COS(RADIANS(D15)) | G15: =ROUND(E15,1) | H15: =ROUND(E15,0) | I15: =ROUND(F15,1) | J15: 93.22 | K15: 23.976 | L15: 2.43 | M15: =ROUND(L15,0) | N15: submitted | O15: =J15-E15
A16: RMP-012 | B16: 4.725 | C16: 25.11 | D16: 41 | E16: =B16*C16 | F16: =C16/COS(RADIANS(D16)) | G16: =ROUND(E16,1) | H16: =ROUND(E16,0) | I16: =ROUND(F16,1) | J16: 113.9 | K16: 25.11 | L16: 4.03 | M16: =ROUND(L16,0) | N16: field-check-required | O16: =J16-E16
... A52: RMP-048 | B52: 4.725 | C52: 25.11 | D52: 41 | E52: =B52*C52 | F52: =C52/COS(RADIANS(D52)) | G52: =ROUND(E52,1) | H52: =ROUND(E52,0) | I52: =ROUND(F52,1) | J52: 113.9 | K52: 25.11 | L52: 5.1 | M52: =ROUND(L52,0) | N52: field-check-required | O52: =J52-E52
A53: TOTALS | B53: =SUM(B5:B52) | E53: =SUM(E5:E52) | F53: =SUM(F5:F52) | G53: =SUM(G5:G52) | H53: =SUM(H5:H52) | I53: =SUM(I5:I52) | J53: =SUM(J5:J52) | K53: =SUM(K5:K52) | L53: =SUM(L5:L52) | M53: =SUM(M5:M52)
A55: Row check: Σ length = 178.2 ft vs stated movable length 162.0 ft (ferry_ramp_dimensions…csv "Total movable length") — UNRESOLVED BOUNDARY U1: takeoff covers ~9.1% more length than the movable span; see Recommendation.
A56: Joint scope check: Σ geometric skew joint length 1,255.3 LF vs bid items B03/V04 = 1,260 LF (consistent); but two-hinge geometry (N 30.8 ft @27°, S 31.2 ft @33°) = 71.8 LF — UNRESOLVED BOUNDARY U2: whether payable joint scope is the 48-segment joint network or only two hinges.
A57: Payable basis: panel surface = plan (L×W) area — skew is in-plan; panel plate surface is not increased by skew angle. Joint length across a skewed joint = clear width / cos(skew) per FMR-004 "geometric skew length".
A58: Corrosion payable shown as mapped takeoff (rounded whole SF per FMR-006); technician estimate 780 SF is unverified and carried as risk allowance (P10), not as payable quantity.
A59: Verification mix: 16 verified / 16 submitted / 16 field-check-required segments (column N); quantities from non-verified segments remain conditional per memo §2.

Sheet Quantity_Reconciliation
A1: Quantity Reconciliation — physical vs payable vs technician vs submitted
A2: Physical and payable columns are formulas from Segment_Takeoff totals; technician/submitted columns cite source rows.
A4: Item family | B4: Physical computed | C4: Payable (spec) | D4: Technician / submitted claim | E4: Bid quantity | F4: Variance: bid − payable | G4: Payable basis (clause) | H4: Evidence state | I4: Locator
A5: Steel panel removal (SF) | B5: =Segment_Takeoff!E53 | C5: =Segment_Takeoff!G53 | D5: 3877.2 | E5: 3980 | F5: =E5-C5 | G5: geometry verified; vendor schedule differs | H5: ramp_segment_takeoff.csv Σ; ferry_base_ve_bid_items.csv B01; FMR-001
A6: New steel deck panels (SF) | B6: =Segment_Takeoff!E53 | C6: =Segment_Takeoff!H53 | D6: 3877.2 | E6: 3980 | F6: =E6-C6 | G6: geometry verified; vendor schedule differs | H6: ramp_segment_takeoff.csv Σ; ferry_base_ve_bid_items.csv B02; FMR-002
A7: Skewed hinge/joint seals (LF) | B7: =Segment_Takeoff!F53 | C7: =Segment_Takeoff!I53 | D7: 1069.2 | E7: 1260 | F7: =E7-C7 | G7: submitted joint = clear width (skew ignored) | H7: ramp_segment_takeoff.csv Σ; ferry_base_ve_bid_items.csv B03/V04; FMR-004; U2 unresolved
A8: Wearing overlay (SF, VE option) | B8: =Segment_Takeoff!E53 | C8: =Segment_Takeoff!H53 | D8: 3980 | E8: 3980 | F8: =E8-C8 | G8: submitted = plan area (consistent) | H8: ferry_base_ve_bid_items.csv V03; FMR-003
A9: Corrosion repair (SF) | B9: 169.02 | C9: =Segment_Takeoff!M53 | D9: 780 | E9: 820 | F9: =E9-C9 | G9: CONFLICT: mapped 170 / technician 780 / bid 820 | H9: ferry_ramp_dimensions…csv corrosion row; ferry_base_ve_bid_items.csv V05; FMR-006
A10: Bearing interface zones (EA) | B10: 24 | C10: 24 | D10: 24 | E10: 24 | F10: =E10-C10 | G10: count consistent; condition "conditional" per FEE-006 | H10: ferry_ramp_dimensions…csv bearings row; ferry_base_ve_bid_items.csv B04; FMR-005
A11: Coating / containment (SF) | B11: 5240 | C11: 5240 | D11: 5240 | E11: 5240 | F11: =E11-C11 | G11: area consistent; adhesion 680 psi CONTRADICTED (FEE-003) | H11: ferry_ramp_dimensions…csv coating row "not payable until accepted"; ferry_base_ve_bid_items.csv B05; FMR-007
A12: FRP panel zones (SF, VE option) | B12: 1360 | C12: 1360 | D12: 1360 | E12: 1360 | F12: =E12-C12 | G12: FRP qualification FIELD-VERIFICATION-REQUIRED (FEE-008) | H12: ferry_ramp_dimensions…csv FRP row; ferry_base_ve_bid_items.csv V01/V02

Sheet Submitted_Bids
A1: Submitted Bid Items — Internal Consistency Check
A2: Source: ferry_base_ve_bid_items.csv (all rows, evidence_status=submitted_unverified). Amount check = qty × unit price vs submitted amount.
A4: Option | B4: Item | C4: Description | D4: Qty | E4: Unit | F4: Unit price ($) | G4: Submitted amount ($) | H4: Recomputed amount ($) | I4: Δ ($) | J4: Scope status | K4: Estimate date
A5: base_full_replacement | B5: B01 | C5: Remove existing steel deck panels | D5: 3980 | E5: SF | F5: 96 | G5: 382080 | H5: =D5*F5 | I5: =H5-G5 | J5: allowance | K5: 2027-02-15
A6: base_full_replacement | B6: B02 | C6: Fabricate and install orthotropic steel panels | D6: 3980 | E6: SF | F6: 615 | G6: 2447700 | H6: =D6*F6 | I6: =H6-G6 | J6: included | K6: 2027-02-15
A7: base_full_replacement | B7: B03 | C7: Replace skewed hinge seals | D7: 1260 | E7: LF | F7: 840 | G7: 1058400 | H7: =D7*F7 | I7: =H7-G7 | J7: included | K7: 2027-02-15
A8: base_full_replacement | B8: B04 | C8: Bearing-interface repairs | D8: 24 | E8: EA | F8: 18200 | G8: 436800 | H8: =D8*F8 | I8: =H8-G8 | J8: included | K8: 2027-02-15
A9: base_full_replacement | B9: B05 | C9: Protective coating and containment | D9: 5240 | E9: SF | F9: 128 | G9: 670720 | H9: =D9*F9 | I9: =H9-G9 | J9: included | K9: 2027-02-15
A10: base_full_replacement | B10: B06 | C10: Ferry operations and traffic staging | D10: 1 | E10: LS | F10: 410000 | G10: 410000 | H10: =D10*F10 | I10: =H10-G10 | J10: allowance | K10: 2027-02-15
A11: base_full_replacement | B11: B07 | C11: Mobilization and submitted allowances | D11: 1 | E11: LS | F11: 525000 | G11: 525000 | H11: =D11*F11 | I11: =H11-G11 | J11: included | K11: 2027-02-15
A12: ve_overlay_frp | B12: V01 | C12: Selective panel removal | D12: 1360 | E12: SF | F12: 112 | G12: 152320 | H12: =D12*F12 | I12: =H12-G12 | J12: included | K12: 2027-04-01
A13: ve_overlay_frp | B13: V02 | C13: Install qualified FRP panel zones | D13: 1360 | E13: SF | F13: 488 | G13: 663680 | H13: =D13*F13 | I13: =H13-G13 | J13: included | K13: 2027-04-01
A14: ve_overlay_frp | B14: V03 | C14: Prepare and install wearing overlay | D14: 3980 | E14: SF | F14: 174 | G14: 692520 | H14: =D14*F14 | I14: =H14-G14 | J14: included | K14: 2027-04-01
A15: ve_overlay_frp | B15: V04 | C15: Rehabilitate skewed hinge seals | D15: 1260 | E15: LF | F15: 515 | G15: 648900 | H15: =D15*F15 | I15: =H15-G15 | J15: allowance | K15: 2027-04-01
A16: ve_overlay_frp | B16: V05 | C16: Localized corrosion and bearing repair | D16: 820 | E16: SF | F16: 246 | G16: 201720 | H16: =D16*F16 | I16: =H16-G16 | J16: included | K16: 2027-04-01
... A20: add_alternate | B20: A02 | C20: Additional overnight closure window | D20: 3 | E20: EA | F20: 52000 | G20: 156000 | H20: =D20*F20 | I20: =H20-G20 | J20: allowance | K20: 2027-04-01
C22: TOTAL base_full_replacement (B01–B07) | H22: =SUMIF($A$5:$A$21,"base_full_replacement",H5:H21)
C23: TOTAL ve_overlay_frp (V01–V07) | H23: =SUMIF($A$5:$A$21,"ve_overlay_frp",H5:H21)
C24: TOTAL add_alternate (A01–A02) | H24: =SUMIF($A$5:$A$21,"add_alternate",H5:H21)
A26: All amounts are internally consistent (Δ = 0 expected). Items flagged "allowance" are not firm quantities/prices — they are submitted placeholders requiring board-approved basis per FMR-012 (risk) and FMR-009/010 (LS items).

Sheet Market_Evidence
A1: Market & Price-Basis Evidence vs Submitted Unit Prices
A2: Benchmarks are governing-reference ranges; submitted prices are unverified claims (ferry_base_ve_bid_items.csv, evidence_status=submitted_unverified).
A4: Item | B4: Submitted unit price | C4: Benchmark range | D4: Benchmark basis / locator | E4: Assessment
A5: B02 Fabricate+install orthotropic steel panels ($/SF) | B5: 615 | C5: Structural carbon steel $2.75–3.75/LB (≈$42–57/SF plate material at 0.375 in, 15.3 lb/SF) | D5: WSDOT BDM Ch.12 App. 12.3-A3 (PDF p.35); steel weight 490 lb/ft³ per Std Spec 6-03.5 (PDF p.515) | E5: NOT COMPARABLE to material index — price includes fabrication, orthotropic details, install; no direct supplied benchmark. UNVALIDATED — retain price risk.
A6: B05 Protective coating + containment ($/SF) | B6: 128 | C6: Painting existing steel bridges $15–45/SF | D6: WSDOT BDM Ch.12 App. 12.3-A4 (PDF p.37) | E6: ABOVE supplied range; ferry-terminal SSPC Guide 6 Class 1 full-removal containment (Std Spec 6-07.3(12)/(10)A, PDF pp.548,558-559) is more onerous than the generic range, but premium is UNVALIDATED — flag.
A7: B03 Replace skewed hinge seals ($/LF) | B7: 840 | C7: Strip seal $450–900/LF; modular joint $500–7,000/LF | D7: WSDOT BDM Ch.12 Superstructure Cost table (PDF p.36) | E7: WITHIN supplied range. Plausible; still submitted_unverified.
A8: V04 Rehabilitate skewed hinge seals ($/LF) | B8: 515 | C8: Strip seal $450–900/LF | D8: WSDOT BDM Ch.12 Superstructure Cost table (PDF p.36) | E8: WITHIN supplied range (low end). Plausible for rehab scope.
A9: V05 Localized corrosion & bearing repair ($/SF) | B9: 246 | C9: Bridge deck repair $150–350/SF | D9: WSDOT BDM Ch.12 App. 12.3-A4 (PDF p.37) | E9: WITHIN supplied range (concrete deck repair used as proxy; steel loss repair is a different work type — treat as indicative only).
A10: V03 Wearing overlay ($/SF) | B10: 174 | C10: Modified concrete overlay $35–50/CF; furnish+cure $40–75/SY | D10: WSDOT BDM Ch.12 Superstructure Cost table (PDF p.36) | E10: ABOVE supplied ranges; V03 is a polymer/FRP-compatible wearing surface on steel, not modified concrete — no direct supplied benchmark. UNVALIDATED — retain price risk.
A11: B07 Mobilization + submitted allowances (LS) | B11: 525000 | C11: Mobilization 8–10% of contract total for $5–10M contracts | D11: WSDOT CEM M 30-34.04 §14.17 Exhibit 14-5 (PDF p.85); BDM 12.3-A4 "Mobilization — 10%" (PDF p.37) | E11: =9.7% of base work items (formula below) — WITHIN band. Note item bundles unspecified "submitted allowances" — breakdown required per CEM §10.07/§10.08 (lump-sum justification).
A12: Escalation basis | B12: — | C12: PPI ready-mix concrete +2.18%/yr latest (2025-07→2026-07) | D12: FRED PCU327320327320 (fred_ppi_ready_mix_concrete.csv, observations 2025-07=393.322, 2026-07=401.896) | E12: Used as escalation proxy (Parameters P02). Ready-mix is a concrete index; steel/fab index not supplied — stated limitation.
A13: WSDOT 2025 bid history | B13: — | C13: 33-page contract bid history, award dates Jan–Jun 2025 | D13: wsdot_bid_history_2025.pdf (DOT_RGGB02, dated 6/13/2025) | E13: 33 contracts, one per page pp.1-33, awards Jan-Jun 2025. Low bid vs engineer estimate: median -4.3%, mean -1.6%, 21 of 33 under (computed from report figures). ONE directly comparable marine/ferry steel contract: XE3589 SR 304 Bremerton Ferry Terminal Slip 2 Dolphin Replacements (p.6, award 03/11/2025, est $3,091,020, low bid $2,874,016 = -7.0%, 4 bidders, Kitsap). NO orthotropic-panel, FRP, or ferry-ramp bid items in the report -> specialty submitted prices remain UNVALIDATED; competitive ferry-terminal marine work is bidding ~7% under estimate.
A15: Mobilization check: =Submitted_Bids B07 / (base total − B07): | D15: =525000/(Submitted_Bids!H22-525000)

Sheet Independent_Estimate
A1: Independent Engineer Estimate — common scope, payable quantities
A2: Quantities = specification-payable (Quantity_Reconciliation); price basis = submitted unit prices (unverified, flagged); markups per Parameters.
A4: Line | B4: Item | C4: Payable qty | D4: Unit | E4: Unit price ($) | F4: Amount ($) | G4: Price basis | H4: Note
A5: BASE OPTION — full steel deck-panel replacement
A6: E01 | B6: Remove existing steel deck panels | C6: =Quantity_Reconciliation!C5 | D6: SF | E6: 96 | F6: =C6*E6 | G6: submitted_unverified | H6: Bid B01 qty 3980 → payable 3,977.6 (FMR-001)
A7: E02 | B7: Fabricate and install orthotropic steel panels | C7: =Quantity_Reconciliation!C6 | D7: SF | E7: 615 | F7: =C7*E7 | G7: submitted_unverified | H7: Payable whole SF (FMR-002); price unvalidated vs BDM material index
A8: E03 | B8: Replace skewed hinge/joint seals | C8: =Quantity_Reconciliation!C7 | D8: LF | E8: 840 | F8: =C8*E8 | G8: submitted_unverified | H8: Payable geometric skew length (FMR-004); U2 scope boundary flagged
A9: E04 | B9: Bearing-interface repairs | C9: =Quantity_Reconciliation!C10 | D9: EA | E9: 18200 | F9: =C9*E9 | G9: submitted_unverified | H9: 24 zones; condition "conditional" per FEE-006 — see A01 alternate
A10: E05 | B10: Protective coating and containment | C10: =Quantity_Reconciliation!C11 | D10: SF | E10: 128 | F10: =C10*E10 | G10: submitted_unverified | H10: Payable DFT-passing only (FMR-007); adhesion evidence contradicted (FEE-003)
A11: E06 | B11: Ferry operations and traffic staging (LS allowance) | C11: 1 | D11: LS | E11: 410000 | F11: =C11*E11 | G11: submitted allowance | H11: FMR-010: approved stage plans only; 6-hr closure contradicted (FEE-007)
A12: E07 | B12: Mobilization and submitted allowances (LS) | C12: 1 | D12: LS | E12: 525000 | F12: =C12*E12 | G12: submitted_unverified | H12: 9.7% of work items — within CEM Exh.14-5 band; breakdown required
B13: Base construction subtotal (payable quantities) | F13: =SUM(F6:F12)
A14: VE OPTION — staged overlay/FRP panel concept
A15: E08 | B15: Selective panel removal | C15: =Quantity_Reconciliation!C12 | D15: SF | E15: 112 | F15: =C15*E15 | G15: submitted_unverified | H15: FRP zone = submitted max boundary 1,360 SF (34.2% of deck)
A16: E09 | B16: Install qualified FRP panel zones | C16: =Quantity_Reconciliation!C12 | D16: SF | E16: 488 | F16: =C16*E16 | G16: submitted_unverified | H16: CONDITION PRECEDENT: FRP qualification field verification (FEE-008)
A17: E10 | B17: Prepare and install wearing overlay | C17: =Quantity_Reconciliation!C8 | D17: SF | E17: 174 | F17: =C17*E17 | G17: submitted_unverified | H17: Payable accepted finished surface (FMR-003); chloride/adhesion gates open
A18: E11 | B18: Rehabilitate skewed hinge/joint seals | C18: =Quantity_Reconciliation!C7 | D18: LF | E18: 515 | F18: =C18*E18 | G18: submitted allowance | H18: Payable geometric skew length (FMR-004); submitted scope_status=allowance
A19: E12 | B19: Localized corrosion and bearing repair | C19: =Quantity_Reconciliation!C9 | D19: SF | E19: 246 | F19: =C19*E19 | G19: submitted_unverified | H19: Payable = MAPPED area only (FMR-006); technician 780 SF carried as risk allowance E15
A20: E13 | B20: Ferry operations and traffic staging (LS) | C20: 1 | D20: LS | E20: 315000 | F20: =C20*E20 | G20: submitted_unverified | H20: FMR-010; closure window not confirmed
A21: E14 | B21: Qualification testing and submitted allowance (LS) | C21: 1 | D21: LS | E21: 285000 | F21: =C21*E21 | G21: submitted_unverified | H21: FMR-012: board-approved risk basis required
B22: VE construction subtotal (payable quantities, mapped corrosion) | F22: =SUM(F15:F21)
A23: E15 | B23: VE named risk allowance: corrosion extent up to technician 780 SF (P10) above mapped payable | C23: =Parameters!C14-Quantity_Reconciliation!C9 | D23: SF | E23: 246 | F23: =C23*E23 | G23: risk allowance | H23: FMR-012 board-approved risk basis; FMR-006 excludes unmapped steel from payment until mapped
A25: MARKUPS & TOTALS
B26: Base subtotal | F26: =F13
B27: VE subtotal incl corrosion risk allowance | F27: =F22+F23
B28: Escalation factor to construction midpoint (P02, P03) | F28: =(1+Parameters!C6)^Parameters!C7
B29: Base escalated | F29: =F26*F28
B30: VE escalated | F30: =F27*F28
B31: Change-order contingency (P04 = 4% DBB, CEM §14.19) | F31: =Parameters!C8
B32: BASE INDEPENDENT TOTAL (YOE $) | F32: =F29*(1+F31)
B33: VE INDEPENDENT TOTAL (YOE $) | F33: =F30*(1+F31)
B34: Independent savings, VE vs base (YOE $) | F34: =F32-F33
B35: Submitted savings claim (Bid totals) | F35: =Submitted_Bids!H22-Submitted_Bids!H23
A37: Scope parity: both options priced on the same payable joint length, bearing count, coating area, staging and closure constraints (memo §3 common-scope requirement).
A38: Excluded from both totals: sales tax, PE/CE engineering, escalation beyond stated factor — per BDM 12.3.3 (PDF p.15) bridge estimates exclude these; program level must add per CEM Exhibit 7-3/7-5 (PDF pp.39,41).
A39: Price basis limitation: no independent fabrication/marine pricing was supplied for B02, B05, V02, V03 (Market_Evidence); totals inherit submitted-price risk. This is a stated boundary, not an oversight.
A40: Add-alternates excluded from totals: A01 $175,200 (recommended — see Recommendation), A02 $156,000 allowance (deferred pending operations confirmation).

Sheet Bridge_Zero_Residual
A1: Submitted → Independent Estimate Bridge (zero-residual walk)
A2: Every dollar difference is assigned to a named component; residual formula must evaluate to 0. Memo §3 requirement.
A4: Step | B4: Component | C4: Base option ($) | D4: VE option ($) | E4: Basis / locator
A5: S0 | B5: Submitted total (ferry_base_ve_bid_items.csv; estimate dates 2027-02-15 / 2027-04-01) | C5: =Submitted_Bids!H22 | D5: =Submitted_Bids!H23 | E5: Submitted_Bids sheet totals
A6: S1 | B6: Quantity correction: panel removal to payable 3,977.6 SF (FMR-001, 0.1 SF) | C6: =(Quantity_Reconciliation!C5-3980)*96 | D6: 0 | E6: Segment_Takeoff col G total; bid B01 = 3,980 SF
A7: S2 | B7: Quantity correction: hinge/joint seals to payable geometric skew length (FMR-004) | C7: =(Quantity_Reconciliation!C7-1260)*840 | D7: =(Quantity_Reconciliation!C7-1260)*515 | E7: Segment_Takeoff col I total = 1,255.6 LF vs bid 1,260 LF
A8: S3 | B8: Quantity correction: corrosion repair to mapped payable 170 SF (FMR-006) | C8: 0 | D8: =(Quantity_Reconciliation!C9-820)*246 | E8: Bid V05 = 820 SF; payable = mapped takeoff only
A9: S4 | B9: Named risk allowance: corrosion extent to technician 780 SF (board-approved basis required, FMR-012) | C9: 0 | D9: =Independent_Estimate!F23 | E9: Parameters P10; dimensions file corrosion row (unverified)
A10: S5 | B10: Price-basis adjustment | C10: 0 | D10: 0 | E10: NONE — no independent pricing supplied; submitted prices retained as unverified basis (Market_Evidence flags)
A11: S6 | B11: Escalation to construction midpoint (PPI proxy +2.18%/yr × 0.85 yr) | C11: =Independent_Estimate!F29-Independent_Estimate!F26-0 | D11: =Independent_Estimate!F30-Independent_Estimate!F27 | E11: Parameters P02/P03; FRED PCU327320327320
A12: S7 | B12: Change-order contingency 4% (DBB) | C12: =Independent_Estimate!F29*Parameters!C8 | D12: =Independent_Estimate!F30*Parameters!C8 | E12: CEM M 30-34.04 §14.19 (PDF p.86)
B13: INDEPENDENT TOTAL (sum of steps) | C13: =SUM(C5:C12) | D13: =SUM(D5:D12)
B14: Independent_Estimate sheet total (cross-check) | C14: =Independent_Estimate!F32 | D14: =Independent_Estimate!F33
B15: RESIDUAL (must be 0) | C15: =C13-C14 | D15: =D13-D14

Sheet Evidence_Gates
A1: Technical / Evidence Gate Matrix
A2: 8 unique gates distilled from ferry_engineering_evidence_ledger.csv (24 rows = 8 gates × 3 repeat observations, FEE-001…024). States are as-recorded; nothing upgraded without new field evidence.
A4: Gate | B4: Domain | C4: Observed value | D4: Evidence state | E4: Ledger rows | F4: Decision impact | G4: Required action before reliance
A5: G1 | B5: Steel thickness | C5: 0.31 in (grid) | D5: submitted | E5: FEE-001/009/017 | F5: Nominal plate 0.375 in (dimensions file) → 0.31 in implies ~17% section loss; if verified low, overlay/FRP substrate adequacy fails and base replacement is forced. | G5: Independent UT thickness survey across all 12 panel groups; acceptance limits in spec before relying on VE substrate.
A6: G2 | B6: Corrosion loss | C6: 18% (UT survey) | D6: independently-verified | E6: FEE-002/010/018 | F6: Only verified condition evidence. 18% of 3,978.6 SF ≈ 716 SF potential repair extent — supports technician 780 SF more than mapped 170 SF; drives VE corrosion risk allowance. | G6: Extend UT mapping to full deck; reconcile mapped 170 SF vs 18%-extent ~716 SF before fixing V05 payable quantity.
A7: G3 | B7: Coating adhesion | C7: 680 psi (pull-off) | D7: contradicted | E7: FEE-003/011/019 | F7: Overcoat/overlay bond assumptions are unreliable; coating payment is DFT-passing only (FMR-007). Affects both options (base coating, VE overlay bond). | G7: Repeat pull-off testing per accepted test plan; resolve contradiction before accepting coating/overlay scope pricing.
A8: G4 | B8: Chloride contamination | C8: 6.8 µg/cm² | D8: field-verification-required | E8: FEE-004/012/020 | F8: Above common coating/overlay acceptance thresholds if confirmed; drives surface-prep level and overlay bond risk in VE option. | G8: Field chloride verification; adjust prep scope before VE overlay award.
A9: G5 | B9: Hinge geometry | C9: 27° skew (field survey) | D9: submitted | E9: FEE-005/013/021 | F9: Joint payable quantity is geometric skew length (FMR-004); takeoff skews 18–41° per segment. Submitted joint length (1,069 LF) ignored skew; bid 1,260 LF matches computed 1,255.3 LF. | G9: Confirm joint network scope (boundary U2: 48-segment joints vs two hinges = 71.8 LF) and re-survey skews.
A10: G6 | B10: Bearing interface | C10: conditional (visual/NDE dossier) | D10: independently-verified | E10: FEE-006/014/022 | F10: Bearing repairs B04 (24 EA) rest on conditional condition; adjacent damage excluded from payment (FMR-005). Expanded NDE (A01, 12 EA, $175,200) is the prudent hedge. | G10: Accept A01 add-alternate; complete NDE before finalizing B04 scope.
A11: G7 | B11: Tidal closure | C11: 6 hr/night (ops calendar) | D11: contradicted | E11: FEE-007/015/023 | F11: VE overlay cure windows and all night work assume 6-hr closures; contradiction threatens VE staging feasibility and triggers A02 closure premium ($52,000/window). Unapproved outage excluded from payment (FMR-010). | G11: Obtain operations-approved closure windows in writing before VE award; defer A02 until then.
A12: G8 | B12: FRP qualification | C12: vendor submittal: submitted | D12: field-verification-required | E12: FEE-008/016/024 | F12: VE V02 ($663,680) and the 22-yr life claim rest on an unverified vendor submittal. FHWA VE doctrine: VE must confirm required functions and life-cycle cost (23 U.S.C. 106(f)(2), fhwa_ve_policy.pdf p.1) — an unqualified system cannot confirm function. | G12: Independent qualification testing (V07 scope) with acceptance criteria fixed before award; failure reverts to base scope.
A14: Repeat-observation note: each gate appears 3× in the ledger with identical value and state (e.g., FEE-001/009/017) — treated as one evidence record, not three independent confirmations.

Sheet Lifecycle
A1: Lifecycle Present-Worth Comparison (40-yr analysis horizon)
A2: Base life 40 yr (planning assumption, P07); VE claimed life 22 yr (SUBMITTED, UNVERIFIED, P06). Real discount rate P01; renewal at P08 fraction of VE independent total. No maintenance costs supplied — exclusion stated.
A4: Component | B4: Base option | C4: VE option | D4: Note
A5: Initial independent total (YOE $, from Independent_Estimate) | B5: =Independent_Estimate!F32 | C5: =Independent_Estimate!F33 | D5: Includes escalation + 4% COC
A6: Analysis horizon (yr) | B6: =Parameters!C11 | C6: =Parameters!C11 | D6: P07
A7: Service life before renewal (yr) | B7: =Parameters!C11 | C7: =Parameters!C10 | D7: Base 40; VE 22 claimed — UNVERIFIED
A8: Renewal events within horizon | B8: 0 | C8: 1 | D8: VE renewed once at yr 22 within 40-yr horizon
A9: Renewal cost fraction (P08) | B9: 0 | C9: =Parameters!C12 | D9: Conservative: full VE scope repeat
A10: PW of renewal ($) | B10: 0 | C10: =Independent_Estimate!F33*Parameters!C12/(1+Parameters!C5)^Parameters!C10 | D10: Discounted at P01 = 3% real
A11: LIFECYCLE PW TOTAL ($) | B11: =B5+B10 | C11: =C5+C10
A12: Lifecycle advantage of VE ($) | B12: =B11-C11 | D12: Positive = VE cheaper over 40 yr
A15: Discount-rate sensitivity (PW totals, $)
A16: Rate | B16: Base PW | C16: VE PW (1 renewal at claimed life) | D16: VE PW advantage
A17: 0.02 | B17: =Independent_Estimate!F32 | C17: =Independent_Estimate!F33+Independent_Estimate!F33*Parameters!C12/(1+A17)^Parameters!C10 | D17: =B17-C17
A18: 0.03 | B18: =Independent_Estimate!F32 | C18: =Independent_Estimate!F33+Independent_Estimate!F33*Parameters!C12/(1+A18)^Parameters!C10 | D18: =B18-C18
A19: 0.04 | B19: =Independent_Estimate!F32 | C19: =Independent_Estimate!F33+Independent_Estimate!F33*Parameters!C12/(1+A19)^Parameters!C10 | D19: =B19-C19
A21: Result is robust: VE holds a PW advantage at 2%–4% real discount even with a full-scope renewal at yr 22, because the submitted VE price is ~50% of base.
A22: The decision therefore turns on EVIDENCE (verified life, qualification, closure windows), not on first cost — see Sensitivity_Switch.
A23: Exclusions: routine maintenance, deck-overlay renewal of the BASE option within 40 yr, residual/salvage value — none supplied; both options treated symmetrically.

Sheet Sensitivity_Switch
A1: Joint Cost / Evidence Switch — decision-changing conditions
A2: Conditions under which the recommendation flips. All cells formula-driven from Independent_Estimate and Parameters.
A4: SWITCH 1 — Verified VE service life (the governing switch)
A5: If the overlay/FRP system life verifies BELOW the flip value, a second renewal lands inside the 40-yr horizon and the VE PW advantage disappears.
A6: Candidate verified life L (yr) | B6: Renewals in 40-yr horizon | C6: VE PW with renewals ($) | D6: Base PW ($) | E6: VE advantage ($) | F6: Verdict
A7: 22 | B7: =INT(Parameters!C11/A7) | C7: =Independent_Estimate!F33 + Independent_Estimate!F33*Parameters!C12*SUMPRODUCT((ROW(INDIRECT("1:"&B7))*A7<=Parameters!C11)/(1+Parameters!C5)^(ROW(INDIRECT("1:"&B7))*A7)) | D7: =Independent_Estimate!F32 | E7: =D7-C7 | F7: =IF(E7>0,"VE holds","REVERT TO BASE")
A8: 20 | B8: =INT(Parameters!C11/A8) | C8: =Independent_Estimate!F33 + Independent_Estimate!F33*Parameters!C12*SUMPRODUCT((ROW(INDIRECT("1:"&B8))*A8<=Parameters!C11)/(1+Parameters!C5)^(ROW(INDIRECT("1:"&B8))*A8)) | D8: =Independent_Estimate!F32 | E8: =D8-C8 | F8: =IF(E8>0,"VE holds","REVERT TO BASE")
A9: 18 | B9: =INT(Parameters!C11/A9) | C9: =Independent_Estimate!F33 + Independent_Estimate!F33*Parameters!C12*SUMPRODUCT((ROW(INDIRECT("1:"&B9))*A9<=Parameters!C11)/(1+Parameters!C5)^(ROW(INDIRECT("1:"&B9))*A9)) | D9: =Independent_Estimate!F32 | E9: =D9-C9 | F9: =IF(E9>0,"VE holds","REVERT TO BASE")
A10: 16 | B10: =INT(Parameters!C11/A10) | C10: =Independent_Estimate!F33 + Independent_Estimate!F33*Parameters!C12*SUMPRODUCT((ROW(INDIRECT("1:"&B10))*A10<=Parameters!C11)/(1+Parameters!C5)^(ROW(INDIRECT("1:"&B10))*A10)) | D10: =Independent_Estimate!F32 | E10: =D10-C10 | F10: =IF(E10>0,"VE holds","REVERT TO BASE")
A11: 15 | B11: =INT(Parameters!C11/A11) | C11: =Independent_Estimate!F33 + Independent_Estimate!F33*Parameters!C12*SUMPRODUCT((ROW(INDIRECT("1:"&B11))*A11<=Parameters!C11)/(1+Parameters!C5)^(ROW(INDIRECT("1:"&B11))*A11)) | D11: =Independent_Estimate!F32 | E11: =D11-C11 | F11: =IF(E11>0,"VE holds","REVERT TO BASE")
A12: 14 | B12: =INT(Parameters!C11/A12) | C12: =Independent_Estimate!F33 + Independent_Estimate!F33*Parameters!C12*SUMPRODUCT((ROW(INDIRECT("1:"&B12))*A12<=Parameters!C11)/(1+Parameters!C5)^(ROW(INDIRECT("1:"&B12))*A12)) | D12: =Independent_Estimate!F32 | E12: =D12-C12 | F12: =IF(E12>0,"VE holds","REVERT TO BASE")
A13: 12 | B13: =INT(Parameters!C11/A13) | C13: =Independent_Estimate!F33 + Independent_Estimate!F33*Parameters!C12*SUMPRODUCT((ROW(INDIRECT("1:"&B13))*A13<=Parameters!C11)/(1+Parameters!C5)^(ROW(INDIRECT("1:"&B13))*A13)) | D13: =Independent_Estimate!F32 | E13: =D13-C13 | F13: =IF(E13>0,"VE holds","REVERT TO BASE")
A14: 10 | B14: =INT(Parameters!C11/A14) | C14: =Independent_Estimate!F33 + Independent_Estimate!F33*Parameters!C12*SUMPRODUCT((ROW(INDIRECT("1:"&B14))*A14<=Parameters!C11)/(1+Parameters!C5)^(ROW(INDIRECT("1:"&B14))*A14)) | D14: =Independent_Estimate!F32 | E14: =D14-C14 | F14: =IF(E14>0,"VE holds","REVERT TO BASE")
A15: 8 | B15: =INT(Parameters!C11/A15) | C15: =Independent_Estimate!F33 + Independent_Estimate!F33*Parameters!C12*SUMPRODUCT((ROW(INDIRECT("1:"&B15))*A15<=Parameters!C11)/(1+Parameters!C5)^(ROW(INDIRECT("1:"&B15))*A15)) | D15: =Independent_Estimate!F32 | E15: =D15-C15 | F15: =IF(E15>0,"VE holds","REVERT TO BASE")
A17: SWITCH 2 — Verified corrosion extent (VE first-cost erosion)
A18: Verified corrosion (SF) | B18: VE total ($) | C18: VE advantage vs base ($) | D18: Verdict | E18: Note
A19: 170 | B19: =(Independent_Estimate!F22-Quantity_Reconciliation!C9*246+A19*246)*(1+Parameters!C6)^Parameters!C7*(1+Parameters!C8) | C19: =Independent_Estimate!F32-B19 | D19: =IF(C19>0,"VE holds","REVERT TO BASE") | E19: Mapped payable only (FMR-006)
A20: 400 | B20: =(Independent_Estimate!F22-Quantity_Reconciliation!C9*246+A20*246)*(1+Parameters!C6)^Parameters!C7*(1+Parameters!C8) | C20: =Independent_Estimate!F32-B20 | D20: =IF(C20>0,"VE holds","REVERT TO BASE") | E20: Intermediate
A21: 716 | B21: =(Independent_Estimate!F22-Quantity_Reconciliation!C9*246+A21*246)*(1+Parameters!C6)^Parameters!C7*(1+Parameters!C8) | C21: =Independent_Estimate!F32-B21 | D21: =IF(C21>0,"VE holds","REVERT TO BASE") | E21: 18% verified loss applied deck-wide (FEE-002)
A22: 780 | B22: =(Independent_Estimate!F22-Quantity_Reconciliation!C9*246+A22*246)*(1+Parameters!C6)^Parameters!C7*(1+Parameters!C8) | C22: =Independent_Estimate!F32-B22 | D22: =IF(C22>0,"VE holds","REVERT TO BASE") | E22: Technician estimate (P10, unverified)
A23: 1000 | B23: =(Independent_Estimate!F22-Quantity_Reconciliation!C9*246+A23*246)*(1+Parameters!C6)^Parameters!C7*(1+Parameters!C8) | C23: =Independent_Estimate!F32-B23 | D23: =IF(C23>0,"VE holds","REVERT TO BASE") | E23: Beyond technician estimate
A24: 1500 | B24: =(Independent_Estimate!F22-Quantity_Reconciliation!C9*246+A24*246)*(1+Parameters!C6)^Parameters!C7*(1+Parameters!C8) | C24: =Independent_Estimate!F32-B24 | D24: =IF(C24>0,"VE holds","REVERT TO BASE") | E24: ~38% of deck — substrate adequacy questionable (engineering judgment)
A26: SWITCH 3 — Closure windows
A27: If operations cannot confirm ≥6-hr night windows in writing (G7 contradicted), VE staging is infeasible as priced: each additional overnight window = $52,000 (A02 basis) and unapproved outages are non-payable service failures (FMR-010). More than ~60 extra windows would erode the VE advantage arithmetically, but the OPERATIONAL floor (1 ramp always active; memo §4) governs first — treat as a gate, not a cost.
A29: SWITCH 4 — Evidence gates failing
A30: Failure of G8 (FRP qualification), G1 (thickness < 0.31 in on verification), or unresolved G3/G4 (adhesion/chloride) each independently reverts the decision to the base scope regardless of cost, because VE function cannot be confirmed (23 U.S.C. 106(f)(2) function test, fhwa_ve_policy.pdf p.1).
A32: NON-SWITCHES (checked, do not flip decision)
A33: Quantity corrections (panels −2.4 SF; joints −4.4 LF) and 2%–4% discount rate move totals <1%; corrosion extent alone cannot flip the decision arithmetically within the deck area (breakeven ≈ 12,800 SF > 3,978.6 SF deck) — it matters through substrate adequacy (Switch 4), not price.

Sheet Recommendation
A1: Recommendation & Board Disposition
A2: All figures reference Independent_Estimate / Lifecycle / Sensitivity_Switch cells so this sheet cannot drift from the model.
A4: R1 — DEFENSIBLE BASE SCOPE (decision floor)
A5: Full steel deck-panel replacement at SPECIFICATION-PAYABLE quantities: removal 3,977.6 SF (FMR-001); new orthotropic panels 3,980 SF (FMR-002);
A6: skewed hinge/joint seals 1,255.6 LF geometric skew length (FMR-004); bearing-interface repairs 24 EA (FMR-005); coating + containment 5,240 SF DFT-passing only (FMR-007).
A7: Independent base total (YOE $, incl. escalation + 4% DBB change-order contingency): =Independent_Estimate!F32 — see cell link below.
A9: Base independent total ($): | B9: =Independent_Estimate!F32
A10: VE independent total incl. corrosion risk allowance ($): | B10: =Independent_Estimate!F33
A11: Independent first-cost advantage of VE ($): | B11: =Independent_Estimate!F32-Independent_Estimate!F33
A12: Lifecycle PW advantage of VE, 40-yr @3% real ($): | B12: =Lifecycle!B12-Lifecycle!C12
A14: R2 — VE DISPOSITION: CONDITIONAL APPROVAL (not acceptance as submitted)
A15: The overlay/FRP VE concept is technically plausible and cost-advantaged on both first cost and 40-yr present worth at the CLAIMED 22-yr life.
A16: It is NOT approvable as submitted because function-critical evidence is unverified or contradicted: FRP qualification (G8), steel thickness (G1), coating adhesion (G3, contradicted), chloride (G4), closure windows (G7, contradicted).
A17: Per FHWA VE doctrine (23 U.S.C. 106(f)(2); fhwa_ve_policy.pdf p.1) VE must confirm needed functions and life-cycle cost — confirmation is impossible on the current evidence record.
A18: DISPOSITION: approve the VE concept conditionally; fix acceptance criteria and complete gates G1–G8 actions (Evidence_Gates col G) BEFORE award; if any of G1/G3/G4/G7/G8 fails, revert to base scope R1.
A19: Verified-life floor: if qualification verifies a system life below ~16 yr (Sensitivity_Switch Switch 1), revert to base — the PW advantage is exhausted by a second renewal.
A21: R3 — ADD-ALTERNATES
A22: A01 Expanded bearing NDE + contingent repair (12 EA, $175,200 submitted): ACCEPT NOW — bearing evidence is "conditional" (G6) and FMR-005 excludes unverified adjacent damage; NDE is the cheapest risk control available.
A23: A02 Additional overnight closure windows (3 EA, $156,000 allowance): DEFER — do not buy closure windows until operations confirms the 6-hr window contradiction (G7) in writing.
A25: R4 — UNRESOLVED BOUNDARIES (stated, not fabricated)
A26: U1: takeoff totals 178.2 ft vs stated movable length 162.0 ft (~9.1% excess) — payable quantities assume full takeoff; confirm coverage before PS&E. Sensitivity: −9.1% panel scope if 162 ft governs.
A27: U2: joint scope ambiguity — bid/takeoff joint network 1,255.3 LF vs two-hinge geometry 71.8 LF (N 30.8 ft @ 27°, S 31.2 ft @ 33°). Quantities carry the 48-segment network; if only two hinges are in scope, joint items reduce ~94%.
... A36: Estimate file / BOE documentation duties per CEM §6.01/§6.04 (PDF pp.34–35) apply to any reissue of this estimate.
