Workbook

Sheet AAPL-3-Statements
B2: =Company_Name&" - Financial Statements" -> Apple Inc. - Financial Statements
B3: ($ in Millions, Except Per Share Amounts in Dollars and Share Counts in Thousands)
B5: Assumptions & Valuation Overview
B7: Valuation Date: | E7: 40207 | G7: Last Historical Year: | I7: 2009 | K7: Days in Year: | M7: 360
B8: Company Name: | E8: Apple Inc. | G8: Debt Issue Date: | I8: 2010 | K8: Debt Amount: | M8: 1000
B9: Share Price: | E9: 192.06 | G9: Share Units: | I9: 1000 | K9: Tax Rate: | M9: 0.3
B11: Basic Shares Outstanding: | E11: 900678.47 | G11: Options Calculations (in Thousands Except Exercise Price):
B12: Basic Equity Value: | E12: =E11/Units*Share_Price -> 172984.31
B13: Diluted Shares Outstanding: | E13: =E11+J20 -> 920525.62 | I13: Exercise
B14: Diluted Equity Value: | E14: =E13/Units*Share_Price -> 176796.15 | G14: Name | H14: Number | I14: Price | J14: Dilution
B15: Less: Cash & Investments | E15: =H99+H100+H108 -> 35395 | G15: Tranche A | H15: 34375 | I15: 81.17 | J15: =IF(I15>Share_Price,0,H15-H15*I15/Share_Price) -> 19847.151
B16: Plus: Debt | E16: =H124 -> 0 | G16: Tranche B
B17: Plus: Minority Interest | E17: 0 | G17: Tranche C
B18: Plus: Preferred Stock | E18: 0 | G18: Tranche D
B19: Plus: Other Liabilities | E19: 0 | G19: Tranche E
B20: Enterprise Value: | E20: =Equity_Value-E15+E16+E17+E18+E19 -> 141401.15 | G20: Total | J20: =SUM(J15:J19) -> 19847.151
F22: Historical | I22: Projections
F23: =G23-1 -> 2007 | G23: =H23-1 -> 2008 | H23: =Hist_Year -> 2009 | I23: =H23+1 -> 2010 | J23: =I23+1 -> 2011 | K23: =J23+1 -> 2012 | L23: =K23+1 -> 2013 | M23: =L23+1 -> 2014
F24: ="FY "&Hist_Year-2 -> FY 2007 | G24: ="FY "&Hist_Year-1 -> FY 2008 | H24: ="FY "&Hist_Year -> FY 2009 | I24: ="FY "&Hist_Year+1&"E" -> FY 2010E | J24: ="FY "&Hist_Year+2&"E" -> FY 2011E | K24: ="FY "&Hist_Year+3&"E" -> FY 2012E | L24: ="FY "&Hist_Year+4&"E" -> FY 2013E | M24: ="FY "&Hist_Year+5&"E" -> FY 2014E
B26: EV / Revenue: | F26: =Enterprise_Value/F66 -> 5.7531594 | G26: =Enterprise_Value/G66 -> 3.7716026 | H26: =Enterprise_Value/H66 -> 3.29568 | I26: =Enterprise_Value/I66 -> 2.636544 | J26: =Enterprise_Value/J66 -> 2.2534564 | K26: =Enterprise_Value/K66 -> 2.0301409 | L26: =Enterprise_Value/L66 -> 1.8625146 | M26: =Enterprise_Value/M66 -> 1.7406679
B27: EV / EBIT: | F27: =Enterprise_Value/F90 -> 30.415391 | G27: =Enterprise_Value/G90 -> 15.990179 | H27: =Enterprise_Value/H90 -> 11.357522 | I27: =Enterprise_Value/I90 -> 9.1094316 | J27: =Enterprise_Value/J90 -> 7.7816399 | K27: =Enterprise_Value/K90 -> 7.0059466 | L27: =Enterprise_Value/L90 -> 6.4223593 | M27: =Enterprise_Value/M90 -> 6.0012089
B28: EV / EBITDA: | F28: =Enterprise_Value/F91 -> 28.41663 | G28: =Enterprise_Value/G91 -> 15.140931 | H28: =Enterprise_Value/H91 -> 10.725209 | I28: =Enterprise_Value/I91 -> 8.5801669 | J28: =Enterprise_Value/J91 -> 7.333476 | K28: =Enterprise_Value/K91 -> 6.6067352 | L28: =Enterprise_Value/L91 -> 6.0612249 | M28: =Enterprise_Value/M91 -> 5.6646962
B30: Equity Value / FCF: | F30: =Equity_Value/F92 -> 37.338152 | G30: =Equity_Value/G92 -> 20.787319 | H30: =Equity_Value/H92 -> 17.146363 | I30: =Equity_Value/I92 -> 13.53647 | J30: =Equity_Value/J92 -> 12.094069 | K30: =Equity_Value/K92 -> 10.941841 | L30: =Equity_Value/L92 -> 10.098435 | M30: =Equity_Value/M92 -> 9.1218144
B31: P / E: | F31: =Share_Price/F87 -> 48.869076 | G31: =Share_Price/G87 -> 28.315871 | H31: =Share_Price/H87 -> 21.153537 | I31: =Share_Price/I87 -> 16.574667 | J31: =Share_Price/J87 -> 14.13121 | K31: =Share_Price/K87 -> 12.208721 | L31: =Share_Price/L87 -> 11.084718 | M31: =Share_Price/M87 -> 9.8165282
B32: P / BV: | G32: =Share_Price/G93 -> 7.9461049 | H32: =Share_Price/H93 -> 5.5576627 | I32: =Share_Price/I93 -> 4.0718411 | J32: =Share_Price/J93 -> 3.1005085 | K32: =Share_Price/K93 -> 2.4318258 | L32: =Share_Price/L93 -> 1.9657387 | M32: =Share_Price/M93 -> 1.6171864
B34: Operating Assumptions
F36: =F22 -> Historical | I36: =I22 -> Projections
F37: =F24 -> FY 2007 | G37: =G24 -> FY 2008 | H37: =H24 -> FY 2009 | I37: =I24 -> FY 2010E | J37: =J24 -> FY 2011E | K37: =K24 -> FY 2012E | L37: =L24 -> FY 2013E | M37: =M24 -> FY 2014E
B39: Revenue Growth %: | F39: =F66/19315-1 -> 0.27248253 | G39: =G66/F66-1 -> 0.52538856 | H39: =H66/G66-1 -> 0.14440799 | I39: 0.25 | J39: 0.17 | K39: 0.11 | L39: 0.09 | M39: 0.07
B40: COGS % Revenue: | F40: =F67/F66 -> 0.66246236 | G40: =G67/G66 -> 0.64145173 | H40: =H67/H66 -> 0.59024201 | I40: =H40 -> 0.59024201 | J40: =I40 -> 0.59024201 | K40: =J40 -> 0.59024201 | L40: =K40 -> 0.59024201 | M40: =L40 -> 0.59024201
B41: R&D % Revenue: | F41: =F70/F66 -> 0.024249329 | G41: =G70/G66 -> 0.020235968 | H41: =H70/H66 -> 0.019352834 | I41: =H41 -> 0.019352834 | J41: =I41 -> 0.019352834 | K41: =J41 -> 0.019352834 | L41: =K41 -> 0.019352834 | M41: =L41 -> 0.019352834
B42: SG&A % Revenue: | F42: =F71/F66 -> 0.11083082 | G42: =G71/G66 -> 0.089212522 | H42: =H71/H66 -> 0.083121625 | I42: =H42 -> 0.083121625 | J42: =I42 -> 0.083121625 | K42: =J42 -> 0.083121625 | L42: =K42 -> 0.083121625 | M42: =L42 -> 0.083121625
B44: Stock-Based Compensation % Revenue: | F44: =F76/F66 -> 0.0098462039 | G44: =G76/G66 -> 0.013763303 | H44: =H76/H66 -> 0.016548188 | I44: =H44 -> 0.016548188 | J44: =I44 -> 0.016548188 | K44: =J44 -> 0.016548188 | L44: =K44 -> 0.016548188 | M44: =L44 -> 0.016548188
B45: Depreciation & Amortization % Revenue: | F45: =F74/F66 -> 0.013304581 | G45: =G74/G66 -> 0.013229842 | H45: =H74/H66 -> 0.017107563 | I45: =H45 -> 0.017107563 | J45: =I45 -> 0.017107563 | K45: =J45 -> 0.017107563 | L45: =K45 -> 0.017107563 | M45: =L45 -> 0.017107563
B46: Effective Cash Interest Rate: | F46: 0.0527 | G46: 0.0344 | H46: 0.0143 | I46: 0.01 | J46: 0.01 | K46: 0.02 | L46: 0.02 | M46: 0.03
B47: Debt Interest Rate: | F47: 0 | G47: 0 | H47: 0 | I47: 0.09 | J47: =I47 -> 0.09 | K47: =J47 -> 0.09 | L47: =K47 -> 0.09 | M47: =L47 -> 0.09
B48: Effective Tax Rate: | F48: =F83/F82 -> 0.30183779 | G48: =G83/G82 -> 0.3160836 | H48: =H83/H82 -> 0.31750373 | I48: =Tax_Rate -> 0.3 | J48: =Tax_Rate -> 0.3 | K48: =Tax_Rate -> 0.3 | L48: =Tax_Rate -> 0.3 | M48: =Tax_Rate -> 0.3
B50: Accounts Receivable % Revenue: | G50: =G101/G66 -> 0.064602171 | H50: =H101/H66 -> 0.078335858 | I50: =I51/Days_In_Year -> 0.078335858 | J50: =J51/Days_In_Year -> 0.078335858 | K50: =K51/Days_In_Year -> 0.078335858 | L50: =L51/Days_In_Year -> 0.078335858 | M50: =M51/Days_In_Year -> 0.078335858
B51: Accounts Receivable Days: | G51: =G50*Days_In_Year -> 23.256782 | H51: =H50*Days_In_Year -> 28.200909 | I51: =H51 -> 28.200909 | J51: =I51 -> 28.200909 | K51: =J51 -> 28.200909 | L51: =K51 -> 28.200909 | M51: =L51 -> 28.200909
B52: Inventory % COGS: | G52: =G102/G67 -> 0.021165415 | H52: =H102/H67 -> 0.017966909 | I52: =H52 -> 0.017966909 | J52: =I52 -> 0.017966909 | K52: =J52 -> 0.017966909 | L52: =K52 -> 0.017966909 | M52: =L52 -> 0.017966909
B53: Amortization of Intangibles: | I53: 40 | J53: 37 | K53: 28 | L53: 13 | M53: 10
B55: Accounts Payable % COGS: | G55: =G117/G67 -> 0.22953455 | H55: =H117/H67 -> 0.22117068 | I55: =I56/Days_In_Year -> 0.22117068 | J55: =J56/Days_In_Year -> 0.22117068 | K55: =K56/Days_In_Year -> 0.22117068 | L55: =L56/Days_In_Year -> 0.22117068 | M55: =M56/Days_In_Year -> 0.22117068
B56: Accounts Payable Days: | G56: =G55*Days_In_Year -> 82.63244 | H56: =H55*Days_In_Year -> 79.621444 | I56: =H56 -> 79.621444 | J56: =I56 -> 79.621444 | K56: =J56 -> 79.621444 | L56: =K56 -> 79.621444 | M56: =L56 -> 79.621444
B57: Accrued Expenses % Operating Expenses: | G57: =G118/G72 -> 1.029407 | H57: =H118/H72 -> 0.87611827 | I57: =H57 -> 0.87611827 | J57: =I57 -> 0.87611827 | K57: =J57 -> 0.87611827 | L57: =K57 -> 0.87611827 | M57: =L57 -> 0.87611827
B58: Short-Term Deferred Revenue % Revenue: | G58: =G119/G66 -> 0.043130351 | H58: =H119/H66 -> 0.047849901 | I58: =H58 -> 0.047849901 | J58: =I58 -> 0.047849901 | K58: =J58 -> 0.047849901 | L58: =K58 -> 0.047849901 | M58: =L58 -> 0.047849901
B59: Long-Term Deferred Revenue % Revenue: | G59: =G123/G66 -> 0.020484916 | H59: =H123/H66 -> 0.019881133 | I59: =H59 -> 0.019881133 | J59: =I59 -> 0.019881133 | K59: =J59 -> 0.019881133 | L59: =K59 -> 0.019881133 | M59: =L59 -> 0.019881133
B61: CapEx % Revenue: | F61: =-F163/F66 -> 0.029904793 | G61: =-G163/G66 -> 0.029100317 | H61: =-H163/H66 -> 0.026663559 | I61: =H61 -> 0.026663559 | J61: =I61 -> 0.026663559 | K61: =J61 -> 0.026663559 | L61: =K61 -> 0.026663559 | M61: =L61 -> 0.026663559
B63: Income Statement
F64: =F$24 -> FY 2007 | G64: =G$24 -> FY 2008 | H64: =H$24 -> FY 2009 | I64: =I$24 -> FY 2010E | J64: =J$24 -> FY 2011E | K64: =K$24 -> FY 2012E | L64: =L$24 -> FY 2013E | M64: =M$24 -> FY 2014E
B66: Revenue: | F66: 24578 | G66: 37491 | H66: 42905 | I66: =H66*(1+I39) -> 53631.25 | J66: =I66*(1+J39) -> 62748.562 | K66: =J66*(1+K39) -> 69650.904 | L66: =K66*(1+L39) -> 75919.486 | M66: =L66*(1+M39) -> 81233.85
B67: Cost of Goods Sold: | F67: =16426-35-F$74/3 -> 16282 | G67: =24294-80-G$74/3 -> 24048.667 | H67: =25683-114-H$74/3 -> 25324.333 | I67: =I40*I66 -> 31655.417 | J67: =J40*J66 -> 37036.838 | K67: =K40*K66 -> 41110.89 | L67: =L40*L66 -> 44810.87 | M67: =M40*M66 -> 47947.631
B68: Gross Profit: | F68: =F66-F67 -> 8296 | G68: =G66-G67 -> 13442.333 | H68: =H66-H67 -> 17580.667 | I68: =I66-I67 -> 21975.833 | J68: =J66-J67 -> 25711.725 | K68: =K66-K67 -> 28540.015 | L68: =L66-L67 -> 31108.616 | M68: =M66-M67 -> 33286.219
B69: Operating Expenses:
B70: Research & Development: | F70: =782-77-F$74/3 -> 596 | G70: =1109-185-G$74/3 -> 758.66667 | H70: =1333-258-H$74/3 -> 830.33333 | I70: =I41*I66 -> 1037.9167 | J70: =J41*J66 -> 1214.3625 | K70: =K41*K66 -> 1347.9424 | L70: =L41*L66 -> 1469.2572 | M70: =M41*M66 -> 1572.1052
B71: Selling, General & Administrative: | F71: =2963-130-F$74/3 -> 2724 | G71: =3761-251-G$74/3 -> 3344.6667 | H71: =4149-338-H$74/3 -> 3566.3333 | I71: =I42*I66 -> 4457.9167 | J71: =J42*J66 -> 5215.7625 | K71: =K42*K66 -> 5789.4964 | L71: =L42*L66 -> 6310.551 | M71: =M42*M66 -> 6752.2896
B72: Total Operating Expenses: | F72: =SUM(F70:F71) -> 3320 | G72: =SUM(G70:G71) -> 4103.3333 | H72: =SUM(H70:H71) -> 4396.6667 | I72: =SUM(I70:I71) -> 5495.8333 | J72: =SUM(J70:J71) -> 6430.125 | K72: =SUM(K70:K71) -> 7137.4388 | L72: =SUM(L70:L71) -> 7779.8082 | M72: =SUM(M70:M71) -> 8324.3948
B74: Depreciation & Amortization of PP&E: | F74: 327 | G74: 496 | H74: 734 | I74: =I45*I66 -> 917.5 | J74: =J45*J66 -> 1073.475 | K74: =K45*K66 -> 1191.5573 | L74: =L45*L66 -> 1298.7974 | M74: =M45*M66 -> 1389.7132
B75: Amortization of Intangibles: | F75: 0 | G75: 0 | H75: 0 | I75: =I53 -> 40 | J75: =J53 -> 37 | K75: =K53 -> 28 | L75: =L53 -> 13 | M75: =M53 -> 10
B76: Stock-Based Compensation: | F76: 242 | G76: 516 | H76: 710 | I76: =I44*I66 -> 887.5 | J76: =J44*J66 -> 1038.375 | K76: =K44*K66 -> 1152.5963 | L76: =L44*L66 -> 1256.3299 | M76: =M44*M66 -> 1344.273
B78: Operating Income: | F78: =F68-F72-F74-F75-F76 -> 4407 | G78: =G68-G72-G74-G75-G76 -> 8327 | H78: =H68-H72-H74-H75-H76 -> 11740 | I78: =I68-I72-I74-I75-I76 -> 14635 | J78: =J68-J72-J74-J75-J76 -> 17132.75 | K78: =K68-K72-K74-K75-K76 -> 19030.423 | L78: =L68-L72-L74-L75-L76 -> 20760.681 | M78: =M68-M72-M74-M75-M76 -> 22217.838
B79: Interest Income: | F79: 647 | G79: 653 | H79: 407 | I79: =AVERAGE(H99+H100+H108,I99+I100+I108)*I46 -> 424.25364 | J79: =AVERAGE(I99+I100+I108,J99+J100+J108)*J46 -> 567.64936 | K79: =AVERAGE(J99+J100+J108,K99+K100+K108)*K46 -> 1443.061 | L79: =AVERAGE(K99+K100+K108,L99+L100+L108)*L46 -> 1779.7118 | M79: =AVERAGE(L99+L100+L108,M99+M100+M108)*M46 -> 3222.9023
B80: Interest Expense: | F80: 0 | G80: 0 | H80: 0 | I80: =-AVERAGE(H124,I124)*I47 -> -45 | J80: =-AVERAGE(I124,J124)*J47 -> -90 | K80: =-AVERAGE(J124,K124)*K47 -> -90 | L80: =-AVERAGE(K124,L124)*L47 -> -90 | M80: =-AVERAGE(L124,M124)*M47 -> -90
B81: Other Income & Expense: | F81: -48 | G81: -33 | H81: -81 | I81: 0 | J81: =I81 -> 0 | K81: =J81 -> 0 | L81: =K81 -> 0 | M81: =L81 -> 0
B82: Pre-Tax Income: | F82: =SUM(F78:F81) -> 5006 | G82: =SUM(G78:G81) -> 8947 | H82: =SUM(H78:H81) -> 12066 | I82: =SUM(I78:I81) -> 15014.254 | J82: =SUM(J78:J81) -> 17610.399 | K82: =SUM(K78:K81) -> 20383.483 | L82: =SUM(L78:L81) -> 22450.392 | M82: =SUM(M78:M81) -> 25350.74
B83: Income Tax Provision: | F83: 1511 | G83: 2828 | H83: 3831 | I83: =I82*I48 -> 4504.2761 | J83: =J82*J48 -> 5283.1198 | K83: =K82*K48 -> 6115.045 | L83: =L82*L48 -> 6735.1177 | M83: =M82*M48 -> 7605.2221
B85: Net Income: | F85: =F82-F83 -> 3495 | G85: =G82-G83 -> 6119 | H85: =H82-H83 -> 8235 | I85: =I82-I83 -> 10509.978 | J85: =J82-J83 -> 12327.28 | K85: =K82-K83 -> 14268.438 | L85: =L82-L83 -> 15715.275 | M85: =M82-M83 -> 17745.518
B87: Earnings Per Share (EPS): | F87: =F85*Units/F88 -> 3.9300927 | G87: =G85*Units/G88 -> 6.7827685 | H87: =H85*Units/H88 -> 9.0793325 | I87: =I85*Units/I88 -> 11.587563 | J87: =J85*Units/J88 -> 13.591192 | K87: =K85*Units/K88 -> 15.731378 | L87: =L85*Units/L88 -> 17.326558 | M87: =M85*Units/M88 -> 19.564962
B88: Diluted Shares Outstanding: | F88: 889292 | G88: 902139 | H88: 907005 | I88: =H88 -> 907005 | J88: =I88 -> 907005 | K88: =J88 -> 907005 | L88: =K88 -> 907005 | M88: =L88 -> 907005
B90: EBIT: | F90: =F78+F76 -> 4649 | G90: =G78+G76 -> 8843 | H90: =H78+H76 -> 12450 | I90: =I78+I76 -> 15522.5 | J90: =J78+J76 -> 18171.125 | K90: =K78+K76 -> 20183.019 | L90: =L78+L76 -> 22017.01 | M90: =M78+M76 -> 23562.111
B91: EBITDA: | F91: =F78+F76+F75+F74 -> 4976 | G91: =G78+G76+G75+G74 -> 9339 | H91: =H78+H76+H75+H74 -> 13184 | I91: =I78+I76+I75+I74 -> 16480 | J91: =J78+J76+J75+J74 -> 19281.6 | K91: =K78+K76+K75+K74 -> 21402.576 | L91: =L78+L76+L75+L74 -> 23328.808 | M91: =M78+M76+M75+M74 -> 24961.824
B92: Levered Free Cash Flow: | F92: =F157+F163 -> 4735 | G92: =G157+G163 -> 8505 | H92: =H157+H163 -> 10311 | I92: =I157+I163 -> 13060.728 | J92: =J157+J163 -> 14618.417 | K92: =K157+K163 -> 16157.806 | L92: =L157+L163 -> 17507.283 | M92: =M157+M163 -> 19381.687
B93: Book Value Per Share (BV): | G93: =(G113-G110-G111-G126)*Units/G88 -> 24.170333 | H93: =(H113-H110-H111-H126)*Units/H88 -> 34.557693 | I93: =(I113-I110-I111-I126)*Units/I88 -> 47.167852 | J93: =(J113-J110-J111-J126)*Units/J88 -> 61.944677 | K93: =(K113-K110-K111-K126)*Units/K88 -> 78.977698 | L93: =(L113-L110-L111-L126)*Units/L88 -> 97.70373 | M93: =(M113-M110-M111-M126)*Units/M88 -> 118.76182
B95: Balance Sheet
G96: =G$24 -> FY 2008 | H96: =H$24 -> FY 2009 | I96: =I$24 -> FY 2010E | J96: =J$24 -> FY 2011E | K96: =K$24 -> FY 2012E | L96: =L$24 -> FY 2013E | M96: =M$24 -> FY 2014E
B97: Assets:
B98: Current Assets:
B99: Cash & Cash-Equivalents: | G99: =G178 -> 11875 | H99: =H178 -> 6559 | I99: =I178 -> 20619.728 | J99: =J178 -> 35238.145 | K99: =K178 -> 51395.951 | L99: =L178 -> 68903.233 | M99: =M178 -> 88284.92
B100: Short-Term Securities: | G100: 10236 | H100: =G100-H160-H161 -> 26282 | I100: =H100-I160-I161 -> 26282 | J100: =I100-J160-J161 -> 26282 | K100: =J100-K160-K161 -> 26282 | L100: =K100-L160-L161 -> 26282 | M100: =L100-M160-M161 -> 26282
B101: Accounts Receivable: | G101: 2422 | H101: 3361 | I101: =I50*I66 -> 4201.25 | J101: =J50*J66 -> 4915.4625 | K101: =K50*K66 -> 5456.1634 | L101: =L50*L66 -> 5947.2181 | M101: =M50*M66 -> 6363.5233
B102: Inventory: | G102: 509 | H102: 455 | I102: =I52*I67 -> 568.75 | J102: =J52*J67 -> 665.4375 | K102: =K52*K67 -> 738.63563 | L102: =L52*L67 -> 805.11283 | M102: =M52*M67 -> 861.47073
B103: Deferred Tax Assets: | G103: 1044 | H103: =G103-H147 -> 4 | I103: =H103-I147 -> 4 | J103: =I103-J147 -> 4 | K103: =J103-K147 -> 4 | L103: =K103-L147 -> 4 | M103: =L103-M147 -> 4
B104: Other Current Assets: | G104: 3920 | H104: 3140 | I104: =H104 -> 3140 | J104: =I104 -> 3140 | K104: =J104 -> 3140 | L104: =K104 -> 3140 | M104: =L104 -> 3140
B105: Total Current Assets: | G105: =SUM(G99:G104) -> 30006 | H105: =SUM(H99:H104) -> 39801 | I105: =SUM(I99:I104) -> 54815.728 | J105: =SUM(J99:J104) -> 70245.045 | K105: =SUM(K99:K104) -> 87016.75 | L105: =SUM(L99:L104) -> 105081.56 | M105: =SUM(M99:M104) -> 124935.91
B107: Long-Term Assets:
B108: Long-Term Securities: | G108: 2379 | H108: =G108-H162-H165 -> 2554 | I108: =H108-I162-I165 -> 2554 | J108: =I108-J162-J165 -> 2554 | K108: =J108-K162-K165 -> 2554 | L108: =K108-L162-L165 -> 2554 | M108: =L108-M162-M165 -> 2554
B109: Plants, Property & Equipment: | G109: 2455 | H109: =G109-H163-H144-H148 -> 2839 | I109: =H109-I163-I144-I148 -> 3351.5 | J109: =I109-J163-J144-J148 -> 3951.125 | K109: =J109-K163-K144-K148 -> 4616.7087 | L109: =K109-L163-L144-L148 -> 5342.195 | M109: =L109-M163-M144-M148 -> 6118.4654
B110: Goodwill: | G110: 207 | H110: =G110 -> 207 | I110: =H110 -> 207 | J110: =I110 -> 207 | K110: =J110 -> 207 | L110: =K110 -> 207 | M110: =L110 -> 207
B111: Other Intangible Assets: | G111: 285 | H111: =G111-H145-H164 -> 354 | I111: =H111-I145-I164 -> 314 | J111: =I111-J145-J164 -> 277 | K111: =J111-K145-K164 -> 249 | L111: =K111-L145-L164 -> 236 | M111: =L111-M145-M164 -> 226
B112: Other Assets: | G112: 839 | H112: 2011 | I112: =H112 -> 2011 | J112: =I112 -> 2011 | K112: =J112 -> 2011 | L112: =K112 -> 2011 | M112: =L112 -> 2011
B113: Total Assets: | G113: =SUM(G108:G112)+G105 -> 36171 | H113: =SUM(H108:H112)+H105 -> 47766 | I113: =SUM(I108:I112)+I105 -> 63253.228 | J113: =SUM(J108:J112)+J105 -> 79245.17 | K113: =SUM(K108:K112)+K105 -> 96654.458 | L113: =SUM(L108:L112)+L105 -> 115431.76 | M113: =SUM(M108:M112)+M105 -> 136052.38
B115: Liabilities & Shareholders' Equity:
B116: Current Liabilities:
B117: Accounts Payable: | G117: 5520 | H117: 5601 | I117: =I55*I67 -> 7001.25 | J117: =J55*J67 -> 8191.4625 | K117: =K55*K67 -> 9092.5234 | L117: =L55*L67 -> 9910.8505 | M117: =M55*M67 -> 10604.61
B118: Accrued Expenses: | G118: 4224 | H118: 3852 | I118: =I57*I72 -> 4815 | J118: =J57*J72 -> 5633.55 | K118: =K57*K72 -> 6253.2405 | L118: =L57*L72 -> 6816.0321 | M118: =M57*M72 -> 7293.1544
B119: Deferred Revenue: | G119: 1617 | H119: 2053 | I119: =I58*I66 -> 2566.25 | J119: =J58*J66 -> 3002.5125 | K119: =K58*K66 -> 3332.7889 | L119: =L58*L66 -> 3632.7399 | M119: =M58*M66 -> 3887.0317
B120: Total Current Liabilities: | G120: =SUM(G117:G119) -> 11361 | H120: =SUM(H117:H119) -> 11506 | I120: =SUM(I117:I119) -> 14382.5 | J120: =SUM(J117:J119) -> 16827.525 | K120: =SUM(K117:K119) -> 18678.553 | L120: =SUM(L117:L119) -> 20359.622 | M120: =SUM(M117:M119) -> 21784.796
B122: Long-Term Liabilities:
B123: Deferred Revenue: | G123: 768 | H123: 853 | I123: =I59*I66 -> 1066.25 | J123: =J59*J66 -> 1247.5125 | K123: =K59*K66 -> 1384.7389 | L123: =L59*L66 -> 1509.3654 | M123: =M59*M66 -> 1615.0209
B124: Long-Term Debt: | G124: 0 | H124: 0 | I124: =H124+I173 -> 1000 | J124: =I124+J173 -> 1000 | K124: =J124+K173 -> 1000 | L124: =K124+L173 -> 1000 | M124: =L124+M173 -> 1000
B125: Other Long-Term Liabilities: | G125: 1745 | H125: 3502 | I125: =H125 -> 3502 | J125: =I125 -> 3502 | K125: =J125 -> 3502 | L125: =K125 -> 3502 | M125: =L125 -> 3502
...

Sheet ValSum
B2: ="Valuation Summary - "&TEXT(Company_Name,"") -> Valuation Summary - Apple Inc.
B3: ($ in Millions, Except Per Share Amounts in Dollars and Share Counts in Thousands)
B5: ="Valuation Statistics - "&TEXT(Company_Name,"") -> Valuation Statistics - Apple Inc. | C5: =TEXT(Company_Name,"")&" - Range of Valuation Multiples / Premiums" -> Apple Inc. - Range of Valuation Multiples / Premiums | I5: =TEXT(Company_Name,"")&" - Implied Per Share Value Range" -> Apple Inc. - Implied Per Share Value Range
D7: 25th | F7: 75th | H7: Applicable | J7: 25th | L7: 75th
C8: Minimum | D8: Pecentile | E8: Median | F8: Pecentile | G8: Maximum | H8: =TEXT(Company_Name,"") -> Apple Inc. | I8: Minimum | J8: Pecentile | K8: Median | L8: Pecentile | M8: Maximum
B9: Methodology Name | C9: Multiple | D9: Multiple | E9: Multiple | F9: Multiple | G9: Multiple | H9: Figure | I9: Multiple | J9: Multiple | K9: Multiple | L9: Multiple | M9: Multiple
B11: Public Company Comparables:
B12: =Hist_Year&" EV / Revenue:" -> 2009 EV / Revenue: | C12: ='Public Comps'!$L$35 -> 0.29321149 | D12: ='Public Comps'!$L$34 -> 0.45467864 | E12: ='Public Comps'!$L$33 -> 1.086233 | F12: ='Public Comps'!$L$32 -> 2.8302336 | G12: ='Public Comps'!$L$31 -> 3.0646433 | H12: ='AAPL-3-Statements'!H66 -> 42905 | I12: =(C12*$H12+$R$12)*Units/Diluted_Shares -> 52.117223 | J12: =(D12*$H12+$R$12)*Units/Diluted_Shares -> 59.643084 | K12: =(E12*$H12+$R$12)*Units/Diluted_Shares -> 89.079351 | L12: =(F12*$H12+$R$12)*Units/Diluted_Shares -> 170.3659 | M12: =(G12*$H12+$R$12)*Units/Diluted_Shares -> 181.29156 | O12: Balance Sheet Adjustment: | R12: ='AAPL-3-Statements'!E15-'AAPL-3-Statements'!E16-'AAPL-3-Statements'!E17-'AAPL-3-Statements'!E18-'AAPL-3-Statements'!E19 -> 35395
B13: =Hist_Year+1&"E EV / Revenue:" -> 2010E EV / Revenue: | C13: ='Public Comps'!$M$35 -> 0.27229807 | D13: ='Public Comps'!$M$34 -> 0.48355989 | E13: ='Public Comps'!$M$33 -> 1.0020225 | F13: ='Public Comps'!$M$32 -> 2.323086 | G13: ='Public Comps'!$M$31 -> 2.5914302 | H13: ='AAPL-3-Statements'!I66 -> 53631.25 | I13: =(C13*$H13+$R$12)*Units/Diluted_Shares -> 54.315366 | J13: =(D13*$H13+$R$12)*Units/Diluted_Shares -> 66.623807 | K13: =(E13*$H13+$R$12)*Units/Diluted_Shares -> 96.830245 | L13: =(F13*$H13+$R$12)*Units/Diluted_Shares -> 173.79745 | M13: =(G13*$H13+$R$12)*Units/Diluted_Shares -> 189.4316
B14: =Hist_Year&" EV / EBITDA:" -> 2009 EV / EBITDA: | C14: ='Public Comps'!$N$35 -> 4.4015957 | D14: ='Public Comps'!$N$34 -> 7.3014148 | E14: ='Public Comps'!$N$33 -> 7.5719685 | F14: ='Public Comps'!$N$32 -> 10.586646 | G14: ='Public Comps'!$N$31 -> 11.517707 | H14: ='AAPL-3-Statements'!H91 -> 13184 | I14: =(C14*$H14+$R$12)*Units/Diluted_Shares -> 101.49162 | J14: =(D14*$H14+$R$12)*Units/Diluted_Shares -> 143.02356 | K14: =(E14*$H14+$R$12)*Units/Diluted_Shares -> 146.8985 | L14: =(F14*$H14+$R$12)*Units/Diluted_Shares -> 190.07546 | M14: =(G14*$H14+$R$12)*Units/Diluted_Shares -> 203.41036
B15: =Hist_Year+1&"E EV / EBITDA:" -> 2010E EV / EBITDA: | C15: ='Public Comps'!$O$35 -> 3.6521838 | D15: ='Public Comps'!$O$34 -> 5.0613455 | E15: ='Public Comps'!$O$33 -> 5.5347156 | F15: ='Public Comps'!$O$32 -> 6.842085 | G15: ='Public Comps'!$O$31 -> 8.3506373 | H15: ='AAPL-3-Statements'!I91 -> 16480 | I15: =(C15*$H15+$R$12)*Units/Diluted_Shares -> 103.83523 | J15: =(D15*$H15+$R$12)*Units/Diluted_Shares -> 129.06319 | K15: =(E15*$H15+$R$12)*Units/Diluted_Shares -> 137.53785 | L15: =(F15*$H15+$R$12)*Units/Diluted_Shares -> 160.94344 | M15: =(G15*$H15+$R$12)*Units/Diluted_Shares -> 187.95077
B16: =Hist_Year&" P / E:" -> 2009 P / E: | C16: ='Public Comps'!$P$35 -> 14.990446 | D16: ='Public Comps'!$P$34 -> 16.054965 | E16: ='Public Comps'!$P$33 -> 19.736491 | F16: ='Public Comps'!$P$32 -> 29.089089 | G16: ='Public Comps'!$P$31 -> 47.166825 | H16: ='AAPL-3-Statements'!H87 -> 9.0793325 | I16: =C16*$H16 -> 136.10324 | J16: =D16*$H16 -> 145.76837 | K16: =E16*$H16 -> 179.19416 | L16: =F16*$H16 -> 264.10951 | M16: =G16*$H16 -> 428.24329
B17: =Hist_Year+1&"E P / E:" -> 2010E P / E: | C17: ='Public Comps'!$Q$35 -> 10.932203 | D17: ='Public Comps'!$Q$34 -> 12.162791 | E17: ='Public Comps'!$Q$33 -> 16.282609 | F17: ='Public Comps'!$Q$32 -> 16.616702 | G17: ='Public Comps'!$Q$31 -> 44.573394 | H17: ='AAPL-3-Statements'!I87 -> 11.587563 | I17: =C17*$H17 -> 126.6776 | J17: =D17*$H17 -> 140.9371 | K17: =E17*$H17 -> 188.67575 | L17: =F17*$H17 -> 192.54708 | M17: =G17*$H17 -> 516.49702
B19: Precedent Transactions:
B20: Trailing EV / Revenue: | C20: ='M&A-Comps'!$K$20 -> 0.40673666 | D20: ='M&A-Comps'!$K$19 -> 1.9443931 | E20: ='M&A-Comps'!$K$18 -> 2.732626 | F20: ='M&A-Comps'!$K$17 -> 6.0324032 | G20: ='M&A-Comps'!$K$16 -> 8.278749 | H20: ='AAPL-3-Statements'!H66 -> 42905 | I20: =(C20*$H20+$R$12)*Units/Diluted_Shares -> 57.408545 | J20: =(D20*$H20+$R$12)*Units/Diluted_Shares -> 129.07754 | K20: =(E20*$H20+$R$12)*Units/Diluted_Shares -> 165.81648 | L20: =(F20*$H20+$R$12)*Units/Diluted_Shares -> 319.61659 | M20: =(G20*$H20+$R$12)*Units/Diluted_Shares -> 424.31706
B21: Forward EV / Revenue: | C21: ='M&A-Comps'!$L$20 -> 0.43266177 | D21: ='M&A-Comps'!$L$19 -> 2.1430785 | E21: ='M&A-Comps'!$L$18 -> 2.7392064 | F21: ='M&A-Comps'!$L$17 -> 4.9811727 | G21: ='M&A-Comps'!$L$16 -> 7.4560742 | H21: ='AAPL-3-Statements'!I66 -> 53631.25 | I21: =(C21*$H21+$R$12)*Units/Diluted_Shares -> 63.658403 | J21: =(D21*$H21+$R$12)*Units/Diluted_Shares -> 163.30993 | K21: =(E21*$H21+$R$12)*Units/Diluted_Shares -> 198.04127 | L21: =(F21*$H21+$R$12)*Units/Diluted_Shares -> 328.6617 | M21: =(G21*$H21+$R$12)*Units/Diluted_Shares -> 472.8533
B22: Trailing EV / EBITDA: | C22: ='M&A-Comps'!$M$20 -> 8.654416 | D22: ='M&A-Comps'!$M$19 -> 11.48861 | E22: ='M&A-Comps'!$M$18 -> 14.372059 | F22: ='M&A-Comps'!$M$17 -> 17.251684 | G22: ='M&A-Comps'!$M$16 -> 39.654905 | H22: ='AAPL-3-Statements'!H91 -> 13184 | I22: =(C22*$H22+$R$12)*Units/Diluted_Shares -> 162.40159 | J22: =(D22*$H22+$R$12)*Units/Diluted_Shares -> 202.99363 | K22: =(E22*$H22+$R$12)*Units/Diluted_Shares -> 244.29111 | L22: =(F22*$H22+$R$12)*Units/Diluted_Shares -> 285.53383 | M22: =(G22*$H22+$R$12)*Units/Diluted_Shares -> 606.3984
B23: Forward EV / EBITDA: | C23: ='M&A-Comps'!$N$20 -> 9.6487136 | D23: ='M&A-Comps'!$N$19 -> 13.363937 | E23: ='M&A-Comps'!$N$18 -> 19.064474 | F23: ='M&A-Comps'!$N$17 -> 23.868387 | G23: ='M&A-Comps'!$N$16 -> 32.797394 | H23: ='AAPL-3-Statements'!I91 -> 16480 | I23: =(C23*$H23+$R$12)*Units/Diluted_Shares -> 211.18999 | J23: =(D23*$H23+$R$12)*Units/Diluted_Shares -> 277.70296 | K23: =(E23*$H23+$R$12)*Units/Diluted_Shares -> 379.75862 | L23: =(F23*$H23+$R$12)*Units/Diluted_Shares -> 465.76218 | M23: =(G23*$H23+$R$12)*Units/Diluted_Shares -> 625.61654
B25: Discounted Cash Flow Analysis:
B26: 11-15% Discount Rate, 5-9x Terminal Multiple: | I26: =DCF!I43 -> 163.88468 | J26: =DCF!H44 -> 182.19365 | K26: =DCF!G45 -> 201.97959 | L26: =DCF!F46 -> 223.35893 | M26: =DCF!E47 -> 246.45785

Sheet Valuation Graph
G25: Min. | H25: 25th | I25: Median | J25: 75th | K25: Max | L25: Min Point | M25: 25 Point | N25: Med Point | O25: 75 Point | P25: Max Point
B26: =ValSum!B26 -> 11-15% Discount Rate, 5-9x Terminal Multiple: | G26: =ValSum!I26 -> 163.88468 | H26: =ValSum!J26 -> 182.19365 | I26: =ValSum!K26 -> 201.97959 | J26: =ValSum!L26 -> 223.35893 | K26: =ValSum!M26 -> 246.45785 | L26: =G26 -> 163.88468 | M26: =H26-G26 -> 18.30897 | N26: =I26-H26 -> 19.785945 | O26: =J26-I26 -> 21.379336 | P26: =K26-J26 -> 23.098925
B28: =ValSum!B23 -> Forward EV / EBITDA: | G28: =ValSum!I23 -> 211.18999 | H28: =ValSum!J23 -> 277.70296 | I28: =ValSum!K23 -> 379.75862 | J28: =ValSum!L23 -> 465.76218 | K28: =ValSum!M23 -> 625.61654 | L28: =G28 -> 211.18999 | M28: =H28-G28 -> 66.512965 | N28: =I28-H28 -> 102.05566 | O28: =J28-I28 -> 86.003558 | P28: =K28-J28 -> 159.85437
B29: =ValSum!B22 -> Trailing EV / EBITDA: | G29: =ValSum!I22 -> 162.40159 | H29: =ValSum!J22 -> 202.99363 | I29: =ValSum!K22 -> 244.29111 | J29: =ValSum!L22 -> 285.53383 | K29: =ValSum!M22 -> 606.3984 | L29: =G29 -> 162.40159 | M29: =H29-G29 -> 40.592048 | N29: =I29-H29 -> 41.297473 | O29: =J29-I29 -> 41.242722 | P29: =K29-J29 -> 320.86457
B30: =ValSum!B21 -> Forward EV / Revenue: | G30: =ValSum!I21 -> 63.658403 | H30: =ValSum!J21 -> 163.30993 | I30: =ValSum!K21 -> 198.04127 | J30: =ValSum!L21 -> 328.6617 | K30: =ValSum!M21 -> 472.8533 | L30: =G30 -> 63.658403 | M30: =H30-G30 -> 99.651529 | N30: =I30-H30 -> 34.731338 | O30: =J30-I30 -> 130.62043 | P30: =K30-J30 -> 144.1916
B31: =ValSum!B20 -> Trailing EV / Revenue: | G31: =ValSum!I20 -> 57.408545 | H31: =ValSum!J20 -> 129.07754 | I31: =ValSum!K20 -> 165.81648 | J31: =ValSum!L20 -> 319.61659 | K31: =ValSum!M20 -> 424.31706 | L31: =G31 -> 57.408545 | M31: =H31-G31 -> 71.668999 | N31: =I31-H31 -> 36.738934 | O31: =J31-I31 -> 153.80011 | P31: =K31-J31 -> 104.70047
B33: =ValSum!B17 -> 2010E P / E: | G33: =ValSum!I17 -> 126.6776 | H33: =ValSum!J17 -> 140.9371 | I33: =ValSum!K17 -> 188.67575 | J33: =ValSum!L17 -> 192.54708 | K33: =ValSum!M17 -> 516.49702 | L33: =G33 -> 126.6776 | M33: =H33-G33 -> 14.259508 | N33: =I33-H33 -> 47.73865 | O33: =J33-I33 -> 3.8713313 | P33: =K33-J33 -> 323.94993
B34: =ValSum!B16 -> 2009 P / E: | G34: =ValSum!I16 -> 136.10324 | H34: =ValSum!J16 -> 145.76837 | I34: =ValSum!K16 -> 179.19416 | J34: =ValSum!L16 -> 264.10951 | K34: =ValSum!M16 -> 428.24329 | L34: =G34 -> 136.10324 | M34: =H34-G34 -> 9.6651265 | N34: =I34-H34 -> 33.425794 | O34: =J34-I34 -> 84.915345 | P34: =K34-J34 -> 164.13378
B35: =ValSum!B15 -> 2010E EV / EBITDA: | G35: =ValSum!I15 -> 103.83523 | H35: =ValSum!J15 -> 129.06319 | I35: =ValSum!K15 -> 137.53785 | J35: =ValSum!L15 -> 160.94344 | K35: =ValSum!M15 -> 187.95077 | L35: =G35 -> 103.83523 | M35: =H35-G35 -> 25.22796 | N35: =I35-H35 -> 8.474658 | O35: =J35-I35 -> 23.405593 | P35: =K35-J35 -> 27.007332
B36: =ValSum!B14 -> 2009 EV / EBITDA: | G36: =ValSum!I14 -> 101.49162 | H36: =ValSum!J14 -> 143.02356 | I36: =ValSum!K14 -> 146.8985 | J36: =ValSum!L14 -> 190.07546 | K36: =ValSum!M14 -> 203.41036 | L36: =G36 -> 101.49162 | M36: =H36-G36 -> 41.531939 | N36: =I36-H36 -> 3.8749383 | O36: =J36-I36 -> 43.176965 | P36: =K36-J36 -> 13.334901
B37: =ValSum!B13 -> 2010E EV / Revenue: | G37: =ValSum!I13 -> 54.315366 | H37: =ValSum!J13 -> 66.623807 | I37: =ValSum!K13 -> 96.830245 | J37: =ValSum!L13 -> 173.79745 | K37: =ValSum!M13 -> 189.4316 | L37: =G37 -> 54.315366 | M37: =H37-G37 -> 12.308441 | N37: =I37-H37 -> 30.206438 | O37: =J37-I37 -> 76.967206 | P37: =K37-J37 -> 15.634146
B38: =ValSum!B12 -> 2009 EV / Revenue: | G38: =ValSum!I12 -> 52.117223 | H38: =ValSum!J12 -> 59.643084 | I38: =ValSum!K12 -> 89.079351 | J38: =ValSum!L12 -> 170.3659 | K38: =ValSum!M12 -> 181.29156 | L38: =G38 -> 52.117223 | M38: =H38-G38 -> 7.5258613 | N38: =I38-H38 -> 29.436267 | O38: =J38-I38 -> 81.286546 | P38: =K38-J38 -> 10.925659

Sheet Public Comps
B2: ="Comparable Companies - US-Based Hardware & Networking Companies with Over $20 Billion Revenue" -> Comparable Companies - US-Based Hardware & Networking Companies with Over $20 Billion Revenue
B3: ='AAPL-3-Statements'!B3 -> ($ in Millions, Except Per Share Amounts in Dollars and Share Counts in Thousands)
B5: Operating Statistics | E5: Capitalization | R5: Projected
C6: Share | D6: Diluted | E6: Equity | H6: Preferred | I6: Minority | J6: Other | K6: Enterprise | L6: Revenue | N6: EBITDA | P6: EPS | R6: Revenue | S6: EBITDA Margin
B7: Company Name | C7: Price | D7: Shares | E7: Value | F7: Cash | G7: Debt | H7: Stock | I7: Interest | J7: Liabilities | K7: Value | L7: =Hist_Year -> 2009 | M7: =Hist_Year+1&"E" -> 2010E | N7: =Hist_Year -> 2009 | O7: =Hist_Year+1&"E" -> 2010E | P7: =Hist_Year -> 2009 | Q7: =Hist_Year+1&"E" -> 2010E | R7: Growth | S7: =Hist_Year -> 2009 | T7: =Hist_Year+1&"E" -> 2010E
B8: Hewlett-Packard Company | C8: 47.07 | D8: 2438478 | E8: =C8/Units*D8 -> 114779.16 | F8: 13334 | G8: 15830 | H8: 0 | I8: 0 | J8: 7155 | K8: =E8-F8+G8+H8+I8+J8 -> 124430.16 | L8: 114552 | M8: 124179 | N8: 16433 | O8: 18186 | P8: 3.14 | Q8: 3.87 | R8: =M8/L8-1 -> 0.084040436 | S8: =N8/L8 -> 0.1434545 | T8: =O8/M8 -> 0.14644988
B9: Dell Inc. | C9: 12.9 | D9: 1956656.4 | E9: =C9/Units*D9 -> 25240.867 | F9: 13954 | G9: 3793 | H9: 0 | I9: 0 | J9: 0 | K9: =E9-F9+G9+H9+I9+J9 -> 15079.867 | L9: 51430 | M9: 55380 | N9: 3426 | O9: 4129 | P9: 0.78611536 | Q9: 1.18 | R9: =M9/L9-1 -> 0.076803422 | S9: =N9/L9 -> 0.066614816 | T9: =O9/M9 -> 0.074557602
B10: Cisco Systems, Inc. | C10: 22.47 | D10: 5862885.6 | E10: =C10/Units*D10 -> 131739.04 | F10: 35365 | G10: 10273 | H10: 0 | I10: 24 | J10: 0 | K10: =E10-F10+G10+H10+I10+J10 -> 106671.04 | L10: 34807 | M10: 41163 | N10: 10076 | O10: 12774 | P10: 0.97428036 | Q10: 1.38 | R10: =M10/L10-1 -> 0.18260695 | S10: =N10/L10 -> 0.289482 | T10: =O10/M10 -> 0.31032724
B11: Intel Corporation | C11: 19.4 | D11: 5527029.8 | E11: =C11/Units*D11 -> 107224.38 | F11: 17307 | G11: 2224 | H11: 0 | I11: 0 | J11: 645 | K11: =E11-F11+G11+H11+I11+J11 -> 92786.379 | L11: 32784 | M11: 39941 | N11: 12708 | O11: 18332.354 | P11: 0.41130604 | Q11: 1.1675 | R11: =M11/L11-1 -> 0.21830771 | S11: =N11/L11 -> 0.38762811 | T11: =O11/M11 -> 0.45898587
B12: Motorola, Inc. | C12: 6.15 | D12: 2315349.1 | E12: =C12/Units*D12 -> 14239.397 | F12: 7606 | G12: 3925 | H12: 0 | I12: 107 | J12: 0 | K12: =E12-F12+G12+H12+I12+J12 -> 10665.397 | L12: 23457 | M12: 22056 | N12: 926 | O12: 1927 | P12: -1.6985333 | Q12: 0.13797468 | R12: =M12/L12-1 -> -0.059726308 | S12: =N12/L12 -> 0.039476489 | T12: =O12/M12 -> 0.087368517
B14: Maximum | C14: =MAX(C8:C12) -> 47.07 | E14: =MAX(E8:E12) -> 131739.04 | F14: =MAX(F8:F12) -> 35365 | G14: =MAX(G8:G12) -> 15830 | H14: =MAX(H8:H12) -> 0 | I14: =MAX(I8:I12) -> 107 | J14: =MAX(J8:J12) -> 7155 | K14: =MAX(K8:K12) -> 124430.16 | L14: =MAX(L8:L12) -> 114552 | ... T14: =MAX(T8:T12) -> 0.45898587
B15: 75th Percentile | C15: =QUARTILE(C8:C12,3) -> 22.47 | E15: =QUARTILE(E8:E12,3) -> 114779.16 | F15: =QUARTILE(F8:F12,3) -> 17307 | G15: =QUARTILE(G8:G12,3) -> 10273 | H15: =QUARTILE(H8:H12,3) -> 0 | I15: =QUARTILE(I8:I12,3) -> 24 | J15: =QUARTILE(J8:J12,3) -> 645 | K15: =QUARTILE(K8:K12,3) -> 106671.04 | L15: =QUARTILE(L8:L12,3) -> 51430 | ... T15: =QUARTILE(T8:T12,3) -> 0.31032724
B16: Median | C16: =MEDIAN(C8:C12) -> 19.4 | E16: =MEDIAN(E8:E12) -> 107224.38 | F16: =MEDIAN(F8:F12) -> 13954 | G16: =MEDIAN(G8:G12) -> 3925 | H16: =MEDIAN(H8:H12) -> 0 | I16: =MEDIAN(I8:I12) -> 0 | J16: =MEDIAN(J8:J12) -> 0 | K16: =MEDIAN(K8:K12) -> 92786.379 | L16: =MEDIAN(L8:L12) -> 34807 | ... T16: =MEDIAN(T8:T12) -> 0.14644988
B17: 25th Percentile | C17: =QUARTILE(C8:C12,1) -> 12.9 | E17: =QUARTILE(E8:E12,1) -> 25240.867 | F17: =QUARTILE(F8:F12,1) -> 13334 | G17: =QUARTILE(G8:G12,1) -> 3793 | H17: =QUARTILE(H8:H12,1) -> 0 | I17: =QUARTILE(I8:I12,1) -> 0 | J17: =QUARTILE(J8:J12,1) -> 0 | K17: =QUARTILE(K8:K12,1) -> 15079.867 | L17: =QUARTILE(L8:L12,1) -> 32784 | ... T17: =QUARTILE(T8:T12,1) -> 0.087368517
B18: Minimum | C18: =MIN(C8:C12) -> 6.15 | E18: =MIN(E8:E12) -> 14239.397 | F18: =MIN(F8:F12) -> 7606 | G18: =MIN(G8:G12) -> 2224 | H18: =MIN(H8:H12) -> 0 | I18: =MIN(I8:I12) -> 0 | J18: =MIN(J8:J12) -> 0 | K18: =MIN(K8:K12) -> 10665.397 | L18: =MIN(L8:L12) -> 23457 | ... T18: =MIN(T8:T12) -> 0.074557602
B20: =Company_Name -> Apple Inc. | C20: =Share_Price -> 192.06 | D20: =Diluted_Shares -> 920525.62 | E20: =C20/Units*D20 -> 176796.15 | F20: ='AAPL-3-Statements'!E15 -> 35395 | G20: ='AAPL-3-Statements'!E16 -> 0 | H20: ='AAPL-3-Statements'!E18 -> 0 | I20: ='AAPL-3-Statements'!E17 -> 0 | J20: ='AAPL-3-Statements'!E19 -> 0 | K20: =E20-F20+G20+H20+I20+J20 -> 141401.15 | L20: ='AAPL-3-Statements'!H66 -> 42905 | M20: ='AAPL-3-Statements'!I66 -> 53631.25 | N20: ='AAPL-3-Statements'!H91 -> 13184 | O20: ='AAPL-3-Statements'!I91 -> 16480 | P20: ='AAPL-3-Statements'!H87 -> 9.0793325 | Q20: ='AAPL-3-Statements'!I87 -> 11.587563 | R20: =M20/L20-1 -> 0.25 | S20: =N20/L20 -> 0.30728353 | T20: =O20/M20 -> 0.30728353
B22: Valuation Statistics | E22: Capitalization | L22: Enterprise Value / | N22: Enterprise Value /
C23: Share | E23: Equity | K23: Enterprise | L23: Revenue | N23: EBITDA | P23: P / E Multiple
B24: Company Name | C24: Price | E24: Value | K24: Value | L24: =L7 -> 2009 | M24: =M7 -> 2010E | N24: =N7 -> 2009 | O24: =O7 -> 2010E | P24: =P7 -> 2009 | Q24: =Q7 -> 2010E
B25: =B8 -> Hewlett-Packard Company | C25: =C8 -> 47.07 | E25: =E8 -> 114779.16 | K25: =K8 -> 124430.16 | L25: =IF($K25/L8>0,$K25/L8,"NM") -> 1.086233 | M25: =IF($K25/M8>0,$K25/M8,"NM") -> 1.0020225 | N25: =IF($K25/N8>0,$K25/N8,"NM") -> 7.5719685 | O25: =IF($K25/O8>0,$K25/O8,"NM") -> 6.842085 | P25: =IF($C25/P8>0,$C25/P8,"NM") -> 14.990446 | Q25: =IF($C25/Q8>0,$C25/Q8,"NM") -> 12.162791
B26: =B9 -> Dell Inc. | C26: =C9 -> 12.9 | E26: =E9 -> 25240.867 | K26: =K9 -> 15079.867 | L26: =IF($K26/L9>0,$K26/L9,"NM") -> 0.29321149 | M26: =IF($K26/M9>0,$K26/M9,"NM") -> 0.27229807 | N26: =IF($K26/N9>0,$K26/N9,"NM") -> 4.4015957 | O26: =IF($K26/O9>0,$K26/O9,"NM") -> 3.6521838 | P26: =IF($C26/P9>0,$C26/P9,"NM") -> 16.409805 | Q26: =IF($C26/Q9>0,$C26/Q9,"NM") -> 10.932203
B27: =B10 -> Cisco Systems, Inc. | C27: =C10 -> 22.47 | E27: =E10 -> 131739.04 | K27: =K10 -> 106671.04 | L27: =IF($K27/L10>0,$K27/L10,"NM") -> 3.0646433 | M27: =IF($K27/M10>0,$K27/M10,"NM") -> 2.5914302 | N27: =IF($K27/N10>0,$K27/N10,"NM") -> 10.586646 | O27: =IF($K27/O10>0,$K27/O10,"NM") -> 8.3506373 | P27: =IF($C27/P10>0,$C27/P10,"NM") -> 23.063177 | Q27: =IF($C27/Q10>0,$C27/Q10,"NM") -> 16.282609
B28: =B11 -> Intel Corporation | C28: =C11 -> 19.4 | E28: =E11 -> 107224.38 | K28: =K11 -> 92786.379 | L28: =IF($K28/L11>0,$K28/L11,"NM") -> 2.8302336 | M28: =IF($K28/M11>0,$K28/M11,"NM") -> 2.323086 | N28: =IF($K28/N11>0,$K28/N11,"NM") -> 7.3014148 | O28: =IF($K28/O11>0,$K28/O11,"NM") -> 5.0613455 | P28: =IF($C28/P11>0,$C28/P11,"NM") -> 47.166825 | Q28: =IF($C28/Q11>0,$C28/Q11,"NM") -> 16.616702
B29: =B12 -> Motorola, Inc. | C29: =C12 -> 6.15 | E29: =E12 -> 14239.397 | K29: =K12 -> 10665.397 | L29: =IF($K29/L12>0,$K29/L12,"NM") -> 0.45467864 | M29: =IF($K29/M12>0,$K29/M12,"NM") -> 0.48355989 | N29: =IF($K29/N12>0,$K29/N12,"NM") -> 11.517707 | O29: =IF($K29/O12>0,$K29/O12,"NM") -> 5.5347156 | P29: =IF($C29/P12>0,$C29/P12,"NM") -> NM | Q29: =IF($C29/Q12>0,$C29/Q12,"NM") -> 44.573394
B31: Maximum | C31: =MAX(C25:C29) -> 47.07 | E31: =MAX(E25:E29) -> 131739.04 | F31: =MAX(F25:F29) -> 0 | G31: =MAX(G25:G29) -> 0 | H31: =MAX(H25:H29) -> 0 | I31: =MAX(I25:I29) -> 0 | J31: =MAX(J25:J29) -> 0 | K31: =MAX(K25:K29) -> 124430.16 | L31: =MAX(L25:L29) -> 3.0646433 | ... Q31: =MAX(Q25:Q29) -> 44.573394
B32: 75th Percentile | C32: =QUARTILE(C25:C29,3) -> 22.47 | E32: =QUARTILE(E25:E29,3) -> 114779.16 | F32: =QUARTILE(F25:F29,3) -> #VALUE! | G32: =QUARTILE(G25:G29,3) -> #VALUE! | H32: =QUARTILE(H25:H29,3) -> #VALUE! | I32: =QUARTILE(I25:I29,3) -> #VALUE! | J32: =QUARTILE(J25:J29,3) -> #VALUE! | K32: =QUARTILE(K25:K29,3) -> 106671.04 | L32: =QUARTILE(L25:L29,3) -> 2.8302336 | ... Q32: =QUARTILE(Q25:Q29,3) -> 16.616702
B33: Median | C33: =MEDIAN(C25:C29) -> 19.4 | E33: =MEDIAN(E25:E29) -> 107224.38 | F33: =MEDIAN(F25:F29) -> #VALUE! | G33: =MEDIAN(G25:G29) -> #VALUE! | H33: =MEDIAN(H25:H29) -> #VALUE! | I33: =MEDIAN(I25:I29) -> #VALUE! | J33: =MEDIAN(J25:J29) -> #VALUE! | K33: =MEDIAN(K25:K29) -> 92786.379 | L33: =MEDIAN(L25:L29) -> 1.086233 | ... Q33: =MEDIAN(Q25:Q29) -> 16.282609
B34: 25th Percentile | C34: =QUARTILE(C25:C29,1) -> 12.9 | E34: =QUARTILE(E25:E29,1) -> 25240.867 | F34: =QUARTILE(F25:F29,1) -> #VALUE! | G34: =QUARTILE(G25:G29,1) -> #VALUE! | H34: =QUARTILE(H25:H29,1) -> #VALUE! | I34: =QUARTILE(I25:I29,1) -> #VALUE! | J34: =QUARTILE(J25:J29,1) -> #VALUE! | K34: =QUARTILE(K25:K29,1) -> 15079.867 | L34: =QUARTILE(L25:L29,1) -> 0.45467864 | ... Q34: =QUARTILE(Q25:Q29,1) -> 12.162791
B35: Minimum | C35: =MIN(C25:C29) -> 6.15 | E35: =MIN(E25:E29) -> 14239.397 | F35: =MIN(F25:F29) -> 0 | G35: =MIN(G25:G29) -> 0 | H35: =MIN(H25:H29) -> 0 | I35: =MIN(I25:I29) -> 0 | J35: =MIN(J25:J29) -> 0 | K35: =MIN(K25:K29) -> 10665.397 | L35: =MIN(L25:L29) -> 0.29321149 | ... Q35: =MIN(Q25:Q29) -> 10.932203
B37: =B20 -> Apple Inc. | C37: =C20 -> 192.06 | E37: =E20 -> 176796.15 | K37: =K20 -> 141401.15 | L37: =IF($K37/L20>0,$K37/L20,"NM") -> 3.29568 | M37: =IF($K37/M20>0,$K37/M20,"NM") -> 2.636544 | N37: =IF($K37/N20>0,$K37/N20,"NM") -> 10.725209 | O37: =IF($K37/O20>0,$K37/O20,"NM") -> 8.5801669 | P37: =IF($C37/P20>0,$C37/P20,"NM") -> 21.153537 | Q37: =IF($C37/Q20>0,$C37/Q20,"NM") -> 16.574667

Sheet M&A-Comps
B2: Networking & Hardware M&A Transactions Over $1 Billion with US-Based Sellers Since 1/1/2008
B3: ='AAPL-3-Statements'!B3 -> ($ in Millions, Except Per Share Amounts in Dollars and Share Counts in Thousands)
B5: =TEXT(Company_Name,"")&" - Comparable M&A Transactions" -> Apple Inc. - Comparable M&A Transactions | G5: Operating Metrics | K5: Valuation Multiples
K6: EV / | L6: EV / | M6: EV / | N6: EV /
E7: Equity | F7: Enterprise | G7: Trailing | H7: Forward | I7: Trailing | J7: Forward | K7: Trailing | L7: Forward | M7: Trailing | N7: Forward
B8: Acquirer Name | C8: Target Name | D8: Date | E8: Value | F8: Value | G8: Revenue | H8: Revenue | I8: EBITDA | J8: EBITDA | K8: Revenue | L8: Revenue | M8: EBITDA | N8: EBITDA
B9: Hewlett-Packard Company | C9: 3Com | D9: 40128 | E9: 3180.0634 | F9: 2714.2404 | G9: 1264.83 | H9: 1222.855 | I9: 152.24 | J9: 110.2178 | K9: =IF(ISERROR($F9/G9),"NA",IF($F9/G9>0,$F9/G9,"NM")) -> 2.145933 | L9: =IF(ISERROR($F9/H9),"NA",IF($F9/H9>0,$F9/H9,"NM")) -> 2.219593 | M9: =IF(ISERROR($F9/I9),"NA",IF($F9/I9>0,$F9/I9,"NM")) -> 17.828694 | N9: =IF(ISERROR($F9/J9),"NA",IF($F9/J9>0,$F9/J9,"NM")) -> 24.626153
B10: Cisco Systems, Inc. | C10: Starent Networks | D10: 40099 | E10: 2776.6787 | F10: 2385.9437 | G10: 288.201 | H10: 320 | I10: 153.727 | J10: 110.48548 | K10: =IF(ISERROR($F10/G10),"NA",IF($F10/G10>0,$F10/G10,"NM")) -> 8.278749 | L10: =IF(ISERROR($F10/H10),"NA",IF($F10/H10>0,$F10/H10,"NM")) -> 7.4560742 | M10: =IF(ISERROR($F10/I10),"NA",IF($F10/I10>0,$F10/I10,"NM")) -> 15.520655 | N10: =IF(ISERROR($F10/J10),"NA",IF($F10/J10>0,$F10/J10,"NM")) -> 21.59509
B11: Emerson Electric Co. | C11: Avocent | D11: 40092 | E11: 1114.489 | F11: 1147.439 | G11: 611.246 | H11: 541.865 | I11: 105.17 | J11: 93.232417 | K11: =IF(ISERROR($F11/G11),"NA",IF($F11/G11>0,$F11/G11,"NM")) -> 1.8772132 | L11: =IF(ISERROR($F11/H11),"NA",IF($F11/H11>0,$F11/H11,"NM")) -> 2.1175736 | M11: =IF(ISERROR($F11/I11),"NA",IF($F11/I11>0,$F11/I11,"NM")) -> 10.910326 | N11: =IF(ISERROR($F11/J11),"NA",IF($F11/J11>0,$F11/J11,"NM")) -> 12.307297
B12: EMC Corporation | C12: Data Domain | D12: 40002 | E12: 2362.3224 | F12: 2084.5394 | G12: 300.506 | H12: 375.235 | I12: 52.567 | J12: 63.558079 | K12: =IF(ISERROR($F12/G12),"NA",IF($F12/G12>0,$F12/G12,"NM")) -> 6.9367646 | L12: =IF(ISERROR($F12/H12),"NA",IF($F12/H12>0,$F12/H12,"NM")) -> 5.5552904 | M12: =IF(ISERROR($F12/I12),"NA",IF($F12/I12>0,$F12/I12,"NM")) -> 39.654905 | N12: =IF(ISERROR($F12/J12),"NA",IF($F12/J12>0,$F12/J12,"NM")) -> 32.797394
B13: Oracle Corporation | C13: Sun Microsystems | D13: 39923 | E13: 7074.7012 | F13: 5391.7012 | G13: 13256 | H13: 12461.7 | I13: 623 | J13: 558.8 | K13: =IF(ISERROR($F13/G13),"NA",IF($F13/G13>0,$F13/G13,"NM")) -> 0.40673666 | L13: =IF(ISERROR($F13/H13),"NA",IF($F13/H13>0,$F13/H13,"NM")) -> 0.43266177 | M13: =IF(ISERROR($F13/I13),"NA",IF($F13/I13>0,$F13/I13,"NM")) -> 8.654416 | N13: =IF(ISERROR($F13/J13),"NA",IF($F13/J13>0,$F13/J13,"NM")) -> 9.6487136
B14: Brocade Communication Systems, Inc. | C14: Foundry Networks | D14: 39650 | E14: 2899.1908 | F14: 2062.7808 | G14: 621.447 | H14: 632.984 | I14: 155.994 | J14: 124.761 | K14: =IF(ISERROR($F14/G14),"NA",IF($F14/G14>0,$F14/G14,"NM")) -> 3.319319 | L14: =IF(ISERROR($F14/H14),"NA",IF($F14/H14>0,$F14/H14,"NM")) -> 3.2588198 | M14: =IF(ISERROR($F14/I14),"NA",IF($F14/I14>0,$F14/I14,"NM")) -> 13.223462 | N14: =IF(ISERROR($F14/J14),"NA",IF($F14/J14>0,$F14/J14,"NM")) -> 16.533859
C16: Maximum | E16: =MAX(E9:E14) -> 7074.7012 | F16: =MAX(F9:F14) -> 5391.7012 | G16: =MAX(G9:G14) -> 13256 | H16: =MAX(H9:H14) -> 12461.7 | I16: =MAX(I9:I14) -> 623 | J16: =MAX(J9:J14) -> 558.8 | K16: =MAX(K9:K14) -> 8.278749 | L16: =MAX(L9:L14) -> 7.4560742 | ... N16: =MAX(N9:N14) -> 32.797394
C17: 75th Percentile | E17: =QUARTILE(E9:E14,3) -> 3109.8452 | F17: =QUARTILE(F9:F14,3) -> 2632.1662 | G17: =QUARTILE(G9:G14,3) -> 1103.9842 | H17: =QUARTILE(H9:H14,3) -> 1075.3872 | I17: =QUARTILE(I9:I14,3) -> 155.42725 | J17: =QUARTILE(J9:J14,3) -> 121.19212 | K17: =QUARTILE(K9:K14,3) -> 6.0324032 | L17: =QUARTILE(L9:L14,3) -> 4.9811727 | ... N17: =QUARTILE(N9:N14,3) -> 23.868387
C18: Median | E18: =MEDIAN(E9:E14) -> 2837.9348 | F18: =MEDIAN(F9:F14) -> 2235.2416 | G18: =MEDIAN(G9:G14) -> 616.3465 | H18: =MEDIAN(H9:H14) -> 587.4245 | I18: =MEDIAN(I9:I14) -> 152.9835 | J18: =MEDIAN(J9:J14) -> 110.35164 | K18: =MEDIAN(K9:K14) -> 2.732626 | L18: =MEDIAN(L9:L14) -> 2.7392064 | ... N18: =MEDIAN(N9:N14) -> 19.064474
C19: 25th Percentile | E19: =QUARTILE(E9:E14,1) -> 2465.9115 | F19: =QUARTILE(F9:F14,1) -> 2068.2204 | G19: =QUARTILE(G9:G14,1) -> 378.191 | H19: =QUARTILE(H9:H14,1) -> 416.8925 | I19: =QUARTILE(I9:I14,1) -> 116.9375 | J19: =QUARTILE(J9:J14,1) -> 97.478763 | K19: =QUARTILE(K9:K14,1) -> 1.9443931 | L19: =QUARTILE(L9:L14,1) -> 2.1430785 | ... N19: =QUARTILE(N9:N14,1) -> 13.363937
C20: Minimum | E20: =MIN(E9:E14) -> 1114.489 | F20: =MIN(F9:F14) -> 1147.439 | G20: =MIN(G9:G14) -> 288.201 | H20: =MIN(H9:H14) -> 320 | I20: =MIN(I9:I14) -> 52.567 | J20: =MIN(J9:J14) -> 63.558079 | K20: =MIN(K9:K14) -> 0.40673666 | L20: =MIN(L9:L14) -> 0.43266177 | ... N20: =MIN(N9:N14) -> 9.6487136

Sheet DCF
B2: ="Discounted Cash Flow Analysis - "&TEXT(Company_Name,"") -> Discounted Cash Flow Analysis - Apple Inc.
B3: ='AAPL-3-Statements'!B3 -> ($ in Millions, Except Per Share Amounts in Dollars and Share Counts in Thousands)
B5: =TEXT(Company_Name,"")&" - Cash Flow Projections" -> Apple Inc. - Cash Flow Projections | L5: =TEXT(Company_Name,"")&" - DCF Assumptions & Output" -> Apple Inc. - DCF Assumptions & Output
F6: ='AAPL-3-Statements'!I24 -> FY 2010E | G6: ='AAPL-3-Statements'!J24 -> FY 2011E | H6: ='AAPL-3-Statements'!K24 -> FY 2012E | I6: ='AAPL-3-Statements'!L24 -> FY 2013E | J6: ='AAPL-3-Statements'!M24 -> FY 2014E
B8: Revenue: | F8: ='AAPL-3-Statements'!I66 -> 53631.25 | G8: ='AAPL-3-Statements'!J66 -> 62748.562 | H8: ='AAPL-3-Statements'!K66 -> 69650.904 | I8: ='AAPL-3-Statements'!L66 -> 75919.486 | J8: ='AAPL-3-Statements'!M66 -> 81233.85 | L8: Use Multiples Method? | O8: 1
B9: EBITDA: | F9: ='AAPL-3-Statements'!I91 -> 16480 | G9: ='AAPL-3-Statements'!J91 -> 19281.6 | H9: ='AAPL-3-Statements'!K91 -> 21402.576 | I9: ='AAPL-3-Statements'!L91 -> 23328.808 | J9: ='AAPL-3-Statements'!M91 -> 24961.824 | L9: Discount Rate: | O9: =WACC!G34 -> 0.1249633
B10: Operating Income: | F10: ='AAPL-3-Statements'!I78 -> 14635 | G10: ='AAPL-3-Statements'!J78 -> 17132.75 | H10: ='AAPL-3-Statements'!K78 -> 19030.423 | I10: ='AAPL-3-Statements'!L78 -> 20760.681 | J10: ='AAPL-3-Statements'!M78 -> 22217.838
L11: Terminal EBITDA Multiple: | O11: 7
B12: Less: Taxes | F12: =-F10*Tax_Rate -> -4390.5 | G12: =-G10*Tax_Rate -> -5139.825 | H12: =-H10*Tax_Rate -> -5709.1268 | I12: =-I10*Tax_Rate -> -6228.2042 | J12: =-J10*Tax_Rate -> -6665.3514 | L12: Terminal Growth Rate: | O12: 0.03
L13: Terminal Value: | O13: =IF(O8,O11*J9,J21*(1+O12)/(O9-O12)) -> 174732.77
B14: Plus: Depreciation | F14: ='AAPL-3-Statements'!I144 -> 917.5 | G14: ='AAPL-3-Statements'!J144 -> 1073.475 | H14: ='AAPL-3-Statements'!K144 -> 1191.5573 | I14: ='AAPL-3-Statements'!L144 -> 1298.7974 | J14: ='AAPL-3-Statements'!M144 -> 1389.7132
B15: Plus: Amortization | F15: ='AAPL-3-Statements'!I145 -> 40 | G15: ='AAPL-3-Statements'!J145 -> 37 | H15: ='AAPL-3-Statements'!K145 -> 28 | I15: ='AAPL-3-Statements'!L145 -> 13 | J15: ='AAPL-3-Statements'!M145 -> 10 | L15: PV of Terminal Value: | O15: =IF(O8,O13/((1+O9)^J24),O13/((1+O9)^J25)) -> 96980.093
B16: Plus: Stock-Based Compensation | F16: ='AAPL-3-Statements'!I146 -> 887.5 | G16: ='AAPL-3-Statements'!J146 -> 1038.375 | H16: ='AAPL-3-Statements'!K146 -> 1152.5963 | I16: ='AAPL-3-Statements'!L146 -> 1256.3299 | J16: ='AAPL-3-Statements'!M146 -> 1344.273 | L16: Sum of PV of Cash Flows: | O16: =SUM(F22:J22) -> 56296.251
L17: Enterprise Value: | O17: =SUM(O15:O16) -> 153276.34
B18: Less: Increase in Working Capital: | F18: =SUM('AAPL-3-Statements'!I150:I156) -> 2135.75 | G18: =SUM('AAPL-3-Statements'!J150:J156) -> 1815.3875 | H18: =SUM('AAPL-3-Statements'!K150:K156) -> 1374.3551 | I18: =SUM('AAPL-3-Statements'!L150:L156) -> 1248.1643 | J18: =SUM('AAPL-3-Statements'!M150:M156) -> 1058.166
B19: Less: Capital Expenditures | F19: ='AAPL-3-Statements'!I163 -> -1430 | G19: ='AAPL-3-Statements'!J163 -> -1673.1 | H19: ='AAPL-3-Statements'!K163 -> -1857.141 | I19: ='AAPL-3-Statements'!L163 -> -2024.2837 | J19: ='AAPL-3-Statements'!M163 -> -2165.9835 | L19: Terminal Value % EV: | O19: =O15/O17 -> 0.63271403
B21: Unlevered Free Cash Flow | F21: =F10+F12+F14+F15+F16+F18+F19 -> 12795.25 | G21: =G10+G12+G14+G15+G16+G18+G19 -> 14284.062 | H21: =H10+H12+H14+H15+H16+H18+H19 -> 15210.663 | I21: =I10+I12+I14+I15+I16+I18+I19 -> 16324.484 | J21: =J10+J12+J14+J15+J16+J18+J19 -> 17188.655 | L21: Enterprise Value: | O21: =O17 -> 153276.34
B22: Present Value of Free Cash Flow | F22: =F21/((1+$O$9)^F25) -> 12063.674 | G22: =G21/((1+$O$9)^G25) -> 11971.38 | H22: =H21/((1+$O$9)^H25) -> 11331.888 | I22: =I21/((1+$O$9)^I25) -> 10810.735 | J22: =J21/((1+$O$9)^J25) -> 10118.574 | L22: Balance Sheet Adjustment: | O22: ='AAPL-3-Statements'!E15-'AAPL-3-Statements'!E16-'AAPL-3-Statements'!E17-'AAPL-3-Statements'!E18-'AAPL-3-Statements'!E19 -> 35395
L23: Implied Equity Value: | O23: =SUM(O21:O22) -> 188671.34
B24: Normal Discount Period: | F24: 1 | G24: =F24+1 -> 2 | H24: =G24+1 -> 3 | I24: =H24+1 -> 4 | J24: =I24+1 -> 5
B25: Mid-Year Discount: | F25: 0.5 | G25: =F25+1 -> 1.5 | H25: =G25+1 -> 2.5 | I25: =H25+1 -> 3.5 | J25: =I25+1 -> 4.5 | L25: Implied Price Per Share: | O25: =O23*Units/Diluted_Shares -> 204.96045
B27: Free Cash Flow Growth Rate: | G27: =G21/F21-1 -> 0.11635666 | H27: =H21/G21-1 -> 0.064869562 | I27: =I21/H21-1 -> 0.073226323 | J27: =J21/I21-1 -> 0.052937112
B29: =TEXT(Company_Name,"")&" - Net Present Value Sensitivity - Terminal Growth Rates" -> Apple Inc. - Net Present Value Sensitivity - Terminal Growth Rates
D30: Discount Rate
C31: =O25 -> 204.96045 | D31: 0.1 | E31: =D31+1% -> 0.11 | F31: =E31+1% -> 0.12 | G31: =F31+1% -> 0.13 | H31: =G31+1% -> 0.14 | I31: =H31+1% -> 0.15 | J31: =I31+1% -> 0.16
B32: Terminal Growth Rate | C32: 0 | D32: =TABLE($C$31,$O$12,$C32,$O$9,D$31) -> 220.90082 | E32: =TABLE($C$31,$O$12,$C32,$O$9,E$31) -> 214.2727 | F32: =TABLE($C$31,$O$12,$C32,$O$9,F$31) -> 207.97206 | G32: =TABLE($C$31,$O$12,$C32,$O$9,G$31) -> 201.97959 | H32: =TABLE($C$31,$O$12,$C32,$O$9,H$31) -> 196.27733 | I32: =TABLE($C$31,$O$12,$C32,$O$9,I$31) -> 190.84849 | J32: =TABLE($C$31,$O$12,$C32,$O$9,J$31) -> 185.6774
C33: =C32+1% -> 0.01 | D33: =TABLE($C$31,$O$12,$C33,$O$9,D$31) -> 220.90082 | E33: =TABLE($C$31,$O$12,$C33,$O$9,E$31) -> 214.2727 | F33: =TABLE($C$31,$O$12,$C33,$O$9,F$31) -> 207.97206 | G33: =TABLE($C$31,$O$12,$C33,$O$9,G$31) -> 201.97959 | H33: =TABLE($C$31,$O$12,$C33,$O$9,H$31) -> 196.27733 | I33: =TABLE($C$31,$O$12,$C33,$O$9,I$31) -> 190.84849 | J33: =TABLE($C$31,$O$12,$C33,$O$9,J$31) -> 185.6774
C34: =C33+1% -> 0.02 | D34: =TABLE($C$31,$O$12,$C34,$O$9,D$31) -> 220.90082 | E34: =TABLE($C$31,$O$12,$C34,$O$9,E$31) -> 214.2727 | F34: =TABLE($C$31,$O$12,$C34,$O$9,F$31) -> 207.97206 | G34: =TABLE($C$31,$O$12,$C34,$O$9,G$31) -> 201.97959 | H34: =TABLE($C$31,$O$12,$C34,$O$9,H$31) -> 196.27733 | I34: =TABLE($C$31,$O$12,$C34,$O$9,I$31) -> 190.84849 | J34: =TABLE($C$31,$O$12,$C34,$O$9,J$31) -> 185.6774
C35: =C34+1% -> 0.03 | D35: =TABLE($C$31,$O$12,$C35,$O$9,D$31) -> 220.90082 | E35: =TABLE($C$31,$O$12,$C35,$O$9,E$31) -> 214.2727 | F35: =TABLE($C$31,$O$12,$C35,$O$9,F$31) -> 207.97206 | G35: =TABLE($C$31,$O$12,$C35,$O$9,G$31) -> 201.97959 | H35: =TABLE($C$31,$O$12,$C35,$O$9,H$31) -> 196.27733 | I35: =TABLE($C$31,$O$12,$C35,$O$9,I$31) -> 190.84849 | J35: =TABLE($C$31,$O$12,$C35,$O$9,J$31) -> 185.6774
C36: =C35+1% -> 0.04 | D36: =TABLE($C$31,$O$12,$C36,$O$9,D$31) -> 220.90082 | E36: =TABLE($C$31,$O$12,$C36,$O$9,E$31) -> 214.2727 | F36: =TABLE($C$31,$O$12,$C36,$O$9,F$31) -> 207.97206 | G36: =TABLE($C$31,$O$12,$C36,$O$9,G$31) -> 201.97959 | H36: =TABLE($C$31,$O$12,$C36,$O$9,H$31) -> 196.27733 | I36: =TABLE($C$31,$O$12,$C36,$O$9,I$31) -> 190.84849 | J36: =TABLE($C$31,$O$12,$C36,$O$9,J$31) -> 185.6774
C37: =C36+1% -> 0.05 | D37: =TABLE($C$31,$O$12,$C37,$O$9,D$31) -> 220.90082 | E37: =TABLE($C$31,$O$12,$C37,$O$9,E$31) -> 214.2727 | F37: =TABLE($C$31,$O$12,$C37,$O$9,F$31) -> 207.97206 | G37: =TABLE($C$31,$O$12,$C37,$O$9,G$31) -> 201.97959 | H37: =TABLE($C$31,$O$12,$C37,$O$9,H$31) -> 196.27733 | I37: =TABLE($C$31,$O$12,$C37,$O$9,I$31) -> 190.84849 | J37: =TABLE($C$31,$O$12,$C37,$O$9,J$31) -> 185.6774
B39: =TEXT(Company_Name,"")&" - Net Present Value Sensitivity - Terminal EBITDA Multiples" -> Apple Inc. - Net Present Value Sensitivity - Terminal EBITDA Multiples
D40: =D30 -> Discount Rate
C41: =O25 -> 204.96045 | D41: =D31 -> 0.1 | E41: =E31 -> 0.11 | F41: =F31 -> 0.12 | G41: =G31 -> 0.13 | H41: =H31 -> 0.14 | I41: =I31 -> 0.15 | J41: =J31 -> 0.16
B42: Terminal EBITDA Multiple | C42: 4 | D42: =TABLE($C$41,$O$11,$C42,$O$9,D$41) -> 170.38839 | E42: =TABLE($C$41,$O$11,$C42,$O$9,E$41) -> 165.99498 | F42: =TABLE($C$41,$O$11,$C42,$O$9,F$41) -> 161.81144 | G42: =TABLE($C$41,$O$11,$C42,$O$9,G$41) -> 157.82565 | H42: =TABLE($C$41,$O$11,$C42,$O$9,H$41) -> 154.02628 | I42: =TABLE($C$41,$O$11,$C42,$O$9,I$41) -> 150.40277 | J42: =TABLE($C$41,$O$11,$C42,$O$9,J$41) -> 146.94524
C43: =C42+1 -> 5 | D43: =TABLE($C$41,$O$11,$C43,$O$9,D$41) -> 187.22586 | E43: =TABLE($C$41,$O$11,$C43,$O$9,E$41) -> 182.08755 | F43: =TABLE($C$41,$O$11,$C43,$O$9,F$41) -> 177.19831 | G43: =TABLE($C$41,$O$11,$C43,$O$9,G$41) -> 172.54363 | H43: =TABLE($C$41,$O$11,$C43,$O$9,H$41) -> 168.10997 | I43: =TABLE($C$41,$O$11,$C43,$O$9,I$41) -> 163.88468 | J43: =TABLE($C$41,$O$11,$C43,$O$9,J$41) -> 159.85596
C44: =C43+1 -> 6 | D44: =TABLE($C$41,$O$11,$C44,$O$9,D$41) -> 204.06334 | E44: =TABLE($C$41,$O$11,$C44,$O$9,E$41) -> 198.18013 | F44: =TABLE($C$41,$O$11,$C44,$O$9,F$41) -> 192.58518 | G44: =TABLE($C$41,$O$11,$C44,$O$9,G$41) -> 187.26161 | H44: =TABLE($C$41,$O$11,$C44,$O$9,H$41) -> 182.19365 | I44: =TABLE($C$41,$O$11,$C44,$O$9,I$41) -> 177.36658 | J44: =TABLE($C$41,$O$11,$C44,$O$9,J$41) -> 172.76668
C45: =C44+1 -> 7 | D45: =TABLE($C$41,$O$11,$C45,$O$9,D$41) -> 220.90082 | E45: =TABLE($C$41,$O$11,$C45,$O$9,E$41) -> 214.2727 | F45: =TABLE($C$41,$O$11,$C45,$O$9,F$41) -> 207.97206 | G45: =TABLE($C$41,$O$11,$C45,$O$9,G$41) -> 201.97959 | H45: =TABLE($C$41,$O$11,$C45,$O$9,H$41) -> 196.27733 | I45: =TABLE($C$41,$O$11,$C45,$O$9,I$41) -> 190.84849 | J45: =TABLE($C$41,$O$11,$C45,$O$9,J$41) -> 185.6774
C46: =C45+1 -> 8 | D46: =TABLE($C$41,$O$11,$C46,$O$9,D$41) -> 237.73829 | E46: =TABLE($C$41,$O$11,$C46,$O$9,E$41) -> 230.36528 | F46: =TABLE($C$41,$O$11,$C46,$O$9,F$41) -> 223.35893 | G46: =TABLE($C$41,$O$11,$C46,$O$9,G$41) -> 216.69757 | H46: =TABLE($C$41,$O$11,$C46,$O$9,H$41) -> 210.36101 | I46: =TABLE($C$41,$O$11,$C46,$O$9,I$41) -> 204.33039 | J46: =TABLE($C$41,$O$11,$C46,$O$9,J$41) -> 198.58812
C47: =C46+1 -> 9 | D47: =TABLE($C$41,$O$11,$C47,$O$9,D$41) -> 254.57577 | E47: =TABLE($C$41,$O$11,$C47,$O$9,E$41) -> 246.45785 | F47: =TABLE($C$41,$O$11,$C47,$O$9,F$41) -> 238.7458 | G47: =TABLE($C$41,$O$11,$C47,$O$9,G$41) -> 231.41555 | H47: =TABLE($C$41,$O$11,$C47,$O$9,H$41) -> 224.44469 | I47: =TABLE($C$41,$O$11,$C47,$O$9,I$41) -> 217.81229 | J47: =TABLE($C$41,$O$11,$C47,$O$9,J$41) -> 211.49884

Sheet WACC
B2: ="WACC Analysis - "&TEXT(Company_Name,"") -> WACC Analysis - Apple Inc.
B3: ='AAPL-3-Statements'!B3 -> ($ in Millions, Except Per Share Amounts in Dollars and Share Counts in Thousands)
B5: Discount Rate Calculation - Assumptions
B6: Risk-Free Rate: | E6: 0.0438
B7: Equity Risk Premium: | E7: 0.07
B8: Interest Rate on Debt: | E8: ='AAPL-3-Statements'!I47 -> 0.09
B10: Comparable Companies - Unlevered Beta Calculation
C11: Levered | E11: Equity | G11: Unlevered
B12: Name | C12: Beta | D12: Debt | E12: Value | F12: Tax Rate | G12: Beta
B13: ='Public Comps'!B8 -> Hewlett-Packard Company | C13: 1.04 | D13: ='Public Comps'!G8 -> 15830 | E13: ='Public Comps'!E8 -> 114779.16 | F13: 0.2 | G13: =C13/(1+(1-F13)*(D13/E13)) -> 0.93665542
B14: ='Public Comps'!B9 -> Dell Inc. | C14: 1.31 | D14: ='Public Comps'!G9 -> 3793 | E14: ='Public Comps'!E9 -> 25240.867 | F14: 0.27 | G14: =C14/(1+(1-F14)*(D14/E14)) -> 1.1805006
B15: ='Public Comps'!B10 -> Cisco Systems, Inc. | C15: 1.23 | D15: ='Public Comps'!G10 -> 10273 | E15: ='Public Comps'!E10 -> 131739.04 | F15: 0.22 | G15: =C15/(1+(1-F15)*(D15/E15)) -> 1.1594757
B16: ='Public Comps'!B11 -> Intel Corporation | C16: 1.17 | D16: ='Public Comps'!G11 -> 2224 | E16: ='Public Comps'!E11 -> 107224.38 | F16: 0.33 | G16: =C16/(1+(1-F16)*(D16/E16)) -> 1.1539636
B17: ='Public Comps'!B12 -> Motorola, Inc. | C17: 1.87 | D17: ='Public Comps'!G12 -> 3925 | E17: ='Public Comps'!E12 -> 14239.397 | F17: 0.34 | G17: =C17/(1+(1-F17)*(D17/E17)) -> 1.5821649
B19: Median | C19: =MEDIAN(C13:C17) -> 1.23 | G19: =MEDIAN(G13:G17) -> 1.1594757
B21: =Company_Name -> Apple Inc. | C21: 1.57
B23: =TEXT(Company_Name,"")&" - Levered Beta & WACC Calculation" -> Apple Inc. - Levered Beta & WACC Calculation
C24: Unlevered | E24: Equity | G24: Levered
C25: Beta | D25: Debt | E25: Value | F25: Tax Rate | G25: Beta
B27: =Company_Name -> Apple Inc. | C27: =G19 -> 1.1594757 | D27: 0 | E27: =Equity_Value -> 176796.15 | F27: =Tax_Rate -> 0.3 | G27: =C27*(1+(1-F27)*(D27/E27)) -> 1.1594757
B29: Cost of Equity Based on Comparables: | G29: =E6+E7*G27 -> 0.1249633
B30: Cost of Equity Based on Historical Beta: | G30: =E6+E7*C21 -> 0.1537
B32: WACC = Cost of Equity * % Equity + Cost of Debt * % Debt * (1 - Tax Rate) + Cost of Preferred Stock * % Preferred Stock
B34: WACC | G34: =G29*(E27/(E27+D27))+E8*(D27/(D27+E27))*(1-F27) -> 0.1249633

Sheet Merger-Model
B2: ="Merger Model - "&TEXT(Company_Name,"")&" and "&Seller_Name -> Merger Model - Apple Inc. and Research in Motion Limited
B3: ='AAPL-3-Statements'!B3 -> ($ in Millions, Except Per Share Amounts in Dollars and Share Counts in Thousands)
B5: Transaction Assumptions
B7: Per Share Purchase Price: | F7: 75 | H7: Equity Purchase Price: | L7: ='Merger-Shares-BS'!J15 -> 43048.922
B8: % Cash: | F8: =1/3 -> 0.33333333 | H8: Cash Used: | L8: =F8*L7 -> 14349.641
B9: % Debt: | F9: =1/3 -> 0.33333333 | H9: Debt Issued: | L9: =F9*L7 -> 14349.641
B10: % Stock: | F10: =1/3 -> 0.33333333 | H10: New Shares Issued: | L10: =F10*L7/F34*Units -> 74714.364
B11: Foregone Cash Interest Rate: | F11: ='AAPL-3-Statements'!I46 -> 0.01 | H11: Debt Interest Rate: | L11: ='AAPL-3-Statements'!I47 -> 0.09
B13: Revenue Synergy %: | F13: 0.1 | H13: Revenue Synergy COGS %: | L13: 0.5
B14: Cost Synergies % OpEx: | F14: 0.1
B16: Goodwill Creation & Balance Sheet Adjustments
B18: Goodwill Calculation: | H18: Fixed Asset Write-Up:
B19: Equity Purchase Price: | F19: =L7 -> 43048.922 | H19: PP&E Write-Up %: | L19: 0.1
B20: Less: Seller Book Value: | F20: =-'Merger-Shares-BS'!J62 -> -6986.62 | H20: PP&E Write-Up Amount: | L20: =L19*'Merger-Shares-BS'!J36 -> 173.7403
B21: Plus: Write-Off of Existing Goodwill: | F21: ='Merger-Shares-BS'!J37 -> 146.557 | H21: Depreciation Period (Years): | L21: 8
B22: Total Allocable Purchase Premium: | F22: =F19+F20+F21 -> 36208.859
H23: Intangible Asset Write-Up:
B24: Less: Write-Up of PP&E: | F24: =-L20 -> -173.7403 | H24: Purchase Price to Allocate: | L24: =F22 -> 36208.859
B25: Less: Write-Up of Intangibles: | F25: =-L26 -> -7241.7718 | H25: % Allocated to Intangibles: | L25: 0.2
B26: Less: Write-Down of DTL: | F26: =-'Merger-Shares-BS'!J52 -> -43.265 | H26: Intangibles Write-Up Amount: | L26: =L25*L24 -> 7241.7718
B27: Plus: New Deferred Tax Liability: | F27: =L29 -> 2224.6536 | H27: Amortization Period (Years): | L27: 5
B28: Total Goodwill Created: | F28: =F22+F24+F25+F26+F27 -> 30974.736
H29: New Deferred Tax Liability: | L29: =(L26+L20)*Tax_Rate -> 2224.6536
B31: Buyer - Financial Profile | H31: Seller - Financial Profile
B33: Buyer Name: | F33: =Company_Name -> Apple Inc. | H33: Seller Name: | L33: =Seller_Name -> Research in Motion Limited
B34: Share Price: | F34: =Share_Price -> 192.06 | H34: Share Price: | L34: =Seller_Share_Price -> 62.91
B35: Diluted Shares Outstanding: | F35: =Diluted_Shares -> 920525.62 | H35: Diluted Shares Outstanding: | L35: ='Merger-Shares-BS'!E14 -> 572950.86
B36: Diluted Equity Value: | F36: =Equity_Value -> 176796.15 | H36: Diluted Equity Value: | L36: ='Merger-Shares-BS'!E15 -> 36044.339
B37: Enterprise Value: | F37: =Enterprise_Value -> 141401.15 | H37: Enterprise Value: | L37: ='Merger-Shares-BS'!E21 -> 33546.592
B38: Tax Rate: | F38: =Tax_Rate -> 0.3 | H38: Tax Rate: | L38: ='Merger-Shares-BS'!J9 -> 0.28
B40: Buyer - Income Statement | H40: Seller - Income Statement
E42: ='AAPL-3-Statements'!I96 -> FY 2010E | F42: ='AAPL-3-Statements'!J96 -> FY 2011E | K42: =E42 -> FY 2010E | L42: =F42 -> FY 2011E
B43: Revenue: | E43: ='AAPL-3-Statements'!I66 -> 53631.25 | F43: ='AAPL-3-Statements'!J66 -> 62748.562 | H43: Revenue: | K43: 17231 | L43: 20868
B44: Cost of Goods Sold: | E44: ='AAPL-3-Statements'!I67 -> 31655.417 | F44: ='AAPL-3-Statements'!J67 -> 37036.838 | H44: Cost of Goods Sold: | K44: 9755 | L44: 11868.5
B45: Gross Profit: | E45: =E43-E44 -> 21975.833 | F45: =F43-F44 -> 25711.725 | H45: Gross Profit: | K45: =K43-K44 -> 7476 | L45: =L43-L44 -> 8999.5
B47: Operating Expenses: | E47: ='AAPL-3-Statements'!I72 -> 5495.8333 | F47: ='AAPL-3-Statements'!J72 -> 6430.125 | H47: Operating Expenses: | K47: 2697.532 | L47: 3258.96
B49: Depreciation of PP&E: | E49: ='AAPL-3-Statements'!I74 -> 917.5 | F49: ='AAPL-3-Statements'!J74 -> 1073.475 | H49: Depreciation of PP&E: | K49: 430.775 | L49: 563.436
B50: Amortization of Intangibles: | E50: ='AAPL-3-Statements'!I75 -> 40 | F50: ='AAPL-3-Statements'!J75 -> 37 | H50: Amortization of Intangibles: | K50: 359 | L50: 433
B51: Stock-Based Compensation: | E51: ='AAPL-3-Statements'!I76 -> 887.5 | F51: ='AAPL-3-Statements'!J76 -> 1038.375 | H51: Stock-Based Compensation: | K51: 51.693 | L51: 62.604
B53: Operating Income: | E53: =E45-E47-E49-E50-E51 -> 14635 | F53: =F45-F47-F49-F50-F51 -> 17132.75 | H53: Operating Income: | K53: =K45-K47-K49-K50-K51 -> 3937 | L53: =L45-L47-L49-L50-L51 -> 4681.5
B54: Interest Income / (Expense): | E54: =SUM('AAPL-3-Statements'!I79:I81) -> 379.25364 | F54: =SUM('AAPL-3-Statements'!J79:J81) -> 477.64936 | H54: Interest Income / (Expense): | K54: 25 | L54: 32.5
B55: Pre-Tax Income: | E55: =E53+E54 -> 15014.254 | F55: =F53+F54 -> 17610.399 | H55: Pre-Tax Income: | K55: =K53+K54 -> 3962 | L55: =L53+L54 -> 4714
B56: Income Tax Provision: | E56: =E55*$F$38 -> 4504.2761 | F56: =F55*$F$38 -> 5283.1198 | H56: Income Tax Provision: | K56: 1148 | L56: 1343
B58: Net Income: | E58: =E55-E56 -> 10509.978 | F58: =F55-F56 -> 12327.28 | H58: Net Income: | K58: =K55-K56 -> 2814 | L58: =L55-L56 -> 3371
B60: Earnings Per Share (EPS): | E60: =E58*Units/E61 -> 11.587563 | F60: =F58*Units/F61 -> 13.591192 | H60: Earnings Per Share (EPS): | K60: =K58*Units/K61 -> 5.025 | L60: =L58*Units/L61 -> 6.0196429
B61: Diluted Shares Outstanding: | E61: ='AAPL-3-Statements'!I88 -> 907005 | F61: ='AAPL-3-Statements'!J88 -> 907005 | H61: Diluted Shares Outstanding: | K61: 560000 | L61: 560000
B63: Combined Income Statement
E65: =E42 -> FY 2010E | F65: =F42 -> FY 2011E
B66: Combined Revenue: | E66: =E43+K43 -> 70862.25 | F66: =F43+L43 -> 83616.562
B67: Revenue Synergies: | E67: =K43*$F$13 -> 1723.1 | F67: =L43*$F$13 -> 2086.8
B68: Cost of Goods Sold: | E68: =E44+K44 -> 41410.417 | F68: =F44+L44 -> 48905.338
B69: Revenue Synergy COGS: | E69: =E67*$L$13 -> 861.55 | F69: =F67*$L$13 -> 1043.4
B70: Gross Profit: | E70: =E66+E67-E68-E69 -> 30313.383 | F70: =F66+F67-F68-F69 -> 35754.625
B72: Operating Expenses: | E72: =E47+K47 -> 8193.3653 | F72: =F47+L47 -> 9689.085
B73: OpEx Synergies: | E73: =K47*$F$14 -> 269.7532 | F73: =L47*$F$14 -> 325.896
B75: Depreciation of PP&E: | E75: =E49+K49 -> 1348.275 | F75: =F49+L49 -> 1636.911
B76: Depr. of PP&E Write-Up: | E76: =$L$20/$L$21 -> 21.717537 | F76: =$L$20/$L$21 -> 21.717537
B77: Amortization of Intangibles: | E77: =E50+K50 -> 399 | F77: =F50+L50 -> 470
B78: Amort. of New Intangibles: | E78: =$L$26/$L$27 -> 1448.3544 | F78: =$L$26/$L$27 -> 1448.3544
B79: Stock-Based Compensation: | E79: =E51+K51 -> 939.193 | F79: =F51+L51 -> 1100.979
B81: Operating Income: | E81: =E70-E72+E73-E75-E76-E77-E78-E79 -> 18233.231 | F81: =F70-F72+F73-F75-F76-F77-F78-F79 -> 21713.474
B82: Interest Income / (Expense): | E82: =E54+K54 -> 404.25364 | F82: =F54+L54 -> 510.14936
B83: Foregone Interest on Cash: | E83: =-$L$8*$F$11 -> -143.49641 | F83: =-$L$8*$F$11 -> -143.49641
B84: Interest Paid on New Debt: | E84: =-$L$9*$L$11 -> -1291.4677 | F84: =-$L$9*$L$11 -> -1291.4677
B85: Pre-Tax Income: | E85: =E81+E82+E83+E84 -> 17202.521 | F85: =F81+F82+F83+F84 -> 20788.659
B86: Income Tax Provision: | E86: =E85*$F$38 -> 5160.7563 | F86: =F85*$F$38 -> 6236.5978
B88: Net Income: | E88: =E85-E86 -> 12041.765 | F88: =F85-F86 -> 14552.062
B90: Earnings Per Share (EPS): | E90: =E88*Units/E91 -> 12.265995 | F90: =F88*Units/F91 -> 14.823036
B91: Diluted Shares Outstanding: | E91: =E61+$L$10 -> 981719.36 | F91: =F61+$L$10 -> 981719.36
B93: Accretion / Dilution: | E93: =E90-E60 -> 0.67843183 | F93: =F90-F60 -> 1.2318436
B94: Accretion / Dilution %: | E94: =E93/E60 -> 0.058548276 | F94: =F93/F60 -> 0.090635432
B96: Sensitivity Analysis - Year 1 EPS Accretion/Dilution and Purchase Price vs. Operating Expense Synergies:
D98: Expense Synergies % Seller OpEx:
C99: =E94 -> 0.058548276 | D99: 0 | E99: =D99+2% -> 0.02 | F99: =E99+2% -> 0.04 | G99: =F99+2% -> 0.06 | H99: =G99+2% -> 0.08 | I99: =H99+2% -> 0.1 | J99: =I99+2% -> 0.12 | K99: =J99+2% -> 0.14 | L99: =K99+2% -> 0.16
B100: Per Share Purchase Price | C100: =C101+5 -> 110 | D100: =TABLE($C$99,$F$7,$C100,$F$14,D$99) -> -0.082449079 | E100: =TABLE($C$99,$F$7,$C100,$F$14,E$99) -> -0.079244148 | F100: =TABLE($C$99,$F$7,$C100,$F$14,F$99) -> -0.076039217 | G100: =TABLE($C$99,$F$7,$C100,$F$14,G$99) -> -0.072834286 | H100: =TABLE($C$99,$F$7,$C100,$F$14,H$99) -> -0.069629356 | I100: =TABLE($C$99,$F$7,$C100,$F$14,I$99) -> -0.066424425 | J100: =TABLE($C$99,$F$7,$C100,$F$14,J$99) -> -0.063219494 | K100: =TABLE($C$99,$F$7,$C100,$F$14,K$99) -> -0.060014563 | L100: =TABLE($C$99,$F$7,$C100,$F$14,L$99) -> -0.056809632
C101: =C102+5 -> 105 | D101: =TABLE($C$99,$F$7,$C101,$F$14,D$99) -> -0.065207694 | E101: =TABLE($C$99,$F$7,$C101,$F$14,E$99) -> -0.061986839 | F101: =TABLE($C$99,$F$7,$C101,$F$14,F$99) -> -0.058765984 | G101: =TABLE($C$99,$F$7,$C101,$F$14,G$99) -> -0.055545129 | H101: =TABLE($C$99,$F$7,$C101,$F$14,H$99) -> -0.052324273 | I101: =TABLE($C$99,$F$7,$C101,$F$14,I$99) -> -0.049103418 | J101: =TABLE($C$99,$F$7,$C101,$F$14,J$99) -> -0.045882563 | K101: =TABLE($C$99,$F$7,$C101,$F$14,K$99) -> -0.042661708 | L101: =TABLE($C$99,$F$7,$C101,$F$14,L$99) -> -0.039440853
C102: =C103+5 -> 100 | D102: =TABLE($C$99,$F$7,$C102,$F$14,D$99) -> -0.04779412 | E102: =TABLE($C$99,$F$7,$C102,$F$14,E$99) -> -0.044557182 | F102: =TABLE($C$99,$F$7,$C102,$F$14,F$99) -> -0.041320244 | G102: =TABLE($C$99,$F$7,$C102,$F$14,G$99) -> -0.038083306 | H102: =TABLE($C$99,$F$7,$C102,$F$14,H$99) -> -0.034846368 | I102: =TABLE($C$99,$F$7,$C102,$F$14,I$99) -> -0.03160943 | J102: =TABLE($C$99,$F$7,$C102,$F$14,J$99) -> -0.028372491 | K102: =TABLE($C$99,$F$7,$C102,$F$14,K$99) -> -0.025135553 | L102: =TABLE($C$99,$F$7,$C102,$F$14,L$99) -> -0.021898615
C103: =C104+5 -> 95 | D103: =TABLE($C$99,$F$7,$C103,$F$14,D$99) -> -0.030205767 | E103: =TABLE($C$99,$F$7,$C103,$F$14,E$99) -> -0.026952584 | F103: =TABLE($C$99,$F$7,$C103,$F$14,F$99) -> -0.023699402 | G103: =TABLE($C$99,$F$7,$C103,$F$14,G$99) -> -0.020446219 | H103: =TABLE($C$99,$F$7,$C103,$F$14,H$99) -> -0.017193036 | I103: =TABLE($C$99,$F$7,$C103,$F$14,I$99) -> -0.013939853 | J103: =TABLE($C$99,$F$7,$C103,$F$14,J$99) -> -0.010686671 | K103: =TABLE($C$99,$F$7,$C103,$F$14,K$99) -> -0.007433488 | L103: =TABLE($C$99,$F$7,$C103,$F$14,L$99) -> -0.0041803052
C104: =C105+5 -> 90 | D104: =TABLE($C$99,$F$7,$C104,$F$14,D$99) -> -0.012439989 | E104: =TABLE($C$99,$F$7,$C104,$F$14,E$99) -> -0.0091703982 | F104: =TABLE($C$99,$F$7,$C104,$F$14,F$99) -> -0.005900807 | G104: =TABLE($C$99,$F$7,$C104,$F$14,G$99) -> -0.0026312158 | H104: =TABLE($C$99,$F$7,$C104,$F$14,H$99) -> 0.00063837536 | I104: =TABLE($C$99,$F$7,$C104,$F$14,I$99) -> 0.0039079665 | J104: =TABLE($C$99,$F$7,$C104,$F$14,J$99) -> 0.0071775577 | K104: =TABLE($C$99,$F$7,$C104,$F$14,K$99) -> 0.010447149 | L104: =TABLE($C$99,$F$7,$C104,$F$14,L$99) -> 0.01371674
C105: =C106+5 -> 85 | D105: =TABLE($C$99,$F$7,$C105,$F$14,D$99) -> 0.0055059114 | E105: =TABLE($C$99,$F$7,$C105,$F$14,E$99) -> 0.0087920774 | F105: =TABLE($C$99,$F$7,$C105,$F$14,F$99) -> 0.012078243 | G105: =TABLE($C$99,$F$7,$C105,$F$14,G$99) -> 0.015364409 | H105: =TABLE($C$99,$F$7,$C105,$F$14,H$99) -> 0.018650575 | I105: =TABLE($C$99,$F$7,$C105,$F$14,I$99) -> 0.021936741 | J105: =TABLE($C$99,$F$7,$C105,$F$14,J$99) -> 0.025222907 | K105: =TABLE($C$99,$F$7,$C105,$F$14,K$99) -> 0.028509073 | L105: =TABLE($C$99,$F$7,$C105,$F$14,L$99) -> 0.031795239
C106: =C107+5 -> 80 | D106: =TABLE($C$99,$F$7,$C106,$F$14,D$99) -> 0.023634688 | E106: =TABLE($C$99,$F$7,$C106,$F$14,E$99) -> 0.026937598 | F106: =TABLE($C$99,$F$7,$C106,$F$14,F$99) -> 0.030240508 | G106: =TABLE($C$99,$F$7,$C106,$F$14,G$99) -> 0.033543417 | H106: =TABLE($C$99,$F$7,$C106,$F$14,H$99) -> 0.036846327 | I106: =TABLE($C$99,$F$7,$C106,$F$14,I$99) -> 0.040149237 | J106: =TABLE($C$99,$F$7,$C106,$F$14,J$99) -> 0.043452146 | K106: =TABLE($C$99,$F$7,$C106,$F$14,K$99) -> 0.046755056 | L106: =TABLE($C$99,$F$7,$C106,$F$14,L$99) -> 0.050057966
C107: =C108+5 -> 75 | D107: =TABLE($C$99,$F$7,$C107,$F$14,D$99) -> 0.041949151 | E107: =TABLE($C$99,$F$7,$C107,$F$14,E$99) -> 0.045268976 | F107: =TABLE($C$99,$F$7,$C107,$F$14,F$99) -> 0.048588801 | G107: =TABLE($C$99,$F$7,$C107,$F$14,G$99) -> 0.051908626 | H107: =TABLE($C$99,$F$7,$C107,$F$14,H$99) -> 0.055228451 | I107: =TABLE($C$99,$F$7,$C107,$F$14,I$99) -> 0.058548276 | J107: =TABLE($C$99,$F$7,$C107,$F$14,J$99) -> 0.061868101 | K107: =TABLE($C$99,$F$7,$C107,$F$14,K$99) -> 0.065187925 | L107: =TABLE($C$99,$F$7,$C107,$F$14,L$99) -> 0.06850775
C108: =C109+5 -> 70 | D108: =TABLE($C$99,$F$7,$C108,$F$14,D$99) -> 0.060452168 | E108: =TABLE($C$99,$F$7,$C108,$F$14,E$99) -> 0.063789082 | F108: =TABLE($C$99,$F$7,$C108,$F$14,F$99) -> 0.067125996 | G108: =TABLE($C$99,$F$7,$C108,$F$14,G$99) -> 0.07046291 | H108: =TABLE($C$99,$F$7,$C108,$F$14,H$99) -> 0.073799825 | I108: =TABLE($C$99,$F$7,$C108,$F$14,I$99) -> 0.077136739 | J108: =TABLE($C$99,$F$7,$C108,$F$14,J$99) -> 0.080473653 | K108: =TABLE($C$99,$F$7,$C108,$F$14,K$99) -> 0.083810567 | L108: =TABLE($C$99,$F$7,$C108,$F$14,L$99) -> 0.087147482
C109: 65 | D109: =TABLE($C$99,$F$7,$C109,$F$14,D$99) -> 0.079146664 | E109: =TABLE($C$99,$F$7,$C109,$F$14,E$99) -> 0.082500845 | F109: =TABLE($C$99,$F$7,$C109,$F$14,F$99) -> 0.085855025 | G109: =TABLE($C$99,$F$7,$C109,$F$14,G$99) -> 0.089209206 | H109: =TABLE($C$99,$F$7,$C109,$F$14,H$99) -> 0.092563386 | I109: =TABLE($C$99,$F$7,$C109,$F$14,I$99) -> 0.095917567 | J109: =TABLE($C$99,$F$7,$C109,$F$14,J$99) -> 0.099271747 | K109: =TABLE($C$99,$F$7,$C109,$F$14,K$99) -> 0.10262593 | L109: =TABLE($C$99,$F$7,$C109,$F$14,L$99) -> 0.10598011
B111: Sensitivity Analysis - Year 1 EPS Accretion/Dilution and Purchase Price vs. Revenue Synergies:
D113: Revenue Synergies % Seller Revenue:
C114: =E94 -> 0.058548276 | D114: =D99 -> 0 | E114: =E99 -> 0.02 | F114: =F99 -> 0.04 | G114: =G99 -> 0.06 | H114: =H99 -> 0.08 | I114: =I99 -> 0.1 | J114: =J99 -> 0.12 | K114: =K99 -> 0.14 | L114: =L99 -> 0.16
B115: Per Share Purchase Price | C115: =C100 -> 110 | D115: =TABLE($C$114,$F$7,$C115,$F$13,D$114) -> -0.11760469 | E115: =TABLE($C$114,$F$7,$C115,$F$13,E$114) -> -0.10736864 | F115: =TABLE($C$114,$F$7,$C115,$F$13,F$114) -> -0.097132586 | G115: =TABLE($C$114,$F$7,$C115,$F$13,G$114) -> -0.086896532 | H115: =TABLE($C$114,$F$7,$C115,$F$13,H$114) -> -0.076660478 | I115: =TABLE($C$114,$F$7,$C115,$F$13,I$114) -> -0.066424425 | J115: =TABLE($C$114,$F$7,$C115,$F$13,J$114) -> -0.056188371 | K115: =TABLE($C$114,$F$7,$C115,$F$13,K$114) -> -0.045952317 | L115: =TABLE($C$114,$F$7,$C115,$F$13,L$114) -> -0.035716263
C116: =C101 -> 105 | D116: =TABLE($C$114,$F$7,$C116,$F$13,D$114) -> -0.10053798 | E116: =TABLE($C$114,$F$7,$C116,$F$13,E$114) -> -0.09025107 | F116: =TABLE($C$114,$F$7,$C116,$F$13,F$114) -> -0.079964157 | G116: =TABLE($C$114,$F$7,$C116,$F$13,G$114) -> -0.069677244 | H116: =TABLE($C$114,$F$7,$C116,$F$13,H$114) -> -0.059390331 | I116: =TABLE($C$114,$F$7,$C116,$F$13,I$114) -> -0.049103418 | J116: =TABLE($C$114,$F$7,$C116,$F$13,J$114) -> -0.038816506 | K116: =TABLE($C$114,$F$7,$C116,$F$13,K$114) -> -0.028529593 | L116: =TABLE($C$114,$F$7,$C116,$F$13,L$114) -> -0.01824268
C117: =C102 -> 100 | D117: =TABLE($C$114,$F$7,$C117,$F$13,D$114) -> -0.083300829 | E117: =TABLE($C$114,$F$7,$C117,$F$13,E$114) -> -0.072962549 | F117: =TABLE($C$114,$F$7,$C117,$F$13,F$114) -> -0.062624269 | G117: =TABLE($C$114,$F$7,$C117,$F$13,G$114) -> -0.052285989 | H117: =TABLE($C$114,$F$7,$C117,$F$13,H$114) -> -0.041947709 | I117: =TABLE($C$114,$F$7,$C117,$F$13,I$114) -> -0.03160943 | J117: =TABLE($C$114,$F$7,$C117,$F$13,J$114) -> -0.02127115 | K117: =TABLE($C$114,$F$7,$C117,$F$13,K$114) -> -0.01093287 | L117: =TABLE($C$114,$F$7,$C117,$F$13,L$114) -> -0.00059458972
C118: =C103 -> 95 | D118: =TABLE($C$114,$F$7,$C118,$F$13,D$114) -> -0.065890666 | E118: =TABLE($C$114,$F$7,$C118,$F$13,E$114) -> -0.055500504 | F118: =TABLE($C$114,$F$7,$C118,$F$13,F$114) -> -0.045110341 | G118: =TABLE($C$114,$F$7,$C118,$F$13,G$114) -> -0.034720179 | H118: =TABLE($C$114,$F$7,$C118,$F$13,H$114) -> -0.024330016 | I118: =TABLE($C$114,$F$7,$C118,$F$13,I$114) -> -0.013939853 | J118: =TABLE($C$114,$F$7,$C118,$F$13,J$114) -> -0.0035496909 | K118: =TABLE($C$114,$F$7,$C118,$F$13,K$114) -> 0.0068404717 | L118: =TABLE($C$114,$F$7,$C118,$F$13,L$114) -> 0.017230634
C119: =C104 -> 90 | D119: =TABLE($C$114,$F$7,$C119,$F$13,D$114) -> -0.048304876 | E119: =TABLE($C$114,$F$7,$C119,$F$13,E$114) -> -0.037862308 | F119: =TABLE($C$114,$F$7,$C119,$F$13,F$114) -> -0.027419739 | G119: =TABLE($C$114,$F$7,$C119,$F$13,G$114) -> -0.016977171 | H119: =TABLE($C$114,$F$7,$C119,$F$13,H$114) -> -0.006534602 | I119: =TABLE($C$114,$F$7,$C119,$F$13,I$114) -> 0.0039079665 | J119: =TABLE($C$114,$F$7,$C119,$F$13,J$114) -> 0.014350535 | K119: =TABLE($C$114,$F$7,$C119,$F$13,K$114) -> 0.024793104 | L119: =TABLE($C$114,$F$7,$C119,$F$13,L$114) -> 0.035235672
C120: =C105 -> 85 | D120: =TABLE($C$114,$F$7,$C120,$F$13,D$114) -> -0.030540788 | E120: =TABLE($C$114,$F$7,$C120,$F$13,E$114) -> -0.020045282 | F120: =TABLE($C$114,$F$7,$C120,$F$13,F$114) -> -0.0095497764 | G120: =TABLE($C$114,$F$7,$C120,$F$13,G$114) -> 0.00094572947 | H120: =TABLE($C$114,$F$7,$C120,$F$13,H$114) -> 0.011441235 | I120: =TABLE($C$114,$F$7,$C120,$F$13,I$114) -> 0.021936741 | J120: =TABLE($C$114,$F$7,$C120,$F$13,J$114) -> 0.032432247 | K120: =TABLE($C$114,$F$7,$C120,$F$13,K$114) -> 0.042927753 | L120: =TABLE($C$114,$F$7,$C120,$F$13,L$114) -> 0.053423259
C121: =C106 -> 80 | D121: =TABLE($C$114,$F$7,$C121,$F$13,D$114) -> -0.012595677 | E121: =TABLE($C$114,$F$7,$C121,$F$13,E$114) -> -0.002046694 | F121: =TABLE($C$114,$F$7,$C121,$F$13,F$114) -> 0.0085022887 | G121: =TABLE($C$114,$F$7,$C121,$F$13,G$114) -> 0.019051271 | H121: =TABLE($C$114,$F$7,$C121,$F$13,H$114) -> 0.029600254 | I121: =TABLE($C$114,$F$7,$C121,$F$13,I$114) -> 0.040149237 | J121: =TABLE($C$114,$F$7,$C121,$F$13,J$114) -> 0.05069822 | K121: =TABLE($C$114,$F$7,$C121,$F$13,K$114) -> 0.061247202 | L121: =TABLE($C$114,$F$7,$C121,$F$13,L$114) -> 0.071796185
C122: =C107 -> 75 | D122: =TABLE($C$114,$F$7,$C122,$F$13,D$114) -> 0.0055332395 | E122: =TABLE($C$114,$F$7,$C122,$F$13,E$114) -> 0.016136247 | F122: =TABLE($C$114,$F$7,$C122,$F$13,F$114) -> 0.026739254 | G122: =TABLE($C$114,$F$7,$C122,$F$13,G$114) -> 0.037342261 | H122: =TABLE($C$114,$F$7,$C122,$F$13,H$114) -> 0.047945268 | I122: =TABLE($C$114,$F$7,$C122,$F$13,I$114) -> 0.058548276 | J122: =TABLE($C$114,$F$7,$C122,$F$13,J$114) -> 0.069151283 | K122: =TABLE($C$114,$F$7,$C122,$F$13,K$114) -> 0.07975429 | L122: =TABLE($C$114,$F$7,$C122,$F$13,L$114) -> 0.090357297
C123: =C108 -> 70 | D123: =TABLE($C$114,$F$7,$C123,$F$13,D$114) -> 0.023848799 | E123: =TABLE($C$114,$F$7,$C123,$F$13,E$114) -> 0.034506387 | F123: =TABLE($C$114,$F$7,$C123,$F$13,F$114) -> 0.045163975 | G123: =TABLE($C$114,$F$7,$C123,$F$13,G$114) -> 0.055821563 | H123: =TABLE($C$114,$F$7,$C123,$F$13,H$114) -> 0.066479151 | I123: =TABLE($C$114,$F$7,$C123,$F$13,I$114) -> 0.077136739 | J123: =TABLE($C$114,$F$7,$C123,$F$13,J$114) -> 0.087794327 | K123: =TABLE($C$114,$F$7,$C123,$F$13,K$114) -> 0.098451915 | L123: =TABLE($C$114,$F$7,$C123,$F$13,L$114) -> 0.1091095
C124: =C109 -> 65 | D124: =TABLE($C$114,$F$7,$C124,$F$13,D$114) -> 0.042353899 | E124: =TABLE($C$114,$F$7,$C124,$F$13,E$114) -> 0.053066632 | F124: =TABLE($C$114,$F$7,$C124,$F$13,F$114) -> 0.063779366 | G124: =TABLE($C$114,$F$7,$C124,$F$13,G$114) -> 0.074492099 | H124: =TABLE($C$114,$F$7,$C124,$F$13,H$114) -> 0.085204833 | I124: =TABLE($C$114,$F$7,$C124,$F$13,I$114) -> 0.095917567 | J124: =TABLE($C$114,$F$7,$C124,$F$13,J$114) -> 0.1066303 | K124: =TABLE($C$114,$F$7,$C124,$F$13,K$114) -> 0.11734303 | L124: =TABLE($C$114,$F$7,$C124,$F$13,L$114) -> 0.12805577

Sheet Merger-Shares-BS
B2: ="Merger Model - Seller Diluted Share Count & Combined Balance Sheets" -> Merger Model - Seller Diluted Share Count & Combined Balance Sheets
B3: ='AAPL-3-Statements'!B3 -> ($ in Millions, Except Per Share Amounts in Dollars and Share Counts in Thousands)
B5: Diluted Share & Enterprise Value Calculations - Seller
B7: Company Name: | E7: Research in Motion Limited | L7: Options Calculations - Current Price:
B8: Share Price: | E8: 62.91
B9: Offer Price Per Share: | E9: =Purchase_Price -> 75 | G9: Tax Rate: | J9: 0.28 | N9: Exercise
L10: Name | M10: Number | N10: Price | O10: Dilution
B11: Current Share Price: | G11: Purchase Price: | L11: Tranche A | M11: 10470 | N11: 38.57 | O11: =IF(N11>Seller_Share_Price,0,M11-M11*N11/Seller_Share_Price) -> 4050.8631
B12: Basic Shares Outstanding: | E12: 568900 | G12: Basic Shares Outstanding: | J12: =E12 -> 568900 | L12: Tranche B
B13: Basic Equity Value: | E13: =E12/Units*Seller_Share_Price -> 35789.499 | G13: Basic Equity Value: | J13: =J12/Units*E9 -> 42667.5 | L13: Total | O13: =SUM(O11:O12) -> 4050.8631
B14: Diluted Shares Outstanding: | E14: =E12+O13 -> 572950.86 | G14: Diluted Shares Outstanding: | J14: =J12+O21 -> 573985.63
B15: Diluted Equity Value: | E15: =E14/Units*Seller_Share_Price -> 36044.339 | G15: Diluted Equity Value: | J15: =J14/Units*E9 -> 43048.922 | L15: Options Calculations - Purchase Price:
B16: Less: Cash & Investments | E16: =J27+J35 -> 2497.747 | G16: Less: Cash & Investments | J16: =E16 -> 2497.747
B17: Plus: Debt | E17: 0 | G17: Plus: Debt | J17: =E17 -> 0 | N17: Exercise
B18: Plus: Minority Interest | E18: 0 | G18: Plus: Minority Interest | J18: =E18 -> 0 | L18: Name | M18: Number | N18: Price | O18: Dilution
B19: Plus: Preferred Stock | E19: 0 | G19: Plus: Preferred Stock | J19: =E19 -> 0 | L19: Tranche A | M19: 10470 | N19: 38.57 | O19: =IF(N19>E9,0,M19-M19*N19/E9) -> 5085.628
B20: Plus: Other Liabilities | E20: 0 | G20: Plus: Other Liabilities | J20: =E20 -> 0 | L20: Tranche B
B21: Enterprise Value: | E21: =E15-E16+E17+E18+E19+E20 -> 33546.592 | G21: Enterprise Value: | J21: =J15-J16+J17+J18+J19+J20 -> 40551.175 | L21: Total | O21: =SUM(O19:O20) -> 5085.628
B23: Balance Sheets - Buyer, Seller & Combined
B25: Assets: | H25: Buyer | J25: Seller | L25: Adjustments | N25: Combined
B26: Current Assets:
B27: Cash & Short-Term Securities: | H27: ='AAPL-3-Statements'!H99+'AAPL-3-Statements'!H100 -> 32841 | J27: =1083.251+580.921 -> 1664.172 | L27: =-'Merger-Model'!L8 -> -14349.641 | N27: =H27+J27+L27 -> 20155.531
B28: Accounts Receivable: | H28: ='AAPL-3-Statements'!H101 -> 3361 | J28: =2365.106+248.162 -> 2613.268 | L28: 0 | N28: =H28+J28+L28 -> 5974.268
B29: Inventory: | H29: ='AAPL-3-Statements'!H102 -> 455 | J29: 572.761 | L29: 0 | N29: =H29+J29+L29 -> 1027.761
B30: Deferred Tax Assets: | H30: ='AAPL-3-Statements'!H103 -> 4 | J30: 175.568 | L30: 0 | N30: =H30+J30+L30 -> 179.568
B31: Other Current Assets: | H31: ='AAPL-3-Statements'!H104 -> 3140 | J31: 189.676 | L31: 0 | N31: =H31+J31+L31 -> 3329.676
B32: Total Current Assets: | H32: =SUM(H27:H31) -> 39801 | J32: =SUM(J27:J31) -> 5215.445 | L32: =SUM(L27:L31) -> -14349.641 | N32: =SUM(N27:N31) -> 30666.804
B34: Long-Term Assets:
B35: Long-Term Securities: | H35: ='AAPL-3-Statements'!H108 -> 2554 | J35: 833.575 | L35: 0 | N35: =H35+J35+L35 -> 3387.575
B36: Plants, Property & Equipment: | H36: ='AAPL-3-Statements'!H109 -> 2839 | J36: 1737.403 | L36: ='Merger-Model'!L20 -> 173.7403 | N36: =H36+J36+L36 -> 4750.1433
B37: Goodwill: | H37: ='AAPL-3-Statements'!H110 -> 207 | J37: 146.557 | L37: =-'Merger-Model'!F21+'Merger-Model'!F28 -> 30828.179 | N37: =H37+J37+L37 -> 31181.736
B38: Other Intangible Assets: | H38: ='AAPL-3-Statements'!H111 -> 354 | J38: 1291.454 | L38: ='Merger-Model'!L26 -> 7241.7718 | N38: =H38+J38+L38 -> 8887.2258
B39: Other Assets: | H39: ='AAPL-3-Statements'!H112 -> 2011 | J39: 0 | L39: 0 | N39: =H39+J39+L39 -> 2011
B40: Total Assets: | H40: =SUM(H35:H39)+H32 -> 47766 | J40: =SUM(J35:J39)+J32 -> 9224.434 | L40: =SUM(L35:L39)+L32 -> 23894.05 | N40: =SUM(N35:N39)+N32 -> 80884.484
B42: Liabilities & Shareholders' Equity:
B43: Current Liabilities:
B44: Accounts Payable: | H44: ='AAPL-3-Statements'!H117 -> 5601 | J44: 496.005 | L44: 0 | N44: =H44+J44+L44 -> 6097.005
B45: Accrued Expenses: | H45: ='AAPL-3-Statements'!H118 -> 3852 | J45: 1603.842 | L45: 0 | N45: =H45+J45+L45 -> 5455.842
B46: Deferred Revenue: | H46: ='AAPL-3-Statements'!H119 -> 2053 | J46: 66.912 | L46: 0 | N46: =H46+J46+L46 -> 2119.912
B47: Total Current Liabilities: | H47: =SUM(H44:H46) -> 11506 | J47: =SUM(J44:J46) -> 2166.759 | L47: =SUM(L44:L46) -> 0 | N47: =SUM(N44:N46) -> 13672.759
B49: Long-Term Liabilities:
B50: Deferred Revenue: | H50: ='AAPL-3-Statements'!H123 -> 853 | J50: 0 | L50: 0 | N50: =H50+J50+L50 -> 853
B51: Long-Term Debt: | H51: ='AAPL-3-Statements'!H124 -> 0 | J51: 0 | L51: ='Merger-Model'!L9 -> 14349.641 | N51: =H51+J51+L51 -> 14349.641
B52: Deferred Income Tax Liability: | H52: 0 | J52: 43.265 | L52: ='Merger-Model'!F26+'Merger-Model'!F27 -> 2181.3886 | N52: =H52+J52+L52 -> 2224.6536
B53: Other Long-Term Liabilities: | H53: ='AAPL-3-Statements'!H125 -> 3502 | J53: 27.79 | L53: 0 | N53: =H53+J53+L53 -> 3529.79
B54: Total Liabilities: | H54: =SUM(H50:H53)+H47 -> 15861 | J54: =SUM(J50:J53)+J47 -> 2237.814 | L54: =SUM(L50:L53)+L47 -> 16531.029 | N54: =SUM(N50:N53)+N47 -> 34629.843
B56: Shareholders' Equity:
B57: Common Stock: | H57: ='AAPL-3-Statements'!H129 -> 7177 | J57: 2236.19 | L57: =-J57 -> -2236.19 | N57: =H57+J57+L57 -> 7177
B58: Additional Paid-In Capital: | H58: ='AAPL-3-Statements'!H130 -> 1185 | J58: 139.113 | L58: =-J58+'Merger-Model'!F10*'Merger-Model'!L7 -> 14210.528 | N58: =H58+J58+L58 -> 15534.641
B59: Treasury Stock: | H59: ='AAPL-3-Statements'!H131 -> 0 | J59: -45.081 | L59: =-J59 -> 45.081 | N59: =H59+J59+L59 -> 0
B60: Retained Earnings: | H60: ='AAPL-3-Statements'!H132 -> 23364 | J60: 4664.361 | L60: =-J60 -> -4664.361 | N60: =H60+J60+L60 -> 23364
B61: Accumulated Other Comprehensive Income: | H61: ='AAPL-3-Statements'!H133 -> 179 | J61: -7.963 | L61: =-J61 -> 7.963 | N61: =H61+J61+L61 -> 179
B62: Total Shareholders' Equity: | H62: =SUM(H57:H61) -> 31905 | J62: =SUM(J57:J61) -> 6986.62 | L62: =SUM(L57:L61) -> 7363.0207 | N62: =SUM(N57:N61) -> 46254.641
B64: Total Liabilities & SE: | H64: =H62+H54 -> 47766 | J64: =J62+J54 -> 9224.434 | L64: =L62+L54 -> 23894.05 | N64: =N62+N54 -> 80884.484

Sheet Basic-LBO
B2: =Company_Name&" - Basic LBO Model" -> Apple Inc. - Basic LBO Model
B3: ='AAPL-3-Statements'!B3 -> ($ in Millions, Except Per Share Amounts in Dollars and Share Counts in Thousands)
B5: Transaction Assumptions
B7: Current Share Price: | F7: =Share_Price -> 192.06 | H7: Equity Purchase Price: | L7: =F17 -> 212713.43
B8: Offer Premium: | F8: 0.2 | H8: Enterprise Value: | L8: =F23 -> 177318.43
B9: Offer Price Per Share: | F9: =F7*(1+F8) -> 230.472 | H9: EBITDA Purchase Multiple: | L9: =L8/'AAPL-3-Statements'!H91 -> 13.449516
B10: % Debt: | F10: 0.5 | H10: Debt Required: | L10: =F10*L7 -> 106356.71
B11: % Equity: | F11: =1-F10 -> 0.5 | H11: Equity Used: | L11: =F11*L7 -> 106356.71
H12: EBITDA Exit Multiple: | L12: 10
B13: Purchase Price Calculations:
B14: Basic Shares Outstanding: | F14: ='AAPL-3-Statements'!E11 -> 900678.47 | H14: Advisory Fee %: | L14: 0.0002
B15: Basic Equity Value: | F15: =F14/Units*F9 -> 207581.17 | H15: Financing Fee %: | L15: 0.0006
B16: Diluted Shares Outstanding: | F16: =F14+K23 -> 922946.93
B17: Diluted Equity Value: | F17: =F16/Units*F9 -> 212713.43 | H17: Options Calculations - Purchase Price:
B18: Less: Cash & Investments | F18: ='AAPL-3-Statements'!E15 -> 35395
B19: Plus: Debt | F19: ='AAPL-3-Statements'!E16 -> 0 | J19: Exercise
B20: Plus: Minority Interest | F20: ='AAPL-3-Statements'!E17 -> 0 | H20: Name | I20: Number | J20: Price | K20: Dilution
B21: Plus: Preferred Stock | F21: ='AAPL-3-Statements'!E18 -> 0 | H21: Tranche A | I21: ='AAPL-3-Statements'!H15 -> 34375 | J21: ='AAPL-3-Statements'!I15 -> 81.17 | K21: =IF(J21>F9,0,I21-I21*J21/F9) -> 22268.459
B22: Plus: Other Liabilities | F22: ='AAPL-3-Statements'!E19 -> 0 | H22: Tranche B
B23: Enterprise Value: | F23: =F17-F18+F19+F20+F21+F22 -> 177318.43 | H23: Total | K23: =SUM(K21:K22) -> 22268.459
B25: Debt Assumptions
B27: Debt %: | F27: =F10 -> 0.5 | H27: Debt Required: | L27: =L10 -> 106356.71
B28: Bank Debt %: | F28: 0.75 | H28: Bank Debt: | L28: =F28*L27 -> 79767.534
B29: High-Yield Debt %: | F29: =1-F28 -> 0.25 | H29: High-Yield Debt: | L29: =F29*L27 -> 26589.178
B31: Bank Debt Interest Rate: | F31: 0.08 | H31: Bank Debt Principal Repayment %: | L31: 0.1
B32: High-Yield Debt Interest Rate: | F32: 0.11 | H32: High-Yield Debt Principal Repayment %: | L32: 0
B34: Sources & Uses
B36: Sources: | H36: Uses:
B37: Bank Debt: | F37: =L28 -> 79767.534 | H37: Equity Value of Company: | L37: =L7 -> 212713.43
B38: High-Yield Debt: | F38: =L29 -> 26589.178 | H38: Advisory Fees: | L38: =L14*L7 -> 42.542685
B39: Investor Equity: | F39: =L40-SUM(F37:F38) -> 106463.07 | H39: Financing Fees: | L39: =L15*L10 -> 63.814028
B40: Total Sources: | F40: =SUM(F37:F39) -> 212819.78 | H40: Total Uses: | L40: =SUM(L37:L39) -> 212819.78
B42: Operating Assumptions
B44: Initial Cash Balance: | F44: ='AAPL-3-Statements'!H99 -> 6559
B45: Minimum Cash Balance: | F45: 5000
F47: ='AAPL-3-Statements'!F22 -> Historical | I47: ='AAPL-3-Statements'!I22 -> Projections
F48: ='AAPL-3-Statements'!F24 -> FY 2007 | G48: ='AAPL-3-Statements'!G24 -> FY 2008 | H48: ='AAPL-3-Statements'!H24 -> FY 2009 | I48: ='AAPL-3-Statements'!I24 -> FY 2010E | J48: ='AAPL-3-Statements'!J24 -> FY 2011E | K48: ='AAPL-3-Statements'!K24 -> FY 2012E | L48: ='AAPL-3-Statements'!L24 -> FY 2013E | M48: ='AAPL-3-Statements'!M24 -> FY 2014E
B50: Revenue Growth %: | F50: ='AAPL-3-Statements'!F39 -> 0.27248253 | G50: ='AAPL-3-Statements'!G39 -> 0.52538856 | H50: ='AAPL-3-Statements'!H39 -> 0.14440799 | I50: ='AAPL-3-Statements'!I39 -> 0.25 | J50: ='AAPL-3-Statements'!J39 -> 0.17 | K50: ='AAPL-3-Statements'!K39 -> 0.11 | L50: ='AAPL-3-Statements'!L39 -> 0.09 | M50: ='AAPL-3-Statements'!M39 -> 0.07
B51: COGS % Revenue: | F51: ='AAPL-3-Statements'!F40 -> 0.66246236 | G51: ='AAPL-3-Statements'!G40 -> 0.64145173 | H51: ='AAPL-3-Statements'!H40 -> 0.59024201 | I51: ='AAPL-3-Statements'!I40 -> 0.59024201 | J51: ='AAPL-3-Statements'!J40 -> 0.59024201 | K51: ='AAPL-3-Statements'!K40 -> 0.59024201 | L51: ='AAPL-3-Statements'!L40 -> 0.59024201 | M51: ='AAPL-3-Statements'!M40 -> 0.59024201
B52: R&D % Revenue: | F52: ='AAPL-3-Statements'!F41 -> 0.024249329 | G52: ='AAPL-3-Statements'!G41 -> 0.020235968 | H52: ='AAPL-3-Statements'!H41 -> 0.019352834 | I52: ='AAPL-3-Statements'!I41 -> 0.019352834 | J52: ='AAPL-3-Statements'!J41 -> 0.019352834 | K52: ='AAPL-3-Statements'!K41 -> 0.019352834 | L52: ='AAPL-3-Statements'!L41 -> 0.019352834 | M52: ='AAPL-3-Statements'!M41 -> 0.019352834
B53: SG&A % Revenue: | F53: ='AAPL-3-Statements'!F42 -> 0.11083082 | G53: ='AAPL-3-Statements'!G42 -> 0.089212522 | H53: ='AAPL-3-Statements'!H42 -> 0.083121625 | I53: ='AAPL-3-Statements'!I42 -> 0.083121625 | J53: ='AAPL-3-Statements'!J42 -> 0.083121625 | K53: ='AAPL-3-Statements'!K42 -> 0.083121625 | L53: ='AAPL-3-Statements'!L42 -> 0.083121625 | M53: ='AAPL-3-Statements'!M42 -> 0.083121625
B55: Stock-Based Compensation % Revenue: | F55: ='AAPL-3-Statements'!F44 -> 0.0098462039 | G55: ='AAPL-3-Statements'!G44 -> 0.013763303 | H55: ='AAPL-3-Statements'!H44 -> 0.016548188 | I55: ='AAPL-3-Statements'!I44 -> 0.016548188 | J55: ='AAPL-3-Statements'!J44 -> 0.016548188 | K55: ='AAPL-3-Statements'!K44 -> 0.016548188 | L55: ='AAPL-3-Statements'!L44 -> 0.016548188 | M55: ='AAPL-3-Statements'!M44 -> 0.016548188
B56: Depreciation & Amortization % Revenue: | F56: ='AAPL-3-Statements'!F45 -> 0.013304581 | G56: ='AAPL-3-Statements'!G45 -> 0.013229842 | H56: ='AAPL-3-Statements'!H45 -> 0.017107563 | I56: ='AAPL-3-Statements'!I45 -> 0.017107563 | J56: ='AAPL-3-Statements'!J45 -> 0.017107563 | K56: ='AAPL-3-Statements'!K45 -> 0.017107563 | L56: ='AAPL-3-Statements'!L45 -> 0.017107563 | M56: ='AAPL-3-Statements'!M45 -> 0.017107563
B57: Effective Cash Interest Rate: | F57: ='AAPL-3-Statements'!F46 -> 0.0527 | G57: ='AAPL-3-Statements'!G46 -> 0.0344 | H57: ='AAPL-3-Statements'!H46 -> 0.0143 | I57: ='AAPL-3-Statements'!I46 -> 0.01 | J57: ='AAPL-3-Statements'!J46 -> 0.01 | K57: ='AAPL-3-Statements'!K46 -> 0.02 | L57: ='AAPL-3-Statements'!L46 -> 0.02 | M57: ='AAPL-3-Statements'!M46 -> 0.03
B58: Effective Tax Rate: | F58: ='AAPL-3-Statements'!F48 -> 0.30183779 | G58: ='AAPL-3-Statements'!G48 -> 0.3160836 | H58: ='AAPL-3-Statements'!H48 -> 0.31750373 | I58: ='AAPL-3-Statements'!I48 -> 0.3 | J58: ='AAPL-3-Statements'!J48 -> 0.3 | K58: ='AAPL-3-Statements'!K48 -> 0.3 | L58: ='AAPL-3-Statements'!L48 -> 0.3 | M58: ='AAPL-3-Statements'!M48 -> 0.3
B60: Amortization of Intangibles: | I60: ='AAPL-3-Statements'!I53 -> 40 | J60: ='AAPL-3-Statements'!J53 -> 37 | K60: ='AAPL-3-Statements'!K53 -> 28 | L60: ='AAPL-3-Statements'!L53 -> 13 | M60: ='AAPL-3-Statements'!M53 -> 10
B61: Change in Working Capital % Revenue: | F61: =SUM('AAPL-3-Statements'!F150:F156)/'AAPL-3-Statements'!F66 -> 0.053747254 | G61: =SUM('AAPL-3-Statements'!G150:G156)/'AAPL-3-Statements'!G66 -> 0.054546424 | H61: =SUM('AAPL-3-Statements'!H150:H156)/'AAPL-3-Statements'!H66 -> 0.016548188 | I61: =SUM('AAPL-3-Statements'!I150:I156)/'AAPL-3-Statements'!I66 -> 0.039822864 | J61: =SUM('AAPL-3-Statements'!J150:J156)/'AAPL-3-Statements'!J66 -> 0.028931141 | K61: =SUM('AAPL-3-Statements'!K150:K156)/'AAPL-3-Statements'!K66 -> 0.01973205 | L61: =SUM('AAPL-3-Statements'!L150:L156)/'AAPL-3-Statements'!L66 -> 0.016440632 | M61: =SUM('AAPL-3-Statements'!M150:M156)/'AAPL-3-Statements'!M66 -> 0.013026171
B62: CapEx % Revenue: | F62: ='AAPL-3-Statements'!F61 -> 0.029904793 | G62: ='AAPL-3-Statements'!G61 -> 0.029100317 | H62: ='AAPL-3-Statements'!H61 -> 0.026663559 | I62: ='AAPL-3-Statements'!I61 -> 0.026663559 | J62: ='AAPL-3-Statements'!J61 -> 0.026663559 | K62: ='AAPL-3-Statements'!K61 -> 0.026663559 | L62: ='AAPL-3-Statements'!L61 -> 0.026663559 | M62: ='AAPL-3-Statements'!M61 -> 0.026663559
B64: Income Statement
F65: =$F$48 -> FY 2007 | G65: =$G$48 -> FY 2008 | H65: =$H$48 -> FY 2009 | I65: =$I$48 -> FY 2010E | J65: =$J$48 -> FY 2011E | K65: =$K$48 -> FY 2012E | L65: =$L$48 -> FY 2013E | M65: =$M$48 -> FY 2014E
B67: Revenue: | F67: ='AAPL-3-Statements'!F66 -> 24578 | G67: ='AAPL-3-Statements'!G66 -> 37491 | H67: ='AAPL-3-Statements'!H66 -> 42905 | I67: =H67*(1+I50) -> 53631.25 | J67: =I67*(1+J50) -> 62748.562 | K67: =J67*(1+K50) -> 69650.904 | L67: =K67*(1+L50) -> 75919.486 | M67: =L67*(1+M50) -> 81233.85
B68: Cost of Goods Sold: | F68: ='AAPL-3-Statements'!F67 -> 16282 | G68: ='AAPL-3-Statements'!G67 -> 24048.667 | H68: ='AAPL-3-Statements'!H67 -> 25324.333 | I68: =I67*I51 -> 31655.417 | J68: =J67*J51 -> 37036.838 | K68: =K67*K51 -> 41110.89 | L68: =L67*L51 -> 44810.87 | M68: =M67*M51 -> 47947.631
B69: Gross Profit: | F69: =F67-F68 -> 8296 | G69: =G67-G68 -> 13442.333 | H69: =H67-H68 -> 17580.667 | I69: =I67-I68 -> 21975.833 | J69: =J67-J68 -> 25711.725 | K69: =K67-K68 -> 28540.015 | L69: =L67-L68 -> 31108.616 | M69: =M67-M68 -> 33286.219
B70: Operating Expenses:
B71: Research & Development: | F71: ='AAPL-3-Statements'!F70 -> 596 | G71: ='AAPL-3-Statements'!G70 -> 758.66667 | H71: ='AAPL-3-Statements'!H70 -> 830.33333 | I71: =I67*I52 -> 1037.9167 | J71: =J67*J52 -> 1214.3625 | K71: =K67*K52 -> 1347.9424 | L71: =L67*L52 -> 1469.2572 | M71: =M67*M52 -> 1572.1052
B72: Selling, General & Administrative: | F72: ='AAPL-3-Statements'!F71 -> 2724 | G72: ='AAPL-3-Statements'!G71 -> 3344.6667 | H72: ='AAPL-3-Statements'!H71 -> 3566.3333 | I72: =I67*I53 -> 4457.9167 | J72: =J67*J53 -> 5215.7625 | K72: =K67*K53 -> 5789.4964 | L72: =L67*L53 -> 6310.551 | M72: =M67*M53 -> 6752.2896
B73: Total Operating Expenses: | F73: =SUM(F71:F72) -> 3320 | G73: =SUM(G71:G72) -> 4103.3333 | H73: =SUM(H71:H72) -> 4396.6667 | I73: =SUM(I71:I72) -> 5495.8333 | J73: =SUM(J71:J72) -> 6430.125 | K73: =SUM(K71:K72) -> 7137.4388 | L73: =SUM(L71:L72) -> 7779.8082 | M73: =SUM(M71:M72) -> 8324.3948
B75: Depreciation & Amortization of PP&E: | F75: ='AAPL-3-Statements'!F74 -> 327 | G75: ='AAPL-3-Statements'!G74 -> 496 | H75: ='AAPL-3-Statements'!H74 -> 734 | I75: =I67*I56 -> 917.5 | J75: =J67*J56 -> 1073.475 | K75: =K67*K56 -> 1191.5573 | L75: =L67*L56 -> 1298.7974 | M75: =M67*M56 -> 1389.7132
B76: Amortization of Intangibles: | F76: ='AAPL-3-Statements'!F75 -> 0 | G76: ='AAPL-3-Statements'!G75 -> 0 | H76: ='AAPL-3-Statements'!H75 -> 0 | I76: =I60 -> 40 | J76: =J60 -> 37 | K76: =K60 -> 28 | L76: =L60 -> 13 | M76: =M60 -> 10
B77: Stock-Based Compensation: | F77: ='AAPL-3-Statements'!F76 -> 242 | G77: ='AAPL-3-Statements'!G76 -> 516 | H77: ='AAPL-3-Statements'!H76 -> 710 | I77: =I67*I55 -> 887.5 | J77: =J67*J55 -> 1038.375 | K77: =K67*K55 -> 1152.5963 | L77: =L67*L55 -> 1256.3299 | M77: =M67*M55 -> 1344.273
B79: Operating Income: | F79: =F69-F73-F75-F76-F77 -> 4407 | G79: =G69-G73-G75-G76-G77 -> 8327 | H79: =H69-H73-H75-H76-H77 -> 11740 | I79: =I69-I73-I75-I76-I77 -> 14635 | J79: =J69-J73-J75-J76-J77 -> 17132.75 | K79: =K69-K73-K75-K76-K77 -> 19030.423 | L79: =L69-L73-L75-L76-L77 -> 20760.681 | M79: =M69-M73-M75-M76-M77 -> 22217.838
B80: Interest Income / (Expense): | F80: =SUM('AAPL-3-Statements'!F79:F81) -> 599 | G80: =SUM('AAPL-3-Statements'!G79:G81) -> 620 | H80: =SUM('AAPL-3-Statements'!H79:H81) -> 326 | I80: =I128 -> -8627.4561 | J80: =J128 -> -7953.9994 | K80: =K128 -> -6850.3728 | L80: =L128 -> -5947.3017 | M80: =M128 -> -4562.6961
B81: Pre-Tax Income: | F81: =SUM(F79:F80) -> 5006 | G81: =SUM(G79:G80) -> 8947 | H81: =SUM(H79:H80) -> 12066 | I81: =SUM(I79:I80) -> 6007.5439 | J81: =SUM(J79:J80) -> 9178.7506 | K81: =SUM(K79:K80) -> 12180.05 | L81: =SUM(L79:L80) -> 14813.379 | M81: =SUM(M79:M80) -> 17655.142
B82: Income Tax Provision: | F82: ='AAPL-3-Statements'!F83 -> 1511 | G82: ='AAPL-3-Statements'!G83 -> 2828 | H82: ='AAPL-3-Statements'!H83 -> 3831 | I82: =I81*I58 -> 1802.2632 | J82: =J81*J58 -> 2753.6252 | K82: =K81*K58 -> 3654.0149 | L82: =L81*L58 -> 4444.0136 | M82: =M81*M58 -> 5296.5426
B84: Net Income: | F84: =F81-F82 -> 3495 | G84: =G81-G82 -> 6119 | H84: =H81-H82 -> 8235 | I84: =I81-I82 -> 4205.2807 | J84: =J81-J82 -> 6425.1254 | K84: =K81-K82 -> 8526.0348 | L84: =L81-L82 -> 10369.365 | M84: =M81-M82 -> 12358.599
B85: EBITDA: | F85: =F79+F77+F76+F75 -> 4976 | G85: =G79+G77+G76+G75 -> 9339 | H85: =H79+H77+H76+H75 -> 13184 | I85: =I79+I77+I76+I75 -> 16480 | J85: =J79+J77+J76+J75 -> 19281.6 | K85: =K79+K77+K76+K75 -> 21402.576 | L85: =L79+L77+L76+L75 -> 23328.808 | M85: =M79+M77+M76+M75 -> 24961.824
B87: Cash Flow Statement
F88: =$F$48 -> FY 2007 | G88: =$G$48 -> FY 2008 | H88: =$H$48 -> FY 2009 | I88: =$I$48 -> FY 2010E | J88: =$J$48 -> FY 2011E | K88: =$K$48 -> FY 2012E | L88: =$L$48 -> FY 2013E | M88: =$M$48 -> FY 2014E
B89: Operating Activities:
B90: Net Income: | I90: =I84 -> 4205.2807 | J90: =J84 -> 6425.1254 | K90: =K84 -> 8526.0348 | L90: =L84 -> 10369.365 | M90: =M84 -> 12358.599
B91: Depreciation & Amortization of PP&E: | I91: =I75 -> 917.5 | J91: =J75 -> 1073.475 | K91: =K75 -> 1191.5573 | L91: =L75 -> 1298.7974 | M91: =M75 -> 1389.7132
B92: Amortization of Intangibles: | I92: =I76 -> 40 | J92: =J76 -> 37 | K92: =K76 -> 28 | L92: =L76 -> 13 | M92: =M76 -> 10
B93: Stock-Based Compensation: | I93: =I77 -> 887.5 | J93: =J77 -> 1038.375 | K93: =K77 -> 1152.5963 | L93: =L77 -> 1256.3299 | M93: =M77 -> 1344.273
B94: Decrease (Increase) in Working Capital: | I94: =I67*I61 -> 2135.75 | J94: =J67*J61 -> 1815.3875 | K94: =K67*K61 -> 1374.3551 | L94: =L67*L61 -> 1248.1643 | M94: =M67*M61 -> 1058.166
B95: Cash Flow from Operations: | I95: =SUM(I90:I94) -> 8186.0307 | J95: =SUM(J90:J94) -> 10389.363 | K95: =SUM(K90:K94) -> 12272.543 | L95: =SUM(L90:L94) -> 14185.657 | M95: =SUM(M90:M94) -> 16160.752
B97: Capital Expenditures: | I97: =-I67*I62 -> -1430 | J97: =-J67*J62 -> -1673.1 | K97: =-K67*K62 -> -1857.141 | L97: =-L67*L62 -> -2024.2837 | M97: =-M67*M62 -> -2165.9835
B99: Free Cash Flow: | I99: =I95+I97 -> 6756.0307 | J99: =J95+J97 -> 8716.2629 | K99: =K95+K97 -> 10415.402 | L99: =L95+L97 -> 12161.373 | M99: =M95+M97 -> 13994.768
B101: Beginning Cash Balance: | I101: =F44 -> 6559 | J101: =I110 -> 5000 | K101: =J110 -> 5000 | L101: =K110 -> 5000 | M101: =L110 -> 5000
B102: Plus: Free Cash Flow: | I102: =I99 -> 6756.0307 | J102: =J99 -> 8716.2629 | K102: =K99 -> 10415.402 | L102: =L99 -> 12161.373 | M102: =M99 -> 13994.768
B103: Less: Minimum Cash Balance: | I103: =-$F$45 -> -5000 | J103: =-$F$45 -> -5000 | K103: =-$F$45 -> -5000 | L103: =-$F$45 -> -5000 | M103: =-$F$45 -> -5000
B105: Cash Available for Debt Repayment: | I105: =I101+I102+I103 -> 8315.0307 | J105: =J101+J102+J103 -> 8716.2629 | K105: =K101+K102+K103 -> 10415.402 | L105: =L101+L102+L103 -> 12161.373 | M105: =M101+M102+M103 -> 13994.768
B106: Cash Used for Debt Repayment: | I106: =I116+I117+I121+I122 -> -8315.0307 | J106: =J116+J117+J121+J122 -> -8716.2629 | K106: =K116+K117+K121+K122 -> -10415.402 | L106: =L116+L117+L121+L122 -> -12161.373 | M106: =M116+M117+M121+M122 -> -13994.768
B108: Beginning Cash Balance: | I108: =I101 -> 6559 | J108: =J101 -> 5000 | K108: =K101 -> 5000 | L108: =L101 -> 5000 | M108: =M101 -> 5000
B109: Net Change in Cash: | I109: =I106+I102 -> -1559 | J109: =J106+J102 -> 0 | K109: =K106+K102 -> 0 | L109: =L106+L102 -> 0 | M109: =M106+M102 -> 0
B110: Ending Cash Balance: | I110: =SUM(I108:I109) -> 5000 | J110: =SUM(J108:J109) -> 5000 | K110: =SUM(K108:K109) -> 5000 | L110: =SUM(L108:L109) -> 5000 | M110: =SUM(M108:M109) -> 5000
B112: Debt & Interest Schedules
F113: =$F$48 -> FY 2007 | G113: =$G$48 -> FY 2008 | H113: =$H$48 -> FY 2009 | I113: =$I$48 -> FY 2010E | J113: =$J$48 -> FY 2011E | K113: =$K$48 -> FY 2012E | L113: =$L$48 -> FY 2013E | M113: =$M$48 -> FY 2014E
B115: Beginning Bank Debt: | I115: =L28 -> 79767.534 | J115: =I118 -> 71452.504 | K115: =J118 -> 62736.241 | L115: =K118 -> 52320.838 | M115: =L118 -> 40159.465
B116: Mandatory Repayment: | I116: =-MIN($L$31*$L$28,I115) -> -7976.7534 | J116: =-MIN($L$31*$L$28,J115) -> -7976.7534 | K116: =-MIN($L$31*$L$28,K115) -> -7976.7534 | L116: =-MIN($L$31*$L$28,L115) -> -7976.7534 | M116: =-MIN($L$31*$L$28,M115) -> -7976.7534
B117: Optional Repayment: | I117: =-MIN(I105+I116,I115+I116) -> -338.27726 | J117: =-MIN(J105+J116,J115+J116) -> -739.50948 | K117: =-MIN(K105+K116,K115+K116) -> -2438.649 | L117: =-MIN(L105+L116,L115+L116) -> -4184.6197 | M117: =-MIN(M105+M116,M115+M116) -> -6018.0147
B118: Ending Bank Debt: | I118: =SUM(I115:I117) -> 71452.504 | J118: =SUM(J115:J117) -> 62736.241 | K118: =SUM(K115:K117) -> 52320.838 | L118: =SUM(L115:L117) -> 40159.465 | M118: =SUM(M115:M117) -> 26164.697
B120: Beginning High-Yield Debt: | I120: =L29 -> 26589.178 | J120: =I123 -> 26589.178 | K120: =J123 -> 26589.178 | L120: =K123 -> 26589.178 | M120: =L123 -> 26589.178
B121: Mandatory Repayment: | I121: =-MIN($L$29*$L$32,I120) -> 0 | J121: =-MIN($L$29*$L$32,J120) -> 0 | K121: =-MIN($L$29*$L$32,K120) -> 0 | L121: =-MIN($L$29*$L$32,L120) -> 0 | M121: =-MIN($L$29*$L$32,M120) -> 0
B122: Optional Repayment: | I122: 0 | J122: =I122 -> 0 | K122: =J122 -> 0 | L122: =K122 -> 0 | M122: =L122 -> 0
B123: Ending High-Yield Debt: | I123: =SUM(I120:I122) -> 26589.178 | J123: =SUM(J120:J122) -> 26589.178 | K123: =SUM(K120:K122) -> 26589.178 | L123: =SUM(L120:L122) -> 26589.178 | M123: =SUM(M120:M122) -> 26589.178
B125: Interest Paid on Debt: | I125: =-AVERAGE(I115,I118)*$F$31-AVERAGE(I120,I123)*$F$32 -> -8973.6111 | J125: =-AVERAGE(J115,J118)*$F$31-AVERAGE(J120,J123)*$F$32 -> -8292.3594 | K125: =-AVERAGE(K115,K118)*$F$31-AVERAGE(K120,K123)*$F$32 -> -7527.0928 | L125: =-AVERAGE(L115,L118)*$F$31-AVERAGE(L120,L123)*$F$32 -> -6624.0217 | M125: =-AVERAGE(M115,M118)*$F$31-AVERAGE(M120,M123)*$F$32 -> -5577.7761
B126: Interest Earned on Cash: | I126: =AVERAGE(I108,I110)*I57+AVERAGE('AAPL-3-Statements'!H100+'AAPL-3-Statements'!H108,'AAPL-3-Statements'!I100+'AAPL-3-Statements'!I108)*'Basic-LBO'!I57 -> 346.155 | J126: =AVERAGE(J108,J110)*J57+AVERAGE('AAPL-3-Statements'!I100+'AAPL-3-Statements'!I108,'AAPL-3-Statements'!J100+'AAPL-3-Statements'!J108)*'Basic-LBO'!J57 -> 338.36 | K126: =AVERAGE(K108,K110)*K57+AVERAGE('AAPL-3-Statements'!J100+'AAPL-3-Statements'!J108,'AAPL-3-Statements'!K100+'AAPL-3-Statements'!K108)*'Basic-LBO'!K57 -> 676.72 | L126: =AVERAGE(L108,L110)*L57+AVERAGE('AAPL-3-Statements'!K100+'AAPL-3-Statements'!K108,'AAPL-3-Statements'!L100+'AAPL-3-Statements'!L108)*'Basic-LBO'!L57 -> 676.72 | M126: =AVERAGE(M108,M110)*M57+AVERAGE('AAPL-3-Statements'!L100+'AAPL-3-Statements'!L108,'AAPL-3-Statements'!M100+'AAPL-3-Statements'!M108)*'Basic-LBO'!M57 -> 1015.08
B128: Net Interest Income / (Expense): | I128: =I126+I125 -> -8627.4561 | J128: =J126+J125 -> -7953.9994 | K128: =K126+K125 -> -6850.3728 | L128: =L126+L125 -> -5947.3017 | M128: =M126+M125 -> -4562.6961
B130: Investor Returns
F131: =$F$48 -> FY 2007 | G131: =$G$48 -> FY 2008 | H131: =$H$48 -> FY 2009 | I131: =$I$48 -> FY 2010E | J131: =$J$48 -> FY 2011E | K131: =$K$48 -> FY 2012E | L131: =$L$48 -> FY 2013E | M131: =$M$48 -> FY 2014E
...

Sheet More-Adv-LBO
B2: =Company_Name&" - More Advanced LBO Model" -> Apple Inc. - More Advanced LBO Model
B3: ='AAPL-3-Statements'!B3 -> ($ in Millions, Except Per Share Amounts in Dollars and Share Counts in Thousands)
B5: Transaction Assumptions
B7: Current Share Price: | F7: =Share_Price -> 192.06 | H7: Equity Purchase Price: | L7: =F17 -> 212713.43
B8: Offer Premium: | F8: 0.2 | H8: Enterprise Value: | L8: =F23 -> 177318.43
B9: Offer Price Per Share: | F9: =F7*(1+F8) -> 230.472 | H9: EBITDA Purchase Multiple: | L9: =L8/H124 -> 13.449516
B10: Leverage Ratio: | F10: 6 | H10: Debt Required: | L10: =F10*H124 -> 79104
H11: Equity Used: | L11: =L7-L10 -> 133609.43
H12: EBITDA Exit Multiple: | L12: 10
B13: Purchase Price Calculations:
B14: Basic Shares Outstanding: | F14: ='AAPL-3-Statements'!E11 -> 900678.47 | H14: Advisory Fee %: | L14: 0.0002
B15: Basic Equity Value: | F15: =F14/Units*F9 -> 207581.17 | H15: Financing Fee %: | L15: 0.0006
B16: Diluted Shares Outstanding: | F16: =F14+K23 -> 922946.93 | H16: Legal & Misc. Fees: | L16: 10
B17: Diluted Equity Value: | F17: =F16/Units*F9 -> 212713.43
B18: Less: Cash & Investments | F18: ='AAPL-3-Statements'!E15 -> 35395 | H18: Options Calculations - Purchase Price:
B19: Plus: Debt | F19: ='AAPL-3-Statements'!E16 -> 0 | J19: Exercise
B20: Plus: Minority Interest | F20: ='AAPL-3-Statements'!E17 -> 0 | H20: Name | I20: Number | J20: Price | K20: Dilution
B21: Plus: Preferred Stock | F21: ='AAPL-3-Statements'!E18 -> 0 | H21: Tranche A | I21: ='AAPL-3-Statements'!H15 -> 34375 | J21: ='AAPL-3-Statements'!I15 -> 81.17 | K21: =IF(J21>F9,0,I21-I21*J21/F9) -> 22268.459
B22: Plus: Other Liabilities | F22: ='AAPL-3-Statements'!E19 -> 0 | H22: Tranche B
B23: Enterprise Value: | F23: =F17-F18+F19+F20+F21+F22 -> 177318.43 | H23: Total | K23: =SUM(K21:K22) -> 22268.459
B25: Debt Assumptions
B27: Leverage Ratio: | F27: =F10 -> 6 | H27: Debt Required: | L27: =L10 -> 79104
B28: Units for LIBOR: | F28: 10000 | H28: Revolver: | L28: 2000
B29: Term Loan A %: | F29: 0.4 | H29: Term Loan A: | L29: =F29*$L$27 -> 31641.6
B30: Term Loan B %: | F30: 0.3 | H30: Term Loan B: | L30: =F30*$L$27 -> 23731.2
B31: Subordinated Note %: | F31: 0.2 | H31: Subordinated Note: | L31: =F31*$L$27 -> 15820.8
B32: PIK Loan %: | F32: 0.1 | H32: PIK Loan: | L32: =F32*$L$27 -> 7910.4
B34: Interest Rates: | H34: Principal Repayment %:
B35: =$H$28 -> Revolver: | F35: 250 | H35: =$H$28 -> Revolver: | L35: N/A
B36: =$H$29 -> Term Loan A: | F36: 350 | H36: =$H$29 -> Term Loan A: | L36: 0.1
B37: =$H$30 -> Term Loan B: | F37: 500 | H37: =$H$30 -> Term Loan B: | L37: 0.05
B38: =$H$31 -> Subordinated Note: | F38: 0.11 | H38: =$H$31 -> Subordinated Note: | L38: 0
B39: =$H$32 -> PIK Loan: | F39: 0.13 | H39: =$H$32 -> PIK Loan: | L39: 0
B41: Sources & Uses
B43: Sources: | H43: Uses:
B44: Excess Cash: | F44: =$F$70-$F$71 -> 1559
B45: =H29 -> Term Loan A: | F45: =L29 -> 31641.6
B46: =H30 -> Term Loan B: | F46: =L30 -> 23731.2 | H46: Equity Value of Company: | L46: =L7 -> 212713.43
B47: =H31 -> Subordinated Note: | F47: =L31 -> 15820.8 | H47: Advisory Fees: | L47: =L14*L7 -> 42.542685
B48: =H32 -> PIK Loan: | F48: =L32 -> 7910.4 | H48: Capitalized Financing Fees: | L48: =(L27+L28)*L15 -> 48.6624
B49: Investor Equity: | F49: =L50-SUM(F44:F48) -> 132151.63 | H49: Legal & Misc. Fees: | L49: =L16 -> 10
B50: Total Sources: | F50: =SUM(F44:F49) -> 212814.63 | H50: Total Uses: | L50: =SUM(L46:L49) -> 212814.63
B52: Goodwill Creation & Balance Sheet Adjustments
B54: Goodwill Calculation: | H54: Fixed Asset Write-Up:
B55: Equity Purchase Price: | F55: =L7 -> 212713.43 | H55: PP&E Write-Up %: | L55: 0.1
B56: Less: Seller Book Value: | F56: =-H174 -> -31905 | H56: PP&E Write-Up Amount: | L56: =L55*H141 -> 283.9
B57: Plus: Write-Off of Existing Goodwill: | F57: =H142 -> 207 | H57: Depreciation Period (Years): | L57: 8
B58: Total Allocable Purchase Premium: | F58: =F55+F56+F57 -> 181015.43
H59: Intangible Asset Write-Up:
B60: Less: Write-Up of PP&E: | F60: =-L56 -> -283.9 | H60: Purchase Price to Allocate: | L60: =F58 -> 181015.43
B61: Less: Write-Up of Intangibles: | F61: =-L62 -> -36203.085 | H61: % Allocated to Intangibles: | L61: 0.2
B62: Less: Write-Down of DTL: | F62: 0 | H62: Intangibles Write-Up Amount: | L62: =L61*L60 -> 36203.085
B63: Plus: New Deferred Tax Liability: | F63: =L66 -> 10946.096 | H63: Amortization Period (Years): | L63: 5
B64: Total Goodwill Created: | F64: =F58+F60+F61+F62+F63 -> 155474.54
B66: Financing Fees Amortization Period: | F66: 5 | H66: New Deferred Tax Liability: | L66: =(L62+L56)*Tax_Rate -> 10946.096
B68: Operating Assumptions
B70: Initial Cash Balance: | F70: ='AAPL-3-Statements'!H99 -> 6559
B71: Minimum Cash Balance: | F71: 5000
F73: ='AAPL-3-Statements'!$F$22 -> Historical | I73: Transaction Adjustments | L73: ='AAPL-3-Statements'!$I$22 -> Projections
F74: ='AAPL-3-Statements'!F24 -> FY 2007 | G74: ='AAPL-3-Statements'!$G$24 -> FY 2008 | H74: ='AAPL-3-Statements'!H24 -> FY 2009 | I74: Debit | J74: Credit | K74: =$H$74 -> FY 2009 | L74: ='AAPL-3-Statements'!$I$24 -> FY 2010E | M74: ='AAPL-3-Statements'!$J$24 -> FY 2011E | N74: ='AAPL-3-Statements'!$K$24 -> FY 2012E | O74: ='AAPL-3-Statements'!$L$24 -> FY 2013E | P74: ='AAPL-3-Statements'!$M$24 -> FY 2014E
B76: Revenue Growth %: | F76: ='AAPL-3-Statements'!F39 -> 0.27248253 | G76: ='AAPL-3-Statements'!G39 -> 0.52538856 | H76: ='AAPL-3-Statements'!H39 -> 0.14440799 | L76: ='AAPL-3-Statements'!I39 -> 0.25 | M76: ='AAPL-3-Statements'!J39 -> 0.17 | N76: ='AAPL-3-Statements'!K39 -> 0.11 | O76: ='AAPL-3-Statements'!L39 -> 0.09 | P76: ='AAPL-3-Statements'!M39 -> 0.07
B77: COGS % Revenue: | F77: ='AAPL-3-Statements'!F40 -> 0.66246236 | G77: ='AAPL-3-Statements'!G40 -> 0.64145173 | H77: ='AAPL-3-Statements'!H40 -> 0.59024201 | L77: ='AAPL-3-Statements'!I40 -> 0.59024201 | M77: ='AAPL-3-Statements'!J40 -> 0.59024201 | N77: ='AAPL-3-Statements'!K40 -> 0.59024201 | O77: ='AAPL-3-Statements'!L40 -> 0.59024201 | P77: ='AAPL-3-Statements'!M40 -> 0.59024201
B78: R&D % Revenue: | F78: ='AAPL-3-Statements'!F41 -> 0.024249329 | G78: ='AAPL-3-Statements'!G41 -> 0.020235968 | H78: ='AAPL-3-Statements'!H41 -> 0.019352834 | L78: ='AAPL-3-Statements'!I41 -> 0.019352834 | M78: ='AAPL-3-Statements'!J41 -> 0.019352834 | N78: ='AAPL-3-Statements'!K41 -> 0.019352834 | O78: ='AAPL-3-Statements'!L41 -> 0.019352834 | P78: ='AAPL-3-Statements'!M41 -> 0.019352834
B79: SG&A % Revenue: | F79: ='AAPL-3-Statements'!F42 -> 0.11083082 | G79: ='AAPL-3-Statements'!G42 -> 0.089212522 | H79: ='AAPL-3-Statements'!H42 -> 0.083121625 | L79: ='AAPL-3-Statements'!I42 -> 0.083121625 | M79: ='AAPL-3-Statements'!J42 -> 0.083121625 | N79: ='AAPL-3-Statements'!K42 -> 0.083121625 | O79: ='AAPL-3-Statements'!L42 -> 0.083121625 | P79: ='AAPL-3-Statements'!M42 -> 0.083121625
B81: Stock-Based Compensation % Revenue: | F81: ='AAPL-3-Statements'!F44 -> 0.0098462039 | G81: ='AAPL-3-Statements'!G44 -> 0.013763303 | H81: ='AAPL-3-Statements'!H44 -> 0.016548188 | L81: ='AAPL-3-Statements'!I44 -> 0.016548188 | M81: ='AAPL-3-Statements'!J44 -> 0.016548188 | N81: ='AAPL-3-Statements'!K44 -> 0.016548188 | O81: ='AAPL-3-Statements'!L44 -> 0.016548188 | P81: ='AAPL-3-Statements'!M44 -> 0.016548188
B82: Depreciation & Amortization % Revenue: | F82: ='AAPL-3-Statements'!F45 -> 0.013304581 | G82: ='AAPL-3-Statements'!G45 -> 0.013229842 | H82: ='AAPL-3-Statements'!H45 -> 0.017107563 | L82: ='AAPL-3-Statements'!I45 -> 0.017107563 | M82: ='AAPL-3-Statements'!J45 -> 0.017107563 | N82: ='AAPL-3-Statements'!K45 -> 0.017107563 | O82: ='AAPL-3-Statements'!L45 -> 0.017107563 | P82: ='AAPL-3-Statements'!M45 -> 0.017107563
B83: Effective Cash Interest Rate: | F83: ='AAPL-3-Statements'!F46 -> 0.0527 | G83: ='AAPL-3-Statements'!G46 -> 0.0344 | H83: ='AAPL-3-Statements'!H46 -> 0.0143 | L83: ='AAPL-3-Statements'!I46 -> 0.01 | M83: ='AAPL-3-Statements'!J46 -> 0.01 | N83: ='AAPL-3-Statements'!K46 -> 0.02 | O83: ='AAPL-3-Statements'!L46 -> 0.02 | P83: ='AAPL-3-Statements'!M46 -> 0.03
B84: Effective Tax Rate: | F84: ='AAPL-3-Statements'!F48 -> 0.30183779 | G84: ='AAPL-3-Statements'!G48 -> 0.3160836 | H84: ='AAPL-3-Statements'!H48 -> 0.31750373 | L84: ='AAPL-3-Statements'!I48 -> 0.3 | M84: ='AAPL-3-Statements'!J48 -> 0.3 | N84: ='AAPL-3-Statements'!K48 -> 0.3 | O84: ='AAPL-3-Statements'!L48 -> 0.3 | P84: ='AAPL-3-Statements'!M48 -> 0.3
B86: Accounts Receivable % Revenue: | G86: ='AAPL-3-Statements'!G50 -> 0.064602171 | H86: ='AAPL-3-Statements'!H50 -> 0.078335858 | L86: ='AAPL-3-Statements'!I50 -> 0.078335858 | M86: ='AAPL-3-Statements'!J50 -> 0.078335858 | N86: ='AAPL-3-Statements'!K50 -> 0.078335858 | O86: ='AAPL-3-Statements'!L50 -> 0.078335858 | P86: ='AAPL-3-Statements'!M50 -> 0.078335858
B87: Accounts Receivable Days: | G87: ='AAPL-3-Statements'!G51 -> 23.256782 | H87: ='AAPL-3-Statements'!H51 -> 28.200909 | L87: ='AAPL-3-Statements'!I51 -> 28.200909 | M87: ='AAPL-3-Statements'!J51 -> 28.200909 | N87: ='AAPL-3-Statements'!K51 -> 28.200909 | O87: ='AAPL-3-Statements'!L51 -> 28.200909 | P87: ='AAPL-3-Statements'!M51 -> 28.200909
B88: Inventory % COGS: | G88: ='AAPL-3-Statements'!G52 -> 0.021165415 | H88: ='AAPL-3-Statements'!H52 -> 0.017966909 | L88: ='AAPL-3-Statements'!I52 -> 0.017966909 | M88: ='AAPL-3-Statements'!J52 -> 0.017966909 | N88: ='AAPL-3-Statements'!K52 -> 0.017966909 | O88: ='AAPL-3-Statements'!L52 -> 0.017966909 | P88: ='AAPL-3-Statements'!M52 -> 0.017966909
B89: Amortization of Intangibles: | L89: ='AAPL-3-Statements'!I53 -> 40 | M89: ='AAPL-3-Statements'!J53 -> 37 | N89: ='AAPL-3-Statements'!K53 -> 28 | O89: ='AAPL-3-Statements'!L53 -> 13 | P89: ='AAPL-3-Statements'!M53 -> 10
B91: Accounts Payable % COGS: | G91: ='AAPL-3-Statements'!G55 -> 0.22953455 | H91: ='AAPL-3-Statements'!H55 -> 0.22117068 | L91: ='AAPL-3-Statements'!I55 -> 0.22117068 | M91: ='AAPL-3-Statements'!J55 -> 0.22117068 | N91: ='AAPL-3-Statements'!K55 -> 0.22117068 | O91: ='AAPL-3-Statements'!L55 -> 0.22117068 | P91: ='AAPL-3-Statements'!M55 -> 0.22117068
B92: Accounts Payable Days: | G92: ='AAPL-3-Statements'!G56 -> 82.63244 | H92: ='AAPL-3-Statements'!H56 -> 79.621444 | L92: ='AAPL-3-Statements'!I56 -> 79.621444 | M92: ='AAPL-3-Statements'!J56 -> 79.621444 | N92: ='AAPL-3-Statements'!K56 -> 79.621444 | O92: ='AAPL-3-Statements'!L56 -> 79.621444 | P92: ='AAPL-3-Statements'!M56 -> 79.621444
B93: Accrued Expenses % Operating Expenses: | G93: ='AAPL-3-Statements'!G57 -> 1.029407 | H93: ='AAPL-3-Statements'!H57 -> 0.87611827 | L93: ='AAPL-3-Statements'!I57 -> 0.87611827 | M93: ='AAPL-3-Statements'!J57 -> 0.87611827 | N93: ='AAPL-3-Statements'!K57 -> 0.87611827 | O93: ='AAPL-3-Statements'!L57 -> 0.87611827 | P93: ='AAPL-3-Statements'!M57 -> 0.87611827
B94: Short-Term Deferred Revenue % Revenue: | G94: ='AAPL-3-Statements'!G58 -> 0.043130351 | H94: ='AAPL-3-Statements'!H58 -> 0.047849901 | L94: ='AAPL-3-Statements'!I58 -> 0.047849901 | M94: ='AAPL-3-Statements'!J58 -> 0.047849901 | N94: ='AAPL-3-Statements'!K58 -> 0.047849901 | O94: ='AAPL-3-Statements'!L58 -> 0.047849901 | P94: ='AAPL-3-Statements'!M58 -> 0.047849901
B95: Long-Term Deferred Revenue % Revenue: | G95: ='AAPL-3-Statements'!G59 -> 0.020484916 | H95: ='AAPL-3-Statements'!H59 -> 0.019881133 | L95: ='AAPL-3-Statements'!I59 -> 0.019881133 | M95: ='AAPL-3-Statements'!J59 -> 0.019881133 | N95: ='AAPL-3-Statements'!K59 -> 0.019881133 | O95: ='AAPL-3-Statements'!L59 -> 0.019881133 | P95: ='AAPL-3-Statements'!M59 -> 0.019881133
B97: CapEx % Revenue: | F97: ='AAPL-3-Statements'!F61 -> 0.029904793 | G97: ='AAPL-3-Statements'!G61 -> 0.029100317 | H97: ='AAPL-3-Statements'!H61 -> 0.026663559 | L97: ='AAPL-3-Statements'!I61 -> 0.026663559 | M97: ='AAPL-3-Statements'!J61 -> 0.026663559 | N97: ='AAPL-3-Statements'!K61 -> 0.026663559 | O97: ='AAPL-3-Statements'!L61 -> 0.026663559 | P97: ='AAPL-3-Statements'!M61 -> 0.026663559
B99: Income Statement
F100: =$F$73 -> Historical | I100: =$I$73 -> Transaction Adjustments | L100: =$L$73 -> Projections
F101: =$F$74 -> FY 2007 | G101: =$G$74 -> FY 2008 | H101: =$H$74 -> FY 2009 | I101: =$I$74 -> Debit | J101: =$J$74 -> Credit | K101: =$K$74 -> FY 2009 | L101: =$L$74 -> FY 2010E | M101: =$M$74 -> FY 2011E | N101: =$N$74 -> FY 2012E | O101: =$O$74 -> FY 2013E | P101: =$P$74 -> FY 2014E
B103: Revenue: | F103: ='AAPL-3-Statements'!F66 -> 24578 | G103: ='AAPL-3-Statements'!G66 -> 37491 | H103: ='AAPL-3-Statements'!H66 -> 42905 | L103: =H103*(1+L76) -> 53631.25 | M103: =L103*(1+M76) -> 62748.562 | N103: =M103*(1+N76) -> 69650.904 | O103: =N103*(1+O76) -> 75919.486 | P103: =O103*(1+P76) -> 81233.85
B104: Cost of Goods Sold: | F104: ='AAPL-3-Statements'!F67 -> 16282 | G104: ='AAPL-3-Statements'!G67 -> 24048.667 | H104: ='AAPL-3-Statements'!H67 -> 25324.333 | L104: =L103*L77 -> 31655.417 | M104: =M103*M77 -> 37036.838 | N104: =N103*N77 -> 41110.89 | O104: =O103*O77 -> 44810.87 | P104: =P103*P77 -> 47947.631
B105: Gross Profit: | F105: =F103-F104 -> 8296 | G105: =G103-G104 -> 13442.333 | H105: =H103-H104 -> 17580.667 | L105: =L103-L104 -> 21975.833 | M105: =M103-M104 -> 25711.725 | N105: =N103-N104 -> 28540.015 | O105: =O103-O104 -> 31108.616 | P105: =P103-P104 -> 33286.219
B106: Operating Expenses:
B107: Research & Development: | F107: ='AAPL-3-Statements'!F70 -> 596 | G107: ='AAPL-3-Statements'!G70 -> 758.66667 | H107: ='AAPL-3-Statements'!H70 -> 830.33333 | L107: =L103*L78 -> 1037.9167 | M107: =M103*M78 -> 1214.3625 | N107: =N103*N78 -> 1347.9424 | O107: =O103*O78 -> 1469.2572 | P107: =P103*P78 -> 1572.1052
B108: Selling, General & Administrative: | F108: ='AAPL-3-Statements'!F71 -> 2724 | G108: ='AAPL-3-Statements'!G71 -> 3344.6667 | H108: ='AAPL-3-Statements'!H71 -> 3566.3333 | L108: =L103*L79 -> 4457.9167 | M108: =M103*M79 -> 5215.7625 | N108: =N103*N79 -> 5789.4964 | O108: =O103*O79 -> 6310.551 | P108: =P103*P79 -> 6752.2896
B109: Total Operating Expenses: | F109: =SUM(F107:F108) -> 3320 | G109: =SUM(G107:G108) -> 4103.3333 | H109: =SUM(H107:H108) -> 4396.6667 | L109: =SUM(L107:L108) -> 5495.8333 | M109: =SUM(M107:M108) -> 6430.125 | N109: =SUM(N107:N108) -> 7137.4388 | O109: =SUM(O107:O108) -> 7779.8082 | P109: =SUM(P107:P108) -> 8324.3948
B111: Depreciation & Amortization of PP&E: | F111: ='AAPL-3-Statements'!F74 -> 327 | G111: ='AAPL-3-Statements'!G74 -> 496 | H111: ='AAPL-3-Statements'!H74 -> 734 | L111: =L103*L82 -> 917.5 | M111: =M103*M82 -> 1073.475 | N111: =N103*N82 -> 1191.5573 | O111: =O103*O82 -> 1298.7974 | P111: =P103*P82 -> 1389.7132
B112: Depreciation of PP&E Write-Up:
B113: New Intangibles Amortization:
B114: Amortization of Financing Fees:
B115: Amortization of Intangibles: | F115: ='AAPL-3-Statements'!F75 -> 0 | G115: ='AAPL-3-Statements'!G75 -> 0 | H115: ='AAPL-3-Statements'!H75 -> 0 | L115: =L89 -> 40 | M115: =M89 -> 37 | N115: =N89 -> 28 | O115: =O89 -> 13 | P115: =P89 -> 10
B116: Stock-Based Compensation: | F116: ='AAPL-3-Statements'!F76 -> 242 | G116: ='AAPL-3-Statements'!G76 -> 516 | H116: ='AAPL-3-Statements'!H76 -> 710 | L116: =L103*L81 -> 887.5 | M116: =M103*M81 -> 1038.375 | N116: =N103*N81 -> 1152.5963 | O116: =O103*O81 -> 1256.3299 | P116: =P103*P81 -> 1344.273
B118: Operating Income: | F118: =F105-F109-SUM(F111:F116) -> 4407 | G118: =G105-G109-SUM(G111:G116) -> 8327 | H118: =H105-H109-SUM(H111:H116) -> 11740 | L118: =L105-L109-SUM(L111:L116) -> 14635 | M118: =M105-M109-SUM(M111:M116) -> 17132.75 | N118: =N105-N109-SUM(N111:N116) -> 19030.423 | O118: =O105-O109-SUM(O111:O116) -> 20760.681 | P118: =P105-P109-SUM(P111:P116) -> 22217.838
B119: Interest Income / (Expense): | F119: =SUM('AAPL-3-Statements'!F79:F81) -> 599 | G119: =SUM('AAPL-3-Statements'!G79:G81) -> 620 | H119: =SUM('AAPL-3-Statements'!H79:H81) -> 326
B120: Pre-Tax Income: | F120: =SUM(F118:F119) -> 5006 | G120: =SUM(G118:G119) -> 8947 | H120: =SUM(H118:H119) -> 12066 | L120: =SUM(L118:L119) -> 14635 | M120: =SUM(M118:M119) -> 17132.75 | N120: =SUM(N118:N119) -> 19030.423 | O120: =SUM(O118:O119) -> 20760.681 | P120: =SUM(P118:P119) -> 22217.838
B121: Income Tax Provision: | F121: ='AAPL-3-Statements'!F83 -> 1511 | G121: ='AAPL-3-Statements'!G83 -> 2828 | H121: ='AAPL-3-Statements'!H83 -> 3831 | L121: =L120*L84 -> 4390.5 | M121: =M120*M84 -> 5139.825 | N121: =N120*N84 -> 5709.1268 | O121: =O120*O84 -> 6228.2042 | P121: =P120*P84 -> 6665.3514
B123: Net Income: | F123: =F120-F121 -> 3495 | G123: =G120-G121 -> 6119 | H123: =H120-H121 -> 8235 | L123: =L120-L121 -> 10244.5 | M123: =M120-M121 -> 11992.925 | N123: =N120-N121 -> 13321.296 | O123: =O120-O121 -> 14532.476 | P123: =P120-P121 -> 15552.487
B124: EBITDA: | F124: =F118+SUM(F111:F116) -> 4976 | G124: =G118+SUM(G111:G116) -> 9339 | H124: =H118+SUM(H111:H116) -> 13184 | L124: =L118+SUM(L111:L116) -> 16480 | M124: =M118+SUM(M111:M116) -> 19281.6 | N124: =N118+SUM(N111:N116) -> 21402.576 | O124: =O118+SUM(O111:O116) -> 23328.808 | P124: =P118+SUM(P111:P116) -> 24961.824
...
