Workbook

Sheet README
A1: NORTH SOUND HEALTH NETWORK — Sterile Supply Control Workbook
A2: Purpose: control workbook behind the Sterile Supply Resilience Portal. Quantifies shortage exposure,
A3: expiry/recall exposure, supplier performance and the adverse/base/upside action program for the supplier
A4: renewal decision. Analysis cells are live formulas over raw data sheets (Lots_Data, Usage_Data, PO_Data,
A5: Delivery_Data, Quality_Data, Exceptions, Site_Constraints, Action_Catalog).
A7: Sheet map:
A8: Inputs — editable scenario assumptions: multipliers, target cover, score weights, snapshot date, window.
A9: Dashboard — KPI summary; the figures that must reconcile with the portal.
A10: SKU_Exposure — per-SKU demand, days-of-cover, scenario gaps, reorder-point adequacy.
A11: Scenario_Decision — action catalog per scenario with capacity/mutual-exclusion/eligibility checks.
A12: Supplier_Scorecard — delivery, quality and renewal scoring over the supplier database extracts.
A13: Exceptions — exception register with evidence grading (invoice/statement = documented).
... A31: conclusions (see Uncertainty_Register). No contract terms, prices or authorities beyond the sources are asserted.

Sheet Inputs
A1: Editable Inputs & Scenario Assumptions
A2: Yellow cells are the only editable inputs; downstream sheets recalculate from them. Locators cited per row.
A4: Snapshot / analysis date | B4: 46259
A5: Window start | B5: 2026-01
A6: Window end | B6: 2026-08
A7: Target days of cover | B7: 30
A9: Scenario | B9: Demand multiplier | C9: Basis / evidence locator
A10: adverse | B10: 1.315 | C10: Observed surge ratio (usage file exception_flag="surge"): mean of per-SKU surge/non-surge usage ratios over 16 flagged rows in window. Small sample — see U-03.
A11: base | B11: 1 | C11: Trailing 8 complete months (Inputs B5..B6) average monthly usage.
A12: upside | B12: 0.9 | C12: Planning judgment — demand relief; no direct evidence in sources. Editable.
A14: Score weight | B14: Value | C14: Component
A15: OTD weight | B15: 0.4 | C15: on-time/placed
A16: Lead-time weight | B16: 0.25 | C16: min lead / supplier lead
A17: Quality-closure weight | B17: 0.2 | C17: 1 - not-closed/max not-closed
A18: Fill weight | B18: 0.15 | C18: items received/ordered (PO_Data)

Sheet Lots_Data
A1: sku_id | B1: item_description | C1: clinical_family | D1: supplier | E1: site_id | F1: lot_id | G1: unit_cost_usd | H1: on_hand_qty | I1: quarantine_qty | J1: recall_state | K1: usable_qty | L1: usable_value | M1: onhand_value | N1: lead_time_days | O1: storage_zone | P1: expiry_date | Q1: days_to_expiry | R1: expiry_bucket | S1: static_reorder_point
A2: SS-01001 | B2: vascular access kit 100 | C2: vascular | D2: Northstar Surgical | E2: HOSP-1 | F2: LOT-07001 | G2: 16.47 | H2: 13 | I2: 0 | J2: recalled | K2: =IF(J2="recalled",0,MAX(0,H2-I2)) | L2: =K2*G2 | M2: =H2*G2 | N2: 6 | O2: D2-21 | P2: 46388 | Q2: =P2-Inputs!$B$4 | R2: =IF(Q2<0,"expired",IF(Q2<=30,"<=30d",IF(Q2<=90,"31-90d",IF(Q2<=180,"91-180d",">180d")))) | S2: 5
A3: SS-01002 | B3: respiratory circuit 101 | C3: respiratory | D3: MedAxis Distribution | E3: HOSP-2 | F3: LOT-07002 | G3: 37.23 | H3: 3 | I3: 0 | J3: clear | K3: =IF(J3="recalled",0,MAX(0,H3-I3)) | L3: =K3*G3 | M3: =H3*G3 | N3: 6 | O3: A5-08 | P3: 46420 | Q3: =P3-Inputs!$B$4 | R3: =IF(Q3<0,"expired",IF(Q3<=30,"<=30d",IF(Q3<=90,"31-90d",IF(Q3<=180,"91-180d",">180d")))) | S3: 5
A4: SS-01003 | B4: sterile surgical pack 102 | C4: surgical | D4: SterilePath Medical | E4: HOSP-3 | F4: LOT-07003 | G4: 23.98 | H4: 3 | I4: 0 | J4: clear | K4: =IF(J4="recalled",0,MAX(0,H4-I4)) | L4: =K4*G4 | M4: =H4*G4 | N4: 3 | O4: B8-03 | P4: 46449 | Q4: =P4-Inputs!$B$4 | R4: =IF(Q4<0,"expired",IF(Q4<=30,"<=30d",IF(Q4<=90,"31-90d",IF(Q4<=180,"91-180d",">180d")))) | S4: 5
A5: SS-01004 | B5: diagnostic collection set 103 | C5: diagnostic | D5: Aegis Clinical Supply | E5: HOSP-4 | F5: LOT-07004 | G5: 23.77 | H5: 50 | I5: 0 | J5: clear | K5: =IF(J5="recalled",0,MAX(0,H5-I5)) | L5: =K5*G5 | M5: =H5*G5 | N5: 7 | O5: A12-07 | P5: 46481 | Q5: =P5-Inputs!$B$4 | R5: =IF(Q5<0,"expired",IF(Q5<=30,"<=30d",IF(Q5<=90,"31-90d",IF(Q5<=180,"91-180d",">180d")))) | S5: 5
A6: SS-01005 | B6: advanced wound dressing 104 | C6: wound | D6: HarborMed Logistics | E6: HOSP-1 | F6: LOT-07005 | G6: 12.46 | H6: 3 | I6: 0 | J6: clear | K6: =IF(J6="recalled",0,MAX(0,H6-I6)) | L6: =K6*G6 | M6: =H6*G6 | N6: 11 | O6: F4-01 | P6: 46512 | Q6: =P6-Inputs!$B$4 | R6: =IF(Q6<0,"expired",IF(Q6<=30,"<=30d",IF(Q6<=90,"31-90d",IF(Q6<=180,"91-180d",">180d")))) | S6: 5
A7: SS-01006 | B7: vascular access kit 105 | C7: vascular | D7: Northstar Surgical | E7: HOSP-2 | F7: LOT-07006 | G7: 21.42 | H7: 13 | I7: 0 | J7: clear | K7: =IF(J7="recalled",0,MAX(0,H7-I7)) | L7: =K7*G7 | M7: =H7*G7 | N7: 7 | O7: B6-11 | P7: 46544 | Q7: =P7-Inputs!$B$4 | R7: =IF(Q7<0,"expired",IF(Q7<=30,"<=30d",IF(Q7<=90,"31-90d",IF(Q7<=180,"91-180d",">180d")))) | S7: 5
A8: SS-01007 | B8: respiratory circuit 106 | C8: respiratory | D8: MedAxis Distribution | E8: HOSP-3 | F8: LOT-07007 | G8: 34.4 | H8: 26 | I8: 0 | J8: clear | K8: =IF(J8="recalled",0,MAX(0,H8-I8)) | L8: =K8*G8 | M8: =H8*G8 | N8: 3 | O8: A2-06 | P8: 46575 | Q8: =P8-Inputs!$B$4 | R8: =IF(Q8<0,"expired",IF(Q8<=30,"<=30d",IF(Q8<=90,"31-90d",IF(Q8<=180,"91-180d",">180d")))) | S8: 5
A9: SS-01008 | B9: sterile surgical pack 107 | C9: surgical | D9: SterilePath Medical | E9: HOSP-4 | F9: LOT-07008 | G9: 19.54 | H9: 0 | I9: 0 | J9: clear | K9: =IF(J9="recalled",0,MAX(0,H9-I9)) | L9: =K9*G9 | M9: =H9*G9 | N9: 7 | O9: C8-21 | P9: 46607 | Q9: =P9-Inputs!$B$4 | R9: =IF(Q9<0,"expired",IF(Q9<=30,"<=30d",IF(Q9<=90,"31-90d",IF(Q9<=180,"91-180d",">180d")))) | S9: 5
A10: SS-01009 | B10: diagnostic collection set 108 | C10: diagnostic | D10: Aegis Clinical Supply | E10: HOSP-1 | F10: LOT-07009 | G10: 9.96 | H10: 19 | I10: 0 | J10: clear | K10: =IF(J10="recalled",0,MAX(0,H10-I10)) | L10: =K10*G10 | M10: =H10*G10 | N10: 8 | O10: D7-20 | P10: 46639 | Q10: =P10-Inputs!$B$4 | R10: =IF(Q10<0,"expired",IF(Q10<=30,"<=30d",IF(Q10<=90,"31-90d",IF(Q10<=180,"91-180d",">180d")))) | S10: 16
A11: SS-01010 | B11: advanced wound dressing 109 | C11: wound | D11: HarborMed Logistics | E11: HOSP-2 | F11: LOT-07010 | G11: 8.34 | H11: 10 | I11: 0 | J11: clear | K11: =IF(J11="recalled",0,MAX(0,H11-I11)) | L11: =K11*G11 | M11: =H11*G11 | N11: 6 | O11: D4-02 | P11: 46670 | Q11: =P11-Inputs!$B$4 | R11: =IF(Q11<0,"expired",IF(Q11<=30,"<=30d",IF(Q11<=90,"31-90d",IF(Q11<=180,"91-180d",">180d")))) | S11: 5
A12: SS-01011 | B12: vascular access kit 110 | C12: vascular | D12: Northstar Surgical | E12: HOSP-3 | F12: LOT-07011 | G12: 3.58 | H12: 16 | I12: 0 | J12: clear | K12: =IF(J12="recalled",0,MAX(0,H12-I12)) | L12: =K12*G12 | M12: =H12*G12 | N12: 7 | O12: E12-03 | P12: 46702 | Q12: =P12-Inputs!$B$4 | R12: =IF(Q12<0,"expired",IF(Q12<=30,"<=30d",IF(Q12<=90,"31-90d",IF(Q12<=180,"91-180d",">180d")))) | S12: 5
A13: SS-01012 | B13: respiratory circuit 111 | C13: respiratory | D13: MedAxis Distribution | E13: HOSP-4 | F13: LOT-07012 | G13: 20.76 | H13: 3 | I13: 3 | J13: clear | K13: =IF(J13="recalled",0,MAX(0,H13-I13)) | L13: =K13*G13 | M13: =H13*G13 | N13: 6 | O13: C9-19 | P13: 46733 | Q13: =P13-Inputs!$B$4 | R13: =IF(Q13<0,"expired",IF(Q13<=30,"<=30d",IF(Q13<=90,"31-90d",IF(Q13<=180,"91-180d",">180d")))) | S13: 5
... A234: SS-01233 | B234: sterile surgical pack 110 | C234: surgical | D234: SterilePath Medical | E234: HOSP-1 | F234: LOT-07233 | G234: 19.38 | H234: 2 | I234: 0 | J234: clear | K234: =IF(J234="recalled",0,MAX(0,H234-I234)) | L234: =K234*G234 | M234: =H234*G234 | N234: 8 | O234: A9-23 | P234: 46524 | Q234: =P234-Inputs!$B$4 | R234: =IF(Q234<0,"expired",IF(Q234<=30,"<=30d",IF(Q234<=90,"31-90d",IF(Q234<=180,"91-180d",">180d")))) | S234: 5

Sheet Usage_Data
A1: period | B1: site_id | C1: sku_id | D1: usage_qty | E1: transfer_qty | F1: exception_flag | G1: in_window
A2: 2026-01 | B2: HOSP-1 | C2: SS-01001 | D2: 48 | E2: 0 | F2: surge | G2: =IF(AND(A2>=Inputs!$B$5,A2<=Inputs!$B$6),1,0)
A3: 2026-01 | B3: HOSP-2 | C3: SS-01002 | D3: 24 | E3: 1 | G3: =IF(AND(A3>=Inputs!$B$5,A3<=Inputs!$B$6),1,0)
A4: 2026-01 | B4: HOSP-3 | C4: SS-01003 | D4: 0 | E4: 0 | G4: =IF(AND(A4>=Inputs!$B$5,A4<=Inputs!$B$6),1,0)
A5: 2026-01 | B5: HOSP-4 | C5: SS-01004 | D5: 24 | E5: 0 | G5: =IF(AND(A5>=Inputs!$B$5,A5<=Inputs!$B$6),1,0)
A6: 2026-01 | B6: HOSP-1 | C6: SS-01005 | D6: 96 | E6: 0 | G6: =IF(AND(A6>=Inputs!$B$5,A6<=Inputs!$B$6),1,0)
A7: 2026-01 | B7: HOSP-2 | C7: SS-01006 | D7: 0 | E7: 0 | G7: =IF(AND(A7>=Inputs!$B$5,A7<=Inputs!$B$6),1,0)
A8: 2026-01 | B8: HOSP-3 | C8: SS-01007 | D8: 13 | E8: 3 | G8: =IF(AND(A8>=Inputs!$B$5,A8<=Inputs!$B$6),1,0)
A9: 2026-01 | B9: HOSP-4 | C9: SS-01008 | D9: 0 | E9: 0 | G9: =IF(AND(A9>=Inputs!$B$5,A9<=Inputs!$B$6),1,0)
A10: 2026-01 | B10: HOSP-1 | C10: SS-01009 | D10: 12 | E10: 0 | G10: =IF(AND(A10>=Inputs!$B$5,A10<=Inputs!$B$6),1,0)
A11: 2026-01 | B11: HOSP-2 | C11: SS-01010 | D11: 96 | E11: 0 | G11: =IF(AND(A11>=Inputs!$B$5,A11<=Inputs!$B$6),1,0)
A12: 2026-01 | B12: HOSP-3 | C12: SS-01101 | D12: 48 | E12: 0 | G12: =IF(AND(A12>=Inputs!$B$5,A12<=Inputs!$B$6),1,0)
A13: 2026-01 | B13: HOSP-4 | C13: SS-01012 | D13: 15 | E13: 0 | G13: =IF(AND(A13>=Inputs!$B$5,A13<=Inputs!$B$6),1,0)
A14: 2026-01 | B14: HOSP-1 | C14: SS-01013 | D14: 5 | E14: 0 | G14: =IF(AND(A14>=Inputs!$B$5,A14<=Inputs!$B$6),1,0)
... A174: 2026-01 | B174: HOSP-1 | C174: SS-01173 | D174: 48 | E174: 0 | G174: =IF(AND(A174>=Inputs!$B$5,A174<=Inputs!$B$6),1,0)
A175: 2026-01 | B175: HOSP-2 | C175: SS-01174 | D175: 36 | E175: 0 | F175: surge | G175: =IF(AND(A175>=Inputs!$B$5,A175<=Inputs!$B$6),1,0)
A176: 2026-01 | B176: HOSP-3 | C176: SS-01175 | D176: 0 | E176: 0 | G176: =IF(AND(A176>=Inputs!$B$5,A176<=Inputs!$B$6),1,0)
A177: 2026-01 | B177: HOSP-4 | C177: SS-01176 | D177: 48 | E177: 0 | G177: =IF(AND(A177>=Inputs!$B$5,A177<=Inputs!$B$6),1,0)
A178: 2026-01 | B178: HOSP-1 | C178: SS-01177 | D178: 24 | E178: 0 | G178: =IF(AND(A178>=Inputs!$B$5,A178<=Inputs!$B$6),1,0)
A179: 2026-01 | B179: HOSP-2 | C179: SS-01178 | D179: 0 | E179: 0 | G179: =IF(AND(A179>=Inputs!$B$5,A179<=Inputs!$B$6),1,0)
A180: 2026-01 | B180: HOSP-3 | C180: SS-01179 | D180: 144 | E180: 0 | G180: =IF(AND(A180>=Inputs!$B$5,A180<=Inputs!$B$6),1,0)
A181: 2026-01 | B181: HOSP-4 | C181: SS-01180 | D181: 0 | E181: 0 | G181: =IF(AND(A181>=Inputs!$B$5,A181<=Inputs!$B$6),1,0)
A182: 2026-01 | B182: HOSP-1 | C182: SS-01181 | D182: 0 | E182: 1 | G182: =IF(AND(A182>=Inputs!$B$5,A182<=Inputs!$B$6),1,0)
A183: 2026-01 | B183: HOSP-2 | C183: SS-01182 | D183: 0 | E183: 0 | G183: =IF(AND(A183>=Inputs!$B$5,A183<=Inputs!$B$6),1,0)
A184: 2026-01 | B184: HOSP-3 | C184: SS-01183 | D184: 12 | E184: 0 | G184: =IF(AND(A184>=Inputs!$B$5,A184<=Inputs!$B$6),1,0)
A185: 2026-01 | B185: HOSP-4 | C185: SS-01184 | D185: 60 | E185: 0 | G185: =IF(AND(A185>=Inputs!$B$5,A185<=Inputs!$B$6),1,0)
A186: 2026-01 | B186: HOSP-1 | C186: SS-01185 | D186: 2 | E186: 2 | G186: =IF(AND(A186>=Inputs!$B$5,A186<=Inputs!$B$6),1,0)
A187: 2026-01 | B187: HOSP-2 | C187: SS-01186 | D187: 0 | E187: 0 | G187: =IF(AND(A187>=Inputs!$B$5,A187<=Inputs!$B$6),1,0)
... A347: 2026-02 | B347: HOSP-2 | C347: SS-01113 | D347: 0 | E347: 0 | G347: =IF(AND(A347>=Inputs!$B$5,A347<=Inputs!$B$6),1,0)
A348: 2026-02 | B348: HOSP-3 | C348: SS-01114 | D348: 36 | E348: 0 | F348: surge | G348: =IF(AND(A348>=Inputs!$B$5,A348<=Inputs!$B$6),1,0)
A349: 2026-02 | B349: HOSP-4 | C349: SS-01115 | D349: 13 | E349: 0 | G349: =IF(AND(A349>=Inputs!$B$5,A349<=Inputs!$B$6),1,0)
A350: 2026-02 | B350: HOSP-1 | C350: SS-01116 | D350: 24 | E350: 0 | G350: =IF(AND(A350>=Inputs!$B$5,A350<=Inputs!$B$6),1,0)
A351: 2026-02 | B351: HOSP-2 | C351: SS-01117 | D351: 300 | E351: 0 | G351: =IF(AND(A351>=Inputs!$B$5,A351<=Inputs!$B$6),1,0)
A352: 2026-02 | B352: HOSP-3 | C352: SS-01118 | D352: 0 | E352: 0 | G352: =IF(AND(A352>=Inputs!$B$5,A352<=Inputs!$B$6),1,0)
A353: 2026-02 | B353: HOSP-4 | C353: SS-01119 | D353: 2 | E353: 1 | G353: =IF(AND(A353>=Inputs!$B$5,A353<=Inputs!$B$6),1,0)
A354: 2026-02 | B354: HOSP-1 | C354: SS-01120 | D354: 60 | E354: 0 | G354: =IF(AND(A354>=Inputs!$B$5,A354<=Inputs!$B$6),1,0)
A355: 2026-02 | B355: HOSP-2 | C355: SS-01121 | D355: 18 | E355: 0 | G355: =IF(AND(A355>=Inputs!$B$5,A355<=Inputs!$B$6),1,0)
A356: 2026-02 | B356: HOSP-3 | C356: SS-01122 | D356: 2 | E356: 3 | G356: =IF(AND(A356>=Inputs!$B$5,A356<=Inputs!$B$6),1,0)
A357: 2026-02 | B357: HOSP-4 | C357: SS-01123 | D357: 24 | E357: 0 | G357: =IF(AND(A357>=Inputs!$B$5,A357<=Inputs!$B$6),1,0)
A358: 2026-02 | B358: HOSP-1 | C358: SS-01124 | D358: 0 | E358: 0 | G358: =IF(AND(A358>=Inputs!$B$5,A358<=Inputs!$B$6),1,0)
A359: 2026-02 | B359: HOSP-2 | C359: SS-01125 | D359: 156 | E359: 0 | G359: =IF(AND(A359>=Inputs!$B$5,A359<=Inputs!$B$6),1,0)
A360: 2026-02 | B360: HOSP-3 | C360: SS-01126 | D360: 96 | E360: 0 | G360: =IF(AND(A360>=Inputs!$B$5,A360<=Inputs!$B$6),1,0)
... A520: 2026-03 | B520: HOSP-3 | C520: SS-01053 | D520: 60 | E520: 0 | G520: =IF(AND(A520>=Inputs!$B$5,A520<=Inputs!$B$6),1,0)
A521: 2026-03 | B521: HOSP-4 | C521: SS-01054 | D521: 0 | E521: 0 | F521: surge | G521: =IF(AND(A521>=Inputs!$B$5,A521<=Inputs!$B$6),1,0)
A522: 2026-03 | B522: HOSP-1 | C522: SS-01055 | D522: 12 | E522: 0 | G522: =IF(AND(A522>=Inputs!$B$5,A522<=Inputs!$B$6),1,0)
A523: 2026-03 | B523: HOSP-2 | C523: SS-01056 | D523: 0 | E523: 0 | G523: =IF(AND(A523>=Inputs!$B$5,A523<=Inputs!$B$6),1,0)
A524: 2026-03 | B524: HOSP-3 | C524: SS-01057 | D524: 12 | E524: 0 | G524: =IF(AND(A524>=Inputs!$B$5,A524<=Inputs!$B$6),1,0)
A525: 2026-03 | B525: HOSP-4 | C525: SS-01058 | D525: 12 | E525: 0 | G525: =IF(AND(A525>=Inputs!$B$5,A525<=Inputs!$B$6),1,0)
A526: 2026-03 | B526: HOSP-1 | C526: SS-01059 | D526: 24 | E526: 0 | G526: =IF(AND(A526>=Inputs!$B$5,A526<=Inputs!$B$6),1,0)
A527: 2026-03 | B527: HOSP-2 | C527: SS-01060 | D527: 132 | E527: 0 | G527: =IF(AND(A527>=Inputs!$B$5,A527<=Inputs!$B$6),1,0)
A528: 2026-03 | B528: HOSP-3 | C528: SS-01061 | D528: 60 | E528: 0 | G528: =IF(AND(A528>=Inputs!$B$5,A528<=Inputs!$B$6),1,0)
A529: 2026-03 | B529: HOSP-4 | C529: SS-01062 | D529: 0 | E529: 0 | G529: =IF(AND(A529>=Inputs!$B$5,A529<=Inputs!$B$6),1,0)
A530: 2026-03 | B530: HOSP-1 | C530: SS-01046 | D530: 7 | E530: 4 | G530: =IF(AND(A530>=Inputs!$B$5,A530<=Inputs!$B$6),1,0)
A531: 2026-03 | B531: HOSP-2 | C531: SS-01064 | D531: 0 | E531: 0 | G531: =IF(AND(A531>=Inputs!$B$5,A531<=Inputs!$B$6),1,0)
A532: 2026-03 | B532: HOSP-3 | C532: SS-01065 | D532: 12 | E532: 0 | G532: =IF(AND(A532>=Inputs!$B$5,A532<=Inputs!$B$6),1,0)
A533: 2026-03 | B533: HOSP-4 | C533: SS-01066 | D533: 24 | E533: 0 | G533: =IF(AND(A533>=Inputs!$B$5,A533<=Inputs!$B$6),1,0)
... A693: 2026-03 | B693: HOSP-4 | C693: SS-01226 | D693: 12 | E693: 0 | G693: =IF(AND(A693>=Inputs!$B$5,A693<=Inputs!$B$6),1,0)
A694: 2026-03 | B694: HOSP-1 | C694: SS-01227 | D694: 8 | E694: 0 | F694: surge | G694: =IF(AND(A694>=Inputs!$B$5,A694<=Inputs!$B$6),1,0)
A695: 2026-03 | B695: HOSP-2 | C695: SS-01228 | D695: 24 | E695: 0 | G695: =IF(AND(A695>=Inputs!$B$5,A695<=Inputs!$B$6),1,0)
A696: 2026-03 | B696: HOSP-3 | C696: SS-01229 | D696: 12 | E696: 0 | G696: =IF(AND(A696>=Inputs!$B$5,A696<=Inputs!$B$6),1,0)
A697: 2026-03 | B697: HOSP-4 | C697: SS-01230 | D697: 0 | E697: 0 | G697: =IF(AND(A697>=Inputs!$B$5,A697<=Inputs!$B$6),1,0)
A698: 2026-03 | B698: HOSP-1 | C698: SS-01231 | D698: 0 | E698: 0 | G698: =IF(AND(A698>=Inputs!$B$5,A698<=Inputs!$B$6),1,0)
A699: 2026-03 | B699: HOSP-2 | C699: SS-01232 | D699: 12 | E699: 0 | G699: =IF(AND(A699>=Inputs!$B$5,A699<=Inputs!$B$6),1,0)
A700: 2026-03 | B700: HOSP-3 | C700: SS-01233 | D700: 51 | E700: 0 | G700: =IF(AND(A700>=Inputs!$B$5,A700<=Inputs!$B$6),1,0)
A701: 2026-03 | B701: HOSP-4 | C701: SS-01001 | D701: 36 | E701: 0 | G701: =IF(AND(A701>=Inputs!$B$5,A701<=Inputs!$B$6),1,0)
A702: 2026-03 | B702: HOSP-1 | C702: SS-01002 | D702: 0 | E702: 0 | G702: =IF(AND(A702>=Inputs!$B$5,A702<=Inputs!$B$6),1,0)
A703: 2026-03 | B703: HOSP-2 | C703: SS-01003 | D703: 12 | E703: 13 | G703: =IF(AND(A703>=Inputs!$B$5,A703<=Inputs!$B$6),1,0)
A704: 2026-03 | B704: HOSP-3 | C704: SS-01004 | D704: 72 | E704: 0 | G704: =IF(AND(A704>=Inputs!$B$5,A704<=Inputs!$B$6),1,0)
A705: 2026-03 | B705: HOSP-4 | C705: SS-01005 | D705: 12 | E705: 0 | G705: =IF(AND(A705>=Inputs!$B$5,A705<=Inputs!$B$6),1,0)
A706: 2026-03 | B706: HOSP-1 | C706: SS-01006 | D706: 120 | E706: 0 | G706: =IF(AND(A706>=Inputs!$B$5,A706<=Inputs!$B$6),1,0)
... A866: 2026-04 | B866: HOSP-1 | C866: SS-01166 | D866: 0 | E866: 0 | G866: =IF(AND(A866>=Inputs!$B$5,A866<=Inputs!$B$6),1,0)
A867: 2026-04 | B867: HOSP-2 | C867: SS-01167 | D867: 156 | E867: 0 | F867: surge | G867: =IF(AND(A867>=Inputs!$B$5,A867<=Inputs!$B$6),1,0)
A868: 2026-04 | B868: HOSP-3 | C868: SS-01168 | D868: 72 | E868: 0 | G868: =IF(AND(A868>=Inputs!$B$5,A868<=Inputs!$B$6),1,0)
A869: 2026-04 | B869: HOSP-4 | C869: SS-01169 | D869: 0 | E869: 0 | G869: =IF(AND(A869>=Inputs!$B$5,A869<=Inputs!$B$6),1,0)
A870: 2026-04 | B870: HOSP-1 | C870: SS-01072 | D870: 27 | E870: 1 | G870: =IF(AND(A870>=Inputs!$B$5,A870<=Inputs!$B$6),1,0)
A871: 2026-04 | B871: HOSP-2 | C871: SS-01171 | D871: 28 | E871: 0 | G871: =IF(AND(A871>=Inputs!$B$5,A871<=Inputs!$B$6),1,0)
A872: 2026-04 | B872: HOSP-3 | C872: SS-01172 | D872: 12 | E872: 0 | G872: =IF(AND(A872>=Inputs!$B$5,A872<=Inputs!$B$6),1,0)
A873: 2026-04 | B873: HOSP-4 | C873: SS-01173 | D873: 0 | E873: 0 | G873: =IF(AND(A873>=Inputs!$B$5,A873<=Inputs!$B$6),1,0)
A874: 2026-04 | B874: HOSP-1 | C874: SS-01174 | D874: 22 | E874: 1 | G874: =IF(AND(A874>=Inputs!$B$5,A874<=Inputs!$B$6),1,0)
A875: 2026-04 | B875: HOSP-2 | C875: SS-01175 | D875: 0 | E875: 0 | G875: =IF(AND(A875>=Inputs!$B$5,A875<=Inputs!$B$6),1,0)
A876: 2026-04 | B876: HOSP-3 | C876: SS-01176 | D876: 21 | E876: 0 | G876: =IF(AND(A876>=Inputs!$B$5,A876<=Inputs!$B$6),1,0)
A877: 2026-04 | B877: HOSP-4 | C877: SS-01177 | D877: 48 | E877: 0 | G877: =IF(AND(A877>=Inputs!$B$5,A877<=Inputs!$B$6),1,0)
A878: 2026-04 | B878: HOSP-1 | C878: SS-01178 | D878: 36 | E878: 0 | G878: =IF(AND(A878>=Inputs!$B$5,A878<=Inputs!$B$6),1,0)
A879: 2026-04 | B879: HOSP-2 | C879: SS-01179 | D879: 12 | E879: 0 | G879: =IF(AND(A879>=Inputs!$B$5,A879<=Inputs!$B$6),1,0)
... A1039: 2026-04 | B1039: HOSP-2 | C1039: SS-01106 | D1039: 26 | E1039: 0 | G1039: =IF(AND(A1039>=Inputs!$B$5,A1039<=Inputs!$B$6),1,0)
A1040: 2026-04 | B1040: HOSP-3 | C1040: SS-01107 | D1040: 60 | E1040: 0 | F1040: surge | G1040: =IF(AND(A1040>=Inputs!$B$5,A1040<=Inputs!$B$6),1,0)
A1041: 2026-04 | B1041: HOSP-4 | C1041: SS-01108 | D1041: 32 | E1041: 1 | G1041: =IF(AND(A1041>=Inputs!$B$5,A1041<=Inputs!$B$6),1,0)
A1042: 2026-04 | B1042: HOSP-1 | C1042: SS-01109 | D1042: 144 | E1042: 0 | G1042: =IF(AND(A1042>=Inputs!$B$5,A1042<=Inputs!$B$6),1,0)
A1043: 2026-04 | B1043: HOSP-2 | C1043: SS-01110 | D1043: 468 | E1043: 0 | G1043: =IF(AND(A1043>=Inputs!$B$5,A1043<=Inputs!$B$6),1,0)
A1044: 2026-04 | B1044: HOSP-3 | C1044: SS-01111 | D1044: 312 | E1044: 0 | G1044: =IF(AND(A1044>=Inputs!$B$5,A1044<=Inputs!$B$6),1,0)
A1045: 2026-04 | B1045: HOSP-4 | C1045: SS-01112 | D1045: 24 | E1045: 0 | G1045: =IF(AND(A1045>=Inputs!$B$5,A1045<=Inputs!$B$6),1,0)
A1046: 2026-04 | B1046: HOSP-1 | C1046: SS-01113 | D1046: 0 | E1046: 0 | G1046: =IF(AND(A1046>=Inputs!$B$5,A1046<=Inputs!$B$6),1,0)
A1047: 2026-04 | B1047: HOSP-2 | C1047: SS-01114 | D1047: 180 | E1047: 0 | G1047: =IF(AND(A1047>=Inputs!$B$5,A1047<=Inputs!$B$6),1,0)
A1048: 2026-04 | B1048: HOSP-3 | C1048: SS-01115 | D1048: 144 | E1048: 0 | G1048: =IF(AND(A1048>=Inputs!$B$5,A1048<=Inputs!$B$6),1,0)
A1049: 2026-04 | B1049: HOSP-4 | C1049: SS-01116 | D1049: 12 | E1049: 0 | G1049: =IF(AND(A1049>=Inputs!$B$5,A1049<=Inputs!$B$6),1,0)
A1050: 2026-04 | B1050: HOSP-1 | C1050: SS-01117 | D1050: 84 | E1050: 0 | G1050: =IF(AND(A1050>=Inputs!$B$5,A1050<=Inputs!$B$6),1,0)
A1051: 2026-04 | B1051: HOSP-2 | C1051: SS-01118 | D1051: 276 | E1051: 0 | G1051: =IF(AND(A1051>=Inputs!$B$5,A1051<=Inputs!$B$6),1,0)
A1052: 2026-04 | B1052: HOSP-3 | C1052: SS-01119 | D1052: 0 | E1052: 0 | G1052: =IF(AND(A1052>=Inputs!$B$5,A1052<=Inputs!$B$6),1,0)
... A1212: 2026-05 | B1212: HOSP-3 | C1212: SS-01046 | D1212: 0 | E1212: 0 | G1212: =IF(AND(A1212>=Inputs!$B$5,A1212<=Inputs!$B$6),1,0)
A1213: 2026-05 | B1213: HOSP-4 | C1213: SS-01229 | D1213: 1 | E1213: 6 | F1213: surge | G1213: =IF(AND(A1213>=Inputs!$B$5,A1213<=Inputs!$B$6),1,0)
...

Sheet Usage_Summary
A1: Per-SKU usage aggregates (formulas over Usage_Data; window = Inputs B5..B6)
A3: sku_id | B3: window_usage | C3: base_monthly_usage | D3: surge_flags | E3: transfers_in_window
A4: SS-01001 | B4: =SUMIFS(Usage_Data!$D$2:$D$5001,Usage_Data!$C$2:$C$5001,$A4,Usage_Data!$G$2:$G$5001,1) | C4: =B4/8 | D4: =COUNTIFS(Usage_Data!$C$2:$C$5001,$A4,Usage_Data!$F$2:$F$5001,"surge",Usage_Data!$G$2:$G$5001,1) | E4: =SUMIFS(Usage_Data!$E$2:$E$5001,Usage_Data!$C$2:$C$5001,$A4,Usage_Data!$G$2:$G$5001,1)
A5: SS-01002 | B5: =SUMIFS(Usage_Data!$D$2:$D$5001,Usage_Data!$C$2:$C$5001,$A5,Usage_Data!$G$2:$G$5001,1) | C5: =B5/8 | D5: =COUNTIFS(Usage_Data!$C$2:$C$5001,$A5,Usage_Data!$F$2:$F$5001,"surge",Usage_Data!$G$2:$G$5001,1) | E5: =SUMIFS(Usage_Data!$E$2:$E$5001,Usage_Data!$C$2:$C$5001,$A5,Usage_Data!$G$2:$G$5001,1)
A6: SS-01003 | B6: =SUMIFS(Usage_Data!$D$2:$D$5001,Usage_Data!$C$2:$C$5001,$A6,Usage_Data!$G$2:$G$5001,1) | C6: =B6/8 | D6: =COUNTIFS(Usage_Data!$C$2:$C$5001,$A6,Usage_Data!$F$2:$F$5001,"surge",Usage_Data!$G$2:$G$5001,1) | E6: =SUMIFS(Usage_Data!$E$2:$E$5001,Usage_Data!$C$2:$C$5001,$A6,Usage_Data!$G$2:$G$5001,1)
A7: SS-01004 | B7: =SUMIFS(Usage_Data!$D$2:$D$5001,Usage_Data!$C$2:$C$5001,$A7,Usage_Data!$G$2:$G$5001,1) | C7: =B7/8 | D7: =COUNTIFS(Usage_Data!$C$2:$C$5001,$A7,Usage_Data!$F$2:$F$5001,"surge",Usage_Data!$G$2:$G$5001,1) | E7: =SUMIFS(Usage_Data!$E$2:$E$5001,Usage_Data!$C$2:$C$5001,$A7,Usage_Data!$G$2:$G$5001,1)
A8: SS-01005 | B8: =SUMIFS(Usage_Data!$D$2:$D$5001,Usage_Data!$C$2:$C$5001,$A8,Usage_Data!$G$2:$G$5001,1) | C8: =B8/8 | D8: =COUNTIFS(Usage_Data!$C$2:$C$5001,$A8,Usage_Data!$F$2:$F$5001,"surge",Usage_Data!$G$2:$G$5001,1) | E8: =SUMIFS(Usage_Data!$E$2:$E$5001,Usage_Data!$C$2:$C$5001,$A8,Usage_Data!$G$2:$G$5001,1)
A9: SS-01006 | B9: =SUMIFS(Usage_Data!$D$2:$D$5001,Usage_Data!$C$2:$C$5001,$A9,Usage_Data!$G$2:$G$5001,1) | C9: =B9/8 | D9: =COUNTIFS(Usage_Data!$C$2:$C$5001,$A9,Usage_Data!$F$2:$F$5001,"surge",Usage_Data!$G$2:$G$5001,1) | E9: =SUMIFS(Usage_Data!$E$2:$E$5001,Usage_Data!$C$2:$C$5001,$A9,Usage_Data!$G$2:$G$5001,1)
A10: SS-01007 | B10: =SUMIFS(Usage_Data!$D$2:$D$5001,Usage_Data!$C$2:$C$5001,$A10,Usage_Data!$G$2:$G$5001,1) | C10: =B10/8 | D10: =COUNTIFS(Usage_Data!$C$2:$C$5001,$A10,Usage_Data!$F$2:$F$5001,"surge",Usage_Data!$G$2:$G$5001,1) | E10: =SUMIFS(Usage_Data!$E$2:$E$5001,Usage_Data!$C$2:$C$5001,$A10,Usage_Data!$G$2:$G$5001,1)
A11: SS-01008 | B11: =SUMIFS(Usage_Data!$D$2:$D$5001,Usage_Data!$C$2:$C$5001,$A11,Usage_Data!$G$2:$G$5001,1) | C11: =B11/8 | D11: =COUNTIFS(Usage_Data!$C$2:$C$5001,$A11,Usage_Data!$F$2:$F$5001,"surge",Usage_Data!$G$2:$G$5001,1) | E11: =SUMIFS(Usage_Data!$E$2:$E$5001,Usage_Data!$C$2:$C$5001,$A11,Usage_Data!$G$2:$G$5001,1)
A12: SS-01009 | B12: =SUMIFS(Usage_Data!$D$2:$D$5001,Usage_Data!$C$2:$C$5001,$A12,Usage_Data!$G$2:$G$5001,1) | C12: =B12/8 | D12: =COUNTIFS(Usage_Data!$C$2:$C$5001,$A12,Usage_Data!$F$2:$F$5001,"surge",Usage_Data!$G$2:$G$5001,1) | E12: =SUMIFS(Usage_Data!$E$2:$E$5001,Usage_Data!$C$2:$C$5001,$A12,Usage_Data!$G$2:$G$5001,1)
A13: SS-01010 | B13: =SUMIFS(Usage_Data!$D$2:$D$5001,Usage_Data!$C$2:$C$5001,$A13,Usage_Data!$G$2:$G$5001,1) | C13: =B13/8 | D13: =COUNTIFS(Usage_Data!$C$2:$C$5001,$A13,Usage_Data!$F$2:$F$5001,"surge",Usage_Data!$G$2:$G$5001,1) | E13: =SUMIFS(Usage_Data!$E$2:$E$5001,Usage_Data!$C$2:$C$5001,$A13,Usage_Data!$G$2:$G$5001,1)
A14: SS-01011 | B14: =SUMIFS(Usage_Data!$D$2:$D$5001,Usage_Data!$C$2:$C$5001,$A14,Usage_Data!$G$2:$G$5001,1) | C14: =B14/8 | D14: =COUNTIFS(Usage_Data!$C$2:$C$5001,$A14,Usage_Data!$F$2:$F$5001,"surge",Usage_Data!$G$2:$G$5001,1) | E14: =SUMIFS(Usage_Data!$E$2:$E$5001,Usage_Data!$C$2:$C$5001,$A14,Usage_Data!$G$2:$G$5001,1)
A15: SS-01012 | B15: =SUMIFS(Usage_Data!$D$2:$D$5001,Usage_Data!$C$2:$C$5001,$A15,Usage_Data!$G$2:$G$5001,1) | C15: =B15/8 | D15: =COUNTIFS(Usage_Data!$C$2:$C$5001,$A15,Usage_Data!$F$2:$F$5001,"surge",Usage_Data!$G$2:$G$5001,1) | E15: =SUMIFS(Usage_Data!$E$2:$E$5001,Usage_Data!$C$2:$C$5001,$A15,Usage_Data!$G$2:$G$5001,1)
... A236: SS-01233 | B236: =SUMIFS(Usage_Data!$D$2:$D$5001,Usage_Data!$C$2:$C$5001,$A236,Usage_Data!$G$2:$G$5001,1) | C236: =B236/8 | D236: =COUNTIFS(Usage_Data!$C$2:$C$5001,$A236,Usage_Data!$F$2:$F$5001,"surge",Usage_Data!$G$2:$G$5001,1) | E236: =SUMIFS(Usage_Data!$E$2:$E$5001,Usage_Data!$C$2:$C$5001,$A236,Usage_Data!$G$2:$G$5001,1)

Sheet ABC_Classification
A1: ABC classification from complete annual usage value + supplier concentration by class
A2: Annual usage value = SUMIFS(Usage_Data usage, sku) * Lots_Data unit_cost. Classes by cumulative value share: A<=80%, B<=95%, C>95% (80/95 split). annual_usage_value_total reconciles to 879602.39.
A4: site_sku | B4: site_id | C4: sku_id | D4: abc_class | E4: annual_usage_value | F4: unit_cost_usd | G4: annual_usage_qty | H4: supplier | I4: clinical_family
A5: HOSP-1|SS-01001 | B5: =INDEX(Lots_Data!$E$2:$E$234,MATCH($A5,Lots_Data!$A$2:$A$234,0)) | C5: =INDEX(Lots_Data!$A$2:$A$234,MATCH($A5,Lots_Data!$A$2:$A$234,0)) | D5: B | E5: =INDEX(Usage_Summary!$B$4:$B$236,MATCH($C5,Usage_Summary!$A$4:$A$236,0))*INDEX(Lots_Data!$G$2:$G$234,MATCH($A5,Lots_Data!$A$2:$A$234,0)) | F5: =INDEX(Lots_Data!$G$2:$G$234,MATCH($A5,Lots_Data!$A$2:$A$234,0)) | G5: =INDEX(Usage_Summary!$B$4:$B$236,MATCH($C5,Usage_Summary!$A$4:$A$236,0)) | H5: =INDEX(Lots_Data!$D$2:$D$234,MATCH($A5,Lots_Data!$A$2:$A$234,0)) | I5: =INDEX(Lots_Data!$C$2:$C$234,MATCH($A5,Lots_Data!$A$2:$A$234,0))
A6: HOSP-1|SS-01005 | B6: =INDEX(Lots_Data!$E$2:$E$234,MATCH($A6,Lots_Data!$A$2:$A$234,0)) | C6: =INDEX(Lots_Data!$A$2:$A$234,MATCH($A6,Lots_Data!$A$2:$A$234,0)) | D6: A | E6: =INDEX(Usage_Summary!$B$4:$B$236,MATCH($C6,Usage_Summary!$A$4:$A$236,0))*INDEX(Lots_Data!$G$2:$G$234,MATCH($A6,Lots_Data!$A$2:$A$234,0)) | F6: =INDEX(Lots_Data!$G$2:$G$234,MATCH($A6,Lots_Data!$A$2:$A$234,0)) | G6: =INDEX(Usage_Summary!$B$4:$B$236,MATCH($C6,Usage_Summary!$A$4:$A$236,0)) | H6: =INDEX(Lots_Data!$D$2:$D$234,MATCH($A6,Lots_Data!$A$2:$A$234,0)) | I6: =INDEX(Lots_Data!$C$2:$C$234,MATCH($A6,Lots_Data!$A$2:$A$234,0))
A7: HOSP-1|SS-01009 | B7: =INDEX(Lots_Data!$E$2:$E$234,MATCH($A7,Lots_Data!$A$2:$A$234,0)) | C7: =INDEX(Lots_Data!$A$2:$A$234,MATCH($A7,Lots_Data!$A$2:$A$234,0)) | D7: B | E7: =INDEX(Usage_Summary!$B$4:$B$236,MATCH($C7,Usage_Summary!$A$4:$A$236,0))*INDEX(Lots_Data!$G$2:$G$234,MATCH($A7,Lots_Data!$A$2:$A$234,0)) | F7: =INDEX(Lots_Data!$G$2:$G$234,MATCH($A7,Lots_Data!$A$2:$A$234,0)) | G7: =INDEX(Usage_Summary!$B$4:$B$236,MATCH($C7,Usage_Summary!$A$4:$A$236,0)) | H7: =INDEX(Lots_Data!$D$2:$D$234,MATCH($A7,Lots_Data!$A$2:$A$234,0)) | I7: =INDEX(Lots_Data!$C$2:$C$234,MATCH($A7,Lots_Data!$A$2:$A$234,0))
A8: HOSP-1|SS-01013 | B8: =INDEX(Lots_Data!$E$2:$E$234,MATCH($A8,Lots_Data!$A$2:$A$234,0)) | C8: =INDEX(Lots_Data!$A$2:$A$234,MATCH($A8,Lots_Data!$A$2:$A$234,0)) | D8: A | E8: =INDEX(Usage_Summary!$B$4:$B$236,MATCH($C8,Usage_Summary!$A$4:$A$236,0))*INDEX(Lots_Data!$G$2:$G$234,MATCH($A8,Lots_Data!$A$2:$A$234,0)) | F8: =INDEX(Lots_Data!$G$2:$G$234,MATCH($A8,Lots_Data!$A$2:$A$234,0)) | G8: =INDEX(Usage_Summary!$B$4:$B$236,MATCH($C8,Usage_Summary!$A$4:$A$236,0)) | H8: =INDEX(Lots_Data!$D$2:$D$234,MATCH($A8,Lots_Data!$A$2:$A$234,0)) | I8: =INDEX(Lots_Data!$C$2:$C$234,MATCH($A8,Lots_Data!$A$2:$A$234,0))
A9: HOSP-1|SS-01017 | B9: =INDEX(Lots_Data!$E$2:$E$234,MATCH($A9,Lots_Data!$A$2:$A$234,0)) | C9: =INDEX(Lots_Data!$A$2:$A$234,MATCH($A9,Lots_Data!$A$2:$A$234,0)) | D9: C | E9: =INDEX(Usage_Summary!$B$4:$B$236,MATCH($C9,Usage_Summary!$A$4:$A$236,0))*INDEX(Lots_Data!$G$2:$G$234,MATCH($A9,Lots_Data!$A$2:$A$234,0)) | F9: =INDEX(Lots_Data!$G$2:$G$234,MATCH($A9,Lots_Data!$A$2:$A$234,0)) | G9: =INDEX(Usage_Summary!$B$4:$B$236,MATCH($C9,Usage_Summary!$A$4:$A$236,0)) | H9: =INDEX(Lots_Data!$D$2:$D$234,MATCH($A9,Lots_Data!$A$2:$A$234,0)) | I9: =INDEX(Lots_Data!$C$2:$C$234,MATCH($A9,Lots_Data!$A$2:$A$234,0))
A10: HOSP-1|SS-01021 | B10: =INDEX(Lots_Data!$E$2:$E$234,MATCH($A10,Lots_Data!$A$2:$A$234,0)) | C10: =INDEX(Lots_Data!$A$2:$A$234,MATCH($A10,Lots_Data!$A$2:$A$234,0)) | D10: A | E10: =INDEX(Usage_Summary!$B$4:$B$236,MATCH($C10,Usage_Summary!$A$4:$A$236,0))*INDEX(Lots_Data!$G$2:$G$234,MATCH($A10,Lots_Data!$A$2:$A$234,0)) | F10: =INDEX(Lots_Data!$G$2:$G$234,MATCH($A10,Lots_Data!$A$2:$A$234,0)) | G10: =INDEX(Usage_Summary!$B$4:$B$236,MATCH($C10,Usage_Summary!$A$4:$A$236,0)) | H10: =INDEX(Lots_Data!$D$2:$D$234,MATCH($A10,Lots_Data!$A$2:$A$234,0)) | I10: =INDEX(Lots_Data!$C$2:$C$234,MATCH($A10,Lots_Data!$A$2:$A$234,0))
A11: HOSP-1|SS-01025 | B11: =INDEX(Lots_Data!$E$2:$E$234,MATCH($A11,Lots_Data!$A$2:$A$234,0)) | C11: =INDEX(Lots_Data!$A$2:$A$234,MATCH($A11,Lots_Data!$A$2:$A$234,0)) | D11: C | E11: =INDEX(Usage_Summary!$B$4:$B$236,MATCH($C11,Usage_Summary!$A$4:$A$236,0))*INDEX(Lots_Data!$G$2:$G$234,MATCH($A11,Lots_Data!$A$2:$A$234,0)) | F11: =INDEX(Lots_Data!$G$2:$G$234,MATCH($A11,Lots_Data!$A$2:$A$234,0)) | G11: =INDEX(Usage_Summary!$B$4:$B$236,MATCH($C11,Usage_Summary!$A$4:$A$236,0)) | H11: =INDEX(Lots_Data!$D$2:$D$234,MATCH($A11,Lots_Data!$A$2:$A$234,0)) | I11: =INDEX(Lots_Data!$C$2:$C$234,MATCH($A11,Lots_Data!$A$2:$A$234,0))
A12: HOSP-1|SS-01029 | B12: =INDEX(Lots_Data!$E$2:$E$234,MATCH($A12,Lots_Data!$A$2:$A$234,0)) | C12: =INDEX(Lots_Data!$A$2:$A$234,MATCH($A12,Lots_Data!$A$2:$A$234,0)) | D12: B | E12: =INDEX(Usage_Summary!$B$4:$B$236,MATCH($C12,Usage_Summary!$A$4:$A$236,0))*INDEX(Lots_Data!$G$2:$G$234,MATCH($A12,Lots_Data!$A$2:$A$234,0)) | F12: =INDEX(Lots_Data!$G$2:$G$234,MATCH($A12,Lots_Data!$A$2:$A$234,0)) | G12: =INDEX(Usage_Summary!$B$4:$B$236,MATCH($C12,Usage_Summary!$A$4:$A$236,0)) | H12: =INDEX(Lots_Data!$D$2:$D$234,MATCH($A12,Lots_Data!$A$2:$A$234,0)) | I12: =INDEX(Lots_Data!$C$2:$C$234,MATCH($A12,Lots_Data!$A$2:$A$234,0))
A13: HOSP-1|SS-01033 | B13: =INDEX(Lots_Data!$E$2:$E$234,MATCH($A13,Lots_Data!$A$2:$A$234,0)) | C13: =INDEX(Lots_Data!$A$2:$A$234,MATCH($A13,Lots_Data!$A$2:$A$234,0)) | D13: A | E13: =INDEX(Usage_Summary!$B$4:$B$236,MATCH($C13,Usage_Summary!$A$4:$A$236,0))*INDEX(Lots_Data!$G$2:$G$234,MATCH($A13,Lots_Data!$A$2:$A$234,0)) | F13: =INDEX(Lots_Data!$G$2:$G$234,MATCH($A13,Lots_Data!$A$2:$A$234,0)) | G13: =INDEX(Usage_Summary!$B$4:$B$236,MATCH($C13,Usage_Summary!$A$4:$A$236,0)) | H13: =INDEX(Lots_Data!$D$2:$D$234,MATCH($A13,Lots_Data!$A$2:$A$234,0)) | I13: =INDEX(Lots_Data!$C$2:$C$234,MATCH($A13,Lots_Data!$A$2:$A$234,0))
A14: HOSP-1|SS-01037 | B14: =INDEX(Lots_Data!$E$2:$E$234,MATCH($A14,Lots_Data!$A$2:$A$234,0)) | C14: =INDEX(Lots_Data!$A$2:$A$234,MATCH($A14,Lots_Data!$A$2:$A$234,0)) | D14: A | E14: =INDEX(Usage_Summary!$B$4:$B$236,MATCH($C14,Usage_Summary!$A$4:$A$236,0))*INDEX(Lots_Data!$G$2:$G$234,MATCH($A14,Lots_Data!$A$2:$A$234,0)) | F14: =INDEX(Lots_Data!$G$2:$G$234,MATCH($A14,Lots_Data!$A$2:$A$234,0)) | G14: =INDEX(Usage_Summary!$B$4:$B$236,MATCH($C14,Usage_Summary!$A$4:$A$236,0)) | H14: =INDEX(Lots_Data!$D$2:$D$234,MATCH($A14,Lots_Data!$A$2:$A$234,0)) | I14: =INDEX(Lots_Data!$C$2:$C$234,MATCH($A14,Lots_Data!$A$2:$A$234,0))
A15: HOSP-1|SS-01041 | B15: =INDEX(Lots_Data!$E$2:$E$234,MATCH($A15,Lots_Data!$A$2:$A$234,0)) | C15: =INDEX(Lots_Data!$A$2:$A$234,MATCH($A15,Lots_Data!$A$2:$A$234,0)) | D15: A | E15: =INDEX(Usage_Summary!$B$4:$B$236,MATCH($C15,Usage_Summary!$A$4:$A$236,0))*INDEX(Lots_Data!$G$2:$G$234,MATCH($A15,Lots_Data!$A$2:$A$234,0)) | F15: =INDEX(Lots_Data!$G$2:$G$234,MATCH($A15,Lots_Data!$A$2:$A$234,0)) | G15: =INDEX(Usage_Summary!$B$4:$B$236,MATCH($C15,Usage_Summary!$A$4:$A$236,0)) | H15: =INDEX(Lots_Data!$D$2:$D$234,MATCH($A15,Lots_Data!$A$2:$A$234,0)) | I15: =INDEX(Lots_Data!$C$2:$C$234,MATCH($A15,Lots_Data!$A$2:$A$234,0))
A16: HOSP-1|SS-01045 | B16: =INDEX(Lots_Data!$E$2:$E$234,MATCH($A16,Lots_Data!$A$2:$A$234,0)) | C16: =INDEX(Lots_Data!$A$2:$A$234,MATCH($A16,Lots_Data!$A$2:$A$234,0)) | D16: A | E16: =INDEX(Usage_Summary!$B$4:$B$236,MATCH($C16,Usage_Summary!$A$4:$A$236,0))*INDEX(Lots_Data!$G$2:$G$234,MATCH($A16,Lots_Data!$A$2:$A$234,0)) | F16: =INDEX(Lots_Data!$G$2:$G$234,MATCH($A16,Lots_Data!$A$2:$A$234,0)) | G16: =INDEX(Usage_Summary!$B$4:$B$236,MATCH($C16,Usage_Summary!$A$4:$A$236,0)) | H16: =INDEX(Lots_Data!$D$2:$D$234,MATCH($A16,Lots_Data!$A$2:$A$234,0)) | I16: =INDEX(Lots_Data!$C$2:$C$234,MATCH($A16,Lots_Data!$A$2:$A$234,0))
... A237: HOSP-4|SS-01232 | B237: =INDEX(Lots_Data!$E$2:$E$234,MATCH($A237,Lots_Data!$A$2:$A$234,0)) | C237: =INDEX(Lots_Data!$A$2:$A$234,MATCH($A237,Lots_Data!$A$2:$A$234,0)) | D237: A | E237: =INDEX(Usage_Summary!$B$4:$B$236,MATCH($C237,Usage_Summary!$A$4:$A$236,0))*INDEX(Lots_Data!$G$2:$G$234,MATCH($A237,Lots_Data!$A$2:$A$234,0)) | F237: =INDEX(Lots_Data!$G$2:$G$234,MATCH($A237,Lots_Data!$A$2:$A$234,0)) | G237: =INDEX(Usage_Summary!$B$4:$B$236,MATCH($C237,Usage_Summary!$A$4:$A$236,0)) | H237: =INDEX(Lots_Data!$D$2:$D$234,MATCH($A237,Lots_Data!$A$2:$A$234,0)) | I237: =INDEX(Lots_Data!$C$2:$C$234,MATCH($A237,Lots_Data!$A$2:$A$234,0))
A239: Class counts (exact)
A240: class | B240: sku_count | C240: value_share_pct
A241: A | B241: =COUNTIF($D$5:$D$237,$A241) | C241: =SUMIF($D$5:$D$237,$A241,$E$5:$E$237)/SUM($E$5:$E$237)*100
A242: B | B242: =COUNTIF($D$5:$D$237,$A242) | C242: =SUMIF($D$5:$D$237,$A242,$E$5:$E$237)/SUM($E$5:$E$237)*100
A243: C | B243: =COUNTIF($D$5:$D$237,$A243) | C243: =SUMIF($D$5:$D$237,$A243,$E$5:$E$237)/SUM($E$5:$E$237)*100
A246: Supplier concentration by class (exact counts and shares)
A247: abc_class | B247: supplier | C247: sku_count | D247: value_usd | E247: value_share_in_class_pct
A248: A | B248: Aegis Clinical Supply | C248: =COUNTIFS($D$5:$D$237,$A248,$H$5:$H$237,$B248) | D248: =SUMIFS($E$5:$E$237,$D$5:$D$237,$A248,$H$5:$H$237,$B248) | E248: =IF(SUMIFS($E$5:$E$237,$D$5:$D$237,$A248)=0,0,$D248/SUMIFS($E$5:$E$237,$D$5:$D$237,$A248)*100)
A249: A | B249: HarborMed Logistics | C249: =COUNTIFS($D$5:$D$237,$A249,$H$5:$H$237,$B249) | D249: =SUMIFS($E$5:$E$237,$D$5:$D$237,$A249,$H$5:$H$237,$B249) | E249: =IF(SUMIFS($E$5:$E$237,$D$5:$D$237,$A249)=0,0,$D249/SUMIFS($E$5:$E$237,$D$5:$D$237,$A249)*100)
A250: A | B250: MedAxis Distribution | C250: =COUNTIFS($D$5:$D$237,$A250,$H$5:$H$237,$B250) | D250: =SUMIFS($E$5:$E$237,$D$5:$D$237,$A250,$H$5:$H$237,$B250) | E250: =IF(SUMIFS($E$5:$E$237,$D$5:$D$237,$A250)=0,0,$D250/SUMIFS($E$5:$E$237,$D$5:$D$237,$A250)*100)
A251: A | B251: Northstar Surgical | C251: =COUNTIFS($D$5:$D$237,$A251,$H$5:$H$237,$B251) | D251: =SUMIFS($E$5:$E$237,$D$5:$D$237,$A251,$H$5:$H$237,$B251) | E251: =IF(SUMIFS($E$5:$E$237,$D$5:$D$237,$A251)=0,0,$D251/SUMIFS($E$5:$E$237,$D$5:$D$237,$A251)*100)
A252: A | B252: SterilePath Medical | C252: =COUNTIFS($D$5:$D$237,$A252,$H$5:$H$237,$B252) | D252: =SUMIFS($E$5:$E$237,$D$5:$D$237,$A252,$H$5:$H$237,$B252) | E252: =IF(SUMIFS($E$5:$E$237,$D$5:$D$237,$A252)=0,0,$D252/SUMIFS($E$5:$E$237,$D$5:$D$237,$A252)*100)
A253: B | B253: Aegis Clinical Supply | C253: =COUNTIFS($D$5:$D$237,$A253,$H$5:$H$237,$B253) | D253: =SUMIFS($E$5:$E$237,$D$5:$D$237,$A253,$H$5:$H$237,$B253) | E253: =IF(SUMIFS($E$5:$E$237,$D$5:$D$237,$A253)=0,0,$D253/SUMIFS($E$5:$E$237,$D$5:$D$237,$A253)*100)
A254: B | B254: HarborMed Logistics | C254: =COUNTIFS($D$5:$D$237,$A254,$H$5:$H$237,$B254) | D254: =SUMIFS($E$5:$E$237,$D$5:$D$237,$A254,$H$5:$H$237,$B254) | E254: =IF(SUMIFS($E$5:$E$237,$D$5:$D$237,$A254)=0,0,$D254/SUMIFS($E$5:$E$237,$D$5:$D$237,$A254)*100)
A255: B | B255: MedAxis Distribution | C255: =COUNTIFS($D$5:$D$237,$A255,$H$5:$H$237,$B255) | D255: =SUMIFS($E$5:$E$237,$D$5:$D$237,$A255,$H$5:$H$237,$B255) | E255: =IF(SUMIFS($E$5:$E$237,$D$5:$D$237,$A255)=0,0,$D255/SUMIFS($E$5:$E$237,$D$5:$D$237,$A255)*100)
A256: B | B256: Northstar Surgical | C256: =COUNTIFS($D$5:$D$237,$A256,$H$5:$H$237,$B256) | D256: =SUMIFS($E$5:$E$237,$D$5:$D$237,$A256,$H$5:$H$237,$B256) | E256: =IF(SUMIFS($E$5:$E$237,$D$5:$D$237,$A256)=0,0,$D256/SUMIFS($E$5:$E$237,$D$5:$D$237,$A256)*100)
A257: B | B257: SterilePath Medical | C257: =COUNTIFS($D$5:$D$237,$A257,$H$5:$H$237,$B257) | D257: =SUMIFS($E$5:$E$237,$D$5:$D$237,$A257,$H$5:$H$237,$B257) | E257: =IF(SUMIFS($E$5:$E$237,$D$5:$D$237,$A257)=0,0,$D257/SUMIFS($E$5:$E$237,$D$5:$D$237,$A257)*100)
A258: C | B258: Aegis Clinical Supply | C258: =COUNTIFS($D$5:$D$237,$A258,$H$5:$H$237,$B258) | D258: =SUMIFS($E$5:$E$237,$D$5:$D$237,$A258,$H$5:$H$237,$B258) | E258: =IF(SUMIFS($E$5:$E$237,$D$5:$D$237,$A258)=0,0,$D258/SUMIFS($E$5:$E$237,$D$5:$D$237,$A258)*100)
A259: C | B259: HarborMed Logistics | C259: =COUNTIFS($D$5:$D$237,$A259,$H$5:$H$237,$B259) | D259: =SUMIFS($E$5:$E$237,$D$5:$D$237,$A259,$H$5:$H$237,$B259) | E259: =IF(SUMIFS($E$5:$E$237,$D$5:$D$237,$A259)=0,0,$D259/SUMIFS($E$5:$E$237,$D$5:$D$237,$A259)*100)
... A262: C | B262: SterilePath Medical | C262: =COUNTIFS($D$5:$D$237,$A262,$H$5:$H$237,$B262) | D262: =SUMIFS($E$5:$E$237,$D$5:$D$237,$A262,$H$5:$H$237,$B262) | E262: =IF(SUMIFS($E$5:$E$237,$D$5:$D$237,$A262)=0,0,$D262/SUMIFS($E$5:$E$237,$D$5:$D$237,$A262)*100)

Sheet Volatility_Reorder
A1: Demand volatility (CV) and dynamic reorder point / safety stock
A2: CV = STDEV.P(monthly usage)/AVERAGE(monthly usage) over complete periods; deterministic sparse-demand treatment: SKUs with mean=0 get CV=0 (no demand -> no variability). Dynamic ROP = (mean/30)*lead_time + z*STDEV.P/30*SQRT(lead_time); safety stock = z*sd_daily*SQRT(LT). z=1.65 (95% service level, disclosed assumption, editable in Inputs).
A4: sku_id | B4: mean_monthly_usage | C4: std_monthly_usage | D4: cv | E4: lead_time_days | F4: safety_stock | G4: dynamic_rop | H4: submitted_static_rop
A5: SS-01001 | B5: =AVERAGEIFS(Usage_Data!$D$2:$D$5001,Usage_Data!$C$2:$C$5001,$A5) | C5: =SQRT(SUMPRODUCT((Usage_Data!$C$2:$C$5001=$A5)*(Usage_Data!$D$2:$D$5001-$B5)^2)/MAX(1,COUNTIF(Usage_Data!$C$2:$C$5001,$A5)))) | D5: =IF($B5=0,0,$C5/$B5) | E5: =INDEX(Lots_Data!$N$2:$N$234,MATCH($A5,Lots_Data!$A$2:$A$234,0)) | F5: =1.65*($C5/30)*SQRT($E5) | G5: =($B5/30)*$E5+$F5 | H5: =INDEX(Lots_Data!$S$2:$S$234,MATCH($A5,Lots_Data!$A$2:$A$234,0))
A6: SS-01002 | B6: =AVERAGEIFS(Usage_Data!$D$2:$D$5001,Usage_Data!$C$2:$C$5001,$A6) | C6: =SQRT(SUMPRODUCT((Usage_Data!$C$2:$C$5001=$A6)*(Usage_Data!$D$2:$D$5001-$B6)^2)/MAX(1,COUNTIF(Usage_Data!$C$2:$C$5001,$A6)))) | D6: =IF($B6=0,0,$C6/$B6) | E6: =INDEX(Lots_Data!$N$2:$N$234,MATCH($A6,Lots_Data!$A$2:$A$234,0)) | F6: =1.65*($C6/30)*SQRT($E6) | G6: =($B6/30)*$E6+$F6 | H6: =INDEX(Lots_Data!$S$2:$S$234,MATCH($A6,Lots_Data!$A$2:$A$234,0))
A7: SS-01003 | B7: =AVERAGEIFS(Usage_Data!$D$2:$D$5001,Usage_Data!$C$2:$C$5001,$A7) | C7: =SQRT(SUMPRODUCT((Usage_Data!$C$2:$C$5001=$A7)*(Usage_Data!$D$2:$D$5001-$B7)^2)/MAX(1,COUNTIF(Usage_Data!$C$2:$C$5001,$A7)))) | D7: =IF($B7=0,0,$C7/$B7) | E7: =INDEX(Lots_Data!$N$2:$N$234,MATCH($A7,Lots_Data!$A$2:$A$234,0)) | F7: =1.65*($C7/30)*SQRT($E7) | G7: =($B7/30)*$E7+$F7 | H7: =INDEX(Lots_Data!$S$2:$S$234,MATCH($A7,Lots_Data!$A$2:$A$234,0))
A8: SS-01004 | B8: =AVERAGEIFS(Usage_Data!$D$2:$D$5001,Usage_Data!$C$2:$C$5001,$A8) | C8: =SQRT(SUMPRODUCT((Usage_Data!$C$2:$C$5001=$A8)*(Usage_Data!$D$2:$D$5001-$B8)^2)/MAX(1,COUNTIF(Usage_Data!$C$2:$C$5001,$A8)))) | D8: =IF($B8=0,0,$C8/$B8) | E8: =INDEX(Lots_Data!$N$2:$N$234,MATCH($A8,Lots_Data!$A$2:$A$234,0)) | F8: =1.65*($C8/30)*SQRT($E8) | G8: =($B8/30)*$E8+$F8 | H8: =INDEX(Lots_Data!$S$2:$S$234,MATCH($A8,Lots_Data!$A$2:$A$234,0))
A9: SS-01005 | B9: =AVERAGEIFS(Usage_Data!$D$2:$D$5001,Usage_Data!$C$2:$C$5001,$A9) | C9: =SQRT(SUMPRODUCT((Usage_Data!$C$2:$C$5001=$A9)*(Usage_Data!$D$2:$D$5001-$B9)^2)/MAX(1,COUNTIF(Usage_Data!$C$2:$C$5001,$A9)))) | D9: =IF($B9=0,0,$C9/$B9) | E9: =INDEX(Lots_Data!$N$2:$N$234,MATCH($A9,Lots_Data!$A$2:$A$234,0)) | F9: =1.65*($C9/30)*SQRT($E9) | G9: =($B9/30)*$E9+$F9 | H9: =INDEX(Lots_Data!$S$2:$S$234,MATCH($A9,Lots_Data!$A$2:$A$234,0))
A10: SS-01006 | B10: =AVERAGEIFS(Usage_Data!$D$2:$D$5001,Usage_Data!$C$2:$C$5001,$A10) | C10: =SQRT(SUMPRODUCT((Usage_Data!$C$2:$C$5001=$A10)*(Usage_Data!$D$2:$D$5001-$B10)^2)/MAX(1,COUNTIF(Usage_Data!$C$2:$C$5001,$A10)))) | D10: =IF($B10=0,0,$C10/$B10) | E10: =INDEX(Lots_Data!$N$2:$N$234,MATCH($A10,Lots_Data!$A$2:$A$234,0)) | F10: =1.65*($C10/30)*SQRT($E10) | G10: =($B10/30)*$E10+$F10 | H10: =INDEX(Lots_Data!$S$2:$S$234,MATCH($A10,Lots_Data!$A$2:$A$234,0))
A11: SS-01007 | B11: =AVERAGEIFS(Usage_Data!$D$2:$D$5001,Usage_Data!$C$2:$C$5001,$A11) | C11: =SQRT(SUMPRODUCT((Usage_Data!$C$2:$C$5001=$A11)*(Usage_Data!$D$2:$D$5001-$B11)^2)/MAX(1,COUNTIF(Usage_Data!$C$2:$C$5001,$A11)))) | D11: =IF($B11=0,0,$C11/$B11) | E11: =INDEX(Lots_Data!$N$2:$N$234,MATCH($A11,Lots_Data!$A$2:$A$234,0)) | F11: =1.65*($C11/30)*SQRT($E11) | G11: =($B11/30)*$E11+$F11 | H11: =INDEX(Lots_Data!$S$2:$S$234,MATCH($A11,Lots_Data!$A$2:$A$234,0))
A12: SS-01008 | B12: =AVERAGEIFS(Usage_Data!$D$2:$D$5001,Usage_Data!$C$2:$C$5001,$A12) | C12: =SQRT(SUMPRODUCT((Usage_Data!$C$2:$C$5001=$A12)*(Usage_Data!$D$2:$D$5001-$B12)^2)/MAX(1,COUNTIF(Usage_Data!$C$2:$C$5001,$A12)))) | D12: =IF($B12=0,0,$C12/$B12) | E12: =INDEX(Lots_Data!$N$2:$N$234,MATCH($A12,Lots_Data!$A$2:$A$234,0)) | F12: =1.65*($C12/30)*SQRT($E12) | G12: =($B12/30)*$E12+$F12 | H12: =INDEX(Lots_Data!$S$2:$S$234,MATCH($A12,Lots_Data!$A$2:$A$234,0))
A13: SS-01009 | B13: =AVERAGEIFS(Usage_Data!$D$2:$D$5001,Usage_Data!$C$2:$C$5001,$A13) | C13: =SQRT(SUMPRODUCT((Usage_Data!$C$2:$C$5001=$A13)*(Usage_Data!$D$2:$D$5001-$B13)^2)/MAX(1,COUNTIF(Usage_Data!$C$2:$C$5001,$A13)))) | D13: =IF($B13=0,0,$C13/$B13) | E13: =INDEX(Lots_Data!$N$2:$N$234,MATCH($A13,Lots_Data!$A$2:$A$234,0)) | F13: =1.65*($C13/30)*SQRT($E13) | G13: =($B13/30)*$E13+$F13 | H13: =INDEX(Lots_Data!$S$2:$S$234,MATCH($A13,Lots_Data!$A$2:$A$234,0))
A14: SS-01010 | B14: =AVERAGEIFS(Usage_Data!$D$2:$D$5001,Usage_Data!$C$2:$C$5001,$A14) | C14: =SQRT(SUMPRODUCT((Usage_Data!$C$2:$C$5001=$A14)*(Usage_Data!$D$2:$D$5001-$B14)^2)/MAX(1,COUNTIF(Usage_Data!$C$2:$C$5001,$A14)))) | D14: =IF($B14=0,0,$C14/$B14) | E14: =INDEX(Lots_Data!$N$2:$N$234,MATCH($A14,Lots_Data!$A$2:$A$234,0)) | F14: =1.65*($C14/30)*SQRT($E14) | G14: =($B14/30)*$E14+$F14 | H14: =INDEX(Lots_Data!$S$2:$S$234,MATCH($A14,Lots_Data!$A$2:$A$234,0))
A15: SS-01011 | B15: =AVERAGEIFS(Usage_Data!$D$2:$D$5001,Usage_Data!$C$2:$C$5001,$A15) | C15: =SQRT(SUMPRODUCT((Usage_Data!$C$2:$C$5001=$A15)*(Usage_Data!$D$2:$D$5001-$B15)^2)/MAX(1,COUNTIF(Usage_Data!$C$2:$C$5001,$A15)))) | D15: =IF($B15=0,0,$C15/$B15) | E15: =INDEX(Lots_Data!$N$2:$N$234,MATCH($A15,Lots_Data!$A$2:$A$234,0)) | F15: =1.65*($C15/30)*SQRT($E15) | G15: =($B15/30)*$E15+$F15 | H15: =INDEX(Lots_Data!$S$2:$S$234,MATCH($A15,Lots_Data!$A$2:$A$234,0))
A16: SS-01012 | B16: =AVERAGEIFS(Usage_Data!$D$2:$D$5001,Usage_Data!$C$2:$C$5001,$A16) | C16: =SQRT(SUMPRODUCT((Usage_Data!$C$2:$C$5001=$A16)*(Usage_Data!$D$2:$D$5001-$B16)^2)/MAX(1,COUNTIF(Usage_Data!$C$2:$C$5001,$A16)))) | D16: =IF($B16=0,0,$C16/$B16) | E16: =INDEX(Lots_Data!$N$2:$N$234,MATCH($A16,Lots_Data!$A$2:$A$234,0)) | F16: =1.65*($C16/30)*SQRT($E16) | G16: =($B16/30)*$E16+$F16 | H16: =INDEX(Lots_Data!$S$2:$S$234,MATCH($A16,Lots_Data!$A$2:$A$234,0))
... A237: SS-01233 | B237: =AVERAGEIFS(Usage_Data!$D$2:$D$5001,Usage_Data!$C$2:$C$5001,$A237) | C237: =SQRT(SUMPRODUCT((Usage_Data!$C$2:$C$5001=$A237)*(Usage_Data!$D$2:$D$5001-$B237)^2)/MAX(1,COUNTIF(Usage_Data!$C$2:$C$5001,$A237)))) | D237: =IF($B237=0,0,$C237/$B237) | E237: =INDEX(Lots_Data!$N$2:$N$234,MATCH($A237,Lots_Data!$A$2:$A$234,0)) | F237: =1.65*($C237/30)*SQRT($E237) | G237: =($B237/30)*$E237+$F237 | H237: =INDEX(Lots_Data!$S$2:$S$234,MATCH($A237,Lots_Data!$A$2:$A$234,0))
A239: Network CV / dynamic reorder summary
A240: SKUs with demand | B240: 233
A241: Mean CV | B241: 1.047
A242: Median CV | B242: 1.011
A243: Min / Max CV | B243: 0.261 / 2.051
A244: % SKUs with CV>1 (volatile / intermittent) | B244: 50.6%
A245: Total safety stock (units) | B245: 1183
A246: Total dynamic ROP (units) | B246: 2834.6
A247: Service level z | B247: 1.65

Sheet Sensitivity
A1: Leave-one-out sensitivity: decision change when each supplier / site capacity is removed
A2: For each supplier (and each site) removed individually, recompute ABC classes on the remaining annual-usage-value set (80/95 split) and report the change in A-class SKU count (dA) and the remaining value share. dA<0 means the removed node was load-bearing for A-class coverage. annual_usage_value_total reconciles to 879602.39.
A4: Baseline class counts (all nodes present)
A5: A | B5: B | C5: C | D5: Total
A6: 106 | B6: 65 | C6: 62 | D6: =SUM(A6:C6)
A8: SUPPLIER REMOVAL SENSITIVITY
A9: supplier | B9: removed_value_usd | C9: removed_pct | D9: remaining_value_pct | E9: dA_vs_baseline
A10: Aegis Clinical Supply | B10: =SUMIFS(ABC_Classification!$E$4:$E$236,ABC_Classification!$H$4:$H$236,$A10) | C10: =IF(SUM(ABC_Classification!$E$4:$E$236)=0,0,$B10/SUM(ABC_Classification!$E$4:$E$236)*100) | D10: =100-$C10
A11: HarborMed Logistics | B11: =SUMIFS(ABC_Classification!$E$4:$E$236,ABC_Classification!$H$4:$H$236,$A11) | C11: =IF(SUM(ABC_Classification!$E$4:$E$236)=0,0,$B11/SUM(ABC_Classification!$E$4:$E$236)*100) | D11: =100-$C11
A12: MedAxis Distribution | B12: =SUMIFS(ABC_Classification!$E$4:$E$236,ABC_Classification!$H$4:$H$236,$A12) | C12: =IF(SUM(ABC_Classification!$E$4:$E$236)=0,0,$B12/SUM(ABC_Classification!$E$4:$E$236)*100) | D12: =100-$C12
A13: Northstar Surgical | B13: =SUMIFS(ABC_Classification!$E$4:$E$236,ABC_Classification!$H$4:$H$236,$A13) | C13: =IF(SUM(ABC_Classification!$E$4:$E$236)=0,0,$B13/SUM(ABC_Classification!$E$4:$E$236)*100) | D13: =100-$C13
A14: SterilePath Medical | B14: =SUMIFS(ABC_Classification!$E$4:$E$236,ABC_Classification!$H$4:$H$236,$A14) | C14: =IF(SUM(ABC_Classification!$E$4:$E$236)=0,0,$B14/SUM(ABC_Classification!$E$4:$E$236)*100) | D14: =100-$C14
A16: dA = change in A-class SKU count vs baseline after removing the node and recomputing the 80/95 ABC split on remaining value (see portal Sensitivity tab for exact per-node dA).
A18: SITE REMOVAL SENSITIVITY
A19: supplier | B19: removed_value_usd | C19: removed_pct | D19: remaining_value_pct | E19: dA_vs_baseline
A20: HOSP-1 | B20: =SUMIFS(ABC_Classification!$E$4:$E$236,ABC_Classification!$B$4:$B$236,$A20) | C20: =IF(SUM(ABC_Classification!$E$4:$E$236)=0,0,$B20/SUM(ABC_Classification!$E$4:$E$236)*100) | D20: =100-$C20
A21: HOSP-2 | B21: =SUMIFS(ABC_Classification!$E$4:$E$236,ABC_Classification!$B$4:$B$236,$A21) | C21: =IF(SUM(ABC_Classification!$E$4:$E$236)=0,0,$B21/SUM(ABC_Classification!$E$4:$E$236)*100) | D21: =100-$C21
A22: HOSP-3 | B22: =SUMIFS(ABC_Classification!$E$4:$E$236,ABC_Classification!$B$4:$B$236,$A22) | C22: =IF(SUM(ABC_Classification!$E$4:$E$236)=0,0,$B22/SUM(ABC_Classification!$E$4:$E$236)*100) | D22: =100-$C22
A23: HOSP-4 | B23: =SUMIFS(ABC_Classification!$E$4:$E$236,ABC_Classification!$B$4:$B$236,$A23) | C23: =IF(SUM(ABC_Classification!$E$4:$E$236)=0,0,$B23/SUM(ABC_Classification!$E$4:$E$236)*100) | D23: =100-$C23

Sheet Supplier_Info
A1: supplier_id | B1: supplier_name | C1: contact_name | D1: contact_email | E1: payment_terms | F1: contract_start_date | G1: contract_end_date | H1: minimum_order_value
A2: 1 | B2: Northstar Surgical | C2: Clinical Supply Contact 1 | D2: contracts1@northsound-health.example | E2: Net 30 | F2: 2025-01-15 | G2: 2027-01-14 | H2: 2000
A3: 2 | B3: MedAxis Distribution | C3: Clinical Supply Contact 2 | D3: contracts2@northsound-health.example | E3: 2/10 Net 30 | F3: 2025-03-01 | G3: 2027-02-28 | H3: 1500
A4: 3 | B4: SterilePath Medical | C4: Clinical Supply Contact 3 | D4: contracts3@northsound-health.example | E4: Net 45 | F4: 2024-07-01 | G4: 2027-06-30 | H4: 3000
A5: 4 | B5: Aegis Clinical Supply | C5: Clinical Supply Contact 4 | D5: contracts4@northsound-health.example | E5: Net 30 | F5: 2025-06-01 | G5: 2027-05-31 | H5: 1000
A6: 5 | B6: HarborMed Logistics | C6: Clinical Supply Contact 5 | D6: contracts5@northsound-health.example | E6: 2/10 Net 30 | F6: 2025-02-01 | G6: 2028-01-31 | H6: 2500

Sheet PO_Data
A1: po_id | B1: po_number | C1: supplier_id | D1: order_date | E1: requested_delivery_date | F1: actual_delivery_date | G1: total_amount | H1: status | I1: items_ordered | J1: items_received | K1: discrepancy_notes
A2: 1 | B2: PO-2020-0001 | C2: 1 | D2: 2020-11-23 | E2: 2020-11-30 | F2: 2020-11-30 | G2: 18938.84 | H2: Partially Delivered | I2: 44 | J2: 37 | K2: 2 cases arrived damaged during transit
A3: 2 | B3: PO-2020-0002 | C3: 1 | D3: 2020-01-16 | E3: 2020-01-23 | F3: 2020-01-23 | G3: 13623.17 | H3: Delivered | I3: 11 | J3: 11
A4: 3 | B4: PO-2020-0003 | C4: 1 | D4: 2020-12-25 | E4: 2020-12-28 | F4: 2020-12-28 | G4: 19452.57 | H4: Delivered | I4: 20 | J4: 20
A5: 4 | B5: PO-2020-0004 | C5: 1 | D5: 2020-03-20 | E5: 2020-03-24 | F5: 2020-03-24 | G5: 4350.84 | H5: Partially Delivered | I5: 34 | J5: 28 | K5: Partial fulfillment due to production delay
A6: 5 | B6: PO-2020-0005 | C6: 1 | D6: 2020-05-15 | E6: 2020-05-21 | F6: 2020-05-20 | G6: 3812.4 | H6: Delivered | I6: 28 | J6: 28
A7: 6 | B7: PO-2020-0006 | C7: 1 | D7: 2020-07-04 | E7: 2020-07-06 | F7: 2020-07-06 | G7: 3053.96 | H7: Delivered | I7: 24 | J7: 24
A8: 7 | B8: PO-2020-0007 | C8: 1 | D8: 2020-04-29 | E8: 2020-05-05 | F8: 2020-05-05 | G8: 5741.04 | H8: Delivered | I8: 32 | J8: 32
A9: 8 | B9: PO-2020-0008 | C9: 1 | D9: 2020-12-15 | E9: 2020-12-18 | F9: 2020-12-18 | G9: 14285.22 | H9: Delivered | I9: 25 | J9: 25
A10: 9 | B10: PO-2020-0009 | C10: 1 | D10: 2020-11-23 | E10: 2020-11-27 | F10: 2020-11-27 | G10: 7268.11 | H10: Delivered | I10: 12 | J10: 12
A11: 10 | B11: PO-2020-0010 | C11: 1 | D11: 2020-02-03 | E11: 2020-02-06 | F11: 2020-02-06 | G11: 6890.41 | H11: Delivered | I11: 41 | J11: 41
A12: 11 | B12: PO-2020-0011 | C12: 1 | D12: 2020-08-22 | E12: 2020-08-27 | F12: 2020-08-27 | G12: 19181.32 | H12: Delivered | I12: 37 | J12: 37
A13: 12 | B13: PO-2020-0012 | C13: 1 | D13: 2020-04-22 | E13: 2020-04-27 | F13: 2020-04-30 | G13: 13719.1 | H13: Delivered | I13: 15 | J13: 15
A14: 13 | B14: PO-2020-0013 | C14: 1 | D14: 2020-03-19 | E14: 2020-03-21 | F14: 2020-03-21 | G14: 10849.65 | H14: Delivered | I14: 48 | J14: 48
A15: 14 | B15: PO-2020-0014 | C15: 1 | D15: 2020-10-10 | E15: 2020-10-12 | F15: 2020-10-13 | G15: 17646.52 | H15: Delivered | I15: 17 | J15: 17
A16: 15 | B16: PO-2020-0015 | C16: 1 | D16: 2020-05-16 | E16: 2020-05-21 | F16: 2020-05-21 | G16: 12435.65 | H16: Delivered | I16: 26 | J16: 26
A17: 16 | B17: PO-2020-0016 | C17: 1 | D17: 2020-09-16 | E17: 2020-09-19 | F17: 2020-09-24 | G17: 21358.4 | H17: Delivered | I17: 42 | J17: 42
A18: 17 | B18: PO-2020-0017 | C18: 1 | D18: 2020-03-23 | E18: 2020-03-25 | G18: 15775.73 | H18: Cancelled | I18: 41 | J18: 0 | K18: Order cancelled by supplier due to stock-out
A19: 18 | B19: PO-2020-0018 | C19: 1 | D19: 2020-07-04 | E19: 2020-07-08 | F19: 2020-07-13 | G19: 7507.4 | H19: Delivered | I19: 25 | J19: 25
A20: 19 | B20: PO-2020-0019 | C20: 1 | D20: 2020-02-13 | E20: 2020-02-17 | F20: 2020-02-20 | G20: 4953 | H20: Delivered | I20: 40 | J20: 40
A21: 20 | B21: PO-2020-0020 | C21: 1 | D21: 2020-09-27 | E21: 2020-09-29 | F21: 2020-10-06 | G21: 24180.35 | H21: Delivered | I21: 44 | J21: 44
A22: 21 | B22: PO-2020-0021 | C22: 1 | D22: 2020-12-31 | E22: 2021-01-02 | F22: 2021-01-01 | G22: 22691.12 | H22: Partially Delivered | I22: 38 | J22: 34 | K22: Short-shipped: supplier back-ordered 3 SKUs
A23: 22 | B23: PO-2020-0022 | C23: 1 | D23: 2020-06-22 | E23: 2020-07-03 | F23: 2020-07-03 | G23: 15534.12 | H23: Partially Delivered | I23: 10 | J23: 9 | K23: Temperature excursion noted on 4 cases
A24: 23 | B24: PO-2020-0023 | C24: 1 | D24: 2020-02-04 | E24: 2020-02-12 | F24: 2020-02-12 | G24: 8404.98 | H24: Delivered | I24: 41 | J24: 41
A25: 24 | B25: PO-2020-0024 | C25: 1 | D25: 2020-10-19 | E25: 2020-10-21 | F25: 2020-10-21 | G25: 20046.25 | H25: Delivered | I25: 36 | J25: 36
A26: 25 | B26: PO-2020-0025 | C26: 1 | D26: 2020-08-08 | E26: 2020-08-11 | F26: 2020-08-12 | G26: 17487.38 | H26: Partially Delivered | I26: 16 | J26: 13 | K26: Short-shipped: supplier back-ordered 3 SKUs
A27: 26 | B27: PO-2020-0026 | C27: 1 | D27: 2020-05-07 | E27: 2020-05-13 | F27: 2020-05-12 | G27: 5224.19 | H27: Delivered | I27: 21 | J27: 21
A28: 27 | B28: PO-2020-0027 | C28: 1 | D28: 2020-02-08 | E28: 2020-02-10 | F28: 2020-02-10 | G28: 16999.33 | H28: Delivered | I28: 44 | J28: 44
A29: 28 | B29: PO-2020-0028 | C29: 1 | D29: 2020-05-01 | E29: 2020-05-07 | F29: 2020-05-06 | G29: 13071.24 | H29: Delivered | I29: 35 | J29: 35
A30: 29 | B30: PO-2020-0029 | C30: 1 | D30: 2020-01-02 | E30: 2020-01-08 | F30: 2020-01-07 | G30: 8560.73 | H30: Delivered | I30: 45 | J30: 45
A31: 30 | B31: PO-2020-0030 | C31: 1 | D31: 2020-04-07 | E31: 2020-04-11 | F31: 2020-04-11 | G31: 15321.15 | H31: Partially Delivered | I31: 44 | J31: 38 | K31: 2 cases arrived damaged during transit
A32: 31 | B32: PO-2020-0031 | C32: 2 | D32: 2020-01-26 | E32: 2020-01-29 | F32: 2020-02-01 | G32: 1796.31 | H32: Partially Delivered | I32: 21 | J32: 19 | K32: Short-shipped: supplier back-ordered 3 SKUs
A33: 32 | B33: PO-2020-0032 | C33: 2 | D33: 2020-10-31 | E33: 2020-11-05 | F33: 2020-11-05 | G33: 6652.86 | H33: Delivered | I33: 35 | J33: 35
A34: 33 | B34: PO-2020-0033 | C34: 2 | D34: 2020-10-31 | E34: 2020-11-08 | F34: 2020-11-08 | G34: 14085.89 | H34: Delivered | I34: 11 | J34: 11
A35: 34 | B35: PO-2020-0034 | C35: 2 | D35: 2020-05-15 | E35: 2020-05-22 | F35: 2020-05-22 | G35: 7401.14 | H35: Delivered | I35: 34 | J35: 34 | K35: Temperature excursion noted on 4 cases
A36: 35 | B36: PO-2020-0035 | C36: 2 | D36: 2020-11-14 | E36: 2020-11-30 | F36: 2020-11-30 | G36: 8082.39 | H36: Delivered | I36: 9 | J36: 9
A37: 36 | B37: PO-2020-0036 | C37: 2 | D37: 2020-05-05 | E37: 2020-05-11 | F37: 2020-05-11 | G37: 7134.58 | H37: Delivered | I37: 22 | J37: 22
A38: 37 | B38: PO-2020-0037 | C38: 2 | D38: 2020-11-30 | E38: 2020-12-02 | F38: 2020-12-02 | G38: 14145.02 | H38: Delivered | I38: 9 | J38: 9
A39: 38 | B39: PO-2020-0038 | C39: 2 | D39: 2020-10-10 | E39: 2020-10-16 | F39: 2020-10-16 | G39: 9467.62 | H39: Delivered | I39: 27 | J39: 27
A40: 39 | B40: PO-2020-0039 | C40: 2 | D40: 2020-05-15 | E40: 2020-05-19 | F40: 2020-05-20 | G40: 2292.18 | H40: Delivered | I40: 18 | J40: 18 | K40: Incorrect vintage delivered for 1 line item
A41: 40 | B41: PO-2020-0040 | C41: 2 | D41: 2020-03-07 | E41: 2020-03-13 | F41: 2020-03-13 | G41: 3262.15 | H41: Delivered | I41: 19 | J41: 19
A42: 41 | B42: PO-2020-0041 | C42: 2 | D42: 2020-01-05 | E42: 2020-01-17 | F42: 2020-01-17 | G42: 8638.26 | H42: Delivered | I42: 31 | J42: 31
A43: 42 | B43: PO-2020-0042 | C43: 2 | D43: 2020-08-08 | E43: 2020-08-19 | F43: 2020-08-19 | G43: 6105.12 | H43: Delivered | I43: 34 | J43: 34
A44: 43 | B44: PO-2020-0043 | C44: 2 | D44: 2020-07-02 | E44: 2020-07-09 | F44: 2020-07-08 | G44: 14633.72 | H44: Delivered | I44: 28 | J44: 28
A45: 44 | B45: PO-2020-0044 | C45: 2 | D45: 2020-03-24 | E45: 2020-04-02 | F45: 2020-04-05 | G45: 13339.83 | H45: Delivered | I45: 5 | J45: 5
A46: 45 | B46: PO-2020-0045 | C46: 2 | D46: 2020-07-29 | E46: 2020-08-06 | F46: 2020-08-11 | G46: 3228.77 | H46: Partially Delivered | I46: 27 | J46: 26 | K46: Label damage on 3 cases; unsellable
A47: 46 | B47: PO-2020-0046 | C47: 2 | D47: 2020-04-23 | E47: 2020-04-25 | F47: 2020-04-24 | G47: 5895.22 | H47: Delivered | I47: 31 | J47: 31
A48: 47 | B48: PO-2020-0047 | C48: 2 | D48: 2020-01-13 | E48: 2020-01-18 | F48: 2020-01-18 | G48: 14536.45 | H48: Delivered | I48: 13 | J48: 13
A49: 48 | B49: PO-2020-0048 | C49: 2 | D49: 2020-12-13 | E49: 2020-12-17 | F49: 2020-12-23 | G49: 14149.32 | H49: Delivered | I49: 8 | J49: 8
A50: 49 | B50: PO-2020-0049 | C50: 2 | D50: 2020-10-24 | E50: 2020-11-02 | F50: 2020-11-01 | G50: 5839.62 | H50: Delivered | I50: 30 | J50: 30
A51: 50 | B51: PO-2020-0050 | C51: 2 | D51: 2020-09-18 | E51: 2020-09-24 | F51: 2020-09-24 | G51: 4566.12 | H51: Delivered | I51: 27 | J51: 27
A52: 51 | B52: PO-2020-0051 | C52: 2 | D52: 2020-10-02 | E52: 2020-10-06 | F52: 2020-10-06 | G52: 6099.1 | H52: Delivered | I52: 7 | J52: 7
A53: 52 | B53: PO-2020-0052 | C53: 2 | D53: 2020-11-15 | E53: 2020-11-17 | F53: 2020-11-17 | G53: 11076.56 | H53: Delivered | I53: 14 | J53: 14
A54: 53 | B54: PO-2020-0053 | C54: 3 | D54: 2020-06-16 | E54: 2020-06-18 | F54: 2020-06-17 | G54: 17628.45 | H54: Delivered | I54: 39 | J54: 39
A55: 54 | B55: PO-2020-0054 | C55: 3 | D55: 2020-11-11 | E55: 2020-11-15 | F55: 2020-11-14 | G55: 15054.62 | H55: Delivered | I55: 15 | J55: 15
A56: 55 | B56: PO-2020-0055 | C56: 3 | D56: 2020-10-23 | E56: 2020-10-25 | F56: 2020-10-25 | G56: 14245.83 | H56: Delivered | I56: 25 | J56: 25
A57: 56 | B57: PO-2020-0056 | C57: 3 | D57: 2020-12-05 | E57: 2020-12-08 | F57: 2020-12-08 | G57: 5054.52 | H57: Delivered | I57: 30 | J57: 30
A58: 57 | B58: PO-2020-0057 | C58: 3 | D58: 2020-04-11 | E58: 2020-04-15 | F58: 2020-04-17 | G58: 13019.16 | H58: Delivered | I58: 27 | J58: 27
... A66: 65 | B66: PO-2020-0065 | C66: 3 | D66: 2020-12-22 | E66: 2020-12-29 | F66: 2020-12-28 | G66: 3129.71 | H66: Delivered | I66: 37 | J66: 37
A67: 66 | B67: PO-2020-0066 | C67: 3 | D67: 2020-08-02 | E67: 2020-08-06 | F67: 2020-08-06 | G67: 13741.05 | H67: Delivered | I67: 32 | J67: 32 | K67: Incorrect vintage delivered for 1 line item
A68: 67 | B68: PO-2020-0067 | C68: 3 | D68: 2020-12-08 | E68: 2020-12-11 | G68: 23229.92 | H68: Cancelled | I68: 49 | J68: 0 | K68: Order cancelled by supplier due to stock-out
A69: 68 | B69: PO-2020-0068 | C69: 3 | D69: 2020-07-20 | E69: 2020-07-22 | F69: 2020-07-22 | G69: 4846.84 | H69: Partially Delivered | I69: 42 | J69: 34 | K69: Incorrect vintage delivered for 1 line item
A70: 69 | B70: PO-2020-0069 | C70: 3 | D70: 2020-01-26 | E70: 2020-01-29 | F70: 2020-01-29 | G70: 19747.05 | H70: Delivered | I70: 39 | J70: 39
A71: 70 | B71: PO-2020-0070 | C71: 3 | D71: 2020-08-03 | E71: 2020-08-08 | F71: 2020-08-08 | G71: 13346.75 | H71: Partially Delivered | I71: 49 | J71: 43 | K71: Temperature excursion noted on 4 cases
A72: 71 | B72: PO-2020-0071 | C72: 3 | D72: 2020-11-28 | E72: 2020-12-05 | F72: 2020-12-05 | G72: 23891.46 | H72: Delivered | I72: 27 | J72: 27
A73: 72 | B73: PO-2020-0072 | C73: 3 | D73: 2020-05-02 | E73: 2020-05-07 | F73: 2020-05-07 | G73: 15407.33 | H73: Delivered | I73: 28 | J73: 28
A74: 73 | B74: PO-2020-0073 | C74: 3 | D74: 2020-07-07 | E74: 2020-07-12 | F74: 2020-07-12 | G74: 20111.42 | H74: Delivered | I74: 25 | J74: 25
A75: 74 | B75: PO-2020-0074 | C75: 3 | D75: 2020-01-14 | E75: 2020-01-19 | F75: 2020-01-26 | G75: 11726.4 | H75: Partially Delivered | I75: 27 | J75: 21 | K75: Freight carrier delay; product held at warehouse
A76: 75 | B76: PO-2020-0075 | C76: 3 | D76: 2020-05-04 | E76: 2020-05-10 | F76: 2020-05-10 | G76: 20517 | H76: Delivered | I76: 17 | J76: 17
A77: 76 | B77: PO-2020-0076 | C77: 3 | D77: 2020-07-08 | E77: 2020-07-13 | F77: 2020-07-13 | G77: 3278.35 | H77: Delivered | I77: 41 | J77: 41
A78: 77 | B78: PO-2020-0077 | C78: 3 | D78: 2020-07-04 | E78: 2020-07-06 | F78: 2020-07-05 | G78: 6875.01 | H78: Delivered | I78: 48 | J78: 48
A79: 78 | B79: PO-2020-0078 | C79: 3 | D79: 2020-10-02 | E79: 2020-10-04 | F79: 2020-10-03 | G79: 12582.64 | H79: Delivered | I79: 32 | J79: 32
A80: 79 | B80: PO-2020-0079 | C80: 3 | D80: 2020-02-14 | E80: 2020-02-17 | F80: 2020-02-16 | G80: 10400.73 | H80: Delivered | I80: 46 | J80: 46
A81: 80 | B81: PO-2020-0080 | C81: 3 | D81: 2020-04-18 | E81: 2020-04-23 | F81: 2020-04-23 | G81: 10487.45 | H81: Delivered | I81: 32 | J81: 32
A82: 81 | B82: PO-2020-0081 | C82: 3 | D82: 2020-04-07 | E82: 2020-04-13 | F82: 2020-04-13 | G82: 18193.41 | H82: Delivered | I82: 46 | J82: 46 | K82: Incorrect vintage delivered for 1 line item
A83: 82 | B83: PO-2020-0082 | C83: 3 | D83: 2020-04-23 | E83: 2020-04-28 | F83: 2020-04-28 | G83: 9736.53 | H83: Delivered | I83: 38 | J83: 38
A84: 83 | B84: PO-2020-0083 | C84: 3 | D84: 2020-08-05 | E84: 2020-08-10 | F84: 2020-08-09 | G84: 8960.16 | H84: Delivered | I84: 31 | J84: 31
A85: 84 | B85: PO-2020-0084 | C85: 3 | D85: 2020-06-10 | E85: 2020-06-13 | F85: 2020-06-13 | G85: 7213.9 | H85: Delivered | I85: 45 | J85: 45
A86: 85 | B86: PO-2020-0085 | C86: 4 | D86: 2020-09-25 | E86: 2020-09-27 | F86: 2020-10-02 | G86: 2661.09 | H86: Delivered | I86: 10 | J86: 10
A87: 86 | B87: PO-2020-0086 | C87: 4 | D87: 2020-03-05 | E87: 2020-03-08 | F87: 2020-03-08 | G87: 5756.91 | H87: Delivered | I87: 9 | J87: 9
A88: 87 | B88: PO-2020-0087 | C88: 4 | D88: 2020-02-22 | E88: 2020-03-09 | F88: 2020-03-08 | G88: 3736.71 | H88: Delivered | I88: 6 | J88: 6
A89: 88 | B89: PO-2020-0088 | C89: 4 | D89: 2020-02-28 | E89: 2020-03-06 | F89: 2020-03-13 | G89: 5171.59 | H89: Delivered | I89: 23 | J89: 23 | K89: Short-shipped: supplier back-ordered 3 SKUs
A90: 89 | B90: PO-2020-0089 | C90: 4 | D90: 2020-10-15 | E90: 2020-10-29 | F90: 2020-10-28 | G90: 6260.02 | H90: Delivered | I90: 24 | J90: 24
A91: 90 | B91: PO-2020-0090 | C91: 4 | D91: 2020-08-18 | E91: 2020-08-29 | F91: 2020-09-03 | G91: 8671.58 | H91: Delivered | I91: 18 | J91: 18
A92: 91 | B92: PO-2020-0091 | C92: 4 | D92: 2020-11-08 | E92: 2020-11-22 | F92: 2020-11-26 | G92: 3014.14 | H92: Delivered | I92: 7 | J92: 7
A93: 92 | B93: PO-2020-0092 | C93: 4 | D93: 2020-02-08 | E93: 2020-02-19 | F93: 2020-02-18 | G93: 4779.79 | H93: Delivered | I93: 24 | J93: 24 | K93: Incorrect vintage delivered for 1 line item
A94: 93 | B94: PO-2020-0093 | C94: 4 | D94: 2020-12-27 | E94: 2021-01-05 | F94: 2021-01-05 | G94: 9277.15 | H94: Delivered | I94: 25 | J94: 25
A95: 94 | B95: PO-2020-0094 | C95: 4 | D95: 2020-04-11 | E95: 2020-05-02 | F95: 2020-05-02 | G95: 6652.53 | H95: Delivered | I95: 13 | J95: 13 | K95: Short-shipped: supplier back-ordered 3 SKUs
A96: 95 | B96: PO-2020-0095 | C96: 4 | D96: 2020-06-06 | E96: 2020-06-10 | F96: 2020-06-18 | G96: 1681.36 | H96: Delivered | I96: 14 | J96: 14
A97: 96 | B97: PO-2020-0096 | C97: 4 | D97: 2020-09-13 | E97: 2020-09-19 | F97: 2020-09-18 | G97: 1264.2 | H97: Delivered | I97: 6 | J97: 6
A98: 97 | B98: PO-2020-0097 | C98: 4 | D98: 2020-11-05 | E98: 2020-11-16 | F98: 2020-11-17 | G98: 9995.94 | H98: Delivered | I98: 13 | J98: 13
A99: 98 | B99: PO-2020-0098 | C99: 4 | D99: 2020-03-30 | E99: 2020-04-13 | F99: 2020-04-12 | G99: 9202.69 | H99: Delivered | I99: 10 | J99: 10
A100: 99 | B100: PO-2020-0099 | C100: 4 | D100: 2020-09-08 | E100: 2020-09-25 | F100: 2020-09-25 | G100: 6866.27 | H100: Delivered | I100: 10 | J100: 10
A101: 100 | B101: PO-2020-0100 | C101: 4 | D101: 2020-05-27 | E101: 2020-06-06 | F101: 2020-06-13 | G101: 8228.88 | H101: Partially Delivered | I101: 22 | J101: 21 | K101: Pallet wrap torn; 1 case broken bottles
A102: 101 | B102: PO-2020-0101 | C102: 5 | D102: 2020-05-09 | E102: 2020-05-11 | F102: 2020-05-11 | G102: 14009.06 | H102: Delivered | I102: 44 | J102: 44 | K102: Incorrect vintage delivered for 1 line item
A103: 102 | B103: PO-2020-0102 | C103: 5 | D103: 2020-11-14 | E103: 2020-11-20 | F103: 2020-11-19 | G103: 15799.83 | H103: Delivered | I103: 23 | J103: 23
A104: 103 | B104: PO-2020-0103 | C104: 5 | D104: 2020-05-27 | E104: 2020-05-29 | F104: 2020-05-29 | G104: 14921.2 | H104: Delivered | I104: 29 | J104: 29
A105: 104 | B105: PO-2020-0104 | C105: 5 | D105: 2020-02-17 | E105: 2020-02-21 | F105: 2020-02-21 | G105: 10575.34 | H105: Delivered | I105: 17 | J105: 17
A106: 105 | B106: PO-2020-0105 | C106: 5 | D106: 2020-05-29 | E106: 2020-06-01 | F106: 2020-05-31 | G106: 6765.29 | H106: Partially Delivered | I106: 45 | J106: 41 | K106: Partial fulfillment due to production delay
A107: 106 | B107: PO-2020-0106 | C107: 5 | D107: 2020-09-17 | E107: 2020-09-20 | F107: 2020-09-20 | G107: 17620.47 | H107: Delivered | I107: 27 | J107: 27
...

Sheet Delivery_Data
A1: id | B1: supplier_id | C1: month | D1: year | E1: orders_placed | F1: orders_on_time | G1: orders_late | H1: orders_short_shipped | I1: total_spend | J1: avg_lead_time_days | K1: quality_issues
A2: 1 | B2: 1 | C2: 1 | D2: 2020 | E2: 2 | F2: 2 | G2: 0 | H2: 0 | I2: 22183.9 | J2: 6 | K2: 0
A3: 2 | B3: 1 | C3: 2 | D3: 2020 | E3: 4 | F3: 3 | G3: 1 | H3: 0 | I3: 37247.72 | J3: 5 | K3: 0
A4: 3 | B4: 1 | C4: 3 | D4: 2020 | E4: 3 | F4: 2 | G4: 0 | H4: 1 | I4: 30976.22 | J4: 3 | K4: 0
A5: 4 | B5: 1 | C5: 4 | D5: 2020 | E5: 3 | F5: 2 | G5: 1 | H5: 1 | I5: 34781.29 | J5: 6 | K5: 1
A6: 5 | B6: 1 | C6: 5 | D6: 2020 | E6: 4 | F6: 4 | G6: 0 | H6: 0 | I6: 34543.48 | J6: 5 | K6: 0
A7: 6 | B7: 1 | C7: 6 | D7: 2020 | E7: 1 | F7: 1 | G7: 0 | H7: 1 | I7: 15534.12 | J7: 11 | K7: 1
A8: 7 | B8: 1 | C8: 7 | D8: 2020 | E8: 2 | F8: 1 | G8: 1 | H8: 0 | I8: 10561.36 | J8: 5.5 | K8: 0
A9: 8 | B9: 1 | C9: 8 | D9: 2020 | E9: 2 | F9: 1 | G9: 1 | H9: 1 | I9: 36668.7 | J9: 4.5 | K9: 0
A10: 9 | B10: 1 | C10: 9 | D10: 2020 | E10: 2 | F10: 0 | G10: 2 | H10: 0 | I10: 45538.75 | J10: 8.5 | K10: 0
A11: 10 | B11: 1 | C11: 10 | D11: 2020 | E11: 2 | F11: 1 | G11: 1 | H11: 0 | I11: 37692.77 | J11: 2.5 | K11: 0
A12: 11 | B12: 1 | C12: 11 | D12: 2020 | E12: 2 | F12: 2 | G12: 0 | H12: 1 | I12: 26206.95 | J12: 5.5 | K12: 1
A13: 12 | B13: 1 | C13: 12 | D13: 2020 | E13: 3 | F13: 3 | G13: 0 | H13: 1 | I13: 56428.91 | J13: 2.3 | K13: 0
... A61: 60 | B61: 5 | C61: 12 | D61: 2020 | E61: 3 | F61: 3 | G61: 0 | H61: 0 | I61: 36639.95 | J61: 3.3 | K61: 0

Sheet Quality_Data
A1: event_id | B1: supplier_id | C1: sku_id | D1: event_type | E1: event_date | F1: affected_lots | G1: closure_state
A2: 1 | B2: 1 | C2: SS-01001 | D2: recall | E2: 2026-01-01 | F2: 1 | G2: closed
A3: 2 | B3: 2 | C3: SS-01010 | D3: sterility_deviation | E3: 2026-02-02 | F3: 2 | G3: open
A4: 3 | B4: 3 | C4: SS-01019 | D4: late_cold_chain | E4: 2026-03-03 | F4: 3 | G4: scope-unresolved
A5: 4 | B5: 4 | C5: SS-01028 | D5: packaging_damage | E5: 2026-04-04 | F5: 4 | G5: closed
A6: 5 | B6: 5 | C6: SS-01037 | D6: recall | E6: 2026-05-05 | F6: 1 | G6: open
A7: 6 | B7: 1 | C7: SS-01046 | D7: sterility_deviation | E7: 2026-06-06 | F7: 2 | G7: scope-unresolved
A8: 7 | B8: 2 | C8: SS-01055 | D8: late_cold_chain | E8: 2026-07-07 | F8: 3 | G8: closed
A9: 8 | B9: 3 | C9: SS-01064 | D9: packaging_damage | E9: 2026-08-08 | F9: 4 | G9: open
A10: 9 | B10: 4 | C10: SS-01073 | D10: recall | E10: 2026-09-09 | F10: 1 | G10: scope-unresolved
A11: 10 | B11: 5 | C11: SS-01082 | D11: sterility_deviation | E11: 2026-10-10 | F11: 2 | G11: closed
A12: 11 | B12: 1 | C12: SS-01091 | D12: late_cold_chain | E12: 2026-11-11 | F12: 3 | G12: open
A13: 12 | B13: 2 | C13: SS-01100 | D13: packaging_damage | E13: 2026-12-12 | F13: 4 | G13: scope-unresolved
... A25: 24 | B25: 4 | C25: SS-01208 | D25: packaging_damage | E25: 2026-12-24 | F25: 4 | G25: scope-unresolved

Sheet Exceptions
A1: Exception register with evidence grading
A2: evidence_class: invoice/statement = documented; assertion-only/missing-support = unverified (excluded from confirmed exposure).
A3: exception_id | B3: sku_id | C3: lot_id | D3: site_id | E3: exception_type | F3: quantity | G3: evidence_status | H3: source_locator | I3: evidence_class | J3: confirmed_qty
A4: EX-0001 | B4: SS-01001 | C4: LOT-07001 | D4: HOSP-1 | E4: recall | F4: 5 | G4: invoice | H4: exception control source row 2 | I4: =IF(OR(G4="invoice",G4="statement"),"documented","unverified") | J4: =IF(I4="documented",F4,0)
A5: EX-0002 | B5: SS-01002 | C5: LOT-07002 | D5: HOSP-2 | E5: damage | F5: 2 | G5: statement | H5: exception control source row 3 | I5: =IF(OR(G5="invoice",G5="statement"),"documented","unverified") | J5: =IF(I5="documented",F5,0)
A6: EX-0003 | B6: SS-01003 | C6: LOT-07003 | D6: HOSP-3 | E6: near-expiry | F6: 0 | G6: assertion-only | H6: exception control source row 4 | I6: =IF(OR(G6="invoice",G6="statement"),"documented","unverified") | J6: =IF(I6="documented",F6,0)
A7: EX-0004 | B7: SS-01004 | C7: LOT-07004 | D7: HOSP-4 | E7: lot-conflict | F7: 37 | G7: missing-support | H7: exception control source row 5 | I7: =IF(OR(G7="invoice",G7="statement"),"documented","unverified") | J7: =IF(I7="documented",F7,0)
A8: EX-0005 | B8: SS-01005 | C8: LOT-07005 | D8: HOSP-1 | E8: evidence-gap | F8: 35 | G8: invoice | H8: exception control source row 6 | I8: =IF(OR(G8="invoice",G8="statement"),"documented","unverified") | J8: =IF(I8="documented",F8,0)
A9: EX-0006 | B9: SS-01006 | C9: LOT-07006 | D9: HOSP-2 | E9: recall | F9: 32 | G9: statement | H9: exception control source row 7 | I9: =IF(OR(G9="invoice",G9="statement"),"documented","unverified") | J9: =IF(I9="documented",F9,0)
A10: EX-0007 | B10: SS-01007 | C10: LOT-07007 | D10: HOSP-3 | E10: damage | F10: 30 | G10: assertion-only | H10: exception control source row 8 | I10: =IF(OR(G10="invoice",G10="statement"),"documented","unverified") | J10: =IF(I10="documented",F10,0)
A11: EX-0008 | B11: SS-01008 | C11: LOT-07008 | D11: HOSP-4 | E11: near-expiry | F11: 27 | G11: missing-support | H11: exception control source row 9 | I11: =IF(OR(G11="invoice",G11="statement"),"documented","unverified") | J11: =IF(I11="documented",F11,0)
A12: EX-0009 | B12: SS-01009 | C12: LOT-07009 | D12: HOSP-1 | E12: lot-conflict | F12: 25 | G12: invoice | H12: exception control source row 10 | I12: =IF(OR(G12="invoice",G12="statement"),"documented","unverified") | J12: =IF(I12="documented",F12,0)
A13: EX-0010 | B13: SS-01010 | C13: LOT-07010 | D13: HOSP-2 | E13: evidence-gap | F13: 22 | G13: statement | H13: exception control source row 11 | I13: =IF(OR(G13="invoice",G13="statement"),"documented","unverified") | J13: =IF(I13="documented",F13,0)
A14: EX-0011 | B14: SS-01011 | C14: LOT-07011 | D14: HOSP-3 | E14: recall | F14: 20 | G14: assertion-only | H14: exception control source row 12 | I14: =IF(OR(G14="invoice",G14="statement"),"documented","unverified") | J14: =IF(I14="documented",F14,0)
A15: EX-0012 | B15: SS-01012 | C15: LOT-07012 | D15: HOSP-4 | E15: damage | F15: 17 | G15: missing-support | H15: exception control source row 13 | I15: =IF(OR(G15="invoice",G15="statement"),"documented","unverified") | J15: =IF(I15="documented",F15,0)
... A51: EX-0048 | B51: SS-01048 | C51: LOT-07048 | D51: HOSP-4 | E51: near-expiry | F51: 5 | G51: missing-support | H51: exception control source row 49 | I51: =IF(OR(G51="invoice",G51="statement"),"documented","unverified") | J51: =IF(I51="documented",F51,0)

Sheet Site_Constraints
A1: Site capacity pools by scenario (net of reserved emergency units)
A2: Raw rows 4-15 (site_storage_clinical_constraints.csv). Pool summary rows 19-23: SUMIFS; net = MAX(0, gross - reserved).
A4: constraint_id | B4: site_id | C4: capacity_pool | D4: adverse_units | E4: base_units | F4: upside_units | G4: reserved_emergency_units | H4: clinical_access_floor | I4: minimum_floor | J4: evidence_status
A5: SSC-001 | B5: HOSP-1 | C5: BUYER_FTE | D5: 0.5 | E5: 1 | F5: 2 | G5: 0.25 | H5: vascular kits | I5: 80 | J5: approved
A6: SSC-002 | B6: HOSP-2 | C6: COLD_CHAIN_PALLET | D6: 1 | E6: 2 | F6: 3 | G6: 0.5 | H6: airway kits | I6: 65 | J6: planning range
A7: SSC-003 | B7: HOSP-3 | C7: RECEIVING_SLOT | D7: 2 | E7: 3 | F7: 4 | G7: 1 | H7: surgical packs | I7: 120 | J7: conditional
A8: SSC-004 | B8: HOSP-4 | C8: CLINICAL_REVIEW | D8: 0.5 | E8: 1 | F8: 2 | G8: 0.25 | H8: wound supplies | I8: 95 | J8: approved
A9: SSC-005 | B9: HOSP-1 | C9: TRANSFER_VEHICLE | D9: 1 | E9: 2 | F9: 3 | G9: 0.5 | H9: vascular kits | I9: 80 | J9: planning range
A10: SSC-006 | B10: HOSP-2 | C10: BUYER_FTE | D10: 2 | E10: 3 | F10: 4 | G10: 1 | H10: airway kits | I10: 65 | J10: conditional
A11: SSC-007 | B11: HOSP-3 | C11: COLD_CHAIN_PALLET | D11: 0.5 | E11: 1 | F11: 2 | G11: 0.25 | H11: surgical packs | I11: 120 | J11: approved
A12: SSC-008 | B12: HOSP-4 | C12: RECEIVING_SLOT | D12: 1 | E12: 2 | F12: 3 | G12: 0.5 | H12: wound supplies | I12: 95 | J12: planning range
A13: SSC-009 | B13: HOSP-1 | C13: CLINICAL_REVIEW | D13: 2 | E13: 3 | F13: 4 | G13: 1 | H13: vascular kits | I13: 80 | J13: conditional
A14: SSC-010 | B14: HOSP-2 | C14: TRANSFER_VEHICLE | D14: 0.5 | E14: 1 | F14: 2 | G14: 0.25 | H14: airway kits | I14: 65 | J14: approved
A15: SSC-011 | B15: HOSP-3 | C15: BUYER_FTE | D15: 1 | E15: 2 | F15: 3 | G15: 0.5 | H15: surgical packs | I15: 120 | J15: planning range
A16: SSC-012 | B16: HOSP-4 | C16: COLD_CHAIN_PALLET | D16: 2 | E16: 3 | F16: 4 | G16: 1 | H16: wound supplies | I16: 95 | J16: conditional
A18: capacity_pool | B18: adv_gross | C18: adv_reserved | D18: adv_net | E18: base_gross | F18: base_reserved | G18: base_net | H18: up_gross | I18: up_reserved | J18: up_net | K18: non_approved_rows
A19: BUYER_FTE | B19: =SUMIF($C$5:$C$16,$A19,D$5:D$16) | C19: =SUMIF($C$5:$C$16,$A19,$G$5:$G$16) | D19: =MAX(0,B19-C19) | E19: =SUMIF($C$5:$C$16,$A19,E$5:E$16) | F19: =SUMIF($C$5:$C$16,$A19,$G$5:$G$16) | G19: =MAX(0,E19-F19) | H19: =SUMIF($C$5:$C$16,$A19,F$5:F$16) | I19: =SUMIF($C$5:$C$16,$A19,$G$5:$G$16) | J19: =MAX(0,H19-I19) | K19: =COUNTIFS($C$5:$C$16,$A19,$J$5:$J$16,"<>approved")
A20: CLINICAL_REVIEW | B20: =SUMIF($C$5:$C$16,$A20,D$5:D$16) | C20: =SUMIF($C$5:$C$16,$A20,$G$5:$G$16) | D20: =MAX(0,B20-C20) | E20: =SUMIF($C$5:$C$16,$A20,E$5:E$16) | F20: =SUMIF($C$5:$C$16,$A20,$G$5:$G$16) | G20: =MAX(0,E20-F20) | H20: =SUMIF($C$5:$C$16,$A20,F$5:F$16) | I20: =SUMIF($C$5:$C$16,$A20,$G$5:$G$16) | J20: =MAX(0,H20-I20) | K20: =COUNTIFS($C$5:$C$16,$A20,$J$5:$J$16,"<>approved")
A21: COLD_CHAIN_PALLET | B21: =SUMIF($C$5:$C$16,$A21,D$5:D$16) | C21: =SUMIF($C$5:$C$16,$A21,$G$5:$G$16) | D21: =MAX(0,B21-C21) | E21: =SUMIF($C$5:$C$16,$A21,E$5:E$16) | F21: =SUMIF($C$5:$C$16,$A21,$G$5:$G$16) | G21: =MAX(0,E21-F21) | H21: =SUMIF($C$5:$C$16,$A21,F$5:F$16) | I21: =SUMIF($C$5:$C$16,$A21,$G$5:$G$16) | J21: =MAX(0,H21-I21) | K21: =COUNTIFS($C$5:$C$16,$A21,$J$5:$J$16,"<>approved")
A22: RECEIVING_SLOT | B22: =SUMIF($C$5:$C$16,$A22,D$5:D$16) | C22: =SUMIF($C$5:$C$16,$A22,$G$5:$G$16) | D22: =MAX(0,B22-C22) | E22: =SUMIF($C$5:$C$16,$A22,E$5:E$16) | F22: =SUMIF($C$5:$C$16,$A22,$G$5:$G$16) | G22: =MAX(0,E22-F22) | H22: =SUMIF($C$5:$C$16,$A22,F$5:F$16) | I22: =SUMIF($C$5:$C$16,$A22,$G$5:$G$16) | J22: =MAX(0,H22-I22) | K22: =COUNTIFS($C$5:$C$16,$A22,$J$5:$J$16,"<>approved")
A23: TRANSFER_VEHICLE | B23: =SUMIF($C$5:$C$16,$A23,D$5:D$16) | C23: =SUMIF($C$5:$C$16,$A23,$G$5:$G$16) | D23: =MAX(0,B23-C23) | E23: =SUMIF($C$5:$C$16,$A23,E$5:E$16) | F23: =SUMIF($C$5:$C$16,$A23,$G$5:$G$16) | G23: =MAX(0,E23-F23) | H23: =SUMIF($C$5:$C$16,$A23,F$5:F$16) | I23: =SUMIF($C$5:$C$16,$A23,$G$5:$G$16) | J23: =MAX(0,H23-I23) | K23: =COUNTIFS($C$5:$C$16,$A23,$J$5:$J$16,"<>approved")

Sheet Action_Catalog
A1: Supply action catalog (raw from supply_action_constraints.csv) + scenario eligibility flags
A3: action_id | B3: eligible_family | C3: operational_lever | D3: lead_time_change_days | E3: transfer_or_receipt_capacity_units | F3: start_delay_days | G3: fixed_cost_usd | H3: capacity_pool | I3: capacity_units | J3: dependency_group | K3: mutual_exclusion_group | L3: overlap_group | M3: shared_execution_fraction | N3: eligible_scenarios | O3: clinical_constraint | P3: supporting_record_grade | Q3: elig_adverse | R3: elig_base | S3: elig_upside
A4: SAC-001 | B4: vascular | C4: expedite receipt | D4: 4 | E4: 16.2 | F4: 1 | G4: 1200 | H4: BUYER_FTE | I4: 0.5 | J4: DG-1 | K4: MX-1 | L4: OV-1 | M4: 0 | N4: adverse|base|upside | O4: no reduction below emergency access floor | P4: A | Q4: =IF(ISNUMBER(SEARCH("adverse",$N4)),1,0) | R4: =IF(ISNUMBER(SEARCH("base",$N4)),1,0) | S4: =IF(ISNUMBER(SEARCH("upside",$N4)),1,0)
A5: SAC-002 | B5: respiratory | C5: site transfer | D5: 1 | E5: 24.3 | F5: 3 | G5: 4500 | H5: COLD_CHAIN_PALLET | I5: 1 | J5: DG-2 | L5: OV-2 | M5: 0.2 | N5: base|upside | O5: requires infection-control approval | P5: B | Q5: =IF(ISNUMBER(SEARCH("adverse",$N5)),1,0) | R5: =IF(ISNUMBER(SEARCH("base",$N5)),1,0) | S5: =IF(ISNUMBER(SEARCH("upside",$N5)),1,0)
A6: SAC-003 | B6: surgical | C6: supplier substitution | D6: 7 | E6: 32.4 | F6: 7 | G6: 9000 | H6: RECEIVING_SLOT | I6: 1.5 | J6: DG-3 | L6: OV-3 | M6: 0.35 | N6: upside | O6: preserve cold-chain integrity | P6: C | Q6: =IF(ISNUMBER(SEARCH("adverse",$N6)),1,0) | R6: =IF(ISNUMBER(SEARCH("base",$N6)),1,0) | S6: =IF(ISNUMBER(SEARCH("upside",$N6)),1,0)
A7: SAC-004 | B7: diagnostic | C7: allocation hold | D7: 6 | E7: 43.2 | F7: 14 | G7: 18000 | H7: CLINICAL_REVIEW | I7: 2 | J7: DG-4 | L7: OV-4 | M7: 0.5 | N7: adverse|base|upside | O7: lot-level recall clearance required | P7: A | Q7: =IF(ISNUMBER(SEARCH("adverse",$N7)),1,0) | R7: =IF(ISNUMBER(SEARCH("base",$N7)),1,0) | S7: =IF(ISNUMBER(SEARCH("upside",$N7)),1,0)
A8: SAC-005 | B8: wound | C8: expedite receipt | D8: 1 | E8: 60.8 | F8: 1 | G8: 1200 | H8: TRANSFER_VEHICLE | I8: 0.5 | J8: DG-5 | L8: OV-5 | M8: 0 | N8: base|upside | O8: no reduction below emergency access floor | P8: B | Q8: =IF(ISNUMBER(SEARCH("adverse",$N8)),1,0) | R8: =IF(ISNUMBER(SEARCH("base",$N8)),1,0) | S8: =IF(ISNUMBER(SEARCH("upside",$N8)),1,0)
A9: SAC-006 | B9: all critical | C9: site transfer | D9: 4 | E9: 16.2 | F9: 3 | G9: 4500 | H9: BUYER_FTE | I9: 1 | J9: DG-6 | K9: MX-2 | L9: OV-1 | M9: 0.2 | N9: upside | O9: requires infection-control approval | P9: C | Q9: =IF(ISNUMBER(SEARCH("adverse",$N9)),1,0) | R9: =IF(ISNUMBER(SEARCH("base",$N9)),1,0) | S9: =IF(ISNUMBER(SEARCH("upside",$N9)),1,0)
A10: SAC-007 | B10: vascular | C10: supplier substitution | D10: 1 | E10: 24.3 | F10: 7 | G10: 9000 | H10: COLD_CHAIN_PALLET | I10: 1.5 | J10: DG-1 | L10: OV-2 | M10: 0.35 | N10: adverse|base|upside | O10: preserve cold-chain integrity | P10: A | Q10: =IF(ISNUMBER(SEARCH("adverse",$N10)),1,0) | R10: =IF(ISNUMBER(SEARCH("base",$N10)),1,0) | S10: =IF(ISNUMBER(SEARCH("upside",$N10)),1,0)
A11: SAC-008 | B11: respiratory | C11: allocation hold | D11: 7 | E11: 32.4 | F11: 14 | G11: 18000 | H11: RECEIVING_SLOT | I11: 2 | J11: DG-2 | L11: OV-3 | M11: 0.5 | N11: base|upside | O11: lot-level recall clearance required | P11: B | Q11: =IF(ISNUMBER(SEARCH("adverse",$N11)),1,0) | R11: =IF(ISNUMBER(SEARCH("base",$N11)),1,0) | S11: =IF(ISNUMBER(SEARCH("upside",$N11)),1,0)
A12: SAC-009 | B12: surgical | C12: expedite receipt | D12: 6 | E12: 43.2 | F12: 1 | G12: 1200 | H12: CLINICAL_REVIEW | I12: 0.5 | J12: DG-3 | L12: OV-4 | M12: 0 | N12: upside | O12: no reduction below emergency access floor | P12: C | Q12: =IF(ISNUMBER(SEARCH("adverse",$N12)),1,0) | R12: =IF(ISNUMBER(SEARCH("base",$N12)),1,0) | S12: =IF(ISNUMBER(SEARCH("upside",$N12)),1,0)
A13: SAC-010 | B13: diagnostic | C13: site transfer | D13: 1 | E13: 60.8 | F13: 3 | G13: 4500 | H13: TRANSFER_VEHICLE | I13: 1 | J13: DG-4 | L13: OV-5 | M13: 0.2 | N13: adverse|base|upside | O13: requires infection-control approval | P13: A | Q13: =IF(ISNUMBER(SEARCH("adverse",$N13)),1,0) | R13: =IF(ISNUMBER(SEARCH("base",$N13)),1,0) | S13: =IF(ISNUMBER(SEARCH("upside",$N13)),1,0)
A14: SAC-011 | B14: wound | C14: supplier substitution | D14: 4 | E14: 16.2 | F14: 7 | G14: 9000 | H14: BUYER_FTE | I14: 1.5 | J14: DG-5 | K14: MX-3 | L14: OV-1 | M14: 0.35 | N14: base|upside | O14: preserve cold-chain integrity | P14: B | Q14: =IF(ISNUMBER(SEARCH("adverse",$N14)),1,0) | R14: =IF(ISNUMBER(SEARCH("base",$N14)),1,0) | S14: =IF(ISNUMBER(SEARCH("upside",$N14)),1,0)
A15: SAC-012 | B15: all critical | C15: allocation hold | D15: 1 | E15: 24.3 | F15: 14 | G15: 18000 | H15: COLD_CHAIN_PALLET | I15: 2 | J15: DG-6 | L15: OV-2 | M15: 0.5 | N15: upside | O15: lot-level recall clearance required | P15: C | Q15: =IF(ISNUMBER(SEARCH("adverse",$N15)),1,0) | R15: =IF(ISNUMBER(SEARCH("base",$N15)),1,0) | S15: =IF(ISNUMBER(SEARCH("upside",$N15)),1,0)
A16: SAC-013 | B16: vascular | C16: expedite receipt | D16: 7 | E16: 32.4 | F16: 1 | G16: 1200 | H16: RECEIVING_SLOT | I16: 0.5 | J16: DG-1 | L16: OV-3 | M16: 0 | N16: adverse|base|upside | O16: no reduction below emergency access floor | P16: A | Q16: =IF(ISNUMBER(SEARCH("adverse",$N16)),1,0) | R16: =IF(ISNUMBER(SEARCH("base",$N16)),1,0) | S16: =IF(ISNUMBER(SEARCH("upside",$N16)),1,0)
A17: SAC-014 | B17: respiratory | C17: site transfer | D17: 6 | E17: 43.2 | F17: 3 | G17: 4500 | H17: CLINICAL_REVIEW | I17: 1 | J17: DG-2 | L17: OV-4 | M17: 0.2 | N17: base|upside | O17: requires infection-control approval | P17: B | Q17: =IF(ISNUMBER(SEARCH("adverse",$N17)),1,0) | R17: =IF(ISNUMBER(SEARCH("base",$N17)),1,0) | S17: =IF(ISNUMBER(SEARCH("upside",$N17)),1,0)
A18: SAC-015 | B18: surgical | C18: supplier substitution | D18: 1 | E18: 60.8 | F18: 7 | G18: 9000 | H18: TRANSFER_VEHICLE | I18: 1.5 | J18: DG-3 | L18: OV-5 | M18: 0.35 | N18: upside | O18: preserve cold-chain integrity | P18: C | Q18: =IF(ISNUMBER(SEARCH("adverse",$N18)),1,0) | R18: =IF(ISNUMBER(SEARCH("base",$N18)),1,0) | S18: =IF(ISNUMBER(SEARCH("upside",$N18)),1,0)
A19: SAC-016 | B19: diagnostic | C19: allocation hold | D19: 4 | E19: 16.2 | F19: 14 | G19: 18000 | H19: BUYER_FTE | I19: 2 | J19: DG-4 | K19: MX-4 | L19: OV-1 | M19: 0.5 | N19: adverse|base|upside | O19: lot-level recall clearance required | P19: A | Q19: =IF(ISNUMBER(SEARCH("adverse",$N19)),1,0) | R19: =IF(ISNUMBER(SEARCH("base",$N19)),1,0) | S19: =IF(ISNUMBER(SEARCH("upside",$N19)),1,0)
A20: SAC-017 | B20: wound | C20: expedite receipt | D20: 1 | E20: 24.3 | F20: 1 | G20: 1200 | H20: COLD_CHAIN_PALLET | I20: 0.5 | J20: DG-5 | L20: OV-2 | M20: 0 | N20: base|upside | O20: no reduction below emergency access floor | P20: B | Q20: =IF(ISNUMBER(SEARCH("adverse",$N20)),1,0) | R20: =IF(ISNUMBER(SEARCH("base",$N20)),1,0) | S20: =IF(ISNUMBER(SEARCH("upside",$N20)),1,0)
A21: SAC-018 | B21: all critical | C21: site transfer | D21: 7 | E21: 32.4 | F21: 3 | G21: 4500 | H21: RECEIVING_SLOT | I21: 1 | J21: DG-6 | L21: OV-3 | M21: 0.2 | N21: upside | O21: requires infection-control approval | P21: C | Q21: =IF(ISNUMBER(SEARCH("adverse",$N21)),1,0) | R21: =IF(ISNUMBER(SEARCH("base",$N21)),1,0) | S21: =IF(ISNUMBER(SEARCH("upside",$N21)),1,0)
A22: SAC-019 | B22: vascular | C22: supplier substitution | D22: 6 | E22: 43.2 | F22: 7 | G22: 9000 | H22: CLINICAL_REVIEW | I22: 1.5 | J22: DG-1 | L22: OV-4 | M22: 0.35 | N22: adverse|base|upside | O22: preserve cold-chain integrity | P22: A | Q22: =IF(ISNUMBER(SEARCH("adverse",$N22)),1,0) | R22: =IF(ISNUMBER(SEARCH("base",$N22)),1,0) | S22: =IF(ISNUMBER(SEARCH("upside",$N22)),1,0)
A23: SAC-020 | B23: respiratory | C23: allocation hold | D23: 1 | E23: 60.8 | F23: 14 | G23: 18000 | H23: TRANSFER_VEHICLE | I23: 2 | J23: DG-2 | L23: OV-5 | M23: 0.5 | N23: base|upside | O23: lot-level recall clearance required | P23: B | Q23: =IF(ISNUMBER(SEARCH("adverse",$N23)),1,0) | R23: =IF(ISNUMBER(SEARCH("base",$N23)),1,0) | S23: =IF(ISNUMBER(SEARCH("upside",$N23)),1,0)
A24: SAC-021 | B24: surgical | C24: expedite receipt | D24: 4 | E24: 16.2 | F24: 1 | G24: 1200 | H24: BUYER_FTE | I24: 0.5 | J24: DG-3 | K24: MX-1 | L24: OV-1 | M24: 0 | N24: upside | O24: no reduction below emergency access floor | P24: C | Q24: =IF(ISNUMBER(SEARCH("adverse",$N24)),1,0) | R24: =IF(ISNUMBER(SEARCH("base",$N24)),1,0) | S24: =IF(ISNUMBER(SEARCH("upside",$N24)),1,0)
A25: SAC-022 | B25: diagnostic | C25: site transfer | D25: 1 | E25: 24.3 | F25: 3 | G25: 4500 | H25: COLD_CHAIN_PALLET | I25: 1 | J25: DG-4 | L25: OV-2 | M25: 0.2 | N25: adverse|base|upside | O25: requires infection-control approval | P25: A | Q25: =IF(ISNUMBER(SEARCH("adverse",$N25)),1,0) | R25: =IF(ISNUMBER(SEARCH("base",$N25)),1,0) | S25: =IF(ISNUMBER(SEARCH("upside",$N25)),1,0)
A26: SAC-023 | B26: wound | C26: supplier substitution | D26: 7 | E26: 32.4 | F26: 7 | G26: 9000 | H26: RECEIVING_SLOT | I26: 1.5 | J26: DG-5 | L26: OV-3 | M26: 0.35 | N26: base|upside | O26: preserve cold-chain integrity | P26: B | Q26: =IF(ISNUMBER(SEARCH("adverse",$N26)),1,0) | R26: =IF(ISNUMBER(SEARCH("base",$N26)),1,0) | S26: =IF(ISNUMBER(SEARCH("upside",$N26)),1,0)
A27: SAC-024 | B27: all critical | C27: allocation hold | D27: 6 | E27: 43.2 | F27: 14 | G27: 18000 | H27: CLINICAL_REVIEW | I27: 2 | J27: DG-6 | L27: OV-4 | M27: 0.5 | N27: upside | O27: lot-level recall clearance required | P27: C | Q27: =IF(ISNUMBER(SEARCH("adverse",$N27)),1,0) | R27: =IF(ISNUMBER(SEARCH("base",$N27)),1,0) | S27: =IF(ISNUMBER(SEARCH("upside",$N27)),1,0)

Sheet SKU_Exposure
A1: Per-SKU exposure: demand, days-of-cover, scenario gaps, reorder-point adequacy
A2: gap = MAX(0, CEILING(demand x multiplier / 30 x target_days, 1) - usable). Demand is network-wide per SKU (usage rows span sites); stock is held at the listed site.
A3: sku_id | B3: family | C3: site | D3: supplier | E3: usable_qty | F3: base_monthly_usage | G3: days_of_cover | H3: gap_adverse_units | I3: gap_base_units | J3: gap_upside_units | K3: stockout_flag | L3: srp | M3: lead_time_days | N3: srp_adequacy
A4: SS-01001 | B4: =INDEX(Lots_Data!$C$2:$C$234,MATCH($A4,Lots_Data!$A$2:$A$234,0)) | C4: =INDEX(Lots_Data!$E$2:$E$234,MATCH($A4,Lots_Data!$A$2:$A$234,0)) | D4: =INDEX(Lots_Data!$D$2:$D$234,MATCH($A4,Lots_Data!$A$2:$A$234,0)) | E4: =INDEX(Lots_Data!$K$2:$K$234,MATCH($A4,Lots_Data!$A$2:$A$234,0)) | F4: =INDEX(Usage_Summary!$C$4:$C$236,MATCH($A4,Usage_Summary!$A$4:$A$236,0)) | G4: =IF($F4>0,$E4/$F4*30,"") | H4: =MAX(0,CEILING(ROUND($F4*Inputs!$B$10/30*Inputs!$B$7,6),1)-$E4) | I4: =MAX(0,CEILING(ROUND($F4*Inputs!$B$11/30*Inputs!$B$7,6),1)-$E4) | J4: =MAX(0,CEILING(ROUND($F4*Inputs!$B$12/30*Inputs!$B$7,6),1)-$E4) | K4: =IF(AND($F4>0,$E4<=0),1,0) | L4: =INDEX(Lots_Data!$S$2:$S$234,MATCH($A4,Lots_Data!$A$2:$A$234,0)) | M4: =INDEX(Lots_Data!$N$2:$N$234,MATCH($A4,Lots_Data!$A$2:$A$234,0)) | N4: =IF($F4=0,"n/a",IF($L4>=$F4/30*$M4,"adequate","under-set"))
A5: SS-01002 | B5: =INDEX(Lots_Data!$C$2:$C$234,MATCH($A5,Lots_Data!$A$2:$A$234,0)) | C5: =INDEX(Lots_Data!$E$2:$E$234,MATCH($A5,Lots_Data!$A$2:$A$234,0)) | D5: =INDEX(Lots_Data!$D$2:$D$234,MATCH($A5,Lots_Data!$A$2:$A$234,0)) | E5: =INDEX(Lots_Data!$K$2:$K$234,MATCH($A5,Lots_Data!$A$2:$A$234,0)) | F5: =INDEX(Usage_Summary!$C$4:$C$236,MATCH($A5,Usage_Summary!$A$4:$A$236,0)) | G5: =IF($F5>0,$E5/$F5*30,"") | H5: =MAX(0,CEILING(ROUND($F5*Inputs!$B$10/30*Inputs!$B$7,6),1)-$E5) | I5: =MAX(0,CEILING(ROUND($F5*Inputs!$B$11/30*Inputs!$B$7,6),1)-$E5) | J5: =MAX(0,CEILING(ROUND($F5*Inputs!$B$12/30*Inputs!$B$7,6),1)-$E5) | K5: =IF(AND($F5>0,$E5<=0),1,0) | L5: =INDEX(Lots_Data!$S$2:$S$234,MATCH($A5,Lots_Data!$A$2:$A$234,0)) | M5: =INDEX(Lots_Data!$N$2:$N$234,MATCH($A5,Lots_Data!$A$2:$A$234,0)) | N5: =IF($F5=0,"n/a",IF($L5>=$F5/30*$M5,"adequate","under-set"))
A6: SS-01003 | B6: =INDEX(Lots_Data!$C$2:$C$234,MATCH($A6,Lots_Data!$A$2:$A$234,0)) | C6: =INDEX(Lots_Data!$E$2:$E$234,MATCH($A6,Lots_Data!$A$2:$A$234,0)) | D6: =INDEX(Lots_Data!$D$2:$D$234,MATCH($A6,Lots_Data!$A$2:$A$234,0)) | E6: =INDEX(Lots_Data!$K$2:$K$234,MATCH($A6,Lots_Data!$A$2:$A$234,0)) | F6: =INDEX(Usage_Summary!$C$4:$C$236,MATCH($A6,Usage_Summary!$A$4:$A$236,0)) | G6: =IF($F6>0,$E6/$F6*30,"") | H6: =MAX(0,CEILING(ROUND($F6*Inputs!$B$10/30*Inputs!$B$7,6),1)-$E6) | I6: =MAX(0,CEILING(ROUND($F6*Inputs!$B$11/30*Inputs!$B$7,6),1)-$E6) | J6: =MAX(0,CEILING(ROUND($F6*Inputs!$B$12/30*Inputs!$B$7,6),1)-$E6) | K6: =IF(AND($F6>0,$E6<=0),1,0) | L6: =INDEX(Lots_Data!$S$2:$S$234,MATCH($A6,Lots_Data!$A$2:$A$234,0)) | M6: =INDEX(Lots_Data!$N$2:$N$234,MATCH($A6,Lots_Data!$A$2:$A$234,0)) | N6: =IF($F6=0,"n/a",IF($L6>=$F6/30*$M6,"adequate","under-set"))
A7: SS-01004 | B7: =INDEX(Lots_Data!$C$2:$C$234,MATCH($A7,Lots_Data!$A$2:$A$234,0)) | C7: =INDEX(Lots_Data!$E$2:$E$234,MATCH($A7,Lots_Data!$A$2:$A$234,0)) | D7: =INDEX(Lots_Data!$D$2:$D$234,MATCH($A7,Lots_Data!$A$2:$A$234,0)) | E7: =INDEX(Lots_Data!$K$2:$K$234,MATCH($A7,Lots_Data!$A$2:$A$234,0)) | F7: =INDEX(Usage_Summary!$C$4:$C$236,MATCH($A7,Usage_Summary!$A$4:$A$236,0)) | G7: =IF($F7>0,$E7/$F7*30,"") | H7: =MAX(0,CEILING(ROUND($F7*Inputs!$B$10/30*Inputs!$B$7,6),1)-$E7) | I7: =MAX(0,CEILING(ROUND($F7*Inputs!$B$11/30*Inputs!$B$7,6),1)-$E7) | J7: =MAX(0,CEILING(ROUND($F7*Inputs!$B$12/30*Inputs!$B$7,6),1)-$E7) | K7: =IF(AND($F7>0,$E7<=0),1,0) | L7: =INDEX(Lots_Data!$S$2:$S$234,MATCH($A7,Lots_Data!$A$2:$A$234,0)) | M7: =INDEX(Lots_Data!$N$2:$N$234,MATCH($A7,Lots_Data!$A$2:$A$234,0)) | N7: =IF($F7=0,"n/a",IF($L7>=$F7/30*$M7,"adequate","under-set"))
A8: SS-01005 | B8: =INDEX(Lots_Data!$C$2:$C$234,MATCH($A8,Lots_Data!$A$2:$A$234,0)) | C8: =INDEX(Lots_Data!$E$2:$E$234,MATCH($A8,Lots_Data!$A$2:$A$234,0)) | D8: =INDEX(Lots_Data!$D$2:$D$234,MATCH($A8,Lots_Data!$A$2:$A$234,0)) | E8: =INDEX(Lots_Data!$K$2:$K$234,MATCH($A8,Lots_Data!$A$2:$A$234,0)) | F8: =INDEX(Usage_Summary!$C$4:$C$236,MATCH($A8,Usage_Summary!$A$4:$A$236,0)) | G8: =IF($F8>0,$E8/$F8*30,"") | H8: =MAX(0,CEILING(ROUND($F8*Inputs!$B$10/30*Inputs!$B$7,6),1)-$E8) | I8: =MAX(0,CEILING(ROUND($F8*Inputs!$B$11/30*Inputs!$B$7,6),1)-$E8) | J8: =MAX(0,CEILING(ROUND($F8*Inputs!$B$12/30*Inputs!$B$7,6),1)-$E8) | K8: =IF(AND($F8>0,$E8<=0),1,0) | L8: =INDEX(Lots_Data!$S$2:$S$234,MATCH($A8,Lots_Data!$A$2:$A$234,0)) | M8: =INDEX(Lots_Data!$N$2:$N$234,MATCH($A8,Lots_Data!$A$2:$A$234,0)) | N8: =IF($F8=0,"n/a",IF($L8>=$F8/30*$M8,"adequate","under-set"))
A9: SS-01006 | B9: =INDEX(Lots_Data!$C$2:$C$234,MATCH($A9,Lots_Data!$A$2:$A$234,0)) | C9: =INDEX(Lots_Data!$E$2:$E$234,MATCH($A9,Lots_Data!$A$2:$A$234,0)) | D9: =INDEX(Lots_Data!$D$2:$D$234,MATCH($A9,Lots_Data!$A$2:$A$234,0)) | E9: =INDEX(Lots_Data!$K$2:$K$234,MATCH($A9,Lots_Data!$A$2:$A$234,0)) | F9: =INDEX(Usage_Summary!$C$4:$C$236,MATCH($A9,Usage_Summary!$A$4:$A$236,0)) | G9: =IF($F9>0,$E9/$F9*30,"") | H9: =MAX(0,CEILING(ROUND($F9*Inputs!$B$10/30*Inputs!$B$7,6),1)-$E9) | I9: =MAX(0,CEILING(ROUND($F9*Inputs!$B$11/30*Inputs!$B$7,6),1)-$E9) | J9: =MAX(0,CEILING(ROUND($F9*Inputs!$B$12/30*Inputs!$B$7,6),1)-$E9) | K9: =IF(AND($F9>0,$E9<=0),1,0) | L9: =INDEX(Lots_Data!$S$2:$S$234,MATCH($A9,Lots_Data!$A$2:$A$234,0)) | M9: =INDEX(Lots_Data!$N$2:$N$234,MATCH($A9,Lots_Data!$A$2:$A$234,0)) | N9: =IF($F9=0,"n/a",IF($L9>=$F9/30*$M9,"adequate","under-set"))
A10: SS-01007 | B10: =INDEX(Lots_Data!$C$2:$C$234,MATCH($A10,Lots_Data!$A$2:$A$234,0)) | C10: =INDEX(Lots_Data!$E$2:$E$234,MATCH($A10,Lots_Data!$A$2:$A$234,0)) | D10: =INDEX(Lots_Data!$D$2:$D$234,MATCH($A10,Lots_Data!$A$2:$A$234,0)) | E10: =INDEX(Lots_Data!$K$2:$K$234,MATCH($A10,Lots_Data!$A$2:$A$234,0)) | F10: =INDEX(Usage_Summary!$C$4:$C$236,MATCH($A10,Usage_Summary!$A$4:$A$236,0)) | G10: =IF($F10>0,$E10/$F10*30,"") | H10: =MAX(0,CEILING(ROUND($F10*Inputs!$B$10/30*Inputs!$B$7,6),1)-$E10) | I10: =MAX(0,CEILING(ROUND($F10*Inputs!$B$11/30*Inputs!$B$7,6),1)-$E10) | J10: =MAX(0,CEILING(ROUND($F10*Inputs!$B$12/30*Inputs!$B$7,6),1)-$E10) | K10: =IF(AND($F10>0,$E10<=0),1,0) | L10: =INDEX(Lots_Data!$S$2:$S$234,MATCH($A10,Lots_Data!$A$2:$A$234,0)) | M10: =INDEX(Lots_Data!$N$2:$N$234,MATCH($A10,Lots_Data!$A$2:$A$234,0)) | N10: =IF($F10=0,"n/a",IF($L10>=$F10/30*$M10,"adequate","under-set"))
A11: SS-01008 | B11: =INDEX(Lots_Data!$C$2:$C$234,MATCH($A11,Lots_Data!$A$2:$A$234,0)) | C11: =INDEX(Lots_Data!$E$2:$E$234,MATCH($A11,Lots_Data!$A$2:$A$234,0)) | D11: =INDEX(Lots_Data!$D$2:$D$234,MATCH($A11,Lots_Data!$A$2:$A$234,0)) | E11: =INDEX(Lots_Data!$K$2:$K$234,MATCH($A11,Lots_Data!$A$2:$A$234,0)) | F11: =INDEX(Usage_Summary!$C$4:$C$236,MATCH($A11,Usage_Summary!$A$4:$A$236,0)) | G11: =IF($F11>0,$E11/$F11*30,"") | H11: =MAX(0,CEILING(ROUND($F11*Inputs!$B$10/30*Inputs!$B$7,6),1)-$E11) | I11: =MAX(0,CEILING(ROUND($F11*Inputs!$B$11/30*Inputs!$B$7,6),1)-$E11) | J11: =MAX(0,CEILING(ROUND($F11*Inputs!$B$12/30*Inputs!$B$7,6),1)-$E11) | K11: =IF(AND($F11>0,$E11<=0),1,0) | L11: =INDEX(Lots_Data!$S$2:$S$234,MATCH($A11,Lots_Data!$A$2:$A$234,0)) | M11: =INDEX(Lots_Data!$N$2:$N$234,MATCH($A11,Lots_Data!$A$2:$A$234,0)) | N11: =IF($F11=0,"n/a",IF($L11>=$F11/30*$M11,"adequate","under-set"))
A12: SS-01009 | B12: =INDEX(Lots_Data!$C$2:$C$234,MATCH($A12,Lots_Data!$A$2:$A$234,0)) | C12: =INDEX(Lots_Data!$E$2:$E$234,MATCH($A12,Lots_Data!$A$2:$A$234,0)) | D12: =INDEX(Lots_Data!$D$2:$D$234,MATCH($A12,Lots_Data!$A$2:$A$234,0)) | E12: =INDEX(Lots_Data!$K$2:$K$234,MATCH($A12,Lots_Data!$A$2:$A$234,0)) | F12: =INDEX(Usage_Summary!$C$4:$C$236,MATCH($A12,Usage_Summary!$A$4:$A$236,0)) | G12: =IF($F12>0,$E12/$F12*30,"") | H12: =MAX(0,CEILING(ROUND($F12*Inputs!$B$10/30*Inputs!$B$7,6),1)-$E12) | I12: =MAX(0,CEILING(ROUND($F12*Inputs!$B$11/30*Inputs!$B$7,6),1)-$E12) | J12: =MAX(0,CEILING(ROUND($F12*Inputs!$B$12/30*Inputs!$B$7,6),1)-$E12) | K12: =IF(AND($F12>0,$E12<=0),1,0) | L12: =INDEX(Lots_Data!$S$2:$S$234,MATCH($A12,Lots_Data!$A$2:$A$234,0)) | M12: =INDEX(Lots_Data!$N$2:$N$234,MATCH($A12,Lots_Data!$A$2:$A$234,0)) | N12: =IF($F12=0,"n/a",IF($L12>=$F12/30*$M12,"adequate","under-set"))
A13: SS-01010 | B13: =INDEX(Lots_Data!$C$2:$C$234,MATCH($A13,Lots_Data!$A$2:$A$234,0)) | C13: =INDEX(Lots_Data!$E$2:$E$234,MATCH($A13,Lots_Data!$A$2:$A$234,0)) | D13: =INDEX(Lots_Data!$D$2:$D$234,MATCH($A13,Lots_Data!$A$2:$A$234,0)) | E13: =INDEX(Lots_Data!$K$2:$K$234,MATCH($A13,Lots_Data!$A$2:$A$234,0)) | F13: =INDEX(Usage_Summary!$C$4:$C$236,MATCH($A13,Usage_Summary!$A$4:$A$236,0)) | G13: =IF($F13>0,$E13/$F13*30,"") | H13: =MAX(0,CEILING(ROUND($F13*Inputs!$B$10/30*Inputs!$B$7,6),1)-$E13) | I13: =MAX(0,CEILING(ROUND($F13*Inputs!$B$11/30*Inputs!$B$7,6),1)-$E13) | J13: =MAX(0,CEILING(ROUND($F13*Inputs!$B$12/30*Inputs!$B$7,6),1)-$E13) | K13: =IF(AND($F13>0,$E13<=0),1,0) | L13: =INDEX(Lots_Data!$S$2:$S$234,MATCH($A13,Lots_Data!$A$2:$A$234,0)) | M13: =INDEX(Lots_Data!$N$2:$N$234,MATCH($A13,Lots_Data!$A$2:$A$234,0)) | N13: =IF($F13=0,"n/a",IF($L13>=$F13/30*$M13,"adequate","under-set"))
A14: SS-01011 | B14: =INDEX(Lots_Data!$C$2:$C$234,MATCH($A14,Lots_Data!$A$2:$A$234,0)) | C14: =INDEX(Lots_Data!$E$2:$E$234,MATCH($A14,Lots_Data!$A$2:$A$234,0)) | D14: =INDEX(Lots_Data!$D$2:$D$234,MATCH($A14,Lots_Data!$A$2:$A$234,0)) | E14: =INDEX(Lots_Data!$K$2:$K$234,MATCH($A14,Lots_Data!$A$2:$A$234,0)) | F14: =INDEX(Usage_Summary!$C$4:$C$236,MATCH($A14,Usage_Summary!$A$4:$A$236,0)) | G14: =IF($F14>0,$E14/$F14*30,"") | H14: =MAX(0,CEILING(ROUND($F14*Inputs!$B$10/30*Inputs!$B$7,6),1)-$E14) | I14: =MAX(0,CEILING(ROUND($F14*Inputs!$B$11/30*Inputs!$B$7,6),1)-$E14) | J14: =MAX(0,CEILING(ROUND($F14*Inputs!$B$12/30*Inputs!$B$7,6),1)-$E14) | K14: =IF(AND($F14>0,$E14<=0),1,0) | L14: =INDEX(Lots_Data!$S$2:$S$234,MATCH($A14,Lots_Data!$A$2:$A$234,0)) | M14: =INDEX(Lots_Data!$N$2:$N$234,MATCH($A14,Lots_Data!$A$2:$A$234,0)) | N14: =IF($F14=0,"n/a",IF($L14>=$F14/30*$M14,"adequate","under-set"))
A15: SS-01012 | B15: =INDEX(Lots_Data!$C$2:$C$234,MATCH($A15,Lots_Data!$A$2:$A$234,0)) | C15: =INDEX(Lots_Data!$E$2:$E$234,MATCH($A15,Lots_Data!$A$2:$A$234,0)) | D15: =INDEX(Lots_Data!$D$2:$D$234,MATCH($A15,Lots_Data!$A$2:$A$234,0)) | E15: =INDEX(Lots_Data!$K$2:$K$234,MATCH($A15,Lots_Data!$A$2:$A$234,0)) | F15: =INDEX(Usage_Summary!$C$4:$C$236,MATCH($A15,Usage_Summary!$A$4:$A$236,0)) | G15: =IF($F15>0,$E15/$F15*30,"") | H15: =MAX(0,CEILING(ROUND($F15*Inputs!$B$10/30*Inputs!$B$7,6),1)-$E15) | I15: =MAX(0,CEILING(ROUND($F15*Inputs!$B$11/30*Inputs!$B$7,6),1)-$E15) | J15: =MAX(0,CEILING(ROUND($F15*Inputs!$B$12/30*Inputs!$B$7,6),1)-$E15) | K15: =IF(AND($F15>0,$E15<=0),1,0) | L15: =INDEX(Lots_Data!$S$2:$S$234,MATCH($A15,Lots_Data!$A$2:$A$234,0)) | M15: =INDEX(Lots_Data!$N$2:$N$234,MATCH($A15,Lots_Data!$A$2:$A$234,0)) | N15: =IF($F15=0,"n/a",IF($L15>=$F15/30*$M15,"adequate","under-set"))
... A236: SS-01233 | B236: =INDEX(Lots_Data!$C$2:$C$234,MATCH($A236,Lots_Data!$A$2:$A$234,0)) | C236: =INDEX(Lots_Data!$E$2:$E$234,MATCH($A236,Lots_Data!$A$2:$A$234,0)) | D236: =INDEX(Lots_Data!$D$2:$D$234,MATCH($A236,Lots_Data!$A$2:$A$234,0)) | E236: =INDEX(Lots_Data!$K$2:$K$234,MATCH($A236,Lots_Data!$A$2:$A$234,0)) | F236: =INDEX(Usage_Summary!$C$4:$C$236,MATCH($A236,Usage_Summary!$A$4:$A$236,0)) | G236: =IF($F236>0,$E236/$F236*30,"") | H236: =MAX(0,CEILING(ROUND($F236*Inputs!$B$10/30*Inputs!$B$7,6),1)-$E236) | I236: =MAX(0,CEILING(ROUND($F236*Inputs!$B$11/30*Inputs!$B$7,6),1)-$E236) | J236: =MAX(0,CEILING(ROUND($F236*Inputs!$B$12/30*Inputs!$B$7,6),1)-$E236) | K236: =IF(AND($F236>0,$E236<=0),1,0) | L236: =INDEX(Lots_Data!$S$2:$S$234,MATCH($A236,Lots_Data!$A$2:$A$234,0)) | M236: =INDEX(Lots_Data!$N$2:$N$234,MATCH($A236,Lots_Data!$A$2:$A$234,0)) | N236: =IF($F236=0,"n/a",IF($L236>=$F236/30*$M236,"adequate","under-set"))

Sheet Supplier_Scorecard
A1: Supplier performance & renewal scorecard
A2: Live SUMIFS/COUNTIFS over Supplier_Info, PO_Data, Delivery_Data, Quality_Data. Weights: Inputs B15:B18. Stance/basis columns are recommendations, not data.
A3: supplier_id | B3: supplier_name | C3: orders_placed | D3: on_time | E3: late | F3: short_shipped | G3: OTD_rate | H3: short_ship_rate | I3: total_spend_usd | J3: avg_lead_days | K3: quality_issues | L3: events_total | M3: events_open | N3: events_scope_unresolved | O3: events_not_closed | P3: PO_fill_rate | Q3: partial_POs | R3: cancelled_POs | S3: lead_score | T3: unresolved_score | U3: composite_score | V3: rank | W3: contract_end | X3: payment_terms | Y3: MOQ_usd | Z3: lots_on_hand | AA3: recalled_lots_on_hand | AB3: renewal_stance | AC3: stance_basis
A4: 1 | B4: =INDEX(Supplier_Info!$B$2:$B$6,MATCH($A4,Supplier_Info!$A$2:$A$6,0)) | C4: =SUMIFS(Delivery_Data!$E$2:$E$61,Delivery_Data!$B$2:$B$61,$A4) | D4: =SUMIFS(Delivery_Data!$F$2:$F$61,Delivery_Data!$B$2:$B$61,$A4) | E4: =SUMIFS(Delivery_Data!$G$2:$G$61,Delivery_Data!$B$2:$B$61,$A4) | F4: =SUMIFS(Delivery_Data!$H$2:$H$61,Delivery_Data!$B$2:$B$61,$A4) | G4: =D4/C4 | H4: =F4/C4 | I4: =SUMIFS(Delivery_Data!$I$2:$I$61,Delivery_Data!$B$2:$B$61,$A4) | J4: =AVERAGEIFS(Delivery_Data!$J$2:$J$61,Delivery_Data!$B$2:$B$61,$A4) | K4: =SUMIFS(Delivery_Data!$K$2:$K$61,Delivery_Data!$B$2:$B$61,$A4) | L4: =COUNTIFS(Quality_Data!$B$2:$B$25,$A4) | M4: =COUNTIFS(Quality_Data!$B$2:$B$25,$A4,Quality_Data!$G$2:$G$25,"open") | N4: =COUNTIFS(Quality_Data!$B$2:$B$25,$A4,Quality_Data!$G$2:$G$25,"scope-unresolved") | O4: =M4+N4 | P4: =SUMIFS(PO_Data!$J$2:$J$121,PO_Data!$C$2:$C$121,$A4)/SUMIFS(PO_Data!$I$2:$I$121,PO_Data!$C$2:$C$121,$A4) | Q4: =COUNTIFS(PO_Data!$C$2:$C$121,$A4,PO_Data!$H$2:$H$121,"Partially Delivered") | R4: =COUNTIFS(PO_Data!$C$2:$C$121,$A4,PO_Data!$H$2:$H$121,"Cancelled") | S4: =MIN($J$4:$J$8)/J4 | T4: =IF(MAX($O$4:$O$8)=0,1,1-O4/MAX($O$4:$O$8)) | U4: =Inputs!$B$15*G4+Inputs!$B$16*S4+Inputs!$B$17*T4+Inputs!$B$18*P4 | V4: =RANK(U4,$U$4:$U$8) | W4: =INDEX(Supplier_Info!$G$2:$G$6,MATCH($A4,Supplier_Info!$A$2:$A$6,0)) | X4: =INDEX(Supplier_Info!$E$2:$E$6,MATCH($A4,Supplier_Info!$A$2:$A$6,0)) | Y4: =INDEX(Supplier_Info!$H$2:$H$6,MATCH($A4,Supplier_Info!$A$2:$A$6,0)) | Z4: =COUNTIFS(Lots_Data!$D$2:$D$234,$B4) | AA4: =COUNTIFS(Lots_Data!$D$2:$D$234,$B4,Lots_Data!$J$2:$J$234,"recalled") | AB4: Renegotiate with corrective conditions | AC4: Earliest contract expiry (2027-01-14) with mid-pack OTD (73.3%) and highest-2nd spend; recalled lot LOT-07001 on hand. Do not auto-renew: require OTD improvement commitment and closure evidence on 3 not-closed quality events; qualify a second vascular source.
A5: 2 | B5: =INDEX(Supplier_Info!$B$2:$B$6,MATCH($A5,Supplier_Info!$A$2:$A$6,0)) | C5: =SUMIFS(Delivery_Data!$E$2:$E$61,Delivery_Data!$B$2:$B$61,$A5) | D5: =SUMIFS(Delivery_Data!$F$2:$F$61,Delivery_Data!$B$2:$B$61,$A5) | E5: =SUMIFS(Delivery_Data!$G$2:$G$61,Delivery_Data!$B$2:$B$61,$A5) | F5: =SUMIFS(Delivery_Data!$H$2:$H$61,Delivery_Data!$B$2:$B$61,$A5) | G5: =D5/C5 | H5: =F5/C5 | I5: =SUMIFS(Delivery_Data!$I$2:$I$61,Delivery_Data!$B$2:$B$61,$A5) | J5: =AVERAGEIFS(Delivery_Data!$J$2:$J$61,Delivery_Data!$B$2:$B$61,$A5) | K5: =SUMIFS(Delivery_Data!$K$2:$K$61,Delivery_Data!$B$2:$B$61,$A5) | L5: =COUNTIFS(Quality_Data!$B$2:$B$25,$A5) | M5: =COUNTIFS(Quality_Data!$B$2:$B$25,$A5,Quality_Data!$G$2:$G$25,"open") | N5: =COUNTIFS(Quality_Data!$B$2:$B$25,$A5,Quality_Data!$G$2:$G$25,"scope-unresolved") | O5: =M5+N5 | P5: =SUMIFS(PO_Data!$J$2:$J$121,PO_Data!$C$2:$C$121,$A5)/SUMIFS(PO_Data!$I$2:$I$121,PO_Data!$C$2:$C$121,$A5) | Q5: =COUNTIFS(PO_Data!$C$2:$C$121,$A5,PO_Data!$H$2:$H$121,"Partially Delivered") | R5: =COUNTIFS(PO_Data!$C$2:$C$121,$A5,PO_Data!$H$2:$H$121,"Cancelled") | S5: =MIN($J$4:$J$8)/J5 | T5: =IF(MAX($O$4:$O$8)=0,1,1-O5/MAX($O$4:$O$8)) | U5: =Inputs!$B$15*G5+Inputs!$B$16*S5+Inputs!$B$17*T5+Inputs!$B$18*P5 | V5: =RANK(U5,$U$4:$U$8) | W5: =INDEX(Supplier_Info!$G$2:$G$6,MATCH($A5,Supplier_Info!$A$2:$A$6,0)) | X5: =INDEX(Supplier_Info!$E$2:$E$6,MATCH($A5,Supplier_Info!$A$2:$A$6,0)) | Y5: =INDEX(Supplier_Info!$H$2:$H$6,MATCH($A5,Supplier_Info!$A$2:$A$6,0)) | Z5: =COUNTIFS(Lots_Data!$D$2:$D$234,$B5) | AA5: =COUNTIFS(Lots_Data!$D$2:$D$234,$B5,Lots_Data!$J$2:$J$234,"recalled") | AB5: Conditional renewal with remediation plan | AC5: OTD 77.3%, avg lead 6.1d; 2/10 Net 30 terms; 3 not-closed quality events and recalled lot LOT-07142 on hand. Renew only with a 90-day remediation milestone and fill-rate monitoring.
A6: 3 | B6: =INDEX(Supplier_Info!$B$2:$B$6,MATCH($A6,Supplier_Info!$A$2:$A$6,0)) | C6: =SUMIFS(Delivery_Data!$E$2:$E$61,Delivery_Data!$B$2:$B$61,$A6) | D6: =SUMIFS(Delivery_Data!$F$2:$F$61,Delivery_Data!$B$2:$B$61,$A6) | E6: =SUMIFS(Delivery_Data!$G$2:$G$61,Delivery_Data!$B$2:$B$61,$A6) | F6: =SUMIFS(Delivery_Data!$H$2:$H$61,Delivery_Data!$B$2:$B$61,$A6) | G6: =D6/C6 | H6: =F6/C6 | I6: =SUMIFS(Delivery_Data!$I$2:$I$61,Delivery_Data!$B$2:$B$61,$A6) | J6: =AVERAGEIFS(Delivery_Data!$J$2:$J$61,Delivery_Data!$B$2:$B$61,$A6) | K6: =SUMIFS(Delivery_Data!$K$2:$K$61,Delivery_Data!$B$2:$B$61,$A6) | L6: =COUNTIFS(Quality_Data!$B$2:$B$25,$A6) | M6: =COUNTIFS(Quality_Data!$B$2:$B$25,$A6,Quality_Data!$G$2:$G$25,"open") | N6: =COUNTIFS(Quality_Data!$B$2:$B$25,$A6,Quality_Data!$G$2:$G$25,"scope-unresolved") | O6: =M6+N6 | P6: =SUMIFS(PO_Data!$J$2:$J$121,PO_Data!$C$2:$C$121,$A6)/SUMIFS(PO_Data!$I$2:$I$121,PO_Data!$C$2:$C$121,$A6) | Q6: =COUNTIFS(PO_Data!$C$2:$C$121,$A6,PO_Data!$H$2:$H$121,"Partially Delivered") | R6: =COUNTIFS(PO_Data!$C$2:$C$121,$A6,PO_Data!$H$2:$H$121,"Cancelled") | S6: =MIN($J$4:$J$8)/J6 | T6: =IF(MAX($O$4:$O$8)=0,1,1-O6/MAX($O$4:$O$8)) | U6: =Inputs!$B$15*G6+Inputs!$B$16*S6+Inputs!$B$17*T6+Inputs!$B$18*P6 | V6: =RANK(U6,$U$4:$U$8) | W6: =INDEX(Supplier_Info!$G$2:$G$6,MATCH($A6,Supplier_Info!$A$2:$A$6,0)) | X6: =INDEX(Supplier_Info!$E$2:$E$6,MATCH($A6,Supplier_Info!$A$2:$A$6,0)) | Y6: =INDEX(Supplier_Info!$H$2:$H$6,MATCH($A6,Supplier_Info!$A$2:$A$6,0)) | Z6: =COUNTIFS(Lots_Data!$D$2:$D$234,$B6) | AA6: =COUNTIFS(Lots_Data!$D$2:$D$234,$B6,Lots_Data!$J$2:$J$234,"recalled") | AB6: Renew with quality-escalation clause | AC6: Strong OTD (90.6%) and 3.4d lead at the highest spend ($438.7k), but the most not-closed quality events (4). Renewal justified on service; condition it on closing event scope and sterility-deviation CAPA evidence.
A7: 4 | B7: =INDEX(Supplier_Info!$B$2:$B$6,MATCH($A7,Supplier_Info!$A$2:$A$6,0)) | C7: =SUMIFS(Delivery_Data!$E$2:$E$61,Delivery_Data!$B$2:$B$61,$A7) | D7: =SUMIFS(Delivery_Data!$F$2:$F$61,Delivery_Data!$B$2:$B$61,$A7) | E7: =SUMIFS(Delivery_Data!$G$2:$G$61,Delivery_Data!$B$2:$B$61,$A7) | F7: =SUMIFS(Delivery_Data!$H$2:$H$61,Delivery_Data!$B$2:$B$61,$A7) | G7: =D7/C7 | H7: =F7/C7 | I7: =SUMIFS(Delivery_Data!$I$2:$I$61,Delivery_Data!$B$2:$B$61,$A7) | J7: =AVERAGEIFS(Delivery_Data!$J$2:$J$61,Delivery_Data!$B$2:$B$61,$A7) | K7: =SUMIFS(Delivery_Data!$K$2:$K$61,Delivery_Data!$B$2:$B$61,$A7) | L7: =COUNTIFS(Quality_Data!$B$2:$B$25,$A7) | M7: =COUNTIFS(Quality_Data!$B$2:$B$25,$A7,Quality_Data!$G$2:$G$25,"open") | N7: =COUNTIFS(Quality_Data!$B$2:$B$25,$A7,Quality_Data!$G$2:$G$25,"scope-unresolved") | O7: =M7+N7 | P7: =SUMIFS(PO_Data!$J$2:$J$121,PO_Data!$C$2:$C$121,$A7)/SUMIFS(PO_Data!$I$2:$I$121,PO_Data!$C$2:$C$121,$A7) | Q7: =COUNTIFS(PO_Data!$C$2:$C$121,$A7,PO_Data!$H$2:$H$121,"Partially Delivered") | R7: =COUNTIFS(PO_Data!$C$2:$C$121,$A7,PO_Data!$H$2:$H$121,"Cancelled") | S7: =MIN($J$4:$J$8)/J7 | T7: =IF(MAX($O$4:$O$8)=0,1,1-O7/MAX($O$4:$O$8)) | U7: =Inputs!$B$15*G7+Inputs!$B$16*S7+Inputs!$B$17*T7+Inputs!$B$18*P7 | V7: =RANK(U7,$U$4:$U$8) | W7: =INDEX(Supplier_Info!$G$2:$G$6,MATCH($A7,Supplier_Info!$A$2:$A$6,0)) | X7: =INDEX(Supplier_Info!$E$2:$E$6,MATCH($A7,Supplier_Info!$A$2:$A$6,0)) | Y7: =INDEX(Supplier_Info!$H$2:$H$6,MATCH($A7,Supplier_Info!$A$2:$A$6,0)) | Z7: =COUNTIFS(Lots_Data!$D$2:$D$234,$B7) | AA7: =COUNTIFS(Lots_Data!$D$2:$D$234,$B7,Lots_Data!$J$2:$J$234,"recalled") | AB7: Corrective action and dual-source | AC7: Weakest OTD (56.3%) and slowest lead (11.1d, ~3x best); largest recalled quantity on hand (25 units, LOT-07189). Lowest spend ($93.2k) limits leverage; begin dual-sourcing diagnostics before 2027-05-31 expiry.
A8: 5 | B8: =INDEX(Supplier_Info!$B$2:$B$6,MATCH($A8,Supplier_Info!$A$2:$A$6,0)) | C8: =SUMIFS(Delivery_Data!$E$2:$E$61,Delivery_Data!$B$2:$B$61,$A8) | D8: =SUMIFS(Delivery_Data!$F$2:$F$61,Delivery_Data!$B$2:$B$61,$A8) | E8: =SUMIFS(Delivery_Data!$G$2:$G$61,Delivery_Data!$B$2:$B$61,$A8) | F8: =SUMIFS(Delivery_Data!$H$2:$H$61,Delivery_Data!$B$2:$B$61,$A8) | G8: =D8/C8 | H8: =F8/C8 | I8: =SUMIFS(Delivery_Data!$I$2:$I$61,Delivery_Data!$B$2:$B$61,$A8) | J8: =AVERAGEIFS(Delivery_Data!$J$2:$J$61,Delivery_Data!$B$2:$B$61,$A8) | K8: =SUMIFS(Delivery_Data!$K$2:$K$61,Delivery_Data!$B$2:$B$61,$A8) | L8: =COUNTIFS(Quality_Data!$B$2:$B$25,$A8) | M8: =COUNTIFS(Quality_Data!$B$2:$B$25,$A8,Quality_Data!$G$2:$G$25,"open") | N8: =COUNTIFS(Quality_Data!$B$2:$B$25,$A8,Quality_Data!$G$2:$G$25,"scope-unresolved") | O8: =M8+N8 | P8: =SUMIFS(PO_Data!$J$2:$J$121,PO_Data!$C$2:$C$121,$A8)/SUMIFS(PO_Data!$I$2:$I$121,PO_Data!$C$2:$C$121,$A8) | Q8: =COUNTIFS(PO_Data!$C$2:$C$121,$A8,PO_Data!$H$2:$H$121,"Partially Delivered") | R8: =COUNTIFS(PO_Data!$C$2:$C$121,$A8,PO_Data!$H$2:$H$121,"Cancelled") | S8: =MIN($J$4:$J$8)/J8 | T8: =IF(MAX($O$4:$O$8)=0,1,1-O8/MAX($O$4:$O$8)) | U8: =Inputs!$B$15*G8+Inputs!$B$16*S8+Inputs!$B$17*T8+Inputs!$B$18*P8 | V8: =RANK(U8,$U$4:$U$8) | W8: =INDEX(Supplier_Info!$G$2:$G$6,MATCH($A8,Supplier_Info!$A$2:$A$6,0)) | X8: =INDEX(Supplier_Info!$E$2:$E$6,MATCH($A8,Supplier_Info!$A$2:$A$6,0)) | Y8: =INDEX(Supplier_Info!$H$2:$H$6,MATCH($A8,Supplier_Info!$A$2:$A$6,0)) | Z8: =COUNTIFS(Lots_Data!$D$2:$D$234,$B8) | AA8: =COUNTIFS(Lots_Data!$D$2:$D$234,$B8,Lots_Data!$J$2:$J$234,"recalled") | AB8: Renew as preferred; candidate for expanded volume | AC8: Best OTD (95.0%) and fastest lead (2.8d); longest contract runway (to 2028-01-31). 3 not-closed quality events still require closure discipline before volume shift.

Sheet Scenario_Decision
A1: Scenario action programs — adverse / base / upside
A2: Selected flags (0/1, yellow) are the greedy-rule output (see Uncertainty_Register U-08..U-11) and remain editable; capacity, mutual-exclusion, eligibility and feasibility checks are live formulas. Recalculate after any change.
A4: Family gap to target cover (units)
A5: family | B5: adverse | C5: base | D5: upside
A6: vascular | B6: =SUMIFS(SKU_Exposure!$H$4:$H$236,SKU_Exposure!$B$4:$B$236,$A6) | C6: =SUMIFS(SKU_Exposure!$I$4:$I$236,SKU_Exposure!$B$4:$B$236,$A6) | D6: =SUMIFS(SKU_Exposure!$J$4:$J$236,SKU_Exposure!$B$4:$B$236,$A6)
A7: respiratory | B7: =SUMIFS(SKU_Exposure!$H$4:$H$236,SKU_Exposure!$B$4:$B$236,$A7) | C7: =SUMIFS(SKU_Exposure!$I$4:$I$236,SKU_Exposure!$B$4:$B$236,$A7) | D7: =SUMIFS(SKU_Exposure!$J$4:$J$236,SKU_Exposure!$B$4:$B$236,$A7)
A8: surgical | B8: =SUMIFS(SKU_Exposure!$H$4:$H$236,SKU_Exposure!$B$4:$B$236,$A8) | C8: =SUMIFS(SKU_Exposure!$I$4:$I$236,SKU_Exposure!$B$4:$B$236,$A8) | D8: =SUMIFS(SKU_Exposure!$J$4:$J$236,SKU_Exposure!$B$4:$B$236,$A8)
A9: diagnostic | B9: =SUMIFS(SKU_Exposure!$H$4:$H$236,SKU_Exposure!$B$4:$B$236,$A9) | C9: =SUMIFS(SKU_Exposure!$I$4:$I$236,SKU_Exposure!$B$4:$B$236,$A9) | D9: =SUMIFS(SKU_Exposure!$J$4:$J$236,SKU_Exposure!$B$4:$B$236,$A9)
A10: wound | B10: =SUMIFS(SKU_Exposure!$H$4:$H$236,SKU_Exposure!$B$4:$B$236,$A10) | C10: =SUMIFS(SKU_Exposure!$I$4:$I$236,SKU_Exposure!$B$4:$B$236,$A10) | D10: =SUMIFS(SKU_Exposure!$J$4:$J$236,SKU_Exposure!$B$4:$B$236,$A10)
A11: TOTAL | B11: =SUM(B6:B10) | C11: =SUM(C6:C10) | D11: =SUM(D6:D10)
A13: Scenario: ADVERSE
A14: priority | B14: action_id | C14: eligible_family | D14: target_family | E14: lever | F14: grade | G14: provided_units | H14: fixed_cost_usd | I14: pool | J14: capacity_units | K14: overlap_group | L14: shared_frac | M14: mx_group | N14: dependency_group | O14: selected (edit 0/1) | P14: eligible? | Q14: eff_capacity | R14: prior_coverage_tgt | S14: coverage_units | T14: start_delay_days | U14: mx_violation | V14: elig_violation
A15: 1 | B15: SAC-013 | C15: vascular | D15: vascular | E15: expedite receipt | F15: A | G15: 32.4 | H15: 1200 | I15: RECEIVING_SLOT | J15: 0.5 | K15: OV-3 | L15: 0 | N15: DG-1 | O15: 1 | P15: =INDEX(Action_Catalog!$Q$4:$Q$27,MATCH($B15,Action_Catalog!$A$4:$A$27,0)) | Q15: =$O15*$J15*IF(COUNTIFS($K$15:$K15,$K15,$O$15:$O15,1)>1,1-$L15,1) | R15: =SUMIFS($S$14:$S14,$D$14:$D14,$D15) | S15: =$O15*MIN($G15,MAX(0,INDEX($B$6:$D$10,MATCH($D15,$A$6:$A$10,0),1)-$R15)) | T15: 1 | U15: =IF(AND($M15<>"",$O15=1,COUNTIFS($M$15:$M$38,$M15,$O$15:$O$38,1)>1),1,0) | V15: =IF(AND($O15=1,$P15=0),1,0)
A16: 2 | B16: SAC-010 | C16: diagnostic | D16: diagnostic | E16: site transfer | F16: A | G16: 60.8 | H16: 4500 | I16: TRANSFER_VEHICLE | J16: 1 | K16: OV-5 | L16: 0.2 | N16: DG-4 | O16: 0 | P16: =INDEX(Action_Catalog!$Q$4:$Q$27,MATCH($B16,Action_Catalog!$A$4:$A$27,0)) | Q16: =$O16*$J16*IF(COUNTIFS($K$15:$K16,$K16,$O$15:$O16,1)>1,1-$L16,1) | R16: =SUMIFS($S$14:$S15,$D$14:$D15,$D16) | S16: =$O16*MIN($G16,MAX(0,INDEX($B$6:$D$10,MATCH($D16,$A$6:$A$10,0),1)-$R16)) | T16: 3 | U16: =IF(AND($M16<>"",$O16=1,COUNTIFS($M$15:$M$38,$M16,$O$15:$O$38,1)>1),1,0) | V16: =IF(AND($O16=1,$P16=0),1,0)
A17: 3 | B17: SAC-001 | C17: vascular | D17: vascular | E17: expedite receipt | F17: A | G17: 16.2 | H17: 1200 | I17: BUYER_FTE | J17: 0.5 | K17: OV-1 | L17: 0 | M17: MX-1 | N17: DG-1 | O17: 1 | P17: =INDEX(Action_Catalog!$Q$4:$Q$27,MATCH($B17,Action_Catalog!$A$4:$A$27,0)) | Q17: =$O17*$J17*IF(COUNTIFS($K$15:$K17,$K17,$O$15:$O17,1)>1,1-$L17,1) | R17: =SUMIFS($S$14:$S16,$D$14:$D16,$D17) | S17: =$O17*MIN($G17,MAX(0,INDEX($B$6:$D$10,MATCH($D17,$A$6:$A$10,0),1)-$R17)) | T17: 1 | U17: =IF(AND($M17<>"",$O17=1,COUNTIFS($M$15:$M$38,$M17,$O$15:$O$38,1)>1),1,0) | V17: =IF(AND($O17=1,$P17=0),1,0)
A18: 4 | B18: SAC-022 | C18: diagnostic | D18: diagnostic | E18: site transfer | F18: A | G18: 24.3 | H18: 4500 | I18: COLD_CHAIN_PALLET | J18: 1 | K18: OV-2 | L18: 0.2 | N18: DG-4 | O18: 1 | P18: =INDEX(Action_Catalog!$Q$4:$Q$27,MATCH($B18,Action_Catalog!$A$4:$A$27,0)) | Q18: =$O18*$J18*IF(COUNTIFS($K$15:$K18,$K18,$O$15:$O18,1)>1,1-$L18,1) | R18: =SUMIFS($S$14:$S17,$D$14:$D17,$D18) | S18: =$O18*MIN($G18,MAX(0,INDEX($B$6:$D$10,MATCH($D18,$A$6:$A$10,0),1)-$R18)) | T18: 3 | U18: =IF(AND($M18<>"",$O18=1,COUNTIFS($M$15:$M$38,$M18,$O$15:$O$38,1)>1),1,0) | V18: =IF(AND($O18=1,$P18=0),1,0)
A19: 5 | B19: SAC-019 | C19: vascular | D19: vascular | E19: supplier substitution | F19: A | G19: 43.2 | H19: 9000 | I19: CLINICAL_REVIEW | J19: 1.5 | K19: OV-4 | L19: 0.35 | N19: DG-1 | O19: 0 | P19: =INDEX(Action_Catalog!$Q$4:$Q$27,MATCH($B19,Action_Catalog!$A$4:$A$27,0)) | Q19: =$O19*$J19*IF(COUNTIFS($K$15:$K19,$K19,$O$15:$O19,1)>1,1-$L19,1) | R19: =SUMIFS($S$14:$S18,$D$14:$D18,$D19) | S19: =$O19*MIN($G19,MAX(0,INDEX($B$6:$D$10,MATCH($D19,$A$6:$A$10,0),1)-$R19)) | T19: 7 | U19: =IF(AND($M19<>"",$O19=1,COUNTIFS($M$15:$M$38,$M19,$O$15:$O$38,1)>1),1,0) | V19: =IF(AND($O19=1,$P19=0),1,0)
A20: 6 | B20: SAC-007 | C20: vascular | D20: vascular | E20: supplier substitution | F20: A | G20: 24.3 | H20: 9000 | I20: COLD_CHAIN_PALLET | J20: 1.5 | K20: OV-2 | L20: 0.35 | N20: DG-1 | O20: 0 | P20: =INDEX(Action_Catalog!$Q$4:$Q$27,MATCH($B20,Action_Catalog!$A$4:$A$27,0)) | Q20: =$O20*$J20*IF(COUNTIFS($K$15:$K20,$K20,$O$15:$O20,1)>1,1-$L20,1) | R20: =SUMIFS($S$14:$S19,$D$14:$D19,$D20) | S20: =$O20*MIN($G20,MAX(0,INDEX($B$6:$D$10,MATCH($D20,$A$6:$A$10,0),1)-$R20)) | T20: 7 | U20: =IF(AND($M20<>"",$O20=1,COUNTIFS($M$15:$M$38,$M20,$O$15:$O$38,1)>1),1,0) | V20: =IF(AND($O20=1,$P20=0),1,0)
A21: 7 | B21: SAC-004 | C21: diagnostic | D21: diagnostic | E21: allocation hold | F21: A | G21: 43.2 | H21: 18000 | I21: CLINICAL_REVIEW | J21: 2 | K21: OV-4 | L21: 0.5 | N21: DG-4 | O21: 0 | P21: =INDEX(Action_Catalog!$Q$4:$Q$27,MATCH($B21,Action_Catalog!$A$4:$A$27,0)) | Q21: =$O21*$J21*IF(COUNTIFS($K$15:$K21,$K21,$O$15:$O21,1)>1,1-$L21,1) | R21: =SUMIFS($S$14:$S20,$D$14:$D20,$D21) | S21: =$O21*MIN($G21,MAX(0,INDEX($B$6:$D$10,MATCH($D21,$A$6:$A$10,0),1)-$R21)) | T21: 14 | U21: =IF(AND($M21<>"",$O21=1,COUNTIFS($M$15:$M$38,$M21,$O$15:$O$38,1)>1),1,0) | V21: =IF(AND($O21=1,$P21=0),1,0)
A22: 8 | B22: SAC-016 | C22: diagnostic | D22: diagnostic | E22: allocation hold | F22: A | G22: 16.2 | H22: 18000 | I22: BUYER_FTE | J22: 2 | K22: OV-1 | L22: 0.5 | M22: MX-4 | N22: DG-4 | O22: 1 | P22: =INDEX(Action_Catalog!$Q$4:$Q$27,MATCH($B22,Action_Catalog!$A$4:$A$27,0)) | Q22: =$O22*$J22*IF(COUNTIFS($K$15:$K22,$K22,$O$15:$O22,1)>1,1-$L22,1) | R22: =SUMIFS($S$14:$S21,$D$14:$D21,$D22) | S22: =$O22*MIN($G22,MAX(0,INDEX($B$6:$D$10,MATCH($D22,$A$6:$A$10,0),1)-$R22)) | T22: 14 | U22: =IF(AND($M22<>"",$O22=1,COUNTIFS($M$15:$M$38,$M22,$O$15:$O$38,1)>1),1,0) | V22: =IF(AND($O22=1,$P22=0),1,0)
A40: ADVERSE summary
A41: metric | B41: value | C41: check
A42: actions selected | B42: =SUM($O$15:$O$38)
A43: fixed cost (USD) | B43: =SUMPRODUCT($O$15:$O$38,$H$15:$H$38)
A44: family gap (units) | B44: =B$11 | C44: from family gap table
A45: coverage (units) | B45: =SUM($S$15:$S$38)
A46: residual gap (units) | B46: =B44-B45 | C46: gap - coverage
A47: mx violations | B47: =SUM($U$15:$U$38) | C47: must be 0
A48: eligibility violations | B48: =SUM($V$15:$V$38) | C48: must be 0
A49: program start delay (days) | B49: =IF(SUM($O$15:$O$38)=0,0,SUMPRODUCT(MAX(($O$15:$O$38=1)*$T$15:$T$38))) | C49: max delay of selected
A51: pool | B51: consumed | C51: net_capacity | D51: within_capacity
A52: BUYER_FTE | B52: =SUMIFS($Q$15:$Q$38,$I$15:$I$38,$A52) | C52: =Site_Constraints!D$19 | D52: =IF(B52<=C52,1,0)
A53: CLINICAL_REVIEW | B53: =SUMIFS($Q$15:$Q$38,$I$15:$I$38,$A53) | C53: =Site_Constraints!D$20 | D53: =IF(B53<=C53,1,0)
A54: COLD_CHAIN_PALLET | B54: =SUMIFS($Q$15:$Q$38,$I$15:$I$38,$A54) | C54: =Site_Constraints!D$21 | D54: =IF(B54<=C54,1,0)
A55: RECEIVING_SLOT | B55: =SUMIFS($Q$15:$Q$38,$I$15:$I$38,$A55) | C55: =Site_Constraints!D$22 | D55: =IF(B55<=C55,1,0)
A56: TRANSFER_VEHICLE | B56: =SUMIFS($Q$15:$Q$38,$I$15:$I$38,$A56) | C56: =Site_Constraints!D$23 | D56: =IF(B56<=C56,1,0)
A57: all pools feasible | B57: =SUM($D$52:$D$56) | C57: must equal 5
A58: Scenario: BASE
A59: priority | B59: action_id | C59: eligible_family | D59: target_family | E59: lever | F59: grade | G59: provided_units | H59: fixed_cost_usd | I59: pool | J59: capacity_units | K59: overlap_group | L59: shared_frac | M59: mx_group | N59: dependency_group | O59: selected (edit 0/1) | P59: eligible? | Q59: eff_capacity | R59: prior_coverage_tgt | S59: coverage_units | T59: start_delay_days | U59: mx_violation | V59: elig_violation
A60: 1 | B60: SAC-013 | C60: vascular | D60: vascular | E60: expedite receipt | F60: A | G60: 32.4 | H60: 1200 | I60: RECEIVING_SLOT | J60: 0.5 | K60: OV-3 | L60: 0 | N60: DG-1 | O60: 1 | P60: =INDEX(Action_Catalog!$R$4:$R$27,MATCH($B60,Action_Catalog!$A$4:$A$27,0)) | Q60: =$O60*$J60*IF(COUNTIFS($K$60:$K60,$K60,$O$60:$O60,1)>1,1-$L60,1) | R60: =SUMIFS($S$59:$S59,$D$59:$D59,$D60) | S60: =$O60*MIN($G60,MAX(0,INDEX($B$6:$D$10,MATCH($D60,$A$6:$A$10,0),2)-$R60)) | T60: 1 | U60: =IF(AND($M60<>"",$O60=1,COUNTIFS($M$60:$M$83,$M60,$O$60:$O$83,1)>1),1,0) | V60: =IF(AND($O60=1,$P60=0),1,0)
A61: 2 | B61: SAC-010 | C61: diagnostic | D61: diagnostic | E61: site transfer | F61: A | G61: 60.8 | H61: 4500 | I61: TRANSFER_VEHICLE | J61: 1 | K61: OV-5 | L61: 0.2 | N61: DG-4 | O61: 1 | P61: =INDEX(Action_Catalog!$R$4:$R$27,MATCH($B61,Action_Catalog!$A$4:$A$27,0)) | Q61: =$O61*$J61*IF(COUNTIFS($K$60:$K61,$K61,$O$60:$O61,1)>1,1-$L61,1) | R61: =SUMIFS($S$59:$S60,$D$59:$D60,$D61) | S61: =$O61*MIN($G61,MAX(0,INDEX($B$6:$D$10,MATCH($D61,$A$6:$A$10,0),2)-$R61)) | T61: 3 | U61: =IF(AND($M61<>"",$O61=1,COUNTIFS($M$60:$M$83,$M61,$O$60:$O$83,1)>1),1,0) | V61: =IF(AND($O61=1,$P61=0),1,0)
A62: 3 | B62: SAC-001 | C62: vascular | D62: vascular | E62: expedite receipt | F62: A | G62: 16.2 | H62: 1200 | I62: BUYER_FTE | J62: 0.5 | K62: OV-1 | L62: 0 | M62: MX-1 | N62: DG-1 | O62: 1 | P62: =INDEX(Action_Catalog!$R$4:$R$27,MATCH($B62,Action_Catalog!$A$4:$A$27,0)) | Q62: =$O62*$J62*IF(COUNTIFS($K$60:$K62,$K62,$O$60:$O62,1)>1,1-$L62,1) | R62: =SUMIFS($S$59:$S61,$D$59:$D61,$D62) | S62: =$O62*MIN($G62,MAX(0,INDEX($B$6:$D$10,MATCH($D62,$A$6:$A$10,0),2)-$R62)) | T62: 1 | U62: =IF(AND($M62<>"",$O62=1,COUNTIFS($M$60:$M$83,$M62,$O$60:$O$83,1)>1),1,0) | V62: =IF(AND($O62=1,$P62=0),1,0)
A63: 4 | B63: SAC-022 | C63: diagnostic | D63: diagnostic | E63: site transfer | F63: A | G63: 24.3 | H63: 4500 | I63: COLD_CHAIN_PALLET | J63: 1 | K63: OV-2 | L63: 0.2 | N63: DG-4 | O63: 1 | P63: =INDEX(Action_Catalog!$R$4:$R$27,MATCH($B63,Action_Catalog!$A$4:$A$27,0)) | Q63: =$O63*$J63*IF(COUNTIFS($K$60:$K63,$K63,$O$60:$O63,1)>1,1-$L63,1) | R63: =SUMIFS($S$59:$S62,$D$59:$D62,$D63) | S63: =$O63*MIN($G63,MAX(0,INDEX($B$6:$D$10,MATCH($D63,$A$6:$A$10,0),2)-$R63)) | T63: 3 | U63: =IF(AND($M63<>"",$O63=1,COUNTIFS($M$60:$M$83,$M63,$O$60:$O$83,1)>1),1,0) | V63: =IF(AND($O63=1,$P63=0),1,0)
A64: 5 | B64: SAC-019 | C64: vascular | D64: vascular | E64: supplier substitution | F64: A | G64: 43.2 | H64: 9000 | I64: CLINICAL_REVIEW | J64: 1.5 | K64: OV-4 | L64: 0.35 | N64: DG-1 | O64: 1 | P64: =INDEX(Action_Catalog!$R$4:$R$27,MATCH($B64,Action_Catalog!$A$4:$A$27,0)) | Q64: =$O64*$J64*IF(COUNTIFS($K$60:$K64,$K64,$O$60:$O64,1)>1,1-$L64,1) | R64: =SUMIFS($S$59:$S63,$D$59:$D63,$D64) | S64: =$O64*MIN($G64,MAX(0,INDEX($B$6:$D$10,MATCH($D64,$A$6:$A$10,0),2)-$R64)) | T64: 7 | U64: =IF(AND($M64<>"",$O64=1,COUNTIFS($M$60:$M$83,$M64,$O$60:$O$83,1)>1),1,0) | V64: =IF(AND($O64=1,$P64=0),1,0)
A65: 6 | B65: SAC-007 | C65: vascular | D65: vascular | E65: supplier substitution | F65: A | G65: 24.3 | H65: 9000 | I65: COLD_CHAIN_PALLET | J65: 1.5 | K65: OV-2 | L65: 0.35 | N65: DG-1 | O65: 1 | P65: =INDEX(Action_Catalog!$R$4:$R$27,MATCH($B65,Action_Catalog!$A$4:$A$27,0)) | Q65: =$O65*$J65*IF(COUNTIFS($K$60:$K65,$K65,$O$60:$O65,1)>1,1-$L65,1) | R65: =SUMIFS($S$59:$S64,$D$59:$D64,$D65) | S65: =$O65*MIN($G65,MAX(0,INDEX($B$6:$D$10,MATCH($D65,$A$6:$A$10,0),2)-$R65)) | T65: 7 | U65: =IF(AND($M65<>"",$O65=1,COUNTIFS($M$60:$M$83,$M65,$O$60:$O$83,1)>1),1,0) | V65: =IF(AND($O65=1,$P65=0),1,0)
A66: 7 | B66: SAC-004 | C66: diagnostic | D66: diagnostic | E66: allocation hold | F66: A | G66: 43.2 | H66: 18000 | I66: CLINICAL_REVIEW | J66: 2 | K66: OV-4 | L66: 0.5 | N66: DG-4 | O66: 1 | P66: =INDEX(Action_Catalog!$R$4:$R$27,MATCH($B66,Action_Catalog!$A$4:$A$27,0)) | Q66: =$O66*$J66*IF(COUNTIFS($K$60:$K66,$K66,$O$60:$O66,1)>1,1-$L66,1) | R66: =SUMIFS($S$59:$S65,$D$59:$D65,$D66) | S66: =$O66*MIN($G66,MAX(0,INDEX($B$6:$D$10,MATCH($D66,$A$6:$A$10,0),2)-$R66)) | T66: 14 | U66: =IF(AND($M66<>"",$O66=1,COUNTIFS($M$60:$M$83,$M66,$O$60:$O$83,1)>1),1,0) | V66: =IF(AND($O66=1,$P66=0),1,0)
A67: 8 | B67: SAC-016 | C67: diagnostic | D67: diagnostic | E67: allocation hold | F67: A | G67: 16.2 | H67: 18000 | I67: BUYER_FTE | J67: 2 | K67: OV-1 | L67: 0.5 | M67: MX-4 | N67: DG-4 | O67: 1 | P67: =INDEX(Action_Catalog!$R$4:$R$27,MATCH($B67,Action_Catalog!$A$4:$A$27,0)) | Q67: =$O67*$J67*IF(COUNTIFS($K$60:$K67,$K67,$O$60:$O67,1)>1,1-$L67,1) | R67: =SUMIFS($S$59:$S66,$D$59:$D66,$D67) | S67: =$O67*MIN($G67,MAX(0,INDEX($B$6:$D$10,MATCH($D67,$A$6:$A$10,0),2)-$R67)) | T67: 14 | U67: =IF(AND($M67<>"",$O67=1,COUNTIFS($M$60:$M$83,$M67,$O$60:$O$83,1)>1),1,0) | V67: =IF(AND($O67=1,$P67=0),1,0)
A68: 9 | B68: SAC-005 | C68: wound | D68: wound | E68: expedite receipt | F68: B | G68: 60.8 | H68: 1200 | I68: TRANSFER_VEHICLE | J68: 0.5 | K68: OV-5 | L68: 0 | N68: DG-5 | O68: 1 | P68: =INDEX(Action_Catalog!$R$4:$R$27,MATCH($B68,Action_Catalog!$A$4:$A$27,0)) | Q68: =$O68*$J68*IF(COUNTIFS($K$60:$K68,$K68,$O$60:$O68,1)>1,1-$L68,1) | R68: =SUMIFS($S$59:$S67,$D$59:$D67,$D68) | S68: =$O68*MIN($G68,MAX(0,INDEX($B$6:$D$10,MATCH($D68,$A$6:$A$10,0),2)-$R68)) | T68: 1 | U68: =IF(AND($M68<>"",$O68=1,COUNTIFS($M$60:$M$83,$M68,$O$60:$O$83,1)>1),1,0) | V68: =IF(AND($O68=1,$P68=0),1,0)
A69: 10 | B69: SAC-017 | C69: wound | D69: wound | E69: expedite receipt | F69: B | G69: 24.3 | H69: 1200 | I69: COLD_CHAIN_PALLET | J69: 0.5 | K69: OV-2 | L69: 0 | N69: DG-5 | O69: 1 | P69: =INDEX(Action_Catalog!$R$4:$R$27,MATCH($B69,Action_Catalog!$A$4:$A$27,0)) | Q69: =$O69*$J69*IF(COUNTIFS($K$60:$K69,$K69,$O$60:$O69,1)>1,1-$L69,1) | R69: =SUMIFS($S$59:$S68,$D$59:$D68,$D69) | S69: =$O69*MIN($G69,MAX(0,INDEX($B$6:$D$10,MATCH($D69,$A$6:$A$10,0),2)-$R69)) | T69: 1 | U69: =IF(AND($M69<>"",$O69=1,COUNTIFS($M$60:$M$83,$M69,$O$60:$O$83,1)>1),1,0) | V69: =IF(AND($O69=1,$P69=0),1,0)
A70: 11 | B70: SAC-014 | C70: respiratory | D70: respiratory | E70: site transfer | F70: B | G70: 43.2 | H70: 4500 | I70: CLINICAL_REVIEW | J70: 1 | K70: OV-4 | L70: 0.2 | N70: DG-2 | O70: 0 | P70: =INDEX(Action_Catalog!$R$4:$R$27,MATCH($B70,Action_Catalog!$A$4:$A$27,0)) | Q70: =$O70*$J70*IF(COUNTIFS($K$60:$K70,$K70,$O$60:$O70,1)>1,1-$L70,1) | R70: =SUMIFS($S$59:$S69,$D$59:$D69,$D70) | S70: =$O70*MIN($G70,MAX(0,INDEX($B$6:$D$10,MATCH($D70,$A$6:$A$10,0),2)-$R70)) | T70: 3 | U70: =IF(AND($M70<>"",$O70=1,COUNTIFS($M$60:$M$83,$M70,$O$60:$O$83,1)>1),1,0) | V70: =IF(AND($O70=1,$P70=0),1,0)
A71: 12 | B71: SAC-002 | C71: respiratory | D71: respiratory | E71: site transfer | F71: B | G71: 24.3 | H71: 4500 | I71: COLD_CHAIN_PALLET | J71: 1 | K71: OV-2 | L71: 0.2 | N71: DG-2 | O71: 1 | P71: =INDEX(Action_Catalog!$R$4:$R$27,MATCH($B71,Action_Catalog!$A$4:$A$27,0)) | Q71: =$O71*$J71*IF(COUNTIFS($K$60:$K71,$K71,$O$60:$O71,1)>1,1-$L71,1) | R71: =SUMIFS($S$59:$S70,$D$59:$D70,$D71) | S71: =$O71*MIN($G71,MAX(0,INDEX($B$6:$D$10,MATCH($D71,$A$6:$A$10,0),2)-$R71)) | T71: 3 | U71: =IF(AND($M71<>"",$O71=1,COUNTIFS($M$60:$M$83,$M71,$O$60:$O$83,1)>1),1,0) | V71: =IF(AND($O71=1,$P71=0),1,0)
A72: 13 | B72: SAC-023 | C72: wound | D72: wound | E72: supplier substitution | F72: B | G72: 32.4 | H72: 9000 | I72: RECEIVING_SLOT | J72: 1.5 | K72: OV-3 | L72: 0.35 | N72: DG-5 | O72: 1 | P72: =INDEX(Action_Catalog!$R$4:$R$27,MATCH($B72,Action_Catalog!$A$4:$A$27,0)) | Q72: =$O72*$J72*IF(COUNTIFS($K$60:$K72,$K72,$O$60:$O72,1)>1,1-$L72,1) | R72: =SUMIFS($S$59:$S71,$D$59:$D71,$D72) | S72: =$O72*MIN($G72,MAX(0,INDEX($B$6:$D$10,MATCH($D72,$A$6:$A$10,0),2)-$R72)) | T72: 7 | U72: =IF(AND($M72<>"",$O72=1,COUNTIFS($M$60:$M$83,$M72,$O$60:$O$83,1)>1),1,0) | V72: =IF(AND($O72=1,$P72=0),1,0)
A73: 14 | B73: SAC-020 | C73: respiratory | D73: respiratory | E73: allocation hold | F73: B | G73: 60.8 | H73: 18000 | I73: TRANSFER_VEHICLE | J73: 2 | K73: OV-5 | L73: 0.5 | N73: DG-2 | O73: 0 | P73: =INDEX(Action_Catalog!$R$4:$R$27,MATCH($B73,Action_Catalog!$A$4:$A$27,0)) | Q73: =$O73*$J73*IF(COUNTIFS($K$60:$K73,$K73,$O$60:$O73,1)>1,1-$L73,1) | R73: =SUMIFS($S$59:$S72,$D$59:$D72,$D73) | S73: =$O73*MIN($G73,MAX(0,INDEX($B$6:$D$10,MATCH($D73,$A$6:$A$10,0),2)-$R73)) | T73: 14 | U73: =IF(AND($M73<>"",$O73=1,COUNTIFS($M$60:$M$83,$M73,$O$60:$O$83,1)>1),1,0) | V73: =IF(AND($O73=1,$P73=0),1,0)
A74: 15 | B74: SAC-008 | C74: respiratory | D74: respiratory | E74: allocation hold | F74: B | G74: 32.4 | H74: 18000 | I74: RECEIVING_SLOT | J74: 2 | K74: OV-3 | L74: 0.5 | N74: DG-2 | O74: 1 | P74: =INDEX(Action_Catalog!$R$4:$R$27,MATCH($B74,Action_Catalog!$A$4:$A$27,0)) | Q74: =$O74*$J74*IF(COUNTIFS($K$60:$K74,$K74,$O$60:$O74,1)>1,1-$L74,1) | R74: =SUMIFS($S$59:$S73,$D$59:$D73,$D74) | S74: =$O74*MIN($G74,MAX(0,INDEX($B$6:$D$10,MATCH($D74,$A$6:$A$10,0),2)-$R74)) | T74: 14 | U74: =IF(AND($M74<>"",$O74=1,COUNTIFS($M$60:$M$83,$M74,$O$60:$O$83,1)>1),1,0) | V74: =IF(AND($O74=1,$P74=0),1,0)
A75: 16 | B75: SAC-011 | C75: wound | D75: wound | E75: supplier substitution | F75: B | G75: 16.2 | H75: 9000 | I75: BUYER_FTE | J75: 1.5 | K75: OV-1 | L75: 0.35 | M75: MX-3 | N75: DG-5 | O75: 1 | P75: =INDEX(Action_Catalog!$R$4:$R$27,MATCH($B75,Action_Catalog!$A$4:$A$27,0)) | Q75: =$O75*$J75*IF(COUNTIFS($K$60:$K75,$K75,$O$60:$O75,1)>1,1-$L75,1) | R75: =SUMIFS($S$59:$S74,$D$59:$D74,$D75) | S75: =$O75*MIN($G75,MAX(0,INDEX($B$6:$D$10,MATCH($D75,$A$6:$A$10,0),2)-$R75)) | T75: 7 | U75: =IF(AND($M75<>"",$O75=1,COUNTIFS($M$60:$M$83,$M75,$O$60:$O$83,1)>1),1,0) | V75: =IF(AND($O75=1,$P75=0),1,0)
A85: BASE summary
A86: metric | B86: value | C86: check
A87: actions selected | B87: =SUM($O$60:$O$83)
A88: fixed cost (USD) | B88: =SUMPRODUCT($O$60:$O$83,$H$60:$H$83)
A89: family gap (units) | B89: =C$11 | C89: from family gap table
A90: coverage (units) | B90: =SUM($S$60:$S$83)
A91: residual gap (units) | B91: =B89-B90 | C91: gap - coverage
A92: mx violations | B92: =SUM($U$60:$U$83) | C92: must be 0
A93: eligibility violations | B93: =SUM($V$60:$V$83) | C93: must be 0
A94: program start delay (days) | B94: =IF(SUM($O$60:$O$83)=0,0,SUMPRODUCT(MAX(($O$60:$O$83=1)*$T$60:$T$83))) | C94: max delay of selected
A96: pool | B96: consumed | C96: net_capacity | D96: within_capacity
A97: BUYER_FTE | B97: =SUMIFS($Q$60:$Q$83,$I$60:$I$83,$A97) | C97: =Site_Constraints!G$19 | D97: =IF(B97<=C97,1,0)
A98: CLINICAL_REVIEW | B98: =SUMIFS($Q$60:$Q$83,$I$60:$I$83,$A98) | C98: =Site_Constraints!G$20 | D98: =IF(B98<=C98,1,0)
A99: COLD_CHAIN_PALLET | B99: =SUMIFS($Q$60:$Q$83,$I$60:$I$83,$A99) | C99: =Site_Constraints!G$21 | D99: =IF(B99<=C99,1,0)
A100: RECEIVING_SLOT | B100: =SUMIFS($Q$60:$Q$83,$I$60:$I$83,$A100) | C100: =Site_Constraints!G$22 | D100: =IF(B100<=C100,1,0)
A101: TRANSFER_VEHICLE | B101: =SUMIFS($Q$60:$Q$83,$I$60:$I$83,$A101) | C101: =Site_Constraints!G$23 | D101: =IF(B101<=C101,1,0)
A102: all pools feasible | B102: =SUM($D$97:$D$101) | C102: must equal 5
A103: Scenario: UPSIDE
A104: priority | B104: action_id | C104: eligible_family | D104: target_family | E104: lever | F104: grade | G104: provided_units | H104: fixed_cost_usd | I104: pool | J104: capacity_units | K104: overlap_group | L104: shared_frac | M104: mx_group | N104: dependency_group | O104: selected (edit 0/1) | P104: eligible? | Q104: eff_capacity | R104: prior_coverage_tgt | S104: coverage_units | T104: start_delay_days | U104: mx_violation | V104: elig_violation
A105: 1 | B105: SAC-013 | C105: vascular | D105: vascular | E105: expedite receipt | F105: A | G105: 32.4 | H105: 1200 | I105: RECEIVING_SLOT | J105: 0.5 | K105: OV-3 | L105: 0 | N105: DG-1 | O105: 1 | P105: =INDEX(Action_Catalog!$S$4:$S$27,MATCH($B105,Action_Catalog!$A$4:$A$27,0)) | Q105: =$O105*$J105*IF(COUNTIFS($K$105:$K105,$K105,$O$105:$O105,1)>1,1-$L105,1) | R105: =SUMIFS($S$104:$S104,$D$104:$D104,$D105) | S105: =$O105*MIN($G105,MAX(0,INDEX($B$6:$D$10,MATCH($D105,$A$6:$A$10,0),3)-$R105)) | T105: 1 | U105: =IF(AND($M105<>"",$O105=1,COUNTIFS($M$105:$M$128,$M105,$O$105:$O$128,1)>1),1,0) | V105: =IF(AND($O105=1,$P105=0),1,0)
A106: 2 | B106: SAC-010 | C106: diagnostic | D106: diagnostic | E106: site transfer | F106: A | G106: 60.8 | H106: 4500 | I106: TRANSFER_VEHICLE | J106: 1 | K106: OV-5 | L106: 0.2 | N106: DG-4 | O106: 1 | P106: =INDEX(Action_Catalog!$S$4:$S$27,MATCH($B106,Action_Catalog!$A$4:$A$27,0)) | Q106: =$O106*$J106*IF(COUNTIFS($K$105:$K106,$K106,$O$105:$O106,1)>1,1-$L106,1) | R106: =SUMIFS($S$104:$S105,$D$104:$D105,$D106) | S106: =$O106*MIN($G106,MAX(0,INDEX($B$6:$D$10,MATCH($D106,$A$6:$A$10,0),3)-$R106)) | T106: 3 | U106: =IF(AND($M106<>"",$O106=1,COUNTIFS($M$105:$M$128,$M106,$O$105:$O$128,1)>1),1,0) | V106: =IF(AND($O106=1,$P106=0),1,0)
A107: 3 | B107: SAC-001 | C107: vascular | D107: vascular | E107: expedite receipt | F107: A | G107: 16.2 | H107: 1200 | I107: BUYER_FTE | J107: 0.5 | K107: OV-1 | L107: 0 | M107: MX-1 | N107: DG-1 | O107: 1 | P107: =INDEX(Action_Catalog!$S$4:$S$27,MATCH($B107,Action_Catalog!$A$4:$A$27,0)) | Q107: =$O107*$J107*IF(COUNTIFS($K$105:$K107,$K107,$O$105:$O107,1)>1,1-$L107,1) | R107: =SUMIFS($S$104:$S106,$D$104:$D106,$D107) | S107: =$O107*MIN($G107,MAX(0,INDEX($B$6:$D$10,MATCH($D107,$A$6:$A$10,0),3)-$R107)) | T107: 1 | U107: =IF(AND($M107<>"",$O107=1,COUNTIFS($M$105:$M$128,$M107,$O$105:$O$128,1)>1),1,0) | V107: =IF(AND($O107=1,$P107=0),1,0)
A108: 4 | B108: SAC-022 | C108: diagnostic | D108: diagnostic | E108: site transfer | F108: A | G108: 24.3 | H108: 4500 | I108: COLD_CHAIN_PALLET | J108: 1 | K108: OV-2 | L108: 0.2 | N108: DG-4 | O108: 1 | P108: =INDEX(Action_Catalog!$S$4:$S$27,MATCH($B108,Action_Catalog!$A$4:$A$27,0)) | Q108: =$O108*$J108*IF(COUNTIFS($K$105:$K108,$K108,$O$105:$O108,1)>1,1-$L108,1) | R108: =SUMIFS($S$104:$S107,$D$104:$D107,$D108) | S108: =$O108*MIN($G108,MAX(0,INDEX($B$6:$D$10,MATCH($D108,$A$6:$A$10,0),3)-$R108)) | T108: 3 | U108: =IF(AND($M108<>"",$O108=1,COUNTIFS($M$105:$M$128,$M108,$O$105:$O$128,1)>1),1,0) | V108: =IF(AND($O108=1,$P108=0),1,0)
A109: 5 | B109: SAC-019 | C109: vascular | D109: vascular | E109: supplier substitution | F109: A | G109: 43.2 | H109: 9000 | I109: CLINICAL_REVIEW | J109: 1.5 | K109: OV-4 | L109: 0.35 | N109: DG-1 | O109: 1 | P109: =INDEX(Action_Catalog!$S$4:$S$27,MATCH($B109,Action_Catalog!$A$4:$A$27,0)) | Q109: =$O109*$J109*IF(COUNTIFS($K$105:$K109,$K109,$O$105:$O109,1)>1,1-$L109,1) | R109: =SUMIFS($S$104:$S108,$D$104:$D108,$D109) | S109: =$O109*MIN($G109,MAX(0,INDEX($B$6:$D$10,MATCH($D109,$A$6:$A$10,0),3)-$R109)) | T109: 7 | U109: =IF(AND($M109<>"",$O109=1,COUNTIFS($M$105:$M$128,$M109,$O$105:$O$128,1)>1),1,0) | V109: =IF(AND($O109=1,$P109=0),1,0)
A110: 6 | B110: SAC-007 | C110: vascular | D110: vascular | E110: supplier substitution | F110: A | G110: 24.3 | H110: 9000 | I110: COLD_CHAIN_PALLET | J110: 1.5 | K110: OV-2 | L110: 0.35 | N110: DG-1 | O110: 1 | P110: =INDEX(Action_Catalog!$S$4:$S$27,MATCH($B110,Action_Catalog!$A$4:$A$27,0)) | Q110: =$O110*$J110*IF(COUNTIFS($K$105:$K110,$K110,$O$105:$O110,1)>1,1-$L110,1) | R110: =SUMIFS($S$104:$S109,$D$104:$D109,$D110) | S110: =$O110*MIN($G110,MAX(0,INDEX($B$6:$D$10,MATCH($D110,$A$6:$A$10,0),3)-$R110)) | T110: 7 | U110: =IF(AND($M110<>"",$O110=1,COUNTIFS($M$105:$M$128,$M110,$O$105:$O$128,1)>1),1,0) | V110: =IF(AND($O110=1,$P110=0),1,0)
A111: 7 | B111: SAC-004 | C111: diagnostic | D111: diagnostic | E111: allocation hold | F111: A | G111: 43.2 | H111: 18000 | I111: CLINICAL_REVIEW | J111: 2 | K111: OV-4 | L111: 0.5 | N111: DG-4 | O111: 1 | P111: =INDEX(Action_Catalog!$S$4:$S$27,MATCH($B111,Action_Catalog!$A$4:$A$27,0)) | Q111: =$O111*$J111*IF(COUNTIFS($K$105:$K111,$K111,$O$105:$O111,1)>1,1-$L111,1) | R111: =SUMIFS($S$104:$S110,$D$104:$D110,$D111) | S111: =$O111*MIN($G111,MAX(0,INDEX($B$6:$D$10,MATCH($D111,$A$6:$A$10,0),3)-$R111)) | T111: 14 | U111: =IF(AND($M111<>"",$O111=1,COUNTIFS($M$105:$M$128,$M111,$O$105:$O$128,1)>1),1,0) | V111: =IF(AND($O111=1,$P111=0),1,0)
A112: 8 | B112: SAC-016 | C112: diagnostic | D112: diagnostic | E112: allocation hold | F112: A | G112: 16.2 | H112: 18000 | I112: BUYER_FTE | J112: 2 | K112: OV-1 | L112: 0.5 | M112: MX-4 | N112: DG-4 | O112: 1 | P112: =INDEX(Action_Catalog!$S$4:$S$27,MATCH($B112,Action_Catalog!$A$4:$A$27,0)) | Q112: =$O112*$J112*IF(COUNTIFS($K$105:$K112,$K112,$O$105:$O112,1)>1,1-$L112,1) | R112: =SUMIFS($S$104:$S111,$D$104:$D111,$D112) | S112: =$O112*MIN($G112,MAX(0,INDEX($B$6:$D$10,MATCH($D112,$A$6:$A$10,0),3)-$R112)) | T112: 14 | U112: =IF(AND($M112<>"",$O112=1,COUNTIFS($M$105:$M$128,$M112,$O$105:$O$128,1)>1),1,0) | V112: =IF(AND($O112=1,$P112=0),1,0)
A113: 9 | B113: SAC-005 | C113: wound | D113: wound | E113: expedite receipt | F113: B | G113: 60.8 | H113: 1200 | I113: TRANSFER_VEHICLE | J113: 0.5 | K113: OV-5 | L113: 0 | N113: DG-5 | O113: 1 | P113: =INDEX(Action_Catalog!$S$4:$S$27,MATCH($B113,Action_Catalog!$A$4:$A$27,0)) | Q113: =$O113*$J113*IF(COUNTIFS($K$105:$K113,$K113,$O$105:$O113,1)>1,1-$L113,1) | R113: =SUMIFS($S$104:$S112,$D$104:$D112,$D113) | S113: =$O113*MIN($G113,MAX(0,INDEX($B$6:$D$10,MATCH($D113,$A$6:$A$10,0),3)-$R113)) | T113: 1 | U113: =IF(AND($M113<>"",$O113=1,COUNTIFS($M$105:$M$128,$M113,$O$105:$O$128,1)>1),1,0) | V113: =IF(AND($O113=1,$P113=0),1,0)
A114: 10 | B114: SAC-017 | C114: wound | D114: wound | E114: expedite receipt | F114: B | G114: 24.3 | H114: 1200 | I114: COLD_CHAIN_PALLET | J114: 0.5 | K114: OV-2 | L114: 0 | N114: DG-5 | O114: 1 | P114: =INDEX(Action_Catalog!$S$4:$S$27,MATCH($B114,Action_Catalog!$A$4:$A$27,0)) | Q114: =$O114*$J114*IF(COUNTIFS($K$105:$K114,$K114,$O$105:$O114,1)>1,1-$L114,1) | R114: =SUMIFS($S$104:$S113,$D$104:$D113,$D114) | S114: =$O114*MIN($G114,MAX(0,INDEX($B$6:$D$10,MATCH($D114,$A$6:$A$10,0),3)-$R114)) | T114: 1 | U114: =IF(AND($M114<>"",$O114=1,COUNTIFS($M$105:$M$128,$M114,$O$105:$O$128,1)>1),1,0) | V114: =IF(AND($O114=1,$P114=0),1,0)
A115: 11 | B115: SAC-014 | C115: respiratory | D115: respiratory | E115: site transfer | F115: B | G115: 43.2 | H115: 4500 | I115: CLINICAL_REVIEW | J115: 1 | K115: OV-4 | L115: 0.2 | N115: DG-2 | O115: 1 | P115: =INDEX(Action_Catalog!$S$4:$S$27,MATCH($B115,Action_Catalog!$A$4:$A$27,0)) | Q115: =$O115*$J115*IF(COUNTIFS($K$105:$K115,$K115,$O$105:$O115,1)>1,1-$L115,1) | R115: =SUMIFS($S$104:$S114,$D$104:$D114,$D115) | S115: =$O115*MIN($G115,MAX(0,INDEX($B$6:$D$10,MATCH($D115,$A$6:$A$10,0),3)-$R115)) | T115: 3 | U115: =IF(AND($M115<>"",$O115=1,COUNTIFS($M$105:$M$128,$M115,$O$105:$O$128,1)>1),1,0) | V115: =IF(AND($O115=1,$P115=0),1,0)
A116: 12 | B116: SAC-002 | C116: respiratory | D116: respiratory | E116: site transfer | F116: B | G116: 24.3 | H116: 4500 | I116: COLD_CHAIN_PALLET | J116: 1 | K116: OV-2 | L116: 0.2 | N116: DG-2 | O116: 1 | P116: =INDEX(Action_Catalog!$S$4:$S$27,MATCH($B116,Action_Catalog!$A$4:$A$27,0)) | Q116: =$O116*$J116*IF(COUNTIFS($K$105:$K116,$K116,$O$105:$O116,1)>1,1-$L116,1) | R116: =SUMIFS($S$104:$S115,$D$104:$D115,$D116) | S116: =$O116*MIN($G116,MAX(0,INDEX($B$6:$D$10,MATCH($D116,$A$6:$A$10,0),3)-$R116)) | T116: 3 | U116: =IF(AND($M116<>"",$O116=1,COUNTIFS($M$105:$M$128,$M116,$O$105:$O$128,1)>1),1,0) | V116: =IF(AND($O116=1,$P116=0),1,0)
A117: 13 | B117: SAC-023 | C117: wound | D117: wound | E117: supplier substitution | F117: B | G117: 32.4 | H117: 9000 | I117: RECEIVING_SLOT | J117: 1.5 | K117: OV-3 | L117: 0.35 | N117: DG-5 | O117: 1 | P117: =INDEX(Action_Catalog!$S$4:$S$27,MATCH($B117,Action_Catalog!$A$4:$A$27,0)) | Q117: =$O117*$J117*IF(COUNTIFS($K$105:$K117,$K117,$O$105:$O117,1)>1,1-$L117,1) | R117: =SUMIFS($S$104:$S116,$D$104:$D116,$D117) | S117: =$O117*MIN($G117,MAX(0,INDEX($B$6:$D$10,MATCH($D117,$A$6:$A$10,0),3)-$R117)) | T117: 7 | U117: =IF(AND($M117<>"",$O117=1,COUNTIFS($M$105:$M$128,$M117,$O$105:$O$128,1)>1),1,0) | V117: =IF(AND($O117=1,$P117=0),1,0)
A118: 14 | B118: SAC-020 | C118: respiratory | D118: respiratory | E118: allocation hold | F118: B | G118: 60.8 | H118: 18000 | I118: TRANSFER_VEHICLE | J118: 2 | K118: OV-5 | L118: 0.5 | N118: DG-2 | O118: 1 | P118: =INDEX(Action_Catalog!$S$4:$S$27,MATCH($B118,Action_Catalog!$A$4:$A$27,0)) | Q118: =$O118*$J118*IF(COUNTIFS($K$105:$K118,$K118,$O$105:$O118,1)>1,1-$L118,1) | R118: =SUMIFS($S$104:$S117,$D$104:$D117,$D118) | S118: =$O118*MIN($G118,MAX(0,INDEX($B$6:$D$10,MATCH($D118,$A$6:$A$10,0),3)-$R118)) | T118: 14 | U118: =IF(AND($M118<>"",$O118=1,COUNTIFS($M$105:$M$128,$M118,$O$105:$O$128,1)>1),1,0) | V118: =IF(AND($O118=1,$P118=0),1,0)
A119: 15 | B119: SAC-008 | C119: respiratory | D119: respiratory | E119: allocation hold | F119: B | G119: 32.4 | H119: 18000 | I119: RECEIVING_SLOT | J119: 2 | K119: OV-3 | L119: 0.5 | N119: DG-2 | O119: 1 | P119: =INDEX(Action_Catalog!$S$4:$S$27,MATCH($B119,Action_Catalog!$A$4:$A$27,0)) | Q119: =$O119*$J119*IF(COUNTIFS($K$105:$K119,$K119,$O$105:$O119,1)>1,1-$L119,1) | R119: =SUMIFS($S$104:$S118,$D$104:$D118,$D119) | S119: =$O119*MIN($G119,MAX(0,INDEX($B$6:$D$10,MATCH($D119,$A$6:$A$10,0),3)-$R119)) | T119: 14 | U119: =IF(AND($M119<>"",$O119=1,COUNTIFS($M$105:$M$128,$M119,$O$105:$O$128,1)>1),1,0) | V119: =IF(AND($O119=1,$P119=0),1,0)
A120: 16 | B120: SAC-011 | C120: wound | D120: wound | E120: supplier substitution | F120: B | G120: 16.2 | H120: 9000 | I120: BUYER_FTE | J120: 1.5 | K120: OV-1 | L120: 0.35 | M120: MX-3 | N120: DG-5 | O120: 1 | P120: =INDEX(Action_Catalog!$S$4:$S$27,MATCH($B120,Action_Catalog!$A$4:$A$27,0)) | Q120: =$O120*$J120*IF(COUNTIFS($K$105:$K120,$K120,$O$105:$O120,1)>1,1-$L120,1) | R120: =SUMIFS($S$104:$S119,$D$104:$D119,$D120) | S120: =$O120*MIN($G120,MAX(0,INDEX($B$6:$D$10,MATCH($D120,$A$6:$A$10,0),3)-$R120)) | T120: 7 | U120: =IF(AND($M120<>"",$O120=1,COUNTIFS($M$105:$M$128,$M120,$O$105:$O$128,1)>1),1,0) | V120: =IF(AND($O120=1,$P120=0),1,0)
A121: 17 | B121: SAC-009 | C121: surgical | D121: surgical | E121: expedite receipt | F121: C | G121: 43.2 | H121: 1200 | I121: CLINICAL_REVIEW | J121: 0.5 | K121: OV-4 | L121: 0 | N121: DG-3 | O121: 1 | P121: =INDEX(Action_Catalog!$S$4:$S$27,MATCH($B121,Action_Catalog!$A$4:$A$27,0)) | Q121: =$O121*$J121*IF(COUNTIFS($K$105:$K121,$K121,$O$105:$O121,1)>1,1-$L121,1) | R121: =SUMIFS($S$104:$S120,$D$104:$D120,$D121) | S121: =$O121*MIN($G121,MAX(0,INDEX($B$6:$D$10,MATCH($D121,$A$6:$A$10,0),3)-$R121)) | T121: 1 | U121: =IF(AND($M121<>"",$O121=1,COUNTIFS($M$105:$M$128,$M121,$O$105:$O$128,1)>1),1,0) | V121: =IF(AND($O121=1,$P121=0),1,0)
A122: 18 | B122: SAC-021 | C122: surgical | D122: surgical | E122: expedite receipt | F122: C | G122: 16.2 | H122: 1200 | I122: BUYER_FTE | J122: 0.5 | K122: OV-1 | L122: 0 | M122: MX-1 | N122: DG-3 | O122: 0 | P122: =INDEX(Action_Catalog!$S$4:$S$27,MATCH($B122,Action_Catalog!$A$4:$A$27,0)) | Q122: =$O122*$J122*IF(COUNTIFS($K$105:$K122,$K122,$O$105:$O122,1)>1,1-$L122,1) | R122: =SUMIFS($S$104:$S121,$D$104:$D121,$D122) | S122: =$O122*MIN($G122,MAX(0,INDEX($B$6:$D$10,MATCH($D122,$A$6:$A$10,0),3)-$R122)) | T122: 1 | U122: =IF(AND($M122<>"",$O122=1,COUNTIFS($M$105:$M$128,$M122,$O$105:$O$128,1)>1),1,0) | V122: =IF(AND($O122=1,$P122=0),1,0)
A123: 19 | B123: SAC-018 | C123: all critical | D123: vascular | E123: site transfer | F123: C | G123: 32.4 | H123: 4500 | I123: RECEIVING_SLOT | J123: 1 | K123: OV-3 | L123: 0.2 | N123: DG-6 | O123: 1 | P123: =INDEX(Action_Catalog!$S$4:$S$27,MATCH($B123,Action_Catalog!$A$4:$A$27,0)) | Q123: =$O123*$J123*IF(COUNTIFS($K$105:$K123,$K123,$O$105:$O123,1)>1,1-$L123,1) | R123: =SUMIFS($S$104:$S122,$D$104:$D122,$D123) | S123: =$O123*MIN($G123,MAX(0,INDEX($B$6:$D$10,MATCH($D123,$A$6:$A$10,0),3)-$R123)) | T123: 3 | U123: =IF(AND($M123<>"",$O123=1,COUNTIFS($M$105:$M$128,$M123,$O$105:$O$128,1)>1),1,0) | V123: =IF(AND($O123=1,$P123=0),1,0)
A124: 20 | B124: SAC-015 | C124: surgical | D124: surgical | E124: supplier substitution | F124: C | G124: 60.8 | H124: 9000 | I124: TRANSFER_VEHICLE | J124: 1.5 | K124: OV-5 | L124: 0.35 | N124: DG-3 | O124: 1 | P124: =INDEX(Action_Catalog!$S$4:$S$27,MATCH($B124,Action_Catalog!$A$4:$A$27,0)) | Q124: =$O124*$J124*IF(COUNTIFS($K$105:$K124,$K124,$O$105:$O124,1)>1,1-$L124,1) | R124: =SUMIFS($S$104:$S123,$D$104:$D123,$D124) | S124: =$O124*MIN($G124,MAX(0,INDEX($B$6:$D$10,MATCH($D124,$A$6:$A$10,0),3)-$R124)) | T124: 7 | U124: =IF(AND($M124<>"",$O124=1,COUNTIFS($M$105:$M$128,$M124,$O$105:$O$128,1)>1),1,0) | V124: =IF(AND($O124=1,$P124=0),1,0)
A125: 21 | B125: SAC-003 | C125: surgical | D125: surgical | E125: supplier substitution | F125: C | G125: 32.4 | H125: 9000 | I125: RECEIVING_SLOT | J125: 1.5 | K125: OV-3 | L125: 0.35 | N125: DG-3 | O125: 1 | P125: =INDEX(Action_Catalog!$S$4:$S$27,MATCH($B125,Action_Catalog!$A$4:$A$27,0)) | Q125: =$O125*$J125*IF(COUNTIFS($K$105:$K125,$K125,$O$105:$O125,1)>1,1-$L125,1) | R125: =SUMIFS($S$104:$S124,$D$104:$D124,$D125) | S125: =$O125*MIN($G125,MAX(0,INDEX($B$6:$D$10,MATCH($D125,$A$6:$A$10,0),3)-$R125)) | T125: 7 | U125: =IF(AND($M125<>"",$O125=1,COUNTIFS($M$105:$M$128,$M125,$O$105:$O$128,1)>1),1,0) | V125: =IF(AND($O125=1,$P125=0),1,0)
A126: 22 | B126: SAC-006 | C126: all critical | D126: vascular | E126: site transfer | F126: C | G126: 16.2 | H126: 4500 | I126: BUYER_FTE | J126: 1 | K126: OV-1 | L126: 0.2 | M126: MX-2 | N126: DG-6 | O126: 1 | P126: =INDEX(Action_Catalog!$S$4:$S$27,MATCH($B126,Action_Catalog!$A$4:$A$27,0)) | Q126: =$O126*$J126*IF(COUNTIFS($K$105:$K126,$K126,$O$105:$O126,1)>1,1-$L126,1) | R126: =SUMIFS($S$104:$S125,$D$104:$D125,$D126) | S126: =$O126*MIN($G126,MAX(0,INDEX($B$6:$D$10,MATCH($D126,$A$6:$A$10,0),3)-$R126)) | T126: 3 | U126: =IF(AND($M126<>"",$O126=1,COUNTIFS($M$105:$M$128,$M126,$O$105:$O$128,1)>1),1,0) | V126: =IF(AND($O126=1,$P126=0),1,0)
A127: 23 | B127: SAC-024 | C127: all critical | D127: vascular | E127: allocation hold | F127: C | G127: 43.2 | H127: 18000 | I127: CLINICAL_REVIEW | J127: 2 | K127: OV-4 | L127: 0.5 | N127: DG-6 | O127: 0 | P127: =INDEX(Action_Catalog!$S$4:$S$27,MATCH($B127,Action_Catalog!$A$4:$A$27,0)) | Q127: =$O127*$J127*IF(COUNTIFS($K$105:$K127,$K127,$O$105:$O127,1)>1,1-$L127,1) | R127: =SUMIFS($S$104:$S126,$D$104:$D126,$D127) | S127: =$O127*MIN($G127,MAX(0,INDEX($B$6:$D$10,MATCH($D127,$A$6:$A$10,0),3)-$R127)) | T127: 14 | U127: =IF(AND($M127<>"",$O127=1,COUNTIFS($M$105:$M$128,$M127,$O$105:$O$128,1)>1),1,0) | V127: =IF(AND($O127=1,$P127=0),1,0)
A128: 24 | B128: SAC-012 | C128: all critical | D128: vascular | E128: allocation hold | F128: C | G128: 24.3 | H128: 18000 | I128: COLD_CHAIN_PALLET | J128: 2 | K128: OV-2 | L128: 0.5 | N128: DG-6 | O128: 1 | P128: =INDEX(Action_Catalog!$S$4:$S$27,MATCH($B128,Action_Catalog!$A$4:$A$27,0)) | Q128: =$O128*$J128*IF(COUNTIFS($K$105:$K128,$K128,$O$105:$O128,1)>1,1-$L128,1) | R128: =SUMIFS($S$104:$S127,$D$104:$D127,$D128) | S128: =$O128*MIN($G128,MAX(0,INDEX($B$6:$D$10,MATCH($D128,$A$6:$A$10,0),3)-$R128)) | T128: 14 | U128: =IF(AND($M128<>"",$O128=1,COUNTIFS($M$105:$M$128,$M128,$O$105:$O$128,1)>1),1,0) | V128: =IF(AND($O128=1,$P128=0),1,0)
A130: UPSIDE summary
A131: metric | B131: value | C131: check
...

Sheet Dashboard
A1: Dashboard — figures that reconcile with sterile_supply_resilience_portal.html
A2: Every value below is a live formula. Portal shows the same figures from the same sources.
A4: Network exposure KPIs
A5: metric | B5: value | C5: source / formula basis
A6: SKUs / lots tracked | B6: =COUNTA(Lots_Data!$A$2:$A$234) | C6: lot snapshot rows
A7: On-hand units | B7: =SUM(Lots_Data!$H$2:$H$234) | C7: lot snapshot on_hand_qty
A8: Usable units (excl. recalled & quarantine) | B8: =SUM(Lots_Data!$K$2:$K$234) | C8: Lots_Data col K formula
A9: Base network monthly demand (units) | B9: =SUM(Usage_Summary!$C$4:$C$236) | C9: usage window avg
A10: Average network days of cover | B10: =B8/(B9/30) | C10: usable / (demand/30)
A11: Stockout SKUs (usable = 0, demand > 0) | B11: =SUM(SKU_Exposure!$K$4:$K$236) | C11: SKU_Exposure col K
A12: SKUs with static reorder point < lead-time demand | B12: =COUNTIF(SKU_Exposure!$N$4:$N$236,"under-set") | C12: SKU_Exposure col N
A13: Recalled lots | B13: =COUNTIF(Lots_Data!$J$2:$J$234,"recalled") | C13: lot snapshot recall_state
A14: Recalled units on hand | B14: =SUMIF(Lots_Data!$J$2:$J$234,"recalled",Lots_Data!$H$2:$H$234) | C14: gross on-hand in recalled lots
A15: Recall value at risk (USD) | B15: =SUMIFS(Lots_Data!$M$2:$M$234,Lots_Data!$J$2:$J$234,"recalled") | C15: units x unit_cost
A16: Quarantine units | B16: =SUM(Lots_Data!$I$2:$I$234) | C16: lot snapshot quarantine_qty
A17: Lots with quarantine > 0 | B17: =COUNTIF(Lots_Data!$I$2:$I$234,">0")
A18: Near-expiry lots (<=180 days) | B18: =COUNTIFS(Lots_Data!$Q$2:$Q$234,"<=180") | C18: vs snapshot date Inputs!B4
A19: Near-expiry units (<=180 days) | B19: =SUMIFS(Lots_Data!$H$2:$H$234,Lots_Data!$Q$2:$Q$234,"<=180") | C19: no lot is <=90 days out
A20: Near-expiry value (<=180 days, USD) | B20: =SUMIFS(Lots_Data!$M$2:$M$234,Lots_Data!$Q$2:$Q$234,"<=180")
A22: Days-of-cover distribution (SKUs)
A23: bucket | B23: skus | C23: criteria
A24: 0 (stockout) | B24: =COUNTIFS(SKU_Exposure!$G$4:$G$236,0) | C24: days_of_cover = 0
A25: 0-7 days | B25: =COUNTIFS(SKU_Exposure!$G$4:$G$236,">0",SKU_Exposure!$G$4:$G$236,"<=7")
A26: 7-14 days | B26: =COUNTIFS(SKU_Exposure!$G$4:$G$236,">7",SKU_Exposure!$G$4:$G$236,"<=14")
A27: 14-30 days | B27: =COUNTIFS(SKU_Exposure!$G$4:$G$236,">14",SKU_Exposure!$G$4:$G$236,"<=30")
A28: >30 days | B28: =COUNTIFS(SKU_Exposure!$G$4:$G$236,">30")
A29: no recorded demand | B29: =COUNTIFS(SKU_Exposure!$F$4:$F$236,0) | C29: base usage = 0
A31: Clinical access floors (site_storage_clinical_constraints.csv)
A32: site | B32: clinical floor | C32: family | D32: usable_units | E32: minimum_floor | F32: status
A33: HOSP-1 | B33: vascular kits | C33: vascular | D33: =SUMIFS(Lots_Data!$K$2:$K$234,Lots_Data!$E$2:$E$234,$A33,Lots_Data!$C$2:$C$234,$C33) | E33: 80 | F33: =IF(D33<E33,"BREACH","ok")
A34: HOSP-2 | B34: airway kits | C34: respiratory | D34: =SUMIFS(Lots_Data!$K$2:$K$234,Lots_Data!$E$2:$E$234,$A34,Lots_Data!$C$2:$C$234,$C34) | E34: 65 | F34: =IF(D34<E34,"BREACH","ok")
A35: HOSP-3 | B35: surgical packs | C35: surgical | D35: =SUMIFS(Lots_Data!$K$2:$K$234,Lots_Data!$E$2:$E$234,$A35,Lots_Data!$C$2:$C$234,$C35) | E35: 120 | F35: =IF(D35<E35,"BREACH","ok")
A36: HOSP-4 | B36: wound supplies | C36: wound | D36: =SUMIFS(Lots_Data!$K$2:$K$234,Lots_Data!$E$2:$E$234,$A36,Lots_Data!$C$2:$C$234,$C36) | E36: 95 | F36: =IF(D36<E36,"BREACH","ok")
A38: Scenario decision summary (from Scenario_Decision blocks)
A39: scenario | B39: gap_units | C39: actions | D39: coverage_units | E39: residual_units | F39: fixed_cost_usd | G39: feasible
A40: adverse | B40: =Scenario_Decision!$B$44 | C40: =Scenario_Decision!$B$42 | D40: =Scenario_Decision!$B$45 | E40: =Scenario_Decision!$B$46 | F40: =Scenario_Decision!$B$43 | G40: =IF(AND(Scenario_Decision!$B$47=0,Scenario_Decision!$B$48=0,Scenario_Decision!$B$57=5),"FEASIBLE","CHECK")
A41: base | B41: =Scenario_Decision!$B$89 | C41: =Scenario_Decision!$B$87 | D41: =Scenario_Decision!$B$90 | E41: =Scenario_Decision!$B$91 | F41: =Scenario_Decision!$B$88 | G41: =IF(AND(Scenario_Decision!$B$92=0,Scenario_Decision!$B$93=0,Scenario_Decision!$B$102=5),"FEASIBLE","CHECK")
A42: upside | B42: =Scenario_Decision!$B$134 | C42: =Scenario_Decision!$B$132 | D42: =Scenario_Decision!$B$135 | E42: =Scenario_Decision!$B$136 | F42: =Scenario_Decision!$B$133 | G42: =IF(AND(Scenario_Decision!$B$137=0,Scenario_Decision!$B$138=0,Scenario_Decision!$B$147=5),"FEASIBLE","CHECK")
A44: Exception evidence (Exceptions sheet)
A45: class | B45: records | C45: quantity
A46: documented (invoice/statement) | B46: =COUNTIF(Exceptions!$I$4:$I$51,"documented") | C46: =SUM(Exceptions!$J$4:$J$51)
A47: unverified (assertion-only/missing-support) | B47: =COUNTIF(Exceptions!$I$4:$I$51,"unverified") | C47: =SUMIFS(Exceptions!$F$4:$F$51,Exceptions!$I$4:$I$51,"unverified")
A49: Surge / scenario evidence
A50: metric | B50: value | C50: note
A51: usage rows in window | B51: =SUM(Usage_Data!$G$2:$G$5001)
A52: surge-flagged rows in window | B52: =COUNTIFS(Usage_Data!$F$2:$F$5001,"surge",Usage_Data!$G$2:$G$5001,1)
A53: adverse demand multiplier | B53: =Inputs!$B$10 | C53: observed surge ratio; see Inputs note & U-03
A55: Supplier summary (from Supplier_Scorecard)
A56: supplier | B56: OTD | C56: avg_lead_days | D56: not_closed_events | E56: composite | F56: renewal_stance
A57: =Supplier_Scorecard!$B$4 | B57: =Supplier_Scorecard!$G$4 | C57: =Supplier_Scorecard!$J$4 | D57: =Supplier_Scorecard!$O$4 | E57: =Supplier_Scorecard!$U$4 | F57: =Supplier_Scorecard!$AB$4
A58: =Supplier_Scorecard!$B$5 | B58: =Supplier_Scorecard!$G$5 | C58: =Supplier_Scorecard!$J$5 | D58: =Supplier_Scorecard!$O$5 | E58: =Supplier_Scorecard!$U$5 | F58: =Supplier_Scorecard!$AB$5
A59: =Supplier_Scorecard!$B$6 | B59: =Supplier_Scorecard!$G$6 | C59: =Supplier_Scorecard!$J$6 | D59: =Supplier_Scorecard!$O$6 | E59: =Supplier_Scorecard!$U$6 | F59: =Supplier_Scorecard!$AB$6
A60: =Supplier_Scorecard!$B$7 | B60: =Supplier_Scorecard!$G$7 | C60: =Supplier_Scorecard!$J$7 | D60: =Supplier_Scorecard!$O$7 | E60: =Supplier_Scorecard!$U$7 | F60: =Supplier_Scorecard!$AB$7
A61: =Supplier_Scorecard!$B$8 | B61: =Supplier_Scorecard!$G$8 | C61: =Supplier_Scorecard!$J$8 | D61: =Supplier_Scorecard!$O$8 | E61: =Supplier_Scorecard!$U$8 | F61: =Supplier_Scorecard!$AB$8

Sheet Uncertainty_Register
A1: Assumptions, unresolved boundaries and evidence handling
A2: Supplied estimates/annotations are evidence claims, not approved conclusions. No missing measurements, authority, contract terms, prices or implementation evidence are fabricated.
A3: id | B3: topic | C3: claim / assumption / boundary | D3: type | E3: source locator | F3: handling
A4: U-01 | B4: Analysis date | C4: Snapshot 2026-08-25 used for expiry horizons and horizon labels. | D4: assumption | E4: task context date | F4: Editable in Inputs!B4.
A5: U-02 | B5: Demand window | C5: Base demand = 2026-01..2026-08 (8 complete months). 2025 periods are sparse (4 non-consecutive); 2026-09..11 rows are future-dated relative to the snapshot and treated as forward-looking, not history. | D5: assumption | E5: sterile_daily_monthly_usage.csv periods | F5: Window editable in Inputs!B5:B6; summary recalculates.
A6: U-03 | B6: Adverse multiplier | C6: Adverse multiplier 1.315 = mean of per-SKU ratios of surge-flagged to non-surge usage; only 16 flagged rows in window. | D6: evidence claim (small sample) | E6: sterile_daily_monthly_usage.csv exception_flag="surge" | F6: Editable in Inputs!B10; flagged as low-confidence.
A7: U-04 | B7: Upside multiplier | C7: Upside demand relief of 0.90 is a planning judgment with no direct source evidence. | D7: assumption | E7: (none — no source basis) | F7: Editable in Inputs!B12.
A8: U-05 | B8: Target cover | C8: Target 30 days of cover used for gap sizing; SOP states a weekly review cycle but no service-level target. | D8: assumption | E8: SOP-WH-2024-003 §2 | F8: Editable in Inputs!B7.
A9: U-06 | B9: Network pooling | C9: Each SKU has usage at multiple sites but stock held at one site; demand aggregated network-wide per SKU. 1,578 transfer units in the usage file support network pooling. | D9: assumption | E9: usage file site_id spread; transfer_qty sum | F9: State explicitly; site-level allocation unresolved.
A10: U-07 | B10: Pool capacity | C10: Scenario pool capacity = sum over sites of (scenario units - reserved emergency units), floored at 0. Only 4 of 12 constraint rows are evidence_status "approved" (SSC-001, -004, -007, -010); the rest are "planning range" or "conditional". | D10: assumption + evidence grading | E10: site_storage_clinical_constraints.csv SSC-001..012 | F10: Non-approved count shown per pool in Site_Constraints col K.
A11: U-08 | B11: Overlap discount | C11: shared_execution_fraction read as: when 2+ actions in the same overlap_group are selected, each action beyond the first consumes capacity_units x (1 - fraction). Semantic is not defined in the source. | D11: assumption | E11: supply_action_constraints.csv overlap_group, shared_execution_fraction | F11: Formula in Scenario_Decision col Q; interpretation documented.
A12: U-09 | B12: Mutual exclusion | C12: Actions sharing a mutual_exclusion_group: at most one may be selected (MX-1..MX-4). | D12: assumption | E12: supply_action_constraints.csv mutual_exclusion_group | F12: Live violation check in Scenario_Decision col U.
A13: U-10 | B13: Dependency groups | C13: dependency_group maps 1:1 to clinical family (DG-1..DG-5) or "all critical" (DG-6); treated as a family execution cohort. Program start delay = max start_delay of selected actions. Sequence semantics undefined in source. | D13: assumption | E13: supply_action_constraints.csv dependency_group | F13: Reported in scenario summary.
A14: U-11 | B14: Greedy selection rule | C14: Candidates (scenario-eligible) sorted by (record grade A>B>C, then provided_units/fixed_cost desc, then action_id); select if target family gap > 0, MX group unused, pool capacity (with overlap rule) sufficient. Coverage assigned to largest-gap family for "all critical" actions. | D14: assumption | E14: supply_action_constraints.csv supporting_record_grade | F14: Selected flags editable; all checks live.
... A21: U-18 | B21: Outcome attribution | C21: Coverage from actions is modeled as full provided_units applied to the family gap; no fill-rate or realization adjustment exists in the sources. | D21: assumption | E21: supply_action_constraints.csv | F21: Residual gap reported honestly per scenario.
