Workbook

Sheet Input
A2: Leveraged Buyout (LBO) Model
L3: http://www.globaliconnect.com/excel_models.php
A4: Input Values | I4: To help us improve this model, please send your feedback to info@globaliconnect.com
A5: *Enter values in yellow cells.
A7: Estimated Cost of Deal: | G7: Debt Assumptions: | L7: Income/BS Assumptions:
A8: Curent Stock Price | C8: 6 | D8: $ amt | G8: =A26 -> Assumed Debt | L8: Income Statement:
A9: Offer Premium | C9: 0.1 | D9: % | G9: Maturity Year | I9: 9 | J9: select no. | L9: Sales Year 1 | N9: 1100000 | O9: $ amt
A10: Offer Price Per Share | C10: =C8*(1+C9) -> 6.6 | D10: $ amt | G10: Annual Repayment | I10: =1/assumed_debt_maturity_year -> 0.11111111 | J10: % of FV | L10: Sales - Annual Increase | N10: 0.1 | O10: %
A11: No. of Shares outstanding | C11: 100000 | D11: nos. | G11: Coupon Rate | I11: 0.0425 | J11: % annual | L11: Cost of goods sold | N11: 0.45 | O11: % of revenue
A12: Equity Purchase Price | C12: =C10*C11 -> 660000 | D12: $ amt | G12: Average Interest | I12: 1 | J12: 1=Yes 0=No | L12: =L11&" - Annual Increase" -> Cost of goods sold - Annual Increase | N12: 0.0025 | O12: %
G13: Optional Prepayment | I13: 1 | J13: 1=Yes 0=No | L13: SG&A expenses | N13: 0.14 | O13: % of revenue
A14: Existing Debt Retired | C14: =Bal_Sheet!C46-C15 -> 185000 | D14: $ amt | L14: =L13&" - Annual Increase" -> SG&A expenses - Annual Increase | N14: 0.005 | O14: %
A15: Assumed Debt | C15: 65000 | D15: $ amt | G15: =A27 -> Bank Revolver | L15: Other expenses | N15: 0.12 | O15: % of revenue
A16: Expensed Transaction Costs | C16: 2500 | D16: $ amt | G16: Coupon Rate | I16: 0.0475 | J16: % annual | L16: =L15&" - Annual Increase" -> Other expenses - Annual Increase | N16: 0.0015 | O16: %
A17: Capitalized Financing Costs | C17: =E27*revolver_limit+SUMPRODUCT(C28:C33,E28:E33) -> 10887.5 | D17: $ amt | G17: Revolver limit | I17: 600000 | J17: $ amt
A18: Cash Infusion | C18: 27500 | D18: $ amt | G18: Undrawn Commitment Fee | I18: 0.01 | J18: % annual | L18: Balance Sheet:
L19: Accounts receivable | N19: 0.18 | O19: % of revenue
A20: Total Funds Requirement | C20: =SUM(C12,C14:C18) -> 950887.5 | D20: $ amt | G20: =A28 -> Term Loan "A" | L20: =L19&" - Annual Increase" -> Accounts receivable - Annual Increase | N20: 0.05 | O20: %
G21: Term Years | I21: 8 | J21: select no. | L21: Inventories | N21: 0.2 | O21: % of COGS
G22: Annual Repayment | I22: =1/I21 -> 0.125 | J22: % of FV | L22: =L21&" - Annual Increase" -> Inventories - Annual Increase | N22: 0.04 | O22: %
A23: Sources of Funds: | G23: Coupon Rate | I23: 0.055 | J23: % annual | L23: Prepaids | N23: 0.045 | O23: % of revenue
A24: Excess Cash | C24: =IF(cash_min=1,Bal_Sheet!C10-cash_min_amt,Bal_Sheet!C10) -> 5000 | D24: $ amt | G24: Average Interest | I24: 1 | J24: 1=Yes 0=No | L24: =L23&" - Annual Increase" -> Prepaids - Annual Increase | N24: 0.02 | O24: % | Q24: Financing | R24: Annual
A25: Debt: | E25: Fees | G25: Optional Prepayment | I25: 1 | J25: 1=Yes 0=No | L25: Other current assets | N25: 0.12 | O25: % of revenue | Q25: Costs | R25: Amortization
A26: =A15 -> Assumed Debt | C26: =C15 -> 65000 | D26: $ amt | L26: =L25&" - Annual Increase" -> Other current assets - Annual Increase | N26: 0.025 | O26: % | S26: Period (Yrs)
A27: Bank Revolver | C27: =C20-SUM(C24,C26,C28:C33,C35,C37:C39) -> 200887.5 | D27: $ amt | E27: 0.0075 | G27: =A29 -> Term Loan "B" | L27: Other long-term assets | N27: 0.04 | O27: % of revenue | Q27: =revolver_limit*E27 -> 4500 | R27: =Q27/S27 -> 450 | S27: 10
A28: Term Loan "A" | C28: 80000 | D28: $ amt | E28: 0.015 | G28: Term Years | I28: 11 | J28: select no. | L28: =L27&" - Annual Increase" -> Other long-term assets - Annual Increase | N28: 0.005 | O28: % | Q28: =C28*E28 -> 1200 | R28: =Q28/I21 -> 150
A29: Term Loan "B" | C29: 55000 | D29: $ amt | E29: 0.0175 | G29: Annual Repayment | I29: 0.04 | J29: % of FV | Q29: =C29*E29 -> 962.5 | R29: =Q29/I28 -> 87.5
A30: Senior Notes | C30: 65000 | D30: $ amt | E30: 0.02 | G30: Bullet Year Repayment | I30: =1-(I28-1)*termloanB_ann_repay -> 0.6 | J30: % of FV | L30: Accounts payable | N30: 0.15 | O30: % of COGS plus inventory increase | Q30: =C30*E30 -> 1300 | R30: =Q30/senior_notes_mat_yr -> 144.44444
A31: Subordinated Notes | C31: 40000 | D31: $ amt | E31: 0.025 | G31: Coupon Rate | I31: 0.0525 | J31: % annual | L31: =L30&" - Annual Increase" -> Accounts payable - Annual Increase | N31: 0.02 | O31: % | Q31: =C31*E31 -> 1000 | R31: =Q31/sub_notes_mat_yr -> 83.333333
A32: Mezzanine Debt | C32: 70000 | D32: $ amt | E32: 0.0275 | G32: Average Interest | I32: 1 | J32: 1=Yes 0=No | L32: Accrued expenses | N32: 0.06 | O32: % of revenue | Q32: =C32*E32 -> 1925 | R32: =Q32/mezzdebt_maturity_year -> 137.5
A33: Seller Notes | C33: 25000 | D33: $ amt | E33: 0 | G33: Optional Prepayment | I33: 1 | J33: 1=Yes 0=No | L33: =L32&" - Annual Increase" -> Accrued expenses - Annual Increase | N33: 0.015 | O33: % | Q33: =C33*E33 -> 0 | R33: =Q33/I56 -> 0
A34: Preferred: | L34: Other current liabilities | N34: 0.08 | O34: % of revenue | Q34: =SUM(Q27:Q33) -> 10887.5 | R34: =SUM(R27:R33) -> 1052.7778
A35: Preferred Stock | C35: 60000 | D35: $ amt | E35: 0.02 | G35: =A30 -> Senior Notes | L35: =L34&" - Annual Increase" -> Other current liabilities - Annual Increase | N35: 0.01 | O35: % | Q35: =C35*E35 -> 1200
A36: Equity: | G36: Maturity Year | I36: 9 | J36: select no. | L36: Capex | N36: 0.1 | O36: % of revenue | Q36: =SUM(Q34:Q35) -> 12087.5
A37: Common - Sponsor Equity | C37: 220000 | D37: $ amt | G37: Coupon Rate | I37: 0.0425 | J37: % annual | L37: Capex Start Year | N37: 1 | O37: in years
A38: Management Equity | C38: 40000 | D38: $ amt | G38: Average Interest | I38: 1 | J38: 1=Yes 0=No | L38: Capex Interval | N38: 1 | O38: in years
A39: New Equity | C39: 25000 | D39: $ amt | G39: Optional Prepayment | I39: 1 | J39: 1=Yes 0=No
A40: Total | C40: =SUM(C24:C39) -> 950887.5 | D40: $ amt
G41: =A31 -> Subordinated Notes | L41: Other Assumptions:
G42: Maturity Year | I42: 12 | J42: select no. | L42: Cash Minimum | N42: 50000 | O42: $ amt
A43: Goodwill / Bargain Purchase: | G43: Coupon Rate | I43: 0.045 | J43: % annual | L43: On / Off | N43: 1 | O43: 1=On. 0=Off.
A44: Equity Purchase Price | C44: =C12 -> 660000 | D44: $ amt | G44: Average Interest | I44: 0 | J44: 1=Yes 0=No
A45: Add: | G45: Years PIK | I45: 5 | J45: enter no. | L45: Tax Rate | N45: 0.35 | O45: %
A46: Existing Goodwill | C46: =Bal_Sheet!C19 -> 20000 | D46: $ amt | G46: Optional Prepayment | I46: 1 | J46: 1=Yes 0=No | L46: Year 1 | N46: 2010 | O46: year
A47: Less:
A48: Net Assets (Book Value) | C48: =SUM(Bal_Sheet!C62:C63) -> 464749 | D48: $ amt | G48: =A32 -> Mezzanine Debt
A49: Fixed Assets (PP&E) Write-up | C49: 2450 | D49: $ amt | G49: Maturity Year | I49: 14 | J49: select no. | L49: DCF Assumptions:
A50: Identifiable Tangibles Write-up | C50: 1200 | D50: $ amt | G50: Coupon Rate | I50: 0.045 | J50: % annual | L50: Discount Rate (WACC) | N50: =IF(WACC!H7=1,ROUND(WACC!L16,2),ROUND(WACC!L7,2)) -> 0.07 | O50: %
A51: Deferred Tax Liability - existing | C51: =Bal_Sheet!C44 -> 1400 | D51: $ amt | G51: Average Interest | I51: 0 | J51: 1=Yes 0=No | L51: Discount Rate Range | N51: 0.01 | O51: %
A52: DTL Created on Assets Write-up | C52: =-SUM(C49:C50)*tax_rate -> -1277.5 | D52: $ amt | G52: Years PIK | I52: 5 | J52: enter no. | L52: EBITDA Terminal Value Multiple | N52: 6 | O52: x
A53: Goodwill/(Gain from Bargain Purchase) | C53: =SUM(C44,C46,-SUM(C48:C52)) -> 211478.5 | D53: $ amt | G53: Optional Prepayment | I53: 1 | J53: 1=Yes 0=No | L53: EBITDA Multiple Range | N53: 2 | O53: x
L54: Perpetuity Growth Rate | N54: 0.03 | O54: %
G55: =A33 -> Seller Notes | L55: Perpetuity Growth Range | N55: 0.005 | O55: %
G56: Term Years | I56: 7 | J56: select no. | L56: Net Debt | N56: =Bal_Sheet!E54+Bal_Sheet!E61-Bal_Sheet!E10 -> 583387.5 | O56: $ amt
G57: Annual Repayment | I57: =1/I56 -> 0.14285714 | J57: % of FV
G58: Coupon Rate | I58: 0.0525 | J58: % annual
G59: Average Interest | I59: 1 | J59: 1=Yes 0=No
G60: Years PIK | I60: 5 | J60: enter no.
G61: Optional Prepayment | I61: 1 | J61: 1=Yes 0=No
G63: =A35 -> Preferred Stock
G64: Preferred Stock Dividend | I64: 0.07 | J64: % annual
G65: Years PIK | I65: 5 | J65: enter no.
G66: Pref Stock Retired Year | J66: select no.

Sheet Inc_St
A2: Income Statements
A4: Year | D4: =year1 -> 2010 | E4: =D4+1 -> 2011 | F4: =E4+1 -> 2012 | G4: =F4+1 -> 2013 | H4: =G4+1 -> 2014 | I4: =H4+1 -> 2015 | J4: =I4+1 -> 2016 | K4: =J4+1 -> 2017 | L4: =K4+1 -> 2018 | M4: =L4+1 -> 2019
A5: Year No. | D5: 1 | E5: =D5+1 -> 2 | F5: =E5+1 -> 3 | G5: =F5+1 -> 4 | H5: =G5+1 -> 5 | I5: =H5+1 -> 6 | J5: =I5+1 -> 7 | K5: =J5+1 -> 8 | L5: =K5+1 -> 9 | M5: =L5+1 -> 10
A8: Net Sales | D8: =sales_yr1 -> 1100000 | E8: =D8*(1+sales_ann_incr) -> 1210000 | F8: =E8*(1+sales_ann_incr) -> 1331000 | G8: =F8*(1+sales_ann_incr) -> 1464100 | H8: =G8*(1+sales_ann_incr) -> 1610510 | I8: =H8*(1+sales_ann_incr) -> 1771561 | J8: =I8*(1+sales_ann_incr) -> 1948717.1 | K8: =J8*(1+sales_ann_incr) -> 2143588.8 | L8: =K8*(1+sales_ann_incr) -> 2357947.7 | M8: =L8*(1+sales_ann_incr) -> 2593742.5
A10: =Input!L11 -> Cost of goods sold | D10: =D8*cogs*(1+cogs_ann_incr)^(D5-1) -> 495000 | E10: =E8*cogs*(1+cogs_ann_incr)^(E5-1) -> 545861.25 | F10: =F8*cogs*(1+cogs_ann_incr)^(F5-1) -> 601948.49 | G10: =G8*cogs*(1+cogs_ann_incr)^(G5-1) -> 663798.7 | H10: =H8*cogs*(1+cogs_ann_incr)^(H5-1) -> 732004.02 | I10: =I8*cogs*(1+cogs_ann_incr)^(I5-1) -> 807217.43 | J10: =J8*cogs*(1+cogs_ann_incr)^(J5-1) -> 890159.02 | K10: =K8*cogs*(1+cogs_ann_incr)^(K5-1) -> 981622.86 | ... M10: =M8*cogs*(1+cogs_ann_incr)^(M5-1) -> 1193709.9
A12: Gross Margin | D12: =D8-D10 -> 605000 | E12: =E8-E10 -> 664138.75 | F12: =F8-F10 -> 729051.51 | G12: =G8-G10 -> 800301.3 | H12: =H8-H10 -> 878505.98 | I12: =I8-I10 -> 964343.57 | J12: =J8-J10 -> 1058558.1 | K12: =K8-K10 -> 1161965.9 | ... M12: =M8-M10 -> 1400032.6
A14: Operating Expenses | D14: =SUM(D15:D16) -> 286000 | E14: =SUM(E15:E16) -> 315664.8 | F14: =SUM(F15:F16) -> 348407.58 | G14: =SUM(G15:G16) -> 384547.81 | H14: =SUM(H15:H16) -> 424438.14 | I14: =SUM(I15:I16) -> 468467.83 | J14: =SUM(J15:J16) -> 517066.57 | K14: =SUM(K15:K16) -> 570708.66 | ... M14: =SUM(M15:M16) -> 695271.43
A15: =Input!L13 -> SG&A expenses | D15: =D8*sga_exp*(1+sga_exp_ann_incr)^(D5-1) -> 154000 | E15: =E8*sga_exp*(1+sga_exp_ann_incr)^(E5-1) -> 170247 | F15: =F8*sga_exp*(1+sga_exp_ann_incr)^(F5-1) -> 188208.06 | G15: =G8*sga_exp*(1+sga_exp_ann_incr)^(G5-1) -> 208064.01 | H15: =H8*sga_exp*(1+sga_exp_ann_incr)^(H5-1) -> 230014.76 | I15: =I8*sga_exp*(1+sga_exp_ann_incr)^(I5-1) -> 254281.32 | J15: =J8*sga_exp*(1+sga_exp_ann_incr)^(J5-1) -> 281108 | K15: =K8*sga_exp*(1+sga_exp_ann_incr)^(K5-1) -> 310764.89 | ... M15: =M8*sga_exp*(1+sga_exp_ann_incr)^(M5-1) -> 379795.18
A16: =Input!L15 -> Other expenses | D16: =D8*other_exp*(1+other_exp_ann_incr)^(D5-1) -> 132000 | E16: =E8*other_exp*(1+other_exp_ann_incr)^(E5-1) -> 145417.8 | F16: =F8*other_exp*(1+other_exp_ann_incr)^(F5-1) -> 160199.52 | G16: =G8*other_exp*(1+other_exp_ann_incr)^(G5-1) -> 176483.8 | H16: =H8*other_exp*(1+other_exp_ann_incr)^(H5-1) -> 194423.38 | I16: =I8*other_exp*(1+other_exp_ann_incr)^(I5-1) -> 214186.52 | J16: =J8*other_exp*(1+other_exp_ann_incr)^(J5-1) -> 235958.57 | K16: =K8*other_exp*(1+other_exp_ann_incr)^(K5-1) -> 259943.76 | ... M16: =M8*other_exp*(1+other_exp_ann_incr)^(M5-1) -> 315476.26
A18: EBITDA | D18: =D12-D14 -> 319000 | E18: =E12-E14 -> 348473.95 | F18: =F12-F14 -> 380643.93 | G18: =G12-G14 -> 415753.49 | H18: =H12-H14 -> 454067.84 | I18: =I12-I14 -> 495875.74 | J18: =J12-J14 -> 541491.51 | K18: =K12-K14 -> 591257.29 | ... M18: =M12-M14 -> 704761.12
A20: D&A | D20: =Depr_Amort!F39+Depr_Amort!F42+Depr_Amort!F43 -> 72924.167 | E20: =Depr_Amort!G39+Depr_Amort!G42+Depr_Amort!G43 -> 85024.167 | F20: =Depr_Amort!H39+Depr_Amort!H42+Depr_Amort!H43 -> 93897.5 | G20: =Depr_Amort!I39+Depr_Amort!I42+Depr_Amort!I43 -> 104355.36 | H20: =Depr_Amort!J39+Depr_Amort!J42+Depr_Amort!J43 -> 117776.27 | I20: =Depr_Amort!K39+Depr_Amort!K42+Depr_Amort!K43 -> 128848.53 | J20: =Depr_Amort!L39+Depr_Amort!L42+Depr_Amort!L43 -> 101531.64 | K20: =Depr_Amort!M39+Depr_Amort!M42+Depr_Amort!M43 -> 115822.24 | ... M20: =Depr_Amort!O39+Depr_Amort!O42+Depr_Amort!O43 -> 149661.32
A22: EBIT | D22: =D18-D20 -> 246075.83 | E22: =E18-E20 -> 263449.78 | F22: =F18-F20 -> 286746.43 | G22: =G18-G20 -> 311398.13 | H22: =H18-H20 -> 336291.57 | I22: =I18-I20 -> 367027.21 | J22: =J18-J20 -> 439959.86 | K22: =K18-K20 -> 475435.06 | ... M22: =M18-M20 -> 555099.8
A24: Interest Expense | D24: =SUM(D25:D32) -> 32061.164 | E24: =SUM(E25:E32) -> 30508.698 | F24: =SUM(F25:F32) -> 26834.518 | G24: =SUM(G25:G32) -> 22778.252 | H24: =SUM(H25:H32) -> 20741.141 | I24: =SUM(I25:I32) -> 16059.282 | J24: =SUM(J25:J32) -> 12049.404 | K24: =SUM(K25:K32) -> 8160.7242 | ... M24: =SUM(M25:M32) -> 6000
A25: =Bal_Sheet!A46 -> Existing Debt | D25: =IF(assumed_debt_avg_int=1,AVERAGE(Bal_Sheet!E46,Bal_Sheet!F46)*assumed_debt_cou_rate,Bal_Sheet!E46*assumed_debt_cou_rate) -> 2609.0278 | E25: =IF(assumed_debt_avg_int=1,AVERAGE(Bal_Sheet!F46,Bal_Sheet!G46)*assumed_debt_cou_rate,Bal_Sheet!F46*assumed_debt_cou_rate) -> 1227.7778 | F25: =IF(assumed_debt_avg_int=1,AVERAGE(Bal_Sheet!G46,Bal_Sheet!H46)*assumed_debt_cou_rate,Bal_Sheet!G46*assumed_debt_cou_rate) -> 0 | G25: =IF(assumed_debt_avg_int=1,AVERAGE(Bal_Sheet!H46,Bal_Sheet!I46)*assumed_debt_cou_rate,Bal_Sheet!H46*assumed_debt_cou_rate) -> 0 | H25: =IF(assumed_debt_avg_int=1,AVERAGE(Bal_Sheet!I46,Bal_Sheet!J46)*assumed_debt_cou_rate,Bal_Sheet!I46*assumed_debt_cou_rate) -> 0 | I25: =IF(assumed_debt_avg_int=1,AVERAGE(Bal_Sheet!J46,Bal_Sheet!K46)*assumed_debt_cou_rate,Bal_Sheet!J46*assumed_debt_cou_rate) -> 0 | J25: =IF(assumed_debt_avg_int=1,AVERAGE(Bal_Sheet!K46,Bal_Sheet!L46)*assumed_debt_cou_rate,Bal_Sheet!K46*assumed_debt_cou_rate) -> 0 | K25: =IF(assumed_debt_avg_int=1,AVERAGE(Bal_Sheet!L46,Bal_Sheet!M46)*assumed_debt_cou_rate,Bal_Sheet!L46*assumed_debt_cou_rate) -> 0 | ... M25: =IF(assumed_debt_avg_int=1,AVERAGE(Bal_Sheet!N46,Bal_Sheet!O46)*assumed_debt_cou_rate,Bal_Sheet!N46*assumed_debt_cou_rate) -> 0
A26: =Bal_Sheet!A47 -> Bank Revolver | D26: =Bal_Sheet!E47*bank_revolver_cou_rate+(revolver_limit-Bal_Sheet!E47)*undrawn_commit_fee -> 13533.281 | E26: =Bal_Sheet!F47*bank_revolver_cou_rate+(revolver_limit-Bal_Sheet!F47)*undrawn_commit_fee -> 14005.141 | F26: =Bal_Sheet!G47*bank_revolver_cou_rate+(revolver_limit-Bal_Sheet!G47)*undrawn_commit_fee -> 14005.141 | G26: =Bal_Sheet!H47*bank_revolver_cou_rate+(revolver_limit-Bal_Sheet!H47)*undrawn_commit_fee -> 14005.141 | H26: =Bal_Sheet!I47*bank_revolver_cou_rate+(revolver_limit-Bal_Sheet!I47)*undrawn_commit_fee -> 14005.141 | I26: =Bal_Sheet!J47*bank_revolver_cou_rate+(revolver_limit-Bal_Sheet!J47)*undrawn_commit_fee -> 14005.141 | J26: =Bal_Sheet!K47*bank_revolver_cou_rate+(revolver_limit-Bal_Sheet!K47)*undrawn_commit_fee -> 12049.404 | K26: =Bal_Sheet!L47*bank_revolver_cou_rate+(revolver_limit-Bal_Sheet!L47)*undrawn_commit_fee -> 8160.7242 | ... M26: =Bal_Sheet!N47*bank_revolver_cou_rate+(revolver_limit-Bal_Sheet!N47)*undrawn_commit_fee -> 6000
A27: =Bal_Sheet!A48 -> Term Loan "A" | D27: =IF(termloanA_avg_int=1,AVERAGE(Bal_Sheet!E48,Bal_Sheet!F48)*termloanA_cou_rate,Bal_Sheet!E48*termloanA_cou_rate) -> 4125 | E27: =IF(termloanA_avg_int=1,AVERAGE(Bal_Sheet!F48,Bal_Sheet!G48)*termloanA_cou_rate,Bal_Sheet!F48*termloanA_cou_rate) -> 3499.7482 | F27: =IF(termloanA_avg_int=1,AVERAGE(Bal_Sheet!G48,Bal_Sheet!H48)*termloanA_cou_rate,Bal_Sheet!G48*termloanA_cou_rate) -> 1574.7482 | G27: =IF(termloanA_avg_int=1,AVERAGE(Bal_Sheet!H48,Bal_Sheet!I48)*termloanA_cou_rate,Bal_Sheet!H48*termloanA_cou_rate) -> 0 | H27: =IF(termloanA_avg_int=1,AVERAGE(Bal_Sheet!I48,Bal_Sheet!J48)*termloanA_cou_rate,Bal_Sheet!I48*termloanA_cou_rate) -> 0 | I27: =IF(termloanA_avg_int=1,AVERAGE(Bal_Sheet!J48,Bal_Sheet!K48)*termloanA_cou_rate,Bal_Sheet!J48*termloanA_cou_rate) -> 0 | J27: =IF(termloanA_avg_int=1,AVERAGE(Bal_Sheet!K48,Bal_Sheet!L48)*termloanA_cou_rate,Bal_Sheet!K48*termloanA_cou_rate) -> 0 | K27: =IF(termloanA_avg_int=1,AVERAGE(Bal_Sheet!L48,Bal_Sheet!M48)*termloanA_cou_rate,Bal_Sheet!L48*termloanA_cou_rate) -> 0 | ... M27: =IF(termloanA_avg_int=1,AVERAGE(Bal_Sheet!N48,Bal_Sheet!O48)*termloanA_cou_rate,Bal_Sheet!N48*termloanA_cou_rate) -> 0
A28: =Bal_Sheet!A49 -> Term Loan "B" | D28: =IF(termloanB_avg_int=1,AVERAGE(Bal_Sheet!E49,Bal_Sheet!F49)*termloanB_cou_rate,Bal_Sheet!E49*termloanB_cou_rate) -> 2829.75 | E28: =IF(termloanB_avg_int=1,AVERAGE(Bal_Sheet!F49,Bal_Sheet!G49)*termloanB_cou_rate,Bal_Sheet!F49*termloanB_cou_rate) -> 2714.25 | F28: =IF(termloanB_avg_int=1,AVERAGE(Bal_Sheet!G49,Bal_Sheet!H49)*termloanB_cou_rate,Bal_Sheet!G49*termloanB_cou_rate) -> 2091.8912 | G28: =IF(termloanB_avg_int=1,AVERAGE(Bal_Sheet!H49,Bal_Sheet!I49)*termloanB_cou_rate,Bal_Sheet!H49*termloanB_cou_rate) -> 763.64116 | H28: =IF(termloanB_avg_int=1,AVERAGE(Bal_Sheet!I49,Bal_Sheet!J49)*termloanB_cou_rate,Bal_Sheet!I49*termloanB_cou_rate) -> 0 | I28: =IF(termloanB_avg_int=1,AVERAGE(Bal_Sheet!J49,Bal_Sheet!K49)*termloanB_cou_rate,Bal_Sheet!J49*termloanB_cou_rate) -> 0 | J28: =IF(termloanB_avg_int=1,AVERAGE(Bal_Sheet!K49,Bal_Sheet!L49)*termloanB_cou_rate,Bal_Sheet!K49*termloanB_cou_rate) -> 0 | K28: =IF(termloanB_avg_int=1,AVERAGE(Bal_Sheet!L49,Bal_Sheet!M49)*termloanB_cou_rate,Bal_Sheet!L49*termloanB_cou_rate) -> 0 | ... M28: =IF(termloanB_avg_int=1,AVERAGE(Bal_Sheet!N49,Bal_Sheet!O49)*termloanB_cou_rate,Bal_Sheet!N49*termloanB_cou_rate) -> 0
A29: =Bal_Sheet!A50 -> Senior Notes | D29: =IF(senior_notes_avg_int=1,AVERAGE(Bal_Sheet!E50,Bal_Sheet!F50)*senior_notes_cou_rate,Bal_Sheet!E50*senior_notes_cou_rate) -> 2762.5 | E29: =IF(senior_notes_avg_int=1,AVERAGE(Bal_Sheet!F50,Bal_Sheet!G50)*senior_notes_cou_rate,Bal_Sheet!F50*senior_notes_cou_rate) -> 2762.5 | F29: =IF(senior_notes_avg_int=1,AVERAGE(Bal_Sheet!G50,Bal_Sheet!H50)*senior_notes_cou_rate,Bal_Sheet!G50*senior_notes_cou_rate) -> 2762.5 | G29: =IF(senior_notes_avg_int=1,AVERAGE(Bal_Sheet!H50,Bal_Sheet!I50)*senior_notes_cou_rate,Bal_Sheet!H50*senior_notes_cou_rate) -> 1504.9079 | H29: =IF(senior_notes_avg_int=1,AVERAGE(Bal_Sheet!I50,Bal_Sheet!J50)*senior_notes_cou_rate,Bal_Sheet!I50*senior_notes_cou_rate) -> 123.65786 | I29: =IF(senior_notes_avg_int=1,AVERAGE(Bal_Sheet!J50,Bal_Sheet!K50)*senior_notes_cou_rate,Bal_Sheet!J50*senior_notes_cou_rate) -> 0 | J29: =IF(senior_notes_avg_int=1,AVERAGE(Bal_Sheet!K50,Bal_Sheet!L50)*senior_notes_cou_rate,Bal_Sheet!K50*senior_notes_cou_rate) -> 0 | K29: =IF(senior_notes_avg_int=1,AVERAGE(Bal_Sheet!L50,Bal_Sheet!M50)*senior_notes_cou_rate,Bal_Sheet!L50*senior_notes_cou_rate) -> 0 | ... M29: =IF(senior_notes_avg_int=1,AVERAGE(Bal_Sheet!N50,Bal_Sheet!O50)*senior_notes_cou_rate,Bal_Sheet!N50*senior_notes_cou_rate) -> 0
A30: =Bal_Sheet!A51 -> Subordinated Notes | D30: =IF(sub_notes_avg_int=1,AVERAGE(Bal_Sheet!E51,Bal_Sheet!F51)*sub_notes_cou_rate,Bal_Sheet!E51*sub_notes_cou_rate) -> 1800 | E30: =IF(sub_notes_avg_int=1,AVERAGE(Bal_Sheet!F51,Bal_Sheet!G51)*sub_notes_cou_rate,Bal_Sheet!F51*sub_notes_cou_rate) -> 1881 | F30: =IF(sub_notes_avg_int=1,AVERAGE(Bal_Sheet!G51,Bal_Sheet!H51)*sub_notes_cou_rate,Bal_Sheet!G51*sub_notes_cou_rate) -> 1965.645 | G30: =IF(sub_notes_avg_int=1,AVERAGE(Bal_Sheet!H51,Bal_Sheet!I51)*sub_notes_cou_rate,Bal_Sheet!H51*sub_notes_cou_rate) -> 2054.099 | H30: =IF(sub_notes_avg_int=1,AVERAGE(Bal_Sheet!I51,Bal_Sheet!J51)*sub_notes_cou_rate,Bal_Sheet!I51*sub_notes_cou_rate) -> 2146.5335 | I30: =IF(sub_notes_avg_int=1,AVERAGE(Bal_Sheet!J51,Bal_Sheet!K51)*sub_notes_cou_rate,Bal_Sheet!J51*sub_notes_cou_rate) -> 96.594007 | J30: =IF(sub_notes_avg_int=1,AVERAGE(Bal_Sheet!K51,Bal_Sheet!L51)*sub_notes_cou_rate,Bal_Sheet!K51*sub_notes_cou_rate) -> 0 | K30: =IF(sub_notes_avg_int=1,AVERAGE(Bal_Sheet!L51,Bal_Sheet!M51)*sub_notes_cou_rate,Bal_Sheet!L51*sub_notes_cou_rate) -> 0 | ... M30: =IF(sub_notes_avg_int=1,AVERAGE(Bal_Sheet!N51,Bal_Sheet!O51)*sub_notes_cou_rate,Bal_Sheet!N51*sub_notes_cou_rate) -> 0
A31: =Bal_Sheet!A52 -> Mezzanine Debt | D31: =IF(mezzdebt_avg_int=1,AVERAGE(Bal_Sheet!E52,Bal_Sheet!F52)*mezzdebt_cou_rate,Bal_Sheet!E52*mezzdebt_cou_rate) -> 3150 | E31: =IF(mezzdebt_avg_int=1,AVERAGE(Bal_Sheet!F52,Bal_Sheet!G52)*mezzdebt_cou_rate,Bal_Sheet!F52*mezzdebt_cou_rate) -> 3291.75 | F31: =IF(mezzdebt_avg_int=1,AVERAGE(Bal_Sheet!G52,Bal_Sheet!H52)*mezzdebt_cou_rate,Bal_Sheet!G52*mezzdebt_cou_rate) -> 3439.8787 | G31: =IF(mezzdebt_avg_int=1,AVERAGE(Bal_Sheet!H52,Bal_Sheet!I52)*mezzdebt_cou_rate,Bal_Sheet!H52*mezzdebt_cou_rate) -> 3594.6733 | H31: =IF(mezzdebt_avg_int=1,AVERAGE(Bal_Sheet!I52,Bal_Sheet!J52)*mezzdebt_cou_rate,Bal_Sheet!I52*mezzdebt_cou_rate) -> 3756.4336 | I31: =IF(mezzdebt_avg_int=1,AVERAGE(Bal_Sheet!J52,Bal_Sheet!K52)*mezzdebt_cou_rate,Bal_Sheet!J52*mezzdebt_cou_rate) -> 1640.4239 | J31: =IF(mezzdebt_avg_int=1,AVERAGE(Bal_Sheet!K52,Bal_Sheet!L52)*mezzdebt_cou_rate,Bal_Sheet!K52*mezzdebt_cou_rate) -> 0 | K31: =IF(mezzdebt_avg_int=1,AVERAGE(Bal_Sheet!L52,Bal_Sheet!M52)*mezzdebt_cou_rate,Bal_Sheet!L52*mezzdebt_cou_rate) -> 0 | ... M31: =IF(mezzdebt_avg_int=1,AVERAGE(Bal_Sheet!N52,Bal_Sheet!O52)*mezzdebt_cou_rate,Bal_Sheet!N52*mezzdebt_cou_rate) -> 0
A32: =Bal_Sheet!A53 -> Seller Notes | D32: =IF(seller_notes_avg_int=1,AVERAGE(Bal_Sheet!E53,Bal_Sheet!F53)*seller_notes_cou_rate,Bal_Sheet!E53*seller_notes_cou_rate) -> 1251.6046 | E32: =IF(seller_notes_avg_int=1,AVERAGE(Bal_Sheet!F53,Bal_Sheet!G53)*seller_notes_cou_rate,Bal_Sheet!F53*seller_notes_cou_rate) -> 1126.5307 | F32: =IF(seller_notes_avg_int=1,AVERAGE(Bal_Sheet!G53,Bal_Sheet!H53)*seller_notes_cou_rate,Bal_Sheet!G53*seller_notes_cou_rate) -> 994.71333 | G32: =IF(seller_notes_avg_int=1,AVERAGE(Bal_Sheet!H53,Bal_Sheet!I53)*seller_notes_cou_rate,Bal_Sheet!H53*seller_notes_cou_rate) -> 855.78901 | H32: =IF(seller_notes_avg_int=1,AVERAGE(Bal_Sheet!I53,Bal_Sheet!J53)*seller_notes_cou_rate,Bal_Sheet!I53*seller_notes_cou_rate) -> 709.37456 | I32: =IF(seller_notes_avg_int=1,AVERAGE(Bal_Sheet!J53,Bal_Sheet!K53)*seller_notes_cou_rate,Bal_Sheet!J53*seller_notes_cou_rate) -> 317.12282 | J32: =IF(seller_notes_avg_int=1,AVERAGE(Bal_Sheet!K53,Bal_Sheet!L53)*seller_notes_cou_rate,Bal_Sheet!K53*seller_notes_cou_rate) -> 0 | K32: =IF(seller_notes_avg_int=1,AVERAGE(Bal_Sheet!L53,Bal_Sheet!M53)*seller_notes_cou_rate,Bal_Sheet!L53*seller_notes_cou_rate) -> 0 | ... M32: =IF(seller_notes_avg_int=1,AVERAGE(Bal_Sheet!N53,Bal_Sheet!O53)*seller_notes_cou_rate,Bal_Sheet!N53*seller_notes_cou_rate) -> 0
A34: Other Expenses (Income) | D34: =SUM(D36:D37) -> -197.22222 | E34: =SUM(E36:E37) -> -297.22222 | F34: =SUM(F36:F37) -> 352.77778 | G34: =SUM(G36:G37) -> -34.722222 | H34: =SUM(H36:H37) -> -256.94444 | I34: =SUM(I36:I37) -> 520.83333 | J34: =SUM(J36:J37) -> -1400 | K34: =SUM(K36:K37) -> -1500 | ... M34: =SUM(M36:M37) -> -1700
A35: Amortization of Capitalized
A36: Financing Costs | D36: =Depr_Amort!F45 -> 1052.7778 | E36: =Depr_Amort!G45 -> 1052.7778 | F36: =Depr_Amort!H45 -> 1802.7778 | G36: =Depr_Amort!I45 -> 1515.2778 | H36: =Depr_Amort!J45 -> 1393.0556 | I36: =Depr_Amort!K45 -> 2270.8333 | J36: =Depr_Amort!L45 -> 450 | K36: =Depr_Amort!M45 -> 450 | ... M36: =Depr_Amort!O45 -> 450
A37: (Gain) Loss on Asset Sales | D37: =-Income_Tax!D11 -> -1250 | E37: =-Income_Tax!E11 -> -1350 | F37: =-Income_Tax!F11 -> -1450 | G37: =-Income_Tax!G11 -> -1550 | H37: =-Income_Tax!H11 -> -1650 | I37: =-Income_Tax!I11 -> -1750 | J37: =-Income_Tax!J11 -> -1850 | K37: =-Income_Tax!K11 -> -1950 | ... M37: =-Income_Tax!M11 -> -2150
A39: Net Income before Taxes | D39: =D22-D24-D34 -> 214211.89 | E39: =E22-E24-E34 -> 233238.31 | F39: =F22-F24-F34 -> 259559.13 | G39: =G22-G24-G34 -> 288654.6 | H39: =H22-H24-H34 -> 315807.37 | I39: =I22-I24-I34 -> 350447.09 | J39: =J22-J24-J34 -> 429310.46 | K39: =K22-K24-K34 -> 468774.33 | ... M39: =M22-M24-M34 -> 550799.8
A41: Income Tax Expense (Benefit) | D41: =Income_Tax!D28 -> 74974.162 | E41: =Income_Tax!E28 -> 81633.408 | F41: =Income_Tax!F28 -> 90845.697 | G41: =Income_Tax!G28 -> 101029.11 | H41: =Income_Tax!H28 -> 110532.58 | I41: =Income_Tax!I28 -> 122656.48 | J41: =Income_Tax!J28 -> 150258.66 | K41: =Income_Tax!K28 -> 164071.02 | ... M41: =Income_Tax!M28 -> 192779.93
A43: Net Income | D43: =D39-D41 -> 139237.73 | E43: =E39-E41 -> 151604.9 | F43: =F39-F41 -> 168713.44 | G43: =G39-G41 -> 187625.49 | H43: =H39-H41 -> 205274.79 | I43: =I39-I41 -> 227790.61 | J43: =J39-J41 -> 279051.8 | K43: =K39-K41 -> 304703.32 | ... M43: =M39-M41 -> 358019.87
A45: Dividend | D45: =SUM(D46:D47) -> 6700 | E45: =SUM(E46:E47) -> 7194 | F45: =SUM(F46:F47) -> 7658.58 | G45: =SUM(G46:G47) -> 8245.1806 | H45: =SUM(H46:H47) -> 8955.3432 | I45: =SUM(I46:I47) -> 9390.7173 | J45: =SUM(J46:J47) -> 9590.7173 | K45: =SUM(K46:K47) -> 9890.7173 | ... M45: =SUM(M46:M47) -> 10290.717
A46: =Input!G64 -> Preferred Stock Dividend | D46: =Bal_Sheet!E61*pref_stock_div -> 4200 | E46: =Bal_Sheet!F61*pref_stock_div -> 4494 | F46: =Bal_Sheet!G61*pref_stock_div -> 4808.58 | G46: =Bal_Sheet!H61*pref_stock_div -> 5145.1806 | H46: =Bal_Sheet!I61*pref_stock_div -> 5505.3432 | I46: =Bal_Sheet!J61*pref_stock_div -> 5890.7173 | J46: =Bal_Sheet!K61*pref_stock_div -> 5890.7173 | K46: =Bal_Sheet!L61*pref_stock_div -> 5890.7173 | ... M46: =Bal_Sheet!N61*pref_stock_div -> 5890.7173
A47: Common Stock Dividend | D47: 2500 | E47: 2700 | F47: 2850 | G47: 3100 | H47: 3450 | I47: 3500 | J47: 3700 | K47: 4000 | L47: 4100 | M47: 4400
A49: Net Income to Common Shareholders | D49: =D43-D45 -> 132537.73 | E49: =E43-E45 -> 144410.9 | F49: =F43-F45 -> 161054.86 | G49: =G43-G45 -> 179380.31 | H49: =H43-H45 -> 196319.45 | I49: =I43-I45 -> 218399.89 | J49: =J43-J45 -> 269461.08 | K49: =K43-K45 -> 294812.6 | ... M49: =M43-M45 -> 347729.15

Sheet Bal_Sheet
A2: Balance Sheets
A4: Year | C4: Pre-Acq | D4: Adj | E4: Post-Acq | F4: =year1 -> 2010 | G4: =F4+1 -> 2011 | H4: =G4+1 -> 2012 | I4: =H4+1 -> 2013 | J4: =I4+1 -> 2014 | K4: =J4+1 -> 2015 | L4: =K4+1 -> 2016 | M4: =L4+1 -> 2017 | N4: =M4+1 -> 2018 | O4: =N4+1 -> 2019
A5: Year No. | E5: =F5-1 -> 0 | F5: 1 | G5: =F5+1 -> 2 | H5: =G5+1 -> 3 | I5: =H5+1 -> 4 | J5: =I5+1 -> 5 | K5: =J5+1 -> 6 | L5: =K5+1 -> 7 | M5: =L5+1 -> 8 | N5: =M5+1 -> 9 | O5: =N5+1 -> 10
A7: ASSETS
A9: Current Assets:
A10: Cash in bank | C10: 55000 | D10: =Input!C18-Input!C24 -> 22500 | E10: =SUM(C10:D10) -> 77500 | F10: =Cash_Flow!D110 -> 50000 | G10: =Cash_Flow!E110 -> 50000 | H10: =Cash_Flow!F110 -> 50000 | I10: =Cash_Flow!G110 -> 50000 | J10: =Cash_Flow!H110 -> 50000 | K10: =Cash_Flow!I110 -> 50000 | L10: =Cash_Flow!J110 -> 50000 | M10: =Cash_Flow!K110 -> 134328.87 | ... O10: =Cash_Flow!M110 -> 352890.02
A11: Accounts receivable | C11: 85000 | E11: =SUM(C11:D11) -> 85000 | F11: =Inc_St!D8*acc_recv*(1+acc_recv_ann_incr)^(F5-1) -> 198000 | G11: =Inc_St!E8*acc_recv*(1+acc_recv_ann_incr)^(G5-1) -> 228690 | H11: =Inc_St!F8*acc_recv*(1+acc_recv_ann_incr)^(H5-1) -> 264136.95 | I11: =Inc_St!G8*acc_recv*(1+acc_recv_ann_incr)^(I5-1) -> 305078.18 | J11: =Inc_St!H8*acc_recv*(1+acc_recv_ann_incr)^(J5-1) -> 352365.29 | K11: =Inc_St!I8*acc_recv*(1+acc_recv_ann_incr)^(K5-1) -> 406981.92 | L11: =Inc_St!J8*acc_recv*(1+acc_recv_ann_incr)^(L5-1) -> 470064.11 | M11: =Inc_St!K8*acc_recv*(1+acc_recv_ann_incr)^(M5-1) -> 542924.05 | ... O11: =Inc_St!M8*acc_recv*(1+acc_recv_ann_incr)^(O5-1) -> 724274.26
A12: Inventories | C12: 95999 | E12: =SUM(C12:D12) -> 95999 | F12: =Inc_St!D10*inventories*(1+inventories_ann_incr)^(F5-1) -> 99000 | G12: =Inc_St!E10*inventories*(1+inventories_ann_incr)^(G5-1) -> 113539.14 | H12: =Inc_St!F10*inventories*(1+inventories_ann_incr)^(H5-1) -> 130213.5 | I12: =Inc_St!G10*inventories*(1+inventories_ann_incr)^(I5-1) -> 149336.65 | J12: =Inc_St!H10*inventories*(1+inventories_ann_incr)^(J5-1) -> 171268.23 | K12: =Inc_St!I10*inventories*(1+inventories_ann_incr)^(K5-1) -> 196420.69 | L12: =Inc_St!J10*inventories*(1+inventories_ann_incr)^(L5-1) -> 225267.03 | M12: =Inc_St!K10*inventories*(1+inventories_ann_incr)^(M5-1) -> 258349.74 | ... O12: =Inc_St!M10*inventories*(1+inventories_ann_incr)^(O5-1) -> 339804.28
A13: Prepaids | C13: 22000 | E13: =SUM(C13:D13) -> 22000 | F13: =Inc_St!D8*prepaids*(1+prepaids_ann_incr)^(F5-1) -> 49500 | G13: =Inc_St!E8*prepaids*(1+prepaids_ann_incr)^(G5-1) -> 55539 | H13: =Inc_St!F8*prepaids*(1+prepaids_ann_incr)^(H5-1) -> 62314.758 | I13: =Inc_St!G8*prepaids*(1+prepaids_ann_incr)^(I5-1) -> 69917.158 | J13: =Inc_St!H8*prepaids*(1+prepaids_ann_incr)^(J5-1) -> 78447.052 | K13: =Inc_St!I8*prepaids*(1+prepaids_ann_incr)^(K5-1) -> 88017.592 | L13: =Inc_St!J8*prepaids*(1+prepaids_ann_incr)^(L5-1) -> 98755.738 | M13: =Inc_St!K8*prepaids*(1+prepaids_ann_incr)^(M5-1) -> 110803.94 | ... O13: =Inc_St!M8*prepaids*(1+prepaids_ann_incr)^(O5-1) -> 139489.31
A14: Other current assets | C14: 45000 | E14: =SUM(C14:D14) -> 45000 | F14: =Inc_St!D8*other_curr_assets*(1+other_curr_assets_ann_incr)^(F5-1) -> 132000 | G14: =Inc_St!E8*other_curr_assets*(1+other_curr_assets_ann_incr)^(G5-1) -> 148830 | H14: =Inc_St!F8*other_curr_assets*(1+other_curr_assets_ann_incr)^(H5-1) -> 167805.83 | I14: =Inc_St!G8*other_curr_assets*(1+other_curr_assets_ann_incr)^(I5-1) -> 189201.07 | J14: =Inc_St!H8*other_curr_assets*(1+other_curr_assets_ann_incr)^(J5-1) -> 213324.2 | K14: =Inc_St!I8*other_curr_assets*(1+other_curr_assets_ann_incr)^(K5-1) -> 240523.04 | L14: =Inc_St!J8*other_curr_assets*(1+other_curr_assets_ann_incr)^(L5-1) -> 271189.73 | M14: =Inc_St!K8*other_curr_assets*(1+other_curr_assets_ann_incr)^(M5-1) -> 305766.42 | ... O14: =Inc_St!M8*other_curr_assets*(1+other_curr_assets_ann_incr)^(O5-1) -> 388707.47
A16: Total Current Assets | C16: =SUM(C10:C14) -> 302999 | E16: =SUM(E10:E14) -> 325499 | F16: =SUM(F10:F14) -> 528500 | G16: =SUM(G10:G14) -> 596598.14 | H16: =SUM(H10:H14) -> 674471.03 | I16: =SUM(I10:I14) -> 763533.06 | J16: =SUM(J10:J14) -> 865404.78 | K16: =SUM(K10:K14) -> 981943.23 | L16: =SUM(L10:L14) -> 1115276.6 | ... O16: =SUM(O10:O14) -> 1945165.3
A18: Non-Current Assets:
A19: Goodwill | C19: 20000 | D19: =-C19+Input!C53 -> 191478.5 | E19: =SUM(C19:D19) -> 211478.5 | F19: =E19-Depr_Amort!F43 -> 211478.5 | G19: =F19-Depr_Amort!G43 -> 211478.5 | H19: =G19-Depr_Amort!H43 -> 211478.5 | I19: =H19-Depr_Amort!I43 -> 211478.5 | J19: =I19-Depr_Amort!J43 -> 211478.5 | K19: =J19-Depr_Amort!K43 -> 211478.5 | L19: =K19-Depr_Amort!L43 -> 211478.5 | M19: =L19-Depr_Amort!M43 -> 211478.5 | ... O19: =N19-Depr_Amort!O43 -> 211478.5
A20: Intangible Assets | C20: 950 | D20: =Input!C50 -> 1200 | E20: =SUM(C20:D20) -> 2150 | F20: =E20-Depr_Amort!F42 -> 1970.8333 | G20: =F20-Depr_Amort!G42 -> 1791.6667 | H20: =G20-Depr_Amort!H42 -> 1612.5 | I20: =H20-Depr_Amort!I42 -> 1433.3333 | J20: =I20-Depr_Amort!J42 -> 1254.1667 | K20: =J20-Depr_Amort!K42 -> 1075 | L20: =K20-Depr_Amort!L42 -> 895.83333 | M20: =L20-Depr_Amort!M42 -> 716.66667 | ... O20: =N20-Depr_Amort!O42 -> 358.33333
A21: =Input!A17 -> Capitalized Financing Costs | C21: 0 | D21: =Input!Q34 -> 10887.5 | E21: =SUM(C21:D21) -> 10887.5 | F21: =E21-Depr_Amort!F45 -> 9834.7222 | G21: =F21-Depr_Amort!G45 -> 8781.9444 | H21: =G21-Depr_Amort!H45 -> 6979.1667 | I21: =H21-Depr_Amort!I45 -> 5463.8889 | J21: =I21-Depr_Amort!J45 -> 4070.8333 | K21: =J21-Depr_Amort!K45 -> 1800 | L21: =K21-Depr_Amort!L45 -> 1350 | M21: =L21-Depr_Amort!M45 -> 900 | ... O21: =N21-Depr_Amort!O45 -> 0
A22: Other Long-Term Assets | C22: 15000 | E22: =SUM(C22:D22) -> 15000 | F22: =Inc_St!D8*other_longterm_assets*(1+other_longterm_assets_ann_incr)^(F5-1) -> 44000 | G22: =Inc_St!E8*other_longterm_assets*(1+other_longterm_assets_ann_incr)^(G5-1) -> 48642 | H22: =Inc_St!F8*other_longterm_assets*(1+other_longterm_assets_ann_incr)^(H5-1) -> 53773.731 | I22: =Inc_St!G8*other_longterm_assets*(1+other_longterm_assets_ann_incr)^(I5-1) -> 59446.86 | J22: =Inc_St!H8*other_longterm_assets*(1+other_longterm_assets_ann_incr)^(J5-1) -> 65718.503 | K22: =Inc_St!I8*other_longterm_assets*(1+other_longterm_assets_ann_incr)^(K5-1) -> 72651.805 | L22: =Inc_St!J8*other_longterm_assets*(1+other_longterm_assets_ann_incr)^(L5-1) -> 80316.571 | M22: =Inc_St!K8*other_longterm_assets*(1+other_longterm_assets_ann_incr)^(M5-1) -> 88789.969 | ... O22: =Inc_St!M8*other_longterm_assets*(1+other_longterm_assets_ann_incr)^(O5-1) -> 108512.91
A23: PP&E:
A24: Gross PP&E | C24: 500000 | D24: =Input!C49 -> 2450 | E24: =SUM(C24:D24) -> 502450 | F24: =E24 -> 502450 | G24: =F24+F25 -> 612450 | H24: =G24+G25 -> 733450 | I24: =H24+H25 -> 866550 | J24: =I24+I25 -> 1012960 | K24: =J24+J25 -> 1174011 | L24: =K24+K25 -> 1351167.1 | M24: =L24+L25 -> 1546038.8 | N24: =M24+M25 -> 1760397.7 | O24: =N24+N25 -> 1996192.5
A25: Capex | C25: 0 | E25: =SUM(C25:D25) -> 0 | F25: =Depr_Amort!B24 -> 110000 | G25: =Depr_Amort!B25 -> 121000 | H25: =Depr_Amort!B26 -> 133100 | I25: =Depr_Amort!B27 -> 146410 | J25: =Depr_Amort!B28 -> 161051 | K25: =Depr_Amort!B29 -> 177156.1 | L25: =Depr_Amort!B30 -> 194871.71 | M25: =Depr_Amort!B31 -> 214358.88 | N25: =Depr_Amort!B32 -> 235794.77 | O25: =Depr_Amort!B33 -> 259374.25
A26: Depreciation (Current) | C26: 0 | E26: =SUM(C26:D26) -> 0 | F26: =Depr_Amort!F39 -> 72745 | G26: =Depr_Amort!G39 -> 84845 | H26: =Depr_Amort!H39 -> 93718.333 | I26: =Depr_Amort!I39 -> 104176.19 | J26: =Depr_Amort!J39 -> 117597.11 | K26: =Depr_Amort!K39 -> 128669.36 | L26: =Depr_Amort!L39 -> 101352.48 | M26: =Depr_Amort!M39 -> 115643.07 | ... O26: =Depr_Amort!O39 -> 149482.15
A27: Accumulated Depreciation | C27: 25000 | E27: =SUM(C27:D27) -> 25000 | F27: =E27+F26 -> 97745 | G27: =F27+G26 -> 182590 | H27: =G27+H26 -> 276308.33 | I27: =H27+I26 -> 380484.52 | J27: =I27+J26 -> 498081.63 | K27: =J27+K26 -> 626750.99 | L27: =K27+L26 -> 728103.47 | M27: =L27+M26 -> 843746.54 | ... O27: =N27+O26 -> 1121096.3
A28: Net PP&E | C28: =C24+C25-C27 -> 475000 | E28: =E24+E25-E27 -> 477450 | F28: =F24+F25-F27 -> 514705 | G28: =G24+G25-G27 -> 550860 | H28: =H24+H25-H27 -> 590241.67 | I28: =I24+I25-I27 -> 632475.48 | J28: =J24+J25-J27 -> 675929.37 | K28: =K24+K25-K27 -> 724416.11 | L28: =L24+L25-L27 -> 817935.34 | ... O28: =O24+O25-O27 -> 1134470.4
A30: Total Non-Current Assets | C30: =SUM(C19,C20,C21,C22,C28) -> 510950 | E30: =SUM(E19,E20,E21,E22,E28) -> 716966 | F30: =SUM(F19,F20,F21,F22,F28) -> 781989.06 | G30: =SUM(G19,G20,G21,G22,G28) -> 821554.11 | H30: =SUM(H19,H20,H21,H22,H28) -> 864085.56 | I30: =SUM(I19,I20,I21,I22,I28) -> 910298.06 | J30: =SUM(J19,J20,J21,J22,J28) -> 958451.37 | K30: =SUM(K19,K20,K21,K22,K28) -> 1011421.4 | L30: =SUM(L19,L20,L21,L22,L28) -> 1111976.2 | ... O30: =SUM(O19,O20,O21,O22,O28) -> 1454820.1
A32: Total Assets | C32: =SUM(C16,C30) -> 813949 | D32: =SUM(D10:D31) -> 228516 | E32: =SUM(E16,E30) -> 1042465 | F32: =SUM(F16,F30) -> 1310489.1 | G32: =SUM(G16,G30) -> 1418152.3 | H32: =SUM(H16,H30) -> 1538556.6 | I32: =SUM(I16,I30) -> 1673831.1 | J32: =SUM(J16,J30) -> 1823856.2 | K32: =SUM(K16,K30) -> 1993364.6 | L32: =SUM(L16,L30) -> 2227252.8 | ... O32: =SUM(O16,O30) -> 3399985.4
A35: LIABILITIES & EQUITY
A37: Current Liabilities:
A38: Accounts payable | C38: 51800 | E38: =SUM(C38:D38) -> 51800 | F38: =(Inc_St!D10+F12-E12)*acc_payable*(1+acc_payable_ann_incr)^(F5-1) -> 74700.15 | G38: =(Inc_St!E10+G12-F12)*acc_payable*(1+acc_payable_ann_incr)^(G5-1) -> 85741.26 | H38: =(Inc_St!F10+H12-G12)*acc_payable*(1+acc_payable_ann_incr)^(H5-1) -> 96542.282 | I38: =(Inc_St!G10+I12-H12)*acc_payable*(1+acc_payable_ann_incr)^(I5-1) -> 108708.32 | J38: =(Inc_St!H10+J12-I12)*acc_payable*(1+acc_payable_ann_incr)^(J5-1) -> 122412.62 | K38: =(Inc_St!I10+K12-J12)*acc_payable*(1+acc_payable_ann_incr)^(K5-1) -> 137850.54 | L38: =(Inc_St!J10+L12-K12)*acc_payable*(1+acc_payable_ann_incr)^(L5-1) -> 155242.4 | M38: =(Inc_St!K10+M12-L12)*acc_payable*(1+acc_payable_ann_incr)^(M5-1) -> 174836.66 | ... O38: =(Inc_St!M10+O12-N12)*acc_payable*(1+acc_payable_ann_incr)^(O5-1) -> 221789.44
A39: Accrued expenses | C39: 24000 | E39: =SUM(C39:D39) -> 24000 | F39: =Inc_St!D8*acc_exp*(1+acc_exp_ann_incr)^(F5-1) -> 66000 | G39: =Inc_St!E8*acc_exp*(1+acc_exp_ann_incr)^(G5-1) -> 73689 | H39: =Inc_St!F8*acc_exp*(1+acc_exp_ann_incr)^(H5-1) -> 82273.769 | I39: =Inc_St!G8*acc_exp*(1+acc_exp_ann_incr)^(I5-1) -> 91858.663 | J39: =Inc_St!H8*acc_exp*(1+acc_exp_ann_incr)^(J5-1) -> 102560.2 | K39: =Inc_St!I8*acc_exp*(1+acc_exp_ann_incr)^(K5-1) -> 114508.46 | L39: =Inc_St!J8*acc_exp*(1+acc_exp_ann_incr)^(L5-1) -> 127848.7 | M39: =Inc_St!K8*acc_exp*(1+acc_exp_ann_incr)^(M5-1) -> 142743.07 | ... O39: =Inc_St!M8*acc_exp*(1+acc_exp_ann_incr)^(O5-1) -> 177939.55
A40: Other current liabilities | C40: 22000 | E40: =SUM(C40:D40) -> 22000 | F40: =Inc_St!D8*other_curr_liab*(1+other_curr_liab_ann_incr)^(F5-1) -> 88000 | G40: =Inc_St!E8*other_curr_liab*(1+other_curr_liab_ann_incr)^(G5-1) -> 97768 | H40: =Inc_St!F8*other_curr_liab*(1+other_curr_liab_ann_incr)^(H5-1) -> 108620.25 | I40: =Inc_St!G8*other_curr_liab*(1+other_curr_liab_ann_incr)^(I5-1) -> 120677.1 | J40: =Inc_St!H8*other_curr_liab*(1+other_curr_liab_ann_incr)^(J5-1) -> 134072.25 | K40: =Inc_St!I8*other_curr_liab*(1+other_curr_liab_ann_incr)^(K5-1) -> 148954.27 | L40: =Inc_St!J8*other_curr_liab*(1+other_curr_liab_ann_incr)^(L5-1) -> 165488.2 | M40: =Inc_St!K8*other_curr_liab*(1+other_curr_liab_ann_incr)^(M5-1) -> 183857.39 | ... O40: =Inc_St!M8*other_curr_liab*(1+other_curr_liab_ann_incr)^(O5-1) -> 226939.03
A42: Total Current Liabilities | C42: =SUM(C38:C40) -> 97800 | E42: =SUM(E38:E40) -> 97800 | F42: =SUM(F38:F40) -> 228700.15 | G42: =SUM(G38:G40) -> 257198.26 | H42: =SUM(H38:H40) -> 287436.3 | I42: =SUM(I38:I40) -> 321244.08 | J42: =SUM(J38:J40) -> 359045.07 | K42: =SUM(K38:K40) -> 401313.27 | L42: =SUM(L38:L40) -> 448579.29 | ... O42: =SUM(O38:O40) -> 626668.02
A44: Deferred Tax Liability | C44: 1400 | D44: =-C44-Input!C52 -> -122.5 | E44: =SUM(C44:D44) -> 1277.5 | F44: =E44+Income_Tax!D30 -> 5872.79 | G44: =F44+Income_Tax!E30 -> 6119.33 | H44: =G44+Income_Tax!F30 -> 6365.87 | I44: =H44+Income_Tax!G30 -> 8645.8822 | J44: =I44+Income_Tax!H30 -> 20303.036 | K44: =J44+Income_Tax!I30 -> 31977.69 | L44: =K44+Income_Tax!J30 -> 52836.927 | M44: =L44+Income_Tax!K30 -> 106242.26 | ... O44: =N44+Income_Tax!M30 -> 139034.95
A45: Long-Term Debt:
A46: Existing Debt | C46: 250000 | D46: =-Input!C14 -> -185000 | E46: =SUM(C46:D46) -> 65000 | F46: =E46-Cash_Flow!D85-Cash_Flow!D100 -> 57777.778 | G46: =F46-Cash_Flow!E85-Cash_Flow!E100 -> 0 | H46: =G46-Cash_Flow!F85-Cash_Flow!F100 -> 0 | I46: =H46-Cash_Flow!G85-Cash_Flow!G100 -> 0 | J46: =I46-Cash_Flow!H85-Cash_Flow!H100 -> 0 | K46: =J46-Cash_Flow!I85-Cash_Flow!I100 -> 0 | L46: =K46-Cash_Flow!J85-Cash_Flow!J100 -> 0 | M46: =L46-Cash_Flow!K85-Cash_Flow!K100 -> 0 | ... O46: =N46-Cash_Flow!M85-Cash_Flow!M100 -> 0
A47: =Input!A27 -> Bank Revolver | C47: 0 | D47: =Input!C27 -> 200887.5 | E47: =SUM(C47:D47) -> 200887.5 | F47: =E47+Cash_Flow!D96-Cash_Flow!D107 -> 213470.43 | G47: =F47+Cash_Flow!E96-Cash_Flow!E107 -> 213470.43 | H47: =G47+Cash_Flow!F96-Cash_Flow!F107 -> 213470.43 | I47: =H47+Cash_Flow!G96-Cash_Flow!G107 -> 213470.43 | J47: =I47+Cash_Flow!H96-Cash_Flow!H107 -> 213470.43 | K47: =J47+Cash_Flow!I96-Cash_Flow!I107 -> 161317.44 | L47: =K47+Cash_Flow!J96-Cash_Flow!J107 -> 57619.311 | M47: =L47+Cash_Flow!K96-Cash_Flow!K107 -> 0 | ... O47: =N47+Cash_Flow!M96-Cash_Flow!M107 -> 0
A48: =Input!A28 -> Term Loan "A" | C48: 0 | D48: =Input!C28 -> 80000 | E48: =SUM(C48:D48) -> 80000 | F48: =E48-Cash_Flow!D86-Cash_Flow!D101 -> 70000 | G48: =F48-Cash_Flow!E86-Cash_Flow!E101 -> 57263.572 | H48: =G48-Cash_Flow!F86-Cash_Flow!F101 -> 0 | I48: =H48-Cash_Flow!G86-Cash_Flow!G101 -> 0 | J48: =I48-Cash_Flow!H86-Cash_Flow!H101 -> 0 | K48: =J48-Cash_Flow!I86-Cash_Flow!I101 -> 0 | L48: =K48-Cash_Flow!J86-Cash_Flow!J101 -> 0 | M48: =L48-Cash_Flow!K86-Cash_Flow!K101 -> 0 | ... O48: =N48-Cash_Flow!M86-Cash_Flow!M101 -> 0
A49: =Input!A29 -> Term Loan "B" | C49: 0 | D49: =Input!C29 -> 55000 | E49: =SUM(C49:D49) -> 55000 | F49: =E49-Cash_Flow!D87-Cash_Flow!D102 -> 52800 | G49: =F49-Cash_Flow!E87-Cash_Flow!E102 -> 50600 | H49: =G49-Cash_Flow!F87-Cash_Flow!F102 -> 29091.092 | I49: =H49-Cash_Flow!G87-Cash_Flow!G102 -> 0 | J49: =I49-Cash_Flow!H87-Cash_Flow!H102 -> 0 | K49: =J49-Cash_Flow!I87-Cash_Flow!I102 -> 0 | L49: =K49-Cash_Flow!J87-Cash_Flow!J102 -> 0 | M49: =L49-Cash_Flow!K87-Cash_Flow!K102 -> 0 | ... O49: =N49-Cash_Flow!M87-Cash_Flow!M102 -> 0
A50: =Input!A30 -> Senior Notes | C50: 0 | D50: =Input!C30 -> 65000 | E50: =SUM(C50:D50) -> 65000 | F50: =E50-Cash_Flow!D88-Cash_Flow!D103 -> 65000 | G50: =F50-Cash_Flow!E88-Cash_Flow!E103 -> 65000 | H50: =G50-Cash_Flow!F88-Cash_Flow!F103 -> 65000 | I50: =H50-Cash_Flow!G88-Cash_Flow!G103 -> 5819.1933 | J50: =I50-Cash_Flow!H88-Cash_Flow!H103 -> 0 | K50: =J50-Cash_Flow!I88-Cash_Flow!I103 -> 0 | L50: =K50-Cash_Flow!J88-Cash_Flow!J103 -> 0 | M50: =L50-Cash_Flow!K88-Cash_Flow!K103 -> 0 | ... O50: =N50-Cash_Flow!M88-Cash_Flow!M103 -> 0
A51: =Input!A31 -> Subordinated Notes | C51: 0 | D51: =Input!C31 -> 40000 | E51: =SUM(C51:D51) -> 40000 | F51: =E51+Cash_Flow!D15-Cash_Flow!D89-Cash_Flow!D104 -> 41800 | G51: =F51+Cash_Flow!E15-Cash_Flow!E89-Cash_Flow!E104 -> 43681 | H51: =G51+Cash_Flow!F15-Cash_Flow!F89-Cash_Flow!F104 -> 45646.645 | I51: =H51+Cash_Flow!G15-Cash_Flow!G89-Cash_Flow!G104 -> 47700.744 | J51: =I51+Cash_Flow!H15-Cash_Flow!H89-Cash_Flow!H104 -> 2146.5335 | K51: =J51+Cash_Flow!I15-Cash_Flow!I89-Cash_Flow!I104 -> 0 | L51: =K51+Cash_Flow!J15-Cash_Flow!J89-Cash_Flow!J104 -> 0 | M51: =L51+Cash_Flow!K15-Cash_Flow!K89-Cash_Flow!K104 -> 0 | ... O51: =N51+Cash_Flow!M15-Cash_Flow!M89-Cash_Flow!M104 -> 0
A52: =Input!A32 -> Mezzanine Debt | C52: 0 | D52: =Input!C32 -> 70000 | E52: =SUM(C52:D52) -> 70000 | F52: =E52+Cash_Flow!D16-Cash_Flow!D90-Cash_Flow!D105 -> 73150 | G52: =F52+Cash_Flow!E16-Cash_Flow!E90-Cash_Flow!E105 -> 76441.75 | H52: =G52+Cash_Flow!F16-Cash_Flow!F90-Cash_Flow!F105 -> 79881.629 | I52: =H52+Cash_Flow!G16-Cash_Flow!G90-Cash_Flow!G105 -> 83476.302 | J52: =I52+Cash_Flow!H16-Cash_Flow!H90-Cash_Flow!H105 -> 36453.864 | K52: =J52+Cash_Flow!I16-Cash_Flow!I90-Cash_Flow!I105 -> 0 | L52: =K52+Cash_Flow!J16-Cash_Flow!J90-Cash_Flow!J105 -> 0 | M52: =L52+Cash_Flow!K16-Cash_Flow!K90-Cash_Flow!K105 -> 0 | ... O52: =N52+Cash_Flow!M16-Cash_Flow!M90-Cash_Flow!M105 -> 0
A53: =Input!A33 -> Seller Notes | C53: 0 | D53: =Input!C33 -> 25000 | E53: =SUM(C53:D53) -> 25000 | F53: =E53+Cash_Flow!D17-Cash_Flow!D91-Cash_Flow!D106 -> 22680.176 | G53: =F53+Cash_Flow!E17-Cash_Flow!E91-Cash_Flow!E106 -> 20235.278 | H53: =G53+Cash_Flow!F17-Cash_Flow!F91-Cash_Flow!F106 -> 17658.563 | I53: =H53+Cash_Flow!G17-Cash_Flow!G91-Cash_Flow!G106 -> 14942.923 | J53: =I53+Cash_Flow!H17-Cash_Flow!H91-Cash_Flow!H106 -> 12080.869 | K53: =J53+Cash_Flow!I17-Cash_Flow!I91-Cash_Flow!I106 -> 0 | L53: =K53+Cash_Flow!J17-Cash_Flow!J91-Cash_Flow!J106 -> 0 | M53: =L53+Cash_Flow!K17-Cash_Flow!K91-Cash_Flow!K106 -> 0 | ... O53: =N53+Cash_Flow!M17-Cash_Flow!M91-Cash_Flow!M106 -> 0
A54: Total Long Term Debt | C54: =SUM(C46:C53) -> 250000 | E54: =SUM(E46:E53) -> 600887.5 | F54: =SUM(F46:F53) -> 596678.39 | G54: =SUM(G46:G53) -> 526692.03 | H54: =SUM(H46:H53) -> 450748.36 | I54: =SUM(I46:I53) -> 365409.59 | J54: =SUM(J46:J53) -> 264151.7 | K54: =SUM(K46:K53) -> 161317.44 | L54: =SUM(L46:L53) -> 57619.311 | ... O54: =SUM(O46:O53) -> 0
A56: Total Long-Term Liabilities | C56: =SUM(C44,C54) -> 251400 | E56: =SUM(E44,E54) -> 602165 | F56: =SUM(F44,F54) -> 602551.18 | G56: =SUM(G44,G54) -> 532811.36 | H56: =SUM(H44,H54) -> 457114.23 | I56: =SUM(I44,I54) -> 374055.48 | J56: =SUM(J44,J54) -> 284454.74 | K56: =SUM(K44,K54) -> 193295.13 | L56: =SUM(L44,L54) -> 110456.24 | ... O56: =SUM(O44,O54) -> 139034.95
A58: Total Liabilities | C58: =SUM(C42,C56) -> 349200 | E58: =SUM(E42,E56) -> 699965 | F58: =SUM(F42,F56) -> 831251.33 | G58: =SUM(G42,G56) -> 790009.62 | H58: =SUM(H42,H56) -> 744550.53 | I58: =SUM(I42,I56) -> 695299.56 | J58: =SUM(J42,J56) -> 643499.81 | K58: =SUM(K42,K56) -> 594608.4 | L58: =SUM(L42,L56) -> 559035.53 | ... O58: =SUM(O42,O56) -> 765702.97
A60: Shareholder's Equity:
A61: =Input!A35 -> Preferred Stock | C61: 0 | D61: =Input!C35 -> 60000 | E61: =SUM(C61:D61) -> 60000 | F61: =E61+Cash_Flow!D18-Cash_Flow!D92 -> 64200 | G61: =F61+Cash_Flow!E18-Cash_Flow!E92 -> 68694 | H61: =G61+Cash_Flow!F18-Cash_Flow!F92 -> 73502.58 | I61: =H61+Cash_Flow!G18-Cash_Flow!G92 -> 78647.761 | J61: =I61+Cash_Flow!H18-Cash_Flow!H92 -> 84153.104 | K61: =J61+Cash_Flow!I18-Cash_Flow!I92 -> 84153.104 | L61: =K61+Cash_Flow!J18-Cash_Flow!J92 -> 84153.104 | M61: =L61+Cash_Flow!K18-Cash_Flow!K92 -> 84153.104 | ... O61: =N61+Cash_Flow!M18-Cash_Flow!M92 -> 84153.104
A62: Common Equity | C62: 440000 | D62: =-C62+SUM(Input!C37:C39) -> -155000 | E62: =SUM(C62:D62) -> 285000 | F62: =E62 -> 285000 | G62: =F62 -> 285000 | H62: =G62 -> 285000 | I62: =H62 -> 285000 | J62: =I62 -> 285000 | K62: =J62 -> 285000 | L62: =K62 -> 285000 | M62: =L62 -> 285000 | ... O62: =N62 -> 285000
A63: Retained Earnings | C63: 24749 | D63: =-C63-Input!C16-MIN(0,Input!C53) -> -27249 | E63: =SUM(C63:D63) -> -2500 | F63: =E63+Inc_St!D49 -> 130037.73 | G63: =F63+Inc_St!E49 -> 274448.63 | H63: =G63+Inc_St!F49 -> 435503.49 | I63: =H63+Inc_St!G49 -> 614883.8 | J63: =I63+Inc_St!H49 -> 811203.25 | K63: =J63+Inc_St!I49 -> 1029603.1 | L63: =K63+Inc_St!J49 -> 1299064.2 | M63: =L63+Inc_St!K49 -> 1593876.8 | ... O63: =N63+Inc_St!M49 -> 2265129.4
A65: Total Shareholder's Equity | C65: =SUM(C61:C63) -> 464749 | E65: =SUM(E61:E63) -> 342500 | F65: =SUM(F61:F63) -> 479237.73 | G65: =SUM(G61:G63) -> 628142.63 | H65: =SUM(H61:H63) -> 794006.07 | I65: =SUM(I61:I63) -> 978531.56 | J65: =SUM(J61:J63) -> 1180356.4 | K65: =SUM(K61:K63) -> 1398756.2 | L65: =SUM(L61:L63) -> 1668217.3 | ... O65: =SUM(O61:O63) -> 2634282.5
A67: Total Liabilities & Equity | C67: =SUM(C58,C65) -> 813949 | D67: =SUM(D38:D66) -> 228516 | E67: =SUM(E58,E65) -> 1042465 | F67: =SUM(F58,F65) -> 1310489.1 | G67: =SUM(G58,G65) -> 1418152.3 | H67: =SUM(H58,H65) -> 1538556.6 | I67: =SUM(I58,I65) -> 1673831.1 | J67: =SUM(J58,J65) -> 1823856.2 | K67: =SUM(K58,K65) -> 1993364.6 | L67: =SUM(L58,L65) -> 2227252.8 | ... O67: =SUM(O58,O65) -> 3399985.4
A70: Balance Sheet Check | C70: =C32-C67 -> 0 | D70: =D32-D67 -> 0 | E70: =E32-E67 -> 0 | F70: =F32-F67 -> 0 | G70: =G32-G67 -> 0 | H70: =H32-H67 -> 0 | I70: =I32-I67 -> 0 | J70: =J32-J67 -> 0 | ... O70: =O32-O67 -> 0

Sheet Cash_Flow
A2: Cash Flows
A4: Year | D4: =year1 -> 2010 | E4: =D4+1 -> 2011 | F4: =E4+1 -> 2012 | G4: =F4+1 -> 2013 | H4: =G4+1 -> 2014 | I4: =H4+1 -> 2015 | J4: =I4+1 -> 2016 | K4: =J4+1 -> 2017 | L4: =K4+1 -> 2018 | M4: =L4+1 -> 2019
A5: Year No. | D5: 1 | E5: =D5+1 -> 2 | F5: =E5+1 -> 3 | G5: =F5+1 -> 4 | H5: =G5+1 -> 5 | I5: =H5+1 -> 6 | J5: =I5+1 -> 7 | K5: =J5+1 -> 8 | L5: =K5+1 -> 9 | M5: =L5+1 -> 10
A7: Cash flows from operating activities
A9: =Inc_St!A49 -> Net Income to Common Shareholders | D9: =Inc_St!D49 -> 132537.73 | E9: =Inc_St!E49 -> 144410.9 | F9: =Inc_St!F49 -> 161054.86 | G9: =Inc_St!G49 -> 179380.31 | H9: =Inc_St!H49 -> 196319.45 | I9: =Inc_St!I49 -> 218399.89 | J9: =Inc_St!J49 -> 269461.08 | K9: =Inc_St!K49 -> 294812.6 | ... M9: =Inc_St!M49 -> 347729.15
A11: Non-cash adjustments:
A12: Depreciation and amortization | D12: =Inc_St!D20 -> 72924.167 | E12: =Inc_St!E20 -> 85024.167 | F12: =Inc_St!F20 -> 93897.5 | G12: =Inc_St!G20 -> 104355.36 | H12: =Inc_St!H20 -> 117776.27 | I12: =Inc_St!I20 -> 128848.53 | J12: =Inc_St!J20 -> 101531.64 | K12: =Inc_St!K20 -> 115822.24 | ... M12: =Inc_St!M20 -> 149661.32
A13: Amortization of Capitalized Financing Costs | D13: =Inc_St!D36 -> 1052.7778 | E13: =Inc_St!E36 -> 1052.7778 | F13: =Inc_St!F36 -> 1802.7778 | G13: =Inc_St!G36 -> 1515.2778 | H13: =Inc_St!H36 -> 1393.0556 | I13: =Inc_St!I36 -> 2270.8333 | J13: =Inc_St!J36 -> 450 | K13: =Inc_St!K36 -> 450 | ... M13: =Inc_St!M36 -> 450
A14: Increase (Decrease) in Deferred Tax Liability | D14: =Income_Tax!D30 -> 4595.29 | E14: =Income_Tax!E30 -> 246.54 | F14: =Income_Tax!F30 -> 246.54 | G14: =Income_Tax!G30 -> 2280.0122 | H14: =Income_Tax!H30 -> 11657.154 | I14: =Income_Tax!I30 -> 11674.654 | J14: =Income_Tax!J30 -> 20859.237 | K14: =Income_Tax!K30 -> 53405.334 | ... M14: =Income_Tax!M30 -> -4989.4325
A15: ="Accrued Interest "&Bal_Sheet!A51 -> Accrued Interest Subordinated Notes | D15: =IF(sub_notes_years_PIK>=D$5,Inc_St!D30,0) -> 1800 | E15: =IF(sub_notes_years_PIK>=E5,Inc_St!E30,0) -> 1881 | F15: =IF(sub_notes_years_PIK>=F5,Inc_St!F30,0) -> 1965.645 | G15: =IF(sub_notes_years_PIK>=G5,Inc_St!G30,0) -> 2054.099 | H15: =IF(sub_notes_years_PIK>=H5,Inc_St!H30,0) -> 2146.5335 | I15: =IF(sub_notes_years_PIK>=I5,Inc_St!I30,0) -> 0 | J15: =IF(sub_notes_years_PIK>=J5,Inc_St!J30,0) -> 0 | K15: =IF(sub_notes_years_PIK>=K5,Inc_St!K30,0) -> 0 | L15: =IF(sub_notes_years_PIK>=L5,Inc_St!L30,0) -> 0 | M15: =IF(sub_notes_years_PIK>=M5,Inc_St!M30,0) -> 0
A16: ="Accrued Interest "&Bal_Sheet!A52 -> Accrued Interest Mezzanine Debt | D16: =IF(mezzdebt_years_PIK>=D$5,Inc_St!D31,0) -> 3150 | E16: =IF(mezzdebt_years_PIK>=E$5,Inc_St!E31,0) -> 3291.75 | F16: =IF(mezzdebt_years_PIK>=F$5,Inc_St!F31,0) -> 3439.8787 | G16: =IF(mezzdebt_years_PIK>=G$5,Inc_St!G31,0) -> 3594.6733 | H16: =IF(mezzdebt_years_PIK>=H$5,Inc_St!H31,0) -> 3756.4336 | I16: =IF(mezzdebt_years_PIK>=I$5,Inc_St!I31,0) -> 0 | J16: =IF(mezzdebt_years_PIK>=J$5,Inc_St!J31,0) -> 0 | K16: =IF(mezzdebt_years_PIK>=K$5,Inc_St!K31,0) -> 0 | ... M16: =IF(mezzdebt_years_PIK>=M$5,Inc_St!M31,0) -> 0
A17: ="Accrued Interest "&Bal_Sheet!A53 -> Accrued Interest Seller Notes | D17: =IF(seller_notes_years_PIK>=D$5,Inc_St!D32,0) -> 1251.6046 | E17: =IF(seller_notes_years_PIK>=E$5,Inc_St!E32,0) -> 1126.5307 | F17: =IF(seller_notes_years_PIK>=F$5,Inc_St!F32,0) -> 994.71333 | G17: =IF(seller_notes_years_PIK>=G$5,Inc_St!G32,0) -> 855.78901 | H17: =IF(seller_notes_years_PIK>=H$5,Inc_St!H32,0) -> 709.37456 | I17: =IF(seller_notes_years_PIK>=I$5,Inc_St!I32,0) -> 0 | J17: =IF(seller_notes_years_PIK>=J$5,Inc_St!J32,0) -> 0 | K17: =IF(seller_notes_years_PIK>=K$5,Inc_St!K32,0) -> 0 | ... M17: =IF(seller_notes_years_PIK>=M$5,Inc_St!M32,0) -> 0
A18: ="Accrued Interest "&Bal_Sheet!A61 -> Accrued Interest Preferred Stock | D18: =IF(pref_stock_years_PIK>=D$5,Inc_St!D46,0) -> 4200 | E18: =IF(pref_stock_years_PIK>=E$5,Inc_St!E46,0) -> 4494 | F18: =IF(pref_stock_years_PIK>=F$5,Inc_St!F46,0) -> 4808.58 | G18: =IF(pref_stock_years_PIK>=G$5,Inc_St!G46,0) -> 5145.1806 | H18: =IF(pref_stock_years_PIK>=H$5,Inc_St!H46,0) -> 5505.3432 | I18: =IF(pref_stock_years_PIK>=I$5,Inc_St!I46,0) -> 0 | J18: =IF(pref_stock_years_PIK>=J$5,Inc_St!J46,0) -> 0 | K18: =IF(pref_stock_years_PIK>=K$5,Inc_St!K46,0) -> 0 | ... M18: =IF(pref_stock_years_PIK>=M$5,Inc_St!M46,0) -> 0
A20: Changes in operating assets and liabilities:
A21: (Increase) decrease in accounts receivable | D21: =-(Bal_Sheet!F11-Bal_Sheet!E11) -> -113000 | E21: =-(Bal_Sheet!G11-Bal_Sheet!F11) -> -30690 | F21: =-(Bal_Sheet!H11-Bal_Sheet!G11) -> -35446.95 | G21: =-(Bal_Sheet!I11-Bal_Sheet!H11) -> -40941.227 | H21: =-(Bal_Sheet!J11-Bal_Sheet!I11) -> -47287.117 | I21: =-(Bal_Sheet!K11-Bal_Sheet!J11) -> -54616.621 | J21: =-(Bal_Sheet!L11-Bal_Sheet!K11) -> -63082.197 | K21: =-(Bal_Sheet!M11-Bal_Sheet!L11) -> -72859.937 | ... M21: =-(Bal_Sheet!O11-Bal_Sheet!N11) -> -97196.978
A22: (Increase) decrease in inventories | D22: =-(Bal_Sheet!F12-Bal_Sheet!E12) -> -3001 | E22: =-(Bal_Sheet!G12-Bal_Sheet!F12) -> -14539.14 | F22: =-(Bal_Sheet!H12-Bal_Sheet!G12) -> -16674.358 | G22: =-(Bal_Sheet!I12-Bal_Sheet!H12) -> -19123.154 | H22: =-(Bal_Sheet!J12-Bal_Sheet!I12) -> -21931.581 | I22: =-(Bal_Sheet!K12-Bal_Sheet!J12) -> -25152.453 | J22: =-(Bal_Sheet!L12-Bal_Sheet!K12) -> -28846.342 | K22: =-(Bal_Sheet!M12-Bal_Sheet!L12) -> -33082.716 | ... M22: =-(Bal_Sheet!O12-Bal_Sheet!N12) -> -43513.294
A23: (Increase) decrease in prepaids & other assets | D23: =-(Bal_Sheet!F13-Bal_Sheet!E13)-(Bal_Sheet!F14-Bal_Sheet!E14) -> -114500 | E23: =-(Bal_Sheet!G13-Bal_Sheet!F13)-(Bal_Sheet!G14-Bal_Sheet!F14) -> -22869 | F23: =-(Bal_Sheet!H13-Bal_Sheet!G13)-(Bal_Sheet!H14-Bal_Sheet!G14) -> -25751.583 | G23: =-(Bal_Sheet!I13-Bal_Sheet!H13)-(Bal_Sheet!I14-Bal_Sheet!H14) -> -28997.643 | H23: =-(Bal_Sheet!J13-Bal_Sheet!I13)-(Bal_Sheet!J14-Bal_Sheet!I14) -> -32653.029 | I23: =-(Bal_Sheet!K13-Bal_Sheet!J13)-(Bal_Sheet!K14-Bal_Sheet!J14) -> -36769.376 | J23: =-(Bal_Sheet!L13-Bal_Sheet!K13)-(Bal_Sheet!L14-Bal_Sheet!K14) -> -41404.834 | K23: =-(Bal_Sheet!M13-Bal_Sheet!L13)-(Bal_Sheet!M14-Bal_Sheet!L14) -> -46624.89 | ... M23: =-(Bal_Sheet!O13-Bal_Sheet!N13)-(Bal_Sheet!O14-Bal_Sheet!N14) -> -59123.12
A24: Increase (decrease) in accounts payable | D24: =Bal_Sheet!F38-Bal_Sheet!E38 -> 22900.15 | E24: =Bal_Sheet!G38-Bal_Sheet!F38 -> 11041.11 | F24: =Bal_Sheet!H38-Bal_Sheet!G38 -> 10801.023 | G24: =Bal_Sheet!I38-Bal_Sheet!H38 -> 12166.038 | H24: =Bal_Sheet!J38-Bal_Sheet!I38 -> 13704.3 | I24: =Bal_Sheet!K38-Bal_Sheet!J38 -> 15437.921 | J24: =Bal_Sheet!L38-Bal_Sheet!K38 -> 17391.854 | K24: =Bal_Sheet!M38-Bal_Sheet!L38 -> 19594.267 | ... M24: =Bal_Sheet!O38-Bal_Sheet!N38 -> 24875.818
A25: Increase (decrease) in accrued exp & other liabilities | D25: =(Bal_Sheet!F39-Bal_Sheet!E39)+(Bal_Sheet!F40-Bal_Sheet!E40) -> 108000 | E25: =(Bal_Sheet!G39-Bal_Sheet!F39)+(Bal_Sheet!G40-Bal_Sheet!F40) -> 17457 | F25: =(Bal_Sheet!H39-Bal_Sheet!G39)+(Bal_Sheet!H40-Bal_Sheet!G40) -> 19437.017 | G25: =(Bal_Sheet!I39-Bal_Sheet!H39)+(Bal_Sheet!I40-Bal_Sheet!H40) -> 21641.742 | H25: =(Bal_Sheet!J39-Bal_Sheet!I39)+(Bal_Sheet!J40-Bal_Sheet!I40) -> 24096.692 | I25: =(Bal_Sheet!K39-Bal_Sheet!J39)+(Bal_Sheet!K40-Bal_Sheet!J40) -> 26830.283 | J25: =(Bal_Sheet!L39-Bal_Sheet!K39)+(Bal_Sheet!L40-Bal_Sheet!K40) -> 29874.16 | K25: =(Bal_Sheet!M39-Bal_Sheet!L39)+(Bal_Sheet!M40-Bal_Sheet!L40) -> 33263.563 | ... M25: =(Bal_Sheet!O39-Bal_Sheet!N39)+(Bal_Sheet!O40-Bal_Sheet!N40) -> 41240.389
A27: Net cash provided by (used in) operating activities | D27: =SUM(D9:D26) -> 121910.72 | E27: =SUM(E9:E26) -> 201927.63 | F27: =SUM(F9:F26) -> 220575.64 | G27: =SUM(G9:G26) -> 243926.46 | H27: =SUM(H9:H26) -> 275192.88 | I27: =SUM(I9:I26) -> 286923.66 | J27: =SUM(J9:J26) -> 306234.6 | K27: =SUM(K9:K26) -> 364780.46 | ... M27: =SUM(M9:M26) -> 359133.86
A29: Cash flows from investing activities
A30: Purchase of property & equipment | D30: =-Bal_Sheet!F25 -> -110000 | E30: =-Bal_Sheet!G25 -> -121000 | F30: =-Bal_Sheet!H25 -> -133100 | G30: =-Bal_Sheet!I25 -> -146410 | H30: =-Bal_Sheet!J25 -> -161051 | I30: =-Bal_Sheet!K25 -> -177156.1 | J30: =-Bal_Sheet!L25 -> -194871.71 | K30: =-Bal_Sheet!M25 -> -214358.88 | ... M30: =-Bal_Sheet!O25 -> -259374.25
A31: (Increase) decrease in other long-term assets | D31: =-(Bal_Sheet!F22-Bal_Sheet!E22) -> -29000 | E31: =-(Bal_Sheet!G22-Bal_Sheet!F22) -> -4642 | F31: =-(Bal_Sheet!H22-Bal_Sheet!G22) -> -5131.731 | G31: =-(Bal_Sheet!I22-Bal_Sheet!H22) -> -5673.1286 | H31: =-(Bal_Sheet!J22-Bal_Sheet!I22) -> -6271.6437 | I31: =-(Bal_Sheet!K22-Bal_Sheet!J22) -> -6933.3021 | J31: =-(Bal_Sheet!L22-Bal_Sheet!K22) -> -7664.7655 | K31: =-(Bal_Sheet!M22-Bal_Sheet!L22) -> -8473.3982 | ... M31: =-(Bal_Sheet!O22-Bal_Sheet!N22) -> -10355.596
A33: Net cash provided by (used in) investing activities | D33: =SUM(D30:D32) -> -139000 | E33: =SUM(E30:E32) -> -125642 | F33: =SUM(F30:F32) -> -138231.73 | G33: =SUM(G30:G32) -> -152083.13 | H33: =SUM(H30:H32) -> -167322.64 | I33: =SUM(I30:I32) -> -184089.4 | J33: =SUM(J30:J32) -> -202536.48 | K33: =SUM(K30:K32) -> -222832.28 | ... M33: =SUM(M30:M32) -> -269729.84
A35: Cash flows from financing activities
A36: ="Increase (decrease) in "&Bal_Sheet!A46 -> Increase (decrease) in Existing Debt | D36: =-D85-D100 -> -7222.2222 | E36: =-E85-E100 -> -57777.778 | F36: =-F85-F100 -> 0 | G36: =-G85-G100 -> 0 | H36: =-H85-H100 -> 0 | I36: =-I85-I100 -> 0 | J36: =-J85-J100 -> 0 | K36: =-K85-K100 -> 0 | ... M36: =-M85-M100 -> 0
A37: ="Increase (decrease) in "&Bal_Sheet!A48 -> Increase (decrease) in Term Loan "A" | D37: =-D86-D101 -> -10000 | E37: =-E86-E101 -> -12736.428 | F37: =-F86-F101 -> -57263.572 | G37: =-G86-G101 -> 0 | H37: =-H86-H101 -> 0 | I37: =-I86-I101 -> 0 | J37: =-J86-J101 -> 0 | K37: =-K86-K101 -> 0 | ... M37: =-M86-M101 -> 0
A38: ="Increase (decrease) in "&Bal_Sheet!A49 -> Increase (decrease) in Term Loan "B" | D38: =-D87-D102 -> -2200 | E38: =-E87-E102 -> -2200 | F38: =-F87-F102 -> -21508.908 | G38: =-G87-G102 -> -29091.092 | H38: =-H87-H102 -> 0 | I38: =-I87-I102 -> 0 | J38: =-J87-J102 -> 0 | K38: =-K87-K102 -> 0 | ... M38: =-M87-M102 -> 0
A39: ="Increase (decrease) in "&Bal_Sheet!A50 -> Increase (decrease) in Senior Notes | D39: =-D88-D103 -> 0 | E39: =-E88-E103 -> 0 | F39: =-F88-F103 -> 0 | G39: =-G88-G103 -> -59180.807 | H39: =-H88-H103 -> -5819.1933 | I39: =-I88-I103 -> 0 | J39: =-J88-J103 -> 0 | K39: =-K88-K103 -> 0 | ... M39: =-M88-M103 -> 0
A40: ="Increase (decrease) in "&Bal_Sheet!A51 -> Increase (decrease) in Subordinated Notes | D40: =-D89-D104 -> 0 | E40: =-E89-E104 -> 0 | F40: =-F89-F104 -> 0 | G40: =-G89-G104 -> 0 | H40: =-H89-H104 -> -47700.744 | I40: =-I89-I104 -> -2146.5335 | J40: =-J89-J104 -> 0 | K40: =-K89-K104 -> 0 | ... M40: =-M89-M104 -> 0
A41: ="Increase (decrease) in "&Bal_Sheet!A52 -> Increase (decrease) in Mezzanine Debt | D41: =-D90-D105 -> 0 | E41: =-E90-E105 -> 0 | F41: =-F90-F105 -> 0 | G41: =-G90-G105 -> 0 | H41: =-H90-H105 -> -50778.871 | I41: =-I90-I105 -> -36453.864 | J41: =-J90-J105 -> 0 | K41: =-K90-K105 -> 0 | ... M41: =-M90-M105 -> 0
A42: ="Increase (decrease) in "&Bal_Sheet!A53 -> Increase (decrease) in Seller Notes | D42: =-D91-D106 -> -3571.4286 | E42: =-E91-E106 -> -3571.4286 | F42: =-F91-F106 -> -3571.4286 | G42: =-G91-G106 -> -3571.4286 | H42: =-H91-H106 -> -3571.4286 | I42: =-I91-I106 -> -12080.869 | J42: =-J91-J106 -> 0 | K42: =-K91-K106 -> 0 | ... M42: =-M91-M106 -> 0
A43: ="Increase (decrease) in "&Bal_Sheet!A61 -> Increase (decrease) in Preferred Stock | D43: =-D92 -> 0 | E43: =-E92 -> 0 | F43: =-F92 -> 0 | G43: =-G92 -> 0 | H43: =-H92 -> 0 | I43: =-I92 -> 0 | J43: =-J92 -> 0 | K43: =-K92 -> 0 | ... M43: =-M92 -> 0
A45: Net cash provided by (used in) financing activities | D45: =SUM(D36:D44) -> -22993.651 | E45: =SUM(E36:E44) -> -76285.635 | F45: =SUM(F36:F44) -> -82343.908 | G45: =SUM(G36:G44) -> -91843.327 | H45: =SUM(H36:H44) -> -107870.24 | I45: =SUM(I36:I44) -> -50681.267 | J45: =SUM(J36:J44) -> 0 | K45: =SUM(K36:K44) -> 0 | ... M45: =SUM(M36:M44) -> 0
A47: Net increase (decrease) in cash | D47: =D27+D33+D45 -> -40082.932 | E47: =E27+E33+E45 -> 0 | F47: =F27+F33+F45 -> 0 | G47: =G27+G33+G45 -> 0 | H47: =H27+H33+H45 -> 0 | I47: =I27+I33+I45 -> 52152.993 | J47: =J27+J33+J45 -> 103698.13 | K47: =K27+K33+K45 -> 141948.18 | ... M47: =M27+M33+M45 -> 89404.016
A49: Cash at beginning of year | D49: =Bal_Sheet!E10 -> 77500 | E49: =D55 -> 50000 | F49: =E55 -> 50000 | G49: =F55 -> 50000 | H49: =G55 -> 50000 | I49: =H55 -> 50000 | J49: =I55 -> 50000 | K49: =J55 -> 50000 | L49: =K55 -> 134328.87 | M49: =L55 -> 263486
A51: ="Cash available for "&Bal_Sheet!A47 -> Cash available for Bank Revolver | D51: =D47+D49 -> 37417.068 | E51: =E47+E49 -> 50000 | F51: =F47+F49 -> 50000 | G51: =G47+G49 -> 50000 | H51: =H47+H49 -> 50000 | I51: =I47+I49 -> 102152.99 | J51: =J47+J49 -> 153698.13 | K51: =K47+K49 -> 191948.18 | ... M51: =M47+M49 -> 352890.02
A53: ="Added (retired) "&Bal_Sheet!A47 -> Added (retired) Bank Revolver | D53: =IF(cash_min=1,MIN(-MIN(Bal_Sheet!E47,D51-cash_min_amt),(revolver_limit-Bal_Sheet!E47)),MIN(-MIN(Bal_Sheet!E47,D51),(revolver_limit-Bal_Sheet!E47))) -> 12582.932 | E53: =IF(cash_min=1,MIN(-MIN(Bal_Sheet!F47,E51-cash_min_amt),(revolver_limit-Bal_Sheet!F47)),MIN(-MIN(Bal_Sheet!F47,E51),(revolver_limit-Bal_Sheet!F47))) -> 0 | F53: =IF(cash_min=1,MIN(-MIN(Bal_Sheet!G47,F51-cash_min_amt),(revolver_limit-Bal_Sheet!G47)),MIN(-MIN(Bal_Sheet!G47,F51),(revolver_limit-Bal_Sheet!G47))) -> 0 | G53: =IF(cash_min=1,MIN(-MIN(Bal_Sheet!H47,G51-cash_min_amt),(revolver_limit-Bal_Sheet!H47)),MIN(-MIN(Bal_Sheet!H47,G51),(revolver_limit-Bal_Sheet!H47))) -> 0 | H53: =IF(cash_min=1,MIN(-MIN(Bal_Sheet!I47,H51-cash_min_amt),(revolver_limit-Bal_Sheet!I47)),MIN(-MIN(Bal_Sheet!I47,H51),(revolver_limit-Bal_Sheet!I47))) -> 0 | I53: =IF(cash_min=1,MIN(-MIN(Bal_Sheet!J47,I51-cash_min_amt),(revolver_limit-Bal_Sheet!J47)),MIN(-MIN(Bal_Sheet!J47,I51),(revolver_limit-Bal_Sheet!J47))) -> -52152.993 | J53: =IF(cash_min=1,MIN(-MIN(Bal_Sheet!K47,J51-cash_min_amt),(revolver_limit-Bal_Sheet!K47)),MIN(-MIN(Bal_Sheet!K47,J51),(revolver_limit-Bal_Sheet!K47))) -> -103698.13 | K53: =IF(cash_min=1,MIN(-MIN(Bal_Sheet!L47,K51-cash_min_amt),(revolver_limit-Bal_Sheet!L47)),MIN(-MIN(Bal_Sheet!L47,K51),(revolver_limit-Bal_Sheet!L47))) -> -57619.311 | ... M53: =IF(cash_min=1,MIN(-MIN(Bal_Sheet!N47,M51-cash_min_amt),(revolver_limit-Bal_Sheet!N47)),MIN(-MIN(Bal_Sheet!N47,M51),(revolver_limit-Bal_Sheet!N47))) -> 0
A55: Cash at end of year | D55: =D51+D53 -> 50000 | E55: =E51+E53 -> 50000 | F55: =F51+F53 -> 50000 | G55: =G51+G53 -> 50000 | H55: =H51+H53 -> 50000 | I55: =I51+I53 -> 50000 | J55: =J51+J53 -> 50000 | K55: =K51+K53 -> 134328.87 | ... M55: =M51+M53 -> 352890.02
A59: Free Cash Flows
A61: EBIT | D61: =Inc_St!D22 -> 246075.83 | E61: =Inc_St!E22 -> 263449.78 | F61: =Inc_St!F22 -> 286746.43 | G61: =Inc_St!G22 -> 311398.13 | H61: =Inc_St!H22 -> 336291.57 | I61: =Inc_St!I22 -> 367027.21 | J61: =Inc_St!J22 -> 439959.86 | K61: =Inc_St!K22 -> 475435.06 | ... M61: =Inc_St!M22 -> 555099.8
A62: Add: Amortization of non-deductible goodwill & intangibles | D62: =IF(goodwill_intang_deductible=1,0,Depr_Amort!F43+Depr_Amort!F42) -> 0 | E62: =IF(goodwill_intang_deductible=1,0,Depr_Amort!G43+Depr_Amort!G42) -> 0 | F62: =IF(goodwill_intang_deductible=1,0,Depr_Amort!H43+Depr_Amort!H42) -> 0 | G62: =IF(goodwill_intang_deductible=1,0,Depr_Amort!I43+Depr_Amort!I42) -> 0 | H62: =IF(goodwill_intang_deductible=1,0,Depr_Amort!J43+Depr_Amort!J42) -> 0 | I62: =IF(goodwill_intang_deductible=1,0,Depr_Amort!K43+Depr_Amort!K42) -> 0 | J62: =IF(goodwill_intang_deductible=1,0,Depr_Amort!L43+Depr_Amort!L42) -> 0 | K62: =IF(goodwill_intang_deductible=1,0,Depr_Amort!M43+Depr_Amort!M42) -> 0 | ... M62: =IF(goodwill_intang_deductible=1,0,Depr_Amort!O43+Depr_Amort!O42) -> 0
A63: EBIT (Adj) | D63: =SUM(D61:D62) -> 246075.83 | E63: =SUM(E61:E62) -> 263449.78 | F63: =SUM(F61:F62) -> 286746.43 | G63: =SUM(G61:G62) -> 311398.13 | H63: =SUM(H61:H62) -> 336291.57 | I63: =SUM(I61:I62) -> 367027.21 | J63: =SUM(J61:J62) -> 439959.86 | K63: =SUM(K61:K62) -> 475435.06 | ... M63: =SUM(M61:M62) -> 555099.8
A64: Less: Tax on EBIT (Adj) | D64: =D63*tax_rate -> 86126.542 | E64: =E63*tax_rate -> 92207.424 | F64: =F63*tax_rate -> 100361.25 | G64: =G63*tax_rate -> 108989.35 | H64: =H63*tax_rate -> 117702.05 | I64: =I63*tax_rate -> 128459.52 | J64: =J63*tax_rate -> 153985.95 | K64: =K63*tax_rate -> 166402.27 | ... M64: =M63*tax_rate -> 194284.93
A65: Unlevered Net Income | D65: =D63-D64 -> 159949.29 | E65: =E63-E64 -> 171242.36 | F65: =F63-F64 -> 186385.18 | G65: =G63-G64 -> 202408.79 | H65: =H63-H64 -> 218589.52 | I65: =I63-I64 -> 238567.68 | J65: =J63-J64 -> 285973.91 | K65: =K63-K64 -> 309032.79 | ... M65: =M63-M64 -> 360814.87
A66: Plus: D&A & other non-cash charges affecting EBIT | D66: =Depr_Amort!F39+IF(goodwill_intang_deductible=1,Depr_Amort!F43+Depr_Amort!F42,0) -> 72924.167 | E66: =Depr_Amort!G39+IF(goodwill_intang_deductible=1,Depr_Amort!G43+Depr_Amort!G42,0) -> 85024.167 | F66: =Depr_Amort!H39+IF(goodwill_intang_deductible=1,Depr_Amort!H43+Depr_Amort!H42,0) -> 93897.5 | G66: =Depr_Amort!I39+IF(goodwill_intang_deductible=1,Depr_Amort!I43+Depr_Amort!I42,0) -> 104355.36 | H66: =Depr_Amort!J39+IF(goodwill_intang_deductible=1,Depr_Amort!J43+Depr_Amort!J42,0) -> 117776.27 | I66: =Depr_Amort!K39+IF(goodwill_intang_deductible=1,Depr_Amort!K43+Depr_Amort!K42,0) -> 128848.53 | J66: =Depr_Amort!L39+IF(goodwill_intang_deductible=1,Depr_Amort!L43+Depr_Amort!L42,0) -> 101531.64 | K66: =Depr_Amort!M39+IF(goodwill_intang_deductible=1,Depr_Amort!M43+Depr_Amort!M42,0) -> 115822.24 | ... M66: =Depr_Amort!O39+IF(goodwill_intang_deductible=1,Depr_Amort!O43+Depr_Amort!O42,0) -> 149661.32
A67: Less: Capital Expenditures | D67: =Bal_Sheet!F25 -> 110000 | E67: =Bal_Sheet!G25 -> 121000 | F67: =Bal_Sheet!H25 -> 133100 | G67: =Bal_Sheet!I25 -> 146410 | H67: =Bal_Sheet!J25 -> 161051 | I67: =Bal_Sheet!K25 -> 177156.1 | J67: =Bal_Sheet!L25 -> 194871.71 | K67: =Bal_Sheet!M25 -> 214358.88 | ... M67: =Bal_Sheet!O25 -> 259374.25
A68: Less: Increase in Net (non-cash) Working Capital | D68: =-SUM(Cash_Flow!D21:D25) -> 99600.85 | E68: =-SUM(Cash_Flow!E21:E25) -> 39600.03 | F68: =-SUM(Cash_Flow!F21:F25) -> 47634.852 | G68: =-SUM(Cash_Flow!G21:G25) -> 55254.245 | H68: =-SUM(Cash_Flow!H21:H25) -> 64070.736 | I68: =-SUM(Cash_Flow!I21:I25) -> 74270.246 | J68: =-SUM(Cash_Flow!J21:J25) -> 86067.359 | K68: =-SUM(Cash_Flow!K21:K25) -> 99709.713 | ... M68: =-SUM(Cash_Flow!M21:M25) -> 133717.19
A69: Less: (Increase) decrease in Deferred Tax | D69: =-Income_Tax!D30 -> -4595.29 | E69: =-Income_Tax!E30 -> -246.54 | F69: =-Income_Tax!F30 -> -246.54 | G69: =-Income_Tax!G30 -> -2280.0122 | H69: =-Income_Tax!H30 -> -11657.154 | I69: =-Income_Tax!I30 -> -11674.654 | J69: =-Income_Tax!J30 -> -20859.237 | K69: =-Income_Tax!K30 -> -53405.334 | ... M69: =-Income_Tax!M30 -> 4989.4325
A70: Unlevered Free Cash Flows (UFCF) | D70: =D65+D66-D67-D68-D69 -> 27867.898 | E70: =E65+E66-E67-E68-E69 -> 95913.036 | F70: =F65+F66-F67-F68-F69 -> 99794.367 | G70: =G65+G66-G67-G68-G69 -> 107379.91 | H70: =H65+H66-H67-H68-H69 -> 122901.21 | I70: =I65+I66-I67-I68-I69 -> 127664.52 | J70: =J65+J66-J67-J68-J69 -> 127425.72 | K70: =K65+K66-K67-K68-K69 -> 164191.76 | ... M70: =M65+M66-M67-M68-M69 -> 112395.33
A74: Debt Repayment
A76: Cash Available for Debt Repayment
A77: Cash at beginning of year | D77: =Bal_Sheet!E10 -> 77500 | E77: =D110 -> 50000 | F77: =E110 -> 50000 | G77: =F110 -> 50000 | H77: =G110 -> 50000 | I77: =H110 -> 50000 | J77: =I110 -> 50000 | K77: =J110 -> 50000 | L77: =K110 -> 134328.87 | M77: =L110 -> 263486
A78: Net cash provided by (used in) operating activities | D78: =D27 -> 121910.72 | E78: =E27 -> 201927.63 | F78: =F27 -> 220575.64 | G78: =G27 -> 243926.46 | H78: =H27 -> 275192.88 | I78: =I27 -> 286923.66 | J78: =J27 -> 306234.6 | K78: =K27 -> 364780.46 | ... M78: =M27 -> 359133.86
A79: Net cash provided by (used in) investing activities | D79: =D33 -> -139000 | E79: =E33 -> -125642 | F79: =F33 -> -138231.73 | G79: =G33 -> -152083.13 | H79: =H33 -> -167322.64 | I79: =I33 -> -184089.4 | J79: =J33 -> -202536.48 | K79: =K33 -> -222832.28 | ... M79: =M33 -> -269729.84
A80: Sub-total | D80: =SUM(D77:D79) -> 60410.719 | E80: =SUM(E77:E79) -> 126285.63 | F80: =SUM(F77:F79) -> 132343.91 | G80: =SUM(G77:G79) -> 141843.33 | H80: =SUM(H77:H79) -> 157870.24 | I80: =SUM(I77:I79) -> 152834.26 | J80: =SUM(J77:J79) -> 153698.13 | K80: =SUM(K77:K79) -> 191948.18 | ... M80: =SUM(M77:M79) -> 352890.02
A81: Minimum Cash Balance | D81: =IF(cash_min=1,cash_min_amt,0) -> 50000 | E81: =IF(cash_min=1,cash_min_amt,0) -> 50000 | F81: =IF(cash_min=1,cash_min_amt,0) -> 50000 | G81: =IF(cash_min=1,cash_min_amt,0) -> 50000 | H81: =IF(cash_min=1,cash_min_amt,0) -> 50000 | I81: =IF(cash_min=1,cash_min_amt,0) -> 50000 | J81: =IF(cash_min=1,cash_min_amt,0) -> 50000 | K81: =IF(cash_min=1,cash_min_amt,0) -> 50000 | ... M81: =IF(cash_min=1,cash_min_amt,0) -> 50000
A82: =A76 -> Cash Available for Debt Repayment | D82: =D80-D81 -> 10410.719 | E82: =E80-E81 -> 76285.635 | F82: =F80-F81 -> 82343.908 | G82: =G80-G81 -> 91843.327 | H82: =H80-H81 -> 107870.24 | I82: =I80-I81 -> 102834.26 | J82: =J80-J81 -> 103698.13 | K82: =K80-K81 -> 141948.18 | ... M82: =M80-M81 -> 302890.02
A84: Mandatory Repayment
A85: =Bal_Sheet!A46 -> Existing Debt | D85: =IF(assumed_debt_maturity_year=D5,Bal_Sheet!E46,IF(assumed_debt_maturity_year>D5,MIN(Bal_Sheet!E46,Input!$C$26*assumed_debt_ann_repay),0)) -> 7222.2222 | E85: =IF(assumed_debt_maturity_year=E5,Bal_Sheet!F46,IF(assumed_debt_maturity_year>E5,MIN(Bal_Sheet!F46,Input!$C$26*assumed_debt_ann_repay),0)) -> 7222.2222 | F85: =IF(assumed_debt_maturity_year=F5,Bal_Sheet!G46,IF(assumed_debt_maturity_year>F5,MIN(Bal_Sheet!G46,Input!$C$26*assumed_debt_ann_repay),0)) -> 0 | G85: =IF(assumed_debt_maturity_year=G5,Bal_Sheet!H46,IF(assumed_debt_maturity_year>G5,MIN(Bal_Sheet!H46,Input!$C$26*assumed_debt_ann_repay),0)) -> 0 | H85: =IF(assumed_debt_maturity_year=H5,Bal_Sheet!I46,IF(assumed_debt_maturity_year>H5,MIN(Bal_Sheet!I46,Input!$C$26*assumed_debt_ann_repay),0)) -> 0 | I85: =IF(assumed_debt_maturity_year=I5,Bal_Sheet!J46,IF(assumed_debt_maturity_year>I5,MIN(Bal_Sheet!J46,Input!$C$26*assumed_debt_ann_repay),0)) -> 0 | J85: =IF(assumed_debt_maturity_year=J5,Bal_Sheet!K46,IF(assumed_debt_maturity_year>J5,MIN(Bal_Sheet!K46,Input!$C$26*assumed_debt_ann_repay),0)) -> 0 | K85: =IF(assumed_debt_maturity_year=K5,Bal_Sheet!L46,IF(assumed_debt_maturity_year>K5,MIN(Bal_Sheet!L46,Input!$C$26*assumed_debt_ann_repay),0)) -> 0 | ... M85: =IF(assumed_debt_maturity_year=M5,Bal_Sheet!N46,IF(assumed_debt_maturity_year>M5,MIN(Bal_Sheet!N46,Input!$C$26*assumed_debt_ann_repay),0)) -> 0
A86: =Bal_Sheet!A48 -> Term Loan "A" | D86: =IF(termloanA_term_years=D5,Bal_Sheet!E48,IF(termloanA_term_years>D5,MIN(Bal_Sheet!E48,Input!$C$28*termloanA_ann_repay),0)) -> 10000 | E86: =IF(termloanA_term_years=E5,Bal_Sheet!F48,IF(termloanA_term_years>E5,MIN(Bal_Sheet!F48,Input!$C$28*termloanA_ann_repay),0)) -> 10000 | F86: =IF(termloanA_term_years=F5,Bal_Sheet!G48,IF(termloanA_term_years>F5,MIN(Bal_Sheet!G48,Input!$C$28*termloanA_ann_repay),0)) -> 10000 | G86: =IF(termloanA_term_years=G5,Bal_Sheet!H48,IF(termloanA_term_years>G5,MIN(Bal_Sheet!H48,Input!$C$28*termloanA_ann_repay),0)) -> 0 | H86: =IF(termloanA_term_years=H5,Bal_Sheet!I48,IF(termloanA_term_years>H5,MIN(Bal_Sheet!I48,Input!$C$28*termloanA_ann_repay),0)) -> 0 | I86: =IF(termloanA_term_years=I5,Bal_Sheet!J48,IF(termloanA_term_years>I5,MIN(Bal_Sheet!J48,Input!$C$28*termloanA_ann_repay),0)) -> 0 | J86: =IF(termloanA_term_years=J5,Bal_Sheet!K48,IF(termloanA_term_years>J5,MIN(Bal_Sheet!K48,Input!$C$28*termloanA_ann_repay),0)) -> 0 | K86: =IF(termloanA_term_years=K5,Bal_Sheet!L48,IF(termloanA_term_years>K5,MIN(Bal_Sheet!L48,Input!$C$28*termloanA_ann_repay),0)) -> 0 | ... M86: =IF(termloanA_term_years=M5,Bal_Sheet!N48,IF(termloanA_term_years>M5,MIN(Bal_Sheet!N48,Input!$C$28*termloanA_ann_repay),0)) -> 0
A87: =Bal_Sheet!A49 -> Term Loan "B" | D87: =IF(termloanB_term_years=D5,MIN(Bal_Sheet!E49,Input!$C$29*termloanB_bulletyr_repayment),IF(termloanB_term_years>D5,MIN(Bal_Sheet!E49,Input!$C$29*termloanB_ann_repay),0)) -> 2200 | E87: =IF(termloanB_term_years=E5,MIN(Bal_Sheet!F49,Input!$C$29*termloanB_bulletyr_repayment),IF(termloanB_term_years>E5,MIN(Bal_Sheet!F49,Input!$C$29*termloanB_ann_repay),0)) -> 2200 | F87: =IF(termloanB_term_years=F5,MIN(Bal_Sheet!G49,Input!$C$29*termloanB_bulletyr_repayment),IF(termloanB_term_years>F5,MIN(Bal_Sheet!G49,Input!$C$29*termloanB_ann_repay),0)) -> 2200 | G87: =IF(termloanB_term_years=G5,MIN(Bal_Sheet!H49,Input!$C$29*termloanB_bulletyr_repayment),IF(termloanB_term_years>G5,MIN(Bal_Sheet!H49,Input!$C$29*termloanB_ann_repay),0)) -> 2200 | H87: =IF(termloanB_term_years=H5,MIN(Bal_Sheet!I49,Input!$C$29*termloanB_bulletyr_repayment),IF(termloanB_term_years>H5,MIN(Bal_Sheet!I49,Input!$C$29*termloanB_ann_repay),0)) -> 0 | I87: =IF(termloanB_term_years=I5,MIN(Bal_Sheet!J49,Input!$C$29*termloanB_bulletyr_repayment),IF(termloanB_term_years>I5,MIN(Bal_Sheet!J49,Input!$C$29*termloanB_ann_repay),0)) -> 0 | J87: =IF(termloanB_term_years=J5,MIN(Bal_Sheet!K49,Input!$C$29*termloanB_bulletyr_repayment),IF(termloanB_term_years>J5,MIN(Bal_Sheet!K49,Input!$C$29*termloanB_ann_repay),0)) -> 0 | K87: =IF(termloanB_term_years=K5,MIN(Bal_Sheet!L49,Input!$C$29*termloanB_bulletyr_repayment),IF(termloanB_term_years>K5,MIN(Bal_Sheet!L49,Input!$C$29*termloanB_ann_repay),0)) -> 0 | ... M87: =IF(termloanB_term_years=M5,MIN(Bal_Sheet!N49,Input!$C$29*termloanB_bulletyr_repayment),IF(termloanB_term_years>M5,MIN(Bal_Sheet!N49,Input!$C$29*termloanB_ann_repay),0)) -> 0
A88: =Bal_Sheet!A50 -> Senior Notes | D88: =IF(senior_notes_mat_yr=D5,Bal_Sheet!E50,0) -> 0 | E88: =IF(senior_notes_mat_yr=E5,Bal_Sheet!F50,0) -> 0 | F88: =IF(senior_notes_mat_yr=F5,Bal_Sheet!G50,0) -> 0 | G88: =IF(senior_notes_mat_yr=G5,Bal_Sheet!H50,0) -> 0 | H88: =IF(senior_notes_mat_yr=H5,Bal_Sheet!I50,0) -> 0 | I88: =IF(senior_notes_mat_yr=I5,Bal_Sheet!J50,0) -> 0 | J88: =IF(senior_notes_mat_yr=J5,Bal_Sheet!K50,0) -> 0 | K88: =IF(senior_notes_mat_yr=K5,Bal_Sheet!L50,0) -> 0 | ... M88: =IF(senior_notes_mat_yr=M5,Bal_Sheet!N50,0) -> 0
A89: =Bal_Sheet!A51 -> Subordinated Notes | D89: =IF(sub_notes_mat_yr=D5,Bal_Sheet!E51,0) -> 0 | E89: =IF(sub_notes_mat_yr=E5,Bal_Sheet!F51,0) -> 0 | F89: =IF(sub_notes_mat_yr=F5,Bal_Sheet!G51,0) -> 0 | G89: =IF(sub_notes_mat_yr=G5,Bal_Sheet!H51,0) -> 0 | H89: =IF(sub_notes_mat_yr=H5,Bal_Sheet!I51,0) -> 0 | I89: =IF(sub_notes_mat_yr=I5,Bal_Sheet!J51,0) -> 0 | J89: =IF(sub_notes_mat_yr=J5,Bal_Sheet!K51,0) -> 0 | K89: =IF(sub_notes_mat_yr=K5,Bal_Sheet!L51,0) -> 0 | ... M89: =IF(sub_notes_mat_yr=M5,Bal_Sheet!N51,0) -> 0
A90: =Bal_Sheet!A52 -> Mezzanine Debt | D90: =IF(mezzdebt_maturity_year=D5,Bal_Sheet!E52,0) -> 0 | E90: =IF(mezzdebt_maturity_year=E5,Bal_Sheet!F52,0) -> 0 | F90: =IF(mezzdebt_maturity_year=F5,Bal_Sheet!G52,0) -> 0 | G90: =IF(mezzdebt_maturity_year=G5,Bal_Sheet!H52,0) -> 0 | H90: =IF(mezzdebt_maturity_year=H5,Bal_Sheet!I52,0) -> 0 | I90: =IF(mezzdebt_maturity_year=I5,Bal_Sheet!J52,0) -> 0 | J90: =IF(mezzdebt_maturity_year=J5,Bal_Sheet!K52,0) -> 0 | K90: =IF(mezzdebt_maturity_year=K5,Bal_Sheet!L52,0) -> 0 | ... M90: =IF(mezzdebt_maturity_year=M5,Bal_Sheet!N52,0) -> 0
A91: =Bal_Sheet!A53 -> Seller Notes | D91: =IF(seller_notes_term_year=D5,Bal_Sheet!E53,IF(seller_notes_term_year>D5,MIN(Bal_Sheet!E53,Input!$C$33*seller_notes_ann_repay),0)) -> 3571.4286 | E91: =IF(seller_notes_term_year=E5,Bal_Sheet!F53,IF(seller_notes_term_year>E5,MIN(Bal_Sheet!F53,Input!$C$33*seller_notes_ann_repay),0)) -> 3571.4286 | F91: =IF(seller_notes_term_year=F5,Bal_Sheet!G53,IF(seller_notes_term_year>F5,MIN(Bal_Sheet!G53,Input!$C$33*seller_notes_ann_repay),0)) -> 3571.4286 | G91: =IF(seller_notes_term_year=G5,Bal_Sheet!H53,IF(seller_notes_term_year>G5,MIN(Bal_Sheet!H53,Input!$C$33*seller_notes_ann_repay),0)) -> 3571.4286 | H91: =IF(seller_notes_term_year=H5,Bal_Sheet!I53,IF(seller_notes_term_year>H5,MIN(Bal_Sheet!I53,Input!$C$33*seller_notes_ann_repay),0)) -> 3571.4286 | I91: =IF(seller_notes_term_year=I5,Bal_Sheet!J53,IF(seller_notes_term_year>I5,MIN(Bal_Sheet!J53,Input!$C$33*seller_notes_ann_repay),0)) -> 3571.4286 | J91: =IF(seller_notes_term_year=J5,Bal_Sheet!K53,IF(seller_notes_term_year>J5,MIN(Bal_Sheet!K53,Input!$C$33*seller_notes_ann_repay),0)) -> 0 | K91: =IF(seller_notes_term_year=K5,Bal_Sheet!L53,IF(seller_notes_term_year>K5,MIN(Bal_Sheet!L53,Input!$C$33*seller_notes_ann_repay),0)) -> 0 | ... M91: =IF(seller_notes_term_year=M5,Bal_Sheet!N53,IF(seller_notes_term_year>M5,MIN(Bal_Sheet!N53,Input!$C$33*seller_notes_ann_repay),0)) -> 0
A92: =Bal_Sheet!A61 -> Preferred Stock | D92: =IF(pref_stock_retired_year=D5,Bal_Sheet!E61,0) -> 0 | E92: =IF(pref_stock_retired_year=E5,Bal_Sheet!F61,0) -> 0 | F92: =IF(pref_stock_retired_year=F5,Bal_Sheet!G61,0) -> 0 | G92: =IF(pref_stock_retired_year=G5,Bal_Sheet!H61,0) -> 0 | H92: =IF(pref_stock_retired_year=H5,Bal_Sheet!I61,0) -> 0 | I92: =IF(pref_stock_retired_year=I5,Bal_Sheet!J61,0) -> 0 | J92: =IF(pref_stock_retired_year=J5,Bal_Sheet!K61,0) -> 0 | K92: =IF(pref_stock_retired_year=K5,Bal_Sheet!L61,0) -> 0 | ... M92: =IF(pref_stock_retired_year=M5,Bal_Sheet!N61,0) -> 0
A93: Sub-total | D93: =SUM(D85:D92) -> 22993.651 | E93: =SUM(E85:E92) -> 22993.651 | F93: =SUM(F85:F92) -> 15771.429 | G93: =SUM(G85:G92) -> 5771.4286 | H93: =SUM(H85:H92) -> 3571.4286 | I93: =SUM(I85:I92) -> 3571.4286 | J93: =SUM(J85:J92) -> 0 | K93: =SUM(K85:K92) -> 0 | ... M93: =SUM(M85:M92) -> 0
A95: Cash Balance | D95: =D82-D93 -> -12582.932 | E95: =E82-E93 -> 53291.984 | F95: =F82-F93 -> 66572.48 | G95: =G82-G93 -> 86071.898 | H95: =H82-H93 -> 104298.81 | I95: =I82-I93 -> 99262.832 | J95: =J82-J93 -> 103698.13 | K95: =K82-K93 -> 141948.18 | ... M95: =M82-M93 -> 302890.02
A96: Incremental Revolver | D96: =MIN(revolver_limit-Bal_Sheet!E47,MAX(-D95,0)) -> 12582.932 | E96: =MIN(revolver_limit-Bal_Sheet!F47,MAX(-E95,0)) -> 0 | F96: =MIN(revolver_limit-Bal_Sheet!G47,MAX(-F95,0)) -> 0 | G96: =MIN(revolver_limit-Bal_Sheet!H47,MAX(-G95,0)) -> 0 | H96: =MIN(revolver_limit-Bal_Sheet!I47,MAX(-H95,0)) -> 0 | I96: =MIN(revolver_limit-Bal_Sheet!J47,MAX(-I95,0)) -> 0 | J96: =MIN(revolver_limit-Bal_Sheet!K47,MAX(-J95,0)) -> 0 | K96: =MIN(revolver_limit-Bal_Sheet!L47,MAX(-K95,0)) -> 0 | ... M96: =MIN(revolver_limit-Bal_Sheet!N47,MAX(-M95,0)) -> 0
A97: Cash Available for Optional Repayment | D97: =SUM(D95:D96) -> 0 | E97: =SUM(E95:E96) -> 53291.984 | F97: =SUM(F95:F96) -> 66572.48 | G97: =SUM(G95:G96) -> 86071.898 | H97: =SUM(H95:H96) -> 104298.81 | I97: =SUM(I95:I96) -> 99262.832 | J97: =SUM(J95:J96) -> 103698.13 | K97: =SUM(K95:K96) -> 141948.18 | ... M97: =SUM(M95:M96) -> 302890.02
A99: Optional Repayment
A100: =Bal_Sheet!A46 -> Existing Debt | D100: =IF(AND(assumed_debt_prepay=1,D$5<=assumed_debt_maturity_year),MIN(Bal_Sheet!E46-D85,MAX(D$97,0)),0) -> 0 | E100: =IF(AND(assumed_debt_prepay=1,E$5<=assumed_debt_maturity_year),MIN(Bal_Sheet!F46-E85,MAX(E$97,0)),0) -> 50555.556 | F100: =IF(AND(assumed_debt_prepay=1,F$5<=assumed_debt_maturity_year),MIN(Bal_Sheet!G46-F85,MAX(F$97,0)),0) -> 0 | G100: =IF(AND(assumed_debt_prepay=1,G$5<=assumed_debt_maturity_year),MIN(Bal_Sheet!H46-G85,MAX(G$97,0)),0) -> 0 | H100: =IF(AND(assumed_debt_prepay=1,H$5<=assumed_debt_maturity_year),MIN(Bal_Sheet!I46-H85,MAX(H$97,0)),0) -> 0 | I100: =IF(AND(assumed_debt_prepay=1,I$5<=assumed_debt_maturity_year),MIN(Bal_Sheet!J46-I85,MAX(I$97,0)),0) -> 0 | J100: =IF(AND(assumed_debt_prepay=1,J$5<=assumed_debt_maturity_year),MIN(Bal_Sheet!K46-J85,MAX(J$97,0)),0) -> 0 | K100: =IF(AND(assumed_debt_prepay=1,K$5<=assumed_debt_maturity_year),MIN(Bal_Sheet!L46-K85,MAX(K$97,0)),0) -> 0 | ... M100: =IF(AND(assumed_debt_prepay=1,M$5<=assumed_debt_maturity_year),MIN(Bal_Sheet!N46-M85,MAX(M$97,0)),0) -> 0
A101: =Bal_Sheet!A48 -> Term Loan "A" | D101: =IF(AND(termloanA_prepay=1,D$5<=termloanA_term_years),MIN(Bal_Sheet!E48-D86,MAX(D$97-SUM(D$100:D100),0)),0) -> 0 | E101: =IF(AND(termloanA_prepay=1,E$5<=termloanA_term_years),MIN(Bal_Sheet!F48-E86,MAX(E$97-SUM(E$100:E100),0)),0) -> 2736.4284 | F101: =IF(AND(termloanA_prepay=1,F$5<=termloanA_term_years),MIN(Bal_Sheet!G48-F86,MAX(F$97-SUM(F$100:F100),0)),0) -> 47263.572 | G101: =IF(AND(termloanA_prepay=1,G$5<=termloanA_term_years),MIN(Bal_Sheet!H48-G86,MAX(G$97-SUM(G$100:G100),0)),0) -> 0 | H101: =IF(AND(termloanA_prepay=1,H$5<=termloanA_term_years),MIN(Bal_Sheet!I48-H86,MAX(H$97-SUM(H$100:H100),0)),0) -> 0 | I101: =IF(AND(termloanA_prepay=1,I$5<=termloanA_term_years),MIN(Bal_Sheet!J48-I86,MAX(I$97-SUM(I$100:I100),0)),0) -> 0 | J101: =IF(AND(termloanA_prepay=1,J$5<=termloanA_term_years),MIN(Bal_Sheet!K48-J86,MAX(J$97-SUM(J$100:J100),0)),0) -> 0 | K101: =IF(AND(termloanA_prepay=1,K$5<=termloanA_term_years),MIN(Bal_Sheet!L48-K86,MAX(K$97-SUM(K$100:K100),0)),0) -> 0 | ... M101: =IF(AND(termloanA_prepay=1,M$5<=termloanA_term_years),MIN(Bal_Sheet!N48-M86,MAX(M$97-SUM(M$100:M100),0)),0) -> 0
A102: =Bal_Sheet!A49 -> Term Loan "B" | D102: =IF(AND(termloanB_prepay=1,D$5<=termloanB_term_years),MIN(Bal_Sheet!E49-D87,MAX(D$97-SUM(D$100:D101),0)),0) -> 0 | E102: =IF(AND(termloanB_prepay=1,E$5<=termloanB_term_years),MIN(Bal_Sheet!F49-E87,MAX(E$97-SUM(E$100:E101),0)),0) -> 0 | F102: =IF(AND(termloanB_prepay=1,F$5<=termloanB_term_years),MIN(Bal_Sheet!G49-F87,MAX(F$97-SUM(F$100:F101),0)),0) -> 19308.908 | G102: =IF(AND(termloanB_prepay=1,G$5<=termloanB_term_years),MIN(Bal_Sheet!H49-G87,MAX(G$97-SUM(G$100:G101),0)),0) -> 26891.092 | H102: =IF(AND(termloanB_prepay=1,H$5<=termloanB_term_years),MIN(Bal_Sheet!I49-H87,MAX(H$97-SUM(H$100:H101),0)),0) -> 0 | I102: =IF(AND(termloanB_prepay=1,I$5<=termloanB_term_years),MIN(Bal_Sheet!J49-I87,MAX(I$97-SUM(I$100:I101),0)),0) -> 0 | J102: =IF(AND(termloanB_prepay=1,J$5<=termloanB_term_years),MIN(Bal_Sheet!K49-J87,MAX(J$97-SUM(J$100:J101),0)),0) -> 0 | K102: =IF(AND(termloanB_prepay=1,K$5<=termloanB_term_years),MIN(Bal_Sheet!L49-K87,MAX(K$97-SUM(K$100:K101),0)),0) -> 0 | ... M102: =IF(AND(termloanB_prepay=1,M$5<=termloanB_term_years),MIN(Bal_Sheet!N49-M87,MAX(M$97-SUM(M$100:M101),0)),0) -> 0
A103: =Bal_Sheet!A50 -> Senior Notes | D103: =IF(AND(senior_notes_prepay=1,D$5<=senior_notes_mat_yr),MIN(Bal_Sheet!E50-D88,MAX(D$97-SUM(D$100:D102),0)),0) -> 0 | E103: =IF(AND(senior_notes_prepay=1,E$5<=senior_notes_mat_yr),MIN(Bal_Sheet!F50-E88,MAX(E$97-SUM(E$100:E102),0)),0) -> 0 | F103: =IF(AND(senior_notes_prepay=1,F$5<=senior_notes_mat_yr),MIN(Bal_Sheet!G50-F88,MAX(F$97-SUM(F$100:F102),0)),0) -> 0 | G103: =IF(AND(senior_notes_prepay=1,G$5<=senior_notes_mat_yr),MIN(Bal_Sheet!H50-G88,MAX(G$97-SUM(G$100:G102),0)),0) -> 59180.807 | H103: =IF(AND(senior_notes_prepay=1,H$5<=senior_notes_mat_yr),MIN(Bal_Sheet!I50-H88,MAX(H$97-SUM(H$100:H102),0)),0) -> 5819.1933 | I103: =IF(AND(senior_notes_prepay=1,I$5<=senior_notes_mat_yr),MIN(Bal_Sheet!J50-I88,MAX(I$97-SUM(I$100:I102),0)),0) -> 0 | J103: =IF(AND(senior_notes_prepay=1,J$5<=senior_notes_mat_yr),MIN(Bal_Sheet!K50-J88,MAX(J$97-SUM(J$100:J102),0)),0) -> 0 | K103: =IF(AND(senior_notes_prepay=1,K$5<=senior_notes_mat_yr),MIN(Bal_Sheet!L50-K88,MAX(K$97-SUM(K$100:K102),0)),0) -> 0 | ... M103: =IF(AND(senior_notes_prepay=1,M$5<=senior_notes_mat_yr),MIN(Bal_Sheet!N50-M88,MAX(M$97-SUM(M$100:M102),0)),0) -> 0
A104: =Bal_Sheet!A51 -> Subordinated Notes | D104: =IF(AND(sub_notes_prepay=1,D$5<=sub_notes_mat_yr),MIN(Bal_Sheet!E51-D89,MAX(D$97-SUM(D$100:D103),0)),0) -> 0 | E104: =IF(AND(sub_notes_prepay=1,E$5<=sub_notes_mat_yr),MIN(Bal_Sheet!F51-E89,MAX(E$97-SUM(E$100:E103),0)),0) -> 0 | F104: =IF(AND(sub_notes_prepay=1,F$5<=sub_notes_mat_yr),MIN(Bal_Sheet!G51-F89,MAX(F$97-SUM(F$100:F103),0)),0) -> 0 | G104: =IF(AND(sub_notes_prepay=1,G$5<=sub_notes_mat_yr),MIN(Bal_Sheet!H51-G89,MAX(G$97-SUM(G$100:G103),0)),0) -> 0 | H104: =IF(AND(sub_notes_prepay=1,H$5<=sub_notes_mat_yr),MIN(Bal_Sheet!I51-H89,MAX(H$97-SUM(H$100:H103),0)),0) -> 47700.744 | I104: =IF(AND(sub_notes_prepay=1,I$5<=sub_notes_mat_yr),MIN(Bal_Sheet!J51-I89,MAX(I$97-SUM(I$100:I103),0)),0) -> 2146.5335 | J104: =IF(AND(sub_notes_prepay=1,J$5<=sub_notes_mat_yr),MIN(Bal_Sheet!K51-J89,MAX(J$97-SUM(J$100:J103),0)),0) -> 0 | K104: =IF(AND(sub_notes_prepay=1,K$5<=sub_notes_mat_yr),MIN(Bal_Sheet!L51-K89,MAX(K$97-SUM(K$100:K103),0)),0) -> 0 | ... M104: =IF(AND(sub_notes_prepay=1,M$5<=sub_notes_mat_yr),MIN(Bal_Sheet!N51-M89,MAX(M$97-SUM(M$100:M103),0)),0) -> 0
A105: =Bal_Sheet!A52 -> Mezzanine Debt | D105: =IF(AND(mezzdebt_prepay=1,D$5<=mezzdebt_maturity_year),MIN(Bal_Sheet!E52-D90,MAX(D$97-SUM(D$100:D104),0)),0) -> 0 | E105: =IF(AND(mezzdebt_prepay=1,E$5<=mezzdebt_maturity_year),MIN(Bal_Sheet!F52-E90,MAX(E$97-SUM(E$100:E104),0)),0) -> 0 | F105: =IF(AND(mezzdebt_prepay=1,F$5<=mezzdebt_maturity_year),MIN(Bal_Sheet!G52-F90,MAX(F$97-SUM(F$100:F104),0)),0) -> 0 | G105: =IF(AND(mezzdebt_prepay=1,G$5<=mezzdebt_maturity_year),MIN(Bal_Sheet!H52-G90,MAX(G$97-SUM(G$100:G104),0)),0) -> 0 | H105: =IF(AND(mezzdebt_prepay=1,H$5<=mezzdebt_maturity_year),MIN(Bal_Sheet!I52-H90,MAX(H$97-SUM(H$100:H104),0)),0) -> 50778.871 | I105: =IF(AND(mezzdebt_prepay=1,I$5<=mezzdebt_maturity_year),MIN(Bal_Sheet!J52-I90,MAX(I$97-SUM(I$100:I104),0)),0) -> 36453.864 | J105: =IF(AND(mezzdebt_prepay=1,J$5<=mezzdebt_maturity_year),MIN(Bal_Sheet!K52-J90,MAX(J$97-SUM(J$100:J104),0)),0) -> 0 | K105: =IF(AND(mezzdebt_prepay=1,K$5<=mezzdebt_maturity_year),MIN(Bal_Sheet!L52-K90,MAX(K$97-SUM(K$100:K104),0)),0) -> 0 | ... M105: =IF(AND(mezzdebt_prepay=1,M$5<=mezzdebt_maturity_year),MIN(Bal_Sheet!N52-M90,MAX(M$97-SUM(M$100:M104),0)),0) -> 0
A106: =Bal_Sheet!A53 -> Seller Notes | D106: =IF(AND(seller_notes_prepay=1,D$5<=seller_notes_term_year),MIN(Bal_Sheet!E53-D91,MAX(D$97-SUM(D$100:D105),0)),0) -> 0 | E106: =IF(AND(seller_notes_prepay=1,E$5<=seller_notes_term_year),MIN(Bal_Sheet!F53-E91,MAX(E$97-SUM(E$100:E105),0)),0) -> 0 | F106: =IF(AND(seller_notes_prepay=1,F$5<=seller_notes_term_year),MIN(Bal_Sheet!G53-F91,MAX(F$97-SUM(F$100:F105),0)),0) -> 0 | G106: =IF(AND(seller_notes_prepay=1,G$5<=seller_notes_term_year),MIN(Bal_Sheet!H53-G91,MAX(G$97-SUM(G$100:G105),0)),0) -> 0 | H106: =IF(AND(seller_notes_prepay=1,H$5<=seller_notes_term_year),MIN(Bal_Sheet!I53-H91,MAX(H$97-SUM(H$100:H105),0)),0) -> 0 | I106: =IF(AND(seller_notes_prepay=1,I$5<=seller_notes_term_year),MIN(Bal_Sheet!J53-I91,MAX(I$97-SUM(I$100:I105),0)),0) -> 8509.4408 | J106: =IF(AND(seller_notes_prepay=1,J$5<=seller_notes_term_year),MIN(Bal_Sheet!K53-J91,MAX(J$97-SUM(J$100:J105),0)),0) -> 0 | K106: =IF(AND(seller_notes_prepay=1,K$5<=seller_notes_term_year),MIN(Bal_Sheet!L53-K91,MAX(K$97-SUM(K$100:K105),0)),0) -> 0 | ... M106: =IF(AND(seller_notes_prepay=1,M$5<=seller_notes_term_year),MIN(Bal_Sheet!N53-M91,MAX(M$97-SUM(M$100:M105),0)),0) -> 0
A107: =Bal_Sheet!A47 -> Bank Revolver | D107: =MIN(Bal_Sheet!E47+D96,MAX(D$97-SUM(D$100:D106),0)) -> 0 | E107: =MIN(Bal_Sheet!F47+E96,MAX(E$97-SUM(E$100:E106),0)) -> 0 | F107: =MIN(Bal_Sheet!G47+F96,MAX(F$97-SUM(F$100:F106),0)) -> 0 | G107: =MIN(Bal_Sheet!H47+G96,MAX(G$97-SUM(G$100:G106),0)) -> 0 | H107: =MIN(Bal_Sheet!I47+H96,MAX(H$97-SUM(H$100:H106),0)) -> 0 | I107: =MIN(Bal_Sheet!J47+I96,MAX(I$97-SUM(I$100:I106),0)) -> 52152.993 | J107: =MIN(Bal_Sheet!K47+J96,MAX(J$97-SUM(J$100:J106),0)) -> 103698.13 | K107: =MIN(Bal_Sheet!L47+K96,MAX(K$97-SUM(K$100:K106),0)) -> 57619.311 | ... M107: =MIN(Bal_Sheet!N47+M96,MAX(M$97-SUM(M$100:M106),0)) -> 0
A108: Sub-total | D108: =SUM(D100:D107) -> 0 | E108: =SUM(E100:E107) -> 53291.984 | F108: =SUM(F100:F107) -> 66572.48 | G108: =SUM(G100:G107) -> 86071.898 | H108: =SUM(H100:H107) -> 104298.81 | I108: =SUM(I100:I107) -> 99262.832 | J108: =SUM(J100:J107) -> 103698.13 | K108: =SUM(K100:K107) -> 57619.311 | ... M108: =SUM(M100:M107) -> 0
A110: Cash at end of year | D110: =D97-D108+IF(cash_min=1,cash_min_amt,0) -> 50000 | E110: =E97-E108+IF(cash_min=1,cash_min_amt,0) -> 50000 | F110: =F97-F108+IF(cash_min=1,cash_min_amt,0) -> 50000 | G110: =G97-G108+IF(cash_min=1,cash_min_amt,0) -> 50000 | H110: =H97-H108+IF(cash_min=1,cash_min_amt,0) -> 50000 | I110: =I97-I108+IF(cash_min=1,cash_min_amt,0) -> 50000 | J110: =J97-J108+IF(cash_min=1,cash_min_amt,0) -> 50000 | K110: =K97-K108+IF(cash_min=1,cash_min_amt,0) -> 134328.87 | ... M110: =M97-M108+IF(cash_min=1,cash_min_amt,0) -> 352890.02
A113: Cash Flow Check | D113: =D55-D110 -> 0 | E113: =E55-E110 -> 0 | F113: =F55-F110 -> 0 | G113: =G55-G110 -> 0 | H113: =H55-H110 -> 0 | I113: =I55-I110 -> 0 | J113: =J55-J110 -> 0 | K113: =K55-K110 -> 0 | ... M113: =M55-M110 -> 0

Sheet Depr_Amort
A2: Depreciation & Amortization
A4: Book Depreciation & Amortization: | F4: =Bal_Sheet!A24 -> Gross PP&E | H4: =Bal_Sheet!C24 -> 500000 | J4: Depreciation Method | N4: Goodwill & Intangibles Amortization
F5: PP&E Write-up | H5: =Input!C49 -> 2450 | J5: 0 | K5: 0=SLN 1=Sum of Years | N5: 0=Not Deductible 1=Tax Deductible
F6: Fair Value PP&E | H6: =SUM(H4:H5) -> 502450 | N6: 1 | O6: =IF(N6=1,"Tax Deductible","Not Deductible") -> Tax Deductible
F7: Accumulated Depreciation | H7: =Bal_Sheet!C27 -> 25000 | J7: Manual or Computed Depreciation
F8: Net PP&E | H8: =H6-H7 -> 477450 | J8: 1 | K8: 0=Manual 1=Computed
A11: Year | F11: =year1 -> 2010 | G11: =F11+1 -> 2011 | H11: =G11+1 -> 2012 | I11: =H11+1 -> 2013 | J11: =I11+1 -> 2014 | K11: =J11+1 -> 2015 | L11: =K11+1 -> 2016 | M11: =L11+1 -> 2017 | N11: =M11+1 -> 2018 | O11: =N11+1 -> 2019
A12: Year No. | F12: 1 | G12: =F12+1 -> 2 | H12: =G12+1 -> 3 | I12: =H12+1 -> 4 | J12: =I12+1 -> 5 | K12: =J12+1 -> 6 | L12: =K12+1 -> 7 | M12: =L12+1 -> 8 | N12: =M12+1 -> 9 | O12: =N12+1 -> 10
A14: Existing PP&E (incl Write-up)
B15: Beginning Amt | C15: Remaining Life | D15: Salvage
A16: Class 1 | B16: 90000 | C16: 12 | D16: 900 | F16: =IF(F$12>$C16,0,IF($J$5=1,SYD($B16,$D16,$C16,F$12),SLN($B16,$D16,$C16))) -> 7425 | G16: =IF(G$12>$C16,0,IF($J$5=1,SYD($B16,$D16,$C16,G$12),SLN($B16,$D16,$C16))) -> 7425 | H16: =IF(H$12>$C16,0,IF($J$5=1,SYD($B16,$D16,$C16,H$12),SLN($B16,$D16,$C16))) -> 7425 | I16: =IF(I$12>$C16,0,IF($J$5=1,SYD($B16,$D16,$C16,I$12),SLN($B16,$D16,$C16))) -> 7425 | J16: =IF(J$12>$C16,0,IF($J$5=1,SYD($B16,$D16,$C16,J$12),SLN($B16,$D16,$C16))) -> 7425 | K16: =IF(K$12>$C16,0,IF($J$5=1,SYD($B16,$D16,$C16,K$12),SLN($B16,$D16,$C16))) -> 7425 | L16: =IF(L$12>$C16,0,IF($J$5=1,SYD($B16,$D16,$C16,L$12),SLN($B16,$D16,$C16))) -> 7425 | M16: =IF(M$12>$C16,0,IF($J$5=1,SYD($B16,$D16,$C16,M$12),SLN($B16,$D16,$C16))) -> 7425 | ... O16: =IF(O$12>$C16,0,IF($J$5=1,SYD($B16,$D16,$C16,O$12),SLN($B16,$D16,$C16))) -> 7425
A17: Class 2 | B17: 85000 | C17: 10 | D17: 800 | F17: =IF(F$12>$C17,0,IF($J$5=1,SYD($B17,$D17,$C17,F$12),SLN($B17,$D17,$C17))) -> 8420 | G17: =IF(G$12>$C17,0,IF($J$5=1,SYD($B17,$D17,$C17,G$12),SLN($B17,$D17,$C17))) -> 8420 | H17: =IF(H$12>$C17,0,IF($J$5=1,SYD($B17,$D17,$C17,H$12),SLN($B17,$D17,$C17))) -> 8420 | I17: =IF(I$12>$C17,0,IF($J$5=1,SYD($B17,$D17,$C17,I$12),SLN($B17,$D17,$C17))) -> 8420 | J17: =IF(J$12>$C17,0,IF($J$5=1,SYD($B17,$D17,$C17,J$12),SLN($B17,$D17,$C17))) -> 8420 | K17: =IF(K$12>$C17,0,IF($J$5=1,SYD($B17,$D17,$C17,K$12),SLN($B17,$D17,$C17))) -> 8420 | L17: =IF(L$12>$C17,0,IF($J$5=1,SYD($B17,$D17,$C17,L$12),SLN($B17,$D17,$C17))) -> 8420 | M17: =IF(M$12>$C17,0,IF($J$5=1,SYD($B17,$D17,$C17,M$12),SLN($B17,$D17,$C17))) -> 8420 | ... O17: =IF(O$12>$C17,0,IF($J$5=1,SYD($B17,$D17,$C17,O$12),SLN($B17,$D17,$C17))) -> 8420
A18: Class 3 | B18: 60000 | C18: 8 | D18: 600 | F18: =IF(F$12>$C18,0,IF($J$5=1,SYD($B18,$D18,$C18,F$12),SLN($B18,$D18,$C18))) -> 7425 | G18: =IF(G$12>$C18,0,IF($J$5=1,SYD($B18,$D18,$C18,G$12),SLN($B18,$D18,$C18))) -> 7425 | H18: =IF(H$12>$C18,0,IF($J$5=1,SYD($B18,$D18,$C18,H$12),SLN($B18,$D18,$C18))) -> 7425 | I18: =IF(I$12>$C18,0,IF($J$5=1,SYD($B18,$D18,$C18,I$12),SLN($B18,$D18,$C18))) -> 7425 | J18: =IF(J$12>$C18,0,IF($J$5=1,SYD($B18,$D18,$C18,J$12),SLN($B18,$D18,$C18))) -> 7425 | K18: =IF(K$12>$C18,0,IF($J$5=1,SYD($B18,$D18,$C18,K$12),SLN($B18,$D18,$C18))) -> 7425 | L18: =IF(L$12>$C18,0,IF($J$5=1,SYD($B18,$D18,$C18,L$12),SLN($B18,$D18,$C18))) -> 7425 | M18: =IF(M$12>$C18,0,IF($J$5=1,SYD($B18,$D18,$C18,M$12),SLN($B18,$D18,$C18))) -> 7425 | ... O18: =IF(O$12>$C18,0,IF($J$5=1,SYD($B18,$D18,$C18,O$12),SLN($B18,$D18,$C18))) -> 0
A19: Class 4 | B19: =H8-SUM(B16:B18) -> 242450 | C19: 6 | D19: 600 | F19: =IF(F$12>$C19,0,IF($J$5=1,SYD($B19,$D19,$C19,F$12),SLN($B19,$D19,$C19))) -> 40308.333 | G19: =IF(G$12>$C19,0,IF($J$5=1,SYD($B19,$D19,$C19,G$12),SLN($B19,$D19,$C19))) -> 40308.333 | H19: =IF(H$12>$C19,0,IF($J$5=1,SYD($B19,$D19,$C19,H$12),SLN($B19,$D19,$C19))) -> 40308.333 | I19: =IF(I$12>$C19,0,IF($J$5=1,SYD($B19,$D19,$C19,I$12),SLN($B19,$D19,$C19))) -> 40308.333 | J19: =IF(J$12>$C19,0,IF($J$5=1,SYD($B19,$D19,$C19,J$12),SLN($B19,$D19,$C19))) -> 40308.333 | K19: =IF(K$12>$C19,0,IF($J$5=1,SYD($B19,$D19,$C19,K$12),SLN($B19,$D19,$C19))) -> 40308.333 | L19: =IF(L$12>$C19,0,IF($J$5=1,SYD($B19,$D19,$C19,L$12),SLN($B19,$D19,$C19))) -> 0 | M19: =IF(M$12>$C19,0,IF($J$5=1,SYD($B19,$D19,$C19,M$12),SLN($B19,$D19,$C19))) -> 0 | ... O19: =IF(O$12>$C19,0,IF($J$5=1,SYD($B19,$D19,$C19,O$12),SLN($B19,$D19,$C19))) -> 0
B20: =SUM(B16:B19) -> 477450 | D20: =SUM(D16:D19) -> 2900 | F20: =SUM(F16:F19) -> 63578.333 | G20: =SUM(G16:G19) -> 63578.333 | H20: =SUM(H16:H19) -> 63578.333 | I20: =SUM(I16:I19) -> 63578.333 | J20: =SUM(J16:J19) -> 63578.333 | K20: =SUM(K16:K19) -> 63578.333 | L20: =SUM(L16:L19) -> 23270 | M20: =SUM(M16:M19) -> 23270 | ... O20: =SUM(O16:O19) -> 15845
A22: Capex
A23: Year | B23: Capex | C23: Useful Life | D23: Salvage
A24: =F12 -> 1 | B24: =IF(capex_interval="",0,IF(capex_start_year="",0,IF($A24<capex_start_year,0,IF(MOD($A24-capex_start_year,capex_interval)=0,Inc_St!$D$8*capex,0)))) -> 110000 | C24: 12 | F24: =IF($A24>F$12,0,IF(F$12>$C24+$A24-1,0,IF($J$5=1,SYD($B24,$D24,$C24,F$12),SLN($B24,$D24,$C24)))) -> 9166.6667 | G24: =IF($A24>G$12,0,IF(G$12>$C24+$A24-1,0,IF($J$5=1,SYD($B24,$D24,$C24,G$12),SLN($B24,$D24,$C24)))) -> 9166.6667 | H24: =IF($A24>H$12,0,IF(H$12>$C24+$A24-1,0,IF($J$5=1,SYD($B24,$D24,$C24,H$12),SLN($B24,$D24,$C24)))) -> 9166.6667 | I24: =IF($A24>I$12,0,IF(I$12>$C24+$A24-1,0,IF($J$5=1,SYD($B24,$D24,$C24,I$12),SLN($B24,$D24,$C24)))) -> 9166.6667 | J24: =IF($A24>J$12,0,IF(J$12>$C24+$A24-1,0,IF($J$5=1,SYD($B24,$D24,$C24,J$12),SLN($B24,$D24,$C24)))) -> 9166.6667 | K24: =IF($A24>K$12,0,IF(K$12>$C24+$A24-1,0,IF($J$5=1,SYD($B24,$D24,$C24,K$12),SLN($B24,$D24,$C24)))) -> 9166.6667 | L24: =IF($A24>L$12,0,IF(L$12>$C24+$A24-1,0,IF($J$5=1,SYD($B24,$D24,$C24,L$12),SLN($B24,$D24,$C24)))) -> 9166.6667 | M24: =IF($A24>M$12,0,IF(M$12>$C24+$A24-1,0,IF($J$5=1,SYD($B24,$D24,$C24,M$12),SLN($B24,$D24,$C24)))) -> 9166.6667 | ... O24: =IF($A24>O$12,0,IF(O$12>$C24+$A24-1,0,IF($J$5=1,SYD($B24,$D24,$C24,O$12),SLN($B24,$D24,$C24)))) -> 9166.6667
A25: =G12 -> 2 | B25: =IF(capex_interval="",0,IF(capex_start_year="",0,IF($A25<capex_start_year,0,IF(MOD($A25-capex_start_year,capex_interval)=0,Inc_St!$E$8*capex,0)))) -> 121000 | C25: 10 | F25: =IF($A25>F$12,0,IF(F$12>$C25+$A25-1,0,IF($J$5=1,SYD($B25,$D25,$C25,F$12),SLN($B25,$D25,$C25)))) -> 0 | G25: =IF($A25>G$12,0,IF(G$12>$C25+$A25-1,0,IF($J$5=1,SYD($B25,$D25,$C25,G$12),SLN($B25,$D25,$C25)))) -> 12100 | H25: =IF($A25>H$12,0,IF(H$12>$C25+$A25-1,0,IF($J$5=1,SYD($B25,$D25,$C25,H$12),SLN($B25,$D25,$C25)))) -> 12100 | I25: =IF($A25>I$12,0,IF(I$12>$C25+$A25-1,0,IF($J$5=1,SYD($B25,$D25,$C25,I$12),SLN($B25,$D25,$C25)))) -> 12100 | J25: =IF($A25>J$12,0,IF(J$12>$C25+$A25-1,0,IF($J$5=1,SYD($B25,$D25,$C25,J$12),SLN($B25,$D25,$C25)))) -> 12100 | K25: =IF($A25>K$12,0,IF(K$12>$C25+$A25-1,0,IF($J$5=1,SYD($B25,$D25,$C25,K$12),SLN($B25,$D25,$C25)))) -> 12100 | L25: =IF($A25>L$12,0,IF(L$12>$C25+$A25-1,0,IF($J$5=1,SYD($B25,$D25,$C25,L$12),SLN($B25,$D25,$C25)))) -> 12100 | M25: =IF($A25>M$12,0,IF(M$12>$C25+$A25-1,0,IF($J$5=1,SYD($B25,$D25,$C25,M$12),SLN($B25,$D25,$C25)))) -> 12100 | ... O25: =IF($A25>O$12,0,IF(O$12>$C25+$A25-1,0,IF($J$5=1,SYD($B25,$D25,$C25,O$12),SLN($B25,$D25,$C25)))) -> 12100
A26: =H12 -> 3 | B26: =IF(capex_interval="",0,IF(capex_start_year="",0,IF($A26<capex_start_year,0,IF(MOD($A26-capex_start_year,capex_interval)=0,Inc_St!$F$8*capex,0)))) -> 133100 | C26: 15 | F26: =IF($A26>F$12,0,IF(F$12>$C26+$A26-1,0,IF($J$5=1,SYD($B26,$D26,$C26,F$12),SLN($B26,$D26,$C26)))) -> 0 | G26: =IF($A26>G$12,0,IF(G$12>$C26+$A26-1,0,IF($J$5=1,SYD($B26,$D26,$C26,G$12),SLN($B26,$D26,$C26)))) -> 0 | H26: =IF($A26>H$12,0,IF(H$12>$C26+$A26-1,0,IF($J$5=1,SYD($B26,$D26,$C26,H$12),SLN($B26,$D26,$C26)))) -> 8873.3333 | I26: =IF($A26>I$12,0,IF(I$12>$C26+$A26-1,0,IF($J$5=1,SYD($B26,$D26,$C26,I$12),SLN($B26,$D26,$C26)))) -> 8873.3333 | J26: =IF($A26>J$12,0,IF(J$12>$C26+$A26-1,0,IF($J$5=1,SYD($B26,$D26,$C26,J$12),SLN($B26,$D26,$C26)))) -> 8873.3333 | K26: =IF($A26>K$12,0,IF(K$12>$C26+$A26-1,0,IF($J$5=1,SYD($B26,$D26,$C26,K$12),SLN($B26,$D26,$C26)))) -> 8873.3333 | L26: =IF($A26>L$12,0,IF(L$12>$C26+$A26-1,0,IF($J$5=1,SYD($B26,$D26,$C26,L$12),SLN($B26,$D26,$C26)))) -> 8873.3333 | M26: =IF($A26>M$12,0,IF(M$12>$C26+$A26-1,0,IF($J$5=1,SYD($B26,$D26,$C26,M$12),SLN($B26,$D26,$C26)))) -> 8873.3333 | ... O26: =IF($A26>O$12,0,IF(O$12>$C26+$A26-1,0,IF($J$5=1,SYD($B26,$D26,$C26,O$12),SLN($B26,$D26,$C26)))) -> 8873.3333
A27: =I12 -> 4 | B27: =IF(capex_interval="",0,IF(capex_start_year="",0,IF($A27<capex_start_year,0,IF(MOD($A27-capex_start_year,capex_interval)=0,Inc_St!$G$8*capex,0)))) -> 146410 | C27: 14 | F27: =IF($A27>F$12,0,IF(F$12>$C27+$A27-1,0,IF($J$5=1,SYD($B27,$D27,$C27,F$12),SLN($B27,$D27,$C27)))) -> 0 | G27: =IF($A27>G$12,0,IF(G$12>$C27+$A27-1,0,IF($J$5=1,SYD($B27,$D27,$C27,G$12),SLN($B27,$D27,$C27)))) -> 0 | H27: =IF($A27>H$12,0,IF(H$12>$C27+$A27-1,0,IF($J$5=1,SYD($B27,$D27,$C27,H$12),SLN($B27,$D27,$C27)))) -> 0 | I27: =IF($A27>I$12,0,IF(I$12>$C27+$A27-1,0,IF($J$5=1,SYD($B27,$D27,$C27,I$12),SLN($B27,$D27,$C27)))) -> 10457.857 | J27: =IF($A27>J$12,0,IF(J$12>$C27+$A27-1,0,IF($J$5=1,SYD($B27,$D27,$C27,J$12),SLN($B27,$D27,$C27)))) -> 10457.857 | K27: =IF($A27>K$12,0,IF(K$12>$C27+$A27-1,0,IF($J$5=1,SYD($B27,$D27,$C27,K$12),SLN($B27,$D27,$C27)))) -> 10457.857 | L27: =IF($A27>L$12,0,IF(L$12>$C27+$A27-1,0,IF($J$5=1,SYD($B27,$D27,$C27,L$12),SLN($B27,$D27,$C27)))) -> 10457.857 | M27: =IF($A27>M$12,0,IF(M$12>$C27+$A27-1,0,IF($J$5=1,SYD($B27,$D27,$C27,M$12),SLN($B27,$D27,$C27)))) -> 10457.857 | ... O27: =IF($A27>O$12,0,IF(O$12>$C27+$A27-1,0,IF($J$5=1,SYD($B27,$D27,$C27,O$12),SLN($B27,$D27,$C27)))) -> 10457.857
A28: =J12 -> 5 | B28: =IF(capex_interval="",0,IF(capex_start_year="",0,IF($A28<capex_start_year,0,IF(MOD($A28-capex_start_year,capex_interval)=0,Inc_St!$H$8*capex,0)))) -> 161051 | C28: 12 | F28: =IF($A28>F$12,0,IF(F$12>$C28+$A28-1,0,IF($J$5=1,SYD($B28,$D28,$C28,F$12),SLN($B28,$D28,$C28)))) -> 0 | G28: =IF($A28>G$12,0,IF(G$12>$C28+$A28-1,0,IF($J$5=1,SYD($B28,$D28,$C28,G$12),SLN($B28,$D28,$C28)))) -> 0 | H28: =IF($A28>H$12,0,IF(H$12>$C28+$A28-1,0,IF($J$5=1,SYD($B28,$D28,$C28,H$12),SLN($B28,$D28,$C28)))) -> 0 | I28: =IF($A28>I$12,0,IF(I$12>$C28+$A28-1,0,IF($J$5=1,SYD($B28,$D28,$C28,I$12),SLN($B28,$D28,$C28)))) -> 0 | J28: =IF($A28>J$12,0,IF(J$12>$C28+$A28-1,0,IF($J$5=1,SYD($B28,$D28,$C28,J$12),SLN($B28,$D28,$C28)))) -> 13420.917 | K28: =IF($A28>K$12,0,IF(K$12>$C28+$A28-1,0,IF($J$5=1,SYD($B28,$D28,$C28,K$12),SLN($B28,$D28,$C28)))) -> 13420.917 | L28: =IF($A28>L$12,0,IF(L$12>$C28+$A28-1,0,IF($J$5=1,SYD($B28,$D28,$C28,L$12),SLN($B28,$D28,$C28)))) -> 13420.917 | M28: =IF($A28>M$12,0,IF(M$12>$C28+$A28-1,0,IF($J$5=1,SYD($B28,$D28,$C28,M$12),SLN($B28,$D28,$C28)))) -> 13420.917 | ... O28: =IF($A28>O$12,0,IF(O$12>$C28+$A28-1,0,IF($J$5=1,SYD($B28,$D28,$C28,O$12),SLN($B28,$D28,$C28)))) -> 13420.917
A29: =K12 -> 6 | B29: =IF(capex_interval="",0,IF(capex_start_year="",0,IF($A29<capex_start_year,0,IF(MOD($A29-capex_start_year,capex_interval)=0,Inc_St!$I$8*capex,0)))) -> 177156.1 | C29: 16 | F29: =IF($A29>F$12,0,IF(F$12>$C29+$A29-1,0,IF($J$5=1,SYD($B29,$D29,$C29,F$12),SLN($B29,$D29,$C29)))) -> 0 | G29: =IF($A29>G$12,0,IF(G$12>$C29+$A29-1,0,IF($J$5=1,SYD($B29,$D29,$C29,G$12),SLN($B29,$D29,$C29)))) -> 0 | H29: =IF($A29>H$12,0,IF(H$12>$C29+$A29-1,0,IF($J$5=1,SYD($B29,$D29,$C29,H$12),SLN($B29,$D29,$C29)))) -> 0 | I29: =IF($A29>I$12,0,IF(I$12>$C29+$A29-1,0,IF($J$5=1,SYD($B29,$D29,$C29,I$12),SLN($B29,$D29,$C29)))) -> 0 | J29: =IF($A29>J$12,0,IF(J$12>$C29+$A29-1,0,IF($J$5=1,SYD($B29,$D29,$C29,J$12),SLN($B29,$D29,$C29)))) -> 0 | K29: =IF($A29>K$12,0,IF(K$12>$C29+$A29-1,0,IF($J$5=1,SYD($B29,$D29,$C29,K$12),SLN($B29,$D29,$C29)))) -> 11072.256 | L29: =IF($A29>L$12,0,IF(L$12>$C29+$A29-1,0,IF($J$5=1,SYD($B29,$D29,$C29,L$12),SLN($B29,$D29,$C29)))) -> 11072.256 | M29: =IF($A29>M$12,0,IF(M$12>$C29+$A29-1,0,IF($J$5=1,SYD($B29,$D29,$C29,M$12),SLN($B29,$D29,$C29)))) -> 11072.256 | ... O29: =IF($A29>O$12,0,IF(O$12>$C29+$A29-1,0,IF($J$5=1,SYD($B29,$D29,$C29,O$12),SLN($B29,$D29,$C29)))) -> 11072.256
A30: =L12 -> 7 | B30: =IF(capex_interval="",0,IF(capex_start_year="",0,IF($A30<capex_start_year,0,IF(MOD($A30-capex_start_year,capex_interval)=0,Inc_St!$J$8*capex,0)))) -> 194871.71 | C30: 15 | F30: =IF($A30>F$12,0,IF(F$12>$C30+$A30-1,0,IF($J$5=1,SYD($B30,$D30,$C30,F$12),SLN($B30,$D30,$C30)))) -> 0 | G30: =IF($A30>G$12,0,IF(G$12>$C30+$A30-1,0,IF($J$5=1,SYD($B30,$D30,$C30,G$12),SLN($B30,$D30,$C30)))) -> 0 | H30: =IF($A30>H$12,0,IF(H$12>$C30+$A30-1,0,IF($J$5=1,SYD($B30,$D30,$C30,H$12),SLN($B30,$D30,$C30)))) -> 0 | I30: =IF($A30>I$12,0,IF(I$12>$C30+$A30-1,0,IF($J$5=1,SYD($B30,$D30,$C30,I$12),SLN($B30,$D30,$C30)))) -> 0 | J30: =IF($A30>J$12,0,IF(J$12>$C30+$A30-1,0,IF($J$5=1,SYD($B30,$D30,$C30,J$12),SLN($B30,$D30,$C30)))) -> 0 | K30: =IF($A30>K$12,0,IF(K$12>$C30+$A30-1,0,IF($J$5=1,SYD($B30,$D30,$C30,K$12),SLN($B30,$D30,$C30)))) -> 0 | L30: =IF($A30>L$12,0,IF(L$12>$C30+$A30-1,0,IF($J$5=1,SYD($B30,$D30,$C30,L$12),SLN($B30,$D30,$C30)))) -> 12991.447 | M30: =IF($A30>M$12,0,IF(M$12>$C30+$A30-1,0,IF($J$5=1,SYD($B30,$D30,$C30,M$12),SLN($B30,$D30,$C30)))) -> 12991.447 | ... O30: =IF($A30>O$12,0,IF(O$12>$C30+$A30-1,0,IF($J$5=1,SYD($B30,$D30,$C30,O$12),SLN($B30,$D30,$C30)))) -> 12991.447
A31: =M12 -> 8 | B31: =IF(capex_interval="",0,IF(capex_start_year="",0,IF($A31<capex_start_year,0,IF(MOD($A31-capex_start_year,capex_interval)=0,Inc_St!$K$8*capex,0)))) -> 214358.88 | C31: 15 | F31: =IF($A31>F$12,0,IF(F$12>$C31+$A31-1,0,IF($J$5=1,SYD($B31,$D31,$C31,F$12),SLN($B31,$D31,$C31)))) -> 0 | G31: =IF($A31>G$12,0,IF(G$12>$C31+$A31-1,0,IF($J$5=1,SYD($B31,$D31,$C31,G$12),SLN($B31,$D31,$C31)))) -> 0 | H31: =IF($A31>H$12,0,IF(H$12>$C31+$A31-1,0,IF($J$5=1,SYD($B31,$D31,$C31,H$12),SLN($B31,$D31,$C31)))) -> 0 | I31: =IF($A31>I$12,0,IF(I$12>$C31+$A31-1,0,IF($J$5=1,SYD($B31,$D31,$C31,I$12),SLN($B31,$D31,$C31)))) -> 0 | J31: =IF($A31>J$12,0,IF(J$12>$C31+$A31-1,0,IF($J$5=1,SYD($B31,$D31,$C31,J$12),SLN($B31,$D31,$C31)))) -> 0 | K31: =IF($A31>K$12,0,IF(K$12>$C31+$A31-1,0,IF($J$5=1,SYD($B31,$D31,$C31,K$12),SLN($B31,$D31,$C31)))) -> 0 | L31: =IF($A31>L$12,0,IF(L$12>$C31+$A31-1,0,IF($J$5=1,SYD($B31,$D31,$C31,L$12),SLN($B31,$D31,$C31)))) -> 0 | M31: =IF($A31>M$12,0,IF(M$12>$C31+$A31-1,0,IF($J$5=1,SYD($B31,$D31,$C31,M$12),SLN($B31,$D31,$C31)))) -> 14290.592 | ... O31: =IF($A31>O$12,0,IF(O$12>$C31+$A31-1,0,IF($J$5=1,SYD($B31,$D31,$C31,O$12),SLN($B31,$D31,$C31)))) -> 14290.592
A32: =N12 -> 9 | B32: =IF(capex_interval="",0,IF(capex_start_year="",0,IF($A32<capex_start_year,0,IF(MOD($A32-capex_start_year,capex_interval)=0,Inc_St!$L$8*capex,0)))) -> 235794.77 | C32: 12 | F32: =IF($A32>F$12,0,IF(F$12>$C32+$A32-1,0,IF($J$5=1,SYD($B32,$D32,$C32,F$12),SLN($B32,$D32,$C32)))) -> 0 | G32: =IF($A32>G$12,0,IF(G$12>$C32+$A32-1,0,IF($J$5=1,SYD($B32,$D32,$C32,G$12),SLN($B32,$D32,$C32)))) -> 0 | H32: =IF($A32>H$12,0,IF(H$12>$C32+$A32-1,0,IF($J$5=1,SYD($B32,$D32,$C32,H$12),SLN($B32,$D32,$C32)))) -> 0 | I32: =IF($A32>I$12,0,IF(I$12>$C32+$A32-1,0,IF($J$5=1,SYD($B32,$D32,$C32,I$12),SLN($B32,$D32,$C32)))) -> 0 | J32: =IF($A32>J$12,0,IF(J$12>$C32+$A32-1,0,IF($J$5=1,SYD($B32,$D32,$C32,J$12),SLN($B32,$D32,$C32)))) -> 0 | K32: =IF($A32>K$12,0,IF(K$12>$C32+$A32-1,0,IF($J$5=1,SYD($B32,$D32,$C32,K$12),SLN($B32,$D32,$C32)))) -> 0 | L32: =IF($A32>L$12,0,IF(L$12>$C32+$A32-1,0,IF($J$5=1,SYD($B32,$D32,$C32,L$12),SLN($B32,$D32,$C32)))) -> 0 | M32: =IF($A32>M$12,0,IF(M$12>$C32+$A32-1,0,IF($J$5=1,SYD($B32,$D32,$C32,M$12),SLN($B32,$D32,$C32)))) -> 0 | ... O32: =IF($A32>O$12,0,IF(O$12>$C32+$A32-1,0,IF($J$5=1,SYD($B32,$D32,$C32,O$12),SLN($B32,$D32,$C32)))) -> 19649.564
A33: =O12 -> 10 | B33: =IF(capex_interval="",0,IF(capex_start_year="",0,IF($A33<capex_start_year,0,IF(MOD($A33-capex_start_year,capex_interval)=0,Inc_St!$M$8*capex,0)))) -> 259374.25 | C33: 12 | F33: =IF($A33>F$12,0,IF(F$12>$C33+$A33-1,0,IF($J$5=1,SYD($B33,$D33,$C33,F$12),SLN($B33,$D33,$C33)))) -> 0 | G33: =IF($A33>G$12,0,IF(G$12>$C33+$A33-1,0,IF($J$5=1,SYD($B33,$D33,$C33,G$12),SLN($B33,$D33,$C33)))) -> 0 | H33: =IF($A33>H$12,0,IF(H$12>$C33+$A33-1,0,IF($J$5=1,SYD($B33,$D33,$C33,H$12),SLN($B33,$D33,$C33)))) -> 0 | I33: =IF($A33>I$12,0,IF(I$12>$C33+$A33-1,0,IF($J$5=1,SYD($B33,$D33,$C33,I$12),SLN($B33,$D33,$C33)))) -> 0 | J33: =IF($A33>J$12,0,IF(J$12>$C33+$A33-1,0,IF($J$5=1,SYD($B33,$D33,$C33,J$12),SLN($B33,$D33,$C33)))) -> 0 | K33: =IF($A33>K$12,0,IF(K$12>$C33+$A33-1,0,IF($J$5=1,SYD($B33,$D33,$C33,K$12),SLN($B33,$D33,$C33)))) -> 0 | L33: =IF($A33>L$12,0,IF(L$12>$C33+$A33-1,0,IF($J$5=1,SYD($B33,$D33,$C33,L$12),SLN($B33,$D33,$C33)))) -> 0 | M33: =IF($A33>M$12,0,IF(M$12>$C33+$A33-1,0,IF($J$5=1,SYD($B33,$D33,$C33,M$12),SLN($B33,$D33,$C33)))) -> 0 | ... O33: =IF($A33>O$12,0,IF(O$12>$C33+$A33-1,0,IF($J$5=1,SYD($B33,$D33,$C33,O$12),SLN($B33,$D33,$C33)))) -> 21614.521
B34: =SUM(B24:B33) -> 1753116.7 | D34: =SUM(D24:D33) -> 0 | F34: =SUM(F24:F33) -> 9166.6667 | G34: =SUM(G24:G33) -> 21266.667 | H34: =SUM(H24:H33) -> 30140 | I34: =SUM(I24:I33) -> 40597.857 | J34: =SUM(J24:J33) -> 54018.774 | K34: =SUM(K24:K33) -> 65091.03 | L34: =SUM(L24:L33) -> 78082.477 | M34: =SUM(M24:M33) -> 92373.069 | ... O34: =SUM(O24:O33) -> 133637.15
A36: Computed Depreciation | F36: =SUM(F20,F34) -> 72745 | G36: =SUM(G20,G34) -> 84845 | H36: =SUM(H20,H34) -> 93718.333 | I36: =SUM(I20,I34) -> 104176.19 | J36: =SUM(J20,J34) -> 117597.11 | K36: =SUM(K20,K34) -> 128669.36 | L36: =SUM(L20,L34) -> 101352.48 | M36: =SUM(M20,M34) -> 115643.07 | ... O36: =SUM(O20,O34) -> 149482.15
A37: Manual Depreciation | F37: 40000 | G37: 40000 | H37: 40000 | I37: 40000 | J37: 40000 | K37: 40000 | L37: 40000 | M37: 40000 | N37: 40000 | O37: 40000
A39: Total Book Depreciation | F39: =IF($J$8=1,F36,F37) -> 72745 | G39: =IF($J$8=1,G36,G37) -> 84845 | H39: =IF($J$8=1,H36,H37) -> 93718.333 | I39: =IF($J$8=1,I36,I37) -> 104176.19 | J39: =IF($J$8=1,J36,J37) -> 117597.11 | K39: =IF($J$8=1,K36,K37) -> 128669.36 | L39: =IF($J$8=1,L36,L37) -> 101352.48 | M39: =IF($J$8=1,M36,M37) -> 115643.07 | ... O39: =IF($J$8=1,O36,O37) -> 149482.15
D41: Period (Yrs)
A42: Amortization of Intangibles (incl Write-up) | D42: 12 | F42: =IF(F$12>$D$42,0,Bal_Sheet!$E$20/$D$42) -> 179.16667 | G42: =IF(G$12>$D$42,0,Bal_Sheet!$E$20/$D$42) -> 179.16667 | H42: =IF(H$12>$D$42,0,Bal_Sheet!$E$20/$D$42) -> 179.16667 | I42: =IF(I$12>$D$42,0,Bal_Sheet!$E$20/$D$42) -> 179.16667 | J42: =IF(J$12>$D$42,0,Bal_Sheet!$E$20/$D$42) -> 179.16667 | K42: =IF(K$12>$D$42,0,Bal_Sheet!$E$20/$D$42) -> 179.16667 | L42: =IF(L$12>$D$42,0,Bal_Sheet!$E$20/$D$42) -> 179.16667 | M42: =IF(M$12>$D$42,0,Bal_Sheet!$E$20/$D$42) -> 179.16667 | ... O42: =IF(O$12>$D$42,0,Bal_Sheet!$E$20/$D$42) -> 179.16667
A43: Impairment of Goodwill | F43: 0 | G43: 0 | H43: 0 | I43: 0 | J43: 0 | K43: 0 | L43: 0 | M43: 0 | N43: 0 | O43: 0
D44: Total Cost ($)
A45: Amortization of Capitalized Financing Costs | D45: =Input!Q34 -> 10887.5 | F45: =SUM(F46:F52) -> 1052.7778 | G45: =SUM(G46:G52) -> 1052.7778 | H45: =SUM(H46:H52) -> 1802.7778 | I45: =SUM(I46:I52) -> 1515.2778 | J45: =SUM(J46:J52) -> 1393.0556 | K45: =SUM(K46:K52) -> 2270.8333 | L45: =SUM(L46:L52) -> 450 | M45: =SUM(M46:M52) -> 450 | ... O45: =SUM(O46:O52) -> 450
A46: =Input!A27 -> Bank Revolver | F46: =IF(F$12>Input!$S$27,0,Input!$R$27) -> 450 | G46: =IF(G$12>Input!$S$27,0,Input!$R$27) -> 450 | H46: =IF(H$12>Input!$S$27,0,Input!$R$27) -> 450 | I46: =IF(I$12>Input!$S$27,0,Input!$R$27) -> 450 | J46: =IF(J$12>Input!$S$27,0,Input!$R$27) -> 450 | K46: =IF(K$12>Input!$S$27,0,Input!$R$27) -> 450 | L46: =IF(L$12>Input!$S$27,0,Input!$R$27) -> 450 | M46: =IF(M$12>Input!$S$27,0,Input!$R$27) -> 450 | ... O46: =IF(O$12>Input!$S$27,0,Input!$R$27) -> 450
A47: =Input!A28 -> Term Loan "A" | F47: =IF(AND(ROUND(Bal_Sheet!F48,2)=0,ROUND(Bal_Sheet!E48,2)>0),Input!$Q28-SUM($E47:E47),(MIN(Input!$Q28-SUM($E47:E47),Input!$R28))) -> 150 | G47: =IF(AND(ROUND(Bal_Sheet!G48,2)=0,ROUND(Bal_Sheet!F48,2)>0),Input!$Q28-SUM($E47:F47),(MIN(Input!$Q28-SUM($E47:F47),Input!$R28))) -> 150 | H47: =IF(AND(ROUND(Bal_Sheet!H48,2)=0,ROUND(Bal_Sheet!G48,2)>0),Input!$Q28-SUM($E47:G47),(MIN(Input!$Q28-SUM($E47:G47),Input!$R28))) -> 900 | I47: =IF(AND(ROUND(Bal_Sheet!I48,2)=0,ROUND(Bal_Sheet!H48,2)>0),Input!$Q28-SUM($E47:H47),(MIN(Input!$Q28-SUM($E47:H47),Input!$R28))) -> 0 | J47: =IF(AND(ROUND(Bal_Sheet!J48,2)=0,ROUND(Bal_Sheet!I48,2)>0),Input!$Q28-SUM($E47:I47),(MIN(Input!$Q28-SUM($E47:I47),Input!$R28))) -> 0 | K47: =IF(AND(ROUND(Bal_Sheet!K48,2)=0,ROUND(Bal_Sheet!J48,2)>0),Input!$Q28-SUM($E47:J47),(MIN(Input!$Q28-SUM($E47:J47),Input!$R28))) -> 0 | L47: =IF(AND(ROUND(Bal_Sheet!L48,2)=0,ROUND(Bal_Sheet!K48,2)>0),Input!$Q28-SUM($E47:K47),(MIN(Input!$Q28-SUM($E47:K47),Input!$R28))) -> 0 | M47: =IF(AND(ROUND(Bal_Sheet!M48,2)=0,ROUND(Bal_Sheet!L48,2)>0),Input!$Q28-SUM($E47:L47),(MIN(Input!$Q28-SUM($E47:L47),Input!$R28))) -> 0 | ... O47: =IF(AND(ROUND(Bal_Sheet!O48,2)=0,ROUND(Bal_Sheet!N48,2)>0),Input!$Q28-SUM($E47:N47),(MIN(Input!$Q28-SUM($E47:N47),Input!$R28))) -> 0
A48: =Input!A29 -> Term Loan "B" | F48: =IF(AND(ROUND(Bal_Sheet!F49,2)=0,ROUND(Bal_Sheet!E49,2)>0),Input!$Q29-SUM($E48:E48),(MIN(Input!$Q29-SUM($E48:E48),Input!$R29))) -> 87.5 | G48: =IF(AND(ROUND(Bal_Sheet!G49,2)=0,ROUND(Bal_Sheet!F49,2)>0),Input!$Q29-SUM($E48:F48),(MIN(Input!$Q29-SUM($E48:F48),Input!$R29))) -> 87.5 | H48: =IF(AND(ROUND(Bal_Sheet!H49,2)=0,ROUND(Bal_Sheet!G49,2)>0),Input!$Q29-SUM($E48:G48),(MIN(Input!$Q29-SUM($E48:G48),Input!$R29))) -> 87.5 | I48: =IF(AND(ROUND(Bal_Sheet!I49,2)=0,ROUND(Bal_Sheet!H49,2)>0),Input!$Q29-SUM($E48:H48),(MIN(Input!$Q29-SUM($E48:H48),Input!$R29))) -> 700 | J48: =IF(AND(ROUND(Bal_Sheet!J49,2)=0,ROUND(Bal_Sheet!I49,2)>0),Input!$Q29-SUM($E48:I48),(MIN(Input!$Q29-SUM($E48:I48),Input!$R29))) -> 0 | K48: =IF(AND(ROUND(Bal_Sheet!K49,2)=0,ROUND(Bal_Sheet!J49,2)>0),Input!$Q29-SUM($E48:J48),(MIN(Input!$Q29-SUM($E48:J48),Input!$R29))) -> 0 | L48: =IF(AND(ROUND(Bal_Sheet!L49,2)=0,ROUND(Bal_Sheet!K49,2)>0),Input!$Q29-SUM($E48:K48),(MIN(Input!$Q29-SUM($E48:K48),Input!$R29))) -> 0 | M48: =IF(AND(ROUND(Bal_Sheet!M49,2)=0,ROUND(Bal_Sheet!L49,2)>0),Input!$Q29-SUM($E48:L48),(MIN(Input!$Q29-SUM($E48:L48),Input!$R29))) -> 0 | ... O48: =IF(AND(ROUND(Bal_Sheet!O49,2)=0,ROUND(Bal_Sheet!N49,2)>0),Input!$Q29-SUM($E48:N48),(MIN(Input!$Q29-SUM($E48:N48),Input!$R29))) -> 0
A49: =Input!A30 -> Senior Notes | F49: =IF(AND(ROUND(Bal_Sheet!F50,2)=0,ROUND(Bal_Sheet!E50,2)>0),Input!$Q30-SUM($E49:E49),(MIN(Input!$Q30-SUM($E49:E49),Input!$R30))) -> 144.44444 | G49: =IF(AND(ROUND(Bal_Sheet!G50,2)=0,ROUND(Bal_Sheet!F50,2)>0),Input!$Q30-SUM($E49:F49),(MIN(Input!$Q30-SUM($E49:F49),Input!$R30))) -> 144.44444 | H49: =IF(AND(ROUND(Bal_Sheet!H50,2)=0,ROUND(Bal_Sheet!G50,2)>0),Input!$Q30-SUM($E49:G49),(MIN(Input!$Q30-SUM($E49:G49),Input!$R30))) -> 144.44444 | I49: =IF(AND(ROUND(Bal_Sheet!I50,2)=0,ROUND(Bal_Sheet!H50,2)>0),Input!$Q30-SUM($E49:H49),(MIN(Input!$Q30-SUM($E49:H49),Input!$R30))) -> 144.44444 | J49: =IF(AND(ROUND(Bal_Sheet!J50,2)=0,ROUND(Bal_Sheet!I50,2)>0),Input!$Q30-SUM($E49:I49),(MIN(Input!$Q30-SUM($E49:I49),Input!$R30))) -> 722.22222 | K49: =IF(AND(ROUND(Bal_Sheet!K50,2)=0,ROUND(Bal_Sheet!J50,2)>0),Input!$Q30-SUM($E49:J49),(MIN(Input!$Q30-SUM($E49:J49),Input!$R30))) -> 0 | L49: =IF(AND(ROUND(Bal_Sheet!L50,2)=0,ROUND(Bal_Sheet!K50,2)>0),Input!$Q30-SUM($E49:K49),(MIN(Input!$Q30-SUM($E49:K49),Input!$R30))) -> 0 | M49: =IF(AND(ROUND(Bal_Sheet!M50,2)=0,ROUND(Bal_Sheet!L50,2)>0),Input!$Q30-SUM($E49:L49),(MIN(Input!$Q30-SUM($E49:L49),Input!$R30))) -> 0 | ... O49: =IF(AND(ROUND(Bal_Sheet!O50,2)=0,ROUND(Bal_Sheet!N50,2)>0),Input!$Q30-SUM($E49:N49),(MIN(Input!$Q30-SUM($E49:N49),Input!$R30))) -> 0
A50: =Input!A31 -> Subordinated Notes | F50: =IF(AND(ROUND(Bal_Sheet!F51,2)=0,ROUND(Bal_Sheet!E51,2)>0),Input!$Q31-SUM($E50:E50),(MIN(Input!$Q31-SUM($E50:E50),Input!$R31))) -> 83.333333 | G50: =IF(AND(ROUND(Bal_Sheet!G51,2)=0,ROUND(Bal_Sheet!F51,2)>0),Input!$Q31-SUM($E50:F50),(MIN(Input!$Q31-SUM($E50:F50),Input!$R31))) -> 83.333333 | H50: =IF(AND(ROUND(Bal_Sheet!H51,2)=0,ROUND(Bal_Sheet!G51,2)>0),Input!$Q31-SUM($E50:G50),(MIN(Input!$Q31-SUM($E50:G50),Input!$R31))) -> 83.333333 | I50: =IF(AND(ROUND(Bal_Sheet!I51,2)=0,ROUND(Bal_Sheet!H51,2)>0),Input!$Q31-SUM($E50:H50),(MIN(Input!$Q31-SUM($E50:H50),Input!$R31))) -> 83.333333 | J50: =IF(AND(ROUND(Bal_Sheet!J51,2)=0,ROUND(Bal_Sheet!I51,2)>0),Input!$Q31-SUM($E50:I50),(MIN(Input!$Q31-SUM($E50:I50),Input!$R31))) -> 83.333333 | K50: =IF(AND(ROUND(Bal_Sheet!K51,2)=0,ROUND(Bal_Sheet!J51,2)>0),Input!$Q31-SUM($E50:J50),(MIN(Input!$Q31-SUM($E50:J50),Input!$R31))) -> 583.33333 | L50: =IF(AND(ROUND(Bal_Sheet!L51,2)=0,ROUND(Bal_Sheet!K51,2)>0),Input!$Q31-SUM($E50:K50),(MIN(Input!$Q31-SUM($E50:K50),Input!$R31))) -> 0 | M50: =IF(AND(ROUND(Bal_Sheet!M51,2)=0,ROUND(Bal_Sheet!L51,2)>0),Input!$Q31-SUM($E50:L50),(MIN(Input!$Q31-SUM($E50:L50),Input!$R31))) -> 0 | ... O50: =IF(AND(ROUND(Bal_Sheet!O51,2)=0,ROUND(Bal_Sheet!N51,2)>0),Input!$Q31-SUM($E50:N50),(MIN(Input!$Q31-SUM($E50:N50),Input!$R31))) -> 0
A51: =Input!A32 -> Mezzanine Debt | F51: =IF(AND(ROUND(Bal_Sheet!F52,2)=0,ROUND(Bal_Sheet!E52,2)>0),Input!$Q32-SUM($E51:E51),(MIN(Input!$Q32-SUM($E51:E51),Input!$R32))) -> 137.5 | G51: =IF(AND(ROUND(Bal_Sheet!G52,2)=0,ROUND(Bal_Sheet!F52,2)>0),Input!$Q32-SUM($E51:F51),(MIN(Input!$Q32-SUM($E51:F51),Input!$R32))) -> 137.5 | H51: =IF(AND(ROUND(Bal_Sheet!H52,2)=0,ROUND(Bal_Sheet!G52,2)>0),Input!$Q32-SUM($E51:G51),(MIN(Input!$Q32-SUM($E51:G51),Input!$R32))) -> 137.5 | I51: =IF(AND(ROUND(Bal_Sheet!I52,2)=0,ROUND(Bal_Sheet!H52,2)>0),Input!$Q32-SUM($E51:H51),(MIN(Input!$Q32-SUM($E51:H51),Input!$R32))) -> 137.5 | J51: =IF(AND(ROUND(Bal_Sheet!J52,2)=0,ROUND(Bal_Sheet!I52,2)>0),Input!$Q32-SUM($E51:I51),(MIN(Input!$Q32-SUM($E51:I51),Input!$R32))) -> 137.5 | K51: =IF(AND(ROUND(Bal_Sheet!K52,2)=0,ROUND(Bal_Sheet!J52,2)>0),Input!$Q32-SUM($E51:J51),(MIN(Input!$Q32-SUM($E51:J51),Input!$R32))) -> 1237.5 | L51: =IF(AND(ROUND(Bal_Sheet!L52,2)=0,ROUND(Bal_Sheet!K52,2)>0),Input!$Q32-SUM($E51:K51),(MIN(Input!$Q32-SUM($E51:K51),Input!$R32))) -> 0 | M51: =IF(AND(ROUND(Bal_Sheet!M52,2)=0,ROUND(Bal_Sheet!L52,2)>0),Input!$Q32-SUM($E51:L51),(MIN(Input!$Q32-SUM($E51:L51),Input!$R32))) -> 0 | ... O51: =IF(AND(ROUND(Bal_Sheet!O52,2)=0,ROUND(Bal_Sheet!N52,2)>0),Input!$Q32-SUM($E51:N51),(MIN(Input!$Q32-SUM($E51:N51),Input!$R32))) -> 0
A52: =Input!A33 -> Seller Notes | F52: =IF(AND(ROUND(Bal_Sheet!F53,2)=0,ROUND(Bal_Sheet!E53,2)>0),Input!$Q33-SUM($E52:E52),(MIN(Input!$Q33-SUM($E52:E52),Input!$R33))) -> 0 | G52: =IF(AND(ROUND(Bal_Sheet!G53,2)=0,ROUND(Bal_Sheet!F53,2)>0),Input!$Q33-SUM($E52:F52),(MIN(Input!$Q33-SUM($E52:F52),Input!$R33))) -> 0 | H52: =IF(AND(ROUND(Bal_Sheet!H53,2)=0,ROUND(Bal_Sheet!G53,2)>0),Input!$Q33-SUM($E52:G52),(MIN(Input!$Q33-SUM($E52:G52),Input!$R33))) -> 0 | I52: =IF(AND(ROUND(Bal_Sheet!I53,2)=0,ROUND(Bal_Sheet!H53,2)>0),Input!$Q33-SUM($E52:H52),(MIN(Input!$Q33-SUM($E52:H52),Input!$R33))) -> 0 | J52: =IF(AND(ROUND(Bal_Sheet!J53,2)=0,ROUND(Bal_Sheet!I53,2)>0),Input!$Q33-SUM($E52:I52),(MIN(Input!$Q33-SUM($E52:I52),Input!$R33))) -> 0 | K52: =IF(AND(ROUND(Bal_Sheet!K53,2)=0,ROUND(Bal_Sheet!J53,2)>0),Input!$Q33-SUM($E52:J52),(MIN(Input!$Q33-SUM($E52:J52),Input!$R33))) -> 0 | L52: =IF(AND(ROUND(Bal_Sheet!L53,2)=0,ROUND(Bal_Sheet!K53,2)>0),Input!$Q33-SUM($E52:K52),(MIN(Input!$Q33-SUM($E52:K52),Input!$R33))) -> 0 | M52: =IF(AND(ROUND(Bal_Sheet!M53,2)=0,ROUND(Bal_Sheet!L53,2)>0),Input!$Q33-SUM($E52:L52),(MIN(Input!$Q33-SUM($E52:L52),Input!$R33))) -> 0 | ... O52: =IF(AND(ROUND(Bal_Sheet!O53,2)=0,ROUND(Bal_Sheet!N53,2)>0),Input!$Q33-SUM($E52:N52),(MIN(Input!$Q33-SUM($E52:N52),Input!$R33))) -> 0
A58: Tax Depreciation & Amortization: | F58: Tax PP&E | H58: 415000 | J58: Depreciation Method
J59: 0 | K59: 0=SLN 1=Sum of Years
A62: Existing PP&E (Tax)
B63: Beginning Amt | C63: Remaining Life | D63: Salvage
A64: Class 1 | B64: 130000 | C64: 12 | D64: 900 | F64: =IF(F$12>$C64,0,IF($J$5=1,SYD($B64,$D64,$C64,F$12),SLN($B64,$D64,$C64))) -> 10758.333 | G64: =IF(G$12>$C64,0,IF($J$5=1,SYD($B64,$D64,$C64,G$12),SLN($B64,$D64,$C64))) -> 10758.333 | H64: =IF(H$12>$C64,0,IF($J$5=1,SYD($B64,$D64,$C64,H$12),SLN($B64,$D64,$C64))) -> 10758.333 | I64: =IF(I$12>$C64,0,IF($J$5=1,SYD($B64,$D64,$C64,I$12),SLN($B64,$D64,$C64))) -> 10758.333 | J64: =IF(J$12>$C64,0,IF($J$5=1,SYD($B64,$D64,$C64,J$12),SLN($B64,$D64,$C64))) -> 10758.333 | K64: =IF(K$12>$C64,0,IF($J$5=1,SYD($B64,$D64,$C64,K$12),SLN($B64,$D64,$C64))) -> 10758.333 | L64: =IF(L$12>$C64,0,IF($J$5=1,SYD($B64,$D64,$C64,L$12),SLN($B64,$D64,$C64))) -> 10758.333 | M64: =IF(M$12>$C64,0,IF($J$5=1,SYD($B64,$D64,$C64,M$12),SLN($B64,$D64,$C64))) -> 10758.333 | ... O64: =IF(O$12>$C64,0,IF($J$5=1,SYD($B64,$D64,$C64,O$12),SLN($B64,$D64,$C64))) -> 10758.333
A65: Class 2 | B65: 105000 | C65: 10 | D65: 800 | F65: =IF(F$12>$C65,0,IF($J$5=1,SYD($B65,$D65,$C65,F$12),SLN($B65,$D65,$C65))) -> 10420 | G65: =IF(G$12>$C65,0,IF($J$5=1,SYD($B65,$D65,$C65,G$12),SLN($B65,$D65,$C65))) -> 10420 | H65: =IF(H$12>$C65,0,IF($J$5=1,SYD($B65,$D65,$C65,H$12),SLN($B65,$D65,$C65))) -> 10420 | I65: =IF(I$12>$C65,0,IF($J$5=1,SYD($B65,$D65,$C65,I$12),SLN($B65,$D65,$C65))) -> 10420 | J65: =IF(J$12>$C65,0,IF($J$5=1,SYD($B65,$D65,$C65,J$12),SLN($B65,$D65,$C65))) -> 10420 | K65: =IF(K$12>$C65,0,IF($J$5=1,SYD($B65,$D65,$C65,K$12),SLN($B65,$D65,$C65))) -> 10420 | L65: =IF(L$12>$C65,0,IF($J$5=1,SYD($B65,$D65,$C65,L$12),SLN($B65,$D65,$C65))) -> 10420 | M65: =IF(M$12>$C65,0,IF($J$5=1,SYD($B65,$D65,$C65,M$12),SLN($B65,$D65,$C65))) -> 10420 | ... O65: =IF(O$12>$C65,0,IF($J$5=1,SYD($B65,$D65,$C65,O$12),SLN($B65,$D65,$C65))) -> 10420
A66: Class 3 | B66: 95000 | C66: 8 | D66: 600 | F66: =IF(F$12>$C66,0,IF($J$5=1,SYD($B66,$D66,$C66,F$12),SLN($B66,$D66,$C66))) -> 11800 | G66: =IF(G$12>$C66,0,IF($J$5=1,SYD($B66,$D66,$C66,G$12),SLN($B66,$D66,$C66))) -> 11800 | H66: =IF(H$12>$C66,0,IF($J$5=1,SYD($B66,$D66,$C66,H$12),SLN($B66,$D66,$C66))) -> 11800 | I66: =IF(I$12>$C66,0,IF($J$5=1,SYD($B66,$D66,$C66,I$12),SLN($B66,$D66,$C66))) -> 11800 | J66: =IF(J$12>$C66,0,IF($J$5=1,SYD($B66,$D66,$C66,J$12),SLN($B66,$D66,$C66))) -> 11800 | K66: =IF(K$12>$C66,0,IF($J$5=1,SYD($B66,$D66,$C66,K$12),SLN($B66,$D66,$C66))) -> 11800 | L66: =IF(L$12>$C66,0,IF($J$5=1,SYD($B66,$D66,$C66,L$12),SLN($B66,$D66,$C66))) -> 11800 | M66: =IF(M$12>$C66,0,IF($J$5=1,SYD($B66,$D66,$C66,M$12),SLN($B66,$D66,$C66))) -> 11800 | ... O66: =IF(O$12>$C66,0,IF($J$5=1,SYD($B66,$D66,$C66,O$12),SLN($B66,$D66,$C66))) -> 0
A67: Class 4 | B67: =H58-SUM(B64:B66) -> 85000 | C67: 6 | D67: 600 | F67: =IF(F$12>$C67,0,IF($J$5=1,SYD($B67,$D67,$C67,F$12),SLN($B67,$D67,$C67))) -> 14066.667 | G67: =IF(G$12>$C67,0,IF($J$5=1,SYD($B67,$D67,$C67,G$12),SLN($B67,$D67,$C67))) -> 14066.667 | H67: =IF(H$12>$C67,0,IF($J$5=1,SYD($B67,$D67,$C67,H$12),SLN($B67,$D67,$C67))) -> 14066.667 | I67: =IF(I$12>$C67,0,IF($J$5=1,SYD($B67,$D67,$C67,I$12),SLN($B67,$D67,$C67))) -> 14066.667 | J67: =IF(J$12>$C67,0,IF($J$5=1,SYD($B67,$D67,$C67,J$12),SLN($B67,$D67,$C67))) -> 14066.667 | K67: =IF(K$12>$C67,0,IF($J$5=1,SYD($B67,$D67,$C67,K$12),SLN($B67,$D67,$C67))) -> 14066.667 | L67: =IF(L$12>$C67,0,IF($J$5=1,SYD($B67,$D67,$C67,L$12),SLN($B67,$D67,$C67))) -> 0 | M67: =IF(M$12>$C67,0,IF($J$5=1,SYD($B67,$D67,$C67,M$12),SLN($B67,$D67,$C67))) -> 0 | ... O67: =IF(O$12>$C67,0,IF($J$5=1,SYD($B67,$D67,$C67,O$12),SLN($B67,$D67,$C67))) -> 0
B68: =SUM(B64:B67) -> 415000 | D68: =SUM(D64:D67) -> 2900 | F68: =SUM(F64:F67) -> 47045 | G68: =SUM(G64:G67) -> 47045 | H68: =SUM(H64:H67) -> 47045 | I68: =SUM(I64:I67) -> 47045 | J68: =SUM(J64:J67) -> 47045 | K68: =SUM(K64:K67) -> 47045 | L68: =SUM(L64:L67) -> 32978.333 | M68: =SUM(M64:M67) -> 32978.333 | ... O68: =SUM(O64:O67) -> 21178.333
A70: Capex
A71: Year | B71: Capex | C71: Useful Life | D71: Salvage
A72: =F12 -> 1 | B72: =IF(capex_interval="",0,IF(capex_start_year="",0,IF($A72<capex_start_year,0,IF(MOD($A72-capex_start_year,capex_interval)=0,Inc_St!$D$8*capex,0)))) -> 110000 | C72: 12 | F72: =IF($A72>F$12,0,IF(F$12>$C72+$A72-1,0,IF($J$5=1,SYD($B72,$D72,$C72,F$12),SLN($B72,$D72,$C72)))) -> 9166.6667 | G72: =IF($A72>G$12,0,IF(G$12>$C72+$A72-1,0,IF($J$5=1,SYD($B72,$D72,$C72,G$12),SLN($B72,$D72,$C72)))) -> 9166.6667 | H72: =IF($A72>H$12,0,IF(H$12>$C72+$A72-1,0,IF($J$5=1,SYD($B72,$D72,$C72,H$12),SLN($B72,$D72,$C72)))) -> 9166.6667 | I72: =IF($A72>I$12,0,IF(I$12>$C72+$A72-1,0,IF($J$5=1,SYD($B72,$D72,$C72,I$12),SLN($B72,$D72,$C72)))) -> 9166.6667 | J72: =IF($A72>J$12,0,IF(J$12>$C72+$A72-1,0,IF($J$5=1,SYD($B72,$D72,$C72,J$12),SLN($B72,$D72,$C72)))) -> 9166.6667 | K72: =IF($A72>K$12,0,IF(K$12>$C72+$A72-1,0,IF($J$5=1,SYD($B72,$D72,$C72,K$12),SLN($B72,$D72,$C72)))) -> 9166.6667 | L72: =IF($A72>L$12,0,IF(L$12>$C72+$A72-1,0,IF($J$5=1,SYD($B72,$D72,$C72,L$12),SLN($B72,$D72,$C72)))) -> 9166.6667 | M72: =IF($A72>M$12,0,IF(M$12>$C72+$A72-1,0,IF($J$5=1,SYD($B72,$D72,$C72,M$12),SLN($B72,$D72,$C72)))) -> 9166.6667 | ... O72: =IF($A72>O$12,0,IF(O$12>$C72+$A72-1,0,IF($J$5=1,SYD($B72,$D72,$C72,O$12),SLN($B72,$D72,$C72)))) -> 9166.6667
A73: =G12 -> 2 | B73: =IF(capex_interval="",0,IF(capex_start_year="",0,IF($A73<capex_start_year,0,IF(MOD($A73-capex_start_year,capex_interval)=0,Inc_St!$E$8*capex,0)))) -> 121000 | C73: 8 | F73: =IF($A73>F$12,0,IF(F$12>$C73+$A73-1,0,IF($J$5=1,SYD($B73,$D73,$C73,F$12),SLN($B73,$D73,$C73)))) -> 0 | G73: =IF($A73>G$12,0,IF(G$12>$C73+$A73-1,0,IF($J$5=1,SYD($B73,$D73,$C73,G$12),SLN($B73,$D73,$C73)))) -> 15125 | H73: =IF($A73>H$12,0,IF(H$12>$C73+$A73-1,0,IF($J$5=1,SYD($B73,$D73,$C73,H$12),SLN($B73,$D73,$C73)))) -> 15125 | I73: =IF($A73>I$12,0,IF(I$12>$C73+$A73-1,0,IF($J$5=1,SYD($B73,$D73,$C73,I$12),SLN($B73,$D73,$C73)))) -> 15125 | J73: =IF($A73>J$12,0,IF(J$12>$C73+$A73-1,0,IF($J$5=1,SYD($B73,$D73,$C73,J$12),SLN($B73,$D73,$C73)))) -> 15125 | K73: =IF($A73>K$12,0,IF(K$12>$C73+$A73-1,0,IF($J$5=1,SYD($B73,$D73,$C73,K$12),SLN($B73,$D73,$C73)))) -> 15125 | L73: =IF($A73>L$12,0,IF(L$12>$C73+$A73-1,0,IF($J$5=1,SYD($B73,$D73,$C73,L$12),SLN($B73,$D73,$C73)))) -> 15125 | M73: =IF($A73>M$12,0,IF(M$12>$C73+$A73-1,0,IF($J$5=1,SYD($B73,$D73,$C73,M$12),SLN($B73,$D73,$C73)))) -> 15125 | ... O73: =IF($A73>O$12,0,IF(O$12>$C73+$A73-1,0,IF($J$5=1,SYD($B73,$D73,$C73,O$12),SLN($B73,$D73,$C73)))) -> 0
A74: =H12 -> 3 | B74: =IF(capex_interval="",0,IF(capex_start_year="",0,IF($A74<capex_start_year,0,IF(MOD($A74-capex_start_year,capex_interval)=0,Inc_St!$F$8*capex,0)))) -> 133100 | C74: 15 | F74: =IF($A74>F$12,0,IF(F$12>$C74+$A74-1,0,IF($J$5=1,SYD($B74,$D74,$C74,F$12),SLN($B74,$D74,$C74)))) -> 0 | G74: =IF($A74>G$12,0,IF(G$12>$C74+$A74-1,0,IF($J$5=1,SYD($B74,$D74,$C74,G$12),SLN($B74,$D74,$C74)))) -> 0 | H74: =IF($A74>H$12,0,IF(H$12>$C74+$A74-1,0,IF($J$5=1,SYD($B74,$D74,$C74,H$12),SLN($B74,$D74,$C74)))) -> 8873.3333 | I74: =IF($A74>I$12,0,IF(I$12>$C74+$A74-1,0,IF($J$5=1,SYD($B74,$D74,$C74,I$12),SLN($B74,$D74,$C74)))) -> 8873.3333 | J74: =IF($A74>J$12,0,IF(J$12>$C74+$A74-1,0,IF($J$5=1,SYD($B74,$D74,$C74,J$12),SLN($B74,$D74,$C74)))) -> 8873.3333 | K74: =IF($A74>K$12,0,IF(K$12>$C74+$A74-1,0,IF($J$5=1,SYD($B74,$D74,$C74,K$12),SLN($B74,$D74,$C74)))) -> 8873.3333 | L74: =IF($A74>L$12,0,IF(L$12>$C74+$A74-1,0,IF($J$5=1,SYD($B74,$D74,$C74,L$12),SLN($B74,$D74,$C74)))) -> 8873.3333 | M74: =IF($A74>M$12,0,IF(M$12>$C74+$A74-1,0,IF($J$5=1,SYD($B74,$D74,$C74,M$12),SLN($B74,$D74,$C74)))) -> 8873.3333 | ... O74: =IF($A74>O$12,0,IF(O$12>$C74+$A74-1,0,IF($J$5=1,SYD($B74,$D74,$C74,O$12),SLN($B74,$D74,$C74)))) -> 8873.3333
A75: =I12 -> 4 | B75: =IF(capex_interval="",0,IF(capex_start_year="",0,IF($A75<capex_start_year,0,IF(MOD($A75-capex_start_year,capex_interval)=0,Inc_St!$G$8*capex,0)))) -> 146410 | C75: 9 | F75: =IF($A75>F$12,0,IF(F$12>$C75+$A75-1,0,IF($J$5=1,SYD($B75,$D75,$C75,F$12),SLN($B75,$D75,$C75)))) -> 0 | G75: =IF($A75>G$12,0,IF(G$12>$C75+$A75-1,0,IF($J$5=1,SYD($B75,$D75,$C75,G$12),SLN($B75,$D75,$C75)))) -> 0 | H75: =IF($A75>H$12,0,IF(H$12>$C75+$A75-1,0,IF($J$5=1,SYD($B75,$D75,$C75,H$12),SLN($B75,$D75,$C75)))) -> 0 | I75: =IF($A75>I$12,0,IF(I$12>$C75+$A75-1,0,IF($J$5=1,SYD($B75,$D75,$C75,I$12),SLN($B75,$D75,$C75)))) -> 16267.778 | J75: =IF($A75>J$12,0,IF(J$12>$C75+$A75-1,0,IF($J$5=1,SYD($B75,$D75,$C75,J$12),SLN($B75,$D75,$C75)))) -> 16267.778 | K75: =IF($A75>K$12,0,IF(K$12>$C75+$A75-1,0,IF($J$5=1,SYD($B75,$D75,$C75,K$12),SLN($B75,$D75,$C75)))) -> 16267.778 | L75: =IF($A75>L$12,0,IF(L$12>$C75+$A75-1,0,IF($J$5=1,SYD($B75,$D75,$C75,L$12),SLN($B75,$D75,$C75)))) -> 16267.778 | M75: =IF($A75>M$12,0,IF(M$12>$C75+$A75-1,0,IF($J$5=1,SYD($B75,$D75,$C75,M$12),SLN($B75,$D75,$C75)))) -> 16267.778 | ... O75: =IF($A75>O$12,0,IF(O$12>$C75+$A75-1,0,IF($J$5=1,SYD($B75,$D75,$C75,O$12),SLN($B75,$D75,$C75)))) -> 16267.778
A76: =J12 -> 5 | B76: =IF(capex_interval="",0,IF(capex_start_year="",0,IF($A76<capex_start_year,0,IF(MOD($A76-capex_start_year,capex_interval)=0,Inc_St!$H$8*capex,0)))) -> 161051 | C76: 4 | F76: =IF($A76>F$12,0,IF(F$12>$C76+$A76-1,0,IF($J$5=1,SYD($B76,$D76,$C76,F$12),SLN($B76,$D76,$C76)))) -> 0 | G76: =IF($A76>G$12,0,IF(G$12>$C76+$A76-1,0,IF($J$5=1,SYD($B76,$D76,$C76,G$12),SLN($B76,$D76,$C76)))) -> 0 | H76: =IF($A76>H$12,0,IF(H$12>$C76+$A76-1,0,IF($J$5=1,SYD($B76,$D76,$C76,H$12),SLN($B76,$D76,$C76)))) -> 0 | I76: =IF($A76>I$12,0,IF(I$12>$C76+$A76-1,0,IF($J$5=1,SYD($B76,$D76,$C76,I$12),SLN($B76,$D76,$C76)))) -> 0 | J76: =IF($A76>J$12,0,IF(J$12>$C76+$A76-1,0,IF($J$5=1,SYD($B76,$D76,$C76,J$12),SLN($B76,$D76,$C76)))) -> 40262.75 | K76: =IF($A76>K$12,0,IF(K$12>$C76+$A76-1,0,IF($J$5=1,SYD($B76,$D76,$C76,K$12),SLN($B76,$D76,$C76)))) -> 40262.75 | L76: =IF($A76>L$12,0,IF(L$12>$C76+$A76-1,0,IF($J$5=1,SYD($B76,$D76,$C76,L$12),SLN($B76,$D76,$C76)))) -> 40262.75 | M76: =IF($A76>M$12,0,IF(M$12>$C76+$A76-1,0,IF($J$5=1,SYD($B76,$D76,$C76,M$12),SLN($B76,$D76,$C76)))) -> 40262.75 | ... O76: =IF($A76>O$12,0,IF(O$12>$C76+$A76-1,0,IF($J$5=1,SYD($B76,$D76,$C76,O$12),SLN($B76,$D76,$C76)))) -> 0
A77: =K12 -> 6 | B77: =IF(capex_interval="",0,IF(capex_start_year="",0,IF($A77<capex_start_year,0,IF(MOD($A77-capex_start_year,capex_interval)=0,Inc_St!$I$8*capex,0)))) -> 177156.1 | C77: 16 | F77: =IF($A77>F$12,0,IF(F$12>$C77+$A77-1,0,IF($J$5=1,SYD($B77,$D77,$C77,F$12),SLN($B77,$D77,$C77)))) -> 0 | G77: =IF($A77>G$12,0,IF(G$12>$C77+$A77-1,0,IF($J$5=1,SYD($B77,$D77,$C77,G$12),SLN($B77,$D77,$C77)))) -> 0 | H77: =IF($A77>H$12,0,IF(H$12>$C77+$A77-1,0,IF($J$5=1,SYD($B77,$D77,$C77,H$12),SLN($B77,$D77,$C77)))) -> 0 | I77: =IF($A77>I$12,0,IF(I$12>$C77+$A77-1,0,IF($J$5=1,SYD($B77,$D77,$C77,I$12),SLN($B77,$D77,$C77)))) -> 0 | J77: =IF($A77>J$12,0,IF(J$12>$C77+$A77-1,0,IF($J$5=1,SYD($B77,$D77,$C77,J$12),SLN($B77,$D77,$C77)))) -> 0 | K77: =IF($A77>K$12,0,IF(K$12>$C77+$A77-1,0,IF($J$5=1,SYD($B77,$D77,$C77,K$12),SLN($B77,$D77,$C77)))) -> 11072.256 | L77: =IF($A77>L$12,0,IF(L$12>$C77+$A77-1,0,IF($J$5=1,SYD($B77,$D77,$C77,L$12),SLN($B77,$D77,$C77)))) -> 11072.256 | M77: =IF($A77>M$12,0,IF(M$12>$C77+$A77-1,0,IF($J$5=1,SYD($B77,$D77,$C77,M$12),SLN($B77,$D77,$C77)))) -> 11072.256 | ... O77: =IF($A77>O$12,0,IF(O$12>$C77+$A77-1,0,IF($J$5=1,SYD($B77,$D77,$C77,O$12),SLN($B77,$D77,$C77)))) -> 11072.256
A78: =L12 -> 7 | B78: =IF(capex_interval="",0,IF(capex_start_year="",0,IF($A78<capex_start_year,0,IF(MOD($A78-capex_start_year,capex_interval)=0,Inc_St!$J$8*capex,0)))) -> 194871.71 | C78: 15 | F78: =IF($A78>F$12,0,IF(F$12>$C78+$A78-1,0,IF($J$5=1,SYD($B78,$D78,$C78,F$12),SLN($B78,$D78,$C78)))) -> 0 | G78: =IF($A78>G$12,0,IF(G$12>$C78+$A78-1,0,IF($J$5=1,SYD($B78,$D78,$C78,G$12),SLN($B78,$D78,$C78)))) -> 0 | H78: =IF($A78>H$12,0,IF(H$12>$C78+$A78-1,0,IF($J$5=1,SYD($B78,$D78,$C78,H$12),SLN($B78,$D78,$C78)))) -> 0 | I78: =IF($A78>I$12,0,IF(I$12>$C78+$A78-1,0,IF($J$5=1,SYD($B78,$D78,$C78,I$12),SLN($B78,$D78,$C78)))) -> 0 | J78: =IF($A78>J$12,0,IF(J$12>$C78+$A78-1,0,IF($J$5=1,SYD($B78,$D78,$C78,J$12),SLN($B78,$D78,$C78)))) -> 0 | K78: =IF($A78>K$12,0,IF(K$12>$C78+$A78-1,0,IF($J$5=1,SYD($B78,$D78,$C78,K$12),SLN($B78,$D78,$C78)))) -> 0 | L78: =IF($A78>L$12,0,IF(L$12>$C78+$A78-1,0,IF($J$5=1,SYD($B78,$D78,$C78,L$12),SLN($B78,$D78,$C78)))) -> 12991.447 | M78: =IF($A78>M$12,0,IF(M$12>$C78+$A78-1,0,IF($J$5=1,SYD($B78,$D78,$C78,M$12),SLN($B78,$D78,$C78)))) -> 12991.447 | ... O78: =IF($A78>O$12,0,IF(O$12>$C78+$A78-1,0,IF($J$5=1,SYD($B78,$D78,$C78,O$12),SLN($B78,$D78,$C78)))) -> 12991.447
A79: =M12 -> 8 | B79: =IF(capex_interval="",0,IF(capex_start_year="",0,IF($A79<capex_start_year,0,IF(MOD($A79-capex_start_year,capex_interval)=0,Inc_St!$K$8*capex,0)))) -> 214358.88 | C79: 2 | F79: =IF($A79>F$12,0,IF(F$12>$C79+$A79-1,0,IF($J$5=1,SYD($B79,$D79,$C79,F$12),SLN($B79,$D79,$C79)))) -> 0 | G79: =IF($A79>G$12,0,IF(G$12>$C79+$A79-1,0,IF($J$5=1,SYD($B79,$D79,$C79,G$12),SLN($B79,$D79,$C79)))) -> 0 | H79: =IF($A79>H$12,0,IF(H$12>$C79+$A79-1,0,IF($J$5=1,SYD($B79,$D79,$C79,H$12),SLN($B79,$D79,$C79)))) -> 0 | I79: =IF($A79>I$12,0,IF(I$12>$C79+$A79-1,0,IF($J$5=1,SYD($B79,$D79,$C79,I$12),SLN($B79,$D79,$C79)))) -> 0 | J79: =IF($A79>J$12,0,IF(J$12>$C79+$A79-1,0,IF($J$5=1,SYD($B79,$D79,$C79,J$12),SLN($B79,$D79,$C79)))) -> 0 | K79: =IF($A79>K$12,0,IF(K$12>$C79+$A79-1,0,IF($J$5=1,SYD($B79,$D79,$C79,K$12),SLN($B79,$D79,$C79)))) -> 0 | L79: =IF($A79>L$12,0,IF(L$12>$C79+$A79-1,0,IF($J$5=1,SYD($B79,$D79,$C79,L$12),SLN($B79,$D79,$C79)))) -> 0 | M79: =IF($A79>M$12,0,IF(M$12>$C79+$A79-1,0,IF($J$5=1,SYD($B79,$D79,$C79,M$12),SLN($B79,$D79,$C79)))) -> 107179.44 | ... O79: =IF($A79>O$12,0,IF(O$12>$C79+$A79-1,0,IF($J$5=1,SYD($B79,$D79,$C79,O$12),SLN($B79,$D79,$C79)))) -> 0
A80: =N12 -> 9 | B80: =IF(capex_interval="",0,IF(capex_start_year="",0,IF($A80<capex_start_year,0,IF(MOD($A80-capex_start_year,capex_interval)=0,Inc_St!$L$8*capex,0)))) -> 235794.77 | C80: 12 | F80: =IF($A80>F$12,0,IF(F$12>$C80+$A80-1,0,IF($J$5=1,SYD($B80,$D80,$C80,F$12),SLN($B80,$D80,$C80)))) -> 0 | G80: =IF($A80>G$12,0,IF(G$12>$C80+$A80-1,0,IF($J$5=1,SYD($B80,$D80,$C80,G$12),SLN($B80,$D80,$C80)))) -> 0 | H80: =IF($A80>H$12,0,IF(H$12>$C80+$A80-1,0,IF($J$5=1,SYD($B80,$D80,$C80,H$12),SLN($B80,$D80,$C80)))) -> 0 | I80: =IF($A80>I$12,0,IF(I$12>$C80+$A80-1,0,IF($J$5=1,SYD($B80,$D80,$C80,I$12),SLN($B80,$D80,$C80)))) -> 0 | J80: =IF($A80>J$12,0,IF(J$12>$C80+$A80-1,0,IF($J$5=1,SYD($B80,$D80,$C80,J$12),SLN($B80,$D80,$C80)))) -> 0 | K80: =IF($A80>K$12,0,IF(K$12>$C80+$A80-1,0,IF($J$5=1,SYD($B80,$D80,$C80,K$12),SLN($B80,$D80,$C80)))) -> 0 | L80: =IF($A80>L$12,0,IF(L$12>$C80+$A80-1,0,IF($J$5=1,SYD($B80,$D80,$C80,L$12),SLN($B80,$D80,$C80)))) -> 0 | M80: =IF($A80>M$12,0,IF(M$12>$C80+$A80-1,0,IF($J$5=1,SYD($B80,$D80,$C80,M$12),SLN($B80,$D80,$C80)))) -> 0 | ... O80: =IF($A80>O$12,0,IF(O$12>$C80+$A80-1,0,IF($J$5=1,SYD($B80,$D80,$C80,O$12),SLN($B80,$D80,$C80)))) -> 19649.564
A81: =O12 -> 10 | B81: =IF(capex_interval="",0,IF(capex_start_year="",0,IF($A81<capex_start_year,0,IF(MOD($A81-capex_start_year,capex_interval)=0,Inc_St!$M$8*capex,0)))) -> 259374.25 | C81: 12 | F81: =IF($A81>F$12,0,IF(F$12>$C81+$A81-1,0,IF($J$5=1,SYD($B81,$D81,$C81,F$12),SLN($B81,$D81,$C81)))) -> 0 | G81: =IF($A81>G$12,0,IF(G$12>$C81+$A81-1,0,IF($J$5=1,SYD($B81,$D81,$C81,G$12),SLN($B81,$D81,$C81)))) -> 0 | H81: =IF($A81>H$12,0,IF(H$12>$C81+$A81-1,0,IF($J$5=1,SYD($B81,$D81,$C81,H$12),SLN($B81,$D81,$C81)))) -> 0 | I81: =IF($A81>I$12,0,IF(I$12>$C81+$A81-1,0,IF($J$5=1,SYD($B81,$D81,$C81,I$12),SLN($B81,$D81,$C81)))) -> 0 | J81: =IF($A81>J$12,0,IF(J$12>$C81+$A81-1,0,IF($J$5=1,SYD($B81,$D81,$C81,J$12),SLN($B81,$D81,$C81)))) -> 0 | K81: =IF($A81>K$12,0,IF(K$12>$C81+$A81-1,0,IF($J$5=1,SYD($B81,$D81,$C81,K$12),SLN($B81,$D81,$C81)))) -> 0 | L81: =IF($A81>L$12,0,IF(L$12>$C81+$A81-1,0,IF($J$5=1,SYD($B81,$D81,$C81,L$12),SLN($B81,$D81,$C81)))) -> 0 | M81: =IF($A81>M$12,0,IF(M$12>$C81+$A81-1,0,IF($J$5=1,SYD($B81,$D81,$C81,M$12),SLN($B81,$D81,$C81)))) -> 0 | ... O81: =IF($A81>O$12,0,IF(O$12>$C81+$A81-1,0,IF($J$5=1,SYD($B81,$D81,$C81,O$12),SLN($B81,$D81,$C81)))) -> 21614.521
B82: =SUM(B72:B81) -> 1753116.7 | D82: =SUM(D72:D81) -> 0 | F82: =SUM(F72:F81) -> 9166.6667 | G82: =SUM(G72:G81) -> 24291.667 | H82: =SUM(H72:H81) -> 33165 | I82: =SUM(I72:I81) -> 49432.778 | J82: =SUM(J72:J81) -> 89695.528 | K82: =SUM(K72:K81) -> 100767.78 | L82: =SUM(L72:L81) -> 113759.23 | M82: =SUM(M72:M81) -> 220938.67 | ... O82: =SUM(O72:O81) -> 99635.566
A84: Total Tax Depreciation | F84: =SUM(F68,F82) -> 56211.667 | G84: =SUM(G68,G82) -> 71336.667 | H84: =SUM(H68,H82) -> 80210 | I84: =SUM(I68,I82) -> 96477.778 | J84: =SUM(J68,J82) -> 136740.53 | K84: =SUM(K68,K82) -> 147812.78 | L84: =SUM(L68,L82) -> 146737.56 | M84: =SUM(M68,M82) -> 253917.01 | ... O84: =SUM(O68,O82) -> 120813.9
D86: Period (Yrs)
A87: Amortization of Intangibles (incl Write-up) | D87: 15 | F87: =IF(F$12>$D$87,0,Bal_Sheet!$E$20/$D$87) -> 143.33333 | G87: =IF(G$12>$D$87,0,Bal_Sheet!$E$20/$D$87) -> 143.33333 | H87: =IF(H$12>$D$87,0,Bal_Sheet!$E$20/$D$87) -> 143.33333 | I87: =IF(I$12>$D$87,0,Bal_Sheet!$E$20/$D$87) -> 143.33333 | J87: =IF(J$12>$D$87,0,Bal_Sheet!$E$20/$D$87) -> 143.33333 | K87: =IF(K$12>$D$87,0,Bal_Sheet!$E$20/$D$87) -> 143.33333 | L87: =IF(L$12>$D$87,0,Bal_Sheet!$E$20/$D$87) -> 143.33333 | M87: =IF(M$12>$D$87,0,Bal_Sheet!$E$20/$D$87) -> 143.33333 | ... O87: =IF(O$12>$D$87,0,Bal_Sheet!$E$20/$D$87) -> 143.33333
A88: Amortization of Goodwill | D88: 15 | F88: =IF(F$12>$D$88,0,Bal_Sheet!$E$19/$D$88) -> 14098.567 | G88: =IF(G$12>$D$88,0,Bal_Sheet!$E$19/$D$88) -> 14098.567 | H88: =IF(H$12>$D$88,0,Bal_Sheet!$E$19/$D$88) -> 14098.567 | I88: =IF(I$12>$D$88,0,Bal_Sheet!$E$19/$D$88) -> 14098.567 | J88: =IF(J$12>$D$88,0,Bal_Sheet!$E$19/$D$88) -> 14098.567 | K88: =IF(K$12>$D$88,0,Bal_Sheet!$E$19/$D$88) -> 14098.567 | L88: =IF(L$12>$D$88,0,Bal_Sheet!$E$19/$D$88) -> 14098.567 | M88: =IF(M$12>$D$88,0,Bal_Sheet!$E$19/$D$88) -> 14098.567 | ... O88: =IF(O$12>$D$88,0,Bal_Sheet!$E$19/$D$88) -> 14098.567

Sheet Income_Tax
A2: Income Tax Calculation
A4: Year | D4: =year1 -> 2010 | E4: =D4+1 -> 2011 | F4: =E4+1 -> 2012 | G4: =F4+1 -> 2013 | H4: =G4+1 -> 2014 | I4: =H4+1 -> 2015 | J4: =I4+1 -> 2016 | K4: =J4+1 -> 2017 | L4: =K4+1 -> 2018 | M4: =L4+1 -> 2019
A5: Year No. | D5: 1 | E5: =D5+1 -> 2 | F5: =E5+1 -> 3 | G5: =F5+1 -> 4 | H5: =G5+1 -> 5 | I5: =H5+1 -> 6 | J5: =I5+1 -> 7 | K5: =J5+1 -> 8 | L5: =K5+1 -> 9 | M5: =L5+1 -> 10
A8: Net Income before Tax | D8: =Inc_St!D39 -> 214211.89 | E8: =Inc_St!E39 -> 233238.31 | F8: =Inc_St!F39 -> 259559.13 | G8: =Inc_St!G39 -> 288654.6 | H8: =Inc_St!H39 -> 315807.37 | I8: =Inc_St!I39 -> 350447.09 | J8: =Inc_St!J39 -> 429310.46 | K8: =Inc_St!K39 -> 468774.33 | ... M8: =Inc_St!M39 -> 550799.8
A10: Add: Book Depreciation | D10: =Depr_Amort!F39 -> 72745 | E10: =Depr_Amort!G39 -> 84845 | F10: =Depr_Amort!H39 -> 93718.333 | G10: =Depr_Amort!I39 -> 104176.19 | H10: =Depr_Amort!J39 -> 117597.11 | I10: =Depr_Amort!K39 -> 128669.36 | J10: =Depr_Amort!L39 -> 101352.48 | K10: =Depr_Amort!M39 -> 115643.07 | ... M10: =Depr_Amort!O39 -> 149482.15
A11: Add: Book (Gain) Loss on Assets Sale | D11: =D48 -> 1250 | E11: =E48 -> 1350 | F11: =F48 -> 1450 | G11: =G48 -> 1550 | H11: =H48 -> 1650 | I11: =I48 -> 1750 | J11: =J48 -> 1850 | K11: =K48 -> 1950 | ... M11: =M48 -> 2150
A12: Add: Book Impairment of Goodwill | D12: =Depr_Amort!F43 -> 0 | E12: =Depr_Amort!G43 -> 0 | F12: =Depr_Amort!H43 -> 0 | G12: =Depr_Amort!I43 -> 0 | H12: =Depr_Amort!J43 -> 0 | I12: =Depr_Amort!K43 -> 0 | J12: =Depr_Amort!L43 -> 0 | K12: =Depr_Amort!M43 -> 0 | ... M12: =Depr_Amort!O43 -> 0
A13: Add: Book Amortization of Intangibles | D13: =Depr_Amort!F42 -> 179.16667 | E13: =Depr_Amort!G42 -> 179.16667 | F13: =Depr_Amort!H42 -> 179.16667 | G13: =Depr_Amort!I42 -> 179.16667 | H13: =Depr_Amort!J42 -> 179.16667 | I13: =Depr_Amort!K42 -> 179.16667 | J13: =Depr_Amort!L42 -> 179.16667 | K13: =Depr_Amort!M42 -> 179.16667 | ... M13: =Depr_Amort!O42 -> 179.16667
A14: Add: Non-Deductible Expenses | D14: 0 | E14: 0 | F14: 0 | G14: 0 | H14: 0 | I14: 0 | J14: 0 | K14: 0 | L14: 0 | M14: 0
A16: Less: Tax Depreciation | D16: =Depr_Amort!F84 -> 56211.667 | E16: =Depr_Amort!G84 -> 71336.667 | F16: =Depr_Amort!H84 -> 80210 | G16: =Depr_Amort!I84 -> 96477.778 | H16: =Depr_Amort!J84 -> 136740.53 | I16: =Depr_Amort!K84 -> 147812.78 | J16: =Depr_Amort!L84 -> 146737.56 | K16: =Depr_Amort!M84 -> 253917.01 | ... M16: =Depr_Amort!O84 -> 120813.9
A17: Less: Tax (Gain) Loss on Assets Sale | D17: =D49 -> 1350 | E17: =E49 -> 1500 | F17: =F49 -> 1600 | G17: =G49 -> 1700 | H17: =H49 -> 1750 | I17: =I49 -> 1900 | J17: =J49 -> 2000 | K17: =K49 -> 2200 | ... M17: =M49 -> 2500
A18: Less: Tax Amortization of Goodwill | D18: =IF(goodwill_intang_deductible=1,Depr_Amort!F88,0) -> 14098.567 | E18: =IF(goodwill_intang_deductible=1,Depr_Amort!G88,0) -> 14098.567 | F18: =IF(goodwill_intang_deductible=1,Depr_Amort!H88,0) -> 14098.567 | G18: =IF(goodwill_intang_deductible=1,Depr_Amort!I88,0) -> 14098.567 | H18: =IF(goodwill_intang_deductible=1,Depr_Amort!J88,0) -> 14098.567 | I18: =IF(goodwill_intang_deductible=1,Depr_Amort!K88,0) -> 14098.567 | J18: =IF(goodwill_intang_deductible=1,Depr_Amort!L88,0) -> 14098.567 | K18: =IF(goodwill_intang_deductible=1,Depr_Amort!M88,0) -> 14098.567 | ... M18: =IF(goodwill_intang_deductible=1,Depr_Amort!O88,0) -> 14098.567
A19: Less: Tax Amortization of Intangibles | D19: =IF(goodwill_intang_deductible=1,Depr_Amort!F87,0) -> 143.33333 | E19: =IF(goodwill_intang_deductible=1,Depr_Amort!G87,0) -> 143.33333 | F19: =IF(goodwill_intang_deductible=1,Depr_Amort!H87,0) -> 143.33333 | G19: =IF(goodwill_intang_deductible=1,Depr_Amort!I87,0) -> 143.33333 | H19: =IF(goodwill_intang_deductible=1,Depr_Amort!J87,0) -> 143.33333 | I19: =IF(goodwill_intang_deductible=1,Depr_Amort!K87,0) -> 143.33333 | J19: =IF(goodwill_intang_deductible=1,Depr_Amort!L87,0) -> 143.33333 | K19: =IF(goodwill_intang_deductible=1,Depr_Amort!M87,0) -> 143.33333 | ... M19: =IF(goodwill_intang_deductible=1,Depr_Amort!O87,0) -> 143.33333
A21: Pre-NOL Taxable Income | D21: =D8+SUM(D10:D14)-SUM(D16:D19) -> 216582.49 | E21: =E8+SUM(E10:E14)-SUM(E16:E19) -> 232533.91 | F21: =F8+SUM(F10:F14)-SUM(F16:F19) -> 258854.73 | G21: =G8+SUM(G10:G14)-SUM(G16:G19) -> 282140.28 | H21: =H8+SUM(H10:H14)-SUM(H16:H19) -> 282501.22 | I21: =I8+SUM(I10:I14)-SUM(I16:I19) -> 317090.94 | J21: =J8+SUM(J10:J14)-SUM(J16:J19) -> 369712.64 | K21: =K8+SUM(K10:K14)-SUM(K16:K19) -> 316187.66 | ... M21: =M8+SUM(M10:M14)-SUM(M16:M19) -> 565055.32
A23: Less: NOLs Used | D23: =MIN(MAX(0,D21),D33) -> 15500 | E23: =MIN(MAX(0,E21),E33) -> 0 | F23: =MIN(MAX(0,F21),F33) -> 0 | G23: =MIN(MAX(0,G21),G33) -> 0 | H23: =MIN(MAX(0,H21),H33) -> 0 | I23: =MIN(MAX(0,I21),I33) -> 0 | J23: =MIN(MAX(0,J21),J33) -> 0 | K23: =MIN(MAX(0,K21),K33) -> 0 | ... M23: =MIN(MAX(0,M21),M33) -> 0
A25: Post-NOL Taxable Income | D25: =D21-D23 -> 201082.49 | E25: =E21-E23 -> 232533.91 | F25: =F21-F23 -> 258854.73 | G25: =G21-G23 -> 282140.28 | H25: =H21-H23 -> 282501.22 | I25: =I21-I23 -> 317090.94 | J25: =J21-J23 -> 369712.64 | K25: =K21-K23 -> 316187.66 | ... M25: =M21-M23 -> 565055.32
A26: Cash Taxes Payable | D26: =MAX(0,D25)*tax_rate -> 70378.872 | E26: =MAX(0,E25)*tax_rate -> 81386.868 | F26: =MAX(0,F25)*tax_rate -> 90599.157 | G26: =MAX(0,G25)*tax_rate -> 98749.099 | H26: =MAX(0,H25)*tax_rate -> 98875.426 | I26: =MAX(0,I25)*tax_rate -> 110981.83 | J26: =MAX(0,J25)*tax_rate -> 129399.42 | K26: =MAX(0,K25)*tax_rate -> 110665.68 | ... M26: =MAX(0,M25)*tax_rate -> 197769.36
A28: Total Book Tax | D28: =D8*tax_rate+IF(goodwill_intang_deductible=0,D12+D13,0)*tax_rate -> 74974.162 | E28: =E8*tax_rate+IF(goodwill_intang_deductible=0,E12+E13,0)*tax_rate -> 81633.408 | F28: =F8*tax_rate+IF(goodwill_intang_deductible=0,F12+F13,0)*tax_rate -> 90845.697 | G28: =G8*tax_rate+IF(goodwill_intang_deductible=0,G12+G13,0)*tax_rate -> 101029.11 | H28: =H8*tax_rate+IF(goodwill_intang_deductible=0,H12+H13,0)*tax_rate -> 110532.58 | I28: =I8*tax_rate+IF(goodwill_intang_deductible=0,I12+I13,0)*tax_rate -> 122656.48 | J28: =J8*tax_rate+IF(goodwill_intang_deductible=0,J12+J13,0)*tax_rate -> 150258.66 | K28: =K8*tax_rate+IF(goodwill_intang_deductible=0,K12+K13,0)*tax_rate -> 164071.02 | ... M28: =M8*tax_rate+IF(goodwill_intang_deductible=0,M12+M13,0)*tax_rate -> 192779.93
A29: Increase (Decrease) in Deferred
A30: Tax Liability | D30: =D28-D26 -> 4595.29 | E30: =E28-E26 -> 246.54 | F30: =F28-F26 -> 246.54 | G30: =G28-G26 -> 2280.0122 | H30: =H28-H26 -> 11657.154 | I30: =I28-I26 -> 11674.654 | J30: =J28-J26 -> 20859.237 | K30: =K28-K26 -> 53405.334 | ... M30: =M28-M26 -> -4989.4325
A33: Beginning NOL Balance | D33: 15500 | E33: =D36 -> 0 | F33: =E36 -> 0 | G33: =F36 -> 0 | H33: =G36 -> 0 | I33: =H36 -> 0 | J33: =I36 -> 0 | K33: =J36 -> 0 | L33: =K36 -> 0 | M33: =L36 -> 0
A34: Current Year NOL | D34: =MIN(0,D21) -> 0 | E34: =MIN(0,E21) -> 0 | F34: =MIN(0,F21) -> 0 | G34: =MIN(0,G21) -> 0 | H34: =MIN(0,H21) -> 0 | I34: =MIN(0,I21) -> 0 | J34: =MIN(0,J21) -> 0 | K34: =MIN(0,K21) -> 0 | ... M34: =MIN(0,M21) -> 0
A35: NOLs Used | D35: =D23 -> 15500 | E35: =E23 -> 0 | F35: =F23 -> 0 | G35: =G23 -> 0 | H35: =H23 -> 0 | I35: =I23 -> 0 | J35: =J23 -> 0 | K35: =K23 -> 0 | ... M35: =M23 -> 0
A36: Ending NOL Balance | D36: =D33+D34-D35 -> 0 | E36: =E33+E34-E35 -> 0 | F36: =F33+F34-F35 -> 0 | G36: =G33+G34-G35 -> 0 | H36: =H33+H34-H35 -> 0 | I36: =I33+I34-I35 -> 0 | J36: =J33+J34-J35 -> 0 | K36: =K33+K34-K35 -> 0 | ... M36: =M33+M34-M35 -> 0
A41: Projected Asset Sales:
A43: Estimated Sale Proceeds | D43: 4000 | E43: 4500 | F43: 5000 | G43: 5500 | H43: 6000 | I43: 6500 | J43: 7000 | K43: 7500 | L43: 8000 | M43: 8500
A45: Book Basis of Assets | D45: =SUM(D53:D54) -> 2750 | E45: =SUM(E53:E54) -> 3150 | F45: =SUM(F53:F54) -> 3550 | G45: =SUM(G53:G54) -> 3950 | H45: =SUM(H53:H54) -> 4350 | I45: =SUM(I53:I54) -> 4750 | J45: =SUM(J53:J54) -> 5150 | K45: =SUM(K53:K54) -> 5550 | ... M45: =SUM(M53:M54) -> 6350
A46: Tax Basis of Assets | D46: 2650 | E46: 3000 | F46: 3400 | G46: 3800 | H46: 4250 | I46: 4600 | J46: 5000 | K46: 5300 | L46: 5700 | M46: 6000
A48: Book Gain (Loss) on Sale | D48: =D43-D45 -> 1250 | E48: =E43-E45 -> 1350 | F48: =F43-F45 -> 1450 | G48: =G43-G45 -> 1550 | H48: =H43-H45 -> 1650 | I48: =I43-I45 -> 1750 | J48: =J43-J45 -> 1850 | K48: =K43-K45 -> 1950 | ... M48: =M43-M45 -> 2150
A49: Tax Gain (Loss) on Sale | D49: =D43-D46 -> 1350 | E49: =E43-E46 -> 1500 | F49: =F43-F46 -> 1600 | G49: =G43-G46 -> 1700 | H49: =H43-H46 -> 1750 | I49: =I43-I46 -> 1900 | J49: =J43-J46 -> 2000 | K49: =K43-K46 -> 2200 | ... M49: =M43-M46 -> 2500
A52: Allocation to Balance Sheet:
A53: =Bal_Sheet!A23 -> PP&E: | D53: 1500 | E53: 1700 | F53: 1900 | G53: 2100 | H53: 2300 | I53: 2500 | J53: 2700 | K53: 2900 | L53: 3100 | M53: 3300
A54: =Bal_Sheet!A22 -> Other Long-Term Assets | D54: 1250 | E54: 1450 | F54: 1650 | G54: 1850 | H54: 2050 | I54: 2250 | J54: 2450 | K54: 2650 | L54: 2850 | M54: 3050

Sheet WACC
A2: Weighted Average Cost of Capital
A5: Risk Free Rate (Treasury Bill Rate) | E5: 0.05 | H5: WACC | L5: Manual
A6: Market Risk Premium | E6: 0.045 | H6: 0 = Manual 1 = Computed | L6: WACC
A7: Levered Beta | E7: 1.2 | H7: 1 | I7: =IF(H7=0,"Manual","Computed") -> Computed | L7: 0.085
A10: Estimated Cost of Debt | D10: Amount | E10: Int. Rate | F10: Wtd. Rate | H10: Computed WACC
A11: =Bal_Sheet!A46 -> Existing Debt | D11: =Bal_Sheet!E46 -> 65000 | E11: =assumed_debt_cou_rate -> 0.0425 | F11: =IF($D$20=0,0,E11*(D11/$D$20)) -> 0.0045973664 | J11: Proportion | K11: Rate | L11: Wtd. Cost
A12: =Bal_Sheet!A47 -> Bank Revolver | D12: =Bal_Sheet!E47 -> 200887.5 | E12: =bank_revolver_cou_rate -> 0.0475 | F12: =IF($D$20=0,0,E12*(D12/$D$20)) -> 0.015880104 | H12: Cost of Debt (Post-Tax) | J12: =IF($D$20+$D$25+$D$28=0,0,D20/($D$20+$D$25+$D$28)) -> 0.63694664 | K12: =F21 -> 0.03095613 | L12: =J12*K12 -> 0.019717403
A13: =Bal_Sheet!A48 -> Term Loan "A" | D13: =Bal_Sheet!E48 -> 80000 | E13: =termloanA_cou_rate -> 0.055 | F13: =IF($D$20=0,0,E13*(D13/$D$20)) -> 0.0073225021 | H13: Cost of Preferred Stock | J13: =IF($D$20+$D$25+$D$28=0,0,D25/($D$20+$D$25+$D$28)) -> 0.063600588 | K13: =E25 -> 0.07 | L13: =J13*K13 -> 0.0044520412
A14: =Bal_Sheet!A49 -> Term Loan "B" | D14: =Bal_Sheet!E49 -> 55000 | E14: =termloanB_cou_rate -> 0.0525 | F14: =IF($D$20=0,0,E14*(D14/$D$20)) -> 0.004805392 | H14: Cost of Equity | J14: =IF($D$20+$D$25+$D$28=0,0,D28/($D$20+$D$25+$D$28)) -> 0.29945277 | K14: =E28 -> 0.16026463 | L14: =J14*K14 -> 0.047991688
A15: =Bal_Sheet!A50 -> Senior Notes | D15: =Bal_Sheet!E50 -> 65000 | E15: =senior_notes_cou_rate -> 0.0425 | F15: =IF($D$20=0,0,E15*(D15/$D$20)) -> 0.0045973664
A16: =Bal_Sheet!A51 -> Subordinated Notes | D16: =Bal_Sheet!E51 -> 40000 | E16: =sub_notes_cou_rate -> 0.045 | F16: =IF($D$20=0,0,E16*(D16/$D$20)) -> 0.0029955691 | H16: WACC | L16: =SUM(L12:L14) -> 0.072161132
A17: =Bal_Sheet!A52 -> Mezzanine Debt | D17: =Bal_Sheet!E52 -> 70000 | E17: =mezzdebt_cou_rate -> 0.045 | F17: =IF($D$20=0,0,E17*(D17/$D$20)) -> 0.0052422458
A18: =Bal_Sheet!A53 -> Seller Notes | D18: =Bal_Sheet!E53 -> 25000 | E18: =seller_notes_cou_rate -> 0.0525 | F18: =IF($D$20=0,0,E18*(D18/$D$20)) -> 0.0021842691
A20: Total Debt | D20: =SUM(D11:D19) -> 600887.5 | F20: =SUM(F11:F19) -> 0.047624815
E21: Post-Tax | F21: =F20*(1-tax_rate) -> 0.03095613
A24: Estimated Cost of Preferred Stock
A25: =Bal_Sheet!A61 -> Preferred Stock | D25: =Bal_Sheet!E61 -> 60000 | E25: =pref_stock_div -> 0.07
A27: Estimated Cost of Equity (CAPM)
A28: Total Book Equity | D28: =Bal_Sheet!E62+Bal_Sheet!E63 -> 282500 | E28: =E5+E6*D54 -> 0.16026463
A32: Beta Calculation
A34: Levered Beta | D34: =E7 -> 1.2
A36: Pre-Acquisition:
A37: Debt | D37: =Bal_Sheet!C54 -> 250000
A38: Equity | D38: =Input!C8*no_shares_outs -> 600000
A39: Preferred Stock | D39: 0
A40: Debt/Equity Ratio | D40: =D37/D38 -> 0.41666667
A41: Preferred Stock/Equity Ratio | D41: =D39/D38 -> 0
A43: Post-Acquisition:
A44: =A37 -> Debt | D44: =Bal_Sheet!E54 -> 600887.5
A45: =A38 -> Equity | D45: =SUM(Bal_Sheet!E62:E63) -> 282500
A46: =A39 -> Preferred Stock | D46: =Bal_Sheet!E61 -> 60000
A47: =A40 -> Debt/Equity Ratio | D47: =D44/D45 -> 2.1270354
A48: =A41 -> Preferred Stock/Equity Ratio | D48: =D46/D45 -> 0.21238938
A50: =Input!L45 -> Tax Rate | D50: =tax_rate -> 0.35
A52: Unlevered Beta | D52: =D34/(1+(1-D50)*D40+D41) -> 0.9442623
A54: Relevered Beta | D54: =D52*(1+(1-D50)*D47+D48) -> 2.4503251

Sheet DCF_Analysis
B2: Discounted Cash Flow Analysis
B5: NPV of Free Cash Flow
B7: ="NPV of FCFF @ "&TEXT(B30,"0.00%") -> NPV of FCFF @ 6.00% | D7: =NPV(B30,Cash_Flow!$D$70:$M$70) -> 802189.02
B8: ="NPV of FCFF @ "&TEXT(B31,"0.00%") -> NPV of FCFF @ 7.00% | D8: =NPV(B31,Cash_Flow!$D$70:$M$70) -> 760040.43
B9: ="NPV of FCFF @ "&TEXT(B32,"0.00%") -> NPV of FCFF @ 8.00% | D9: =NPV(B32,Cash_Flow!$D$70:$M$70) -> 720896.15
B12: FV of Terminal Value (EBITDA) | H12: PV of Terminal Value (EBITDA)
J13: =C29 -> 4 | K13: =D29 -> 6 | L13: =E29 -> 8
B14: ="Terminal Value @ "&TEXT(C29,"0.0x") -> Terminal Value @ 4.0x | D14: =(Cash_Flow!$M$61+Cash_Flow!$M$62+Cash_Flow!$M$66)*C29 -> 2819044.5 | H14: ="Terminal Value @ "&TEXT(B30,"0.00%") -> Terminal Value @ 6.00% | J14: =$D$14/(1+B30)^Cash_Flow!$M$5 -> 1574139.7 | K14: =$D$15/(1+B30)^Cash_Flow!$M$5 -> 2361209.6 | L14: =$D$16/(1+B30)^Cash_Flow!$M$5 -> 3148279.4
B15: ="Terminal Value @ "&TEXT(D29,"0.0x") -> Terminal Value @ 6.0x | D15: =(Cash_Flow!$M$61+Cash_Flow!$M$62+Cash_Flow!$M$66)*D29 -> 4228566.7 | H15: ="Terminal Value @ "&TEXT(B31,"0.00%") -> Terminal Value @ 7.00% | J15: =$D$14/(1+B31)^Cash_Flow!$M$5 -> 1433059.3 | K15: =$D$15/(1+B31)^Cash_Flow!$M$5 -> 2149588.9 | L15: =$D$16/(1+B31)^Cash_Flow!$M$5 -> 2866118.5
B16: ="Terminal Value @ "&TEXT(E29,"0.0x") -> Terminal Value @ 8.0x | D16: =(Cash_Flow!$M$61+Cash_Flow!$M$62+Cash_Flow!$M$66)*E29 -> 5638089 | H16: ="Terminal Value @ "&TEXT(B32,"0.00%") -> Terminal Value @ 8.00% | J16: =$D$14/(1+B32)^Cash_Flow!$M$5 -> 1305763.1 | K16: =$D$15/(1+B32)^Cash_Flow!$M$5 -> 1958644.6 | L16: =$D$16/(1+B32)^Cash_Flow!$M$5 -> 2611526.1
B19: FV of Terminal Value (Perpetuity) | H19: PV of Terminal Value (Perpetuity)
D20: =H29 -> 0.025 | E20: =I29 -> 0.03 | F20: =J29 -> 0.035 | J20: =H29 -> 0.025 | K20: =I29 -> 0.03 | L20: =J29 -> 0.035
B21: ="Terminal Value @ "&TEXT(G30,"0.00%") -> Terminal Value @ 6.00% | D21: =(Cash_Flow!$M$70*(1+D$20))/($G30-D$20) -> 3291577.5 | E21: =(Cash_Flow!$M$70*(1+E$20))/($G30-E$20) -> 3858906.3 | F21: =(Cash_Flow!$M$70*(1+F$20))/($G30-F$20) -> 4653166.6 | H21: ="Terminal Value @ "&TEXT(G30,"0.00%") -> Terminal Value @ 6.00% | J21: =D21/(1+$G30)^Cash_Flow!$M$5 -> 1837999.7 | K21: =E21/(1+$G30)^Cash_Flow!$M$5 -> 2154793.1 | L21: =F21/(1+$G30)^Cash_Flow!$M$5 -> 2598303.9
B22: ="Terminal Value @ "&TEXT(G31,"0.00%") -> Terminal Value @ 7.00% | D22: =(Cash_Flow!$M$70*(1+D$20))/($G31-D$20) -> 2560115.8 | E22: =(Cash_Flow!$M$70*(1+E$20))/($G31-E$20) -> 2894179.7 | F22: =(Cash_Flow!$M$70*(1+F$20))/($G31-F$20) -> 3323690.4 | H22: ="Terminal Value @ "&TEXT(G31,"0.00%") -> Terminal Value @ 7.00% | J22: =D22/(1+$G31)^Cash_Flow!$M$5 -> 1301433.1 | K22: =E22/(1+$G31)^Cash_Flow!$M$5 -> 1471254.2 | L22: =F22/(1+$G31)^Cash_Flow!$M$5 -> 1689595.7
B23: ="Terminal Value @ "&TEXT(G32,"0.00%") -> Terminal Value @ 8.00% | D23: =(Cash_Flow!$M$70*(1+D$20))/($G32-D$20) -> 2094640.2 | E23: =(Cash_Flow!$M$70*(1+E$20))/($G32-E$20) -> 2315343.8 | F23: =(Cash_Flow!$M$70*(1+F$20))/($G32-F$20) -> 2585092.6 | H23: ="Terminal Value @ "&TEXT(G32,"0.00%") -> Terminal Value @ 8.00% | J23: =D23/(1+$G32)^Cash_Flow!$M$5 -> 970223.71 | K23: =E23/(1+$G32)^Cash_Flow!$M$5 -> 1072452.2 | L23: =F23/(1+$G32)^Cash_Flow!$M$5 -> 1197398
B27: Total Enterprise Value | L27: Percentage Split of DCF Analysis
C28: EBITDA Multiple Method | H28: Perpetuity Growth Method
C29: =D29-ebitda_multiple_range -> 4 | D29: =ebitda_multiple -> 6 | E29: =D29+ebitda_multiple_range -> 8 | H29: =I29-perpetuity_growth_range -> 0.025 | I29: =perpetuity_growth_rate -> 0.03 | J29: =I29+perpetuity_growth_range -> 0.035 | N29: =C28 -> EBITDA Multiple Method
B30: =B31-discount_rate_range -> 0.06 | C30: =$D7+J14 -> 2376328.7 | D30: =$D7+K14 -> 3163398.6 | E30: =$D7+L14 -> 3950468.5 | G30: =G31-discount_rate_range -> 0.06 | H30: =$D7+J21 -> 2640188.7 | I30: =$D7+K21 -> 2956982.1 | J30: =$D7+L21 -> 3400493 | L30: Cash Flow % of TEV: | N30: =C29 -> 4 | O30: =D29 -> 6 | P30: =E29 -> 8
B31: =WACC -> 0.07 | C31: =$D8+J15 -> 2193099.7 | D31: =$D8+K15 -> 2909629.3 | E31: =$D8+L15 -> 3626159 | G31: =B31 -> 0.07 | H31: =$D8+J22 -> 2061473.5 | I31: =$D8+K22 -> 2231294.6 | J31: =$D8+L22 -> 2449636.1 | L31: ="@ "&TEXT(B30,"0.00%") -> @ 6.00% | N31: =$D7/C30 -> 0.33757493 | O31: =$D7/D30 -> 0.25358455 | P31: =$D7/E30 -> 0.20306174
B32: =B31+discount_rate_range -> 0.08 | C32: =$D9+J16 -> 2026659.2 | D32: =$D9+K16 -> 2679540.7 | E32: =$D9+L16 -> 3332422.3 | G32: =G31+discount_rate_range -> 0.08 | H32: =$D9+J23 -> 1691119.9 | I32: =$D9+K23 -> 1793348.3 | J32: =$D9+L23 -> 1918294.2 | L32: ="@ "&TEXT(B31,"0.00%") -> @ 7.00% | N32: =$D8/C31 -> 0.34655991 | O32: =$D8/D31 -> 0.26121555 | P32: =$D8/E31 -> 0.20959931
L33: ="@ "&TEXT(B32,"0.00%") -> @ 8.00% | N33: =$D9/C32 -> 0.35570665 | O33: =$D9/D32 -> 0.26903721 | P33: =$D9/E32 -> 0.21632797
L34: Terminal Value % of TEV:
B35: Total Equity Value | L35: ="@ "&TEXT(B30,"0.00%") -> @ 6.00% | N35: =J14/C30 -> 0.66242507 | O35: =K14/D30 -> 0.74641545 | P35: =L14/E30 -> 0.79693826
C36: EBITDA Multiple Method | H36: Perpetuity Growth Method | L36: ="@ "&TEXT(B31,"0.00%") -> @ 7.00% | N36: =J15/C31 -> 0.65344009 | O36: =K15/D31 -> 0.73878445 | P36: =L15/E31 -> 0.79040069
C37: =D37-ebitda_multiple_range -> 4 | D37: =D29 -> 6 | E37: =D37+ebitda_multiple_range -> 8 | H37: =I37-perpetuity_growth_range -> 0.025 | I37: =I29 -> 0.03 | J37: =I37+perpetuity_growth_range -> 0.035 | L37: ="@ "&TEXT(B32,"0.00%") -> @ 8.00% | N37: =J16/C32 -> 0.64429335 | O37: =K16/D32 -> 0.73096279 | P37: =L16/E32 -> 0.78367203
B38: =B39-discount_rate_range -> 0.06 | C38: =C30-Input!$N$56 -> 1792941.2 | D38: =D30-Input!$N$56 -> 2580011.1 | E38: =E30-Input!$N$56 -> 3367081 | G38: =G39-discount_rate_range -> 0.06 | H38: =H30-Input!$N$56 -> 2056801.2 | I38: =I30-Input!$N$56 -> 2373594.6 | J38: =J30-Input!$N$56 -> 2817105.5
B39: =B31 -> 0.07 | C39: =C31-Input!$N$56 -> 1609712.2 | D39: =D31-Input!$N$56 -> 2326241.8 | E39: =E31-Input!$N$56 -> 3042771.5 | G39: =B31 -> 0.07 | H39: =H31-Input!$N$56 -> 1478086 | I39: =I31-Input!$N$56 -> 1647907.1 | J39: =J31-Input!$N$56 -> 1866248.6 | N39: =H28 -> Perpetuity Growth Method
B40: =B39+discount_rate_range -> 0.08 | C40: =C32-Input!$N$56 -> 1443271.7 | D40: =D32-Input!$N$56 -> 2096153.2 | E40: =E32-Input!$N$56 -> 2749034.8 | G40: =G39+discount_rate_range -> 0.08 | H40: =H32-Input!$N$56 -> 1107732.4 | I40: =I32-Input!$N$56 -> 1209960.8 | J40: =J32-Input!$N$56 -> 1334906.7 | L40: Cash Flow % of TEV: | N40: =H29 -> 0.025 | O40: =I29 -> 0.03 | P40: =J29 -> 0.035
L41: ="@ "&TEXT(B30,"0.00%") -> @ 6.00% | N41: =$D7/H30 -> 0.30383776 | O41: =$D7/I30 -> 0.27128639 | P41: =$D7/J30 -> 0.23590374
L42: ="@ "&TEXT(B31,"0.00%") -> @ 7.00% | N42: =$D8/H31 -> 0.36868795 | O42: =$D8/I31 -> 0.34062755 | P42: =$D8/J31 -> 0.31026667
B43: Total Equity Value Per Share | L43: ="@ "&TEXT(B32,"0.00%") -> @ 8.00% | N43: =$D9/H32 -> 0.4262833 | O43: =$D9/I32 -> 0.40198334 | P43: =$D9/J32 -> 0.37580062
C44: EBITDA Multiple Method | H44: Perpetuity Growth Method | L44: Terminal Value % of TEV:
C45: =D45-ebitda_multiple_range -> 4 | D45: =D29 -> 6 | E45: =D45+ebitda_multiple_range -> 8 | H45: =I45-perpetuity_growth_range -> 0.025 | I45: =I29 -> 0.03 | J45: =I45+perpetuity_growth_range -> 0.035 | L45: ="@ "&TEXT(B30,"0.00%") -> @ 6.00% | N45: =J21/H30 -> 0.69616224 | O45: =K21/I30 -> 0.72871361 | P45: =L21/J30 -> 0.76409626
B46: =B47-discount_rate_range -> 0.06 | C46: =IF(no_shares_outs=0,0,C38/no_shares_outs) -> 17.929412 | D46: =IF(no_shares_outs=0,0,D38/no_shares_outs) -> 25.800111 | E46: =IF(no_shares_outs=0,0,E38/no_shares_outs) -> 33.67081 | G46: =G47-discount_rate_range -> 0.06 | H46: =IF(no_shares_outs=0,0,H38/no_shares_outs) -> 20.568012 | I46: =IF(no_shares_outs=0,0,I38/no_shares_outs) -> 23.735946 | J46: =IF(no_shares_outs=0,0,J38/no_shares_outs) -> 28.171055 | L46: ="@ "&TEXT(B31,"0.00%") -> @ 7.00% | N46: =J22/H31 -> 0.63131205 | O46: =K22/I31 -> 0.65937245 | P46: =L22/J31 -> 0.68973333
B47: =B31 -> 0.07 | C47: =IF(no_shares_outs=0,0,C39/no_shares_outs) -> 16.097122 | D47: =IF(no_shares_outs=0,0,D39/no_shares_outs) -> 23.262418 | E47: =IF(no_shares_outs=0,0,E39/no_shares_outs) -> 30.427715 | G47: =B31 -> 0.07 | H47: =IF(no_shares_outs=0,0,H39/no_shares_outs) -> 14.78086 | I47: =IF(no_shares_outs=0,0,I39/no_shares_outs) -> 16.479071 | J47: =IF(no_shares_outs=0,0,J39/no_shares_outs) -> 18.662486 | L47: ="@ "&TEXT(B32,"0.00%") -> @ 8.00% | N47: =J23/H32 -> 0.5737167 | O47: =K23/I32 -> 0.59801666 | P47: =L23/J32 -> 0.62419938
B48: =B47+discount_rate_range -> 0.08 | C48: =IF(no_shares_outs=0,0,C40/no_shares_outs) -> 14.432717 | D48: =IF(no_shares_outs=0,0,D40/no_shares_outs) -> 20.961532 | E48: =IF(no_shares_outs=0,0,E40/no_shares_outs) -> 27.490348 | G48: =G47+discount_rate_range -> 0.08 | H48: =IF(no_shares_outs=0,0,H40/no_shares_outs) -> 11.077324 | I48: =IF(no_shares_outs=0,0,I40/no_shares_outs) -> 12.099608 | J48: =IF(no_shares_outs=0,0,J40/no_shares_outs) -> 13.349067

Sheet IRR_Returns
A2: IRR / Returns Calculation
A4: Exit Year | B4: 2018 | C4: =IF(exit_year>0,HLOOKUP(exit_year,Inc_St!D4:M5,2,FALSE()),0) -> 9
A6: Equity Allocation on Exit | C6: Investment | D6: Undiluted | E6: % Allocation | F6: Diluted | G6: Allocation | I6: Allocation of Exit Proceeds
A8: =Input!A37 -> Common - Sponsor Equity | C8: =Input!C37 -> 220000 | D8: =C8/SUM($C$8:$C$10) -> 0.77192982 | E8: 0 | F8: =D8*(1-$E$16) -> 0.63298246 | G8: =F8*$L$16 -> 2565228.2 | I8: EBITDA Multiple (Exit Year) | L8: =ebitda_multiple -> 6
A9: =Input!A38 -> Management Equity | C9: =Input!C38 -> 40000 | D9: =C9/SUM($C$8:$C$10) -> 0.14035088 | E9: 0 | F9: =D9*(1-$E$16) -> 0.11508772 | G9: =F9*$L$16 -> 466405.13 | I9: EBITDA (Exit Year) | L9: =IF($C$4>0,OFFSET(Inc_St!C18,0,$C$4,1,1),0) -> 645545.45
A10: =Input!A39 -> New Equity | C10: =Input!C39 -> 25000 | D10: =C10/SUM($C$8:$C$10) -> 0.087719298 | E10: 0.02 | F10: =D10*(1-$E$16)+E10 -> 0.091929825 | G10: =F10*$L$16 -> 372555.32 | I10: Exit Year Enterprise Value | L10: =L8*L9 -> 3873272.7
A11: =Input!A31 -> Subordinated Notes | C11: =Input!C31 -> 40000 | D11: N/A | E11: 0.03 | F11: =E11 -> 0.03 | G11: =F11*$L$16 -> 121578.17
A12: =Input!A32 -> Mezzanine Debt | C12: =Input!C32 -> 70000 | D12: N/A | E12: 0.05 | F12: =E12 -> 0.05 | G12: =F12*$L$16 -> 202630.28 | I12: Less: Debt | L12: =IF($C$4>0,OFFSET(Bal_Sheet!$E54,0,$C$4,1,1),0) -> 0
A13: =Input!A35 -> Preferred Stock | C13: =Input!C35 -> 60000 | D13: N/A | E13: 0.04 | F13: =E13 -> 0.04 | G13: =F13*$L$16 -> 162104.22 | I13: Less: Preferred Stock | L13: =IF($C$4>0,OFFSET(Bal_Sheet!$E61,0,$C$4,1,1),0) -> 84153.104
A14: Management Performance Equity | C14: N/A | D14: N/A | E14: 0.04 | F14: =E14 -> 0.04 | G14: =F14*$L$16 -> 162104.22 | I14: Add: Excess Cash | L14: =IF($C$4>0,OFFSET(Bal_Sheet!$E10,0,$C$4,1,1),0) -> 263486
A16: Total | C16: =SUM(C8:C15) -> 455000 | D16: =SUM(D8:D15) -> 1 | E16: =SUM(E8:E15) -> 0.18 | F16: =SUM(F8:F15) -> 1 | G16: =SUM(G8:G15) -> 4052605.6 | I16: Equity Value - Allocable Proceeds | L16: =SUM(L10,-L12,-L13,L14) -> 4052605.6
A21: Cash Flows & IRR | C21: Post-Acq | D21: =year1 -> 2010 | E21: =D21+1 -> 2011 | F21: =E21+1 -> 2012 | G21: =F21+1 -> 2013 | H21: =G21+1 -> 2014 | I21: =H21+1 -> 2015 | J21: =I21+1 -> 2016 | K21: =J21+1 -> 2017 | L21: =K21+1 -> 2018 | M21: =L21+1 -> 2019
C22: =D22-1 -> 0 | D22: 1 | E22: =D22+1 -> 2 | F22: =E22+1 -> 3 | G22: =F22+1 -> 4 | H22: =G22+1 -> 5 | I22: =H22+1 -> 6 | J22: =I22+1 -> 7 | K22: =J22+1 -> 8 | L22: =K22+1 -> 9 | M22: =L22+1 -> 10
A24: =A11 -> Subordinated Notes
A25: Initial Investment | C25: =-Bal_Sheet!E51 -> -40000
A26: Cash Interest | D26: =IF($C$4>=D$22,Inc_St!D$30-Cash_Flow!D$15,0) -> 0 | E26: =IF($C$4>=E$22,Inc_St!E$30-Cash_Flow!E$15,0) -> 0 | F26: =IF($C$4>=F$22,Inc_St!F$30-Cash_Flow!F$15,0) -> 0 | G26: =IF($C$4>=G$22,Inc_St!G$30-Cash_Flow!G$15,0) -> 0 | H26: =IF($C$4>=H$22,Inc_St!H$30-Cash_Flow!H$15,0) -> 0 | I26: =IF($C$4>=I$22,Inc_St!I$30-Cash_Flow!I$15,0) -> 96.594007 | J26: =IF($C$4>=J$22,Inc_St!J$30-Cash_Flow!J$15,0) -> 0 | K26: =IF($C$4>=K$22,Inc_St!K$30-Cash_Flow!K$15,0) -> 0 | ... M26: =IF($C$4>=M$22,Inc_St!M$30-Cash_Flow!M$15,0) -> 0
A27: Repayment | D27: =IF($C$4>=D$22,SUM(Cash_Flow!D$89,Cash_Flow!D$104),0) -> 0 | E27: =IF($C$4>=E$22,SUM(Cash_Flow!E$89,Cash_Flow!E$104),0) -> 0 | F27: =IF($C$4>=F$22,SUM(Cash_Flow!F$89,Cash_Flow!F$104),0) -> 0 | G27: =IF($C$4>=G$22,SUM(Cash_Flow!G$89,Cash_Flow!G$104),0) -> 0 | H27: =IF($C$4>=H$22,SUM(Cash_Flow!H$89,Cash_Flow!H$104),0) -> 47700.744 | I27: =IF($C$4>=I$22,SUM(Cash_Flow!I$89,Cash_Flow!I$104),0) -> 2146.5335 | J27: =IF($C$4>=J$22,SUM(Cash_Flow!J$89,Cash_Flow!J$104),0) -> 0 | K27: =IF($C$4>=K$22,SUM(Cash_Flow!K$89,Cash_Flow!K$104),0) -> 0 | ... M27: =IF($C$4>=M$22,SUM(Cash_Flow!M$89,Cash_Flow!M$104),0) -> 0
A28: Principal | D28: =IF($C$4=D$22,Bal_Sheet!F$51,0) -> 0 | E28: =IF($C$4=E$22,Bal_Sheet!G$51,0) -> 0 | F28: =IF($C$4=F$22,Bal_Sheet!H$51,0) -> 0 | G28: =IF($C$4=G$22,Bal_Sheet!I$51,0) -> 0 | H28: =IF($C$4=H$22,Bal_Sheet!J$51,0) -> 0 | I28: =IF($C$4=I$22,Bal_Sheet!K$51,0) -> 0 | J28: =IF($C$4=J$22,Bal_Sheet!L$51,0) -> 0 | K28: =IF($C$4=K$22,Bal_Sheet!M$51,0) -> 0 | ... M28: =IF($C$4=M$22,Bal_Sheet!O$51,0) -> 0
A29: Participation on Exit | D29: =IF($C$4=D$22,$G$11,0) -> 0 | E29: =IF($C$4=E$22,$G$11,0) -> 0 | F29: =IF($C$4=F$22,$G$11,0) -> 0 | G29: =IF($C$4=G$22,$G$11,0) -> 0 | H29: =IF($C$4=H$22,$G$11,0) -> 0 | I29: =IF($C$4=I$22,$G$11,0) -> 0 | J29: =IF($C$4=J$22,$G$11,0) -> 0 | K29: =IF($C$4=K$22,$G$11,0) -> 0 | ... M29: =IF($C$4=M$22,$G$11,0) -> 0
A30: IRR | B30: =IF($C$4>0,IRR($C30:$M30,),0) -> 0.21407384 | C30: =C25 -> -40000 | D30: =SUM(D26:D29) -> 0 | E30: =SUM(E26:E29) -> 0 | F30: =SUM(F26:F29) -> 0 | G30: =SUM(G26:G29) -> 0 | H30: =SUM(H26:H29) -> 47700.744 | I30: =SUM(I26:I29) -> 2243.1275 | J30: =SUM(J26:J29) -> 0 | K30: =SUM(K26:K29) -> 0 | ... M30: =SUM(M26:M29) -> 0
A33: =A12 -> Mezzanine Debt
A34: Initial Investment | C34: =-Bal_Sheet!E52 -> -70000
A35: Cash Interest | D35: =IF($C$4>=D$22,Inc_St!D$31-Cash_Flow!D$16,0) -> 0 | E35: =IF($C$4>=E$22,Inc_St!E$31-Cash_Flow!E$16,0) -> 0 | F35: =IF($C$4>=F$22,Inc_St!F$31-Cash_Flow!F$16,0) -> 0 | G35: =IF($C$4>=G$22,Inc_St!G$31-Cash_Flow!G$16,0) -> 0 | H35: =IF($C$4>=H$22,Inc_St!H$31-Cash_Flow!H$16,0) -> 0 | I35: =IF($C$4>=I$22,Inc_St!I$31-Cash_Flow!I$16,0) -> 1640.4239 | J35: =IF($C$4>=J$22,Inc_St!J$31-Cash_Flow!J$16,0) -> 0 | K35: =IF($C$4>=K$22,Inc_St!K$31-Cash_Flow!K$16,0) -> 0 | ... M35: =IF($C$4>=M$22,Inc_St!M$31-Cash_Flow!M$16,0) -> 0
A36: Repayment | D36: =IF($C$4>=D$22,SUM(Cash_Flow!D$90,Cash_Flow!D$105),0) -> 0 | E36: =IF($C$4>=E$22,SUM(Cash_Flow!E$90,Cash_Flow!E$105),0) -> 0 | F36: =IF($C$4>=F$22,SUM(Cash_Flow!F$90,Cash_Flow!F$105),0) -> 0 | G36: =IF($C$4>=G$22,SUM(Cash_Flow!G$90,Cash_Flow!G$105),0) -> 0 | H36: =IF($C$4>=H$22,SUM(Cash_Flow!H$90,Cash_Flow!H$105),0) -> 50778.871 | I36: =IF($C$4>=I$22,SUM(Cash_Flow!I$90,Cash_Flow!I$105),0) -> 36453.864 | J36: =IF($C$4>=J$22,SUM(Cash_Flow!J$90,Cash_Flow!J$105),0) -> 0 | K36: =IF($C$4>=K$22,SUM(Cash_Flow!K$90,Cash_Flow!K$105),0) -> 0 | ... M36: =IF($C$4>=M$22,SUM(Cash_Flow!M$90,Cash_Flow!M$105),0) -> 0
A37: Principal | D37: =IF($C$4=D$22,Bal_Sheet!F$52,0) -> 0 | E37: =IF($C$4=E$22,Bal_Sheet!G$52,0) -> 0 | F37: =IF($C$4=F$22,Bal_Sheet!H$52,0) -> 0 | G37: =IF($C$4=G$22,Bal_Sheet!I$52,0) -> 0 | H37: =IF($C$4=H$22,Bal_Sheet!J$52,0) -> 0 | I37: =IF($C$4=I$22,Bal_Sheet!K$52,0) -> 0 | J37: =IF($C$4=J$22,Bal_Sheet!L$52,0) -> 0 | K37: =IF($C$4=K$22,Bal_Sheet!M$52,0) -> 0 | ... M37: =IF($C$4=M$22,Bal_Sheet!O$52,0) -> 0
A38: Participation on Exit | D38: =IF($C$4=D$22,$G$12,0) -> 0 | E38: =IF($C$4=E$22,$G$12,0) -> 0 | F38: =IF($C$4=F$22,$G$12,0) -> 0 | G38: =IF($C$4=G$22,$G$12,0) -> 0 | H38: =IF($C$4=H$22,$G$12,0) -> 0 | I38: =IF($C$4=I$22,$G$12,0) -> 0 | J38: =IF($C$4=J$22,$G$12,0) -> 0 | K38: =IF($C$4=K$22,$G$12,0) -> 0 | ... M38: =IF($C$4=M$22,$G$12,0) -> 0
A39: IRR | B39: =IF($C$4>0,IRR($C39:$M39,),0) -> 0.20560734 | C39: =C34 -> -70000 | D39: =SUM(D35:D38) -> 0 | E39: =SUM(E35:E38) -> 0 | F39: =SUM(F35:F38) -> 0 | G39: =SUM(G35:G38) -> 0 | H39: =SUM(H35:H38) -> 50778.871 | I39: =SUM(I35:I38) -> 38094.288 | J39: =SUM(J35:J38) -> 0 | K39: =SUM(K35:K38) -> 0 | ... M39: =SUM(M35:M38) -> 0
A42: =A13 -> Preferred Stock
A43: Initial Investment | C43: =-Bal_Sheet!E61 -> -60000
A44: Cash Dividend | D44: =IF($C$4>=D$22,Inc_St!D$46-Cash_Flow!D$18,0) -> 0 | E44: =IF($C$4>=E$22,Inc_St!E$46-Cash_Flow!E$18,0) -> 0 | F44: =IF($C$4>=F$22,Inc_St!F$46-Cash_Flow!F$18,0) -> 0 | G44: =IF($C$4>=G$22,Inc_St!G$46-Cash_Flow!G$18,0) -> 0 | H44: =IF($C$4>=H$22,Inc_St!H$46-Cash_Flow!H$18,0) -> 0 | I44: =IF($C$4>=I$22,Inc_St!I$46-Cash_Flow!I$18,0) -> 5890.7173 | J44: =IF($C$4>=J$22,Inc_St!J$46-Cash_Flow!J$18,0) -> 5890.7173 | K44: =IF($C$4>=K$22,Inc_St!K$46-Cash_Flow!K$18,0) -> 5890.7173 | ... M44: =IF($C$4>=M$22,Inc_St!M$46-Cash_Flow!M$18,0) -> 0
A45: Repayment | D45: =IF($C$4>=D$22,Cash_Flow!D$92,0) -> 0 | E45: =IF($C$4>=E$22,Cash_Flow!E$92,0) -> 0 | F45: =IF($C$4>=F$22,Cash_Flow!F$92,0) -> 0 | G45: =IF($C$4>=G$22,Cash_Flow!G$92,0) -> 0 | H45: =IF($C$4>=H$22,Cash_Flow!H$92,0) -> 0 | I45: =IF($C$4>=I$22,Cash_Flow!I$92,0) -> 0 | J45: =IF($C$4>=J$22,Cash_Flow!J$92,0) -> 0 | K45: =IF($C$4>=K$22,Cash_Flow!K$92,0) -> 0 | ... M45: =IF($C$4>=M$22,Cash_Flow!M$92,0) -> 0
A46: Principal | D46: =IF($C$4=D$22,Bal_Sheet!F$61,0) -> 0 | E46: =IF($C$4=E$22,Bal_Sheet!G$61,0) -> 0 | F46: =IF($C$4=F$22,Bal_Sheet!H$61,0) -> 0 | G46: =IF($C$4=G$22,Bal_Sheet!I$61,0) -> 0 | H46: =IF($C$4=H$22,Bal_Sheet!J$61,0) -> 0 | I46: =IF($C$4=I$22,Bal_Sheet!K$61,0) -> 0 | J46: =IF($C$4=J$22,Bal_Sheet!L$61,0) -> 0 | K46: =IF($C$4=K$22,Bal_Sheet!M$61,0) -> 0 | ... M46: =IF($C$4=M$22,Bal_Sheet!O$61,0) -> 0
A47: Participation on Exit | D47: =IF($C$4=D$22,$G$13,0) -> 0 | E47: =IF($C$4=E$22,$G$13,0) -> 0 | F47: =IF($C$4=F$22,$G$13,0) -> 0 | G47: =IF($C$4=G$22,$G$13,0) -> 0 | H47: =IF($C$4=H$22,$G$13,0) -> 0 | I47: =IF($C$4=I$22,$G$13,0) -> 0 | J47: =IF($C$4=J$22,$G$13,0) -> 0 | K47: =IF($C$4=K$22,$G$13,0) -> 0 | ... M47: =IF($C$4=M$22,$G$13,0) -> 0
A48: IRR | B48: =IF($C$4>0,IRR($C48:$M48,),0) -> 0.18536585 | C48: =C43 -> -60000 | D48: =SUM(D44:D47) -> 0 | E48: =SUM(E44:E47) -> 0 | F48: =SUM(F44:F47) -> 0 | G48: =SUM(G44:G47) -> 0 | H48: =SUM(H44:H47) -> 0 | I48: =SUM(I44:I47) -> 5890.7173 | J48: =SUM(J44:J47) -> 5890.7173 | K48: =SUM(K44:K47) -> 5890.7173 | ... M48: =SUM(M44:M47) -> 0
A51: =A8 -> Common - Sponsor Equity
A52: Initial Investment | C52: =-Input!C37 -> -220000
A53: Cash Dividend | D53: =IF($C$4>=D$22,Inc_St!D$47*$D$8,0) -> 1929.8246 | E53: =IF($C$4>=E$22,Inc_St!E$47*$D$8,0) -> 2084.2105 | F53: =IF($C$4>=F$22,Inc_St!F$47*$D$8,0) -> 2200 | G53: =IF($C$4>=G$22,Inc_St!G$47*$D$8,0) -> 2392.9825 | H53: =IF($C$4>=H$22,Inc_St!H$47*$D$8,0) -> 2663.1579 | I53: =IF($C$4>=I$22,Inc_St!I$47*$D$8,0) -> 2701.7544 | J53: =IF($C$4>=J$22,Inc_St!J$47*$D$8,0) -> 2856.1404 | K53: =IF($C$4>=K$22,Inc_St!K$47*$D$8,0) -> 3087.7193 | ... M53: =IF($C$4>=M$22,Inc_St!M$47*$D$8,0) -> 0
A54: Participation on Exit | D54: =IF($C$4=D$22,$G$8,0) -> 0 | E54: =IF($C$4=E$22,$G$8,0) -> 0 | F54: =IF($C$4=F$22,$G$8,0) -> 0 | G54: =IF($C$4=G$22,$G$8,0) -> 0 | H54: =IF($C$4=H$22,$G$8,0) -> 0 | I54: =IF($C$4=I$22,$G$8,0) -> 0 | J54: =IF($C$4=J$22,$G$8,0) -> 0 | K54: =IF($C$4=K$22,$G$8,0) -> 0 | ... M54: =IF($C$4=M$22,$G$8,0) -> 0
A55: IRR | B55: =IF($C$4>0,IRR($C55:$M55,),0) -> 0.31824371 | C55: =C52 -> -220000 | D55: =SUM(D53:D54) -> 1929.8246 | E55: =SUM(E53:E54) -> 2084.2105 | F55: =SUM(F53:F54) -> 2200 | G55: =SUM(G53:G54) -> 2392.9825 | H55: =SUM(H53:H54) -> 2663.1579 | I55: =SUM(I53:I54) -> 2701.7544 | J55: =SUM(J53:J54) -> 2856.1404 | K55: =SUM(K53:K54) -> 3087.7193 | ... M55: =SUM(M53:M54) -> 0
A58: =A9 -> Management Equity
A59: Initial Investment | C59: =-Input!C38 -> -40000
A60: Cash Dividend | D60: =IF($C$4>=D$22,Inc_St!D$47*$D$9,0) -> 350.87719 | E60: =IF($C$4>=E$22,Inc_St!E$47*$D$9,0) -> 378.94737 | F60: =IF($C$4>=F$22,Inc_St!F$47*$D$9,0) -> 400 | G60: =IF($C$4>=G$22,Inc_St!G$47*$D$9,0) -> 435.08772 | H60: =IF($C$4>=H$22,Inc_St!H$47*$D$9,0) -> 484.21053 | I60: =IF($C$4>=I$22,Inc_St!I$47*$D$9,0) -> 491.22807 | J60: =IF($C$4>=J$22,Inc_St!J$47*$D$9,0) -> 519.29825 | K60: =IF($C$4>=K$22,Inc_St!K$47*$D$9,0) -> 561.40351 | ... M60: =IF($C$4>=M$22,Inc_St!M$47*$D$9,0) -> 0
A61: Participation on Exit | D61: =IF($C$4=D$22,SUM($G$9,$G$14),0) -> 0 | E61: =IF($C$4=E$22,SUM($G$9,$G$14),0) -> 0 | F61: =IF($C$4=F$22,SUM($G$9,$G$14),0) -> 0 | G61: =IF($C$4=G$22,SUM($G$9,$G$14),0) -> 0 | H61: =IF($C$4=H$22,SUM($G$9,$G$14),0) -> 0 | I61: =IF($C$4=I$22,SUM($G$9,$G$14),0) -> 0 | J61: =IF($C$4=J$22,SUM($G$9,$G$14),0) -> 0 | K61: =IF($C$4=K$22,SUM($G$9,$G$14),0) -> 0 | ... M61: =IF($C$4=M$22,SUM($G$9,$G$14),0) -> 0
A62: IRR | B62: =IF($C$4>0,IRR($C62:$M62,),0) -> 0.36214839 | C62: =C59 -> -40000 | D62: =SUM(D60:D61) -> 350.87719 | E62: =SUM(E60:E61) -> 378.94737 | F62: =SUM(F60:F61) -> 400 | G62: =SUM(G60:G61) -> 435.08772 | H62: =SUM(H60:H61) -> 484.21053 | I62: =SUM(I60:I61) -> 491.22807 | J62: =SUM(J60:J61) -> 519.29825 | K62: =SUM(K60:K61) -> 561.40351 | ... M62: =SUM(M60:M61) -> 0
A65: =A10 -> New Equity
A66: Initial Investment | C66: =-Input!C39 -> -25000
A67: Cash Dividend | D67: =IF($C$4>=D$22,Inc_St!D$47*$D$10,0) -> 219.29825 | E67: =IF($C$4>=E$22,Inc_St!E$47*$D$10,0) -> 236.84211 | F67: =IF($C$4>=F$22,Inc_St!F$47*$D$10,0) -> 250 | G67: =IF($C$4>=G$22,Inc_St!G$47*$D$10,0) -> 271.92982 | H67: =IF($C$4>=H$22,Inc_St!H$47*$D$10,0) -> 302.63158 | I67: =IF($C$4>=I$22,Inc_St!I$47*$D$10,0) -> 307.01754 | J67: =IF($C$4>=J$22,Inc_St!J$47*$D$10,0) -> 324.5614 | K67: =IF($C$4>=K$22,Inc_St!K$47*$D$10,0) -> 350.87719 | ... M67: =IF($C$4>=M$22,Inc_St!M$47*$D$10,0) -> 0
A68: Participation on Exit | D68: =IF($C$4=D$22,$G$10,0) -> 0 | E68: =IF($C$4=E$22,$G$10,0) -> 0 | F68: =IF($C$4=F$22,$G$10,0) -> 0 | G68: =IF($C$4=G$22,$G$10,0) -> 0 | H68: =IF($C$4=H$22,$G$10,0) -> 0 | I68: =IF($C$4=I$22,$G$10,0) -> 0 | J68: =IF($C$4=J$22,$G$10,0) -> 0 | K68: =IF($C$4=K$22,$G$10,0) -> 0 | ... M68: =IF($C$4=M$22,$G$10,0) -> 0
A69: IRR | B69: =IF($C$4>0,IRR($C69:$M69,),0) -> 0.35424162 | C69: =C66 -> -25000 | D69: =SUM(D67:D68) -> 219.29825 | E69: =SUM(E67:E68) -> 236.84211 | F69: =SUM(F67:F68) -> 250 | G69: =SUM(G67:G68) -> 271.92982 | H69: =SUM(H67:H68) -> 302.63158 | I69: =SUM(I67:I68) -> 307.01754 | J69: =SUM(J67:J68) -> 324.5614 | K69: =SUM(K67:K68) -> 350.87719 | ... M69: =SUM(M67:M68) -> 0

Sheet Ratios
A2: Ratio Analysis
A4: Year | D4: =year1 -> 2010 | E4: =D4+1 -> 2011 | F4: =E4+1 -> 2012 | G4: =F4+1 -> 2013 | H4: =G4+1 -> 2014 | I4: =H4+1 -> 2015 | J4: =I4+1 -> 2016 | K4: =J4+1 -> 2017 | L4: =K4+1 -> 2018 | M4: =L4+1 -> 2019
A5: Year No. | D5: 1 | E5: =D5+1 -> 2 | F5: =E5+1 -> 3 | G5: =F5+1 -> 4 | H5: =G5+1 -> 5 | I5: =H5+1 -> 6 | J5: =I5+1 -> 7 | K5: =J5+1 -> 8 | L5: =K5+1 -> 9 | M5: =L5+1 -> 10
A8: Capital Ratios
A9: Debt Ratio | D9: =IF(Bal_Sheet!F32>0,(Bal_Sheet!F42+Bal_Sheet!F56+Bal_Sheet!F61)/Bal_Sheet!F32,"N/A") -> 0.68329554 | E9: =IF(Bal_Sheet!G32>0,(Bal_Sheet!G42+Bal_Sheet!G56+Bal_Sheet!G61)/Bal_Sheet!G32,"N/A") -> 0.60550877 | F9: =IF(Bal_Sheet!H32>0,(Bal_Sheet!H42+Bal_Sheet!H56+Bal_Sheet!H61)/Bal_Sheet!H32,"N/A") -> 0.53170167 | G9: =IF(Bal_Sheet!I32>0,(Bal_Sheet!I42+Bal_Sheet!I56+Bal_Sheet!I61)/Bal_Sheet!I32,"N/A") -> 0.46238077 | H9: =IF(Bal_Sheet!J32>0,(Bal_Sheet!J42+Bal_Sheet!J56+Bal_Sheet!J61)/Bal_Sheet!J32,"N/A") -> 0.39896398 | I9: =IF(Bal_Sheet!K32>0,(Bal_Sheet!K42+Bal_Sheet!K56+Bal_Sheet!K61)/Bal_Sheet!K32,"N/A") -> 0.34051046 | J9: =IF(Bal_Sheet!L32>0,(Bal_Sheet!L42+Bal_Sheet!L56+Bal_Sheet!L61)/Bal_Sheet!L32,"N/A") -> 0.28878115 | K9: =IF(Bal_Sheet!M32>0,(Bal_Sheet!M42+Bal_Sheet!M56+Bal_Sheet!M61)/Bal_Sheet!M32,"N/A") -> 0.26912124 | ... M9: =IF(Bal_Sheet!O32>0,(Bal_Sheet!O42+Bal_Sheet!O56+Bal_Sheet!O61)/Bal_Sheet!O32,"N/A") -> 0.24995874
A10: Total Debt / Book Capitalization | D10: =IF(Bal_Sheet!F54+Bal_Sheet!F65>0,(Bal_Sheet!F54+Bal_Sheet!F61)/(Bal_Sheet!F54+Bal_Sheet!F65),"N/A") -> 0.61424713 | E10: =IF(Bal_Sheet!G54+Bal_Sheet!G65>0,(Bal_Sheet!G54+Bal_Sheet!G61)/(Bal_Sheet!G54+Bal_Sheet!G65),"N/A") -> 0.51555954 | F10: =IF(Bal_Sheet!H54+Bal_Sheet!H65>0,(Bal_Sheet!H54+Bal_Sheet!H61)/(Bal_Sheet!H54+Bal_Sheet!H65),"N/A") -> 0.42116817 | G10: =IF(Bal_Sheet!I54+Bal_Sheet!I65>0,(Bal_Sheet!I54+Bal_Sheet!I61)/(Bal_Sheet!I54+Bal_Sheet!I65),"N/A") -> 0.33041429 | H10: =IF(Bal_Sheet!J54+Bal_Sheet!J65>0,(Bal_Sheet!J54+Bal_Sheet!J61)/(Bal_Sheet!J54+Bal_Sheet!J65),"N/A") -> 0.24112348 | I10: =IF(Bal_Sheet!K54+Bal_Sheet!K65>0,(Bal_Sheet!K54+Bal_Sheet!K61)/(Bal_Sheet!K54+Bal_Sheet!K65),"N/A") -> 0.15734548 | J10: =IF(Bal_Sheet!L54+Bal_Sheet!L65>0,(Bal_Sheet!L54+Bal_Sheet!L61)/(Bal_Sheet!L54+Bal_Sheet!L65),"N/A") -> 0.082147066 | K10: =IF(Bal_Sheet!M54+Bal_Sheet!M65>0,(Bal_Sheet!M54+Bal_Sheet!M61)/(Bal_Sheet!M54+Bal_Sheet!M65),"N/A") -> 0.042868987 | ... M10: =IF(Bal_Sheet!O54+Bal_Sheet!O65>0,(Bal_Sheet!O54+Bal_Sheet!O61)/(Bal_Sheet!O54+Bal_Sheet!O65),"N/A") -> 0.031945361
A11: Total Debt / Equity | D11: =IF(Bal_Sheet!F62+Bal_Sheet!F63>0,(Bal_Sheet!F54+Bal_Sheet!F61)/(Bal_Sheet!F62+Bal_Sheet!F63),"N/A") -> 1.5923333 | E11: =IF(Bal_Sheet!G62+Bal_Sheet!G63>0,(Bal_Sheet!G54+Bal_Sheet!G61)/(Bal_Sheet!G62+Bal_Sheet!G63),"N/A") -> 1.0642372 | F11: =IF(Bal_Sheet!H62+Bal_Sheet!H63>0,(Bal_Sheet!H54+Bal_Sheet!H61)/(Bal_Sheet!H62+Bal_Sheet!H63),"N/A") -> 0.72761749 | G11: =IF(Bal_Sheet!I62+Bal_Sheet!I63>0,(Bal_Sheet!I54+Bal_Sheet!I61)/(Bal_Sheet!I62+Bal_Sheet!I63),"N/A") -> 0.49346077 | H11: =IF(Bal_Sheet!J62+Bal_Sheet!J63>0,(Bal_Sheet!J54+Bal_Sheet!J61)/(Bal_Sheet!J62+Bal_Sheet!J63),"N/A") -> 0.31773743 | I11: =IF(Bal_Sheet!K62+Bal_Sheet!K63>0,(Bal_Sheet!K54+Bal_Sheet!K61)/(Bal_Sheet!K62+Bal_Sheet!K63),"N/A") -> 0.18672597 | J11: =IF(Bal_Sheet!L62+Bal_Sheet!L63>0,(Bal_Sheet!L54+Bal_Sheet!L61)/(Bal_Sheet!L62+Bal_Sheet!L63),"N/A") -> 0.089499159 | K11: =IF(Bal_Sheet!M62+Bal_Sheet!M63>0,(Bal_Sheet!M54+Bal_Sheet!M61)/(Bal_Sheet!M62+Bal_Sheet!M63),"N/A") -> 0.044789048 | ... M11: =IF(Bal_Sheet!O62+Bal_Sheet!O63>0,(Bal_Sheet!O54+Bal_Sheet!O61)/(Bal_Sheet!O62+Bal_Sheet!O63),"N/A") -> 0.032999543
A14: Leverage Ratios
A15: Total Debt / EBITDA | D15: =IF(Inc_St!D18<>0,(Bal_Sheet!F54+Bal_Sheet!F61)/Inc_St!D18,"N/A") -> 2.0717191 | E15: =IF(Inc_St!E18<>0,(Bal_Sheet!G54+Bal_Sheet!G61)/Inc_St!E18,"N/A") -> 1.7085525 | F15: =IF(Inc_St!F18<>0,(Bal_Sheet!H54+Bal_Sheet!H61)/Inc_St!F18,"N/A") -> 1.3772739 | G15: =IF(Inc_St!G18<>0,(Bal_Sheet!I54+Bal_Sheet!I61)/Inc_St!G18,"N/A") -> 1.0680785 | H15: =IF(Inc_St!H18<>0,(Bal_Sheet!J54+Bal_Sheet!J61)/Inc_St!H18,"N/A") -> 0.76707657 | I15: =IF(Inc_St!I18<>0,(Bal_Sheet!K54+Bal_Sheet!K61)/Inc_St!I18,"N/A") -> 0.49502431 | J15: =IF(Inc_St!J18<>0,(Bal_Sheet!L54+Bal_Sheet!L61)/Inc_St!J18,"N/A") -> 0.26181835 | K15: =IF(Inc_St!K18<>0,(Bal_Sheet!M54+Bal_Sheet!M61)/Inc_St!K18,"N/A") -> 0.14232908 | ... M15: =IF(Inc_St!M18<>0,(Bal_Sheet!O54+Bal_Sheet!O61)/Inc_St!M18,"N/A") -> 0.11940656
A16: Total Debt / (EBITDA - Capex) | D16: =IF(Inc_St!D18+Cash_Flow!D30<>0,(Bal_Sheet!F54+Bal_Sheet!F61)/(Inc_St!D18+Cash_Flow!D30),"N/A") -> 3.1620975 | E16: =IF(Inc_St!E18+Cash_Flow!E30<>0,(Bal_Sheet!G54+Bal_Sheet!G61)/(Inc_St!E18+Cash_Flow!E30),"N/A") -> 2.6173812 | F16: =IF(Inc_St!F18+Cash_Flow!F30<>0,(Bal_Sheet!H54+Bal_Sheet!H61)/(Inc_St!F18+Cash_Flow!F30),"N/A") -> 2.1178097 | G16: =IF(Inc_St!G18+Cash_Flow!G30<>0,(Bal_Sheet!I54+Bal_Sheet!I61)/(Inc_St!G18+Cash_Flow!G30),"N/A") -> 1.6486656 | H16: =IF(Inc_St!H18+Cash_Flow!H30<>0,(Bal_Sheet!J54+Bal_Sheet!J61)/(Inc_St!H18+Cash_Flow!H30),"N/A") -> 1.1886853 | I16: =IF(Inc_St!I18+Cash_Flow!I30<>0,(Bal_Sheet!K54+Bal_Sheet!K61)/(Inc_St!I18+Cash_Flow!I30),"N/A") -> 0.77017703 | J16: =IF(Inc_St!J18+Cash_Flow!J30<>0,(Bal_Sheet!L54+Bal_Sheet!L61)/(Inc_St!J18+Cash_Flow!J30),"N/A") -> 0.40901419 | K16: =IF(Inc_St!K18+Cash_Flow!K30<>0,(Bal_Sheet!M54+Bal_Sheet!M61)/(Inc_St!K18+Cash_Flow!K30),"N/A") -> 0.22327795 | ... M16: =IF(Inc_St!M18+Cash_Flow!M30<>0,(Bal_Sheet!O54+Bal_Sheet!O61)/(Inc_St!M18+Cash_Flow!M30),"N/A") -> 0.18894383
A17: Net Debt / EBITDA | D17: =IF(Inc_St!D18<>0,(Bal_Sheet!F54+Bal_Sheet!F61-Bal_Sheet!F10)/Inc_St!D18,"N/A") -> 1.9149793 | E17: =IF(Inc_St!E18<>0,(Bal_Sheet!G54+Bal_Sheet!G61-Bal_Sheet!G10)/Inc_St!E18,"N/A") -> 1.5650697 | F17: =IF(Inc_St!F18<>0,(Bal_Sheet!H54+Bal_Sheet!H61-Bal_Sheet!H10)/Inc_St!F18,"N/A") -> 1.2459175 | G17: =IF(Inc_St!G18<>0,(Bal_Sheet!I54+Bal_Sheet!I61-Bal_Sheet!I10)/Inc_St!G18,"N/A") -> 0.94781491 | H17: =IF(Inc_St!H18<>0,(Bal_Sheet!J54+Bal_Sheet!J61-Bal_Sheet!J10)/Inc_St!H18,"N/A") -> 0.65696087 | I17: =IF(Inc_St!I18<>0,(Bal_Sheet!K54+Bal_Sheet!K61-Bal_Sheet!K10)/Inc_St!I18,"N/A") -> 0.39419259 | J17: =IF(Inc_St!J18<>0,(Bal_Sheet!L54+Bal_Sheet!L61-Bal_Sheet!L10)/Inc_St!J18,"N/A") -> 0.1694808 | K17: =IF(Inc_St!K18<>0,(Bal_Sheet!M54+Bal_Sheet!M61-Bal_Sheet!M10)/Inc_St!K18,"N/A") -> -0.084862822 | ... M17: =IF(Inc_St!M18<>0,(Bal_Sheet!O54+Bal_Sheet!O61-Bal_Sheet!O10)/Inc_St!M18,"N/A") -> -0.38131632
A18: Senior Debt / EBITDA | D18: =IF(Inc_St!D18<>0,SUM(Bal_Sheet!F46:F50)/Inc_St!D18,"N/A") -> 1.4390226 | E18: =IF(Inc_St!E18<>0,SUM(Bal_Sheet!G46:G50)/Inc_St!E18,"N/A") -> 1.1086453 | F18: =IF(Inc_St!F18<>0,SUM(Bal_Sheet!H46:H50)/Inc_St!F18,"N/A") -> 0.80800323 | G18: =IF(Inc_St!G18<>0,SUM(Bal_Sheet!I46:I50)/Inc_St!G18,"N/A") -> 0.52745108 | H18: =IF(Inc_St!H18<>0,SUM(Bal_Sheet!J46:J50)/Inc_St!H18,"N/A") -> 0.47012894 | I18: =IF(Inc_St!I18<>0,SUM(Bal_Sheet!K46:K50)/Inc_St!I18,"N/A") -> 0.32531827 | J18: =IF(Inc_St!J18<>0,SUM(Bal_Sheet!L46:L50)/Inc_St!J18,"N/A") -> 0.10640852 | K18: =IF(Inc_St!K18<>0,SUM(Bal_Sheet!M46:M50)/Inc_St!K18,"N/A") -> 0 | ... M18: =IF(Inc_St!M18<>0,SUM(Bal_Sheet!O46:O50)/Inc_St!M18,"N/A") -> 0
A21: Interest Coverage
A22: EBITDA / Total Interest | D22: =IF(Inc_St!D24+Inc_St!D46>0,Inc_St!D18/(Inc_St!D24+Inc_St!D46),"N/A") -> 8.7972908 | E22: =IF(Inc_St!E24+Inc_St!E46>0,Inc_St!E18/(Inc_St!E24+Inc_St!E46),"N/A") -> 9.9556312 | F22: =IF(Inc_St!F24+Inc_St!F46>0,Inc_St!F18/(Inc_St!F24+Inc_St!F46),"N/A") -> 12.029288 | G22: =IF(Inc_St!G24+Inc_St!G46>0,Inc_St!G18/(Inc_St!G24+Inc_St!G46),"N/A") -> 14.889054 | H22: =IF(Inc_St!H24+Inc_St!H46>0,Inc_St!H18/(Inc_St!H24+Inc_St!H46),"N/A") -> 17.30014 | I22: =IF(Inc_St!I24+Inc_St!I46>0,Inc_St!I18/(Inc_St!I24+Inc_St!I46),"N/A") -> 22.591151 | J22: =IF(Inc_St!J24+Inc_St!J46>0,Inc_St!J18/(Inc_St!J24+Inc_St!J46),"N/A") -> 30.183269 | K22: =IF(Inc_St!K24+Inc_St!K46>0,Inc_St!K18/(Inc_St!K24+Inc_St!K46),"N/A") -> 42.078053 | ... M22: =IF(Inc_St!M24+Inc_St!M46>0,Inc_St!M18/(Inc_St!M24+Inc_St!M46),"N/A") -> 59.269858
A23: EBITDA / Senior Interest | D23: =IF(SUM(Inc_St!D25:D29)>0,Inc_St!D18/SUM(Inc_St!D25:D29),"N/A") -> 12.335864 | E23: =IF(SUM(Inc_St!E25:E29)>0,Inc_St!E18/SUM(Inc_St!E25:E29),"N/A") -> 14.394149 | F23: =IF(SUM(Inc_St!F25:F29)>0,Inc_St!F18/SUM(Inc_St!F25:F29),"N/A") -> 18.627714 | G23: =IF(SUM(Inc_St!G25:G29)>0,Inc_St!G18/SUM(Inc_St!G25:G29),"N/A") -> 25.547585 | H23: =IF(SUM(Inc_St!H25:H29)>0,Inc_St!H18/SUM(Inc_St!H25:H29),"N/A") -> 32.137752 | I23: =IF(SUM(Inc_St!I25:I29)>0,Inc_St!I18/SUM(Inc_St!I25:I29),"N/A") -> 35.406693 | J23: =IF(SUM(Inc_St!J25:J29)>0,Inc_St!J18/SUM(Inc_St!J25:J29),"N/A") -> 44.939277 | K23: =IF(SUM(Inc_St!K25:K29)>0,Inc_St!K18/SUM(Inc_St!K25:K29),"N/A") -> 72.451572 | ... M23: =IF(SUM(Inc_St!M25:M29)>0,Inc_St!M18/SUM(Inc_St!M25:M29),"N/A") -> 117.46019
A24: EBITDA / Cash Interest | D24: =IF(Inc_St!D24+Inc_St!D46-SUM(Cash_Flow!D15:D18)>0,Inc_St!D18/(Inc_St!D24+Inc_St!D46-SUM(Cash_Flow!D15:D18)),"N/A") -> 12.335864 | E24: =IF(Inc_St!E24+Inc_St!E46-SUM(Cash_Flow!E15:E18)>0,Inc_St!E18/(Inc_St!E24+Inc_St!E46-SUM(Cash_Flow!E15:E18)),"N/A") -> 14.394149 | F24: =IF(Inc_St!F24+Inc_St!F46-SUM(Cash_Flow!F15:F18)>0,Inc_St!F18/(Inc_St!F24+Inc_St!F46-SUM(Cash_Flow!F15:F18)),"N/A") -> 18.627714 | G24: =IF(Inc_St!G24+Inc_St!G46-SUM(Cash_Flow!G15:G18)>0,Inc_St!G18/(Inc_St!G24+Inc_St!G46-SUM(Cash_Flow!G15:G18)),"N/A") -> 25.547585 | H24: =IF(Inc_St!H24+Inc_St!H46-SUM(Cash_Flow!H15:H18)>0,Inc_St!H18/(Inc_St!H24+Inc_St!H46-SUM(Cash_Flow!H15:H18)),"N/A") -> 32.137752 | I24: =IF(Inc_St!I24+Inc_St!I46-SUM(Cash_Flow!I15:I18)>0,Inc_St!I18/(Inc_St!I24+Inc_St!I46-SUM(Cash_Flow!I15:I18)),"N/A") -> 22.591151 | J24: =IF(Inc_St!J24+Inc_St!J46-SUM(Cash_Flow!J15:J18)>0,Inc_St!J18/(Inc_St!J24+Inc_St!J46-SUM(Cash_Flow!J15:J18)),"N/A") -> 30.183269 | K24: =IF(Inc_St!K24+Inc_St!K46-SUM(Cash_Flow!K15:K18)>0,Inc_St!K18/(Inc_St!K24+Inc_St!K46-SUM(Cash_Flow!K15:K18)),"N/A") -> 42.078053 | ... M24: =IF(Inc_St!M24+Inc_St!M46-SUM(Cash_Flow!M15:M18)>0,Inc_St!M18/(Inc_St!M24+Inc_St!M46-SUM(Cash_Flow!M15:M18)),"N/A") -> 59.269858
A26: (EBITDA - Capex) / Total Interest | D26: =IF(Inc_St!D24+Inc_St!D46>0,(Inc_St!D18+Cash_Flow!D30)/(Inc_St!D24+Inc_St!D46),"N/A") -> 5.7637422 | E26: =IF(Inc_St!E24+Inc_St!E46>0,(Inc_St!E18+Cash_Flow!E30)/(Inc_St!E24+Inc_St!E46),"N/A") -> 6.4987548 | F26: =IF(Inc_St!F24+Inc_St!F46>0,(Inc_St!F18+Cash_Flow!F30)/(Inc_St!F24+Inc_St!F46),"N/A") -> 7.8229992 | G26: =IF(Inc_St!G24+Inc_St!G46>0,(Inc_St!G18+Cash_Flow!G30)/(Inc_St!G24+Inc_St!G46),"N/A") -> 9.6457874 | H26: =IF(Inc_St!H24+Inc_St!H46>0,(Inc_St!H18+Cash_Flow!H30)/(Inc_St!H24+Inc_St!H46),"N/A") -> 11.164042 | I26: =IF(Inc_St!I24+Inc_St!I46>0,(Inc_St!I18+Cash_Flow!I30)/(Inc_St!I24+Inc_St!I46),"N/A") -> 14.520257 | J26: =IF(Inc_St!J24+Inc_St!J46>0,(Inc_St!J18+Cash_Flow!J30)/(Inc_St!J24+Inc_St!J46),"N/A") -> 19.320928 | K26: =IF(Inc_St!K24+Inc_St!K46>0,(Inc_St!K18+Cash_Flow!K30)/(Inc_St!K24+Inc_St!K46),"N/A") -> 26.822758 | ... M26: =IF(Inc_St!M24+Inc_St!M46>0,(Inc_St!M18+Cash_Flow!M30)/(Inc_St!M24+Inc_St!M46),"N/A") -> 37.456687
A27: (EBITDA - Capex) / Senior Interest | D27: =IF(SUM(Inc_St!D25:D29)>0,(Inc_St!D18+Cash_Flow!D30)/SUM(Inc_St!D25:D29),"N/A") -> 8.0821177 | E27: =IF(SUM(Inc_St!E25:E29)>0,(Inc_St!E18+Cash_Flow!E30)/SUM(Inc_St!E25:E29),"N/A") -> 9.3960936 | F27: =IF(SUM(Inc_St!F25:F29)>0,(Inc_St!F18+Cash_Flow!F30)/SUM(Inc_St!F25:F29),"N/A") -> 12.114149 | G27: =IF(SUM(Inc_St!G25:G29)>0,(Inc_St!G18+Cash_Flow!G30)/SUM(Inc_St!G25:G29),"N/A") -> 16.550855 | H27: =IF(SUM(Inc_St!H25:H29)>0,(Inc_St!H18+Cash_Flow!H30)/SUM(Inc_St!H25:H29),"N/A") -> 20.738977 | I27: =IF(SUM(Inc_St!I25:I29)>0,(Inc_St!I18+Cash_Flow!I30)/SUM(Inc_St!I25:I29),"N/A") -> 22.757331 | J27: =IF(SUM(Inc_St!J25:J29)>0,(Inc_St!J18+Cash_Flow!J30)/SUM(Inc_St!J25:J29),"N/A") -> 28.766551 | K27: =IF(SUM(Inc_St!K25:K29)>0,(Inc_St!K18+Cash_Flow!K30)/SUM(Inc_St!K25:K29),"N/A") -> 46.184432 | ... M27: =IF(SUM(Inc_St!M25:M29)>0,(Inc_St!M18+Cash_Flow!M30)/SUM(Inc_St!M25:M29),"N/A") -> 74.231146
A28: (EBITDA - Capex) / Cash Interest | D28: =IF(Inc_St!D24+Inc_St!D46-SUM(Cash_Flow!D15:D18)>0,(Inc_St!D18+Cash_Flow!D30)/(Inc_St!D24+Inc_St!D46-SUM(Cash_Flow!D15:D18)),"N/A") -> 8.0821177 | E28: =IF(Inc_St!E24+Inc_St!E46-SUM(Cash_Flow!E15:E18)>0,(Inc_St!E18+Cash_Flow!E30)/(Inc_St!E24+Inc_St!E46-SUM(Cash_Flow!E15:E18)),"N/A") -> 9.3960936 | F28: =IF(Inc_St!F24+Inc_St!F46-SUM(Cash_Flow!F15:F18)>0,(Inc_St!F18+Cash_Flow!F30)/(Inc_St!F24+Inc_St!F46-SUM(Cash_Flow!F15:F18)),"N/A") -> 12.114149 | G28: =IF(Inc_St!G24+Inc_St!G46-SUM(Cash_Flow!G15:G18)>0,(Inc_St!G18+Cash_Flow!G30)/(Inc_St!G24+Inc_St!G46-SUM(Cash_Flow!G15:G18)),"N/A") -> 16.550855 | H28: =IF(Inc_St!H24+Inc_St!H46-SUM(Cash_Flow!H15:H18)>0,(Inc_St!H18+Cash_Flow!H30)/(Inc_St!H24+Inc_St!H46-SUM(Cash_Flow!H15:H18)),"N/A") -> 20.738977 | I28: =IF(Inc_St!I24+Inc_St!I46-SUM(Cash_Flow!I15:I18)>0,(Inc_St!I18+Cash_Flow!I30)/(Inc_St!I24+Inc_St!I46-SUM(Cash_Flow!I15:I18)),"N/A") -> 14.520257 | J28: =IF(Inc_St!J24+Inc_St!J46-SUM(Cash_Flow!J15:J18)>0,(Inc_St!J18+Cash_Flow!J30)/(Inc_St!J24+Inc_St!J46-SUM(Cash_Flow!J15:J18)),"N/A") -> 19.320928 | K28: =IF(Inc_St!K24+Inc_St!K46-SUM(Cash_Flow!K15:K18)>0,(Inc_St!K18+Cash_Flow!K30)/(Inc_St!K24+Inc_St!K46-SUM(Cash_Flow!K15:K18)),"N/A") -> 26.822758 | ... M28: =IF(Inc_St!M24+Inc_St!M46-SUM(Cash_Flow!M15:M18)>0,(Inc_St!M18+Cash_Flow!M30)/(Inc_St!M24+Inc_St!M46-SUM(Cash_Flow!M15:M18)),"N/A") -> 37.456687
A30: EBIT / Total Interest | D30: =IF(Inc_St!D24+Inc_St!D46>0,Inc_St!D22/(Inc_St!D24+Inc_St!D46),"N/A") -> 6.786209 | E30: =IF(Inc_St!E24+Inc_St!E46>0,Inc_St!E22/(Inc_St!E24+Inc_St!E46),"N/A") -> 7.5265565 | F30: =IF(Inc_St!F24+Inc_St!F46>0,Inc_St!F22/(Inc_St!F24+Inc_St!F46),"N/A") -> 9.061895 | G30: =IF(Inc_St!G24+Inc_St!G46>0,Inc_St!G22/(Inc_St!G24+Inc_St!G46),"N/A") -> 11.151857 | H30: =IF(Inc_St!H24+Inc_St!H46>0,Inc_St!H22/(Inc_St!H24+Inc_St!H46),"N/A") -> 12.812824 | I30: =IF(Inc_St!I24+Inc_St!I46>0,Inc_St!I22/(Inc_St!I24+Inc_St!I46),"N/A") -> 16.721058 | J30: =IF(Inc_St!J24+Inc_St!J46>0,Inc_St!J22/(Inc_St!J24+Inc_St!J46),"N/A") -> 24.523795 | K30: =IF(Inc_St!K24+Inc_St!K46>0,Inc_St!K22/(Inc_St!K24+Inc_St!K46),"N/A") -> 33.835323 | ... M30: =IF(Inc_St!M24+Inc_St!M46>0,Inc_St!M22/(Inc_St!M24+Inc_St!M46),"N/A") -> 46.683458
A33: Asset Utilization
A34: Total Asset Turnover (Sales) | D34: =IF(OR(Bal_Sheet!F32>0,Bal_Sheet!E32>0),Inc_St!D8/AVERAGE(Bal_Sheet!F32,Bal_Sheet!E32),0) -> 0.93499488 | E34: =IF(OR(Bal_Sheet!G32>0,Bal_Sheet!F32>0),Inc_St!E8/AVERAGE(Bal_Sheet!G32,Bal_Sheet!F32),0) -> 0.88688828 | F34: =IF(OR(Bal_Sheet!H32>0,Bal_Sheet!G32>0),Inc_St!F8/AVERAGE(Bal_Sheet!H32,Bal_Sheet!G32),0) -> 0.90032537 | G34: =IF(OR(Bal_Sheet!I32>0,Bal_Sheet!H32>0),Inc_St!G8/AVERAGE(Bal_Sheet!I32,Bal_Sheet!H32),0) -> 0.91153381 | H34: =IF(OR(Bal_Sheet!J32>0,Bal_Sheet!I32>0),Inc_St!H8/AVERAGE(Bal_Sheet!J32,Bal_Sheet!I32),0) -> 0.92089994 | I34: =IF(OR(Bal_Sheet!K32>0,Bal_Sheet!J32>0),Inc_St!I8/AVERAGE(Bal_Sheet!K32,Bal_Sheet!J32),0) -> 0.92819415 | J34: =IF(OR(Bal_Sheet!L32>0,Bal_Sheet!K32>0),Inc_St!J8/AVERAGE(Bal_Sheet!L32,Bal_Sheet!K32),0) -> 0.92342749 | K34: =IF(OR(Bal_Sheet!M32>0,Bal_Sheet!L32>0),Inc_St!K8/AVERAGE(Bal_Sheet!M32,Bal_Sheet!L32),0) -> 0.89354136 | ... M34: =IF(OR(Bal_Sheet!O32>0,Bal_Sheet!N32>0),Inc_St!M8/AVERAGE(Bal_Sheet!O32,Bal_Sheet!N32),0) -> 0.81167135
A35: Fixed Asset Turnover (Sales) | D35: =IF(OR(Bal_Sheet!F28>0,Bal_Sheet!E28>0),Inc_St!D8/AVERAGE(Bal_Sheet!F28,Bal_Sheet!E28),0) -> 2.2173955 | E35: =IF(OR(Bal_Sheet!G28>0,Bal_Sheet!F28>0),Inc_St!E8/AVERAGE(Bal_Sheet!G28,Bal_Sheet!F28),0) -> 2.2710956 | F35: =IF(OR(Bal_Sheet!H28>0,Bal_Sheet!G28>0),Inc_St!F8/AVERAGE(Bal_Sheet!H28,Bal_Sheet!G28),0) -> 2.3328333 | G35: =IF(OR(Bal_Sheet!I28>0,Bal_Sheet!H28>0),Inc_St!G8/AVERAGE(Bal_Sheet!I28,Bal_Sheet!H28),0) -> 2.3948302 | H35: =IF(OR(Bal_Sheet!J28>0,Bal_Sheet!I28>0),Inc_St!H8/AVERAGE(Bal_Sheet!J28,Bal_Sheet!I28),0) -> 2.4617916 | I35: =IF(OR(Bal_Sheet!K28>0,Bal_Sheet!J28>0),Inc_St!I8/AVERAGE(Bal_Sheet!K28,Bal_Sheet!J28),0) -> 2.5301771 | J35: =IF(OR(Bal_Sheet!L28>0,Bal_Sheet!K28>0),Inc_St!J8/AVERAGE(Bal_Sheet!L28,Bal_Sheet!K28),0) -> 2.526943 | K35: =IF(OR(Bal_Sheet!M28>0,Bal_Sheet!L28>0),Inc_St!K8/AVERAGE(Bal_Sheet!M28,Bal_Sheet!L28),0) -> 2.4715848 | ... M35: =IF(OR(Bal_Sheet!O28>0,Bal_Sheet!N28>0),Inc_St!M8/AVERAGE(Bal_Sheet!O28,Bal_Sheet!N28),0) -> 2.4026716
A38: Activity Ratios
A39: Inventory Turnover (COGS) | D39: =IF(OR(Bal_Sheet!F12>0,Bal_Sheet!E12>0),Inc_St!D10/AVERAGE(Bal_Sheet!F12,Bal_Sheet!E12),"N/A") -> 5.0769491 | E39: =IF(OR(Bal_Sheet!G12>0,Bal_Sheet!F12>0),Inc_St!E10/AVERAGE(Bal_Sheet!G12,Bal_Sheet!F12),"N/A") -> 5.1365716 | F39: =IF(OR(Bal_Sheet!H12>0,Bal_Sheet!G12>0),Inc_St!F10/AVERAGE(Bal_Sheet!H12,Bal_Sheet!G12),"N/A") -> 4.9390111 | G39: =IF(OR(Bal_Sheet!I12>0,Bal_Sheet!H12>0),Inc_St!G10/AVERAGE(Bal_Sheet!I12,Bal_Sheet!H12),"N/A") -> 4.7490491 | H39: =IF(OR(Bal_Sheet!J12>0,Bal_Sheet!I12>0),Inc_St!H10/AVERAGE(Bal_Sheet!J12,Bal_Sheet!I12),"N/A") -> 4.5663934 | I39: =IF(OR(Bal_Sheet!K12>0,Bal_Sheet!J12>0),Inc_St!I10/AVERAGE(Bal_Sheet!K12,Bal_Sheet!J12),"N/A") -> 4.3907629 | J39: =IF(OR(Bal_Sheet!L12>0,Bal_Sheet!K12>0),Inc_St!J10/AVERAGE(Bal_Sheet!L12,Bal_Sheet!K12),"N/A") -> 4.2218874 | K39: =IF(OR(Bal_Sheet!M12>0,Bal_Sheet!L12>0),Inc_St!K10/AVERAGE(Bal_Sheet!M12,Bal_Sheet!L12),"N/A") -> 4.0595071 | ... M39: =IF(OR(Bal_Sheet!O12>0,Bal_Sheet!N12>0),Inc_St!M10/AVERAGE(Bal_Sheet!O12,Bal_Sheet!N12),"N/A") -> 3.7532425
A40: Accounts Receivable Turnover (Sales) | D40: =IF(OR(Bal_Sheet!F11>0,Bal_Sheet!E11>0),Inc_St!D8/AVERAGE(Bal_Sheet!F11,Bal_Sheet!E11),"N/A") -> 7.7738516 | E40: =IF(OR(Bal_Sheet!G11>0,Bal_Sheet!F11>0),Inc_St!E8/AVERAGE(Bal_Sheet!G11,Bal_Sheet!F11),"N/A") -> 5.6715648 | F40: =IF(OR(Bal_Sheet!H11>0,Bal_Sheet!G11>0),Inc_St!F8/AVERAGE(Bal_Sheet!H11,Bal_Sheet!G11),"N/A") -> 5.4014903 | G40: =IF(OR(Bal_Sheet!I11>0,Bal_Sheet!H11>0),Inc_St!G8/AVERAGE(Bal_Sheet!I11,Bal_Sheet!H11),"N/A") -> 5.1442765 | H40: =IF(OR(Bal_Sheet!J11>0,Bal_Sheet!I11>0),Inc_St!H8/AVERAGE(Bal_Sheet!J11,Bal_Sheet!I11),"N/A") -> 4.8993109 | I40: =IF(OR(Bal_Sheet!K11>0,Bal_Sheet!J11>0),Inc_St!I8/AVERAGE(Bal_Sheet!K11,Bal_Sheet!J11),"N/A") -> 4.6660104 | J40: =IF(OR(Bal_Sheet!L11>0,Bal_Sheet!K11>0),Inc_St!J8/AVERAGE(Bal_Sheet!L11,Bal_Sheet!K11),"N/A") -> 4.4438195 | K40: =IF(OR(Bal_Sheet!M11>0,Bal_Sheet!L11>0),Inc_St!K8/AVERAGE(Bal_Sheet!M11,Bal_Sheet!L11),"N/A") -> 4.232209 | ... M40: =IF(OR(Bal_Sheet!O11>0,Bal_Sheet!N11>0),Inc_St!M8/AVERAGE(Bal_Sheet!O11,Bal_Sheet!N11),"N/A") -> 3.8387383
A41: Accounts Payable Turnover (COGS & Inv) | D41: =IF(OR(Bal_Sheet!F38>0,Bal_Sheet!E38>0),(Inc_St!D10+Bal_Sheet!F12-Bal_Sheet!E12)/AVERAGE(Bal_Sheet!F38,Bal_Sheet!E38),"N/A") -> 7.8735243 | E41: =IF(OR(Bal_Sheet!G38>0,Bal_Sheet!F38>0),(Inc_St!E10+Bal_Sheet!G12-Bal_Sheet!F12)/AVERAGE(Bal_Sheet!G38,Bal_Sheet!F38),"N/A") -> 6.9857326 | F41: =IF(OR(Bal_Sheet!H38>0,Bal_Sheet!G38>0),(Inc_St!F10+Bal_Sheet!H12-Bal_Sheet!G12)/AVERAGE(Bal_Sheet!H38,Bal_Sheet!G38),"N/A") -> 6.7874789 | G41: =IF(OR(Bal_Sheet!I38>0,Bal_Sheet!H38>0),(Inc_St!G10+Bal_Sheet!I12-Bal_Sheet!H12)/AVERAGE(Bal_Sheet!I38,Bal_Sheet!H38),"N/A") -> 6.6545174 | H41: =IF(OR(Bal_Sheet!J38>0,Bal_Sheet!I38>0),(Inc_St!H10+Bal_Sheet!J12-Bal_Sheet!I12)/AVERAGE(Bal_Sheet!J38,Bal_Sheet!I38),"N/A") -> 6.5241652 | I41: =IF(OR(Bal_Sheet!K38>0,Bal_Sheet!J38>0),(Inc_St!I10+Bal_Sheet!K12-Bal_Sheet!J12)/AVERAGE(Bal_Sheet!K38,Bal_Sheet!J38),"N/A") -> 6.3963711 | J41: =IF(OR(Bal_Sheet!L38>0,Bal_Sheet!K38>0),(Inc_St!J10+Bal_Sheet!L12-Bal_Sheet!K12)/AVERAGE(Bal_Sheet!L38,Bal_Sheet!K38),"N/A") -> 6.271085 | K41: =IF(OR(Bal_Sheet!M38>0,Bal_Sheet!L38>0),(Inc_St!K10+Bal_Sheet!M12-Bal_Sheet!L12)/AVERAGE(Bal_Sheet!M38,Bal_Sheet!L38),"N/A") -> 6.1482578 | ... M41: =IF(OR(Bal_Sheet!O38>0,Bal_Sheet!N38>0),(Inc_St!M10+Bal_Sheet!O12-Bal_Sheet!N12)/AVERAGE(Bal_Sheet!O38,Bal_Sheet!N38),"N/A") -> 5.9097882
A42: Inventory Holding Period (Days) | D42: =IF(OR(D39="N/A",D39=0),"N/A",365/D39) -> 71.893571 | E42: =IF(OR(E39="N/A",E39=0),"N/A",365/E39) -> 71.059071 | F42: =IF(OR(F39="N/A",F39=0),"N/A",365/F39) -> 73.901433 | G42: =IF(OR(G39="N/A",G39=0),"N/A",365/G39) -> 76.857491 | H42: =IF(OR(H39="N/A",H39=0),"N/A",365/H39) -> 79.93179 | I42: =IF(OR(I39="N/A",I39=0),"N/A",365/I39) -> 83.129062 | J42: =IF(OR(J39="N/A",J39=0),"N/A",365/J39) -> 86.454224 | K42: =IF(OR(K39="N/A",K39=0),"N/A",365/K39) -> 89.912393 | ... M42: =IF(OR(M39="N/A",M39=0),"N/A",365/M39) -> 97.249245
A43: Days Receivable (Sales) | D43: =IF(OR(D40="N/A",D40=0),"N/A",365/D40) -> 46.952273 | E43: =IF(OR(E40="N/A",E40=0),"N/A",365/E40) -> 64.356136 | F43: =IF(OR(F40="N/A",F40=0),"N/A",365/F40) -> 67.573943 | G43: =IF(OR(G40="N/A",G40=0),"N/A",365/G40) -> 70.95264 | H43: =IF(OR(H40="N/A",H40=0),"N/A",365/H40) -> 74.500272 | I43: =IF(OR(I40="N/A",I40=0),"N/A",365/I40) -> 78.225286 | J43: =IF(OR(J40="N/A",J40=0),"N/A",365/J40) -> 82.13655 | K43: =IF(OR(K40="N/A",K40=0),"N/A",365/K40) -> 86.243378 | ... M43: =IF(OR(M40="N/A",M40=0),"N/A",365/M40) -> 95.083324
A44: Days Payable (COGS & Inv) | D44: =IF(OR(D41="N/A",D41=0),"N/A",365/D41) -> 46.357894 | E44: =IF(OR(E41="N/A",E41=0),"N/A",365/E41) -> 52.249352 | F44: =IF(OR(F41="N/A",F41=0),"N/A",365/F41) -> 53.775489 | G44: =IF(OR(G41="N/A",G41=0),"N/A",365/G41) -> 54.849958 | H44: =IF(OR(H41="N/A",H41=0),"N/A",365/H41) -> 55.945855 | I44: =IF(OR(I41="N/A",I41=0),"N/A",365/I41) -> 57.063606 | J44: =IF(OR(J41="N/A",J41=0),"N/A",365/J41) -> 58.203644 | K44: =IF(OR(K41="N/A",K41=0),"N/A",365/K41) -> 59.366411 | ... M44: =IF(OR(M41="N/A",M41=0),"N/A",365/M41) -> 61.761942
A47: Liquidity Ratios
A48: Current Ratio | D48: =IF(Bal_Sheet!F42>0,Bal_Sheet!F16/Bal_Sheet!F42,"N/A") -> 2.3108861 | E48: =IF(Bal_Sheet!G42>0,Bal_Sheet!G16/Bal_Sheet!G42,"N/A") -> 2.3196041 | F48: =IF(Bal_Sheet!H42>0,Bal_Sheet!H16/Bal_Sheet!H42,"N/A") -> 2.3465061 | G48: =IF(Bal_Sheet!I42>0,Bal_Sheet!I16/Bal_Sheet!I42,"N/A") -> 2.3768004 | H48: =IF(Bal_Sheet!J42>0,Bal_Sheet!J16/Bal_Sheet!J42,"N/A") -> 2.4102957 | I48: =IF(Bal_Sheet!K42>0,Bal_Sheet!K16/Bal_Sheet!K42,"N/A") -> 2.4468247 | J48: =IF(Bal_Sheet!L42>0,Bal_Sheet!L16/Bal_Sheet!L42,"N/A") -> 2.4862419 | K48: =IF(Bal_Sheet!M42>0,Bal_Sheet!M16/Bal_Sheet!M42,"N/A") -> 2.6965954 | ... M48: =IF(Bal_Sheet!O42>0,Bal_Sheet!O16/Bal_Sheet!O42,"N/A") -> 3.1039805
A49: Quick (Acid Test) Ratio | D49: =IF(Bal_Sheet!F42>0,(Bal_Sheet!F10+Bal_Sheet!F11)/Bal_Sheet!F42,"N/A") -> 1.0843893 | E49: =IF(Bal_Sheet!G42>0,(Bal_Sheet!G10+Bal_Sheet!G11)/Bal_Sheet!G42,"N/A") -> 1.083561 | F49: =IF(Bal_Sheet!H42>0,(Bal_Sheet!H10+Bal_Sheet!H11)/Bal_Sheet!H42,"N/A") -> 1.0928924 | G49: =IF(Bal_Sheet!I42>0,(Bal_Sheet!I10+Bal_Sheet!I11)/Bal_Sheet!I42,"N/A") -> 1.1053221 | H49: =IF(Bal_Sheet!J42>0,(Bal_Sheet!J10+Bal_Sheet!J11)/Bal_Sheet!J42,"N/A") -> 1.120654 | I49: =IF(Bal_Sheet!K42>0,(Bal_Sheet!K10+Bal_Sheet!K11)/Bal_Sheet!K42,"N/A") -> 1.1387162 | J49: =IF(Bal_Sheet!L42>0,(Bal_Sheet!L10+Bal_Sheet!L11)/Bal_Sheet!L42,"N/A") -> 1.1593583 | K49: =IF(Bal_Sheet!M42>0,(Bal_Sheet!M10+Bal_Sheet!M11)/Bal_Sheet!M42,"N/A") -> 1.3506238 | ... M49: =IF(Bal_Sheet!O42>0,(Bal_Sheet!O10+Bal_Sheet!O11)/Bal_Sheet!O42,"N/A") -> 1.7188755
A52: Returns
A53: Return on Equity (ROE) | D53: =IF(AND(Bal_Sheet!F62+Bal_Sheet!F63>0,Bal_Sheet!E62+Bal_Sheet!E63>0),(Inc_St!D43-Inc_St!D46)/AVERAGE((Bal_Sheet!F62+Bal_Sheet!F63),(Bal_Sheet!E62+Bal_Sheet!E63)),"N/A") -> 0.38718402 | E53: =IF(AND(Bal_Sheet!G62+Bal_Sheet!G63>0,Bal_Sheet!F62+Bal_Sheet!F63>0),(Inc_St!E43-Inc_St!E46)/AVERAGE((Bal_Sheet!G62+Bal_Sheet!G63),(Bal_Sheet!F62+Bal_Sheet!F63)),"N/A") -> 0.30192501 | F53: =IF(AND(Bal_Sheet!H62+Bal_Sheet!H63>0,Bal_Sheet!G62+Bal_Sheet!G63>0),(Inc_St!F43-Inc_St!F46)/AVERAGE((Bal_Sheet!H62+Bal_Sheet!H63),(Bal_Sheet!G62+Bal_Sheet!G63)),"N/A") -> 0.25611092 | G53: =IF(AND(Bal_Sheet!I62+Bal_Sheet!I63>0,Bal_Sheet!H62+Bal_Sheet!H63>0),(Inc_St!G43-Inc_St!G46)/AVERAGE((Bal_Sheet!I62+Bal_Sheet!I63),(Bal_Sheet!H62+Bal_Sheet!H63)),"N/A") -> 0.22523049 | H53: =IF(AND(Bal_Sheet!J62+Bal_Sheet!J63>0,Bal_Sheet!I62+Bal_Sheet!I63>0),(Inc_St!H43-Inc_St!H46)/AVERAGE((Bal_Sheet!J62+Bal_Sheet!J63),(Bal_Sheet!I62+Bal_Sheet!I63)),"N/A") -> 0.20016106 | I53: =IF(AND(Bal_Sheet!K62+Bal_Sheet!K63>0,Bal_Sheet!J62+Bal_Sheet!J63>0),(Inc_St!I43-Inc_St!I46)/AVERAGE((Bal_Sheet!K62+Bal_Sheet!K63),(Bal_Sheet!J62+Bal_Sheet!J63)),"N/A") -> 0.18408769 | J53: =IF(AND(Bal_Sheet!L62+Bal_Sheet!L63>0,Bal_Sheet!K62+Bal_Sheet!K63>0),(Inc_St!J43-Inc_St!J46)/AVERAGE((Bal_Sheet!L62+Bal_Sheet!L63),(Bal_Sheet!K62+Bal_Sheet!K63)),"N/A") -> 0.18847356 | K53: =IF(AND(Bal_Sheet!M62+Bal_Sheet!M63>0,Bal_Sheet!L62+Bal_Sheet!L63>0),(Inc_St!K43-Inc_St!K46)/AVERAGE((Bal_Sheet!M62+Bal_Sheet!M63),(Bal_Sheet!L62+Bal_Sheet!L63)),"N/A") -> 0.17257735 | ... M53: =IF(AND(Bal_Sheet!O62+Bal_Sheet!O63>0,Bal_Sheet!N62+Bal_Sheet!N63>0),(Inc_St!M43-Inc_St!M46)/AVERAGE((Bal_Sheet!O62+Bal_Sheet!O63),(Bal_Sheet!N62+Bal_Sheet!N63)),"N/A") -> 0.14818599
A54: Return on Assets (ROA) | D54: =IF(AND(Bal_Sheet!F32>0,Bal_Sheet!E32>0),(Inc_St!D43-Inc_St!D46+Inc_St!D24*(1-tax_rate))/AVERAGE(Bal_Sheet!F32,Bal_Sheet!E32),"N/A") -> 0.13249514 | E54: =IF(AND(Bal_Sheet!G32>0,Bal_Sheet!F32>0),(Inc_St!E43-Inc_St!E46+Inc_St!E24*(1-tax_rate))/AVERAGE(Bal_Sheet!G32,Bal_Sheet!F32),"N/A") -> 0.1223624 | F54: =IF(AND(Bal_Sheet!H32>0,Bal_Sheet!G32>0),(Inc_St!F43-Inc_St!F46+Inc_St!F24*(1-tax_rate))/AVERAGE(Bal_Sheet!H32,Bal_Sheet!G32),"N/A") -> 0.12266835 | G54: =IF(AND(Bal_Sheet!I32>0,Bal_Sheet!H32>0),(Inc_St!G43-Inc_St!G46+Inc_St!G24*(1-tax_rate))/AVERAGE(Bal_Sheet!I32,Bal_Sheet!H32),"N/A") -> 0.12282837 | H54: =IF(AND(Bal_Sheet!J32>0,Bal_Sheet!I32>0),(Inc_St!H43-Inc_St!H46+Inc_St!H24*(1-tax_rate))/AVERAGE(Bal_Sheet!J32,Bal_Sheet!I32),"N/A") -> 0.1219384 | I54: =IF(AND(Bal_Sheet!K32>0,Bal_Sheet!J32>0),(Inc_St!I43-Inc_St!I46+Inc_St!I24*(1-tax_rate))/AVERAGE(Bal_Sheet!K32,Bal_Sheet!J32),"N/A") -> 0.12173172 | J54: =IF(AND(Bal_Sheet!L32>0,Bal_Sheet!K32>0),(Inc_St!J43-Inc_St!J46+Inc_St!J24*(1-tax_rate))/AVERAGE(Bal_Sheet!L32,Bal_Sheet!K32),"N/A") -> 0.13315265 | K54: =IF(AND(Bal_Sheet!M32>0,Bal_Sheet!L32>0),(Inc_St!K43-Inc_St!K46+Inc_St!K24*(1-tax_rate))/AVERAGE(Bal_Sheet!M32,Bal_Sheet!L32),"N/A") -> 0.12676927 | ... M54: =IF(AND(Bal_Sheet!O32>0,Bal_Sheet!N32>0),(Inc_St!M43-Inc_St!M46+Inc_St!M24*(1-tax_rate))/AVERAGE(Bal_Sheet!O32,Bal_Sheet!N32),"N/A") -> 0.11141379
A57: Operating Results
A58: Sales Growth | D58: N/A | E58: =IF(Inc_St!D8>0,(Inc_St!E8-Inc_St!D8)/Inc_St!D8,"N/A") -> 0.1 | F58: =IF(Inc_St!E8>0,(Inc_St!F8-Inc_St!E8)/Inc_St!E8,"N/A") -> 0.1 | G58: =IF(Inc_St!F8>0,(Inc_St!G8-Inc_St!F8)/Inc_St!F8,"N/A") -> 0.1 | H58: =IF(Inc_St!G8>0,(Inc_St!H8-Inc_St!G8)/Inc_St!G8,"N/A") -> 0.1 | I58: =IF(Inc_St!H8>0,(Inc_St!I8-Inc_St!H8)/Inc_St!H8,"N/A") -> 0.1 | J58: =IF(Inc_St!I8>0,(Inc_St!J8-Inc_St!I8)/Inc_St!I8,"N/A") -> 0.1 | K58: =IF(Inc_St!J8>0,(Inc_St!K8-Inc_St!J8)/Inc_St!J8,"N/A") -> 0.1 | L58: =IF(Inc_St!K8>0,(Inc_St!L8-Inc_St!K8)/Inc_St!K8,"N/A") -> 0.1 | M58: =IF(Inc_St!L8>0,(Inc_St!M8-Inc_St!L8)/Inc_St!L8,"N/A") -> 0.1
A59: Gross Margin | D59: =IF(Inc_St!D8>0,Inc_St!D12/Inc_St!D8,"N/A") -> 0.55 | E59: =IF(Inc_St!E8>0,Inc_St!E12/Inc_St!E8,"N/A") -> 0.548875 | F59: =IF(Inc_St!F8>0,Inc_St!F12/Inc_St!F8,"N/A") -> 0.54774719 | G59: =IF(Inc_St!G8>0,Inc_St!G12/Inc_St!G8,"N/A") -> 0.54661656 | H59: =IF(Inc_St!H8>0,Inc_St!H12/Inc_St!H8,"N/A") -> 0.5454831 | I59: =IF(Inc_St!I8>0,Inc_St!I12/Inc_St!I8,"N/A") -> 0.5443468 | J59: =IF(Inc_St!J8>0,Inc_St!J12/Inc_St!J8,"N/A") -> 0.54320767 | K59: =IF(Inc_St!K8>0,Inc_St!K12/Inc_St!K8,"N/A") -> 0.54206569 | ... M59: =IF(Inc_St!M8>0,Inc_St!M12/Inc_St!M8,"N/A") -> 0.53977316
A60: EBITDA Margin | D60: =IF(Inc_St!D8>0,Inc_St!D18/Inc_St!D8,"N/A") -> 0.29 | E60: =IF(Inc_St!E8>0,Inc_St!E18/Inc_St!E8,"N/A") -> 0.287995 | F60: =IF(Inc_St!F8>0,Inc_St!F18/Inc_St!F8,"N/A") -> 0.28598342 | G60: =IF(Inc_St!G8>0,Inc_St!G18/Inc_St!G8,"N/A") -> 0.28396523 | H60: =IF(Inc_St!H8>0,Inc_St!H18/Inc_St!H8,"N/A") -> 0.28194041 | I60: =IF(Inc_St!I8>0,Inc_St!I18/Inc_St!I8,"N/A") -> 0.27990893 | J60: =IF(Inc_St!J8>0,Inc_St!J18/Inc_St!J8,"N/A") -> 0.27787076 | K60: =IF(Inc_St!K8>0,Inc_St!K18/Inc_St!K8,"N/A") -> 0.27582589 | ... M60: =IF(Inc_St!M8>0,Inc_St!M18/Inc_St!M8,"N/A") -> 0.27171592
A61: EBIT Margin | D61: =IF(Inc_St!D8>0,Inc_St!D22/Inc_St!D8,"N/A") -> 0.2237053 | E61: =IF(Inc_St!E8>0,Inc_St!E22/Inc_St!E8,"N/A") -> 0.21772709 | F61: =IF(Inc_St!F8>0,Inc_St!F22/Inc_St!F8,"N/A") -> 0.21543684 | G61: =IF(Inc_St!G8>0,Inc_St!G22/Inc_St!G8,"N/A") -> 0.21268911 | H61: =IF(Inc_St!H8>0,Inc_St!H22/Inc_St!H8,"N/A") -> 0.20881061 | I61: =IF(Inc_St!I8>0,Inc_St!I22/Inc_St!I8,"N/A") -> 0.20717729 | J61: =IF(Inc_St!J8>0,Inc_St!J22/Inc_St!J8,"N/A") -> 0.22576897 | K61: =IF(Inc_St!K8>0,Inc_St!K22/Inc_St!K8,"N/A") -> 0.22179396 | ... M61: =IF(Inc_St!M8>0,Inc_St!M22/Inc_St!M8,"N/A") -> 0.214015
A62: Pre-Tax Profit Ratio | D62: =IF(Inc_St!D8>0,Inc_St!D39/Inc_St!D8,"N/A") -> 0.19473808 | E62: =IF(Inc_St!E8>0,Inc_St!E39/Inc_St!E8,"N/A") -> 0.19275893 | F62: =IF(Inc_St!F8>0,Inc_St!F39/Inc_St!F8,"N/A") -> 0.19501062 | G62: =IF(Inc_St!G8>0,Inc_St!G39/Inc_St!G8,"N/A") -> 0.19715498 | H62: =IF(Inc_St!H8>0,Inc_St!H39/Inc_St!H8,"N/A") -> 0.19609153 | I62: =IF(Inc_St!I8>0,Inc_St!I39/Inc_St!I8,"N/A") -> 0.19781825 | J62: =IF(Inc_St!J8>0,Inc_St!J39/Inc_St!J8,"N/A") -> 0.22030415 | K62: =IF(Inc_St!K8>0,Inc_St!K39/Inc_St!K8,"N/A") -> 0.21868669 | ... M62: =IF(Inc_St!M8>0,Inc_St!M39/Inc_St!M8,"N/A") -> 0.21235717
