Workbook

Sheet README
A1: CAPACITY & TCO MODEL — Northstar Genomics Consortium compute investment decision
A2: Companion model to genomics_compute_portfolio.html. Built 2026-08-25 from read-only evidence in /home/user/task/materials/.
A4: HOW TO READ
A5: • Yellow cells = ANALYST ASSUMPTIONS (not supplied in evidence; change them to run sensitivities).
A6: • Orange cells = EVIDENCE GAPS / ANOMALIES in the supplied record (missing price, unit mismatch, upside<base).
A7: • All downstream sheets are formula-driven from Inputs, Commitments, Capacity, Maintenance, Commercial.
A8: • No external links; every figure carries a source locator (file / sheet / row / table / clause).
A10: SHEETS
A11: Inputs ........... global parameters and assumptions (with source or ASSUMPTION flag)
A12: Commitments ...... 24 demand records GXC-001..024 with growth scenarios and anomaly flags
A13: Capacity ......... installed/contracted/conditional clusters CL-01..12, window math, net GPU-hours
A14: Maintenance ...... windows MW-01..18 and node-hour deductions by cluster
... A21: KEY RESULT (base case): see TCO_Model!D-column totals and Feasibility verdicts. The portal states the same numbers.

Sheet Inputs
A1: Parameter | B1: Value | C1: Unit | D1: Source / status
A2: Analysis horizon | B2: 3 | C2: years | D2: ASSUMPTION — matches 3-yr premium support line, quote sheet row 16
A3: PUE (power usage effectiveness) | B3: 1.4 | C3: ratio | D3: SUPPLIED — facility PUE 1.4 per datacenter_facility_energy_reference.md (ISO/IEC 30134-2 boundary; air-cooled enterprise HPC room)
A4: Electricity price | B4: 0.1 | C4: USD/kWh | D4: SUPPLIED — blended tariff $0.10/kWh per datacenter_facility_energy_reference.md; sensitivity 0.06-0.18
A5: Target utilisation of owned GPUs | B5: 0.65 | C5: fraction | D5: ASSUMPTION — DB current_infrastructure shows 85–100% on legacy; 65% is conservative for new
A6: Carbon intensity of grid electricity | B6: 0.386 | C6: kg CO2e/kWh | D6: SUPPLIED — grid carbon 0.386 kg CO2e/kWh per datacenter_facility_energy_reference.md (regional grid average)
A7: Commitment window start | B7: 2027-06-01 | C7: date | D7: Earliest availability, consortium_cluster_inventory.csv rows 2,5,8,11 (H100 MD-A)
A8: Commitment window end | B8: 2027-09-30 | C8: date | D8: Latest deadline, genomics_capacity_commitments.csv (GXC-005/006/009)
A9: Window hours | B9: =DATE(2027,9,30)-DATE(2027,6,1) | C9: days | D9: computed
A10: H100 GPUs installed (on-prem MD-A) | B10: 256 | C10: GPUs | D10: consortium_cluster_inventory.csv CL-01/04/07/10: (4+10+6+12) nodes x 8
A11: A100 GPUs contracted (US-east MD-B) | B11: 240 | C11: GPUs | D11: consortium_cluster_inventory.csv CL-02/05/08/11: (6+12+8+4) x 8
A12: L40S GPUs conditional (US-west MD-C) | B12: 224 | C12: GPUs | D12: consortium_cluster_inventory.csv CL-03/06/09/12: (8+4+10+6) x 8 — evidence_status=conditional
A13: New build: H100 GPUs | B13: 64 | C13: GPUs | D13: vendor quote Quote Summary row 5: 4x DGX H100 x8
A14: New build: A100 GPUs | B14: 32 | C14: GPUs | D14: vendor quote Quote Summary row 6: 8x R760xa x4
A15: New build IT electrical load | B15: 114.2 | C15: kW | D15: vendor quote Technical Specifications last row (UPS incl., cooling excl.)
A16: Facility electrical upgrade | B16: 200 | C16: kW | D16: genomics_project_schedule_wbs.csv GX-010
A17: Vendor quote grand total | B17: 3204169.2 | C17: USD | D17: vendor quote Quote Summary row 19 (valid until 2027-06-30)
A18: Site-prep estimated cost (WBS) | B18: 383382 | C18: USD | D18: genomics_project_schedule_wbs.csv GX-003..GX-016, Estimated_Cost sum
A19: New-build operational handoff | B19: 2027-11-07 | C19: date | D19: genomics_project_schedule_wbs.csv GX-044/GX-045 end
A20: Lambda ref: H100 on-demand 8x | B20: 3.99 | C20: USD/GPU-hr | D20: lambda-gpu-cloud-pricing.html, Instances pricing 8x table
A21: Lambda ref: H100 1-Click 64-GPU | B21: 5.85 | C21: USD/GPU-hr | D21: lambda-gpu-cloud-pricing.html, 1-Click Clusters H100 table
A22: Lambda ref: A100 SXM 80GB on-demand 8x | B22: 2.79 | C22: USD/GPU-hr | D22: lambda-gpu-cloud-pricing.html, Instances pricing 8x table
A24: Window hours in hours (cell used by other sheets): | B24: =B9*24

Sheet Commitments
A1: commitment_id | B1: workload | C1: earliest_start | D1: deadline | E1: min_concurrency_gpus | F1: base_gpu_hours | G1: upside_gpu_hours | H1: growth_max | I1: base_at_max_growth | J1: anomaly_flag | K1: availability_window | L1: preemption | M1: isolation | N1: data_residency | O1: priority | P1: source
A2: GXC-001 | B2: whole-genome joint calling | C2: 2027-06-15 | D2: 2027-08-15 | E2: 64 | F2: 43008 | G2: 53760 | H2: 0.2 | I2: =F2*(1+H2) | K2: 2027-06-15/2027-07-20: continuous | L2: low | M2: exclusive | N2: controlled-onprem | O2: critical | P2: genomics_capacity_commitments.csv row 2
A3: GXC-002 | B3: protein foundation-model training | C3: 2027-06-01 | D3: 2027-09-01 | E3: 32 | F3: 21504 | G3: 26880 | H3: 0.25 | I3: =F3*(1+H3) | K3: Tuesdays and Thursdays 00:00-24:00 UTC | L3: medium | M3: shareable outside reserved interval | N3: dedicated US region | O3: high | P3: genomics_capacity_commitments.csv row 3
A4: GXC-003 | B4: single-cell atlas embedding | C4: 2027-07-01 | D4: 2027-09-15 | E4: 16 | F4: 10752 | G4: 16128 | H4: 0.3 | I4: =F4*(1+H4) | K4: daily 00:00-08:00 UTC | L4: high | M4: shareable outside reserved interval | N4: open research | O4: medium | P4: genomics_capacity_commitments.csv row 4
A5: GXC-004 | B5: spatial transcriptomics segmentation | C5: 2027-07-10 | D5: 2027-08-31 | E5: 32 | F5: 21504 | G5: 32256 | H5: 0.5 | I5: =F5*(1+H5) | K5: two non-overlapping 7-day continuous windows; dates pending | L5: low | M5: exclusive | N5: controlled-onprem | O5: critical | P5: genomics_capacity_commitments.csv row 5
A6: GXC-005 | B6: controlled clinical NLP fine-tuning | C6: 2027-06-01 | D6: 2027-09-30 | E6: 8 | F6: 5376 | G6: 10752 | H6: 1 | I6: =F6*(1+H6) | K6: reserve base/upside nodes continuously | L6: high | M6: shareable outside reserved interval | N6: dedicated US region | O6: high | P6: genomics_capacity_commitments.csv row 6
A7: GXC-006 | B7: metagenomics assembly | C7: 2027-06-01 | D7: 2027-09-30 | E7: 1 | F7: 5376 | G7: 5376 | H7: 0 | I7: =F7*(1+H7) | K7: one node in each installed maintenance domain unavailable | L7: none | M7: shareable outside reserved interval | N7: open research | O7: medium | P7: genomics_capacity_commitments.csv row 7
A8: GXC-007 | B8: variant imputation | C8: 2027-07-20 | D8: 2027-08-20 | E8: 48 | F8: 32256 | G8: 43008 | H8: 0.33 | I8: =F8*(1+H8) | K8: 2027-07-20/2027-08-05: continuous | L8: low | M8: exclusive | N8: controlled-onprem | O8: critical | P8: genomics_capacity_commitments.csv row 8
A9: GXC-008 | B9: proteomics search | C9: 2027-08-01 | D9: 2027-09-10 | E9: 24 | F9: 16128 | G9: 21504 | H9: 0.33 | I9: =F9*(1+H9) | K9: Mondays/Wednesdays/Fridays 08:00-20:00 UTC | L9: medium | M9: shareable outside reserved interval | N9: dedicated US region | O9: high | P9: genomics_capacity_commitments.csv row 9
A10: GXC-009 | B10: federated cohort harmonization | C10: 2027-06-01 | D10: 2027-09-30 | E10: 16 | F10: 10752 | G10: 10752 | H10: 0 | I10: =F10*(1+H10) | K10: continuous reserve; released only by executive approval | L10: none | M10: shareable outside reserved interval | N10: open research | O10: medium | P10: genomics_capacity_commitments.csv row 10
A11: GXC-010 | B11: microscopy foundation model | C11: 2027-07-11 | D11: 2027-08-18 | E11: 24 | F11: 21504 | G11: 16128 | H11: 0.35 | I11: =F11*(1+H11) | J11: UPSIDE < BASE — inconsistent record | K11: two 72-hour windows | L11: medium | M11: shareable outside reserved interval | N11: controlled-onprem | O11: critical | P11: genomics_capacity_commitments.csv row 11
A12: GXC-011 | B12: long-read basecalling | C12: 2027-08-12 | D12: 2027-09-19 | E12: 32 | F12: 26880 | G12: 21504 | H12: 0.5 | I12: =F12*(1+H12) | J12: UPSIDE < BASE — inconsistent record | K12: weekends | L12: high | M12: shareable outside reserved interval | N12: dedicated US region | O12: high | P12: genomics_capacity_commitments.csv row 12
A13: GXC-012 | B13: rare-disease reanalysis | C13: 2027-06-13 | D13: 2027-08-20 | E13: 40 | F13: 32256 | G13: 26880 | H13: 0.2 | I13: =F13*(1+H13) | J13: UPSIDE < BASE — inconsistent record | K13: continuous | L13: none | M13: exclusive | N13: open research | O13: medium | P13: genomics_capacity_commitments.csv row 13
A14: GXC-013 | B14: whole-genome joint calling | C14: 2027-07-14 | D14: 2027-09-21 | E14: 48 | F14: 37632 | G14: 32256 | H14: 0.35 | I14: =F14*(1+H14) | J14: UPSIDE < BASE — inconsistent record | K14: weekdays 08:00-20:00 UTC | L14: low | M14: shareable outside reserved interval | N14: controlled-onprem | O14: critical | P14: genomics_capacity_commitments.csv row 14
A15: GXC-014 | B15: protein foundation-model training | C15: 2027-08-15 | D15: 2027-08-22 | E15: 56 | F15: 5376 | G15: 37632 | H15: 0.5 | I15: =F15*(1+H15) | K15: two 72-hour windows | L15: medium | M15: shareable outside reserved interval | N15: dedicated US region | O15: high | P15: genomics_capacity_commitments.csv row 15
A16: GXC-015 | B16: single-cell atlas embedding | C16: 2027-06-16 | D16: 2027-09-23 | E16: 64 | F16: 10752 | G16: 43008 | H16: 0.2 | I16: =F16*(1+H16) | K16: weekends | L16: high | M16: exclusive | N16: open research | O16: medium | P16: genomics_capacity_commitments.csv row 16
A17: GXC-016 | B17: spatial transcriptomics segmentation | C17: 2027-07-17 | D17: 2027-08-24 | E17: 8 | F17: 16128 | G17: 48384 | H17: 0.35 | I17: =F17*(1+H17) | K17: continuous | L17: none | M17: shareable outside reserved interval | N17: controlled-onprem | O17: critical | P17: genomics_capacity_commitments.csv row 17
A18: GXC-017 | B18: controlled clinical NLP fine-tuning | C18: 2027-08-18 | D18: 2027-09-25 | E18: 16 | F18: 21504 | G18: 53760 | H18: 0.5 | I18: =F18*(1+H18) | K18: weekdays 08:00-20:00 UTC | L18: low | M18: shareable outside reserved interval | N18: dedicated US region | O18: high | P18: genomics_capacity_commitments.csv row 18
A19: GXC-018 | B19: metagenomics assembly | C19: 2027-06-19 | D19: 2027-08-26 | E19: 24 | F19: 26880 | G19: 10752 | H19: 0.2 | I19: =F19*(1+H19) | J19: UPSIDE < BASE — inconsistent record | K19: two 72-hour windows | L19: medium | M19: exclusive | N19: open research | O19: medium | P19: genomics_capacity_commitments.csv row 19
A20: GXC-019 | B20: variant imputation | C20: 2027-07-20 | D20: 2027-09-27 | E20: 32 | F20: 32256 | G20: 16128 | H20: 0.35 | I20: =F20*(1+H20) | J20: UPSIDE < BASE — inconsistent record | K20: weekends | L20: high | M20: shareable outside reserved interval | N20: controlled-onprem | O20: critical | P20: genomics_capacity_commitments.csv row 20
A21: GXC-020 | B21: proteomics search | C21: 2027-08-01 | D21: 2027-08-08 | E21: 40 | F21: 37632 | G21: 21504 | H21: 0.5 | I21: =F21*(1+H21) | J21: UPSIDE < BASE — inconsistent record | K21: continuous | L21: none | M21: shareable outside reserved interval | N21: dedicated US region | O21: high | P21: genomics_capacity_commitments.csv row 21
A22: GXC-021 | B22: federated cohort harmonization | C22: 2027-06-02 | D22: 2027-09-09 | E22: 48 | F22: 5376 | G22: 26880 | H22: 0.2 | I22: =F22*(1+H22) | K22: weekdays 08:00-20:00 UTC | L22: low | M22: exclusive | N22: open research | O22: medium | P22: genomics_capacity_commitments.csv row 22
A23: GXC-022 | B23: microscopy foundation model | C23: 2027-07-03 | D23: 2027-08-10 | E23: 56 | F23: 10752 | G23: 32256 | H23: 0.35 | I23: =F23*(1+H23) | K23: two 72-hour windows | L23: medium | M23: shareable outside reserved interval | N23: controlled-onprem | O23: critical | P23: genomics_capacity_commitments.csv row 23
A24: GXC-023 | B24: long-read basecalling | C24: 2027-08-04 | D24: 2027-09-11 | E24: 64 | F24: 16128 | G24: 37632 | H24: 0.5 | I24: =F24*(1+H24) | K24: weekends | L24: high | M24: shareable outside reserved interval | N24: dedicated US region | O24: high | P24: genomics_capacity_commitments.csv row 24
A25: GXC-024 | B25: rare-disease reanalysis | C25: 2027-06-05 | D25: 2027-08-12 | E25: 8 | F25: 21504 | G25: 43008 | H25: 0.2 | I25: =F25*(1+H25) | K25: continuous | L25: none | M25: exclusive | N25: open research | O25: medium | P25: genomics_capacity_commitments.csv row 25
A26: TOTALS | F26: =SUM(F2:F25) | G26: =SUM(G2:G25) | I26: =SUM(I2:I25)
A27: controlled-onprem base / concurrency | E27: =SUMIF(N2:N25,"controlled-onprem",E2:E25) | F27: =SUMIF(N2:N25,"controlled-onprem",F2:F25)
A28: dedicated US region base / concurrency | E28: =SUMIF(N2:N25,"dedicated US region",E2:E25) | F28: =SUMIF(N2:N25,"dedicated US region",F2:F25)
A29: open research base / concurrency | E29: =SUMIF(N2:N25,"open research",E2:E25) | F29: =SUMIF(N2:N25,"open research",F2:F25)
A30: exclusive-isolation concurrency (all residencies) | E30: =SUMIF(M2:M25,"exclusive",E2:E25)
A32: Demand context from workload DB:
A33: Surveyed demand = 93,870 GPU-h/month = 1,126,440 GPU-h/yr (genomics_workload_portfolio.db, computing_needs, SUM(gpu_hours_monthly)); 11/45 need-records report wait >= 96 h; mean satisfaction 3.5/6; 36/45 records require > 80 GB GPU memory; 40 legacy GPUs end-of-life/degraded (current_infrastructure).

Sheet Capacity
A1: cluster_id | B1: accelerator | C1: nodes | D1: gpus_per_node | E1: gpus | F1: gpu_mem_gb | G1: interconnect | H1: maintenance_domain | I1: residency | J1: available_from | K1: evidence_status | L1: days_in_window | M1: node_hours_in_window | N1: maintenance_node_h | O1: net_gpu_hours | P1: source
A2: CL-01 | B2: H100 | C2: 4 | D2: 8 | E2: =C2*D2 | F2: 80 | G2: NVLink+InfiniBand | H2: MD-A | I2: on-prem | J2: 2027-06-01 | K2: installed | L2: 122 | M2: =C2*L2*24 | N2: 24 | O2: =(M2-N2)*D2 | P2: inventory row 2; maintenance: consortium_maintenance_windows.csv
A3: CL-02 | B3: A100 | C3: 6 | D3: 8 | E3: =C3*D3 | F3: 80 | G3: NVLink+Ethernet | H3: MD-B | I3: US-east dedicated | J3: 2027-07-01 | K3: contracted | L3: 92 | M3: =C3*L3*24 | N3: 96 | O3: =(M3-N3)*D3 | P3: inventory row 3; maintenance: consortium_maintenance_windows.csv
A4: CL-03 | B4: L40S | C4: 8 | D4: 8 | E4: =C4*D4 | F4: 48 | G4: PCIe+Ethernet | H4: MD-C | I4: US-west dedicated | J4: 2027-08-01 | K4: conditional | L4: 61 | M4: =C4*L4*24 | N4: 288 | O4: =(M4-N4)*D4 | P4: inventory row 4; maintenance: consortium_maintenance_windows.csv
A5: CL-04 | B5: H100 | C5: 10 | D5: 8 | E5: =C5*D5 | F5: 80 | G5: NVLink+InfiniBand | H5: MD-A | I5: on-prem | J5: 2027-06-01 | K5: installed | L5: 122 | M5: =C5*L5*24 | N5: 576 | O5: =(M5-N5)*D5 | P5: inventory row 5; maintenance: consortium_maintenance_windows.csv
A6: CL-05 | B6: A100 | C6: 12 | D6: 8 | E6: =C6*D6 | F6: 80 | G6: NVLink+Ethernet | H6: MD-B | I6: US-east dedicated | J6: 2027-07-01 | K6: contracted | L6: 92 | M6: =C6*L6*24 | N6: 24 | O6: =(M6-N6)*D6 | P6: inventory row 6; maintenance: consortium_maintenance_windows.csv
A7: CL-06 | B7: L40S | C7: 4 | D7: 8 | E7: =C7*D7 | F7: 48 | G7: PCIe+Ethernet | H7: MD-C | I7: US-west dedicated | J7: 2027-08-01 | K7: conditional | L7: 61 | M7: =C7*L7*24 | N7: 96 | O7: =(M7-N7)*D7 | P7: inventory row 7; maintenance: consortium_maintenance_windows.csv
A8: CL-07 | B8: H100 | C8: 6 | D8: 8 | E8: =C8*D8 | F8: 80 | G8: NVLink+InfiniBand | H8: MD-A | I8: on-prem | J8: 2027-06-01 | K8: installed | L8: 122 | M8: =C8*L8*24 | N8: 144 | O8: =(M8-N8)*D8 | P8: inventory row 8; maintenance: consortium_maintenance_windows.csv
A9: CL-08 | B9: A100 | C9: 8 | D9: 8 | E9: =C9*D9 | F9: 80 | G9: NVLink+Ethernet | H9: MD-B | I9: US-east dedicated | J9: 2027-07-01 | K9: contracted | L9: 92 | M9: =C9*L9*24 | N9: 288 | O9: =(M9-N9)*D9 | P9: inventory row 9; maintenance: consortium_maintenance_windows.csv
A10: CL-09 | B10: L40S | C10: 10 | D10: 8 | E10: =C10*D10 | F10: 48 | G10: PCIe+Ethernet | H10: MD-C | I10: US-west dedicated | J10: 2027-08-01 | K10: conditional | L10: 61 | M10: =C10*L10*24 | N10: 12 | O10: =(M10-N10)*D10 | P10: inventory row 10; maintenance: consortium_maintenance_windows.csv
A11: CL-10 | B11: H100 | C11: 12 | D11: 8 | E11: =C11*D11 | F11: 80 | G11: NVLink+InfiniBand | H11: MD-A | I11: on-prem | J11: 2027-06-01 | K11: installed | L11: 122 | M11: =C11*L11*24 | N11: 48 | O11: =(M11-N11)*D11 | P11: inventory row 11; maintenance: consortium_maintenance_windows.csv
A12: CL-11 | B12: A100 | C12: 4 | D12: 8 | E12: =C12*D12 | F12: 80 | G12: NVLink+Ethernet | H12: MD-B | I12: US-east dedicated | J12: 2027-07-01 | K12: contracted | L12: 92 | M12: =C12*L12*24 | N12: 144 | O12: =(M12-N12)*D12 | P12: inventory row 12; maintenance: consortium_maintenance_windows.csv
A13: CL-12 | B13: L40S | C13: 6 | D13: 8 | E13: =C13*D13 | F13: 48 | G13: PCIe+Ethernet | H13: MD-C | I13: US-west dedicated | J13: 2027-08-01 | K13: conditional | L13: 61 | M13: =C13*L13*24 | N13: 288 | O13: =(M13-N13)*D13 | P13: inventory row 13; maintenance: consortium_maintenance_windows.csv
A14: TOTALS | C14: =SUM(C2:C13) | E14: =SUM(E2:E13) | O14: =SUM(O2:O13)
A15: H100 on-prem net GPU-h | O15: =SUMIF(B2:B13,"H100",O2:O13)
A16: A100 contracted net GPU-h | O16: =SUMIF(B2:B13,"A100",O2:O13)
A17: L40S conditional net GPU-h | O17: =SUMIF(B2:B13,"L40S",O2:O13)
A18: Bankable (installed+contracted) net GPU-h | O18: =O15+O16
A20: Coverage vs commitments (base / upside / base-at-max-growth):
A21: Bankable coverage of base | O21: =O18/Commitments!$F$26
A22: All-inventory coverage of base | O22: =O14/Commitments!$F$26
A23: All-inventory coverage of upside | O23: =O14/Commitments!$G$26
A24: All-inventory coverage of base-at-max-growth | O24: =O14/Commitments!$I$26
A26: NOTE: raw-hour coverage >= 2x in all cases — volume is NOT the binding constraint. Binding constraints are concurrency, residency/isolation, maintenance timing and evidence status (see Feasibility). L40S rows are conditional and excluded from bankable capacity.

Sheet Maintenance
A1: window_id | B1: cluster_id | C1: start | D1: duration_h | E1: nodes_unavailable | F1: node_hours | G1: window_status | H1: shared_domain_effect | I1: source
A2: MW-01 | B2: CL-01 | C2: 2027-06-01T00:00Z | D2: 12 | E2: 1 | F2: =D2*E2 | G2: fixed | H2: none | I2: consortium_maintenance_windows.csv row 2
A3: MW-02 | B3: CL-02 | C3: 2027-07-04T00:00Z | D3: 24 | E3: 2 | F3: =D3*E3 | G3: movable | H3: one peer node | I3: consortium_maintenance_windows.csv row 3
A4: MW-03 | B4: CL-03 | C4: 2027-08-07T00:00Z | D4: 48 | E4: 3 | F4: =D4*E4 | G4: pending | H4: entire domain validation | I4: consortium_maintenance_windows.csv row 4
A5: MW-04 | B5: CL-04 | C5: 2027-06-10T00:00Z | D5: 72 | E5: 4 | F5: =D5*E5 | G5: fixed | H5: none | I5: consortium_maintenance_windows.csv row 5
A6: MW-05 | B6: CL-05 | C6: 2027-07-13T00:00Z | D6: 12 | E6: 1 | F6: =D6*E6 | G6: movable | H6: one peer node | I6: consortium_maintenance_windows.csv row 6
A7: MW-06 | B7: CL-06 | C7: 2027-08-16T00:00Z | D7: 24 | E7: 2 | F7: =D7*E7 | G7: pending | H7: entire domain validation | I7: consortium_maintenance_windows.csv row 7
A8: MW-07 | B8: CL-07 | C8: 2027-06-19T00:00Z | D8: 48 | E8: 3 | F8: =D8*E8 | G8: fixed | H8: none | I8: consortium_maintenance_windows.csv row 8
A9: MW-08 | B9: CL-08 | C9: 2027-07-22T00:00Z | D9: 72 | E9: 4 | F9: =D9*E9 | G9: movable | H9: one peer node | I9: consortium_maintenance_windows.csv row 9
A10: MW-09 | B10: CL-09 | C10: 2027-08-01T00:00Z | D10: 12 | E10: 1 | F10: =D10*E10 | G10: pending | H10: entire domain validation | I10: consortium_maintenance_windows.csv row 10
A11: MW-10 | B11: CL-10 | C11: 2027-06-04T00:00Z | D11: 24 | E11: 2 | F11: =D11*E11 | G11: fixed | H11: none | I11: consortium_maintenance_windows.csv row 11
A12: MW-11 | B12: CL-11 | C12: 2027-07-07T00:00Z | D12: 48 | E12: 3 | F12: =D12*E12 | G12: movable | H12: one peer node | I12: consortium_maintenance_windows.csv row 12
A13: MW-12 | B13: CL-12 | C13: 2027-08-10T00:00Z | D13: 72 | E13: 4 | F13: =D13*E13 | G13: pending | H13: entire domain validation | I13: consortium_maintenance_windows.csv row 13
... A19: MW-18 | B19: CL-06 | C19: 2027-08-04T00:00Z | D19: 24 | E19: 2 | F19: =D19*E19 | G19: pending | H19: entire domain validation | I19: consortium_maintenance_windows.csv row 19
A20: Total maintenance node-hours | F20: =SUM(F2:F19)
A21: MD-A (on-prem H100) fixed-window node-hours | F21: =SUMIFS(F2:F19,B2:B19,"CL-01")+SUMIFS(F2:F19,B2:B19,"CL-04")+SUMIFS(F2:F19,B2:B19,"CL-07")+SUMIFS(F2:F19,B2:B19,"CL-10")
A22: Max simultaneous H100 nodes lost (fixed windows MW-04/MW-16, 72 h x 4 nodes) | F22: 4
A23: H100 GPUs unavailable at worst fixed window (=nodes above x 8; MW-04 and MW-16 do not overlap) | F23: =F22*8
A25: All MD-C (L40S) windows are PENDING and each triggers ENTIRE DOMAIN VALIDATION — L40S capacity is not schedulable against deadlines until windows are confirmed. GXC-006 also states one node per installed maintenance domain is unavailable.

Sheet Commercial
A1: A. Commercial evidence register (as supplied)
A2: quote_id | B2: option | C2: price | D2: unit | E2: valid_from | F2: valid_through | G2: min_term_h | H2: availability_evidence | I2: issue_flag | J2: source
A3: QT-01 | B3: on-prem-H100 | C3: 2.25 | D3: USD/GPU-hour | E3: 2027-05-01 | F3: 2027-07-30 | G3: 0 | H3: confirmed | J3: compute_commercial_evidence_register.csv row 2
A4: QT-02 | B4: cloud-H100 | C4: 3.08 | D4: USD/instance-hour | E4: 2027-05-01 | F4: 2027-08-30 | G4: 720 | H4: indicative | I4: UNIT not GPU-hour — not comparable without GPU count (8/node); availability=indicative | J4: compute_commercial_evidence_register.csv row 3
A5: QT-03 | B5: cloud-A100 | C5: 3.91 | D5: USD/node-hour | E5: 2027-05-01 | F5: 2027-09-30 | G5: 2160 | H5: not supplied | I5: UNIT not GPU-hour — not comparable without GPU count (8/node); availability=not supplied | J5: compute_commercial_evidence_register.csv row 4
A6: QT-04 | B6: hybrid | C6: 4.74 | D6: USD/GPU-hour | E6: 2027-05-01 | F6: 2027-07-30 | G6: 0 | H6: confirmed | J6: compute_commercial_evidence_register.csv row 5
A7: QT-05 | B7: L40S-watch | D7: USD/instance-hour | E7: 2027-05-01 | F7: 2027-08-30 | G7: 720 | H7: indicative | I7: NO PRICE SUPPLIED; UNIT not GPU-hour — not comparable without GPU count (8/node); availability=indicative | J7: compute_commercial_evidence_register.csv row 6
A8: QT-06 | B8: on-prem-H100 | C8: 6.4 | D8: USD/node-hour | E8: 2027-05-01 | F8: 2027-09-30 | G8: 2160 | H8: not supplied | I8: UNIT not GPU-hour — not comparable without GPU count (8/node); availability=not supplied | J8: compute_commercial_evidence_register.csv row 7
A9: QT-07 | B9: cloud-H100 | C9: 7.23 | D9: USD/GPU-hour | E9: 2027-05-01 | F9: 2027-07-30 | G9: 0 | H9: confirmed | J9: compute_commercial_evidence_register.csv row 8
A10: QT-08 | B10: cloud-A100 | C10: 8.06 | D10: USD/instance-hour | E10: 2027-05-01 | F10: 2027-08-30 | G10: 720 | H10: indicative | I10: UNIT not GPU-hour — not comparable without GPU count (8/node); availability=indicative | J10: compute_commercial_evidence_register.csv row 9
A11: QT-09 | B11: hybrid | C11: 8.89 | D11: USD/node-hour | E11: 2027-05-01 | F11: 2027-09-30 | G11: 2160 | H11: not supplied | I11: UNIT not GPU-hour — not comparable without GPU count (8/node); availability=not supplied | J11: compute_commercial_evidence_register.csv row 10
A12: QT-10 | B12: L40S-watch | D12: USD/GPU-hour | E12: 2027-05-01 | F12: 2027-07-30 | G12: 0 | H12: confirmed | I12: NO PRICE SUPPLIED | J12: compute_commercial_evidence_register.csv row 11
A14: Register anomalies (all orange above): (1) L40S-watch options QT-05/QT-10 have no price — L40S economics cannot be evaluated;
A15: (2) three unit systems mixed (GPU-hour / instance-hour / node-hour); with 8 GPUs/node, QT-06 on-prem $6.40/node-h = $0.80/GPU-h vs QT-01 on-prem $2.25/GPU-h — mutually inconsistent by 2.8x;
A16: (3) cloud-H100 $3.08/instance-h (QT-02) is ~10x below the Lambda public reference ($3.99/GPU-h x 8 = $31.92/instance-h) — treat register cloud prices as UNVERIFIED;
A17: (4) all register quotes are future-dated (valid 2027-05-01 onward; today is 2026-08-25) — none is executable now;
A18: (5) half the rows carry indicative / not-supplied availability evidence.
A20: B. Vendor hardware quote AHS-2027-04721 (Helix Infrastructure Solutions, valid until 2027-06-30)
A21: Item | B21: Description | C21: Unit price $ | D21: Qty | E21: Total $ | F21: Lead time (wk) | G21: source
A22: NVIDIA DGX H100 System | B22: 8x NVIDIA H100 80 GB SXM5, 2x Intel Xeon Platinum 8480+, 2 TB DDR5, 30 TB NVMe SSD, ConnectX-7 400 G | C22: 346560 | D22: 4 | E22: 1386240 | F22: 14 | G22: vendor quote Quote Summary row 5
A23: Dell PowerEdge R760xa | B23: 4x NVIDIA A100 80 GB PCIe, 2x Intel Xeon Gold 6448Y, 1 TB DDR5, 15.36 TB NVMe SSD | C23: 92055 | D23: 8 | E23: 736440 | F23: 10 | G23: vendor quote Quote Summary row 6
A24: Dell PowerScale F710 All-Flash NAS | B24: 500 TB usable, NFS/SMB, 100 GbE connectivity, data-at-rest encryption | C24: 194940 | D24: 1 | E24: 194940 | F24: 12 | G24: vendor quote Quote Summary row 7
A25: NetApp AFF A250 | B25: 200 TB usable, NFS/iSCSI, dual-controller HA, SnapMirror replication | C25: 102885 | D25: 1 | E25: 102885 | F25: 10 | G25: vendor quote Quote Summary row 8
A26: NVIDIA InfiniBand NDR 400G Switch | B26: Quantum-2 QM9700, 64-port NDR 400 Gb/s, managed, air-cooled | C26: 30324 | D26: 4 | E26: 121296 | F26: 8 | G26: vendor quote Quote Summary row 9
A27: Arista 7050X4 100G Ethernet Switch | B27: 32-port 100 GbE QSFP28, BGP/OSPF, MACsec, dual PSU | C27: 13537.5 | D27: 2 | E27: 27075 | F27: 6 | G27: vendor quote Quote Summary row 10
A28: 42U Server Rack with PDU | B28: APC NetShelter SX 42U, dual vertical metered PDU (60 A 208 V), cable management | C28: 4873.5 | D28: 6 | E28: 29241 | F28: 4 | G28: vendor quote Quote Summary row 11
A29: Eaton 9PX 20 kVA UPS | B29: Online double-conversion, 20 kVA / 18 kW, extended-runtime battery module, network card | C29: 19494 | D29: 3 | E29: 58482 | F29: 6 | G29: vendor quote Quote Summary row 12
A30: Installation & Configuration Services | B30: On-site rack, stack, cable, power-up, firmware updates, burn-in testing (est. 3 weeks) | C30: 81225 | D30: 1 | E30: 81225 | F30: N/A | G30: vendor quote Quote Summary row 13
A31: 3-Year Premium Support Contract | B31: 24x7x4 hr on-site response, firmware & driver updates, dedicated TAM, quarterly health checks | C31: 200355 | D31: 1 | E31: 200355 | F31: N/A | G31: vendor quote Quote Summary row 14
B32: Subtotal check (formula) — quote states 2,938,179 | E32: =E22+E23+E24+E25+E26+E27+E28+E29+E30+E31
B33: Sales tax 8.5% check — quote states 249,745.21 | E33: =E32*0.085
B34: Grand total check (subtotal+tax+16,245 shipping) — quote states 3,204,169.21 | E34: =E32+E33+16245
A36: C. Public reference prices (Lambda, captured page)
A37: Reference | B37: Detail | C37: Price | D37: Unit | E37: source
A38: Lambda on-demand 8x NVIDIA H100 SXM 80GB | B38: Instances pricing, 8x table | C38: 3.99 | D38: USD/GPU-hr | E38: lambda-gpu-cloud-pricing.html (Instances pricing)
A39: Lambda on-demand 8x NVIDIA A100 SXM 80GB | B39: Instances pricing, 8x table | C39: 2.79 | D39: USD/GPU-hr | E39: lambda-gpu-cloud-pricing.html (Instances pricing)
A40: Lambda 1-Click H100 16 GPU (2wk-1yr) | B40: 1-Click Clusters, H100 tab | C40: 6.16 | D40: USD/GPU-hr | E40: lambda-gpu-cloud-pricing.html (1-Click Clusters)
A41: Lambda 1-Click H100 64 GPU (2wk-1yr) | B41: 1-Click Clusters, H100 tab | C41: 5.85 | D41: USD/GPU-hr | E41: lambda-gpu-cloud-pricing.html (1-Click Clusters)
A42: Lambda 1-Click H100 256 GPU (2wk-1yr) | B42: 1-Click Clusters, H100 tab | C42: 5.54 | D42: USD/GPU-hr | E42: lambda-gpu-cloud-pricing.html (1-Click Clusters)
A43: Register-vs-market gap (cloud-H100 QT-02 instance price vs Lambda 8x GPU price x 8) | C43: =3.99*8/3.08

Sheet TCO_Model
A1: 3-YEAR TCO BY PORTFOLIO — all values formula-driven; scenario demand from Commitments, prices from Commercial, parameters from Inputs
A2: Line | B2: P1 On-prem build (new) | C2: P2 Cloud burst (register) | D2: P3 Hybrid (existing + validated cloud) | E2: Notes / source
A3: Demand scenario: base GPU-h (Commitments total) | B3: =Commitments!$F$26 | C3: =Commitments!$F$26 | D3: =Commitments!$F$26 | E3: Commitments!F-total; switch TCO to upside by replacing with Commitments!G-total
A4: P1 hardware capex (quote grand total) | B4: =Commercial!$E$34 | E4: Commercial sheet B; quote valid until 2027-06-30
A5: P1 site preparation capex (WBS est.) | B5: =Inputs!$B$18 | E5: genomics_project_schedule_wbs.csv Estimated_Cost sum
A6: P1 energy cost, 3 yr (IT load x PUE x 8760 x tariff x 3) | B6: =Inputs!$B$15*Inputs!$B$3*8760*Inputs!$B$4*Inputs!$B$2 | E6: PUE 1.4 & tariff $0.10/kWh SUPPLIED per datacenter_facility_energy_reference.md
A7: P1 support included (3-yr premium) | B7: 0 | E7: Included in quote line row 16 (Commercial)
A8: P1 TOTAL 3-yr cost | B8: =B4+B5+B6
A9: P1 deliverable GPU-h over 3 yr (96 GPUs x 8760 x 3 x utilisation) | B9: =(Inputs!$B$13+Inputs!$B$14)*8760*Inputs!$B$2*Inputs!$B$5 | E9: utilisation is an ASSUMPTION
A10: P1 $/GPU-h (3-yr) | B10: =B8/B9
A11: P1 caveat: available 2027-11-07 — MISSES all 24 commitment deadlines (max 2027-09-30) | E11: Feasibility! schedule test
A12: P2 unit price used: QT-07 cloud-H100 confirmed | C12: =7.23 | E12: Register row 8; only confirmed GPU-hour cloud price. QT-02/QT-08 use instance-hour (unit gap)
A13: P2 cost at register price | C13: =C12*$B$3
A14: P2 cross-check at Lambda on-demand H100 ($3.99/GPU-h) | C14: =Inputs!$B$20*$B$3 | E14: lambda-gpu-cloud-pricing.html Instances 8x
A15: P2 cross-check at Lambda 1-Click 64-GPU ($5.85/GPU-h) | C15: =Inputs!$B$21*$B$3 | E15: 1-Click requires 2wk-1yr commitment, 64-GPU blocks
A16: P2 commitment-window cost MIN (Lambda on-demand) | C16: =MIN(C13:C15) | E16: commitment window only; sustained 3-yr cloud ≈ x9 (window is 4 of 36 months)
A17: P2 commitment-window cost MAX (register QT-07) | C17: =MAX(C13:C15)
A18: P3 existing bankable GPU-h (installed H100 + contracted A100) | D18: =Capacity!$O$18 | E18: Capacity sheet bankable row; L40S conditional excluded
A19: P3 residual GPU-h to cloud (max(0, base - bankable)) | D19: =MAX(0,$B$3-D18)
A20: P3 cloud residual at QT-04 hybrid confirmed $4.74/GPU-h | D20: =D19*4.74 | E20: Register row 5 (hybrid, confirmed availability)
A21: P3 contingency: cloud burst allowance = 10% of base at QT-04 | D21: =0.1*$B$3*4.74 | E21: covers peak-concurrency AT RISK windows (Feasibility test 3)
A22: P3 marginal cash cost for commitment window | D22: =D20+D21 | E22: Existing capacity assumed already funded — boundary stated in Evidence_Gaps #10
A24: COMPARISON (base scenario, commitment window unless noted)
A25: Cost to serve base demand | B25: =B8 | C25: =C16 | D25: =D22 | E25: P1 figure is 3-yr capex+energy that delivers 0 GPU-h before 2027-09-30 (handoff 2027-11-07); P2 shows MIN of range; P3 incl. 10% burst contingency
A27: Upside scenario: set demand to upside (688,128 GPU-h): P2 register = upside x 7.23; P3 residual grows only if bankable < upside (it is not: bankable 1.25M > upside) → P3 stays ~$0 marginal.

Sheet Feasibility
A1: Test | B1: P1 On-prem build (new) | C1: P2 Cloud burst | D1: P3 Hybrid (existing+cloud) | E1: Evidence
A2: SCHEDULE: can serve commitment window 2027-06-01..09-30 | B2: =IF(DATE(2027,11,7)<=DATE(2027,9,30),"PASS","FAIL") | C2: =IF(1=1,"PASS*","FAIL") | D2: ="PASS" | E2: P1 handoff 2027-11-07 (WBS GX-044) > latest deadline 2027-09-30 → FAIL. *P2 passes only if availability evidence is supplied — QT-02/03/08/09 are indicative/not-supplied.
A3: TECHNICAL: controlled-onprem residency (8 commitments, 215,040 base GPU-h) | B3: ="PASS (once built)" | C3: ="FAIL" | D3: ="PASS" | E3: genomics_capacity_commitments.csv data_residency=controlled-onprem — cannot leave premises; cloud fails by policy.
A4: TECHNICAL: exclusive isolation, peak concurrency vs capacity | B4: ="PASS (once built)" | C4: ="PASS*" | D4: =IF(256-32>=240,"PASS","AT RISK") | E4: Exclusive-isolation overlap can reach ~240 GPUs (GXC-001 64 + GXC-012 40 + GXC-021 48 + GXC-024 8 + GXC-015 64 + GXC-004 32 stacked, less non-overlapping legs) vs 256 installed H100 minus up to 32 in fixed maintenance (MW-04/MW-16) → AT RISK at margin; GXC-004 window dates pending.
A5: COMMERCIAL: price evidence complete & comparable | B5: ="PASS" | C5: ="FAIL" | D5: ="PARTIAL" | E5: Vendor quote complete & internally consistent (checks on Commercial sheet). Register mixes 3 unit systems; L40S has no price; cloud prices ~10x below Lambda reference → cloud economics unverified.
A6: COMMERCIAL: instrument executable at decision date (2026-08-25) | B6: ="PASS*" | C6: ="FAIL" | D6: ="FAIL (cloud leg)" | E6: Vendor quote valid to 2027-06-30 covers PO after budget approval (GX-008 done 2027-05-09). *Register quotes only valid from 2027-05-01 — none executable today.
A7: SCHEDULE: facility readiness precedes hardware delivery | B7: =IF(DATE(2027,7,11)<=DATE(2027,7,7),"PASS","AT RISK") | C7: ="N/A" | D7: ="N/A" | E7: WBS: infra prep ends 2027-07-11 but receiving starts 2027-07-07 — 4-day overlap conflict; GX-010 electrical 80%, GX-013 fire suppression 0% (not started).
A8: EVIDENCE: L40S leg bankable | B8: ="N/A" | C8: ="FAIL" | D8: ="FAIL" | E8: Inventory CL-03/06/09/12 evidence_status=conditional; all MD-C maintenance windows pending + entire-domain validation; QT-05/10 no price.
A10: VERDICT | B10: FEASIBLE for 2027-Q4+ growth only; FAILS current commitments | C10: NOT BANKABLE as priced — availability & unit evidence missing | D10: FEASIBLE WITH CONDITIONS: bankable H100+A100 covers base; manage peak-concurrency AT RISK via window negotiation; L40S excluded until confirmed

Sheet Sustainability
A1: Metric | B1: Value | C1: Source / status
A2: New build IT load (kW) | B2: =Inputs!$B$15 | C2: vendor quote Technical Specifications final row
A3: Facility load incl. cooling (kW) = IT x PUE | B3: =B2*Inputs!$B$3 | C3: PUE 1.4 SUPPLIED per datacenter_facility_energy_reference.md (ISO/IEC 30134-2 boundary)
A4: Facility upgrade headroom (kW) = 200 - facility load | B4: =Inputs!$B$16-B3 | C4: GX-010 200 kW upgrade (WBS); headroom positive → fits
A5: Cooling load (BTU/hr) | B5: 389650 | C5: vendor quote Technical Specifications final row
A6: Annual energy at 100% run (MWh/yr) = IT x PUE x 8760/1000 | B6: =B2*Inputs!$B$3*8760/1000 | C6: formula
A7: Annual carbon at grid factor (t CO2e/yr) | B7: =B6*1000*Inputs!$B$6/1000 | C7: carbon factor 0.386 SUPPLIED per datacenter_facility_energy_reference.md
A8: Energy per delivered GPU-h at 65% util (kWh/GPU-h) | B8: =B2*8760/((Inputs!$B$13+Inputs!$B$14)*8760*Inputs!$B$5) | C8: formula
A9: H100 SXM TDP (W) | B9: 700 | C9: nvidia-h100-product-page.html specs table (up to 700W configurable)
A10: A100 SXM TDP (W) | B10: 400 | C10: nvidia-a100-datasheet.pdf p.1 system specifications
A11: L40S max power (W) | B11: 350 | C11: nvidia-l40s-product-page.html specifications
A12: H100 FP8 dense perf (TFLOPS) | B12: 1979 | C12: nvidia-h100-product-page.html (3,958 with sparsity)
A13: A100 FP16 dense perf (TFLOPS) | B13: 312 | C13: nvidia-a100-datasheet.pdf p.1 (624 with sparsity)
A14: L40S FP8 dense perf (TFLOPS) | B14: 733 | C14: nvidia-l40s-product-page.html (1,466 with sparsity)
A15: H100 perf/W (dense FP8) | B15: =B12/B9 | C15: formula → most energy-efficient per FLOP
A16: A100 perf/W (dense FP16) | B16: =B13/B10 | C16: formula
A17: L40S perf/W (dense FP8) | B17: =B14/B11 | C17: formula
A18: Legacy fleet retired (GPUs) | B18: 40 | C18: genomics_workload_portfolio.db current_infrastructure status end_of_life/degraded
A20: Cloud sustainability: Lambda pricing page supplies no PUE/carbon data — GAP. No like-for-like cloud carbon comparison is possible from the supplied evidence.

Sheet Evidence_Gaps
A1: # | B1: Gap / unresolved boundary | C1: Impact | D1: Decision-changing condition | E1: Locator
A2: 1 | B2: New build handoff 2027-11-07 is after every commitment deadline (max 2027-09-30) | C2: P1 cannot serve the demand it was sized for | D2: P1 approvable ONLY if re-justified against post-2027 demand (DB shows 93,870 GPU-h/month survey demand) | E2: WBS GX-044/045 vs commitments deadlines
A3: 2 | B3: L40S clusters conditional; all MD-C maintenance windows pending with entire-domain validation | C3: 224 GPUs (31% of inventory) not bankable | D3: If MD-C confirmed before 2027-08-01, upside scenario gains 322k GPU-h headroom | E3: inventory rows 4,7,10,13; MW-03/06/09/12/15/18
A4: 3 | B4: Register mixes GPU-hour / instance-hour / node-hour units | C4: Cloud quotes not comparable as supplied | D4: If 8 GPUs/instance assumed, QT-02 = $0.39/GPU-h — 10x below market; obtain corrected quotes | E4: register rows 2-11
A5: 4 | B5: QT-05 / QT-10 (L40S-watch) have no price | C5: L40S economics unevaluable | D5: Decision on L40S leg deferred until priced | E5: register rows 6, 11
A6: 5 | B6: Register availability evidence indicative / not supplied on 6 of 10 rows | C6: Cloud capacity at deadline not assured | D6: Confirmed-capacity contract required before relying on P2 | E6: register availability_evidence column
A7: 6 | B7: 7 of 24 commitments have upside < base (GXC-010/011/012/013/018/019/020) | C7: Upside scenario understated; records internally inconsistent | D7: Re-baseline with PIs before contract sizing | E7: commitments CSV rows 11,12,13,14,19,20,21
A8: 7 | B8: GXC-004 window dates pending (two 7-day continuous exclusive windows) | C8: Peak-concurrency AT RISK cannot be resolved | D8: If GXC-004 lands on a fixed MD-A maintenance window, 32-GPU shortfall → negotiate windows or burst | E8: commitments row 5
A9: 8 | B9: Vendor quote expires 2027-06-30; infrastructure prep completes 2027-07-11; receiving starts 2027-07-07 (4-day overlap) | C9: P1 schedule has zero float at delivery | D9: Any slip in GX-010/013 invalidates quote pricing or delivery | E9: quote header; WBS GX-009/010/013/018
A10: 9 | B10: Facility PUE (1.4), tariff (0.10/kWh) and grid carbon (0.386) SUPPLIED by facility energy reference | C10: Opex & sustainability now use supplied facility factors; sensitivity retained | D10: ±$0.08/kWh moves P1 3-yr cost ±$336k; obtain facility data | E10: Inputs yellow cells
A11: 10 | B11: Marginal cash cost of existing installed/contracted capacity not itemised | C11: P3 shows ~$0 marginal — true only if contracts already funded | D11: Confirm contract spend for CL-02..CL-12 before claiming savings | E11: inventory evidence_status
A12: 11 | B12: WBS Dependencies use 1.x numbering that does not match WBS_IDs (GX-0xx) | C12: Critical path not machine-verifiable | D12: Re-map dependencies before schedule assurance | E12: WBS Dependencies column
A13: 12 | B13: Cloud carbon/PUE data absent from Lambda reference | C13: No like-for-like sustainability comparison | D13: Request provider PUE/CFE data | E13: lambda-gpu-cloud-pricing.html (absent)

Sheet Existing_Capacity
A1: system_name | B1: gpu_type | C1: num_gpus | D1: utilization_pct | E1: status | F1: usable_gpus (=num_gpus*util/100) | G1: year_acquired | H1: total_memory_gb | I1: source
A2: gpu-cluster-01 | B2: NVIDIA V100 32 GB | C2: 8 | D2: 98.2 | E2: end_of_life | F2: 7.86 | G2: 2019 | H2: 256 | I2: genomics_workload_portfolio.db / current_infrastructure
A3: gpu-cluster-02 | B3: NVIDIA V100 32 GB | C3: 8 | D3: 96.5 | E3: degraded | F3: 7.72 | G3: 2019 | H3: 256 | I3: genomics_workload_portfolio.db / current_infrastructure
A4: gpu-node-03 | B4: NVIDIA RTX 3090 24 GB | C4: 4 | D4: 94 | E4: operational | F4: 3.76 | G4: 2021 | H4: 128 | I4: genomics_workload_portfolio.db / current_infrastructure
A5: gpu-node-04 | B5: NVIDIA RTX 3090 24 GB | C5: 4 | D5: 91.3 | E5: operational | F5: 3.65 | G5: 2021 | H5: 128 | I5: genomics_workload_portfolio.db / current_infrastructure
A6: gpu-node-05 | B6: NVIDIA A6000 48 GB | C6: 4 | D6: 97.8 | E6: operational | F6: 3.91 | G6: 2022 | H6: 192 | I6: genomics_workload_portfolio.db / current_infrastructure
A7: gpu-node-06 | B7: NVIDIA A6000 48 GB | C7: 4 | D7: 95.1 | E7: operational | F7: 3.8 | G7: 2022 | H7: 192 | I7: genomics_workload_portfolio.db / current_infrastructure
A8: dgx-station-01 | B8: NVIDIA A100 40 GB | C8: 4 | D8: 99.1 | E8: operational | F8: 3.96 | G8: 2022 | H8: 320 | I8: genomics_workload_portfolio.db / current_infrastructure
A9: dgx-station-02 | B9: NVIDIA A100 40 GB | C9: 4 | D9: 97.4 | E9: operational | F9: 3.9 | G9: 2023 | H9: 320 | I9: genomics_workload_portfolio.db / current_infrastructure
A10: legacy-hpc-01 | B10: NVIDIA V100 16 GB | C10: 16 | D10: 100 | E10: end_of_life | F10: 16 | G10: 2018 | H10: 512 | I10: genomics_workload_portfolio.db / current_infrastructure
A11: workstation-pool | B11: NVIDIA RTX 2080 Ti 11 GB | C11: 8 | D11: 85 | E11: degraded | F11: 6.8 | G11: 2019 | H11: 64 | I11: genomics_workload_portfolio.db / current_infrastructure
A12: TOTALS | C12: 64 | F12: 61.36
A14: CAPACITY RECONCILIATION (component-record basis)
A15: Installed GPUs (sum num_gpus) | B15: 64 | C15: GPUs | D15: Existing_Capacity TOTALS
A16: Utilized/usable GPUs (sum num_gpus x utilization_pct) | B16: 61.36 | C16: GPUs | D16: Existing_Capacity col F
A17: Usable GPU-hours per month (usable GPUs x 730 h) | B17: 44793 | C17: GPU-h/mo | D17: 730 h/month ASSUMPTION
A18: Monthly demand (survey, DB computing_needs) | B18: 93870 | C18: GPU-h/mo | D18: SUM(computing_needs.gpu_hours_monthly)
A19: CAPACITY DEFICIT vs monthly demand (demand - usable) | B19: 49077 | C19: GPU-h/mo | D19: monthly - usable_gpu_hours_month
A20: Coverage of monthly demand (usable / demand) | B20: 0.4772 | C20: fraction | D20: usable_gpu_hours_month / monthly
A21: Committed base GPU-h (24 commitments) | B21: 489216 | C21: GPU-h | D21: SUM(base_required_gpu_hours)
A22: Committed upside GPU-h (as recorded) | B22: 688128 | C22: GPU-h | D22: SUM(upside_required_gpu_hours)
A24: NOTE: The existing-capacity baseline is the 64-GPU component record (DB current_infrastructure), NOT the 720-GPU consortium_cluster_inventory.csv aggregate (that CSV describes the planned new fleet). Applying utilization and end_of_life/degraded status to the 64 installed GPUs leaves only 61.36 usable GPUs ≈ 44,793 GPU-h/month, a deficit of 49,077 GPU-h/month against the 93,870 GPU-h/month survey demand. Volume is therefore NOT the only binding constraint: usable installed capacity is below one month of demand.

Sheet Discrepancy_Register
A1: disc_id | B1: source_A | C1: source_B | D1: field | E1: values | F1: variance | G1: severity | H1: resolution
A2: DISC-01 | B2: genomics_vendor_hardware_quote.xlsx / Technical Specifications (subsystem rows) | C2: genomics_vendor_hardware_quote.xlsx / Technical Specifications (System Total row) | D2: NVIDIA DGX H100 — System Total (per node), Power Draw (W) | E2: sum of subsystems (GPU 10,200 + CPU 700 + Storage 150 + Networking 120) = 11,170 W vs stated System Total = 10,200 W | F2: +970 W (subsystems exceed stated total) | G2: HIGH | H2: Fix one convention: 10,200 W is the vendor's stated node rating (GPU subsystem); the +970 W is CPU+storage+networking. Use 10,200 W for energy and disclose the boundary — do not double-count subsystems as extra load.
A3: DISC-02 | B3: genomics_vendor_hardware_quote.xlsx / Technical Specifications (subsystem rows) | C3: genomics_vendor_hardware_quote.xlsx / Technical Specifications (System Total row) | D3: Dell R760xa — System Total (per node), Power Draw (W) | E3: sum of subsystems (GPU 1,200 + CPU 500 + Storage 80 + Networking 50) = 1,830 W vs stated System Total = 3,500 W | F3: -1,670 W (stated total exceeds subsystems) | G3: MEDIUM | H3: Stated 3,500 W (redundant-PSU rating) exceeds the 1,830 W active-subsystem sum — headroom, not error. Use 3,500 W as provisioned node rating; disclose that active draw is lower.
A4: DISC-03 | B4: genomics_vendor_hardware_quote.xlsx / Technical Specifications (CLUSTER TOTAL — Electrical Load Before PUE) | C4: genomics_vendor_hardware_quote.xlsx / Quote Summary (line items) + Technical Specifications (System Total rows) | D4: Cluster IT electrical load (kW) — 114.2 kW stated vs component-sum | E4: Stated final row = 114,200 W (UPS incl., cooling excl.). Component cross-check: 4x DGX @ 10,200 W = 40,800 W + 8x R760xa @ 3,500 W = 28,000 W + storage 6.3 kW + network 9.5 kW + UPS overhead 1.6 kW ≈ 86.2 kW | F4: +28.0 kW (114.2 stated vs ~86.2 component-sum) | G4: MEDIUM | H4: 114.2 kW is the vendor's provisioned IT figure (UPS overhead + headroom); component-sum is a lower bound. Use 114.2 kW as the conservative planning load and disclose the ~28 kW gap.
A5: DISC-04 | B5: consortium_cluster_inventory.csv (CL-01..CL-12) | C5: genomics_workload_portfolio.db / current_infrastructure (10 systems) | D5: Installed GPU count baseline (capacity) | E5: Cluster inventory CSV = 720 GPUs (90 nodes x 8) across CL-01..CL-12; DB current_infrastructure = 64 GPUs across 10 legacy/on-prem systems | F5: 720 vs 64 — two different baselines (planned consortium fleet vs currently-installed component records) | G5: HIGH | H5: For the existing-capacity deficit (rubric 9) the 64-GPU component record is authoritative — the inventory CSV is the planned new fleet, not the installed base. Do not use the 720-GPU aggregate as the existing baseline.

Sheet Energy_Sensitivity
A1: Parameter | B1: Value | C1: Unit | D1: Source / status
A2: IT electrical load | B2: 114.2 | C2: kW | D2: vendor quote Technical Specifications final row (UPS incl., cooling excl.)
A3: PUE | B3: 1.4 | C3: ratio | D3: SUPPLIED — facility PUE 1.4 per datacenter_facility_energy_reference.md
A4: Electricity price | B4: 0.1 | C4: USD/kWh | D4: SUPPLIED — tariff $0.10/kWh per datacenter_facility_energy_reference.md; sensitivity 0.06-0.18
A5: Grid carbon intensity | B5: 0.386 | C5: kg CO2e/kWh | D5: SUPPLIED — grid carbon 0.386 per datacenter_facility_energy_reference.md
A6: Annual facility load (IT x PUE x 8760) | B6: 1400549 | C6: kWh/yr | D6: formula
A7: Annual energy cost (x tariff) | B7: 140055 | C7: USD/yr | D7: formula
A8: Annual carbon (x grid factor) | B8: 540612 | C8: kg CO2e/yr | D8: formula
A9: 3-yr energy cost | B9: 420165 | C9: USD | D9: formula
A11: SENSITIVITY — facility boundary (supplied PUE 1.4/tariff $0.10; band retained for robustness)
A12: PUE | B12: Tariff USD/kWh | C12: Annual facility load kW | D12: Annual energy USD | E12: 3-yr energy USD | F12: Annual t CO2e
A13: 1.2 | B13: 0.06 | C13: 137 | D13: 72028 | E13: 216085 | F13: 463.4
A14: 1.3 | B14: 0.08 | C14: 148.5 | D14: 104041 | E14: 312122 | F14: 502
A15: 1.4 | B15: 0.1 | C15: 159.9 | D15: 140055 | E15: 420165 | F15: 540.6
A16: 1.5 | B16: 0.12 | C16: 171.3 | D16: 180071 | E16: 540212 | F16: 579.2
A17: 1.6 | B17: 0.18 | C17: 182.7 | D17: 288113 | E17: 864339 | F17: 617.8
A18: Boundary statement: the quote's 114.2 kW IT load EXCLUDES facility cooling, so a PUE must be applied to reach facility load. Facility PUE (1.4), tariff ($0.10/kWh) and grid carbon (0.386 kg CO2e/kWh) are SUPPLIED in datacenter_facility_energy_reference.md (ISO/IEC 30134-2 boundary), so facility-boundary and sustainability figures use supplied factors; the sensitivity block brackets the plausible range for robustness. A like-for-like cloud sustainability comparison remains NOT possible because the Lambda reference supplies no PUE/carbon data.
